Workbook
Name _DLX1.USE: #REF!
Name _DLX2.USE: PopulationByCohort1995!$A$1:$R$4

Sheet FINAL_DATA_for_DelNegro
A1: date | B1: obs_gdp | C1: obs_hours | D1: obs_wages | E1: obs_gdpdeflator | F1: obs_corepce | G1: obs_nominalrate | H1: obs_consumption | I1: obs_investment | J1: obs_BBBspread | K1: obs_longinflation | L1: obs_longrate | M1: obs_tfp | N1: obs_gdi | O1: obs_AAAspread | P1: obs_nominalrate1 | Q1: obs_nominalrate2 | R1: obs_nominalrate3 | S1: obs_nominalrate4 | T1: obs_nominalrate5 | U1: obs_nominalrate6
A2: 25749 | B2: =+Data_input!AO5 -> 1.8683193 | C2: =+Data_input!AW5 -> NaN | D2: =+Data_input!AU5 -> 2.6176958 | E2: =+Data_input!AR5 -> 1.8127385 | F2: =+Data_input!AS5 -> NaN | G2: =+Data_input!AT5 -> 1.98925 | H2: =+Data_input!AP5 -> 0.57886079 | I2: =+Data_input!AQ5 -> 5.6701088 | J2: =+Data_input!AW5 -> NaN | K2: =+Data_input!AX5 -> NaN | L2: =+Data_input!AY5 -> 2.0636 | M2: NaN | N2: =+Data_input!AN5 -> NaN | O2: NaN | P2: NaN | Q2: NaN | R2: NaN | S2: NaN | T2: NaN | U2: NaN
A3: 25841 | B3: =+Data_input!AO6 -> 1.0169411 | C3: =+Data_input!AW6 -> NaN | D3: =+Data_input!AU6 -> 2.0318583 | E3: =+Data_input!AR6 -> 1.7804625 | F3: =+Data_input!AS6 -> NaN | G3: =+Data_input!AT6 -> 1.9005 | H3: =+Data_input!AP6 -> 0.99087964 | I3: =+Data_input!AQ6 -> 0.69820336 | J3: =+Data_input!AW6 -> NaN | K3: =+Data_input!AX6 -> NaN | L3: =+Data_input!AY6 -> 2.0962 | M3: NaN | N3: =+Data_input!AN6 -> NaN | O3: NaN | P3: NaN | Q3: NaN | R3: NaN | S3: NaN | T3: NaN | U3: NaN
A4: 25933 | B4: =+Data_input!AO7 -> 1.043116 | C4: =+Data_input!AW7 -> NaN | D4: =+Data_input!AU7 -> 2.2601571 | E4: =+Data_input!AR7 -> 1.169604 | F4: =+Data_input!AS7 -> NaN | G4: =+Data_input!AT7 -> 1.8105 | H4: =+Data_input!AP7 -> 1.7487773 | I4: =+Data_input!AQ7 -> -0.039820886 | J4: =+Data_input!AW7 -> NaN | K4: =+Data_input!AX7 -> NaN | L4: =+Data_input!AY7 -> 2.085225 | M4: NaN | N4: =+Data_input!AN7 -> NaN | O4: NaN | P4: NaN | Q4: NaN | R4: NaN | S4: NaN | T4: NaN | U4: NaN
A5: 26023 | B5: =+Data_input!AO8 -> -0.37846203 | C5: =+Data_input!AW8 -> NaN | D5: =+Data_input!AU8 -> 0.96647751 | E5: =+Data_input!AR8 -> 2.2989518 | F5: =+Data_input!AS8 -> NaN | G5: =+Data_input!AT8 -> 1.62925 | H5: =+Data_input!AP8 -> -0.106649 | I5: =+Data_input!AQ8 -> -0.81746172 | J5: =+Data_input!AW8 -> NaN | K5: =+Data_input!AX8 -> NaN | L5: =+Data_input!AY8 -> 1.96515 | M5: NaN | N5: =+Data_input!AN8 -> NaN | O5: NaN | P5: NaN | Q5: NaN | R5: NaN | S5: NaN | T5: NaN | U5: NaN
A6: 26114 | B6: =+Data_input!AO9 -> 0.98464723 | C6: =+Data_input!AW9 -> NaN | D6: =+Data_input!AU9 -> 0.83746693 | E6: =+Data_input!AR9 -> 1.1299555 | F6: =+Data_input!AS9 -> NaN | G6: =+Data_input!AT9 -> 1.48475 | H6: =+Data_input!AP9 -> 1.1782578 | I6: =+Data_input!AQ9 -> 2.825207 | J6: =+Data_input!AW9 -> NaN | K6: =+Data_input!AX9 -> NaN | L6: =+Data_input!AY9 -> 1.9827 | M6: NaN | N6: =+Data_input!AN9 -> NaN | O6: NaN | P6: NaN | Q6: NaN | R6: NaN | S6: NaN | T6: NaN | U6: NaN
A7: 26206 | B7: =+Data_input!AO10 -> 1.8406942 | C7: =+Data_input!AW10 -> NaN | D7: =+Data_input!AU10 -> 1.9469213 | E7: =+Data_input!AR10 -> 1.6713481 | F7: =+Data_input!AS10 -> NaN | G7: =+Data_input!AT10 -> 1.5565 | H7: =+Data_input!AP10 -> 1.1525321 | I7: =+Data_input!AQ10 -> 0.16846011 | J7: =+Data_input!AW10 -> NaN | K7: =+Data_input!AX10 -> NaN | L7: =+Data_input!AY10 -> 2.00675 | M7: NaN | N7: =+Data_input!AN10 -> NaN | O7: NaN | P7: NaN | Q7: NaN | R7: NaN | S7: NaN | T7: NaN | U7: NaN
A8: 26298 | B8: =+Data_input!AO11 -> 0.66489089 | C8: =+Data_input!AW11 -> NaN | D8: =+Data_input!AU11 -> 1.6442656 | E8: =+Data_input!AR11 -> 1.0989122 | F8: =+Data_input!AS11 -> NaN | G8: =+Data_input!AT11 -> 1.5015 | H8: =+Data_input!AP11 -> 1.0130494 | I8: =+Data_input!AQ11 -> 1.6042895 | J8: =+Data_input!AW11 -> NaN | K8: =+Data_input!AX11 -> NaN | L8: =+Data_input!AY11 -> 1.9615 | M8: NaN | N8: =+Data_input!AN11 -> NaN | O8: NaN | P8: NaN | Q8: NaN | R8: NaN | S8: NaN | T8: NaN | U8: NaN
A9: 26389 | B9: =+Data_input!AO12 -> 1.250487 | C9: =+Data_input!AW12 -> NaN | D9: =+Data_input!AU12 -> 1.9664668 | E9: =+Data_input!AR12 -> 2.1622464 | F9: =+Data_input!AS12 -> NaN | G9: =+Data_input!AT12 -> 1.26175 | H9: =+Data_input!AP12 -> 0.92275964 | I9: =+Data_input!AQ12 -> 0.36421884 | J9: =+Data_input!AW12 -> NaN | K9: =+Data_input!AX12 -> NaN | L9: =+Data_input!AY12 -> 1.8969 | M9: NaN | N9: =+Data_input!AN12 -> NaN | O9: NaN | P9: NaN | Q9: NaN | R9: NaN | S9: NaN | T9: NaN | U9: NaN
A10: 26480 | B10: =+Data_input!AO13 -> 0.60518929 | C10: =+Data_input!AW13 -> NaN | D10: =+Data_input!AU13 -> 0.43958249 | E10: =+Data_input!AR13 -> 1.5915455 | F10: =+Data_input!AS13 -> NaN | G10: =+Data_input!AT13 -> 1.1885 | H10: =+Data_input!AP13 -> 0.37279123 | I10: =+Data_input!AQ13 -> 1.2797619 | J10: =+Data_input!AW13 -> NaN | K10: =+Data_input!AX13 -> NaN | L10: =+Data_input!AY13 -> 1.887425 | M10: NaN | N10: =+Data_input!AN13 -> NaN | O10: NaN | P10: NaN | Q10: NaN | R10: NaN | S10: NaN | T10: NaN | U10: NaN
A11: 26572 | B11: =+Data_input!AO14 -> 1.1230313 | C11: =+Data_input!AW14 -> NaN | D11: =+Data_input!AU14 -> 0.92436195 | E11: =+Data_input!AR14 -> 1.5666117 | F11: =+Data_input!AS14 -> NaN | G11: =+Data_input!AT14 -> 1.21425 | H11: =+Data_input!AP14 -> 2.0697722 | I11: =+Data_input!AQ14 -> 0.57111497 | J11: =+Data_input!AW14 -> NaN | K11: =+Data_input!AX14 -> NaN | L11: =+Data_input!AY14 -> 1.8957 | M11: NaN | N11: =+Data_input!AN14 -> NaN | O11: NaN | P11: NaN | Q11: NaN | R11: NaN | S11: NaN | T11: NaN | U11: NaN
A12: 26664 | B12: =+Data_input!AO15 -> 1.16364 | C12: =+Data_input!AW15 -> NaN | D12: =+Data_input!AU15 -> 1.4520609 | E12: =+Data_input!AR15 -> 1.542447 | F12: =+Data_input!AS15 -> NaN | G12: =+Data_input!AT15 -> 1.59875 | H12: =+Data_input!AP15 -> 0.70780832 | I12: =+Data_input!AQ15 -> 2.0215344 | J12: =+Data_input!AW15 -> NaN | K12: =+Data_input!AX15 -> NaN | L12: =+Data_input!AY15 -> 1.953675 | M12: NaN | N12: =+Data_input!AN15 -> NaN | O12: NaN | P12: NaN | Q12: NaN | R12: NaN | S12: NaN | T12: NaN | U12: NaN
A13: 26754 | B13: =+Data_input!AO16 -> 1.6539551 | C13: =+Data_input!AW16 -> NaN | D13: =+Data_input!AU16 -> 1.4655741 | E13: =+Data_input!AR16 -> 3.509132 | F13: =+Data_input!AS16 -> NaN | G13: =+Data_input!AT16 -> 1.69775 | H13: =+Data_input!AP16 -> 0.31973793 | I13: =+Data_input!AQ16 -> 1.2620153 | J13: =+Data_input!AW16 -> NaN | K13: =+Data_input!AX16 -> NaN | L13: =+Data_input!AY16 -> 1.993975 | M13: NaN | N13: =+Data_input!AN16 -> NaN | O13: NaN | P13: NaN | Q13: NaN | R13: NaN | S13: NaN | T13: NaN | U13: NaN
... A59: 30955 | B59: =+Data_input!AO62 -> 0.81441567 | C59: =+Data_input!AW62 -> NaN | D59: =+Data_input!AU62 -> 0.36647659 | E59: =+Data_input!AR62 -> 1.6051709 | F59: =+Data_input!AS62 -> NaN | G59: =+Data_input!AT62 -> 2.6035 | H59: =+Data_input!AP62 -> -0.055643632 | I59: =+Data_input!AQ62 -> 0.99961582 | J59: =+Data_input!AW62 -> NaN | K59: =+Data_input!AX62 -> NaN | L59: =+Data_input!AY62 -> 3.0523 | M59: NaN | N59: =+Data_input!AN62 -> NaN | O59: NaN | P59: NaN | Q59: NaN | R59: NaN | S59: NaN | T59: NaN | U59: NaN
A60: 31047 | B60: =+Data_input!AO63 -> 0.41563574 | C60: =+Data_input!AW63 -> NaN | D60: =+Data_input!AU63 -> 0.68857054 | E60: =+Data_input!AR63 -> 1.1084832 | F60: =+Data_input!AS63 -> NaN | G60: =+Data_input!AT63 -> 2.532 | H60: =+Data_input!AP63 -> 0.51023579 | I60: =+Data_input!AQ63 -> 1.2325852 | J60: NaN | K60: =+Data_input!AX63 -> NaN | L60: =+Data_input!AY63 -> 2.854575 | M60: NaN | N60: =+Data_input!AN63 -> NaN | O60: NaN | P60: NaN | Q60: NaN | R60: NaN | S60: NaN | T60: NaN | U60: NaN
A61: 31137 | B61: =+Data_input!AO64 -> 0.15719806 | C61: =+Data_input!AW64 -> 5.5978026 | D61: =+Data_input!AU64 -> 0.42849366 | E61: =+Data_input!AR64 -> 1.5625318 | F61: =+Data_input!AS64 -> NaN | G61: =+Data_input!AT64 -> 2.46575 | H61: =+Data_input!AP64 -> 0.91156536 | I61: =+Data_input!AQ64 -> -1.6384293 | J61: NaN | K61: =+Data_input!AX64 -> NaN | L61: =+Data_input!AY64 -> 2.73685 | M61: NaN | N61: =+Data_input!AN64 -> NaN | O61: NaN | P61: NaN | Q61: NaN | R61: NaN | S61: NaN | T61: NaN | U61: NaN
A62: 31228 | B62: =+Data_input!AO65 -> 0.81002553 | C62: =+Data_input!AW65 -> 5.520391 | D62: =+Data_input!AU65 -> 0.058433534 | E62: =+Data_input!AR65 -> 1.3857035 | F62: =+Data_input!AS65 -> NaN | G62: =+Data_input!AT65 -> 2.4905 | H62: =+Data_input!AP65 -> 0.33825091 | I62: =+Data_input!AQ65 -> 1.3479054 | J62: NaN | K62: =+Data_input!AX65 -> NaN | L62: =+Data_input!AY65 -> 2.711025 | M62: NaN | N62: =+Data_input!AN65 -> NaN | O62: NaN | P62: NaN | Q62: NaN | R62: NaN | S62: NaN | T62: NaN | U62: NaN
A63: 31320 | B63: =+Data_input!AO66 -> 0.62970295 | C63: =+Data_input!AW66 -> 5.3781865 | D63: =+Data_input!AU66 -> 0.49315274 | E63: =+Data_input!AR66 -> 1.5174798 | F63: =+Data_input!AS66 -> NaN | G63: =+Data_input!AT66 -> 2.33675 | H63: =+Data_input!AP66 -> 0.38085288 | I63: =+Data_input!AQ66 -> 1.3035571 | J63: NaN | K63: =+Data_input!AX66 -> NaN | L63: =+Data_input!AY66 -> 2.66725 | M63: NaN | N63: =+Data_input!AN66 -> NaN | O63: NaN | P63: NaN | Q63: NaN | R63: NaN | S63: NaN | T63: NaN | U63: NaN
A64: 31412 | B64: =+Data_input!AO67 -> 0.30455885 | C64: =+Data_input!AW67 -> 5.1799106 | D64: =+Data_input!AU67 -> -0.021903326 | E64: =+Data_input!AR67 -> 1.4947961 | F64: =+Data_input!AS67 -> NaN | G64: =+Data_input!AT67 -> 2.157 | H64: =+Data_input!AP67 -> 0.11889201 | I64: =+Data_input!AQ67 -> 0.91909959 | J64: NaN | K64: =+Data_input!AX67 -> NaN | L64: =+Data_input!AY67 -> 2.572575 | M64: NaN | N64: =+Data_input!AN67 -> NaN | O64: NaN | P64: NaN | Q64: NaN | R64: NaN | S64: NaN | T64: NaN | U64: NaN
A65: 31502 | B65: =+Data_input!AO68 -> -0.62857192 | C65: =+Data_input!AW68 -> 4.9528112 | D65: =+Data_input!AU68 -> -0.39107677 | E65: =+Data_input!AR68 -> 1.7647517 | F65: =+Data_input!AS68 -> NaN | G65: =+Data_input!AT68 -> 2.18725 | H65: =+Data_input!AP68 -> -0.83985339 | I65: =+Data_input!AQ68 -> -2.4798995 | J65: NaN | K65: =+Data_input!AX68 -> NaN | L65: =+Data_input!AY68 -> 2.441575 | M65: NaN | N65: =+Data_input!AN68 -> NaN | O65: NaN | P65: NaN | Q65: NaN | R65: NaN | S65: NaN | T65: NaN | U65: NaN
A66: 31593 | B66: =+Data_input!AO69 -> 1.5520692 | C66: =+Data_input!AW69 -> 4.7847139 | D66: =+Data_input!AU69 -> 0.21563372 | E66: =+Data_input!AR69 -> 1.3034218 | F66: =+Data_input!AS69 -> NaN | G66: =+Data_input!AT69 -> 2.007 | H66: =+Data_input!AP69 -> 0.79713751 | I66: =+Data_input!AQ69 -> 1.9949517 | J66: NaN | K66: =+Data_input!AX69 -> NaN | L66: =+Data_input!AY69 -> 2.14955 | M66: NaN | N66: =+Data_input!AN69 -> NaN | O66: NaN | P66: NaN | Q66: NaN | R66: NaN | S66: NaN | T66: NaN | U66: NaN
A67: 31685 | B67: =+Data_input!AO70 -> 0.17993857 | C67: =+Data_input!AW70 -> 4.6991955 | D67: =+Data_input!AU70 -> 0.12063218 | E67: =+Data_input!AR70 -> 1.1445046 | F67: =+Data_input!AS70 -> NaN | G67: =+Data_input!AT70 -> 1.93825 | H67: =+Data_input!AP70 -> -0.1687724 | I67: =+Data_input!AQ70 -> 0.35558028 | J67: NaN | K67: =+Data_input!AX70 -> NaN | L67: =+Data_input!AY70 -> 2.100925 | M67: NaN | N67: =+Data_input!AN70 -> NaN | O67: NaN | P67: NaN | Q67: NaN | R67: NaN | S67: NaN | T67: NaN | U67: NaN
A68: 31777 | B68: =+Data_input!AO71 -> -0.15538542 | C68: =+Data_input!AW71 -> 4.6741029 | D68: =+Data_input!AU71 -> 0.13742315 | E68: =+Data_input!AR71 -> 0.84986347 | F68: =+Data_input!AS71 -> NaN | G68: =+Data_input!AT71 -> 1.96875 | H68: =+Data_input!AP71 -> 0.49766429 | I68: =+Data_input!AQ71 -> 0.56819114 | J68: NaN | K68: =+Data_input!AX71 -> NaN | L68: =+Data_input!AY71 -> 2.11825 | M68: NaN | N68: =+Data_input!AN71 -> NaN | O68: NaN | P68: NaN | Q68: NaN | R68: NaN | S68: NaN | T68: NaN | U68: NaN
A69: 31867 | B69: =+Data_input!AO72 -> -0.73311494 | C69: =+Data_input!AW72 -> 4.7316413 | D69: =+Data_input!AU72 -> 0.10782261 | E69: =+Data_input!AR72 -> 0.84270162 | F69: =+Data_input!AS72 -> NaN | G69: =+Data_input!AT72 -> 2.02625 | H69: =+Data_input!AP72 -> -0.21567591 | I69: =+Data_input!AQ72 -> -1.8246121 | J69: NaN | K69: =+Data_input!AX72 -> NaN | L69: =+Data_input!AY72 -> 2.1178 | M69: NaN | N69: =+Data_input!AN72 -> NaN | O69: NaN | P69: NaN | Q69: NaN | R69: NaN | S69: NaN | T69: NaN | U69: NaN
A70: 31958 | B70: =+Data_input!AO73 -> 1.3643364 | C70: =+Data_input!AW73 -> 4.7600493 | D70: =+Data_input!AU73 -> 0.96286134 | E70: =+Data_input!AR73 -> 0.83565946 | F70: =+Data_input!AS73 -> NaN | G70: =+Data_input!AT73 -> 2.1065 | H70: =+Data_input!AP73 -> 1.5481834 | I70: =+Data_input!AQ73 -> 2.9212492 | J70: NaN | K70: =+Data_input!AX73 -> NaN | L70: =+Data_input!AY73 -> 2.17225 | M70: NaN | N70: =+Data_input!AN73 -> NaN | O70: NaN | P70: NaN | Q70: NaN | R70: NaN | S70: NaN | T70: NaN | U70: NaN
A71: 32050 | B71: =+Data_input!AO74 -> 0.82396912 | C71: =+Data_input!AW74 -> 4.7343351 | D71: =+Data_input!AU74 -> 0.61028185 | E71: =+Data_input!AR74 -> 0.69108775 | F71: =+Data_input!AS74 -> NaN | G71: =+Data_input!AT74 -> 2.1225 | H71: =+Data_input!AP74 -> 0.75014426 | I71: =+Data_input!AQ74 -> 2.0098641 | J71: NaN | K71: =+Data_input!AX74 -> NaN | L71: =+Data_input!AY74 -> 2.36805 | M71: NaN | N71: =+Data_input!AN74 -> NaN | O71: NaN | P71: NaN | Q71: NaN | R71: NaN | S71: NaN | T71: NaN | U71: NaN
... A111: 35703 | B111: =+Data_input!AO114 -> 0.5654589 | C111: =+Data_input!AW114 -> 1.1282396 | D111: =+Data_input!AU114 -> 0.24862192 | E111: =+Data_input!AR114 -> 0.17587365 | F111: =+Data_input!AS114 -> 0.31662296 | G111: =+Data_input!AT114 -> 1.0725 | H111: =+Data_input!AP114 -> 0.51604853 | I111: =+Data_input!AQ114 -> -0.82142386 | J111: NaN | K111: =+Data_input!AX114 -> NaN | L111: =+Data_input!AY114 -> 1.4525 | M111: NaN | N111: =+Data_input!AN114 -> NaN | O111: NaN | P111: NaN | Q111: NaN | R111: NaN | S111: NaN | T111: NaN | U111: NaN
A112: 35795 | B112: =+Data_input!AO115 -> 0.82901063 | C112: =+Data_input!AW115 -> 1.165307 | D112: =+Data_input!AU115 -> -0.12312815 | E112: =+Data_input!AR115 -> 0.54582936 | F112: =+Data_input!AS115 -> 0.31562362 | G112: =+Data_input!AT115 -> 1.095 | H112: =+Data_input!AP115 -> 0.8166924 | I112: =+Data_input!AQ115 -> 1.3712064 | J112: ='Option Adjusted rate'!O4/4 -> 1.5675 | K112: =+Data_input!AX115 -> NaN | L112: =+Data_input!AY115 -> 1.4 | M112: NaN | N112: =+Data_input!AN115 -> NaN | O112: NaN | P112: NaN | Q112: NaN | R112: NaN | S112: NaN | T112: NaN | U112: NaN
A113: 35885 | B113: =+Data_input!AO116 -> 0.30281109 | C113: =+Data_input!AW116 -> 1.0840195 | D113: =+Data_input!AU116 -> 0.2596156 | E113: =+Data_input!AR116 -> -0.2596156 | F113: =+Data_input!AS116 -> 0.34080515 | G113: =+Data_input!AT116 -> 1.0525 | H113: =+Data_input!AP116 -> -0.01941419 | I113: =+Data_input!AQ116 -> 1.7004603 | J113: ='Option Adjusted rate'!O5/4 -> 1.4453283 | K113: =+Data_input!AX116 -> NaN | L113: =+Data_input!AY116 -> 1.279175 | M113: NaN | N113: =+Data_input!AN116 -> NaN | O113: NaN | P113: NaN | Q113: NaN | R113: NaN | S113: NaN | T113: NaN | U113: NaN
A114: 35976 | B114: =+Data_input!AO117 -> -0.00262313 | C114: =+Data_input!AW117 -> 1.3763298 | D114: =+Data_input!AU117 -> 0.022276693 | E114: =+Data_input!AR117 -> 0.5385598 | F114: =+Data_input!AS117 -> 0.44392291 | G114: =+Data_input!AT117 -> 1.0175 | H114: =+Data_input!AP117 -> -0.031786087 | I114: =+Data_input!AQ117 -> -0.4906888 | J114: ='Option Adjusted rate'!O6/4 -> 1.3649152 | K114: =+Data_input!AX117 -> NaN | L114: =+Data_input!AY117 -> 1.2475 | M114: -0.0076444745 | N114: =+Data_input!AN117 -> NaN | O114: NaN | P114: NaN | Q114: NaN | R114: NaN | S114: NaN | T114: NaN | U114: NaN
A115: 36068 | B115: =+Data_input!AO118 -> 0.1252822 | C115: =+Data_input!AW118 -> 1.6372747 | D115: =+Data_input!AU118 -> -0.017941778 | E115: =+Data_input!AR118 -> 0.4674504 | F115: =+Data_input!AS118 -> 0.32516124 | G115: =+Data_input!AT118 -> 0.9875 | H115: =+Data_input!AP118 -> 0.59588844 | I115: =+Data_input!AQ118 -> 1.2595788 | J115: ='Option Adjusted rate'!O7/4 -> 1.7830613 | K115: =+Data_input!AX118 -> NaN | L115: =+Data_input!AY118 -> 1.14 | M115: -0.0033146378 | N115: =+Data_input!AN118 -> NaN | O115: NaN | P115: NaN | Q115: NaN | R115: NaN | S115: NaN | T115: NaN | U115: NaN
A116: 36160 | B116: =+Data_input!AO119 -> 0.038402457 | C116: =+Data_input!AW119 -> 1.3035559 | D116: =+Data_input!AU119 -> -0.44791865 | E116: =+Data_input!AR119 -> 1.0185116 | F116: =+Data_input!AS119 -> 0.27232073 | G116: =+Data_input!AT119 -> 0.915 | H116: =+Data_input!AP119 -> 0.29856019 | I116: =+Data_input!AQ119 -> 0.36035351 | J116: ='Option Adjusted rate'!O8/4 -> 2.1331477 | K116: =+Data_input!AX119 -> NaN | L116: =+Data_input!AY119 -> 1.036675 | M116: 0.0062073288 | N116: =+Data_input!AN119 -> NaN | O116: NaN | P116: NaN | Q116: NaN | R116: NaN | S116: NaN | T116: NaN | U116: NaN
A117: 36250 | B117: =+Data_input!AO120 -> 0.84265283 | C117: =+Data_input!AW120 -> 1.2310841 | D117: =+Data_input!AU120 -> -0.061541097 | E117: =+Data_input!AR120 -> 0.23055089 | F117: =+Data_input!AS120 -> 0.16820862 | G117: =+Data_input!AT120 -> 0.7775 | H117: =+Data_input!AP120 -> 0.48357053 | I117: =+Data_input!AQ120 -> 1.3717029 | J117: ='Option Adjusted rate'!O9/4 -> 1.8570411 | K117: =+Data_input!AX120 -> 0.475 | L117: =+Data_input!AY120 -> 0.9981 | M117: 0.010277129 | N117: =+Data_input!AN120 -> NaN | O117: NaN | P117: NaN | Q117: NaN | R117: NaN | S117: NaN | T117: NaN | U117: NaN
A118: 36341 | B118: =+Data_input!AO121 -> 0.18693549 | C118: =+Data_input!AW121 -> 2.0081971 | D118: =+Data_input!AU121 -> 0.73969227 | E118: =+Data_input!AR121 -> 0.20760282 | F118: =+Data_input!AS121 -> 0.27112534 | G118: =+Data_input!AT121 -> 0.655 | H118: =+Data_input!AP121 -> 0.69713061 | I118: =+Data_input!AQ121 -> 1.4679547 | J118: ='Option Adjusted rate'!O10/4 -> 1.7022348 | K118: =+Data_input!AX121 -> NaN | L118: =+Data_input!AY121 -> 1.06435 | M118: -0.0051862826 | N118: =+Data_input!AN121 -> NaN | O118: NaN | P118: NaN | Q118: NaN | R118: NaN | S118: NaN | T118: NaN | U118: NaN
A119: 36433 | B119: =+Data_input!AO122 -> 0.92636177 | C119: =+Data_input!AW122 -> 1.5636612 | D119: =+Data_input!AU122 -> 0.42465873 | E119: =+Data_input!AR122 -> 0.091040884 | F119: =+Data_input!AS122 -> 0.25753298 | G119: =+Data_input!AT122 -> 0.6525 | H119: =+Data_input!AP122 -> 0.95113209 | I119: =+Data_input!AQ122 -> 1.5412529 | J119: ='Option Adjusted rate'!O11/4 -> 1.5569648 | K119: =+Data_input!AX122 -> NaN | L119: =+Data_input!AY122 -> 1.262675 | M119: 0.010012727 | N119: =+Data_input!AN122 -> NaN | O119: NaN | P119: NaN | Q119: NaN | R119: NaN | S119: NaN | T119: NaN | U119: NaN
A120: 36525 | B120: =+Data_input!AO123 -> 0.77124127 | C120: =+Data_input!AW123 -> 1.8812739 | D120: =+Data_input!AU123 -> 0.51412695 | E120: =+Data_input!AR123 -> 0.31450303 | F120: =+Data_input!AS123 -> 0.29534532 | G120: =+Data_input!AT123 -> 0.7775 | H120: =+Data_input!AP123 -> 0.61767219 | I120: =+Data_input!AQ123 -> 0.5306946 | J120: ='Option Adjusted rate'!O12/4 -> 1.4585013 | K120: =+Data_input!AX123 -> NaN | L120: =+Data_input!AY123 -> 1.330025 | M120: 0.0012719113 | N120: =+Data_input!AN123 -> NaN | O120: NaN | P120: NaN | Q120: NaN | R120: NaN | S120: NaN | T120: NaN | U120: NaN
A121: 36616 | B121: =+Data_input!AO124 -> 0.81684359 | C121: =+Data_input!AW124 -> 2.0405808 | D121: =+Data_input!AU124 -> 0.25394238 | E121: =+Data_input!AR124 -> 0.46365675 | F121: =+Data_input!AS124 -> 0.19214763 | G121: =+Data_input!AT124 -> 0.8425 | H121: =+Data_input!AP124 -> 0.75601082 | I121: =+Data_input!AQ124 -> 2.5460331 | J121: ='Option Adjusted rate'!O13/4 -> 1.3387698 | K121: =+Data_input!AX124 -> 0.45 | L121: =+Data_input!AY124 -> 1.4044 | M121: 0.0059700813 | N121: =+Data_input!AN124 -> NaN | O121: =AAA_bond_data!I3 -> 0.094783333 | P121: NaN | Q121: NaN | R121: NaN | S121: NaN | T121: NaN | U121: NaN
A122: 36707 | B122: =+Data_input!AO125 -> 0.5885124 | C122: =+Data_input!AW125 -> 2.026313 | D122: =+Data_input!AU125 -> 0.23136427 | E122: =+Data_input!AR125 -> 0.2441902 | F122: =+Data_input!AS125 -> 0.17900529 | G122: =+Data_input!AT125 -> 1.0275 | H122: =+Data_input!AP125 -> 0.6968552 | I122: =+Data_input!AQ125 -> -0.095243287 | J122: ='Option Adjusted rate'!O14/4 -> 1.6417742 | K122: =+Data_input!AX125 -> NaN | L122: =+Data_input!AY125 -> 1.356225 | M122: 0.0022616091 | N122: =+Data_input!AN125 -> NaN | O122: =AAA_bond_data!I4 -> 0.11169167 | P122: NaN | Q122: NaN | R122: NaN | S122: NaN | T122: NaN | U122: NaN
A123: 36799 | B123: =+Data_input!AO126 -> 0.35888118 | C123: =+Data_input!AW126 -> 2.0407133 | D123: =+Data_input!AU126 -> 0.32688075 | E123: =+Data_input!AR126 -> 0.52933943 | F123: =+Data_input!AS126 -> 0.31885749 | G123: =+Data_input!AT126 -> 1.14 | H123: =+Data_input!AP126 -> 0.28066409 | I123: =+Data_input!AQ126 -> 0.46474739 | J123: ='Option Adjusted rate'!O15/4 -> 1.902122 | K123: =+Data_input!AX126 -> NaN | L123: =+Data_input!AY126 -> 1.359925 | M123: 0.00068997365 | N123: =+Data_input!AN126 -> NaN | O123: =AAA_bond_data!I5 -> 0.123675 | P123: NaN | Q123: NaN | R123: NaN | S123: NaN | T123: NaN | U123: NaN
A124: 36891 | B124: =+Data_input!AO127 -> 0.29328572 | C124: =+Data_input!AW127 -> 2.2494962 | D124: =+Data_input!AU127 -> 0.087029855 | E124: =+Data_input!AR127 -> 0.58686663 | F124: =+Data_input!AS127 -> 0.4066596 | G124: =+Data_input!AT127 -> 1.2275 | H124: =+Data_input!AP127 -> 0.27053892 | I124: =+Data_input!AQ127 -> 0.56065532 | J124: ='Option Adjusted rate'!O16/4 -> 2.6170851 | K124: =+Data_input!AX127 -> NaN | L124: =+Data_input!AY127 -> 1.318325 | M124: 0.00019842795 | N124: =+Data_input!AN127 -> NaN | O124: =AAA_bond_data!I6 -> 0.14478333 | P124: NaN | Q124: NaN | R124: NaN | S124: NaN | T124: NaN | U124: NaN
A125: 36981 | B125: =+Data_input!AO128 -> 1.066543 | C125: =+Data_input!AW128 -> 2.4373456 | D125: =+Data_input!AU128 -> -0.20258512 | E125: =+Data_input!AR128 -> 0.74135599 | F125: =+Data_input!AS128 -> 0.29126849 | G125: =+Data_input!AT128 -> 1.1975 | H125: =+Data_input!AP128 -> 0.58195044 | I125: =+Data_input!AQ128 -> 0.69346271 | J125: ='Option Adjusted rate'!O17/4 -> 2.5808575 | K125: =+Data_input!AX128 -> 0.45 | L125: =+Data_input!AY128 -> 1.247275 | M125: 0.0098689357 | N125: =+Data_input!AN128 -> NaN | O125: =AAA_bond_data!I7 -> 0.11433333 | P125: NaN | Q125: NaN | R125: NaN | S125: NaN | T125: NaN | U125: NaN
A126: 37072 | B126: =+Data_input!AO129 -> -0.0033490631 | C126: =+Data_input!AW129 -> 2.1168453 | D126: =+Data_input!AU129 -> 0.056014985 | E126: =+Data_input!AR129 -> 0.63863325 | F126: =+Data_input!AS129 -> 0.5548564 | G126: =+Data_input!AT129 -> 1.165 | H126: =+Data_input!AP129 -> 0.33047002 | I126: =+Data_input!AQ129 -> -1.2121815 | J126: ='Option Adjusted rate'!O18/4 -> 2.7838867 | K126: =+Data_input!AX129 -> 0.45 | L126: =+Data_input!AY129 -> 1.297675 | M126: 0.0024914308 | N126: =+Data_input!AN129 -> NaN | O126: =AAA_bond_data!I8 -> 0.091025 | P126: NaN | Q126: NaN | R126: NaN | S126: NaN | T126: NaN | U126: NaN
A127: 37164 | B127: =+Data_input!AO130 -> 0.010394459 | C127: =+Data_input!AW130 -> 1.9817236 | D127: =+Data_input!AU130 -> 0.060207972 | E127: =+Data_input!AR130 -> 0.60099898 | F127: =+Data_input!AS130 -> 0.6393002 | G127: =+Data_input!AT130 -> 1.085 | H127: =+Data_input!AP130 -> -0.12665652 | I127: =+Data_input!AQ130 -> -1.5774757 | J127: ='Option Adjusted rate'!O19/4 -> 3.2033582 | K127: =+Data_input!AX130 -> 0.45 | L127: =+Data_input!AY130 -> 1.2788 | M127: 0.0020499607 | N127: =+Data_input!AN130 -> NaN | O127: =AAA_bond_data!I9 -> 0.10088333 | P127: NaN | Q127: NaN | R127: NaN | S127: NaN | T127: NaN | U127: NaN
A128: 37256 | B128: =+Data_input!AO131 -> -0.30191394 | C128: =+Data_input!AW131 -> 1.8129294 | D128: =+Data_input!AU131 -> -0.02686963 | E128: =+Data_input!AR131 -> 0.79753136 | F128: =+Data_input!AS131 -> 0.61040364 | G128: =+Data_input!AT131 -> 0.88 | H128: =+Data_input!AP131 -> -0.29268286 | I128: =+Data_input!AQ131 -> -0.43084039 | J128: ='Option Adjusted rate'!O20/4 -> 3.6031807 | K128: =+Data_input!AX131 -> 0.45 | L128: =+Data_input!AY131 -> 1.203525 | M128: -0.00040030308 | N128: =+Data_input!AN131 -> NaN | O128: =AAA_bond_data!I10 -> 0.059059102 | P128: NaN | Q128: NaN | R128: NaN | S128: NaN | T128: NaN | U128: NaN
A129: 37346 | B129: =+Data_input!AO132 -> -0.16359979 | C129: =+Data_input!AW132 -> 1.4033876 | D129: =+Data_input!AU132 -> -0.15809465 | E129: =+Data_input!AR132 -> 0.68273251 | F129: =+Data_input!AS132 -> 0.77936932 | G129: =+Data_input!AT132 -> 0.8375 | H129: =+Data_input!AP132 -> -0.33748167 | I129: =+Data_input!AQ132 -> -1.470943 | J129: ='Option Adjusted rate'!O21/4 -> 3.027892 | K129: =+Data_input!AX132 -> 0.475 | L129: =+Data_input!AY132 -> 1.2838 | M129: 0.00039300753 | N129: =+Data_input!AN132 -> NaN | O129: =AAA_bond_data!I11 -> -0.062447209 | P129: NaN | Q129: NaN | R129: NaN | S129: NaN | T129: NaN | U129: NaN
A130: 37437 | B130: =+Data_input!AO133 -> 0.25061134 | C130: =+Data_input!AW133 -> 1.3115264 | D130: =+Data_input!AU133 -> 0.27233458 | E130: =+Data_input!AR133 -> 0.36205114 | F130: =+Data_input!AS133 -> 0.47944034 | G130: =+Data_input!AT133 -> 0.84 | H130: =+Data_input!AP133 -> -0.085792892 | I130: =+Data_input!AQ133 -> -0.44349156 | J130: ='Option Adjusted rate'!O22/4 -> 2.7582437 | K130: =+Data_input!AX133 -> 0.475 | L130: =+Data_input!AY133 -> 1.313775 | M130: 0.0018602196 | N130: =+Data_input!AN133 -> 0.69547567 | O130: =AAA_bond_data!I12 -> -0.095479439 | P130: NaN | Q130: NaN | R130: NaN | S130: NaN | T130: NaN | U130: NaN
A131: 37529 | B131: =+Data_input!AO134 -> 0.25958334 | C131: =+Data_input!AW134 -> 1.0875781 | D131: =+Data_input!AU134 -> 0.0458799 | E131: =+Data_input!AR134 -> 0.68221069 | F131: =+Data_input!AS134 -> 0.55035912 | G131: =+Data_input!AT134 -> 0.835 | H131: =+Data_input!AP134 -> 0.049938196 | I131: =+Data_input!AQ134 -> -0.3753388 | J131: ='Option Adjusted rate'!O23/4 -> 3.0159127 | K131: =+Data_input!AX134 -> 0.475 | L131: =+Data_input!AY134 -> 1.19015 | M131: 0.0004233431 | N131: =+Data_input!AN134 -> 0.15703327 | O131: =AAA_bond_data!I13 -> 0.036650688 | P131: NaN | Q131: NaN | R131: NaN | S131: NaN | T131: NaN | U131: NaN
A132: 37621 | B132: =+Data_input!AO135 -> 0.0036962948 | C132: =+Data_input!AW135 -> 0.88250033 | D132: =+Data_input!AU135 -> 0.16837642 | E132: =+Data_input!AR135 -> 0.45745136 | F132: =+Data_input!AS135 -> 0.45025936 | G132: =+Data_input!AT135 -> 0.7925 | H132: =+Data_input!AP135 -> 0.44872784 | I132: =+Data_input!AQ135 -> 0.43508008 | J132: ='Option Adjusted rate'!O24/4 -> 2.8788375 | K132: =+Data_input!AX135 -> 0.475 | L132: =+Data_input!AY135 -> 1.1352 | M132: 0.0017562027 | N132: =+Data_input!AN135 -> -0.35730688 | O132: =AAA_bond_data!I14 -> 0.089716974 | P132: NaN | Q132: NaN | R132: NaN | S132: NaN | T132: NaN | U132: NaN
... A156: 39813 | B156: =+Data_input!AO159 -> -1.817165 | C156: =+Data_input!AW159 -> 2.5339817 | D156: =+Data_input!AU159 -> -0.02591366 | E156: =+Data_input!AR159 -> 0.28963954 | F156: =+Data_input!AS159 -> 0.42389064 | G156: =+Data_input!AT159 -> 0.9725 | H156: =+Data_input!AP159 -> -1.5606577 | I156: =+Data_input!AQ159 -> -4.2111346 | J156: ='Option Adjusted rate'!O48/4 -> 5.0071652 | K156: =+Data_input!AX159 -> 0.5 | L156: =+Data_input!AY159 -> 1.0417 | M156: -0.014913348 | N156: =+Data_input!AN159 -> -2.68736 | O156: =AAA_bond_data!I38 -> 0.45060752 | P156: NaN | Q156: NaN | R156: NaN | S156: NaN | T156: NaN | U156: NaN
A157: 39903 | B157: =+Data_input!AO160 -> -3.2031278 | C157: =+Data_input!AW160 -> 0.58723333 | D157: =+Data_input!AU160 -> -0.44449753 | E157: =+Data_input!AR160 -> 0.37264124 | F157: =+Data_input!AS160 -> 0.24914707 | G157: =+Data_input!AT160 -> 0.42 | H157: =+Data_input!AP160 -> -1.6862662 | I157: =+Data_input!AQ160 -> -6.4739188 | J157: ='Option Adjusted rate'!O49/4 -> 5.0305988 | K157: =+Data_input!AX160 -> 0.475 | L157: =+Data_input!AY160 -> 1.036825 | M157: -0.011341163 | N157: =+Data_input!AN160 -> -2.0693688 | O157: =AAA_bond_data!I39 -> 0.38839329 | P157: 0.26333333 | Q157: 0.25083333 | R157: 0.25404906 | S157: 0.26166667 | T157: 0.2736387 | U157: 0.29295662
A158: 39994 | B158: =+Data_input!AO161 -> -0.14486729 | C158: =+Data_input!AW161 -> -0.40286214 | D158: =+Data_input!AU161 -> 0.42712165 | E158: =+Data_input!AR161 -> 0.039023943 | F158: =+Data_input!AS161 -> 0.30247403 | G158: =+Data_input!AT161 -> 0.2325 | H158: =+Data_input!AP161 -> -0.069378451 | I158: =+Data_input!AQ161 -> -3.0457485 | J158: ='Option Adjusted rate'!O50/4 -> 4.2350469 | K158: =+Data_input!AX161 -> 0.475 | L158: =+Data_input!AY161 -> 1.045475 | M158: 0.022208188 | N158: =+Data_input!AN161 -> -0.032982158 | O158: =AAA_bond_data!I40 -> 0.31158672 | P158: 0.18666667 | Q158: 0.1875 | R158: 0.19718905 | S158: 0.215 | T158: 0.23513583 | U158: 0.26021333
A159: 40086 | B159: =+Data_input!AO162 -> 0.38468875 | C159: =+Data_input!AW162 -> -0.80040201 | D159: =+Data_input!AU162 -> 0.61735486 | E159: =+Data_input!AR162 -> 0.083735287 | F159: =+Data_input!AS162 -> 0.20473042 | G159: =+Data_input!AT162 -> 0.1325 | H159: =+Data_input!AP162 -> 0.10077442 | I159: =+Data_input!AQ162 -> -0.18987777 | J159: ='Option Adjusted rate'!O51/4 -> 2.8542765 | K159: =+Data_input!AX162 -> 0.5 | L159: =+Data_input!AY162 -> 0.98715 | M159: 0.0038784991 | N159: =+Data_input!AN162 -> 1.0775634 | O159: =AAA_bond_data!I41 -> 0.14438333 | P159: 0.1075 | Q159: 0.12166667 | R159: 0.14445908 | S159: 0.17333333 | T159: 0.20501927 | U159: 0.2403875
A160: 40178 | B160: =+Data_input!AO163 -> 0.40258996 | C160: =+Data_input!AW163 -> -1.1185774 | D160: =+Data_input!AU163 -> 0.40196858 | E160: =+Data_input!AR163 -> 0.21189239 | F160: =+Data_input!AS163 -> 0.21505385 | G160: =+Data_input!AT163 -> 0.1125 | H160: =+Data_input!AP163 -> 0.3355153 | I160: =+Data_input!AQ163 -> -0.73160968 | J160: ='Option Adjusted rate'!O52/4 -> 2.0619992 | K160: =+Data_input!AX163 -> 0.475 | L160: =+Data_input!AY163 -> 0.95935 | M160: -0.00058000808 | N160: =+Data_input!AN163 -> 0.27757209 | O160: =AAA_bond_data!I42 -> 0.10503286 | P160: 0.10666667 | Q160: 0.12333333 | R160: 0.15181279 | S160: 0.18583333 | T160: 0.21806869 | U160: 0.25087587
A161: 40268 | B161: =+Data_input!AO164 -> 0.80888649 | C161: =+Data_input!AW164 -> -0.78811763 | D161: =+Data_input!AU164 -> 0.24723738 | E161: =+Data_input!AR164 -> 0.10520659 | F161: =+Data_input!AS164 -> 0.21459236 | G161: =+Data_input!AT164 -> 0.105 | H161: =+Data_input!AP164 -> 0.90288216 | I161: =+Data_input!AQ164 -> -0.36865908 | J161: ='Option Adjusted rate'!O53/4 -> 1.7407798 | K161: =+Data_input!AX164 -> 0.475 | L161: =+Data_input!AY164 -> 1.0161 | M161: 0.0048806397 | N161: =+Data_input!AN164 -> 0.44401988 | O161: =AAA_bond_data!I43 -> 0.040506177 | P161: 0.090833333 | Q161: 0.10916667 | R161: 0.1347544 | S161: 0.16333333 | T161: 0.19016495 | U161: 0.21690588
A162: 40359 | B162: =+Data_input!AO165 -> 0.82164216 | C162: =+Data_input!AW165 -> -0.65250689 | D162: =+Data_input!AU165 -> 0.51647859 | E162: =+Data_input!AR165 -> 0.25455327 | F162: =+Data_input!AS165 -> 0.23552093 | G162: =+Data_input!AT165 -> 0.105 | H162: =+Data_input!AP165 -> 0.4866205 | I162: =+Data_input!AQ165 -> 2.9857237 | J162: ='Option Adjusted rate'!O54/4 -> 1.7874747 | K162: =+Data_input!AX165 -> 0.475 | L162: =+Data_input!AY165 -> 0.9604 | M162: -0.002096151 | N162: =+Data_input!AN165 -> 0.88615576 | O162: =AAA_bond_data!I44 -> 0.035290565 | P162: 0.10166667 | Q162: 0.11833333 | R162: 0.1314981 | S162: 0.14416667 | T162: 0.15810032 | U162: 0.17257065
A163: 40451 | B163: =+Data_input!AO166 -> 0.36912669 | C163: =+Data_input!AW166 -> -0.73791966 | D163: =+Data_input!AU166 -> 0.018680258 | E163: =+Data_input!AR166 -> 0.34142933 | F163: =+Data_input!AS166 -> 0.33093171 | G163: =+Data_input!AT166 -> 0.1525 | H163: =+Data_input!AP166 -> 0.31634093 | I163: =+Data_input!AQ166 -> -0.89642119 | J163: ='Option Adjusted rate'!O55/4 -> 1.6745949 | K163: =+Data_input!AX166 -> 0.5 | L163: =+Data_input!AY166 -> 0.87865 | M163: -0.0072056525 | N163: =+Data_input!AN166 -> 0.35088279 | O163: =AAA_bond_data!I45 -> 0.05255 | P163: 0.13333333 | Q163: 0.1475 | R163: 0.1604494 | S163: 0.1725 | T163: 0.18376842 | U163: 0.19455341
A164: 40543 | B164: =+Data_input!AO167 -> 0.56665893 | C164: =+Data_input!AW167 -> -0.73881827 | D164: =+Data_input!AU167 -> 0.26557601 | E164: =+Data_input!AR167 -> 0.15099483 | F164: =+Data_input!AS167 -> 0.35108287 | G164: =+Data_input!AT167 -> 0.2025 | H164: =+Data_input!AP167 -> 0.75947458 | I164: =+Data_input!AQ167 -> 0.33059524 | J164: ='Option Adjusted rate'!O56/4 -> 1.4420586 | K164: =+Data_input!AX167 -> 0.475 | L164: =+Data_input!AY167 -> 0.92675 | M164: 0.0030536815 | N164: =+Data_input!AN167 -> 0.88126571 | O164: =AAA_bond_data!I46 -> 0.062208677 | P164: 0.17916667 | Q164: 0.195 | R164: 0.20780619 | S164: 0.22 | T164: 0.23305564 | U164: 0.24641983
A165: 40633 | B165: =+Data_input!AO168 -> 0.98527755 | C165: =+Data_input!AW168 -> -0.11248033 | D165: =+Data_input!AU168 -> 0.45106429 | E165: =+Data_input!AR168 -> 0.3883588 | F165: =+Data_input!AS168 -> 0.44505743 | G165: =+Data_input!AT168 -> 0.215 | H165: =+Data_input!AP168 -> 0.27647018 | I165: =+Data_input!AQ168 -> 1.8404756 | J165: ='Option Adjusted rate'!O57/4 -> 1.2983501 | K165: =+Data_input!AX168 -> 0.5 | L165: =+Data_input!AY168 -> 1.0757 | M165: 0.0013473891 | N165: =+Data_input!AN168 -> 0.71418656 | O165: =AAA_bond_data!I47 -> 0.053158333 | P165: 0.20583333 | Q165: 0.23583333 | R165: 0.26485046 | S165: 0.2925 | T165: 0.3184866 | U165: 0.34356216
A166: 40724 | B166: =+Data_input!AO169 -> -0.052750717 | C166: =+Data_input!AW169 -> -0.49262554 | D166: =+Data_input!AU169 -> 0.30399588 | E166: =+Data_input!AR169 -> 0.2099679 | F166: =+Data_input!AS169 -> 0.4746594 | G166: =+Data_input!AT169 -> 0.305 | H166: =+Data_input!AP169 -> 0.15113715 | I166: =+Data_input!AQ169 -> 0.047297189 | J166: ='Option Adjusted rate'!O58/4 -> 1.2782612 | K166: =+Data_input!AX169 -> 0.5 | L166: =+Data_input!AY169 -> 1.117325 | M166: -0.0029307052 | N166: =+Data_input!AN169 -> 0.13619198 | O166: =AAA_bond_data!I48 -> -0.012032705 | P166: 0.29583333 | Q166: 0.32916667 | R166: 0.35681095 | S166: 0.38083333 | T166: 0.40249786 | U166: 0.42268328
A167: 40816 | B167: =+Data_input!AO170 -> -0.037417743 | C167: =+Data_input!AW170 -> -0.69552341 | D167: =+Data_input!AU170 -> -0.061444234 | E167: =+Data_input!AR170 -> 0.32312025 | F167: =+Data_input!AS170 -> 0.48288987 | G167: =+Data_input!AT170 -> 0.345 | H167: =+Data_input!AP170 -> -0.16876137 | I167: =+Data_input!AQ170 -> -0.91201013 | J167: ='Option Adjusted rate'!O59/4 -> 1.9177223 | K167: =+Data_input!AX170 -> 0.5 | L167: =+Data_input!AY170 -> 1.0708 | M167: -0.00069839804 | N167: =+Data_input!AN170 -> -0.49426537 | O167: =AAA_bond_data!I49 -> -0.084325 | P167: 0.24916667 | Q167: 0.245 | R167: 0.24360584 | S167: 0.24416667 | T167: 0.24707524 | U167: 0.25091873
A168: 40908 | B168: =+Data_input!AO171 -> -0.37454403 | C168: =+Data_input!AW171 -> -1.108852 | D168: =+Data_input!AU171 -> 0.2459208 | E168: =+Data_input!AR171 -> 0.23016262 | F168: =+Data_input!AS171 -> 0.4909908 | G168: =+Data_input!AT171 -> 0.31 | H168: =+Data_input!AP171 -> -0.18084839 | I168: =+Data_input!AQ171 -> -0.52791707 | J168: ='Option Adjusted rate'!O60/4 -> 2.3162374 | K168: =+Data_input!AX171 -> 0.5 | L168: =+Data_input!AY171 -> 1.047175 | M168: -0.0037168057 | N168: =+Data_input!AN171 -> -0.30610794 | O168: =AAA_bond_data!I50 -> -0.061050481 | P168: 0.15416667 | Q168: 0.14083333 | R168: 0.13779245 | S168: 0.13666667 | T168: 0.13809896 | U168: 0.14229167
... A207: 44469 | B207: =+Data_input!AO210 -> 1.7702691 | C207: =+Data_input!AW210 -> -0.77096529 | D207: =+Data_input!AU210 -> 0.66660373 | E207: =+Data_input!AR210 -> 1.2219632 | F207: =+Data_input!AS210 -> 0.6937311 | G207: =+Data_input!AT210 -> -0.14 | H207: =+Data_input!AP210 -> 3.6182817 | I207: =+Data_input!AQ210 -> 0.87204224 | J207: ='Option Adjusted rate'!O99/4 -> 0.75400198 | K207: =+Data_input!AX210 -> 0.45 | L207: =+Data_input!AY210 -> 0.03505 | M207: -0.0016475162 | N207: =+Data_input!AN210 -> 1.0302574 | O207: =AAA_bond_data!I89 -> 0.054666667 | P207: -0.12 | Q207: -0.12 | R207: -0.12125 | S207: -0.1225 | T207: -0.12248047 | U207: -0.12234375
A208: 44561 | B208: =+Data_input!AO211 -> 0.67683784 | C208: =+Data_input!AW211 -> -0.1505032 | D208: =+Data_input!AU211 -> -0.23336922 | E208: =+Data_input!AR211 -> 1.1503298 | F208: =+Data_input!AS211 -> 0.83729208 | G208: =+Data_input!AT211 -> -0.145 | H208: =+Data_input!AP211 -> 0.38831267 | I208: =+Data_input!AQ211 -> 0.57438403 | J208: ='Option Adjusted rate'!O100/4 -> 0.83215909 | K208: =+Data_input!AX211 -> 0.475 | L208: =+Data_input!AY211 -> 0.07865 | M208: -0.00072048092 | N208: =+Data_input!AN211 -> -7.5229047e-05 | O208: =AAA_bond_data!I90 -> 0.066683333 | P208: -0.12 | Q208: -0.12 | R208: -0.12 | S208: -0.12 | T208: NaN | U208: NaN
A209: 44651 | B209: =+Data_input!AO212 -> 0.32195117 | C209: =+Data_input!AW212 -> 0.67440925 | D209: =+Data_input!AU212 -> -0.52701448 | E209: =+Data_input!AR212 -> 1.4076647 | F209: =+Data_input!AS212 -> 1.0964315 | G209: =+Data_input!AT212 -> -0.1375 | H209: =+Data_input!AP212 -> 0.92928724 | I209: =+Data_input!AQ212 -> 1.7703617 | J209: ='Option Adjusted rate'!O101/4 -> 0.98129193 | K209: =+Data_input!AX212 -> 0.5 | L209: =+Data_input!AY212 -> 0.211025 | M209: 0.00044474096 | N209: =+Data_input!AN212 -> 0.96930212 | O209: =AAA_bond_data!I91 -> 0.082516667 | P209: -0.12 | Q209: NaN | R209: NaN | S209: NaN | T209: NaN | U209: NaN
A210: 44742 | B210: =+Data_input!AO213 -> 0.60189144 | C210: =+Data_input!AW213 -> 0.87916912 | D210: =+Data_input!AU213 -> -0.46207089 | E210: =+Data_input!AR213 -> 1.233271 | F210: =+Data_input!AS213 -> 1.5547888 | G210: =+Data_input!AT213 -> -0.135 | H210: =+Data_input!AP213 -> 1.4677621 | I210: =+Data_input!AQ213 -> 1.5329684 | J210: ='Option Adjusted rate'!O102/4 -> 1.1945364 | K210: =+Data_input!AX213 -> 0.525 | L210: =+Data_input!AY213 -> 0.489975 | M210: -0.00092197559 | N210: =+Data_input!AN213 -> 0.26057818 | O210: =AAA_bond_data!I92 -> 0.061175 | P210: NaN | Q210: NaN | R210: NaN | S210: NaN | T210: NaN | U210: NaN
A211: 44834 | B211: =+Data_input!AO214 -> 0.41371668 | C211: =+Data_input!AW214 -> 0.97582975 | D211: =+Data_input!AU214 -> 0.22631227 | E211: =+Data_input!AR214 -> 1.2711205 | F211: =+Data_input!AS214 -> 1.8414751 | G211: =+Data_input!AT214 -> 0.0225 | H211: =+Data_input!AP214 -> 1.4229478 | I211: =+Data_input!AQ214 -> 0.94289878 | J211: ='Option Adjusted rate'!O103/4 -> 1.4378706 | K211: =+Data_input!AX214 -> 0.55 | L211: =+Data_input!AY214 -> 0.580375 | M211: -0.002385349 | N211: =+Data_input!AN214 -> -0.16921709 | O211: =AAA_bond_data!I93 -> 0.05415 | P211: NaN | Q211: NaN | R211: NaN | S211: NaN | T211: NaN | U211: NaN
A212: 44926 | B212: =+Data_input!AO215 -> -0.28388934 | C212: =+Data_input!AW215 -> 1.1842006 | D212: =+Data_input!AU215 -> -0.31865134 | E212: =+Data_input!AR215 -> 1.8568648 | F212: =+Data_input!AS215 -> 1.9646308 | G212: =+Data_input!AT215 -> 0.3375 | H212: =+Data_input!AP215 -> -0.44042566 | I212: =+Data_input!AQ215 -> -2.8514177 | J212: ='Option Adjusted rate'!O104/4 -> 1.3668795 | K212: =+Data_input!AX215 -> 0.55 | L212: =+Data_input!AY215 -> 0.75995 | M212: 0.000451753 | N212: =+Data_input!AN215 -> -0.72881202 | O212: =AAA_bond_data!I94 -> 0.038275 | P212: NaN | Q212: NaN | R212: NaN | S212: NaN | T212: NaN | U212: NaN
A213: 45016 | B213: =+Data_input!AO216 -> -0.25040058 | C213: =+Data_input!AW216 -> 1.7869775 | D213: =+Data_input!AU216 -> -0.47674104 | E213: =+Data_input!AR216 -> 1.9739618 | F213: =+Data_input!AS216 -> 1.7733098 | G213: =+Data_input!AT216 -> 0.5875 | H213: =+Data_input!AP216 -> -0.50203818 | I213: =+Data_input!AQ216 -> 2.3567049 | J213: ='Option Adjusted rate'!O105/4 -> 1.1198787 | K213: =+Data_input!AX216 -> 0.525 | L213: =+Data_input!AY216 -> 0.791675 | M213: -0.0086726071 | N213: =+Data_input!AN216 -> 0.64789447 | O213: =AAA_bond_data!I95 -> 0.0021083333 | P213: NaN | Q213: NaN | R213: NaN | S213: NaN | T213: NaN | U213: NaN
A214: 45107 | B214: =+Data_input!AO217 -> -0.033079096 | C214: =+Data_input!AW217 -> 1.6997823 | D214: =+Data_input!AU217 -> -0.19189735 | E214: =+Data_input!AR217 -> 1.0988731 | F214: =+Data_input!AS217 -> 1.1958923 | G214: =+Data_input!AT217 -> 0.7875 | H214: =+Data_input!AP217 -> 0.26686217 | I214: =+Data_input!AQ217 -> -0.72287779 | J214: ='Option Adjusted rate'!O106/4 -> 1.1567049 | K214: =+Data_input!AX217 -> 0.525 | L214: =+Data_input!AY217 -> 0.79695 | M214: -0.00061153411 | N214: =+Data_input!AN217 -> -0.037677235 | O214: =AAA_bond_data!I96 -> 0.0179 | P214: NaN | Q214: NaN | R214: NaN | S214: NaN | T214: NaN | U214: NaN
A215: 45199 | B215: =+Data_input!AO218 -> -0.1688253 | C215: =+Data_input!AW218 -> 1.8965219 | D215: =+Data_input!AU218 -> 0.48884335 | E215: =+Data_input!AR218 -> 0.73089647 | F215: =+Data_input!AS218 -> 0.839565 | G215: =+Data_input!AT218 -> 0.905 | H215: =+Data_input!AP218 -> 0.17952116 | I215: =+Data_input!AQ218 -> -1.1544371 | J215: ='Option Adjusted rate'!O107/4 -> 1.0938759 | K215: =+Data_input!AX218 -> 0.525 | L215: =+Data_input!AY218 -> 0.843125 | M215: -0.00078822684 | N215: =+Data_input!AN218 -> -0.36633131 | O215: =AAA_bond_data!I97 -> -0.014225 | P215: NaN | Q215: NaN | R215: NaN | S215: NaN | T215: NaN | U215: NaN
A216: 45291 | B216: =+Data_input!AO219 -> -0.14555614 | C216: =+Data_input!AW219 -> 1.8224842 | D216: =+Data_input!AU219 -> 0.30770902 | E216: =+Data_input!AR219 -> 1.1024605 | F216: =+Data_input!AS219 -> 0.4587738 | G216: =+Data_input!AT219 -> 0.9625 | H216: =+Data_input!AP219 -> -0.71269372 | I216: =+Data_input!AQ219 -> -0.44793857 | J216: ='Option Adjusted rate'!O108/4 -> 1.1086923 | K216: =+Data_input!AX219 -> 0.525 | L216: =+Data_input!AY219 -> 0.83415 | M216: 0.010197291 | N216: =+Data_input!AN219 -> -0.5557768 | O216: =AAA_bond_data!I98 -> -0.010333333 | P216: NaN | Q216: NaN | R216: NaN | S216: NaN | T216: NaN | U216: NaN
A217: 45382 | B217: =+Data_input!AO220 -> 0.23804658 | C217: =+Data_input!AW220 -> 1.9090619 | D217: =+Data_input!AU220 -> 0.59616999 | E217: =+Data_input!AR220 -> 0.55834199 | F217: =+Data_input!AS220 -> 0.75447027 | G217: =+Data_input!AT220 -> 0.965 | H217: =+Data_input!AP220 -> 0.42473893 | I217: =+Data_input!AQ220 -> -1.9920593 | J217: ='Option Adjusted rate'!O109/4 -> 0.90685786 | K217: =+Data_input!AX220 -> 0.5 | L217: =+Data_input!AY220 -> 0.7401 | M217: -0.003576708 | N217: =+Data_input!AN220 -> 0.82334856 | O217: =AAA_bond_data!I99 -> 0.0075 | P217: NaN | Q217: NaN | R217: NaN | S217: NaN | T217: NaN | U217: NaN
A218: 45473 | B218: =+Data_input!AO221 -> -0.1237063 | C218: =+Data_input!AW221 -> 1.7508705 | D218: =+Data_input!AU221 -> 0.35770701 | E218: =+Data_input!AR221 -> 0.49951313 | F218: =+Data_input!AS221 -> 0.71602298 | G218: =+Data_input!AT221 -> 0.9425 | H218: =+Data_input!AP221 -> -0.38013065 | I218: =+Data_input!AQ221 -> -1.2817028 | J218: ='Option Adjusted rate'!O110/4 -> 0.86191307 | K218: =+Data_input!AX221 -> 0.5 | L218: =+Data_input!AY221 -> 0.780125 | M218: 0.0011409494 | N218: =+Data_input!AN221 -> 0.1158789 | O218: =AAA_bond_data!I100 -> 0.037566667 | P218: NaN | Q218: NaN | R218: NaN | S218: NaN | T218: NaN | U218: NaN
A219: 45565 | B219: =+Data_input!AO222 -> 0.24883178 | C219: =+Data_input!AW222 -> 1.6355273 | D219: =+Data_input!AU222 -> 0.31342466 | E219: =+Data_input!AR222 -> 0.54480667 | F219: =+Data_input!AS222 -> 0.74349785 | G219: =+Data_input!AT222 -> 0.8875 | H219: =+Data_input!AP222 -> 0.26095144 | I219: =+Data_input!AQ222 -> 0.82998757 | J219: ='Option Adjusted rate'!O111/4 -> 0.88152864 | K219: =+Data_input!AX222 -> 0.5 | L219: =+Data_input!AY222 -> 0.7377 | M219: 0.0033927779 | N219: NaN | O219: =AAA_bond_data!I101 -> 0.068766667 | P219: NaN | Q219: NaN | R219: NaN | S219: NaN | T219: NaN | U219: NaN

Sheet Eur_Productivity_BoEspana
F1: Source: https://www.bde.es/wbe/en/areas-actuacion/analisis-e-investigacion/recursos/europrod-ua.html
A6: country | B6: year | C6: quarter | D6: dZ_Solow | E6: dZ | F6: dZ_Solow_EA | G6: dZ_EA | H6: dZ_interp | I6: dZ_interp_EA | J6: dY | K6: dL | L6: dK | M6: dU | N6: dtotal_hours | O6: alpha_L | P6: alpha_K
A7: DE | B7: 1998 | C7: 1 | M7: 0.0016158154
A8: DE | B8: 1998 | C8: 2 | D8: -0.014616288 | E8: -0.016907867 | F8: -0.0057730451 | G8: -0.0076444745 | H8: -0.016907867 | I8: -0.0076444745 | J8: -0.0088191433 | K8: 0.0064827893 | L8: 0.0041834703 | M8: 0.0022297925 | N8: 0.0061854874 | O8: 0.72867703 | P8: 0.27132297
A9: DE | B9: 1998 | C9: 3 | D9: -0.0014230631 | E9: 4.7634348e-05 | F9: -0.0029452411 | G9: -0.0033146378 | H9: 4.7633424e-05 | I9: -0.0033146383 | J9: 0.0041161883 | K9: 0.0060262503 | L9: 0.0043936088 | M9: -0.0015163539 | N9: 0.0057293619 | O9: 0.72967583 | P9: 0.27032417
A10: DE | B10: 1998 | C10: 4 | D10: -0.00013220015 | E10: 0.0074779023 | F10: 0.00099958212 | G10: 0.0062073288 | H10: 0.0074779028 | I10: 0.0062073292 | J10: 0.00032290738 | K10: -0.0011832172 | L10: 0.0043074507 | M10: -0.0074505541 | N10: -0.0014797393 | O10: 0.73067462 | P10: 0.26932538
A11: DE | B11: 1999 | C11: 1 | D11: 0.011135586 | E11: 0.013945235 | F11: 0.0076715485 | G11: 0.010277129 | H11: 0.013945235 | I11: 0.010277129 | J11: 0.012708548 | K11: -1.9807821e-05 | L11: 0.0053099133 | M11: -0.0026727442 | N11: -0.00031600826 | O11: 0.72684044 | P11: 0.27315956
A12: DE | B12: 1999 | C12: 2 | D12: -0.0021714459 | E12: -0.0014587931 | F12: -0.0055091456 | G12: -0.0051862826 | H12: -0.0014587932 | I12: -0.0051862826 | J12: 2.2983939e-05 | K12: 0.00095612754 | L12: 0.0051117963 | M12: -0.00062481995 | N12: 0.00066035282 | O12: 0.72315657 | P12: 0.2768434
A13: DE | B13: 1999 | C13: 3 | D13: 0.010897027 | E13: 0.0078501739 | F13: 0.011141896 | G13: 0.010012727 | H13: 0.0078501739 | I13: 0.010012728 | J13: 0.014719843 | K13: 0.0031604751 | L13: 0.0054025669 | M13: 0.0030913998 | N13: 0.0026285602 | O13: 0.72445607 | P13: 0.2755439
A14: DE | B14: 1999 | C14: 4 | D14: -0.00054579851 | E14: -0.0024511167 | F14: 0.0046069077 | G14: 0.0012719113 | H14: -0.0024511162 | I14: 0.0012719111 | J14: 0.0029709132 | K14: 0.0028286832 | L14: 0.0051781503 | M14: 0.0019490186 | N14: 0.0022981151 | O14: 0.72575557 | P14: 0.2742444
A15: DE | B15: 2000 | C15: 1 | D15: 0.0092280796 | E15: 0.003720243 | F15: 0.0070113093 | G15: 0.0059700813 | H15: 0.0037202425 | I15: 0.0059700813 | J15: 0.016405847 | K15: 0.0074537271 | L15: 0.0064868559 | M15: 0.005490053 | N15: 0.0069246129 | O15: 0.73297775 | P15: 0.26702225
A16: DE | B16: 2000 | C16: 2 | D16: 0.0032729602 | E16: 0.00061622419 | F16: 0.004099437 | G16: 0.0022616091 | H16: 0.00061622448 | I16: 0.0022616095 | J16: 0.0064134542 | K16: 0.0018105409 | L16: 0.0065814536 | M16: 0.002744935 | N16: 0.0012828393 | O16: 0.73972404 | P16: 0.26027599
A17: DE | B17: 2000 | C17: 3 | D17: 0.0011822217 | E17: -0.0014985532 | F17: 0.0027287528 | G17: 0.00068997365 | H17: -0.001498553 | I17: 0.00068997405 | J17: 0.0041296827 | K17: 0.0013571184 | L17: 0.0070829168 | M17: 0.002782821 | N17: 0.0010994031 | O17: 0.74007183 | P17: 0.2599282
A18: DE | B18: 2000 | C18: 4 | D18: -0.0044390876 | E18: -0.0057701184 | F18: -9.1597089e-05 | G18: 0.00019842795 | H18: -0.0057701184 | I18: 0.00019842743 | J18: -0.0031330602 | K18: -0.00071377051 | L18: 0.0065848245 | M18: 0.0014562565 | N18: -0.0009722517 | O18: 0.74041963 | P18: 0.2595804
A19: DE | B19: 2001 | C19: 1 | D19: 0.023423897 | E19: 0.027066676 | F19: 0.0075819446 | G19: 0.0098689357 | H19: 0.027066676 | I19: 0.0098689357 | J19: 0.023609458 | K19: -0.002159819 | L19: 0.0062043518 | M19: -0.0035057606 | N19: -0.0024191048 | O19: 0.7359736 | P19: 0.2640264
... A116: DE | B116: 2025 | C116: 2 | D116: -0.0019577341 | E116: -0.0047703544 | F116: 0.0016714666 | G116: 0.001334863 | H116: -0.0047703683 | I116: 0.0013348577 | J116: -0.0026081149 | K116: -0.0030395337 | L116: 0.0051833517 | M116: 0.0030136509 | N116: -0.0028698214 | O116: 0.73389846 | P116: 0.26610154
A117: ES | B117: 1998 | C117: 1 | M117: 0.0048643006
A118: ES | B118: 1998 | C118: 2 | D118: -0.0079776561 | E118: -0.012972737 | F118: -0.0057730451 | G118: -0.0076444745 | H118: -0.012972737 | I118: -0.0076444745 | J118: 0.013753803 | K118: 0.027354958 | L118: 0.011133485 | M118: 0.0029896295 | N118: 0.027596211 | O118: 0.77695942 | P118: 0.22304058
A119: ES | B119: 1998 | C119: 3 | D119: -0.012713545 | E119: -0.011286408 | F119: -0.0029452411 | G119: -0.0033146378 | H119: -0.011286408 | I119: -0.0033146383 | J119: 0.0094767949 | K119: 0.027604597 | L119: 0.011937242 | M119: -0.0034138481 | N119: 0.028044645 | O119: 0.78123009 | P119: 0.21876992
A120: ES | B120: 1998 | C120: 4 | D120: 0.011232769 | E120: 0.015455788 | F120: 0.00099958212 | G120: 0.0062073288 | H120: 0.015455788 | I120: 0.0062073292 | J120: 0.011532803 | K120: -0.0061541516 | L120: 0.0125818 | M120: -0.0017876814 | N120: -0.0052036191 | O120: 0.78550076 | P120: 0.21449926
A121: ES | B121: 1999 | C121: 1 | D121: -0.0019116967 | E121: -0.0020340991 | F121: 0.0076715485 | G121: 0.010277129 | H121: -0.0020340988 | I121: 0.010277129 | J121: 0.011863151 | K121: 0.014205856 | L121: 0.012955386 | M121: -5.1561874e-05 | N121: 0.015950095 | O121: 0.79444194 | P121: 0.20555802
A122: ES | B122: 1999 | C122: 2 | D122: -0.012278688 | E122: -0.014158386 | F122: -0.0055091456 | G122: -0.0051862826 | H122: -0.014158386 | I122: -0.0051862826 | J122: 0.012202472 | K122: 0.030042514 | L122: 0.013926527 | M122: -0.00052596541 | N122: 0.030320132 | O122: 0.80418885 | P122: 0.19581115
A123: ES | B123: 1999 | C123: 3 | D123: 0.014693081 | E123: 0.019530658 | F123: 0.011141896 | G123: 0.010012727 | H123: 0.019530658 | I123: 0.010012728 | J123: 0.017590426 | K123: -0.0030831532 | L123: 0.014281319 | M123: -0.0021551009 | N123: -0.0025780462 | O123: 0.81007069 | P123: 0.18992928
A124: ES | B124: 1999 | C124: 4 | D124: -0.005465758 | E124: -0.010100396 | F124: 0.0046069077 | G124: 0.0012719113 | H124: -0.010100396 | I124: 0.0012719111 | J124: 0.01130703 | K124: 0.01796728 | L124: 0.014492263 | M124: 0.0040797153 | N124: 0.020170704 | O124: 0.81595254 | P124: 0.1840474
A125: ES | B125: 2000 | C125: 1 | D125: -0.0017023762 | E125: 0.00012128814 | F125: 0.0070113093 | G125: 0.0059700813 | H125: 0.000121288 | I125: 0.0059700813 | J125: 0.01594029 | K125: 0.019080088 | L125: 0.01486029 | M125: -0.0025222835 | N125: 0.018983684 | O125: 0.82492018 | P125: 0.17507976
A126: ES | B126: 2000 | C126: 2 | D126: 0.0020961999 | E126: -0.0016486609 | F126: 0.004099437 | G126: 0.0022616091 | H126: -0.0016486607 | I126: 0.0022616095 | J126: 0.012224557 | K126: 0.007671921 | L126: 0.014925602 | M126: 0.0049686036 | N126: 0.008545422 | O126: 0.83005965 | P126: 0.16994035
A127: ES | B127: 2000 | C127: 3 | D127: -0.0017041913 | E127: 0.0022158513 | F127: 0.0027287528 | G127: 0.00068997365 | H127: 0.0022158511 | I127: 0.00068997405 | J127: 0.010278716 | K127: 0.010474049 | L127: 0.014909364 | M127: -0.0031727941 | N127: 0.0099302474 | O127: 0.8282851 | P127: 0.17171492
A128: ES | B128: 2000 | C128: 4 | D128: -0.00053393363 | E128: -0.00088808849 | F128: -9.1597089e-05 | G128: 0.00019842795 | H128: -0.00088808872 | I128: 0.00019842743 | J128: 0.01442236 | K128: 0.014952271 | L128: 0.014964041 | M128: 0.00035613467 | N128: 0.015339959 | O128: 0.82651055 | P128: 0.17348948
A129: ES | B129: 2001 | C129: 1 | D129: -0.0026498616 | E129: 0.00078840012 | F129: 0.0075819446 | G129: 0.0098689357 | H129: 0.00078839995 | I129: 0.0098689357 | J129: 0.012822523 | K129: 0.01631872 | L129: 0.01388481 | M129: -0.0038330762 | N129: 0.016071241 | O129: 0.81448758 | P129: 0.18551239
... A226: ES | B226: 2025 | C226: 2 | D226: 0.013459692 | E226: 0.018352261 | F226: 0.0016714666 | G226: 0.001334863 | H226: 0.018352263 | I226: 0.0013348577 | J226: 0.0176723 | K226: 0.003737374 | L226: 0.005284647 | M226: -0.004858261 | N226: 0.0035684288 | O226: 0.71503025 | P226: 0.28496975
A227: FR | B227: 1998 | C227: 1 | M227: -0.00095405424
A228: FR | B228: 1998 | C228: 2 | D228: 0.0045829723 | E228: 0.0040207999 | F228: -0.0057730451 | G228: -0.0076444745 | H228: 0.0040207999 | I228: -0.0076444745 | J228: 0.01030423 | K228: 0.0060490901 | L228: 0.004995842 | M228: 0.00045846612 | N228: 0.006290365 | O228: 0.7872051 | P228: 0.21279491
A229: FR | B229: 1998 | C229: 3 | D229: 0.00031558215 | E229: -0.0024693727 | F229: -0.0029452411 | G229: -0.0033146378 | H229: -0.0024693727 | I229: -0.0033146383 | J229: 0.0069047417 | K229: 0.0074089542 | L229: 0.0047854539 | M229: 0.0025204746 | N229: 0.0076486678 | O229: 0.78833067 | P229: 0.21166934
A230: FR | B230: 1998 | C230: 4 | D230: 0.0058342312 | E230: 0.0073811258 | F230: 0.00099958212 | G230: 0.0062073288 | H230: 0.0073811263 | I230: 0.0062073292 | J230: 0.0094223609 | K230: 0.0031701636 | L230: 0.0045025214 | M230: -0.0014094481 | N230: 0.0034082141 | O230: 0.78945625 | P230: 0.21054377
A231: FR | B231: 1999 | C231: 1 | D231: 0.006893822 | E231: 0.0060754926 | F231: 0.0076715485 | G231: 0.010277129 | H231: 0.0060754921 | I231: 0.010277129 | J231: 0.011089297 | K231: 0.0045464309 | L231: 0.0034239669 | M231: 0.00070736941 | N231: 0.0047828527 | O231: 0.78618824 | P231: 0.21381178
A232: FR | B232: 1999 | C232: 2 | D232: 0.00014138249 | E232: 0.0019630548 | F232: -0.0055091456 | G232: -0.0051862826 | H232: 0.0019630548 | I232: -0.0051862826 | J232: 0.009029787 | K232: 0.01113345 | L232: 0.0039199358 | M232: -0.0025091798 | N232: 0.011005859 | O232: 0.78408056 | P232: 0.21591942
A233: FR | B233: 1999 | C233: 3 | D233: 0.01069246 | E233: 0.0069560753 | F233: 0.011141896 | G233: 0.010012727 | H233: 0.0069560762 | I233: 0.010012728 | J233: 0.017765259 | K233: 0.0082083233 | L233: 0.0045647556 | M233: 0.0033750208 | N233: 0.0080812499 | O233: 0.78752691 | P233: 0.21247308
A234: FR | B234: 1999 | C234: 4 | D234: 0.012083913 | E234: 0.010801884 | F234: 0.0046069077 | G234: 0.0012719113 | H234: 0.010801883 | I234: 0.0012719111 | J234: 0.018129339 | K234: 0.0065537472 | L234: 0.0049249083 | M234: 0.0011141784 | N234: 0.0064273085 | O234: 0.79097325 | P234: 0.20902674
A235: FR | B235: 2000 | C235: 1 | D235: 0.008115924 | E235: 0.0097202919 | F235: 0.0070113093 | G235: 0.0059700813 | H235: 0.0097202919 | I235: 0.0059700813 | J235: 0.012899165 | K235: 0.0036755677 | L235: 0.0072061289 | M235: -0.0011893122 | N235: 0.0035496349 | O235: 0.80382228 | P235: 0.19617769
A236: FR | B236: 2000 | C236: 2 | D236: 0.0091951648 | E236: 0.0089204749 | F236: 0.004099437 | G236: 0.0022616091 | H236: 0.0089204758 | I236: 0.0022616095 | J236: 0.014387998 | K236: 0.0042570806 | L236: 0.0072237896 | M236: 0.00066239043 | N236: 0.0042965901 | O236: 0.81526589 | P236: 0.18473408
A237: FR | B237: 2000 | C237: 3 | D237: -0.0010045981 | E237: -0.0040359618 | F237: 0.0027287528 | G237: 0.00068997365 | H237: -0.0040359609 | I237: 0.00068997405 | J237: 0.0084463982 | K237: 0.0096790483 | L237: 0.0089570787 | M237: 0.0029362256 | N237: 0.0097183073 | O237: 0.81590134 | P237: 0.18409865
A238: FR | B238: 2000 | C238: 4 | D238: -0.0023144141 | E238: -0.0020518031 | F238: -9.1597089e-05 | G238: 0.00019842795 | H238: -0.0020518042 | I238: 0.00019842743 | J238: 0.0060051717 | K238: 0.0079637617 | L238: 0.0090886066 | M238: -0.00011315454 | N238: 0.0080026854 | O238: 0.81653678 | P238: 0.18346322
A239: FR | B239: 2001 | C239: 1 | D239: 0.0055105407 | E239: 0.0064767557 | F239: 0.0075819446 | G239: 0.0098689357 | H239: 0.0064767562 | I239: 0.0098689357 | J239: 0.0057141483 | K239: -0.0036576423 | L239: 0.0085504195 | M239: 0.00054241018 | N239: -0.0036189721 | O239: 0.80728924 | P239: 0.19271076
... A336: FR | B336: 2025 | C336: 2 | D336: 0.0034447925 | E336: 0.0022426555 | F336: 0.0016714666 | G336: 0.001334863 | H336: 0.0022426546 | I336: 0.0013348577 | J336: 0.0029144951 | K336: -0.0025260439 | L336: 0.005165739 | M336: 0.0014690284 | N336: -0.0020094106 | O336: 0.77523351 | P336: 0.22476649
A337: IT | B337: 1998 | C337: 1 | M337: -0.00017492227
A338: IT | B338: 1998 | C338: 2 | D338: -0.0042188279 | E338: -0.0051679537 | F338: -0.0057730451 | G338: -0.0076444745 | H338: -0.0051679537 | I338: -0.0076444745 | J338: 0.0048521077 | K338: 0.0088557675 | L338: 0.0094260657 | M338: 0.0010314157 | N338: 0.0089974375 | O338: 0.76700151 | P338: 0.23299846
A339: IT | B339: 1998 | C339: 3 | D339: -0.0056190141 | E339: -0.0077686696 | F339: -0.0029452411 | G339: -0.0033146378 | H339: -0.0077686701 | I339: -0.0033146383 | J339: -0.0017946104 | K339: 0.00045814645 | L339: 0.00934646 | M339: 0.0034421531 | N339: 0.00096452667 | O339: 0.76668692 | P339: 0.23331305
A340: IT | B340: 1998 | C340: 4 | D340: -0.0097674634 | E340: -0.0036487859 | F340: 0.00099958212 | G340: 0.0062073288 | H340: -0.0036487859 | I340: 0.0062073292 | J340: -0.0029769435 | K340: 0.0051742825 | L340: 0.0094256755 | M340: -0.0054956828 | N340: 0.0050456384 | O340: 0.76637232 | P340: 0.23362765
A341: IT | B341: 1999 | C341: 1 | D341: 0.007658442 | E341: 0.014382852 | F341: 0.0076715485 | G341: 0.010277129 | H341: 0.014382852 | I341: 0.010277129 | J341: 0.0039249002 | K341: -0.012000618 | L341: 0.009968821 | M341: -0.0037980627 | N341: -0.012861063 | O341: 0.75690192 | P341: 0.24309805
A342: IT | B342: 1999 | C342: 2 | D342: -0.017123008 | E342: -0.016242817 | F342: -0.0055091456 | G342: -0.0051862826 | H342: -0.016242817 | I342: -0.0051862826 | J342: 0.0011180692 | K342: 0.023840258 | L342: 0.0087936241 | M342: -0.0026835124 | N342: 0.023379577 | O342: 0.74772698 | P342: 0.25227299
A343: IT | B343: 1999 | C343: 3 | D343: 0.011101544 | E343: 0.011252089 | F343: 0.011141896 | G343: 0.010012727 | H343: 0.01125209 | I343: 0.010012728 | J343: 0.012077955 | K343: -0.003725369 | L343: 0.0088819219 | M343: 0.0013742392 | N343: -0.0033508271 | O343: 0.7480033 | P343: 0.25199667
A344: IT | B344: 1999 | C344: 4 | D344: 0.010434015 | E344: 0.0025685641 | F344: 0.0046069077 | G344: 0.0012719113 | H344: 0.0025685639 | I344: 0.0012719111 | J344: 0.018500805 | K344: 0.0075150779 | L344: 0.0089911884 | M344: 0.0080455961 | N344: 0.006974251 | O344: 0.74827963 | P344: 0.25172034
A345: IT | B345: 2000 | C345: 1 | D345: 0.0069097904 | E345: 0.0082071396 | F345: 0.0070113093 | G345: 0.0059700813 | H345: 0.0082071396 | I345: 0.0059700813 | J345: 0.016534904 | K345: 0.0088033807 | L345: 0.010978068 | M345: -0.0010015329 | N345: 0.0079548722 | O345: 0.75816464 | P345: 0.24183537
A346: IT | B346: 2000 | C346: 2 | D346: 0.0019829716 | E346: 0.0011508075 | F346: 0.004099437 | G346: 0.0022616091 | H346: 0.0011508076 | I346: 0.0022616095 | J346: 0.0086171785 | K346: 0.0039300276 | L346: 0.010994283 | M346: 0.0018991324 | N346: 0.0044654366 | O346: 0.76824021 | P346: 0.23175985
A347: IT | B347: 2000 | C347: 3 | D347: 0.004086704 | E347: -0.00099053758 | F347: 0.0027287528 | G347: 0.00068997365 | H347: -0.00099053769 | I347: 0.00068997405 | J347: 0.012586419 | K347: 0.006937895 | L347: 0.010991573 | M347: 0.005702246 | N347: 0.0069775125 | O347: 0.76889759 | P347: 0.23110244
A348: IT | B348: 2000 | C348: 4 | D348: 0.007654937 | E348: 0.012388306 | F348: -9.1597089e-05 | G348: 0.00019842795 | H348: 0.012388306 | I348: 0.00019842743 | J348: 0.012134253 | K348: 0.00098144985 | L348: 0.010001882 | M348: -0.0033142162 | N348: 0.0016922813 | O348: 0.76955497 | P348: 0.23044503
A349: IT | B349: 2001 | C349: 1 | D349: -0.0062792408 | E349: -0.0075530489 | F349: 0.0075819446 | G349: 0.0098689357 | H349: -0.0075530494 | I349: 0.0098689357 | J349: 0.0050322181 | K349: 0.01193027 | L349: 0.01034832 | M349: 0.0010289369 | N349: 0.011755554 | O349: 0.76362085 | P349: 0.23637912
... A446: IT | B446: 2025 | C446: 2 | D446: -0.0047519533 | E446: -0.0059660538 | F446: 0.0016714666 | G446: 0.001334863 | H446: -0.0059660599 | I446: 0.0013348577 | J446: -0.00083194225 | K446: 0.0035123781 | L446: 0.0047403914 | M446: 0.0012965647 | N446: 0.0021635974 | O446: 0.73520762 | P446: 0.26479238
A447: NL | B447: 1998 | C447: 1 | M447: -0.00057048164
A448: NL | B448: 1998 | C448: 2 | D448: 0.0062084449 | E448: 0.0049572797 | F448: -0.0057730451 | G448: -0.0076444745 | H448: 0.0049572797 | I448: -0.0076444745 | J448: 0.0098669231 | K448: 0.0029501275 | L448: 0.0053199469 | M448: 0.0014180454 | N448: 0.0023815036 | O448: 0.771514 | P448: 0.228486
A449: NL | B449: 1998 | C449: 3 | D449: 0.0037441165 | E449: 0.0036997928 | F449: -0.0029452411 | G449: -0.0033146378 | H449: 0.003699793 | I449: -0.0033146383 | J449: 0.010282542 | K449: 0.0065831812 | L449: 0.0064336304 | M449: 3.3418968e-05 | N449: 0.0060272571 | O449: 0.77364635 | P449: 0.22635365
A450: NL | B450: 1998 | C450: 4 | D450: 0.0065996638 | E450: 0.0098796068 | F450: 0.00099958212 | G450: 0.0062073288 | H450: 0.0098796068 | I450: 0.0062073292 | J450: 0.00618674 | K450: -0.0030716453 | L450: 0.005801558 | M450: -0.0026107822 | N450: -0.0036152392 | O450: 0.77577871 | P450: 0.22422129
A451: NL | B451: 1999 | C451: 1 | D451: 0.0089790495 | E451: 0.013156497 | F451: 0.0076715485 | G451: 0.010277129 | H451: 0.013156496 | I451: 0.010277129 | J451: 0.021373576 | K451: 0.014611556 | L451: 0.007152664 | M451: -0.004710211 | N451: 0.014079623 | O451: 0.77419353 | P451: 0.22580644
A452: NL | B452: 1999 | C452: 2 | D452: 0.0057121483 | E452: 0.0020446582 | F452: -0.0055091456 | G452: -0.0051862826 | H452: 0.0020446591 | I452: -0.0051862826 | J452: 0.012705636 | K452: 0.0070676166 | L452: 0.0068154815 | M452: 0.0036506383 | N452: 0.0065469611 | O452: 0.77283072 | P452: 0.22716936
A453: NL | B453: 1999 | C453: 3 | D453: 0.0080256378 | E453: 0.01000915 | F453: 0.011141896 | G453: 0.010012727 | H453: 0.010009151 | I453: 0.010012728 | J453: 0.014587505 | K453: 0.0057674148 | L453: 0.0084815016 | M453: -0.0017986237 | N453: 0.0052574947 | O453: 0.77540755 | P453: 0.22459248
A454: NL | B454: 1999 | C454: 4 | D454: 0.0072405287 | E454: 0.0059928722 | F454: 0.0046069077 | G454: 0.0012719113 | H454: 0.0059928708 | I454: 0.0012719111 | J454: 0.018101892 | K454: 0.011666401 | L454: 0.0089039765 | M454: 0.0010559198 | N454: 0.011166814 | O454: 0.77798438 | P454: 0.22201559
A455: NL | B455: 2000 | C455: 1 | D455: 0.007923061 | E455: 0.0087937284 | F455: 0.0070113093 | G455: 0.0059700813 | H455: 0.0087937303 | I455: 0.0059700813 | J455: 0.009159781 | K455: -0.00095838279 | L455: 0.0066472171 | M455: -0.00030867071 | N455: -0.0014480099 | O455: 0.78527588 | P455: 0.21472412
A456: NL | B456: 2000 | C456: 2 | D456: 0.0024984388 | E456: 0.00026739814 | F456: 0.004099437 | G456: 0.0022616091 | H456: 0.00026739761 | I456: 0.0022616095 | J456: 0.013886071 | K456: 0.012783403 | L456: 0.0079249386 | M456: 0.0018445044 | N456: 0.012303208 | O456: 0.79227304 | P456: 0.20772691
A457: NL | B457: 2000 | C457: 3 | D457: 0.023297215 | E457: 0.025722662 | F457: 0.0027287528 | G457: 0.00068997365 | H457: 0.025722664 | I457: 0.00068997405 | J457: 0.013137198 | K457: -0.017187051 | L457: 0.0071320403 | M457: -0.00040178854 | N457: -0.018231545 | O457: 0.7942614 | P457: 0.20573859
A458: NL | B458: 2000 | C458: 4 | D458: 0.0050095106 | E458: 0.0015410736 | F458: -9.1597089e-05 | G458: 0.00019842795 | H458: 0.0015410706 | I458: 0.00019842743 | J458: 0.010877122 | K458: 0.0053426283 | L458: 0.0071490733 | M458: 0.0036253566 | N458: 0.0057340963 | O458: 0.79624975 | P458: 0.20375027
A459: NL | B459: 2001 | C459: 1 | D459: -0.0030930473 | E459: 0.0046458091 | F459: 0.0075819446 | G459: 0.0098689357 | H459: 0.0046458095 | I459: 0.0098689357 | J459: 0.0057696812 | K459: 0.010231564 | L459: 0.005631133 | M459: -0.0081654536 | N459: 0.0099205496 | O459: 0.79518479 | P459: 0.20481519
... A556: NL | B556: 2025 | C556: 2 | D556: 0.0065853344 | E556: 0.011744343 | F556: 0.0016714666 | G556: 0.001334863 | H556: 0.01174435 | I556: 0.0013348577 | J556: 0.0035245966 | K556: -0.0068684458 | L556: 0.0054577119 | M556: -0.0038156835 | N556: -0.0070263636 | O556: 0.8000688 | P556: 0.19993119

Sheet PopulationByCohort1995
A1: 95 *Y | B1: A025POP@EUDATA | C1: A025PBAA@EUDATA | D1: A025PBAB@EUDATA | E1: A025PBAC@EUDATA | F1: A025PBAD@EUDATA | G1: A025PBAE@EUDATA | H1: A025PBAF@EUDATA | I1: A025PBAG@EUDATA | J1: A025PBAH@EUDATA | K1: A025PBAI@EUDATA | L1: A025PBAJ@EUDATA | M1: A025PBAK@EUDATA | N1: A025PBAL@EUDATA | O1: A025PBAM@EUDATA | P1: A025PBAN@EUDATA | Q1: A025PBAO@EUDATA | R1: A025PBAP@EUDATA | U1: Population over 15
A2: .DESC | B2: Euro Area 20: Population (Persons) | C2: EA20: Population: Less Than 1 Year (Persons) | D2: EA20: Population: 1 Year (Persons) | E2: EA20: Population: 2 Years (Persons) | F2: EA20: Population: 3 Years (Persons) | G2: EA20: Population: 4 Years (Persons) | H2: EA20: Population: 5 Years (Persons) | I2: EA20: Population: 6 Years (Persons) | J2: EA20: Population: 7 Years (Persons) | K2: EA20: Population: 8 Years (Persons) | L2: EA20: Population: 9 Years (Persons) | M2: EA20: Population: 10 Years (Persons) | N2: EA20: Population: 11 Years (Persons) | O2: EA20: Population: 12 Years (Persons) | P2: EA20: Population: 13 Years (Persons) | Q2: EA20: Population: 14 Years (Persons) | R2: EA20: Population: 15 Years (Persons)
A3: .SOURCE | B3: Eurostat | C3: Eurostat | D3: Eurostat | E3: Eurostat | F3: Eurostat | G3: Eurostat | H3: Eurostat | I3: Eurostat | J3: Eurostat | K3: Eurostat | L3: Eurostat | M3: Eurostat | N3: Eurostat | O3: Eurostat | P3: Eurostat | Q3: Eurostat | R3: Eurostat
A4: .LSOURCE | B4: Statistical Office of the European Communities | C4: Statistical Office of the European Communities | D4: Statistical Office of the European Communities | E4: Statistical Office of the European Communities | F4: Statistical Office of the European Communities | G4: Statistical Office of the European Communities | H4: Statistical Office of the European Communities | I4: Statistical Office of the European Communities | J4: Statistical Office of the European Communities | K4: Statistical Office of the European Communities | L4: Statistical Office of the European Communities | M4: Statistical Office of the European Communities | N4: Statistical Office of the European Communities | O4: Statistical Office of the European Communities | P4: Statistical Office of the European Communities | Q4: Statistical Office of the European Communities | R4: Statistical Office of the European Communities
A5: 95 | B5: 319538165 | C5: #N/A | D5: #N/A | E5: #N/A | F5: #N/A | G5: #N/A | H5: #N/A | I5: #N/A | J5: #N/A | K5: #N/A | L5: #N/A | M5: #N/A | N5: #N/A | O5: #N/A | P5: #N/A | Q5: #N/A | R5: #N/A | U5: =B5-SUM(C5:R5) -> #N/A
A6: 96 | B6: 320260443 | C6: #N/A | D6: #N/A | E6: #N/A | F6: #N/A | G6: #N/A | H6: #N/A | I6: #N/A | J6: #N/A | K6: #N/A | L6: #N/A | M6: #N/A | N6: #N/A | O6: #N/A | P6: #N/A | Q6: #N/A | R6: #N/A | U6: =B6-SUM(C6:R6) -> #N/A
A7: 97 | B7: 320981348 | C7: #N/A | D7: #N/A | E7: #N/A | F7: #N/A | G7: #N/A | H7: #N/A | I7: #N/A | J7: #N/A | K7: #N/A | L7: #N/A | M7: #N/A | N7: #N/A | O7: #N/A | P7: #N/A | Q7: #N/A | R7: #N/A | U7: =B7-SUM(C7:R7) -> #N/A
A8: 98 | B8: 323292356 | C8: #N/A | D8: #N/A | E8: #N/A | F8: #N/A | G8: #N/A | H8: #N/A | I8: #N/A | J8: #N/A | K8: #N/A | L8: #N/A | M8: #N/A | N8: #N/A | O8: #N/A | P8: #N/A | Q8: #N/A | R8: #N/A | U8: =B8-SUM(C8:R8) -> #N/A
A9: 99 | B9: 323901384 | C9: #N/A | D9: #N/A | E9: #N/A | F9: #N/A | G9: #N/A | H9: #N/A | I9: #N/A | J9: #N/A | K9: #N/A | L9: #N/A | M9: #N/A | N9: #N/A | O9: #N/A | P9: #N/A | Q9: #N/A | R9: #N/A | U9: =B9-SUM(C9:R9) -> #N/A
A10: 00 | B10: 324872982 | C10: #N/A | D10: #N/A | E10: #N/A | F10: #N/A | G10: #N/A | H10: #N/A | I10: #N/A | J10: #N/A | K10: #N/A | L10: #N/A | M10: #N/A | N10: #N/A | O10: #N/A | P10: #N/A | Q10: #N/A | R10: #N/A | U10: =B10-SUM(C10:R10) -> #N/A
A11: 01 | B11: 325742537 | C11: 3413888 | D11: 3366430 | E11: 3364066 | F11: 3380967 | G11: 3384817 | H11: 3358690 | I11: 3384304 | J11: 3472646 | K11: 3594947 | L11: 3656027 | M11: 3778016 | N11: 3764270 | O11: 3817487 | P11: 3784664 | Q11: 3824478 | R11: 3829622 | U11: =B11-SUM(C11:R11) -> 268567218
A12: 02 | B12: 327130893 | C12: 3366112 | D12: 3428590 | E12: 3387056 | F12: 3383512 | G12: 3395975 | H12: 3405633 | I12: 3377236 | J12: 3403440 | K12: 3490634 | L12: 3620974 | M12: 3694653 | N12: 3812627 | O12: 3801014 | P12: 3856763 | Q12: 3814776 | R12: 3853794 | U12: =B12-SUM(C12:R12) -> 270038104
A13: 03 | B13: 328935204 | C13: 3361202 | D13: 3385451 | E13: 3449548 | F13: 3407448 | G13: 3405109 | H13: 3418411 | I13: 3425506 | J13: 3396402 | K13: 3423013 | L13: 3511090 | M13: 3641673 | N13: 3714033 | O13: 3831606 | P13: 3820922 | Q13: 3878974 | R13: 3835868 | U13: =B13-SUM(C13:R13) -> 272028948
A14: 04 | B14: 330735833 | C14: 3377858 | D14: 3377565 | E14: 3401647 | F14: 3468906 | G14: 3427886 | H14: 3423465 | I14: 3436804 | J14: 3443054 | K14: 3413242 | L14: 3441094 | M14: 3529166 | N14: 3659619 | O14: 3730886 | P14: 3848628 | Q14: 3838717 | R14: 3898245 | U14: =B14-SUM(C14:R14) -> 274019051
A15: 05 | B15: 332621924 | C15: 3409112 | D15: 3392238 | E15: 3389681 | F15: 3418295 | G15: 3488944 | H15: 3442273 | I15: 3438615 | J15: 3452735 | K15: 3457884 | L15: 3429669 | M15: 3457961 | N15: 3545796 | O15: 3676100 | P15: 3746097 | Q15: 3865448 | R15: 3855330 | U15: =B15-SUM(C15:R15) -> 276155746
A16: 06 | B16: 334222207 | C16: 3398900 | D16: 3420491 | E16: 3402230 | F16: 3403380 | G16: 3435395 | H16: 3506572 | I16: 3456523 | J16: 3454137 | K16: 3468967 | L16: 3474905 | M16: 3445863 | N16: 3474370 | O16: 3562932 | P16: 3691298 | Q16: 3761130 | R16: 3880122 | U16: =B16-SUM(C16:R16) -> 277984992
A17: 07 | B17: 335805090 | C17: 3433172 | D17: 3414905 | E17: 3432560 | F17: 3418004 | G17: 3418873 | H17: 3449789 | I17: 3523250 | J17: 3471760 | K17: 3469779 | L17: 3486269 | M17: 3491245 | N17: 3462937 | O17: 3490421 | P17: 3577268 | Q17: 3706407 | R17: 3776260 | U17: =B17-SUM(C17:R17) -> 279782191
A18: 08 | B18: 337757636 | C18: 3447598 | D18: 3453142 | E18: 3430568 | F18: 3448195 | G18: 3435455 | H18: 3434813 | I18: 3465978 | J18: 3541692 | K18: 3490134 | L18: 3487214 | M18: 3506221 | N18: 3509480 | O18: 3481943 | P18: 3508890 | Q18: 3593918 | R18: 3723952 | U18: =B18-SUM(C18:R18) -> 281798443
A19: 09 | B19: 339200057 | C19: 3520750 | D19: 3466097 | E19: 3464265 | F19: 3444548 | G19: 3459711 | H19: 3446990 | I19: 3445469 | J19: 3476861 | K19: 3557114 | L19: 3503229 | M19: 3501469 | N19: 3522427 | O19: 3525201 | P19: 3498240 | Q19: 3524315 | R19: 3611327 | U19: =B19-SUM(C19:R19) -> 283232044
A20: 10 | B20: 340069444 | C20: 3468073 | D20: 3530078 | E20: 3472989 | F20: 3473503 | G20: 3454223 | H20: 3467468 | I20: 3452816 | J20: 3452141 | K20: 3485921 | L20: 3568908 | M20: 3512790 | N20: 3513086 | O20: 3533871 | P20: 3537062 | Q20: 3509510 | R20: 3537970 | U20: =B20-SUM(C20:R20) -> 284099035
A21: 11 | B21: 339446253 | C21: 3461192 | D21: 3471286 | E21: 3529086 | F21: 3476603 | G21: 3478398 | H21: 3454461 | I21: 3468572 | J21: 3454212 | K21: 3454064 | L21: 3490235 | M21: 3577144 | N21: 3516863 | O21: 3519004 | P21: 3540900 | Q21: 3542836 | R21: 3514887 | U21: =B21-SUM(C21:R21) -> 283496510
A22: 12 | B22: 340292438 | C22: 3382317 | D22: 3465547 | E22: 3474674 | F22: 3534409 | G22: 3487790 | H22: 3489309 | I22: 3466263 | J22: 3478744 | K22: 3463698 | L22: 3461922 | M22: 3497412 | N22: 3586675 | O22: 3523476 | P22: 3526965 | Q22: 3549364 | R22: 3551466 | U22: =B22-SUM(C22:R22) -> 284352407
... A33: 23 | B33: 349665601 | C33: 2942003 | D33: 3119702 | E33: 3094681 | F33: 3184016 | G33: 3268080 | H33: 3354385 | I33: 3440264 | J33: 3463832 | K33: 3511388 | L33: 3490089 | M33: 3581411 | N33: 3602930 | O33: 3697237 | P33: 3694707 | Q33: 3750097 | R33: 3695691 | U33: =B33-SUM(C33:R33) -> 294775088

Sheet Population_compillation
A1: Year | B1: Data 1: Age 15 - 64, EA (Thousands) | C1: Data 2: Age 15 - 64, EA (Thousands) | D1: Data 3: Age 65 and over, EA (Thousands) | E1: Data 4: Age 15 - 64, EA (Thousands) | F1: Data 4: Age 65 and over, EA (Thousands) | G1: Data 5: Age 15 and over, EA (Thansands) | I1: Compiled data | J1: Q023LFN@EUDATA
J2: Labor force NAWM
A3: 1982 | B3: 178626 | G3: =IF(ISNUMBER([1]Sheet2!$B4), [1]Sheet2!$B4/1000, "") | I3: =+I4*J3/J4 -> 2.3033299e+08 | J3: 133.835
A4: 1983 | B4: 180629 | G4: =IF(ISNUMBER([1]Sheet2!$B5), [1]Sheet2!$B5/1000, "") | I4: =+I5*J4/J5 -> 2.3109368e+08 | J4: 134.277
A5: 1984 | B5: 182515 | G5: =IF(ISNUMBER([1]Sheet2!$B6), [1]Sheet2!$B6/1000, "") | I5: =+I6*J5/J6 -> 2.3215039e+08 | J5: 134.891
A6: 1985 | B6: 183666 | G6: =IF(ISNUMBER([1]Sheet2!$B7), [1]Sheet2!$B7/1000, "") | I6: =+I7*J6/J7 -> 2.3340674e+08 | J6: 135.621
A7: 1986 | B7: 184436 | G7: =IF(ISNUMBER([1]Sheet2!$B8), [1]Sheet2!$B8/1000, "") | I7: =+I8*J7/J8 -> 2.3600892e+08 | J7: 137.133
A8: 1987 | B8: 185068 | G8: =IF(ISNUMBER([1]Sheet2!$B9), [1]Sheet2!$B9/1000, "") | I8: =+I9*J8/J9 -> 2.3880903e+08 | J8: 138.76
A9: 1988 | B9: 186205 | G9: =IF(ISNUMBER([1]Sheet2!$B10), [1]Sheet2!$B10/1000, "") | I9: =+I10*J9/J10 -> 2.4125976e+08 | J9: 140.184
A10: 1989 | B10: 186818 | G10: =IF(ISNUMBER([1]Sheet2!$B11), [1]Sheet2!$B11/1000, "") | I10: =+I11*J10/J11 -> 2.439239e+08 | J10: 141.732
A11: 1990 | B11: 187742 | G11: =IF(ISNUMBER([1]Sheet2!$B12), [1]Sheet2!$B12/1000, "") | I11: =+I12*J11/J12 -> 2.4808706e+08 | J11: 144.151
A12: 1991 | B12: 199539 | G12: =IF(ISNUMBER([1]Sheet2!$B13), [1]Sheet2!$B13/1000, "") | I12: =+I13*J12/J13 -> 2.5023489e+08 | J12: 145.399
A13: 1992 | B13: 200189 | G13: =IF(ISNUMBER([1]Sheet2!$B14), [1]Sheet2!$B14/1000, "") | I13: =+I14*J13/J14 -> 2.4994232e+08 | J13: 145.229
A14: 1993 | B14: 200577 | G14: =IF(ISNUMBER([1]Sheet2!$B15), [1]Sheet2!$B15/1000, "") | I14: =+I15*J14/J15 -> 2.5058254e+08 | J14: 145.601
... A17: 1996 | B17: 202015 | G17: =IF(ISNUMBER([1]Sheet2!$B18), [1]Sheet2!$B18/1000, "") | I17: =+I18*J17/J18 -> 2.5470094e+08 | J17: 147.994
A18: 1997 | B18: 202453 | C18: 205396 | G18: =IF(ISNUMBER([1]Sheet2!$B19), [1]Sheet2!$B19/1000, "") | I18: =+I19*J18/J19 -> 2.5699334e+08 | J18: 149.326
A19: 1998 | B19: 202985 | C19: 206115 | G19: =IF(ISNUMBER([1]Sheet2!$B20), [1]Sheet2!$B20/1000, "") | I19: =+I20*J19/J20 -> 2.6040269e+08 | J19: 151.307
A20: 1999 | B20: 203377 | C20: 206634 | G20: =IF(ISNUMBER([1]Sheet2!$B21), [1]Sheet2!$B21/1000, "") | I20: =+I21*J20/J21 -> 2.6337145e+08 | J20: 153.032
A21: 2000 | B21: 203841 | C21: 207387 | D21: 49832 | G21: =IF(ISNUMBER([1]Sheet2!$B22), [1]Sheet2!$B22/1000, "") | I21: =+I22*J21/J22 -> 2.6697355e+08 | J21: 155.125
A22: 2001 | B22: 204527 | C22: 208200 | D22: 50783 | G22: =IF(ISNUMBER([1]Sheet2!$B23), [1]Sheet2!$B23/1000, "") | I22: =PopulationByCohort1995!U11 -> 268567218 | J22: 156.051
A23: 2002 | B23: 205332 | C23: 208935 | D23: 51668 | G23: =IF(ISNUMBER([1]Sheet2!$B24), [1]Sheet2!$B24/1000, "") | I23: =PopulationByCohort1995!U12 -> 270038104 | J23: 157.696
A24: 2003 | B24: 206133 | C24: 210193 | D24: 52456 | G24: =IF(ISNUMBER([1]Sheet2!$B25), [1]Sheet2!$B25/1000, "") | I24: =PopulationByCohort1995!U13 -> 272028948 | J24: 159.074
A25: 2004 | B25: 206429 | C25: 210621 | D25: 53893 | G25: =IF(ISNUMBER([1]Sheet2!$B26), [1]Sheet2!$B26/1000, "") | I25: =PopulationByCohort1995!U14 -> 274019051 | J25: 160.643
A26: 2005 | B26: 207934 | C26: 212301 | D26: 54620 | E26: 217020.2 | F26: 55661.1 | G26: =IF(ISNUMBER([1]Sheet2!$B27), [1]Sheet2!$B27/1000, "") | I26: =PopulationByCohort1995!U15 -> 276155746 | J26: 162.035
A27: 2006 | C27: 213278 | D27: 55628 | E27: 217818.2 | F27: 56669.8 | G27: =IF(ISNUMBER([1]Sheet2!$B28), [1]Sheet2!$B28/1000, "") | I27: =PopulationByCohort1995!U16 -> 277984992 | J27: 163.594
A28: 2007 | C28: 214284 | D28: 56466 | E28: 218709 | F28: 57551.4 | G28: =IF(ISNUMBER([1]Sheet2!$B29), [1]Sheet2!$B29/1000, "") | I28: =PopulationByCohort1995!U17 -> 279782191 | J28: 165.169
A29: 2008 | C29: 215183 | D29: 57165 | E29: 219632.6 | F29: 58286.7 | G29: =IF(ISNUMBER([1]Sheet2!$B30), [1]Sheet2!$B30/1000, "") | I29: =PopulationByCohort1995!U18 -> 281798443 | J29: 166.671
A30: 2009 | C30: 215415 | D30: 57901 | E30: 219826.2 | F30: 59037 | G30: =IF(ISNUMBER([1]Sheet2!$B31), [1]Sheet2!$B31/1000, "") | I30: =PopulationByCohort1995!U19 -> 283232044 | J30: 167.233
A31: 2010 | E31: 218615.5 | F31: 59582.9 | G31: =IF(ISNUMBER([1]Sheet2!$B32), [1]Sheet2!$B32/1000, "") | I31: =PopulationByCohort1995!U20 -> 284099035 | J31: 167.349
A32: 2011 | E32: 218347.1 | F32: 60194.5 | G32: =IF(ISNUMBER([1]Sheet2!$B33), [1]Sheet2!$B33/1000, "") -> 282727.76 | I32: =PopulationByCohort1995!U21 -> 283496510 | J32: 167.61
A33: 2012 | E33: 218138.6 | F33: 61313.4 | G33: =IF(ISNUMBER([1]Sheet2!$B34), [1]Sheet2!$B34/1000, "") -> 283473.88 | I33: =PopulationByCohort1995!U22 -> 284352407 | J33: 169.082
A34: 2013 | E34: 217757.1 | F34: 62542.7 | G34: =IF(ISNUMBER([1]Sheet2!$B35), [1]Sheet2!$B35/1000, "") -> 284253.54 | I34: =PopulationByCohort1995!U23 -> 284979194 | J34: 169.231
A35: 2014 | E35: 218535.9 | F35: 64041.7 | G35: =IF(ISNUMBER([1]Sheet2!$B36), [1]Sheet2!$B36/1000, "") -> 285852.81 | I35: =PopulationByCohort1995!U24 -> 285600306 | J35: 169.516
A36: 2015 | E36: 218336.6 | F36: 65350.8 | G36: =IF(ISNUMBER([1]Sheet2!$B37), [1]Sheet2!$B37/1000, "") -> 286708.94 | I36: =PopulationByCohort1995!U25 -> 286374618 | J36: 169.77
A37: 2016 | E37: 218817.8 | F37: 65902.1 | G37: =IF(ISNUMBER([1]Sheet2!$B38), [1]Sheet2!$B38/1000, "") -> 287971.61 | I37: =PopulationByCohort1995!U26 -> 287524182 | J37: 170.477
A38: 2017 | E38: 218527.6 | F38: 66789.8 | G38: =IF(ISNUMBER([1]Sheet2!$B39), [1]Sheet2!$B39/1000, "") -> 288737.27 | I38: =PopulationByCohort1995!U27 -> 288330927 | J38: 171.399
A39: 2018 | E39: 218152 | F39: 67923.2 | G39: =IF(ISNUMBER([1]Sheet2!$B40), [1]Sheet2!$B40/1000, "") -> 289453.17 | I39: =PopulationByCohort1995!U28 -> 289119880
A40: 2019 | E40: 218198.2 | F40: 68639.8 | G40: =IF(ISNUMBER([1]Sheet2!$B41), [1]Sheet2!$B41/1000, "") -> 290372.87 | I40: =PopulationByCohort1995!U29 -> 290177735
A41: 2020 | G41: =IF(ISNUMBER([1]Sheet2!$B42), [1]Sheet2!$B42/1000, "") | I41: =PopulationByCohort1995!U30 -> 291287854
A42: 2021 | I42: =PopulationByCohort1995!U31 -> 291620824
A43: 2022 | I43: =PopulationByCohort1995!U32 -> 292194011
A44: 2023 | I44: =PopulationByCohort1995!U33 -> 294775088
A48: Source: | B48: Data 1: OEDC, Labour Force Statistics, 1985-2005, page 15
B49: Data 2: OECD, Labour Force Statistics, 1989-2009, page 18-19
B50: Data 3: OECD, Labour Force Statistics, 1989-2009, page 22-23
B51: Data 4: Statistical Office of the European Communities / Haver Analytics
B52: Data 5: Statistical Office of the European Communities / Haver Analytics, please see next tab

Sheet Core data
C1: P023SHXF@EUDATA | D1: P023SHXU@EUDATA
A3: 109 | B3: 1997 - Q1 | C3: --- | D3: 75.5
A4: 110 | B4: 1997 - Q2 | C4: 0.22 | D4: 75.68 | E4: =100*LN(D4/D3) -> 0.23812685 | F4: =100*LN(Data_input!AD113/Data_input!AD112) -> 0.31864074
A5: 111 | B5: 1997 - Q3 | C5: 0.28 | D5: 75.92 | E5: =100*LN(D5/D4) -> 0.31662296 | F5: =100*LN(Data_input!AD114/Data_input!AD113) -> 0.34405221
A6: 112 | B6: 1997 - Q4 | C6: 0.3 | D6: 76.16 | E6: =100*LN(D6/D5) -> 0.31562362 | F6: =100*LN(Data_input!AD115/Data_input!AD114) -> 0.35603651
A7: 113 | B7: 1998 - Q1 | C7: 0.35 | D7: 76.42 | E7: =100*LN(D7/D6) -> 0.34080515 | F7: =100*LN(Data_input!AD116/Data_input!AD115) -> 0.34165605
A8: 114 | B8: 1998 - Q2 | C8: 0.44 | D8: 76.76 | E8: =100*LN(D8/D7) -> 0.44392291 | F8: =100*LN(Data_input!AD117/Data_input!AD116) -> 0.37970586
A9: 115 | B9: 1998 - Q3 | C9: 0.32 | D9: 77.01 | E9: =100*LN(D9/D8) -> 0.32516124 | F9: =100*LN(Data_input!AD118/Data_input!AD117) -> 0.3392045
A10: 116 | B10: 1998 - Q4 | C10: 0.29 | D10: 77.22 | E10: =100*LN(D10/D9) -> 0.27232073 | F10: =100*LN(Data_input!AD119/Data_input!AD118) -> 0.26014583
A11: 117 | B11: 1999 - Q1 | C11: 0.16 | D11: 77.35 | E11: =100*LN(D11/D10) -> 0.16820862 | F11: =100*LN(Data_input!AD120/Data_input!AD119) -> 0.24651326
A12: 118 | B12: 1999 - Q2 | C12: 0.29 | D12: 77.56 | E12: =100*LN(D12/D11) -> 0.27112534 | F12: =100*LN(Data_input!AD121/Data_input!AD120) -> 0.23297965
A13: 119 | B13: 1999 - Q3 | C13: 0.27 | D13: 77.76 | E13: =100*LN(D13/D12) -> 0.25753298 | F13: =100*LN(Data_input!AD122/Data_input!AD121) -> 0.25823126
A14: 120 | B14: 1999 - Q4 | C14: 0.26 | D14: 77.99 | E14: =100*LN(D14/D13) -> 0.29534532 | F14: =100*LN(Data_input!AD123/Data_input!AD122) -> 0.20610596
A15: 121 | B15: 2000 - Q1 | C15: 0.18 | D15: 78.14 | E15: =100*LN(D15/D14) -> 0.19214763 | F15: =100*LN(Data_input!AD124/Data_input!AD123) -> 0.26987101
... A96: 202 | B96: 2020 - Q2 | C96: 0.18 | D96: 105.38 | E96: =100*LN(D96/D95) -> 0.30412493 | F96: =100*LN(Data_input!AD205/Data_input!AD204) -> 0.27541686
A97: 3q2020 | D97: 105.31 | E97: =100*LN(D97/D96) -> -0.066448339 | F97: =100*LN(Data_input!AD206/Data_input!AD205) -> -0.12336894
A98: 4q2020 | D98: 105.37 | E98: =100*LN(D98/D97) -> 0.056958422 | F98: =100*LN(Data_input!AD207/Data_input!AD206) -> 0
A99: 1q2021 | D99: 106.15 | E99: =100*LN(D99/D98) -> 0.73752225 | F99: =100*LN(Data_input!AD208/Data_input!AD207) -> 0.9356904
A100: 2q2021 | D100: 106.3 | E100: =100*LN(D100/D99) -> 0.14120972 | F100: =100*LN(Data_input!AD209/Data_input!AD208) -> 0.065829692
A101: 3q2021 | D101: 107.04 | E101: =100*LN(D101/D100) -> 0.6937311 | F101: =100*LN(Data_input!AD210/Data_input!AD209) -> 0.50637768
A102: 4q2021 | D102: 107.94 | E102: =100*LN(D102/D101) -> 0.83729208 | F102: =100*LN(Data_input!AD211/Data_input!AD210) -> 0.91248305
A103: 1q2022 | D103: 109.13 | E103: =100*LN(D103/D102) -> 1.0964315 | F103: =100*LN(Data_input!AD212/Data_input!AD211) -> 1.2709694
A104: 2q2022 | D104: 110.84 | E104: =100*LN(D104/D103) -> 1.5547888 | F104: =100*LN(Data_input!AD213/Data_input!AD212) -> 1.4716835
A105: 3q2022 | D105: 112.9 | E105: =100*LN(D105/D104) -> 1.8414751 | F105: =100*LN(Data_input!AD214/Data_input!AD213) -> 1.7166269
A106: 4q2022 | D106: 115.14 | E106: =100*LN(D106/D105) -> 1.9646308 | F106: =100*LN(Data_input!AD215/Data_input!AD214) -> 1.9401039
A107: 1q2023 | D107: 117.2 | E107: =100*LN(D107/D106) -> 1.7733098 | F107: =100*LN(Data_input!AD216/Data_input!AD215) -> 1.9713977
A108: 2q2023 | D108: 118.61 | E108: =100*LN(D108/D107) -> 1.1958923 | F108: =100*LN(Data_input!AD217/Data_input!AD216) -> #NUM!
... A113: 3q2024 | D113: 122.85 | E113: =100*LN(D113/D112) -> 0.74349785 | F113: =100*LN(Data_input!AD222/Data_input!AD221) -> #DIV/0!

Sheet BBB

Sheet Data_input
E1: Haver | N1: NAWM
C2: Long term inflation expectations | D2: Long term inflation expectations | E2: J025GDPT@EUDATA and NAWM data | F2: J025PCN@EUDATA | G2: sa(D025IFN@EUDATA) | H2: J025GDPP@EUDATA | I2: sa(N025PP2T@EUDATA) | K2: L025CESI@EUDATA | L2: I023M1@EUDATA | M2: Labor Force | N2: Q023YER@EUDATA | O2: Q023PCR@EUDATA | P2: Q023PCD@EUDATA | Q2: Q023ITR@EUDATA | R2: Q023ITD@EUDATA | S2: Q023YED@EUDATA | T2: Q023LFN@EUDATA | U2: Q023WIN@EUDATA | V2: Q023LNN@EUDATA | W2: Q023STN@EUDATA | Z2: sa(Q023HEX@EUDATA) | AA2: Q023LEN@EUDATA*1000 | AE2: Constructed data | AN2: Model data | AY2: r10 | AZ2: NDI | BA2: Consumption of fixed capital | BB2: GDI | BC2: real GDI | BD2: 2 year govt bond yield | BF2: 5 year govt bond yield | BG2: 10 year govt bond yield
C3: https://www.ecb.europa.eu/stats/ecb_surveys/survey_of_professional_forecasters/html/table_hist_hicp.en.html | D3: V025IMPL@EUDATA | E3: y | F3: C_nom | G3: I_nom | H3: GDP_deflator | I3: Population older than 15 | K3: Nominal wage (compensation per employee) | L3: Short term interest rate | M3: Q023LFN@EUDATA | N3: y | O3: C_real | P3: C_deflator | Q3: I_real | R3: I_deflator | S3: GDP_deflator | T3: Labor force | U3: Nominal wage bill | V3: Employment | W3: Shor term interest rate | X3: Compensation per employee | Y3: Comp/emp_defl by GDP defl | Z3: CPI ex energy | AA3: Employment | AB3: C_deflated by GDP defl | AC3: I_deflated by GDP defl | AD3: CPI ex energy and unprocessed food | AE3: Y | AF3: C | AG3: I | AH3: GDP_deflator | AI3: Population | AJ3: Real wage (deflated by GDP deflator) | AK3: Hours | AM3: Core | AN3: dgdi | AO3: dy | AP3: dc | AQ3: dinve | AR3: pinfobs | AS3: pinfobs_core | AT3: robs | AU3: dw | AV3: labobs | AW3: labobs2 | AX3: longinflation | AZ3: sa(D025NDIN@EUDATA) | BA3: sa(D025K1N@EUDATA) | BB3: sa(K025EB6G@EUNA) | BD3: I023BY2@EUDATA | BE3: I023T2Y@EUDATA | BF3: I023BY5@EUDATA | BG3: I023BY10@EUDATA
A4: 1q70 | J4: =+J5*M4/M5 -> 211530.09 | M4: 123.288 | N4: 738.304 | O4: 410.134 | P4: 0.167 | Q4: 191.787 | R4: 0.17 | S4: 0.164 | T4: 123.288 | U4: 59.583 | V4: 121.35 | W4: 7.987 | X4: =U4/V4 -> 0.49100124 | Y4: =X4/S4 -> 2.99391 | AA4: 93033 | AB4: =O4*P4/S4 -> 417.63645 | AC4: =Q4*R4/S4 -> 198.8036 | AE4: =AE5*N4/N5 -> 1099310 | AF4: =AF5*AB4/AB5 -> 6124.4051 | AG4: =AG5*AC4/AC5 -> 3015.7208 | AH4: =AH5*S4/S5 -> 11.162468 | AI4: =+J4 -> 211530.09 | AJ4: =AJ5*Y4/Y5 -> 0.50450782 | AK4: =AK5*AA4/AA5 -> 214935.71 | AT4: =W4/4 -> 1.99675 | AV4: NaN | AW4: NaN | AX4: NaN | AY4: =+BG4/4 -> 1.980725 | BG4: 7.9229
A5: 2q70 | J5: =+J6*M5/M6 -> 211605.58 | M5: 123.332 | N5: 752.496 | O5: 415.238 | P5: 0.169 | Q5: 203.177 | R5: 0.173 | S5: 0.167 | T5: 123.332 | U5: 62.335 | V5: 121.453 | W5: 7.957 | X5: =U5/V5 -> 0.51324381 | Y5: =X5/S5 -> 3.0733162 | AA5: 93367 | AB5: =O5*P5/S5 -> 420.21091 | AC5: =Q5*R5/S5 -> 210.47677 | AE5: =AE6*N5/N6 -> 1120441.4 | AF5: =AF6*AB5/AB6 -> 6162.1581 | AG5: =AG6*AC5/AC6 -> 3192.7953 | AH5: =AH6*S5/S6 -> 11.36666 | AI5: =+J5 -> 211605.58 | AJ5: =AJ6*Y5/Y6 -> 0.51788867 | AK5: =AK6*AA5/AA6 -> 215707.36 | AL5: =100*LN(AE5) -> 1392.9233 | AN5: NaN | AO5: =100*LN(AE5/AI5/(AE4/AI4)) -> 1.8683193 | AP5: =100*LN(AF5/AI5/(AF4/AI4)) -> 0.57886079 | AQ5: =100*LN(AG5/AI5/(AG4/AI4)) -> 5.6701088 | AR5: =100*LN(AH5/AH4) -> 1.8127385 | AS5: NaN | AT5: =W5/4 -> 1.98925 | AU5: =100*LN(AJ5/AJ4) -> 2.6176958 | AV5: NaN | AW5: NaN | AX5: NaN | AY5: =+BG5/4 -> 2.0636 | BG5: 8.2544
A6: 3q70 | J6: =+J7*M6/M7 -> 211988.19 | M6: 123.555 | N6: 761.562 | O6: 420.219 | P6: 0.172 | Q6: 206.268 | R6: 0.175 | S6: 0.17 | T6: 123.555 | U6: 64.841 | V6: 121.61 | W6: 7.602 | X6: =U6/V6 -> 0.53318806 | Y6: =X6/S6 -> 3.1364004 | AA6: 93722 | AB6: =O6*P6/S6 -> 425.16275 | AC6: =Q6*R6/S6 -> 212.33471 | AE6: =AE7*N6/N7 -> 1133940.4 | AF6: =AF7*AB6/AB7 -> 6234.7741 | AG6: =AG7*AC6/AC7 -> 3220.9789 | AH6: =AH7*S6/S7 -> 11.570851 | AI6: =+J6 -> 211988.19 | AJ6: =AJ7*Y6/Y7 -> 0.52851906 | AK6: =AK7*AA6/AA7 -> 216527.52 | AL6: =100*LN(AE6) -> 1394.1209 | AN6: NaN | AO6: =100*LN(AE6/AI6/(AE5/AI5)) -> 1.0169411 | AP6: =100*LN(AF6/AI6/(AF5/AI5)) -> 0.99087964 | AQ6: =100*LN(AG6/AI6/(AG5/AI5)) -> 0.69820336 | AR6: =100*LN(AH6/AH5) -> 1.7804625 | AS6: NaN | AT6: =W6/4 -> 1.9005 | AU6: =100*LN(AJ6/AJ5) -> 2.0318583 | AV6: NaN | AW6: NaN | AX6: NaN | AY6: =+BG6/4 -> 2.0962 | BG6: 8.3848
A7: 4q70 | J7: =+J8*M7/M8 -> 212329.62 | M7: 123.754 | N7: 770.787 | O7: 428.379 | P7: 0.174 | Q7: 205.426 | R7: 0.178 | S7: 0.172 | T7: 123.754 | U7: 67.221 | V7: 121.823 | W7: 7.242 | X7: =U7/V7 -> 0.55179235 | Y7: =X7/S7 -> 3.2080951 | AA7: 94173 | AB7: =O7*P7/S7 -> 433.36015 | AC7: =Q7*R7/S7 -> 212.59202 | AE7: =AE8*N7/N8 -> 1147676.1 | AF7: =AF8*AB7/AB8 -> 6354.9844 | AG7: =AG8*AC7/AC8 -> 3224.8823 | AH7: =AH8*S7/S8 -> 11.706979 | AI7: =+J7 -> 212329.62 | AJ7: =AJ8*Y7/Y8 -> 0.54060044 | AK7: =AK8*AA7/AA8 -> 217569.47 | AL7: =100*LN(AE7) -> 1395.325 | AN7: NaN | AO7: =100*LN(AE7/AI7/(AE6/AI6)) -> 1.043116 | AP7: =100*LN(AF7/AI7/(AF6/AI6)) -> 1.7487773 | AQ7: =100*LN(AG7/AI7/(AG6/AI6)) -> -0.039820886 | AR7: =100*LN(AH7/AH6) -> 1.169604 | AS7: NaN | AT7: =W7/4 -> 1.8105 | AU7: =100*LN(AJ7/AJ6) -> 2.2601571 | AV7: NaN | AW7: NaN | AX7: NaN | AY7: =+BG7/4 -> 2.085225 | BG7: 8.3409
A8: 1q71 | J8: =+J9*M8/M9 -> 212761.99 | M8: 124.006 | N8: 769.439 | O8: 431.329 | P8: 0.177 | Q8: 204.325 | R8: 0.182 | S8: 0.176 | T8: 124.006 | U8: 69.576 | V8: 122.04 | W8: 6.517 | X8: =U8/V8 -> 0.57010816 | Y8: =X8/S8 -> 3.2392509 | AA8: 94638 | AB8: =O8*P8/S8 -> 433.77973 | AC8: =Q8*R8/S8 -> 211.29062 | AE8: =AE9*N8/N9 -> 1145669 | AF8: =AF9*AB8/AB9 -> 6361.1373 | AG8: =AG9*AC8/AC9 -> 3205.1409 | AH8: =AH9*S8/S9 -> 11.979234 | AI8: =+J8 -> 212761.99 | AJ8: =AJ9*Y8/Y9 -> 0.54585055 | AK8: =AK9*AA8/AA9 -> 218643.77 | AL8: =100*LN(AE8) -> 1395.1499 | AN8: NaN | AO8: =100*LN(AE8/AI8/(AE7/AI7)) -> -0.37846203 | AP8: =100*LN(AF8/AI8/(AF7/AI7)) -> -0.106649 | AQ8: =100*LN(AG8/AI8/(AG7/AI7)) -> -0.81746172 | AR8: =100*LN(AH8/AH7) -> 2.2989518 | AS8: NaN | AT8: =W8/4 -> 1.62925 | AU8: =100*LN(AJ8/AJ7) -> 0.96647751 | AV8: NaN | AW8: NaN | AX8: NaN | AY8: =+BG8/4 -> 1.96515 | BG8: 7.8606
A9: 2q71 | J9: =+J10*M9/M10 -> 213376.22 | M9: 124.364 | N9: 779.296 | O9: 437.729 | P9: 0.179 | Q9: 209.725 | R9: 0.185 | S9: 0.178 | T9: 124.364 | U9: 71.109 | V9: 122.299 | W9: 5.939 | X9: =U9/V9 -> 0.58143566 | Y9: =X9/S9 -> 3.2664925 | AA9: 94933 | AB9: =O9*P9/S9 -> 440.18815 | AC9: =Q9*R9/S9 -> 217.97261 | AE9: =AE10*N9/N10 -> 1160345.7 | AF9: =AF10*AB9/AB10 -> 6455.1132 | AG9: =AG10*AC9/AC10 -> 3306.5023 | AH9: =AH10*S9/S10 -> 12.115362 | AI9: =+J9 -> 213376.22 | AJ9: =AJ10*Y9/Y10 -> 0.55044106 | AK9: =AK10*AA9/AA10 -> 219325.31 | AL9: =100*LN(AE9) -> 1396.4229 | AN9: NaN | AO9: =100*LN(AE9/AI9/(AE8/AI8)) -> 0.98464723 | AP9: =100*LN(AF9/AI9/(AF8/AI8)) -> 1.1782578 | AQ9: =100*LN(AG9/AI9/(AG8/AI8)) -> 2.825207 | AR9: =100*LN(AH9/AH8) -> 1.1299555 | AS9: NaN | AT9: =W9/4 -> 1.48475 | AU9: =100*LN(AJ9/AJ8) -> 0.83746693 | AV9: NaN | AW9: NaN | AX9: NaN | AY9: =+BG9/4 -> 1.9827 | BG9: 7.9308
A10: 3q71 | J10: =+J11*M10/M11 -> 212751.7 | M10: 124 | N10: 791.45 | O10: 441.548 | P10: 0.182 | Q10: 210.716 | R10: 0.187 | S10: 0.181 | T10: 124 | U10: 73.512 | V10: 121.939 | W10: 6.226 | X10: =U10/V10 -> 0.60285881 | Y10: =X10/S10 -> 3.3307116 | AA10: 95086 | AB10: =O10*P10/S10 -> 443.98749 | AC10: =Q10*R10/S10 -> 217.70106 | AE10: =AE11*N10/N11 -> 1178442.6 | AF10: =AF11*AB10/AB11 -> 6510.8284 | AG10: =AG11*AC10/AC11 -> 3302.383 | AH10: =AH11*S10/S11 -> 12.319553 | AI10: =+J10 -> 212751.7 | AJ10: =AJ11*Y10/Y11 -> 0.56126272 | AK10: =AK11*AA10/AA11 -> 219678.79 | AL10: =100*LN(AE10) -> 1397.9704 | AN10: NaN | AO10: =100*LN(AE10/AI10/(AE9/AI9)) -> 1.8406942 | AP10: =100*LN(AF10/AI10/(AF9/AI9)) -> 1.1525321 | AQ10: =100*LN(AG10/AI10/(AG9/AI9)) -> 0.16846011 | AR10: =100*LN(AH10/AH9) -> 1.6713481 | AS10: NaN | AT10: =W10/4 -> 1.5565 | AU10: =100*LN(AJ10/AJ9) -> 1.9469213 | AV10: NaN | AW10: NaN | AX10: NaN | AY10: =+BG10/4 -> 2.00675 | BG10: 8.027
A11: 4q71 | J11: =+J12*M11/M12 -> 213022.78 | M11: 124.158 | N11: 797.745 | O11: 446.639 | P11: 0.184 | Q11: 213.343 | R11: 0.19 | S11: 0.183 | T11: 124.158 | U11: 75.554 | V11: 121.935 | W11: 6.006 | X11: =U11/V11 -> 0.61962521 | Y11: =X11/S11 -> 3.3859301 | AA11: 95370 | AB11: =O11*P11/S11 -> 449.07965 | AC11: =Q11*R11/S11 -> 221.50366 | AE11: =AE12*N11/N12 -> 1187815.6 | AF11: =AF12*AB11/AB12 -> 6585.502 | AG11: =AG12*AC11/AC12 -> 3360.066 | AH11: =AH12*S11/S12 -> 12.455681 | AI11: =+J11 -> 213022.78 | AJ11: =AJ12*Y11/Y12 -> 0.57056766 | AK11: =AK12*AA11/AA12 -> 220334.92 | AL11: =100*LN(AE11) -> 1398.7627 | AN11: NaN | AO11: =100*LN(AE11/AI11/(AE10/AI10)) -> 0.66489089 | AP11: =100*LN(AF11/AI11/(AF10/AI10)) -> 1.0130494 | AQ11: =100*LN(AG11/AI11/(AG10/AI10)) -> 1.6042895 | AR11: =100*LN(AH11/AH10) -> 1.0989122 | AS11: NaN | AT11: =W11/4 -> 1.5015 | AU11: =100*LN(AJ11/AJ10) -> 1.6442656 | AV11: NaN | AW11: NaN | AX11: NaN | AY11: =+BG11/4 -> 1.9615 | BG11: 7.846
A12: 1q72 | J12: =+J13*M12/M13 -> 213492.89 | M12: 124.432 | N12: 809.566 | O12: 454.243 | P12: 0.187 | Q12: 215.876 | R12: 0.193 | S12: 0.187 | T12: 124.432 | U12: 78.822 | V12: 122.064 | W12: 5.047 | X12: =U12/V12 -> 0.64574322 | Y12: =X12/S12 -> 3.4531723 | AA12: 95763 | AB12: =O12*P12/S12 -> 454.243 | AC12: =Q12*R12/S12 -> 222.8025 | AE12: =AE13*N12/N13 -> 1205416.7 | AF12: =AF13*AB12/AB13 -> 6661.2197 | AG12: =AG13*AC12/AC13 -> 3379.7686 | AH12: =AH13*S12/S13 -> 12.727936 | AI12: =+J12 -> 213492.89 | AJ12: =AJ13*Y12/Y13 -> 0.58189873 | AK12: =AK13*AA12/AA13 -> 221242.87 | AL12: =100*LN(AE12) -> 1400.2336 | AN12: NaN | AO12: =100*LN(AE12/AI12/(AE11/AI11)) -> 1.250487 | AP12: =100*LN(AF12/AI12/(AF11/AI11)) -> 0.92275964 | AQ12: =100*LN(AG12/AI12/(AG11/AI11)) -> 0.36421884 | AR12: =100*LN(AH12/AH11) -> 2.1622464 | AS12: NaN | AT12: =W12/4 -> 1.26175 | AU12: =100*LN(AJ12/AJ11) -> 1.9664668 | AV12: NaN | AW12: NaN | AX12: NaN | AY12: =+BG12/4 -> 1.8969 | BG12: 7.5876
A13: 2q72 | J13: =+J14*M13/M14 -> 213633.59 | M13: 124.514 | N13: 815.017 | O13: 456.24 | P13: 0.19 | Q13: 218.908 | R13: 0.196 | S13: 0.19 | T13: 124.514 | U13: 80.469 | V13: 122.109 | W13: 4.754 | X13: =U13/V13 -> 0.65899319 | Y13: =X13/S13 -> 3.4683852 | AA13: 96007 | AB13: =O13*P13/S13 -> 456.24 | AC13: =Q13*R13/S13 -> 225.82088 | AE13: =AE14*N13/N14 -> 1213533.1 | AF13: =AF14*AB13/AB14 -> 6690.5046 | AG13: =AG14*AC13/AC14 -> 3425.5554 | AH13: =AH14*S13/S14 -> 12.932128 | AI13: =+J13 -> 213633.59 | AJ13: =AJ14*Y13/Y14 -> 0.58446229 | AK13: =AK14*AA13/AA14 -> 221806.59 | AL13: =100*LN(AE13) -> 1400.9047 | AN13: NaN | AO13: =100*LN(AE13/AI13/(AE12/AI12)) -> 0.60518929 | AP13: =100*LN(AF13/AI13/(AF12/AI12)) -> 0.37279123 | AQ13: =100*LN(AG13/AI13/(AG12/AI12)) -> 1.2797619 | AR13: =100*LN(AH13/AH12) -> 1.5915455 | AS13: NaN | AT13: =W13/4 -> 1.1885 | AU13: =100*LN(AJ13/AJ12) -> 0.43958249 | AV13: NaN | AW13: NaN | AX13: NaN | AY13: =+BG13/4 -> 1.887425 | BG13: 7.5497
A14: 3q72 | J14: =+J15*M14/M15 -> 214136.3 | M14: 124.807 | N14: 826.161 | O14: 464.471 | P14: 0.194 | Q14: 221.9 | R14: 0.198 | S14: 0.193 | T14: 124.807 | U14: 82.652 | V14: 122.336 | W14: 4.857 | X14: =U14/V14 -> 0.6756147 | Y14: =X14/S14 -> 3.5005943 | AA14: 96349 | AB14: =O14*P14/S14 -> 466.87759 | AC14: =Q14*R14/S14 -> 227.6487 | AE14: =AE15*N14/N15 -> 1230126.1 | AF14: =AF15*AB14/AB15 -> 6846.4988 | AG14: =AG15*AC14/AC15 -> 3453.2823 | AH14: =AH15*S14/S15 -> 13.136319 | AI14: =+J14 -> 214136.3 | AJ14: =AJ15*Y14/Y15 -> 0.58988988 | AK14: =AK15*AA14/AA15 -> 222596.72 | AL14: =100*LN(AE14) -> 1402.2627 | AN14: NaN | AO14: =100*LN(AE14/AI14/(AE13/AI13)) -> 1.1230313 | AP14: =100*LN(AF14/AI14/(AF13/AI13)) -> 2.0697722 | AQ14: =100*LN(AG14/AI14/(AG13/AI13)) -> 0.57111497 | AR14: =100*LN(AH14/AH13) -> 1.5666117 | AS14: NaN | AT14: =W14/4 -> 1.21425 | AU14: =100*LN(AJ14/AJ13) -> 0.92436195 | AV14: NaN | AW14: NaN | AX14: NaN | AY14: =+BG14/4 -> 1.8957 | BG14: 7.5828
A15: 4q72 | J15: =+J16*M15/M16 -> 214757.39 | M15: 125.169 | N15: 838.255 | O15: 469.164 | P15: 0.197 | Q15: 227.176 | R15: 0.201 | S15: 0.196 | T15: 125.169 | U15: 85.445 | V15: 122.739 | W15: 6.395 | X15: =U15/V15 -> 0.696152 | Y15: =X15/S15 -> 3.5517959 | AA15: 96954 | AB15: =O15*P15/S15 -> 471.55769 | AC15: =Q15*R15/S15 -> 232.97131 | AE15: =AE16*N15/N16 -> 1248133.7 | AF15: =AF16*AB15/AB16 -> 6915.13 | AG15: =AG16*AC15/AC16 -> 3534.0227 | AH15: =AH16*S15/S16 -> 13.340511 | AI15: =+J15 -> 214757.39 | AJ15: =AJ16*Y15/Y16 -> 0.59851793 | AK15: =AK16*AA15/AA16 -> 223994.46 | AL15: =100*LN(AE15) -> 1403.716 | AN15: NaN | AO15: =100*LN(AE15/AI15/(AE14/AI14)) -> 1.16364 | AP15: =100*LN(AF15/AI15/(AF14/AI14)) -> 0.70780832 | AQ15: =100*LN(AG15/AI15/(AG14/AI14)) -> 2.0215344 | AR15: =100*LN(AH15/AH14) -> 1.542447 | AS15: NaN | AT15: =W15/4 -> 1.59875 | AU15: =100*LN(AJ15/AJ14) -> 1.4520609 | AV15: NaN | AW15: NaN | AX15: NaN | AY15: =+BG15/4 -> 1.953675 | BG15: 7.8147
A16: 1q73 | J16: =+J17*M16/M17 -> 215301.28 | M16: 125.486 | N16: 854.393 | O16: 478.985 | P16: 0.201 | Q16: 231.957 | R16: 0.207 | S16: 0.203 | T16: 125.486 | U16: 90.098 | V16: 123.142 | W16: 6.791 | X16: =U16/V16 -> 0.73165939 | Y16: =X16/S16 -> 3.6042334 | AA16: 97460 | AB16: =O16*P16/S16 -> 474.26594 | AC16: =Q16*R16/S16 -> 236.52758 | AE16: =AE17*N16/N17 -> 1272162.6 | AF16: =AF17*AB16/AB17 -> 6954.8448 | AG16: =AG17*AC16/AC17 -> 3587.969 | AH16: =AH17*S16/S17 -> 13.816957 | AI16: =+J16 -> 215301.28 | AJ16: =AJ17*Y16/Y17 -> 0.60735425 | AK16: =AK17*AA16/AA17 -> 225163.48 | AL16: =100*LN(AE16) -> 1405.6229 | AN16: NaN | AO16: =100*LN(AE16/AI16/(AE15/AI15)) -> 1.6539551 | AP16: =100*LN(AF16/AI16/(AF15/AI15)) -> 0.31973793 | AQ16: =100*LN(AG16/AI16/(AG15/AI15)) -> 1.2620153 | AR16: =100*LN(AH16/AH15) -> 3.509132 | AS16: NaN | AT16: =W16/4 -> 1.69775 | AU16: =100*LN(AJ16/AJ15) -> 1.4655741 | AV16: NaN | AW16: NaN | AX16: NaN | AY16: =+BG16/4 -> 1.993975 | BG16: 7.9759
... A31: 4q76 | J31: =+J32*M31/M32 -> 219419.06 | M31: 127.886 | N31: 951.276 | O31: 538.687 | P31: 0.308 | Q31: 224.284 | R31: 0.33 | S31: 0.306 | T31: 127.886 | U31: 160.645 | V31: 123.131 | W31: 9.206 | X31: =U31/V31 -> 1.3046674 | Y31: =X31/S31 -> 4.2636189 | AA31: 99177 | AB31: =O31*P31/S31 -> 542.20783 | AC31: =Q31*R31/S31 -> 241.8749 | AE31: =AE32*N31/N32 -> 1416418.2 | AF31: =AF32*AB31/AB32 -> 7951.1747 | AG31: =AG32*AC31/AC32 -> 3669.0844 | AH31: =AH32*S31/S32 -> 20.827532 | AI31: =+J31 -> 219419.06 | AJ31: =AJ32*Y31/Y32 -> 0.71846819 | AK31: =AK32*AA31/AA32 -> 229130.3 | AL31: =100*LN(AE31) -> 1416.3642 | AN31: NaN | AO31: =100*LN(AE31/AI31/(AE30/AI30)) -> 1.4783333 | AP31: =100*LN(AF31/AI31/(AF30/AI30)) -> 1.316252 | AQ31: =100*LN(AG31/AI31/(AG30/AI30)) -> 2.7205823 | AR31: =100*LN(AH31/AH30) -> 2.3141529 | AS31: NaN | AT31: =W31/4 -> 2.3015 | AU31: =100*LN(AJ31/AJ30) -> 1.2646933 | AV31: NaN | AW31: NaN | AX31: NaN | AY31: =+BG31/4 -> 2.608875 | BG31: 10.4355
A32: 1q77 | D32: 0 | J32: =+J33*M32/M33 -> 219726.18 | M32: 128.065 | N32: 955.198 | O32: 539.92 | P32: 0.316 | Q32: 226.971 | R32: 0.338 | S32: 0.314 | T32: 128.065 | U32: 165.219 | V32: 123.247 | W32: 10.214 | X32: =U32/V32 -> 1.3405519 | Y32: =X32/S32 -> 4.2692736 | AA32: 99415 | AB32: =O32*P32/S32 -> 543.35898 | AC32: =Q32*R32/S32 -> 244.3191 | AE32: =AE33*N32/N33 -> 1422257.9 | AF32: =AF33*AB32/AB33 -> 7968.0557 | AG32: =AG33*AC32/AC33 -> 3706.1613 | AH32: =AH33*S32/S33 -> 21.372043 | AI32: =+J32 -> 219726.18 | AJ32: =AJ33*Y32/Y33 -> 0.71942106 | AK32: =AK33*AA32/AA33 -> 229680.15 | AL32: =100*LN(AE32) -> 1416.7756 | AN32: NaN | AO32: =100*LN(AE32/AI32/(AE31/AI31)) -> 0.27157021 | AP32: =100*LN(AF32/AI32/(AF31/AI31)) -> 0.072212442 | AQ32: =100*LN(AG32/AI32/(AG31/AI31)) -> 0.86558017 | AR32: =100*LN(AH32/AH31) -> 2.5807884 | AS32: NaN | AT32: =W32/4 -> 2.5535 | AU32: =100*LN(AJ32/AJ31) -> 0.13253785 | AV32: NaN | AW32: NaN | AX32: NaN | AY32: =+BG32/4 -> 2.577725 | BG32: 10.3109
A33: 2q77 | J33: =+J34*M33/M34 -> 220108.79 | M33: 128.288 | N33: 956.485 | O33: 546.948 | P33: 0.324 | Q33: 223.799 | R33: 0.346 | S33: 0.323 | T33: 128.288 | U33: 172.11 | V33: 123.263 | W33: 9.372 | X33: =U33/V33 -> 1.3962827 | Y33: =X33/S33 -> 4.3228568 | AA33: 99367 | AB33: =O33*P33/S33 -> 548.64134 | AC33: =Q33*R33/S33 -> 239.73515 | AE33: =AE34*N33/N34 -> 1424174.2 | AF33: =AF34*AB33/AB34 -> 8045.5185 | AG33: =AG34*AC33/AC34 -> 3636.6258 | AH33: =AH34*S33/S34 -> 21.984617 | AI33: =+J33 -> 220108.79 | AJ33: =AJ34*Y33/Y34 -> 0.72845044 | AK33: =AK34*AA33/AA34 -> 229569.26 | AL33: =100*LN(AE33) -> 1416.9103 | AN33: NaN | AO33: =100*LN(AE33/AI33/(AE32/AI32)) -> -0.039333118 | AP33: =100*LN(AF33/AI33/(AF32/AI32)) -> 0.79349294 | AQ33: =100*LN(AG33/AI33/(AG32/AI32)) -> -2.0680175 | AR33: =100*LN(AH33/AH32) -> 2.8259337 | AS33: NaN | AT33: =W33/4 -> 2.343 | AU33: =100*LN(AJ33/AJ32) -> 1.2472791 | AV33: NaN | AW33: NaN | AX33: NaN | AY33: =+BG33/4 -> 2.555775 | BG33: 10.2231
A34: 3q77 | J34: =+J35*M34/M35 -> 219872.01 | M34: 128.15 | N34: 957.236 | O34: 551.311 | P34: 0.332 | Q34: 224.98 | R34: 0.354 | S34: 0.33 | T34: 128.15 | U34: 176.347 | V34: 122.93 | W34: 8.998 | X34: =U34/V34 -> 1.4345318 | Y34: =X34/S34 -> 4.3470662 | AA34: 99527 | AB34: =O34*P34/S34 -> 554.65228 | AC34: =Q34*R34/S34 -> 241.34218 | AE34: =AE35*N34/N35 -> 1425292.4 | AF34: =AF35*AB34/AB35 -> 8133.6656 | AG34: =AG35*AC34/AC35 -> 3661.0034 | AH34: =AH35*S34/S35 -> 22.461064 | AI34: =+J34 -> 219872.01 | AJ34: =AJ35*Y34/Y35 -> 0.73253 | AK34: =AK35*AA34/AA35 -> 229938.91 | AL34: =100*LN(AE34) -> 1416.9888 | AN34: NaN | AO34: =100*LN(AE34/AI34/(AE33/AI33)) -> 0.18611421 | AP34: =100*LN(AF34/AI34/(AF33/AI33)) -> 1.197275 | AQ34: =100*LN(AG34/AI34/(AG33/AI33)) -> 0.77572723 | AR34: =100*LN(AH34/AH33) -> 2.1440331 | AS34: NaN | AT34: =W34/4 -> 2.2495 | AU34: =100*LN(AJ34/AJ33) -> 0.55847027 | AV34: NaN | AW34: NaN | AX34: NaN | AY34: =+BG34/4 -> 2.521225 | BG34: 10.0849
A35: 4q77 | J35: =+J36*M35/M36 -> 220062.46 | M35: 128.261 | N35: 968.686 | O35: 556.834 | P35: 0.339 | Q35: 227.76 | R35: 0.364 | S35: 0.338 | T35: 128.261 | U35: 181.473 | V35: 123.015 | W35: 9.13 | X35: =U35/V35 -> 1.4752103 | Y35: =X35/S35 -> 4.3645276 | AA35: 99640 | AB35: =O35*P35/S35 -> 558.48144 | AC35: =Q35*R35/S35 -> 245.28 | AE35: =AE36*N35/N36 -> 1442341.1 | AF35: =AF36*AB35/AB36 -> 8189.8181 | AG35: =AG36*AC35/AC36 -> 3720.7375 | AH35: =AH36*S35/S36 -> 23.005574 | AI35: =+J35 -> 220062.46 | AJ35: =AJ36*Y35/Y36 -> 0.73547245 | AK35: =AK36*AA35/AA36 -> 230199.97 | AL35: =100*LN(AE35) -> 1418.1778 | AN35: NaN | AO35: =100*LN(AE35/AI35/(AE34/AI34)) -> 1.1024751 | AP35: =100*LN(AF35/AI35/(AF34/AI34)) -> 0.6014192 | AQ35: =100*LN(AG35/AI35/(AG34/AI34)) -> 1.531885 | AR35: =100*LN(AH35/AH34) -> 2.3953241 | AS35: NaN | AT35: =W35/4 -> 2.2825 | AU35: =100*LN(AJ35/AJ34) -> 0.40087849 | AV35: NaN | AW35: NaN | AX35: NaN | AY35: =+BG35/4 -> 2.495225 | BG35: 9.9809
A36: 1q78 | J36: =+J37*M36/M37 -> 220393.6 | M36: 128.454 | N36: 974.915 | O36: 558.54 | P36: 0.345 | Q36: 228.481 | R36: 0.372 | S36: 0.346 | T36: 128.454 | U36: 187.532 | V36: 123.195 | W36: 8.057 | X36: =U36/V36 -> 1.5222371 | Y36: =X36/S36 -> 4.3995292 | AA36: 99683 | AB36: =O36*P36/S36 -> 556.92572 | AC36: =Q36*R36/S36 -> 245.65009 | AE36: =AE37*N36/N37 -> 1451615.9 | AF36: =AF37*AB36/AB37 -> 8167.0044 | AG36: =AG37*AC36/AC37 -> 3726.3516 | AH36: =AH37*S36/S37 -> 23.550085 | AI36: =+J36 -> 220393.6 | AJ36: =AJ37*Y36/Y37 -> 0.74137061 | AK36: =AK37*AA36/AA37 -> 230299.32 | AL36: =100*LN(AE36) -> 1418.8188 | AN36: NaN | AO36: =100*LN(AE36/AI36/(AE35/AI35)) -> 0.49061605 | AP36: =100*LN(AF36/AI36/(AF35/AI35)) -> -0.42931172 | AQ36: =100*LN(AG36/AI36/(AG35/AI35)) -> 0.0004106745 | AR36: =100*LN(AH36/AH35) -> 2.339288 | AS36: NaN | AT36: =W36/4 -> 2.01425 | AU36: =100*LN(AJ36/AJ35) -> 0.79875689 | AV36: NaN | AW36: NaN | AX36: NaN | AY36: =+BG36/4 -> 2.4292 | BG36: 9.7168
A37: 2q78 | J37: =+J38*M37/M38 -> 220844.84 | M37: 128.717 | N37: 986.039 | O37: 564.664 | P37: 0.352 | Q37: 230.942 | R37: 0.379 | S37: 0.354 | T37: 128.717 | U37: 192.438 | V37: 123.299 | W37: 7.909 | X37: =U37/V37 -> 1.5607426 | Y37: =X37/S37 -> 4.4088774 | AA37: 99815 | AB37: =O37*P37/S37 -> 561.47381 | AC37: =Q37*R37/S37 -> 247.25146 | AE37: =AE38*N37/N38 -> 1468179.1 | AF37: =AF38*AB37/AB38 -> 8233.6995 | AG37: =AG38*AC37/AC38 -> 3750.6433 | AH37: =AH38*S37/S38 -> 24.094596 | AI37: =+J37 -> 220844.84 | AJ37: =AJ38*Y37/Y38 -> 0.74294589 | AK37: =AK38*AA37/AA38 -> 230604.28 | AL37: =100*LN(AE37) -> 1419.9533 | AN37: NaN | AO37: =100*LN(AE37/AI37/(AE36/AI36)) -> 0.93002874 | AP37: =100*LN(AF37/AI37/(AF36/AI36)) -> 0.60879157 | AQ37: =100*LN(AG37/AI37/(AG36/AI36)) -> 0.44524212 | AR37: =100*LN(AH37/AH36) -> 2.2858138 | AS37: NaN | AT37: =W37/4 -> 1.97725 | AU37: =100*LN(AJ37/AJ36) -> 0.21225544 | AV37: NaN | AW37: NaN | AX37: NaN | AY37: =+BG37/4 -> 2.393825 | BG37: 9.5753
A38: 3q78 | J38: =+J39*M38/M39 -> 221375 | M38: 129.026 | N38: 990.657 | O38: 568.885 | P38: 0.36 | Q38: 231.265 | R38: 0.389 | S38: 0.362 | T38: 129.026 | U38: 198.387 | V38: 123.47 | W38: 9.172 | X38: =U38/V38 -> 1.6067628 | Y38: =X38/S38 -> 4.4385712 | AA38: 100068 | AB38: =O38*P38/S38 -> 565.74199 | AC38: =Q38*R38/S38 -> 248.51405 | AE38: =AE39*N38/N39 -> 1475055.2 | AF38: =AF39*AB38/AB39 -> 8296.29 | AG38: =AG39*AC38/AC39 -> 3769.7959 | AH38: =AH39*S38/S39 -> 24.639106 | AI38: =+J38 -> 221375 | AJ38: =AJ39*Y38/Y39 -> 0.74794964 | AK38: =AK39*AA38/AA39 -> 231188.79 | AL38: =100*LN(AE38) -> 1420.4206 | AN38: NaN | AO38: =100*LN(AE38/AI38/(AE37/AI37)) -> 0.22747134 | AP38: =100*LN(AF38/AI38/(AF37/AI37)) -> 0.51752595 | AQ38: =100*LN(AG38/AI38/(AG37/AI37)) -> 0.26957438 | AR38: =100*LN(AH38/AH37) -> 2.2347299 | AS38: NaN | AT38: =W38/4 -> 2.293 | AU38: =100*LN(AJ38/AJ37) -> 0.67124341 | AV38: NaN | AW38: NaN | AX38: NaN | AY38: =+BG38/4 -> 2.394175 | BG38: 9.5767
A39: 4q78 | J39: =+J40*M39/M40 -> 221889.72 | M39: 129.326 | N39: 1002.455 | O39: 575.291 | P39: 0.367 | Q39: 233.341 | R39: 0.4 | S39: 0.369 | T39: 129.326 | U39: 204.23 | V39: 123.682 | W39: 9.137 | X39: =U39/V39 -> 1.6512508 | Y39: =X39/S39 -> 4.4749344 | AA39: 100342 | AB39: =O39*P39/S39 -> 572.17289 | AC39: =Q39*R39/S39 -> 252.94417 | AE39: =AE40*N39/N40 -> 1492622 | AF39: =AF40*AB39/AB40 -> 8390.5956 | AG39: =AG40*AC39/AC40 -> 3836.998 | AH39: =AH40*S39/S40 -> 25.115553 | AI39: =+J39 -> 221889.72 | AJ39: =AJ40*Y39/Y40 -> 0.75407724 | AK39: =AK40*AA39/AA40 -> 231821.82 | AL39: =100*LN(AE39) -> 1421.6045 | AN39: NaN | AO39: =100*LN(AE39/AI39/(AE38/AI38)) -> 0.95164971 | AP39: =100*LN(AF39/AI39/(AF38/AI38)) -> 0.89806655 | AQ39: =100*LN(AG39/AI39/(AG38/AI38)) -> 1.5347021 | AR39: =100*LN(AH39/AH38) -> 1.9152432 | AS39: NaN | AT39: =W39/4 -> 2.28425 | AU39: =100*LN(AJ39/AJ38) -> 0.81591651 | AV39: NaN | AW39: NaN | AX39: NaN | AY39: =+BG39/4 -> 2.4428 | BG39: 9.7712
A40: 1q79 | J40: =+J41*M40/M41 -> 222383.86 | M40: 129.614 | N40: 1007.575 | O40: 579.272 | P40: 0.376 | Q40: 229.918 | R40: 0.409 | S40: 0.377 | T40: 129.614 | U40: 211.115 | V40: 123.966 | W40: 7.697 | X40: =U40/V40 -> 1.7030073 | Y40: =X40/S40 -> 4.5172607 | AA40: 100630 | AB40: =O40*P40/S40 -> 577.73547 | AC40: =Q40*R40/S40 -> 249.43359 | AE40: =AE41*N40/N41 -> 1500245.5 | AF40: =AF41*AB40/AB41 -> 8472.1677 | AG40: =AG41*AC40/AC41 -> 3783.7447 | AH40: =AH41*S40/S41 -> 25.660064 | AI40: =+J40 -> 222383.86 | AJ40: =AJ41*Y40/Y41 -> 0.76120971 | AK40: =AK41*AA40/AA41 -> 232487.19 | AL40: =100*LN(AE40) -> 1422.1139 | AN40: NaN | AO40: =100*LN(AE40/AI40/(AE39/AI39)) -> 0.28700079 | AP40: =100*LN(AF40/AI40/(AF39/AI39)) -> 0.74504405 | AQ40: =100*LN(AG40/AI40/(AG39/AI39)) -> -1.6200568 | AR40: =100*LN(AH40/AH39) -> 2.1448543 | AS40: NaN | AT40: =W40/4 -> 1.92425 | AU40: =100*LN(AJ40/AJ39) -> 0.94140766 | AV40: NaN | AW40: NaN | AX40: NaN | AY40: =+BG40/4 -> 2.432425 | BG40: 9.7297
A41: 2q79 | J41: =+J42*M41/M42 -> 223421.88 | M41: 130.219 | N41: 1023.716 | O41: 590.296 | P41: 0.385 | Q41: 238.969 | R41: 0.42 | S41: 0.386 | T41: 130.219 | U41: 217.139 | V41: 124.367 | W41: 9.35 | X41: =U41/V41 -> 1.7459535 | Y41: =X41/S41 -> 4.5231956 | AA41: 101051 | AB41: =O41*P41/S41 -> 588.76674 | AC41: =Q41*R41/S41 -> 260.01808 | AE41: =AE42*N41/N42 -> 1524278.9 | AF41: =AF42*AB41/AB42 -> 8633.9351 | AG41: =AG42*AC41/AC42 -> 3944.3046 | AH41: =AH42*S41/S42 -> 26.272638 | AI41: =+J41 -> 223421.88 | AJ41: =AJ42*Y41/Y42 -> 0.76220981 | AK41: =AK42*AA41/AA42 -> 233459.83 | AL41: =100*LN(AE41) -> 1423.7032 | AN41: NaN | AO41: =100*LN(AE41/AI41/(AE40/AI40)) -> 1.1235845 | AP41: =100*LN(AF41/AI41/(AF40/AI40)) -> 1.4257126 | AQ41: =100*LN(AG41/AI41/(AG40/AI40)) -> 3.690164 | AR41: =100*LN(AH41/AH40) -> 2.3592182 | AS41: NaN | AT41: =W41/4 -> 2.3375 | AU41: =100*LN(AJ41/AJ40) -> 0.13129734 | AV41: NaN | AW41: NaN | AX41: NaN | AY41: =+BG41/4 -> 2.543975 | BG41: 10.1759
A42: 3q79 | J42: =+J43*M42/M43 -> 224555.98 | M42: 130.88 | N42: 1028.938 | O42: 588.095 | P42: 0.397 | Q42: 240.491 | R42: 0.434 | S42: 0.398 | T42: 130.88 | U42: 226.317 | V42: 124.845 | W42: 11.022 | X42: =U42/V42 -> 1.8127839 | Y42: =X42/S42 -> 4.5547333 | AA42: 101552 | AB42: =O42*P42/S42 -> 586.61737 | AC42: =Q42*R42/S42 -> 262.24395 | AE42: =AE43*N42/N43 -> 1532054.3 | AF42: =AF43*AB42/AB43 -> 8602.4159 | AG42: =AG43*AC42/AC43 -> 3978.0696 | AH42: =AH43*S42/S43 -> 27.089404 | AI42: =+J42 -> 224555.98 | AJ42: =AJ43*Y42/Y43 -> 0.76752427 | AK42: =AK43*AA42/AA43 -> 234617.3 | AL42: =100*LN(AE42) -> 1424.212 | AN42: NaN | AO42: =100*LN(AE42/AI42/(AE41/AI41)) -> 0.0024833577 | AP42: =100*LN(AF42/AI42/(AF41/AI41)) -> -0.87205203 | AQ42: =100*LN(AG42/AI42/(AG41/AI41)) -> 0.3460793 | AR42: =100*LN(AH42/AH41) -> 3.0614636 | AS42: NaN | AT42: =W42/4 -> 2.7555 | AU42: =100*LN(AJ42/AJ41) -> 0.6948238 | AV42: NaN | AW42: NaN | AX42: NaN | AY42: =+BG42/4 -> 2.6499 | BG42: 10.5996
A43: 4q79 | J43: =+J44*M43/M44 -> 224998.64 | M43: 131.138 | N43: 1038.711 | O43: 594.092 | P43: 0.409 | Q43: 244.268 | R43: 0.448 | S43: 0.408 | T43: 131.138 | U43: 234.426 | V43: 125.186 | W43: 12.694 | X43: =U43/V43 -> 1.8726215 | Y43: =X43/S43 -> 4.5897587 | AA43: 101882 | AB43: =O43*P43/S43 -> 595.54811 | AC43: =Q43*R43/S43 -> 268.21584 | AE43: =AE44*N43/N44 -> 1546606 | AF43: =AF44*AB43/AB44 -> 8733.3801 | AG43: =AG44*AC43/AC44 -> 4068.6593 | AH43: =AH44*S43/S44 -> 27.770043 | AI43: =+J43 -> 224998.64 | AJ43: =AJ44*Y43/Y44 -> 0.77342644 | AK43: =AK44*AA43/AA44 -> 235379.7 | AL43: =100*LN(AE43) -> 1425.1573 | AN43: NaN | AO43: =100*LN(AE43/AI43/(AE42/AI42)) -> 0.7483988 | AP43: =100*LN(AF43/AI43/(AF42/AI42)) -> 1.3140065 | AQ43: =100*LN(AG43/AI43/(AG42/AI42)) -> 2.0547515 | AR43: =100*LN(AH43/AH42) -> 2.4815169 | AS43: NaN | AT43: =W43/4 -> 3.1735 | AU43: =100*LN(AJ43/AJ42) -> 0.76604691 | AV43: NaN | AW43: NaN | AX43: NaN | AY43: =+BG43/4 -> 2.7837 | BG43: 11.1348
A44: 1q80 | J44: =+J45*M44/M45 -> 225290.32 | M44: 131.308 | N44: 1048.515 | O44: 599.498 | P44: 0.422 | Q44: 246.865 | R44: 0.467 | S44: 0.42 | T44: 131.308 | U44: 243.129 | V44: 125.29 | W44: 12.735 | X44: =U44/V44 -> 1.94053 | Y44: =X44/S44 -> 4.6203095 | AA44: 102185 | AB44: =O44*P44/S44 -> 602.35275 | AC44: =Q44*R44/S44 -> 274.49037 | AE44: =AE45*N44/N45 -> 1561203.8 | AF44: =AF45*AB44/AB45 -> 8833.1664 | AG44: =AG45*AC44/AC45 -> 4163.8398 | AH44: =AH45*S44/S45 -> 28.586809 | AI44: =+J44 -> 225290.32 | AJ44: =AJ45*Y44/Y45 -> 0.77857459 | AK44: =AK45*AA44/AA45 -> 236079.73 | AL44: =100*LN(AE44) -> 1426.0968 | AN44: NaN | AO44: =100*LN(AE44/AI44/(AE43/AI43)) -> 0.80988513 | AP44: =100*LN(AF44/AI44/(AF43/AI43)) -> 1.0065565 | AQ44: =100*LN(AG44/AI44/(AG43/AI43)) -> 2.1828629 | AR44: =100*LN(AH44/AH43) -> 2.8987537 | AS44: NaN | AT44: =W44/4 -> 3.18375 | AU44: =100*LN(AJ44/AJ43) -> 0.66342378 | AV44: NaN | AW44: NaN | AX44: NaN | AY44: =+BG44/4 -> 3.022725 | BG44: 12.0909
... A63: 4q84 | J63: =+J64*M63/M64 -> 231873.61 | M63: 135.145 | N63: 1102.941 | O63: 618.49 | P63: 0.653 | Q63: 227.77 | R63: 0.694 | S63: 0.635 | T63: 135.145 | U63: 372.037 | V63: 123.401 | W63: 10.128 | X63: =U63/V63 -> 3.0148621 | Y63: =X63/S63 -> 4.7478144 | AA63: 100234 | AB63: =O63*P63/S63 -> 636.022 | AC63: =Q63*R63/S63 -> 248.93288 | AE63: =AE64*N63/N64 -> 1642242.3 | AF63: =AF64*AB63/AB64 -> 9326.9071 | AG63: =AG64*AC63/AC64 -> 3776.1494 | AH63: =AH64*S63/S64 -> 43.220532 | AI63: =+J63 -> 231873.61 | AJ63: =AJ64*Y63/Y64 -> 0.80006062 | AK63: =AK64*AA63/AA64 -> 231572.3 | AL63: =100*LN(AE63) -> 1431.1573 | AN63: NaN | AO63: =100*LN(AE63/AI63/(AE62/AI62)) -> 0.41563574 | AP63: =100*LN(AF63/AI63/(AF62/AI62)) -> 0.51023579 | AQ63: =100*LN(AG63/AI63/(AG62/AI62)) -> 1.2325852 | AR63: =100*LN(AH63/AH62) -> 1.1084832 | AS63: NaN | AT63: =W63/4 -> 2.532 | AU63: =100*LN(AJ63/AJ62) -> 0.68857054 | AV63: NaN | AW63: NaN | AX63: NaN | AY63: =+BG63/4 -> 2.854575 | BG63: 11.4183
A64: 1q85 | B64: 0.15719806 | J64: =+J65*M64/M65 -> 232029.74 | M64: 135.236 | N64: 1105.42 | O64: 623.9 | P64: 0.664 | Q64: 225.155 | R64: 0.702 | S64: 0.645 | T64: 135.236 | U64: 379.617 | V64: 123.433 | W64: 9.863 | X64: =U64/V64 -> 3.0754903 | Y64: =X64/S64 -> 4.7682021 | AA64: 100432 | AB64: =O64*P64/S64 -> 642.27845 | AC64: =Q64*R64/S64 -> 245.05242 | AE64: =AE65*N64/N65 -> 1645933.4 | AF64: =AF65*AB64/AB65 -> 9418.6544 | AG64: =AG65*AC64/AC65 -> 3717.2853 | AH64: =AH65*S64/S65 -> 43.90117 | AI64: =+J64 -> 232029.74 | AJ64: =AJ65*Y64/Y65 -> 0.80349618 | AK64: =Hours_q!D64 -> 232029.74 | AL64: =100*LN(AE64) -> 1431.3818 | AN64: NaN | AO64: =100*LN(AE64/AI64/(AE63/AI63)) -> 0.15719806 | AP64: =100*LN(AF64/AI64/(AF63/AI63)) -> 0.91156536 | AQ64: =100*LN(AG64/AI64/(AG63/AI63)) -> -1.6384293 | AR64: =100*LN(AH64/AH63) -> 1.5625318 | AS64: NaN | AT64: =W64/4 -> 2.46575 | AU64: =100*LN(AJ64/AJ63) -> 0.42849366 | AV64: =Hours_q!H64 -> 4.6422508 | AW64: =AV64-AVERAGE($AV$104:$AV$222) -> 5.5978026 | AX64: NaN | AY64: =+BG64/4 -> 2.73685 | BD64: 8.6455 | BE64: --- | BF64: 10.1085 | BG64: 10.9474
A65: 2q85 | B65: 0.81002553 | J65: =+J66*M65/M66 -> 232354.02 | M65: 135.425 | N65: 1115.968 | O65: 628.069 | P65: 0.672 | Q65: 228.785 | R65: 0.711 | S65: 0.654 | T65: 135.425 | U65: 385.607 | V65: 123.583 | W65: 9.962 | X65: =U65/V65 -> 3.1202269 | Y65: =X65/S65 -> 4.7709891 | AA65: 100587 | AB65: =O65*P65/S65 -> 645.3553 | AC65: =Q65*R65/S65 -> 248.72498 | AE65: =AE66*N65/N66 -> 1661639.1 | AF65: =AF66*AB65/AB66 -> 9463.7748 | AG65: =AG66*AC65/AC66 -> 3772.9956 | AH65: =AH66*S65/S66 -> 44.513745 | AI65: =+J65 -> 232354.02 | AJ65: =AJ66*Y65/Y66 -> 0.80396583 | AK65: =Hours_q!D65 -> 232354.02 | AL65: =100*LN(AE65) -> 1432.3315 | AN65: NaN | AO65: =100*LN(AE65/AI65/(AE64/AI64)) -> 0.81002553 | AP65: =100*LN(AF65/AI65/(AF64/AI64)) -> 0.33825091 | AQ65: =100*LN(AG65/AI65/(AG64/AI64)) -> 1.3479054 | AR65: =100*LN(AH65/AH64) -> 1.3857035 | AS65: NaN | AT65: =W65/4 -> 2.4905 | AU65: =100*LN(AJ65/AJ64) -> 0.058433534 | AV65: =Hours_q!H65 -> 4.5648392 | AW65: =AV65-AVERAGE($AV$104:$AV$222) -> 5.520391 | AX65: NaN | AY65: =+BG65/4 -> 2.711025 | BD65: 8.8778 | BE65: --- | BF65: 10.0727 | BG65: 10.8441
A66: 3q85 | B66: 0.62970295 | J66: =+J67*M66/M67 -> 232849.87 | M66: 135.714 | N66: 1125.414 | O66: 633.925 | P66: 0.68 | Q66: 233.534 | R66: 0.718 | S66: 0.664 | T66: 135.714 | U66: 394.139 | V66: 123.803 | W66: 9.347 | X66: =U66/V66 -> 3.1835981 | Y66: =X66/S66 -> 4.7945755 | AA66: 100866 | AB66: =O66*P66/S66 -> 649.2003 | AC66: =Q66*R66/S66 -> 252.52622 | AE66: =AE67*N66/N67 -> 1675703.8 | AF66: =AF67*AB66/AB67 -> 9520.1595 | AG66: =AG67*AC66/AC67 -> 3830.658 | AH66: =AH67*S66/S67 -> 45.194383 | AI66: =+J66 -> 232849.87 | AJ66: =AJ67*Y66/Y67 -> 0.8079404 | AK66: =Hours_q!D66 -> 232849.87 | AL66: =100*LN(AE66) -> 1433.1744 | AN66: NaN | AO66: =100*LN(AE66/AI66/(AE65/AI65)) -> 0.62970295 | AP66: =100*LN(AF66/AI66/(AF65/AI65)) -> 0.38085288 | AQ66: =100*LN(AG66/AI66/(AG65/AI65)) -> 1.3035571 | AR66: =100*LN(AH66/AH65) -> 1.5174798 | AS66: NaN | AT66: =W66/4 -> 2.33675 | AU66: =100*LN(AJ66/AJ65) -> 0.49315274 | AV66: =Hours_q!H66 -> 4.4226347 | AW66: =AV66-AVERAGE($AV$104:$AV$222) -> 5.3781865 | AX66: NaN | AY66: =+BG66/4 -> 2.66725 | BD66: 8.514 | BE66: --- | BF66: 9.7215 | BG66: 10.669
A67: 4q85 | B67: 0.30455885 | J67: =+J68*M67/M68 -> 233525.87 | M67: 136.108 | N67: 1132.124 | O67: 638.595 | P67: 0.688 | Q67: 236.314 | R67: 0.729 | S67: 0.674 | T67: 136.108 | U67: 401.076 | V67: 124.14 | W67: 8.628 | X67: =U67/V67 -> 3.2308362 | Y67: =X67/S67 -> 4.7935254 | AA67: 101222 | AB67: =O67*P67/S67 -> 651.85958 | AC67: =Q67*R67/S67 -> 255.59778 | AE67: =AE68*N67/N68 -> 1685694.8 | AF67: =AF68*AB67/AB68 -> 9559.1564 | AG67: =AG68*AC67/AC68 -> 3877.2516 | AH67: =AH68*S67/S68 -> 45.875021 | AI67: =+J67 -> 233525.87 | AJ67: =AJ68*Y67/Y68 -> 0.80776346 | AK67: =Hours_q!D67 -> 233525.87 | AL67: =100*LN(AE67) -> 1433.7688 | AN67: NaN | AO67: =100*LN(AE67/AI67/(AE66/AI66)) -> 0.30455885 | AP67: =100*LN(AF67/AI67/(AF66/AI66)) -> 0.11889201 | AQ67: =100*LN(AG67/AI67/(AG66/AI66)) -> 0.91909959 | AR67: =100*LN(AH67/AH66) -> 1.4947961 | AS67: NaN | AT67: =W67/4 -> 2.157 | AU67: =100*LN(AJ67/AJ66) -> -0.021903326 | AV67: =Hours_q!H67 -> 4.2243588 | AW67: =AV67-AVERAGE($AV$104:$AV$222) -> 5.1799106 | AX67: NaN | AY67: =+BG67/4 -> 2.572575 | BD67: 8.1262 | BE67: --- | BF67: 9.5708 | BG67: 10.2903
A68: 1q86 | B68: -0.62857192 | J68: =+J69*M68/M69 -> 234196.72 | M68: 136.499 | N68: 1128.262 | O68: 640.792 | P68: 0.694 | Q68: 234.02 | R68: 0.733 | S68: 0.686 | T68: 136.499 | U68: 407.747 | V68: 124.483 | W68: 8.749 | X68: =U68/V68 -> 3.2755236 | Y68: =X68/S68 -> 4.7748157 | AA68: 101604 | AB68: =O68*P68/S68 -> 648.26479 | AC68: =Q68*R68/S68 -> 250.05344 | AE68: =AE69*N68/N69 -> 1679944.4 | AF68: =AF69*AB68/AB69 -> 9506.4408 | AG68: =AG69*AC68/AC69 -> 3793.1475 | AH68: =AH69*S68/S69 -> 46.691787 | AI68: =+J68 -> 234196.72 | AJ68: =AJ69*Y68/Y69 -> 0.80461065 | AK68: =Hours_q!D68 -> 234196.72 | AL68: =100*LN(AE68) -> 1433.4271 | AN68: NaN | AO68: =100*LN(AE68/AI68/(AE67/AI67)) -> -0.62857192 | AP68: =100*LN(AF68/AI68/(AF67/AI67)) -> -0.83985339 | AQ68: =100*LN(AG68/AI68/(AG67/AI67)) -> -2.4798995 | AR68: =100*LN(AH68/AH67) -> 1.7647517 | AS68: NaN | AT68: =W68/4 -> 2.18725 | AU68: =100*LN(AJ68/AJ67) -> -0.39107677 | AV68: =Hours_q!H68 -> 3.9972594 | AW68: =AV68-AVERAGE($AV$104:$AV$222) -> 4.9528112 | AX68: NaN | AY68: =+BG68/4 -> 2.441575 | BD68: 7.8205 | BE68: --- | BF68: 9.1661 | BG68: 9.7663
A69: 2q86 | B69: 1.5520692 | J69: =+J70*M69/M70 -> 234817.82 | M69: 136.861 | N69: 1148.949 | O69: 652.37 | P69: 0.698 | Q69: 240.215 | R69: 0.74 | S69: 0.695 | T69: 136.861 | U69: 414.936 | V69: 124.768 | W69: 8.028 | X69: =U69/V69 -> 3.3256604 | Y69: =X69/S69 -> 4.7851229 | AA69: 101961 | AB69: =O69*P69/S69 -> 655.18599 | AC69: =Q69*R69/S69 -> 255.76849 | AE69: =AE70*N69/N70 -> 1710746.7 | AF69: =AF70*AB69/AB70 -> 9607.9362 | AG69: =AG70*AC69/AC70 -> 3879.8411 | AH69: =AH70*S69/S70 -> 47.304362 | AI69: =+J69 -> 234817.82 | AJ69: =AJ70*Y69/Y70 -> 0.80634753 | AK69: =Hours_q!D69 -> 234817.82 | AL69: =100*LN(AE69) -> 1435.244 | AN69: NaN | AO69: =100*LN(AE69/AI69/(AE68/AI68)) -> 1.5520692 | AP69: =100*LN(AF69/AI69/(AF68/AI68)) -> 0.79713751 | AQ69: =100*LN(AG69/AI69/(AG68/AI68)) -> 1.9949517 | AR69: =100*LN(AH69/AH68) -> 1.3034218 | AS69: NaN | AT69: =W69/4 -> 2.007 | AU69: =100*LN(AJ69/AJ68) -> 0.21563372 | AV69: =Hours_q!H69 -> 3.8291621 | AW69: =AV69-AVERAGE($AV$104:$AV$222) -> 4.7847139 | AX69: NaN | AY69: =+BG69/4 -> 2.14955 | BD69: 7.0358 | BE69: --- | BF69: 7.8932 | BG69: 8.5982
A70: 3q86 | B70: 0.17993857 | J70: =+J71*M70/M71 -> 235586.47 | M70: 137.309 | N70: 1154.786 | O70: 657.157 | P70: 0.702 | Q70: 243.656 | R70: 0.743 | S70: 0.703 | T70: 137.309 | U70: 421.593 | V70: 125.176 | W70: 7.753 | X70: =U70/V70 -> 3.3680019 | Y70: =X70/S70 -> 4.7908988 | AA70: 102273 | AB70: =O70*P70/S70 -> 656.22221 | AC70: =Q70*R70/S70 -> 257.51978 | AE70: =AE71*N70/N71 -> 1719437.8 | AF70: =AF71*AB70/AB71 -> 9623.1319 | AG70: =AG71*AC70/AC71 -> 3906.4071 | AH70: =AH71*S70/S71 -> 47.848872 | AI70: =+J70 -> 235586.47 | AJ70: =AJ71*Y70/Y71 -> 0.80732083 | AK70: =Hours_q!D70 -> 235586.47 | AL70: =100*LN(AE70) -> 1435.7508 | AN70: NaN | AO70: =100*LN(AE70/AI70/(AE69/AI69)) -> 0.17993857 | AP70: =100*LN(AF70/AI70/(AF69/AI69)) -> -0.1687724 | AQ70: =100*LN(AG70/AI70/(AG69/AI69)) -> 0.35558028 | AR70: =100*LN(AH70/AH69) -> 1.1445046 | AS70: NaN | AT70: =W70/4 -> 1.93825 | AU70: =100*LN(AJ70/AJ69) -> 0.12063218 | AV70: =Hours_q!H70 -> 3.7436437 | AW70: =AV70-AVERAGE($AV$104:$AV$222) -> 4.6991955 | AX70: NaN | AY70: =+BG70/4 -> 2.100925 | BD70: 6.8303 | BE70: --- | BF70: 7.6924 | BG70: 8.4037
A71: 4q86 | B71: -0.15538542 | J71: =+J72*M71/M72 -> 236536.99 | M71: 137.863 | N71: 1157.645 | O71: 662.157 | P71: 0.709 | Q71: 245.817 | R71: 0.75 | S71: 0.709 | T71: 137.863 | U71: 427.344 | V71: 125.637 | W71: 7.875 | X71: =U71/V71 -> 3.4014184 | Y71: =X71/S71 -> 4.7974871 | AA71: 102741 | AB71: =O71*P71/S71 -> 662.157 | AC71: =Q71*R71/S71 -> 260.03209 | AE71: =AE72*N71/N72 -> 1723694.7 | AF71: =AF72*AB71/AB72 -> 9710.1623 | AG71: =AG72*AC71/AC72 -> 3944.5171 | AH71: =AH72*S71/S72 -> 48.257255 | AI71: =+J71 -> 236536.99 | AJ71: =AJ72*Y71/Y72 -> 0.80843104 | AK71: =Hours_q!D71 -> 236536.99 | AL71: =100*LN(AE71) -> 1435.9981 | AN71: NaN | AO71: =100*LN(AE71/AI71/(AE70/AI70)) -> -0.15538542 | AP71: =100*LN(AF71/AI71/(AF70/AI70)) -> 0.49766429 | AQ71: =100*LN(AG71/AI71/(AG70/AI70)) -> 0.56819114 | AR71: =100*LN(AH71/AH70) -> 0.84986347 | AS71: NaN | AT71: =W71/4 -> 1.96875 | AU71: =100*LN(AJ71/AJ70) -> 0.13742315 | AV71: =Hours_q!H71 -> 3.7185511 | AW71: =AV71-AVERAGE($AV$104:$AV$222) -> 4.6741029 | AX71: NaN | AY71: =+BG71/4 -> 2.11825 | BD71: 7.0952 | BE71: --- | BF71: 7.8883 | BG71: 8.473
A72: 1q87 | B72: -0.73311494 | J72: =+J73*M72/M73 -> 237134.07 | M72: 138.211 | N72: 1152.09 | O72: 663.326 | P72: 0.714 | Q72: 241.773 | R72: 0.757 | S72: 0.715 | T72: 138.211 | U72: 432.38 | V72: 125.915 | W72: 8.105 | X72: =U72/V72 -> 3.4339038 | Y72: =X72/S72 -> 4.8026627 | AA72: 102992 | AB72: =O72*P72/S72 -> 662.39827 | AC72: =Q72*R72/S72 -> 255.97505 | AE72: =AE73*N72/N73 -> 1715423.5 | AF72: =AF73*AB72/AB73 -> 9713.7004 | AG72: =AG73*AC72/AC73 -> 3882.9745 | AH72: =AH73*S72/S73 -> 48.665638 | AI72: =+J72 -> 237134.07 | AJ72: =AJ73*Y72/Y73 -> 0.80930318 | AK72: =Hours_q!D72 -> 237134.07 | AL72: =100*LN(AE72) -> 1435.5171 | AN72: NaN | AO72: =100*LN(AE72/AI72/(AE71/AI71)) -> -0.73311494 | AP72: =100*LN(AF72/AI72/(AF71/AI71)) -> -0.21567591 | AQ72: =100*LN(AG72/AI72/(AG71/AI71)) -> -1.8246121 | AR72: =100*LN(AH72/AH71) -> 0.84270162 | AS72: NaN | AT72: =W72/4 -> 2.02625 | AU72: =100*LN(AJ72/AJ71) -> 0.10782261 | AV72: =Hours_q!H72 -> 3.7760895 | AW72: =AV72-AVERAGE($AV$104:$AV$222) -> 4.7316413 | AX72: NaN | AY72: =+BG72/4 -> 2.1178 | BD72: 7.0671 | BE72: --- | BF72: 7.8592 | BG72: 8.4712
A73: 2q87 | B73: 1.3643364 | J73: =+J74*M73/M74 -> 237861.54 | M73: 138.635 | N73: 1171.499 | O73: 674.797 | P73: 0.721 | Q73: 249.819 | R73: 0.763 | S73: 0.721 | T73: 138.635 | U73: 441.426 | V73: 126.258 | W73: 8.426 | X73: =U73/V73 -> 3.496222 | Y73: =X73/S73 -> 4.849129 | AA73: 103322 | AB73: =O73*P73/S73 -> 674.797 | AC73: =Q73*R73/S73 -> 264.37156 | AE73: =AE74*N73/N74 -> 1744322.9 | AF73: =AF74*AB73/AB74 -> 9895.5208 | AG73: =AG74*AC73/AC74 -> 4010.3441 | AH73: =AH74*S73/S74 -> 49.074021 | AI73: =+J73 -> 237861.54 | AJ73: =AJ74*Y73/Y74 -> 0.81713329 | AK73: =Hours_q!D73 -> 237861.54 | AL73: =100*LN(AE73) -> 1437.1877 | AN73: NaN | AO73: =100*LN(AE73/AI73/(AE72/AI72)) -> 1.3643364 | AP73: =100*LN(AF73/AI73/(AF72/AI72)) -> 1.5481834 | AQ73: =100*LN(AG73/AI73/(AG72/AI72)) -> 2.9212492 | AR73: =100*LN(AH73/AH72) -> 0.83565946 | AS73: NaN | AT73: =W73/4 -> 2.1065 | AU73: =100*LN(AJ73/AJ72) -> 0.96286134 | AV73: =Hours_q!H73 -> 3.8044975 | AW73: =AV73-AVERAGE($AV$104:$AV$222) -> 4.7600493 | AX73: NaN | AY73: =+BG73/4 -> 2.17225 | BD73: 7.0875 | BE73: --- | BF73: 7.7825 | BG73: 8.689
A74: 3q87 | B74: 0.82396912 | J74: =+J75*M74/M75 -> 238443.18 | M74: 138.974 | N74: 1184.08 | O74: 680.603 | P74: 0.727 | Q74: 255.611 | R74: 0.768 | S74: 0.726 | T74: 138.974 | U74: 448.462 | V74: 126.612 | W74: 8.49 | X74: =U74/V74 -> 3.5420181 | Y74: =X74/S74 -> 4.8788129 | AA74: 103771 | AB74: =O74*P74/S74 -> 681.54047 | AC74: =Q74*R74/S74 -> 270.39841 | AE74: =AE75*N74/N75 -> 1763055.5 | AF74: =AF75*AB74/AB75 -> 9994.41 | AG74: =AG75*AC74/AC75 -> 4101.7675 | AH74: =AH75*S74/S75 -> 49.41434 | AI74: =+J74 -> 238443.18 | AJ74: =AJ75*Y74/Y75 -> 0.82213535 | AK74: =Hours_q!D74 -> 238443.18 | AL74: =100*LN(AE74) -> 1438.2559 | AN74: NaN | AO74: =100*LN(AE74/AI74/(AE73/AI73)) -> 0.82396912 | AP74: =100*LN(AF74/AI74/(AF73/AI73)) -> 0.75014426 | AQ74: =100*LN(AG74/AI74/(AG73/AI73)) -> 2.0098641 | AR74: =100*LN(AH74/AH73) -> 0.69108775 | AS74: NaN | AT74: =W74/4 -> 2.1225 | AU74: =100*LN(AJ74/AJ73) -> 0.61028185 | AV74: =Hours_q!H74 -> 3.7787833 | AW74: =AV74-AVERAGE($AV$104:$AV$222) -> 4.7343351 | AX74: NaN | AY74: =+BG74/4 -> 2.36805 | BD74: 7.4031 | BE74: --- | BF74: 8.3852 | BG74: 9.4722
A75: 4q87 | B75: 1.09127 | J75: =+J76*M75/M76 -> 238861.82 | M75: 139.218 | N75: 1199.174 | O75: 689.169 | P75: 0.732 | Q75: 259.467 | R75: 0.779 | S75: 0.735 | T75: 139.218 | U75: 456.3 | V75: 126.952 | W75: 8.426 | X75: =U75/V75 -> 3.5942719 | Y75: =X75/S75 -> 4.8901658 | Z75: 75.779 | AA75: 104091 | AB75: =O75*P75/S75 -> 686.35607 | AC75: =Q75*R75/S75 -> 274.99972 | AD75: =$AD$84*Z75/$Z$84 -> 56.422766 | AE75: =AE76*N75/N76 -> 1785530 | AF75: =AF76*AB75/AB76 -> 10065.028 | AG75: =AG76*AC75/AC76 -> 4171.5663 | AH75: =AH76*S75/S76 -> 50.026915 | AI75: =+J75 -> 238861.82 | AJ75: =AJ76*Y75/Y76 -> 0.82404845 | AK75: =Hours_q!D75 -> 238861.82 | AL75: =100*LN(AE75) -> 1439.5226 | AM75: =AD75 -> 56.422766 | AN75: NaN | AO75: =100*LN(AE75/AI75/(AE74/AI74)) -> 1.09127 | AP75: =100*LN(AF75/AI75/(AF74/AI74)) -> 0.52867215 | AQ75: =100*LN(AG75/AI75/(AG74/AI74)) -> 1.5119413 | AR75: =100*LN(AH75/AH74) -> 1.2320484 | AS75: NaN | AT75: =W75/4 -> 2.1065 | AU75: =100*LN(AJ75/AJ74) -> 0.23242822 | AV75: =Hours_q!H75 -> 3.7246201 | AW75: =AV75-AVERAGE($AV$104:$AV$222) -> 4.6801719 | AX75: NaN | AY75: =+BG75/4 -> 2.40335 | BD75: 7.7 | BE75: --- | BF75: 8.5697 | BG75: 9.6134
A76: 1q88 | B76: 0.18494882 | J76: =+J77*M76/M77 -> 239736.85 | M76: 139.728 | N76: 1205.795 | O76: 689.533 | P76: 0.737 | Q76: 263.653 | R76: 0.785 | S76: 0.742 | T76: 139.728 | U76: 464.505 | V76: 127.507 | W76: 7.454 | X76: =U76/V76 -> 3.6429765 | Y76: =X76/S76 -> 4.9096718 | Z76: 76.211 | AA76: 104521 | AB76: =O76*P76/S76 -> 684.88655 | AC76: =Q76*R76/S76 -> 278.93208 | AD76: =$AD$84*Z76/$Z$84 -> 56.74442 | AE76: =AE77*N76/N77 -> 1795388.5 | AF76: =AF77*AB76/AB77 -> 10043.478 | AG76: =AG77*AC76/AC77 -> 4231.2177 | AH76: =AH77*S76/S77 -> 50.503362 | AI76: =+J76 -> 239736.85 | AJ76: =AJ77*Y76/Y77 -> 0.82733543 | AK76: =Hours_q!D76 -> 239736.85 | AL76: =100*LN(AE76) -> 1440.0732 | AM76: =AD76 -> 56.74442 | AN76: NaN | AO76: =100*LN(AE76/AI76/(AE75/AI75)) -> 0.18494882 | AP76: =100*LN(AF76/AI76/(AF75/AI75)) -> -0.57999586 | AQ76: =100*LN(AG76/AI76/(AG75/AI75)) -> 1.054162 | AR76: =100*LN(AH76/AH75) -> 0.9478744 | AS76: =100*LN(AM76/AM75) -> 0.56845998 | AT76: =W76/4 -> 1.8635 | AU76: =100*LN(AJ76/AJ75) -> 0.39808878 | AV76: =Hours_q!H76 -> 3.6267096 | AW76: =AV76-AVERAGE($AV$104:$AV$222) -> 4.5822614 | AX76: NaN | AY76: =+BG76/4 -> 2.246525 | BD76: 6.9444 | BE76: --- | BF76: 8.0252 | BG76: 8.9861
A77: 2q88 | B77: 0.61711803 | J77: =+J78*M77/M78 -> 240452.31 | M77: 140.145 | N77: 1216.88 | O77: 693.347 | P77: 0.746 | Q77: 268.634 | R77: 0.794 | S77: 0.75 | T77: 140.145 | U77: 472.34 | V77: 127.975 | W77: 7.26 | X77: =U77/V77 -> 3.6908771 | Y77: =X77/S77 -> 4.9211695 | Z77: 76.674 | AA77: 105023 | AB77: =O77*P77/S77 -> 689.64915 | AC77: =Q77*R77/S77 -> 284.39386 | AD77: =$AD$84*Z77/$Z$84 -> 57.089156 | AE77: =AE78*N77/N78 -> 1811893.6 | AF77: =AF78*AB77/AB78 -> 10113.319 | AG77: =AG78*AC77/AC78 -> 4314.0693 | AH77: =AH78*S77/S78 -> 51.047872 | AI77: =+J77 -> 240452.31 | AJ77: =AJ78*Y77/Y78 -> 0.82927293 | AK77: =Hours_q!D77 -> 240452.31 | AL77: =100*LN(AE77) -> 1440.9883 | AM77: =AD77 -> 57.089156 | AN77: NaN | AO77: =100*LN(AE77/AI77/(AE76/AI76)) -> 0.61711803 | AP77: =100*LN(AF77/AI77/(AF76/AI76)) -> 0.39498579 | AQ77: =100*LN(AG77/AI77/(AG76/AI76)) -> 1.6411869 | AR77: =100*LN(AH77/AH76) -> 1.0723963 | AS77: =100*LN(AM77/AM76) -> 0.60568586 | AT77: =W77/4 -> 1.815 | AU77: =100*LN(AJ77/AJ76) -> 0.23391121 | AV77: =Hours_q!H77 -> 3.5375518 | AW77: =AV77-AVERAGE($AV$104:$AV$222) -> 4.4931036 | AX77: NaN | AY77: =+BG77/4 -> 2.220725 | BD77: 6.6554 | BE77: --- | BF77: 8.006 | BG77: 8.8829
A78: 3q88 | B78: 1.0769623 | J78: =+J79*M78/M79 -> 240822.91 | M78: 140.361 | N78: 1231.952 | O78: 703.335 | P78: 0.753 | Q78: 273.158 | R78: 0.804 | S78: 0.757 | T78: 140.361 | U78: 480.159 | V78: 128.298 | W78: 7.974 | X78: =U78/V78 -> 3.7425291 | Y78: =X78/S78 -> 4.9438958 | Z78: 77.237 | AA78: 105430 | AB78: =O78*P78/S78 -> 699.61857 | AC78: =Q78*R78/S78 -> 290.11761 | AD78: =$AD$84*Z78/$Z$84 -> 57.508349 | AE78: =AE79*N78/N79 -> 1834335.4 | AF78: =AF79*AB78/AB79 -> 10259.515 | AG78: =AG79*AC78/AC79 -> 4400.8948 | AH78: =AH79*S78/S79 -> 51.524319 | AI78: =+J78 -> 240822.91 | AJ78: =AJ79*Y78/Y79 -> 0.83310256 | AK78: =Hours_q!D78 -> 240822.91 | AL78: =100*LN(AE78) -> 1442.2193 | AM78: =AD78 -> 57.508349 | AN78: NaN | AO78: =100*LN(AE78/AI78/(AE77/AI77)) -> 1.0769623 | AP78: =100*LN(AF78/AI78/(AF77/AI77)) -> 1.2812218 | AQ78: =100*LN(AG78/AI78/(AG77/AI77)) -> 1.8386211 | AR78: =100*LN(AH78/AH77) -> 0.92900469 | AS78: =100*LN(AM78/AM77) -> 0.7315949 | AT78: =W78/4 -> 1.9935 | AU78: =100*LN(AJ78/AJ77) -> 0.46074362 | AV78: =Hours_q!H78 -> 3.4876511 | AW78: =AV78-AVERAGE($AV$104:$AV$222) -> 4.4432029 | AX78: NaN | AY78: =+BG78/4 -> 2.258525 | BD78: 7.2227 | BE78: --- | BF78: 8.2723 | BG78: 9.0341
A79: 4q88 | B79: 0.82092983 | J79: =+J80*M79/M80 -> 241063.11 | M79: 140.501 | N79: 1243.346 | O79: 708.594 | P79: 0.761 | Q79: 278.117 | R79: 0.812 | S79: 0.767 | T79: 140.501 | U79: 488.211 | V79: 128.633 | W79: 8.475 | X79: =U79/V79 -> 3.7953791 | Y79: =X79/S79 -> 4.948343 | Z79: 77.892 | AA79: 105791 | AB79: =O79*P79/S79 -> 703.05089 | AC79: =Q79*R79/S79 -> 294.43416 | AD79: =$AD$84*Z79/$Z$84 -> 57.996043 | AE79: =AE80*N79/N80 -> 1851300.6 | AF79: =AF80*AB79/AB80 -> 10309.848 | AG79: =AG80*AC79/AC80 -> 4466.3741 | AH79: =AH80*S79/S80 -> 52.204957 | AI79: =+J79 -> 241063.11 | AJ79: =AJ80*Y79/Y80 -> 0.83385197 | AK79: =Hours_q!D79 -> 241063.11 | AL79: =100*LN(AE79) -> 1443.1399 | AM79: =AD79 -> 57.996043 | AN79: NaN | AO79: =100*LN(AE79/AI79/(AE78/AI78)) -> 0.82092983 | AP79: =100*LN(AF79/AI79/(AF78/AI78)) -> 0.38970687 | AQ79: =100*LN(AG79/AI79/(AG78/AI78)) -> 1.3772098 | AR79: =100*LN(AH79/AH78) -> 1.3123548 | AS79: =100*LN(AM79/AM78) -> 0.8444635 | AT79: =W79/4 -> 2.11875 | AU79: =100*LN(AJ79/AJ78) -> 0.089913698 | AV79: =Hours_q!H79 -> 3.468786 | AW79: =AV79-AVERAGE($AV$104:$AV$222) -> 4.4243378 | AX79: NaN | AY79: =+BG79/4 -> 2.245175 | BD79: 7.3875 | BE79: --- | BF79: 8.5513 | BG79: 8.9807
A80: 1q89 | B80: 0.83384849 | J80: =+J81*M80/M81 -> 241869.51 | M80: 140.971 | N80: 1257.951 | O80: 715.424 | P80: 0.77 | Q80: 285.296 | R80: 0.821 | S80: 0.776 | T80: 140.971 | U80: 499.605 | V80: 129.202 | W80: 9.516 | X80: =U80/V80 -> 3.8668519 | Y80: =X80/S80 -> 4.9830566 | Z80: 78.562 | AA80: 106464 | AB80: =O80*P80/S80 -> 709.89237 | AC80: =Q80*R80/S80 -> 301.84023 | AD80: =$AD$84*Z80/$Z$84 -> 58.494904 | AE80: =AE81*N80/N81 -> 1873047 | AF80: =AF81*AB80/AB81 -> 10410.175 | AG80: =AG81*AC80/AC81 -> 4578.7193 | AH80: =AH81*S80/S81 -> 52.817532 | AI80: =+J80 -> 241869.51 | AJ80: =AJ81*Y80/Y81 -> 0.8397016 | AK80: =Hours_q!D80 -> 241869.51 | AL80: =100*LN(AE80) -> 1444.3077 | AM80: =AD80 -> 58.494904 | AN80: NaN | AO80: =100*LN(AE80/AI80/(AE79/AI79)) -> 0.83384849 | AP80: =100*LN(AF80/AI80/(AF79/AI79)) -> 0.63444978 | AQ80: =100*LN(AG80/AI80/(AG79/AI79)) -> 2.1502811 | AR80: =100*LN(AH80/AH79) -> 1.1665719 | AS80: =100*LN(AM80/AM79) -> 0.85648701 | AT80: =W80/4 -> 2.379 | AU80: =100*LN(AJ80/AJ79) -> 0.69906954 | AV80: =Hours_q!H80 -> 3.4181157 | AW80: =AV80-AVERAGE($AV$104:$AV$222) -> 4.3736675 | AX80: NaN | AY80: =+BG80/4 -> 2.35105 | BD80: 9.2796 | BE80: --- | BF80: 9.0681 | BG80: 9.4042
A81: 2q89 | B81: 0.66983309 | J81: =+J82*M81/M82 -> 242538.65 | M81: 141.361 | N81: 1269.909 | O81: 719.892 | P81: 0.781 | Q81: 288.125 | R81: 0.831 | S81: 0.783 | T81: 141.361 | U81: 507.413 | V81: 129.727 | W81: 9.691 | X81: =U81/V81 -> 3.9113908 | Y81: =X81/S81 -> 4.9953906 | Z81: 79.323 | AA81: 107032 | AB81: =O81*P81/S81 -> 718.0532 | AC81: =Q81*R81/S81 -> 305.78784 | AD81: =$AD$84*Z81/$Z$84 -> 59.061522 | AE81: =AE82*N81/N82 -> 1890852.1 | AF81: =AF82*AB81/AB82 -> 10529.849 | AG81: =AG82*AC81/AC82 -> 4638.6019 | AH81: =AH82*S81/S82 -> 53.293979 | AI81: =+J81 -> 242538.65 | AJ81: =AJ82*Y81/Y82 -> 0.84178003 | AK81: =Hours_q!D81 -> 242538.65 | AL81: =100*LN(AE81) -> 1445.2538 | AM81: =AD81 -> 59.061522 | AN81: NaN | AO81: =100*LN(AE81/AI81/(AE80/AI80)) -> 0.66983309 | AP81: =100*LN(AF81/AI81/(AF80/AI80)) -> 0.86675794 | AQ81: =100*LN(AG81/AI81/(AG80/AI80)) -> 1.0230979 | AR81: =100*LN(AH81/AH80) -> 0.89801758 | AS81: =100*LN(AM81/AM80) -> 0.96400024 | AT81: =W81/4 -> 2.42275 | AU81: =100*LN(AJ81/AJ80) -> 0.24721344 | AV81: =Hours_q!H81 -> 3.2974393 | AW81: =AV81-AVERAGE($AV$104:$AV$222) -> 4.2529911 | AX81: NaN | AY81: =+BG81/4 -> 2.406775 | BD81: 9.6253 | BE81: --- | BF81: 9.1984 | BG81: 9.6271
A82: 3q89 | B82: 0.21423707 | J82: =+J83*M82/M83 -> 243466.86 | M82: 141.902 | N82: 1277.503 | O82: 728.235 | P82: 0.789 | Q82: 290.149 | R82: 0.836 | S82: 0.791 | T82: 141.902 | U82: 518.179 | V82: 130.421 | W82: 10.102 | X82: =U82/V82 -> 3.9731255 | Y82: =X82/S82 -> 5.0229147 | Z82: 79.962 | AA82: 107797 | AB82: =O82*P82/S82 -> 726.3937 | AC82: =Q82*R82/S82 -> 306.65558 | AD82: =$AD$84*Z82/$Z$84 -> 59.537302 | AE82: =AE83*N82/N83 -> 1902159.3 | AF82: =AF83*AB82/AB83 -> 10652.158 | AG82: =AG83*AC82/AC83 -> 4651.765 | AH82: =AH83*S82/S83 -> 53.838489 | AI82: =+J82 -> 243466.86 | AJ82: =AJ83*Y82/Y83 -> 0.84641814 | AK82: =Hours_q!D82 -> 243466.86 | AL82: =100*LN(AE82) -> 1445.85 | AM82: =AD82 -> 59.537302 | AN82: NaN | AO82: =100*LN(AE82/AI82/(AE81/AI81)) -> 0.21423707 | AP82: =100*LN(AF82/AI82/(AF81/AI81)) -> 0.77287204 | AQ82: =100*LN(AG82/AI82/(AG81/AI81)) -> -0.098605954 | AR82: =100*LN(AH82/AH81) -> 1.0165272 | AS82: =100*LN(AM82/AM81) -> 0.80233974 | AT82: =W82/4 -> 2.5255 | AU82: =100*LN(AJ82/AJ81) -> 0.54947659 | AV82: =Hours_q!H82 -> 3.0519776 | AW82: =AV82-AVERAGE($AV$104:$AV$222) -> 4.0075294 | AX82: NaN | AY82: =+BG82/4 -> 2.4012 | BD82: 9.65 | BE82: --- | BF82: 9.5536 | BG82: 9.6048
A83: 4q89 | B83: 0.48006116 | J83: =+J84*M83/M84 -> 244825.73 | M83: 142.694 | N83: 1290.815 | O83: 735.784 | P83: 0.797 | Q83: 296.973 | R83: 0.847 | S83: 0.802 | T83: 142.694 | U83: 529.862 | V83: 131.297 | W83: 11.072 | X83: =U83/V83 -> 4.0355987 | Y83: =X83/S83 -> 5.0319186 | Z83: 80.725 | AA83: 108586 | AB83: =O83*P83/S83 -> 731.19682 | AC83: =Q83*R83/S83 -> 313.63607 | AD83: =$AD$84*Z83/$Z$84 -> 60.105409 | AE83: =AE84*N83/N84 -> 1921980.4 | AF83: =AF84*AB83/AB84 -> 10722.593 | AG83: =AG84*AC83/AC84 -> 4757.6546 | AH83: =AH84*S83/S84 -> 54.587191 | AI83: =+J83 -> 244825.73 | AJ83: =AJ84*Y83/Y84 -> 0.8479354 | AK83: =Hours_q!D83 -> 244825.73 | AL83: =100*LN(AE83) -> 1446.8867 | AM83: =AD83 -> 60.105409 | AN83: NaN | AO83: =100*LN(AE83/AI83/(AE82/AI82)) -> 0.48006116 | AP83: =100*LN(AF83/AI83/(AF82/AI82)) -> 0.10247181 | AQ83: =100*LN(AG83/AI83/(AG82/AI82)) -> 1.6942284 | AR83: =100*LN(AH83/AH82) -> 1.381064 | AS83: =100*LN(AM83/AM82) -> 0.94967948 | AT83: =W83/4 -> 2.768 | AU83: =100*LN(AJ83/AJ82) -> 0.17909596 | AV83: =Hours_q!H83 -> 2.7064765 | AW83: =AV83-AVERAGE($AV$104:$AV$222) -> 3.6620283 | AX83: NaN | AY83: =+BG83/4 -> 2.521675 | BD83: 10.4342 | BE83: --- | BF83: 10.1805 | BG83: 10.0867
A84: 1q90 | B84: 0.86842259 | J84: =+J85*M84/M85 -> 245999.29 | M84: 143.378 | N84: 1308.315 | O84: 741.799 | P84: 0.805 | Q84: 305.774 | R84: 0.859 | S84: 0.813 | T84: 143.378 | U84: 545.546 | V84: 132.12 | W84: 11.226 | X84: =U84/V84 -> 4.1291705 | Y84: =X84/S84 -> 5.0789304 | Z84: 81.537 | AA84: 109432 | AB84: =O84*P84/S84 -> 734.49962 | AC84: =Q84*R84/S84 -> 323.07487 | AD84: 60.71 | AE84: =AE85*N84/N85 -> 1948037.3 | AF84: =AF85*AB84/AB85 -> 10771.026 | AG84: =AG85*AC84/AC85 -> 4900.8349 | AH84: =AH85*S84/S85 -> 55.335894 | AI84: =+J84 -> 245999.29 | AJ84: =AJ85*Y84/Y85 -> 0.85585744 | AK84: =Hours_q!D84 -> 245999.29 | AL84: =100*LN(AE84) -> 1448.2333 | AM84: =AD84 -> 60.71 | AN84: NaN | AO84: =100*LN(AE84/AI84/(AE83/AI83)) -> 0.86842259 | AP84: =100*LN(AF84/AI84/(AF83/AI83)) -> -0.02752055 | AQ84: =100*LN(AG84/AI84/(AG83/AI83)) -> 2.4868745 | AR84: =100*LN(AH84/AH83) -> 1.3622502 | AS84: =100*LN(AM84/AM83) -> 1.0008588 | AT84: =W84/4 -> 2.8065 | AU84: =100*LN(AJ84/AJ83) -> 0.92993631 | AV84: =Hours_q!H84 -> 2.3000759 | AW84: =AV84-AVERAGE($AV$104:$AV$222) -> 3.2556277 | AX84: NaN | AY84: =+BG84/4 -> 2.702125 | BD84: 11.0634 | BE84: --- | BF84: 10.8969 | BG84: 10.8085
A85: 2q90 | B85: 0.10683769 | J85: =+J86*M85/M86 -> 246858.88 | M85: 143.879 | N85: 1314.29 | O85: 746.56 | P85: 0.814 | Q85: 304.029 | R85: 0.871 | S85: 0.825 | T85: 143.879 | U85: 559.037 | V85: 132.699 | W85: 10.618 | X85: =U85/V85 -> 4.21282 | Y85: =X85/S85 -> 5.1064485 | Z85: 82.277 | AA85: 110073 | AB85: =O85*P85/S85 -> 736.60587 | AC85: =Q85*R85/S85 -> 320.98092 | AD85: 61.23 | AE85: =AE86*N85/N86 -> 1956933.9 | AF85: =AF86*AB85/AB86 -> 10801.913 | AG85: =AG86*AC85/AC86 -> 4869.0711 | AH85: =AH86*S85/S86 -> 56.15266 | AI85: =+J85 -> 246858.88 | AJ85: =AJ86*Y85/Y86 -> 0.86049454 | AK85: =Hours_q!D85 -> 246858.88 | AL85: =100*LN(AE85) -> 1448.6889 | AM85: =AD85 -> 61.23 | AN85: NaN | AO85: =100*LN(AE85/AI85/(AE84/AI84)) -> 0.10683769 | AP85: =100*LN(AF85/AI85/(AF84/AI84)) -> -0.062468554 | AQ85: =100*LN(AG85/AI85/(AG84/AI84)) -> -0.99905665 | AR85: =100*LN(AH85/AH84) -> 1.4652277 | AS85: =100*LN(AM85/AM84) -> 0.85288363 | AT85: =W85/4 -> 2.6545 | AU85: =100*LN(AJ85/AJ84) -> 0.54034508 | AV85: =Hours_q!H85 -> 2.0294092 | AW85: =AV85-AVERAGE($AV$104:$AV$222) -> 2.9849611 | AX85: NaN | AY85: =+BG85/4 -> 2.69805 | BD85: 10.7941 | BE85: --- | BF85: 10.8732 | BG85: 10.7922
A86: 3q90 | B86: 0.59147379 | J86: =+J87*M86/M87 -> 247679 | M86: 144.357 | N86: 1326.479 | O86: 749.055 | P86: 0.824 | Q86: 305.079 | R86: 0.878 | S86: 0.832 | T86: 144.357 | U86: 569.059 | V86: 133.225 | W86: 10.536 | X86: =U86/V86 -> 4.271413 | Y86: =X86/S86 -> 5.1339099 | Z86: 82.942 | AA86: 110566 | AB86: =O86*P86/S86 -> 741.85255 | AC86: =Q86*R86/S86 -> 321.94635 | AD86: 61.58 | AE86: =AE87*N86/N87 -> 1975082.9 | AF86: =AF87*AB86/AB87 -> 10878.853 | AG86: =AG87*AC86/AC87 -> 4883.716 | AH86: =AH87*S86/S87 -> 56.629106 | AI86: =+J86 -> 247679 | AJ86: =AJ87*Y86/Y87 -> 0.8651221 | AK86: =Hours_q!D86 -> 247679 | AL86: =100*LN(AE86) -> 1449.6121 | AM86: =AD86 -> 61.58 | AN86: NaN | AO86: =100*LN(AE86/AI86/(AE85/AI85)) -> 0.59147379 | AP86: =100*LN(AF86/AI86/(AF85/AI85)) -> 0.3780803 | AQ86: =100*LN(AG86/AI86/(AG85/AI85)) -> -0.031349945 | AR86: =100*LN(AH86/AH85) -> 0.84490545 | AS86: =100*LN(AM86/AM85) -> 0.5699877 | AT86: =W86/4 -> 2.634 | AU86: =100*LN(AJ86/AJ85) -> 0.53633817 | AV86: =Hours_q!H86 -> 1.9311947 | AW86: =AV86-AVERAGE($AV$104:$AV$222) -> 2.8867466 | AX86: NaN | AY86: =+BG86/4 -> 2.72165 | BD86: 10.8109 | BE86: --- | BF86: 10.9077 | BG86: 10.8866
A87: 4q90 | B87: 0.12741604 | J87: =+J88*M87/M88 -> 248763.35 | M87: 144.989 | N87: 1333.985 | O87: 755.659 | P87: 0.836 | Q87: 307.378 | R87: 0.887 | S87: 0.842 | T87: 144.989 | U87: 582.255 | V87: 133.827 | W87: 11.046 | X87: =U87/V87 -> 4.3508036 | Y87: =X87/S87 -> 5.1672252 | Z87: 83.802 | AA87: 111255 | AB87: =O87*P87/S87 -> 750.27426 | AC87: =Q87*R87/S87 -> 323.80557 | AD87: 62.28 | AE87: =AE88*N87/N88 -> 1986259.1 | AF87: =AF88*AB87/AB88 -> 11002.353 | AG87: =AG88*AC87/AC88 -> 4911.9191 | AH87: =AH88*S87/S88 -> 57.309745 | AI87: =+J87 -> 248763.35 | AJ87: =AJ88*Y87/Y88 -> 0.87073611 | AK87: =Hours_q!D87 -> 248763.35 | AL87: =100*LN(AE87) -> 1450.1764 | AM87: =AD87 -> 62.28 | AN87: NaN | AO87: =100*LN(AE87/AI87/(AE86/AI86)) -> 0.12741604 | AP87: =100*LN(AF87/AI87/(AF86/AI86)) -> 0.69198346 | AQ87: =100*LN(AG87/AI87/(AG86/AI86)) -> 0.13898371 | AR87: =100*LN(AH87/AH86) -> 1.1947573 | AS87: =100*LN(AM87/AM86) -> 1.1303204 | AT87: =W87/4 -> 2.7615 | AU87: =100*LN(AJ87/AJ86) -> 0.64683104 | AV87: =Hours_q!H87 -> 1.9647882 | AW87: =AV87-AVERAGE($AV$104:$AV$222) -> 2.92034 | AX87: NaN | AY87: =+BG87/4 -> 2.744425 | BD87: 10.909 | BE87: --- | BF87: 10.979 | BG87: 10.9777
A88: 1q91 | B88: 0.29291267 | J88: =+J89*M88/M89 -> 249749.9 | M88: 145.564 | N88: 1343.204 | O88: 763.96 | P88: 0.844 | Q88: 307.383 | R88: 0.895 | S88: 0.854 | T88: 145.564 | U88: 591.078 | V88: 134.372 | W88: 11.097 | X88: =U88/V88 -> 4.3988182 | Y88: =X88/S88 -> 5.150841 | Z88: 84.639 | AA88: 111853 | AB88: =O88*P88/S88 -> 755.01433 | AC88: =Q88*R88/S88 -> 322.14026 | AD88: 62.89 | AE88: =AE89*N88/N89 -> 1999985.9 | AF88: =AF89*AB88/AB89 -> 11071.863 | AG88: =AG89*AC88/AC89 -> 4886.6576 | AH88: =AH89*S88/S89 -> 58.126511 | AI88: =+J88 -> 249749.9 | AJ88: =AJ89*Y88/Y89 -> 0.86797518 | AK88: =Hours_q!D88 -> 249749.9 | AL88: =100*LN(AE88) -> 1450.8651 | AM88: =AD88 -> 62.89 | AN88: NaN | AO88: =100*LN(AE88/AI88/(AE87/AI87)) -> 0.29291267 | AP88: =100*LN(AF88/AI88/(AF87/AI87)) -> 0.23399425 | AQ88: =100*LN(AG88/AI88/(AG87/AI87)) -> -0.91141521 | AR88: =100*LN(AH88/AH87) -> 1.415118 | AS88: =100*LN(AM88/AM87) -> 0.97468216 | AT88: =W88/4 -> 2.77425 | AU88: =100*LN(AJ88/AJ87) -> -0.31758393 | AV88: =Hours_q!H88 -> 2.1142192 | AW88: =AV88-AVERAGE($AV$104:$AV$222) -> 3.069771 | AX88: NaN | AY88: =+BG88/4 -> 2.638225 | BD88: 10.6605 | BE88: --- | BF88: 10.6197 | BG88: 10.5529
A89: 2q91 | B89: 0.3165351 | J89: =+J90*M89/M90 -> 249700.14 | M89: 145.535 | N89: 1347.194 | O89: 770.513 | P89: 0.855 | Q89: 308.066 | R89: 0.909 | S89: 0.866 | T89: 145.535 | U89: 606.121 | V89: 134.255 | W89: 10.462 | X89: =U89/V89 -> 4.5146996 | Y89: =X89/S89 -> 5.213279 | Z89: 85.571 | AA89: 111684 | AB89: =O89*P89/S89 -> 760.72588 | AC89: =Q89*R89/S89 -> 323.36258 | AD89: 63.55 | AE89: =AE90*N89/N90 -> 2005926.8 | AF89: =AF90*AB89/AB90 -> 11155.62 | AG89: =AG90*AC89/AC90 -> 4905.1993 | AH89: =AH90*S89/S90 -> 58.943277 | AI89: =+J89 -> 249700.14 | AJ89: =AJ90*Y89/Y90 -> 0.8784967 | AK89: =Hours_q!D89 -> 249700.14 | AL89: =100*LN(AE89) -> 1451.1617 | AM89: =AD89 -> 63.55 | AN89: NaN | AO89: =100*LN(AE89/AI89/(AE88/AI88)) -> 0.3165351 | AP89: =100*LN(AF89/AI89/(AF88/AI88)) -> 0.77355995 | AQ89: =100*LN(AG89/AI89/(AG88/AI88)) -> 0.39864248 | AR89: =100*LN(AH89/AH88) -> 1.3953715 | AS89: =100*LN(AM89/AM88) -> 1.0439829 | AT89: =W89/4 -> 2.6155 | AU89: =100*LN(AJ89/AJ88) -> 1.2049029 | AV89: =Hours_q!H89 -> 2.2669066 | AW89: =AV89-AVERAGE($AV$104:$AV$222) -> 3.2224584 | AX89: NaN | AY89: =+BG89/4 -> 2.512975 | BD89: 10.1222 | BE89: --- | BF89: 10.0859 | BG89: 10.0519
A90: 3q91 | B90: 0.17177257 | J90: =+J91*M90/M91 -> 249202.58 | M90: 145.245 | N90: 1346.821 | O90: 767.967 | P90: 0.869 | Q90: 307.574 | R90: 0.92 | S90: 0.877 | T90: 145.245 | U90: 613.057 | V90: 133.765 | W90: 10.506 | X90: =U90/V90 -> 4.5830897 | Y90: =X90/S90 -> 5.225872 | Z90: 86.65 | AA90: 111223 | AB90: =O90*P90/S90 -> 760.9616 | AC90: =Q90*R90/S90 -> 322.6546 | AD90: 64.21 | AE90: =AE91*N90/N91 -> 2005371.5 | AF90: =AF91*AB90/AB91 -> 11159.076 | AG90: =AG91*AC90/AC91 -> 4894.4596 | AH90: =AH91*S90/S91 -> 59.691979 | AI90: =+J90 -> 249202.58 | AJ90: =AJ91*Y90/Y91 -> 0.88061876 | AK90: =Hours_q!D90 -> 249202.58 | AL90: =100*LN(AE90) -> 1451.134 | AM90: =AD90 -> 64.21 | AN90: NaN | AO90: =100*LN(AE90/AI90/(AE89/AI89)) -> 0.17177257 | AP90: =100*LN(AF90/AI90/(AF89/AI89)) -> 0.2304445 | AQ90: =100*LN(AG90/AI90/(AG89/AI89)) -> -0.019720919 | AR90: =100*LN(AH90/AH89) -> 1.2622084 | AS90: =100*LN(AM90/AM89) -> 1.0331964 | AT90: =W90/4 -> 2.6265 | AU90: =100*LN(AJ90/AJ89) -> 0.24126446 | AV90: =Hours_q!H90 -> 2.3188726 | AW90: =AV90-AVERAGE($AV$104:$AV$222) -> 3.2744244 | AX90: NaN | AY90: =+BG90/4 -> 2.5357 | BD90: 10.2966 | BE90: --- | BF90: 10.2305 | BG90: 10.1428
A91: 4q91 | B91: 0.94105254 | J91: =+J92*M91/M92 -> 249216.31 | M91: 145.253 | N91: 1359.63 | O91: 778.8 | P91: 0.881 | Q91: 311.711 | R91: 0.925 | S91: 0.89 | T91: 145.253 | U91: 622.992 | V91: 133.58 | W91: 10.732 | X91: =U91/V91 -> 4.6638119 | Y91: =X91/S91 -> 5.2402381 | Z91: 87.524 | AA91: 111107 | AB91: =O91*P91/S91 -> 770.92449 | AC91: =Q91*R91/S91 -> 323.9693 | AD91: 64.9 | AE91: =AE92*N91/N92 -> 2024443.6 | AF91: =AF92*AB91/AB92 -> 11305.177 | AG91: =AG92*AC91/AC92 -> 4914.4028 | AH91: =AH92*S91/S92 -> 60.576809 | AI91: =+J91 -> 249216.31 | AJ91: =AJ92*Y91/Y92 -> 0.88303962 | AK91: =Hours_q!D91 -> 249216.31 | AL91: =100*LN(AE91) -> 1452.0805 | AM91: =AD91 -> 64.9 | AN91: NaN | AO91: =100*LN(AE91/AI91/(AE90/AI90)) -> 0.94105254 | AP91: =100*LN(AF91/AI91/(AF90/AI90)) -> 1.2952463 | AQ91: =100*LN(AG91/AI91/(AG90/AI90)) -> 0.40112871 | AR91: =100*LN(AH91/AH90) -> 1.471447 | AS91: =100*LN(AM91/AM90) -> 1.0688662 | AT91: =W91/4 -> 2.683 | AU91: =100*LN(AJ91/AJ90) -> 0.27452701 | AV91: =Hours_q!H91 -> 2.1913876 | AW91: =AV91-AVERAGE($AV$104:$AV$222) -> 3.1469394 | AX91: NaN | AY91: =+BG91/4 -> 2.47355 | BD91: 10.1946 | BE91: --- | BF91: 10.0569 | BG91: 9.8942
A92: 1q92 | B92: 1.4872337 | J92: =+J93*M92/M93 -> 249243.76 | M92: 145.269 | N92: 1380.154 | O92: 783.518 | P92: 0.889 | Q92: 317.316 | R92: 0.929 | S92: 0.896 | T92: 145.269 | U92: 635.394 | V92: 133.451 | W92: 10.849 | X92: =U92/V92 -> 4.7612532 | Y92: =X92/S92 -> 5.3138987 | Z92: 88.392 | AA92: 110890 | AB92: =O92*P92/S92 -> 777.39677 | AC92: =Q92*R92/S92 -> 329.00286 | AD92: 65.62 | AE92: =AE93*N92/N93 -> 2055003.2 | AF92: =AF93*AB92/AB93 -> 11400.089 | AG92: =AG93*AC92/AC93 -> 4990.7587 | AH92: =AH93*S92/S93 -> 60.985191 | AI92: =+J92 -> 249243.76 | AJ92: =AJ93*Y92/Y93 -> 0.89545225 | AK92: =Hours_q!D92 -> 249243.76 | AL92: =100*LN(AE92) -> 1453.5788 | AM92: =AD92 -> 65.62 | AN92: NaN | AO92: =100*LN(AE92/AI92/(AE91/AI91)) -> 1.4872337 | AP92: =100*LN(AF92/AI92/(AF91/AI91)) -> 0.82502746 | AQ92: =100*LN(AG92/AI92/(AG91/AI91)) -> 1.5307551 | AR92: =100*LN(AH92/AH91) -> 0.67189502 | AS92: =100*LN(AM92/AM91) -> 1.1032904 | AT92: =W92/4 -> 2.71225 | AU92: =100*LN(AJ92/AJ91) -> 1.3958831 | AV92: =Hours_q!H92 -> 1.9612218 | AW92: =AV92-AVERAGE($AV$104:$AV$222) -> 2.9167736 | AX92: NaN | AY92: =+BG92/4 -> 2.394975 | BD92: 9.9923 | BE92: --- | BF92: 9.7297 | BG92: 9.5799
A93: 2q92 | B93: -0.84882009 | J93: =+J94*M93/M94 -> 249449.65 | M93: 145.389 | N93: 1369.619 | O93: 784.408 | P93: 0.898 | Q93: 312.656 | R93: 0.933 | S93: 0.905 | T93: 145.389 | U93: 641.64 | V93: 133.246 | W93: 10.979 | X93: =U93/V93 -> 4.8154541 | Y93: =X93/S93 -> 5.3209438 | Z93: 89.256 | AA93: 110758 | AB93: =O93*P93/S93 -> 778.34076 | AC93: =Q93*R93/S93 -> 322.32933 | AD93: 66.3 | AE93: =AE94*N93/N94 -> 2039316.9 | AF93: =AF94*AB93/AB94 -> 11413.932 | AG93: =AG94*AC93/AC94 -> 4889.5257 | AH93: =AH94*S93/S94 -> 61.597766 | AI93: =+J93 -> 249449.65 | AJ93: =AJ94*Y93/Y94 -> 0.89663943 | AK93: =Hours_q!D93 -> 249449.65 | AL93: =100*LN(AE93) -> 1452.8125 | AM93: =AD93 -> 66.3 | AN93: NaN | AO93: =100*LN(AE93/AI93/(AE92/AI92)) -> -0.84882009 | AP93: =100*LN(AF93/AI93/(AF92/AI92)) -> 0.03878471 | AQ93: =100*LN(AG93/AI93/(AG92/AI92)) -> -2.131836 | AR93: =100*LN(AH93/AH92) -> 0.99945307 | AS93: =100*LN(AM93/AM92) -> 1.030937 | AT93: =W93/4 -> 2.74475 | AU93: =100*LN(AJ93/AJ92) -> 0.13249145 | AV93: =Hours_q!H93 -> 1.7157692 | AW93: =AV93-AVERAGE($AV$104:$AV$222) -> 2.671321 | AX93: NaN | AY93: =+BG93/4 -> 2.419025 | BD93: 10.1846 | BE93: --- | BF93: 9.8466 | BG93: 9.6761
A94: 3q92 | B94: -0.16340152 | J94: =+J95*M94/M95 -> 249157.97 | M94: 145.219 | N94: 1365.784 | O94: 782.985 | P94: 0.904 | Q94: 306.64 | R94: 0.939 | S94: 0.912 | T94: 145.219 | U94: 652.254 | V94: 132.606 | W94: 11.928 | X94: =U94/V94 -> 4.9187367 | Y94: =X94/S94 -> 5.3933517 | Z94: 89.967 | AA94: 110152 | AB94: =O94*P94/S94 -> 776.11671 | AC94: =Q94*R94/S94 -> 315.71816 | AD94: 66.93 | AE94: =AE95*N94/N95 -> 2033606.7 | AF94: =AF95*AB94/AB95 -> 11381.318 | AG94: =AG95*AC94/AC95 -> 4789.2384 | AH94: =AH95*S94/S95 -> 62.074213 | AI94: =+J94 -> 249157.97 | AJ94: =AJ95*Y94/Y95 -> 0.90884098 | AK94: =Hours_q!D94 -> 249157.97 | AL94: =100*LN(AE94) -> 1452.5321 | AM94: =AD94 -> 66.93 | AN94: NaN | AO94: =100*LN(AE94/AI94/(AE93/AI93)) -> -0.16340152 | AP94: =100*LN(AF94/AI94/(AF93/AI93)) -> -0.16915477 | AQ94: =100*LN(AG94/AI94/(AG93/AI93)) -> -1.9553931 | AR94: =100*LN(AH94/AH93) -> 0.77050464 | AS94: =100*LN(AM94/AM93) -> 0.94573999 | AT94: =W94/4 -> 2.982 | AU94: =100*LN(AJ94/AJ93) -> 1.351633 | AV94: =Hours_q!H94 -> 1.5494135 | AW94: =AV94-AVERAGE($AV$104:$AV$222) -> 2.5049653 | AX94: NaN | AY94: =+BG94/4 -> 2.513025 | BD94: 10.8492 | BE94: --- | BF94: 10.4018 | BG94: 10.0521
A95: 4q92 | B95: -0.075441519 | J95: =+J96*M95/M96 -> 248847.42 | M95: 145.038 | N95: 1363.053 | O95: 789.441 | P95: 0.914 | Q95: 304.043 | R95: 0.944 | S95: 0.921 | T95: 145.038 | U95: 651.848 | V95: 131.963 | W95: 11.452 | X95: =U95/V95 -> 4.939627 | Y95: =X95/S95 -> 5.3633301 | Z95: 90.704 | AA95: 109666 | AB95: =O95*P95/S95 -> 783.44091 | AC95: =Q95*R95/S95 -> 311.63582 | AD95: 67.53 | AE95: =AE96*N95/N96 -> 2029540.4 | AF95: =AF96*AB95/AB96 -> 11488.723 | AG95: =AG96*AC95/AC96 -> 4727.312 | AH95: =AH96*S95/S96 -> 62.686787 | AI95: =+J95 -> 248847.42 | AJ95: =AJ96*Y95/Y96 -> 0.90378201 | AK95: =Hours_q!D95 -> 248847.42 | AL95: =100*LN(AE95) -> 1452.332 | AM95: =AD95 -> 67.53 | AN95: NaN | AO95: =100*LN(AE95/AI95/(AE94/AI94)) -> -0.075441519 | AP95: =100*LN(AF95/AI95/(AF94/AI94)) -> 1.0639897 | AQ95: =100*LN(AG95/AI95/(AG94/AI94)) -> -1.1767471 | AR95: =100*LN(AH95/AH94) -> 0.98200462 | AS95: =100*LN(AM95/AM94) -> 0.89246465 | AT95: =W95/4 -> 2.863 | AU95: =100*LN(AJ95/AJ94) -> -0.55819516 | AV95: =Hours_q!H95 -> 1.4024862 | AW95: =AV95-AVERAGE($AV$104:$AV$222) -> 2.358038 | AX95: NaN | AY95: =+BG95/4 -> 2.503225 | BD95: 9.8999 | BE95: --- | BF95: 9.6537 | BG95: 10.0129
... A99: 4q93 | B99: 0.031056508 | J99: =+J100*M99/M100 -> 250458.5 | M99: 145.977 | N99: 1363.949 | O99: 783.047 | P99: 0.952 | Q99: 288.404 | R99: 0.967 | S99: 0.955 | T99: 145.977 | U99: 656.581 | V99: 130.245 | W99: 7.412 | X99: =U99/V99 -> 5.0411225 | Y99: =X99/S99 -> 5.2786623 | Z99: 93.821 | AA99: 108366 | AB99: =O99*P99/S99 -> 780.58717 | AC99: =Q99*R99/S99 -> 292.02792 | AD99: 69.98 | AE99: =AE100*N99/N100 -> 2030874.5 | AF99: =AF100*AB99/AB100 -> 11446.874 | AG99: =AG100*AC99/AC100 -> 4429.873 | AH99: =AH100*S99/S100 -> 65.000957 | AI99: =+J99 -> 250458.5 | AJ99: =AJ100*Y99/Y100 -> 0.88951452 | AK99: =Hours_q!D99 -> 250458.5 | AL99: =100*LN(AE99) -> 1452.3977 | AM99: =AD99 -> 69.98 | AN99: NaN | AO99: =100*LN(AE99/AI99/(AE98/AI98)) -> 0.031056508 | AP99: =100*LN(AF99/AI99/(AF98/AI98)) -> 0.4397777 | AQ99: =100*LN(AG99/AI99/(AG98/AI98)) -> -1.733302 | AR99: =100*LN(AH99/AH98) -> 0.84122473 | AS99: =100*LN(AM99/AM98) -> 0.74584396 | AT99: =W99/4 -> 1.853 | AU99: =100*LN(AJ99/AJ98) -> -0.37914989 | AV99: =Hours_q!H99 -> 1.1259266 | AW99: =AV99-AVERAGE($AV$104:$AV$222) -> 2.0814784 | AX99: NaN | AY99: =+BG99/4 -> 1.827275 | BD99: 6.5862 | BE99: --- | BF99: 6.6646 | BG99: 7.3091
A100: 1q94 | B100: 0.80325464 | J100: =+J101*M100/M101 -> 250757.04 | L100: 6.98 | M100: 146.151 | N100: 1376.588 | O100: 783.639 | P100: 0.961 | Q100: 291.35 | R100: 0.973 | S100: 0.96 | T100: 146.151 | U100: 659.257 | V100: 130.136 | W100: 6.84 | X100: =U100/V100 -> 5.065908 | Y100: =X100/S100 -> 5.2769875 | Z100: 94.355 | AA100: 108275 | AB100: =O100*P100/S100 -> 784.45529 | AC100: =Q100*R100/S100 -> 295.29536 | AD100: 70.4 | AE100: =AE101*N100/N101 -> 2049693.5 | AF100: =AF101*AB100/AB101 -> 11503.598 | AG100: =AG101*AC100/AC101 -> 4479.438 | AH100: =AH101*S100/S101 -> 65.341277 | AI100: =+J100 -> 250757.04 | AJ100: =AJ101*Y100/Y101 -> 0.88923229 | AK100: =Hours_q!D100 -> 250757.04 | AL100: =100*LN(AE100) -> 1453.3201 | AM100: =AD100 -> 70.4 | AN100: NaN | AO100: =100*LN(AE100/AI100/(AE99/AI99)) -> 0.80325464 | AP100: =100*LN(AF100/AI100/(AF99/AI99)) -> 0.37519068 | AQ100: =100*LN(AG100/AI100/(AG99/AI99)) -> 0.99354026 | AR100: =100*LN(AH100/AH99) -> 0.5221944 | AS100: =100*LN(AM100/AM99) -> 0.59837762 | AT100: =L100/4 -> 1.745 | AU100: =100*LN(AJ100/AJ99) -> -0.031733366 | AV100: =Hours_q!H100 -> 1.1120575 | AW100: =AV100-AVERAGE($AV$104:$AV$222) -> 2.0676094 | AX100: NaN | AY100: =+BG100/4 -> 1.743325 | BD100: 6.3267 | BE100: --- | BF100: 6.39 | BG100: 6.9733
A101: 2q94 | B101: 0.55859546 | J101: =+J102*M101/M102 -> 250913.17 | L101: 6.43 | M101: 146.242 | N101: 1385.161 | O101: 785.897 | P101: 0.968 | Q101: 296.074 | R101: 0.977 | S101: 0.966 | T101: 146.242 | U101: 664.255 | V101: 130.104 | W101: 6.37 | X101: =U101/V101 -> 5.1055694 | Y101: =X101/S101 -> 5.2852685 | Z101: 94.984 | AA101: 108342 | AB101: =O101*P101/S101 -> 787.52412 | AC101: =Q101*R101/S101 -> 299.44544 | AD101: 70.85 | AE101: =AE102*N101/N102 -> 2062458.4 | AF101: =AF102*AB101/AB102 -> 11548.601 | AG101: =AG102*AC101/AC102 -> 4542.3919 | AH101: =AH102*S101/S102 -> 65.74966 | AI101: =+J101 -> 250913.17 | AJ101: =AJ102*Y101/Y102 -> 0.89062774 | AK101: =Hours_q!D101 -> 250913.17 | AL101: =100*LN(AE101) -> 1453.9409 | AM101: =AD101 -> 70.85 | AN101: NaN | AO101: =100*LN(AE101/AI101/(AE100/AI100)) -> 0.55859546 | AP101: =100*LN(AF101/AI101/(AF100/AI100)) -> 0.32819641 | AQ101: =100*LN(AG101/AI101/(AG100/AI100)) -> 1.33337 | AR101: =100*LN(AH101/AH100) -> 0.62305498 | AS101: =100*LN(AM101/AM100) -> 0.6371703 | AT101: =L101/4 -> 1.6075 | AU101: =100*LN(AJ101/AJ100) -> 0.15680457 | AV101: =Hours_q!H101 -> 1.0549413 | AW101: =AV101-AVERAGE($AV$104:$AV$222) -> 2.0104931 | AX101: NaN | AY101: =+BG101/4 -> 1.965 | BD101: 6.74 | BE101: --- | BF101: 7.3033 | BG101: 7.86
A102: 3q94 | B102: 0.619211 | J102: =+J103*M102/M103 -> 251043.57 | L102: 6.23 | M102: 146.318 | N102: 1394.489 | O102: 791.609 | P102: 0.975 | Q102: 299.249 | R102: 0.981 | S102: 0.973 | T102: 146.318 | U102: 670.06 | V102: 130.343 | W102: 6.383 | X102: =U102/V102 -> 5.140744 | Y102: =X102/S102 -> 5.2833957 | Z102: 95.71 | AA102: 108602 | AB102: =O102*P102/S102 -> 793.23615 | AC102: =Q102*R102/S102 -> 301.70942 | AD102: 71.29 | AE102: =AE103*N102/N103 -> 2076347.5 | AF102: =AF103*AB102/AB103 -> 11632.365 | AG102: =AG103*AC102/AC103 -> 4576.7351 | AH102: =AH103*S102/S103 -> 66.226106 | AI102: =+J102 -> 251043.57 | AJ102: =AJ103*Y102/Y103 -> 0.89031216 | AK102: =Hours_q!D102 -> 251043.57 | AL102: =100*LN(AE102) -> 1454.6121 | AM102: =AD102 -> 71.29 | AN102: NaN | AO102: =100*LN(AE102/AI102/(AE101/AI101)) -> 0.619211 | AP102: =100*LN(AF102/AI102/(AF101/AI101)) -> 0.67074266 | AQ102: =100*LN(AG102/AI102/(AG101/AI101)) -> 0.70125877 | AR102: =100*LN(AH102/AH101) -> 0.7220248 | AS102: =100*LN(AM102/AM101) -> 0.6191099 | AT102: =L102/4 -> 1.5575 | AU102: =100*LN(AJ102/AJ101) -> -0.0354406 | AV102: =Hours_q!H102 -> 0.93841966 | AW102: =AV102-AVERAGE($AV$104:$AV$222) -> 1.8939715 | AX102: NaN | AY102: =+BG102/4 -> 2.1825 | BD102: 7.4433 | BE102: --- | BF102: 8.1833 | BG102: 8.73
A103: 4q94 | B103: 0.61690512 | J103: =+J104*M103/M104 -> 251479.37 | L103: 6.27 | M103: 146.572 | N103: 1405.554 | O103: 795.216 | P103: 0.982 | Q103: 306.642 | R103: 0.986 | S103: 0.981 | T103: 146.572 | U103: 677.862 | V103: 130.568 | W103: 6.507 | X103: =U103/V103 -> 5.1916396 | Y103: =X103/S103 -> 5.2921912 | Z103: 96.352 | AA103: 108838 | AB103: =O103*P103/S103 -> 796.02662 | AC103: =Q103*R103/S103 -> 308.20491 | AD103: 71.75 | AE103: =AE104*N103/N104 -> 2092822.9 | AF103: =AF104*AB103/AB104 -> 11673.285 | AG103: =AG104*AC103/AC104 -> 4675.2673 | AH103: =AH104*S103/S104 -> 66.770617 | AI103: =+J103 -> 251479.37 | AJ103: =AJ104*Y103/Y104 -> 0.8917943 | AK103: =Hours_q!D103 -> 251479.37 | AL103: =100*LN(AE103) -> 1455.4024 | AM103: =AD103 -> 71.75 | AN103: NaN | AO103: =100*LN(AE103/AI103/(AE102/AI102)) -> 0.61690512 | AP103: =100*LN(AF103/AI103/(AF102/AI102)) -> 0.17772128 | AQ103: =100*LN(AG103/AI103/(AG102/AI102)) -> 1.9566018 | AR103: =100*LN(AH103/AH102) -> 0.81883774 | AS103: =100*LN(AM103/AM102) -> 0.64317895 | AT103: =L103/4 -> 1.5675 | AU103: =100*LN(AJ103/AJ102) -> 0.16633629 | AV103: =Hours_q!H103 -> 0.78924611 | AW103: =AV103-AVERAGE($AV$104:$AV$222) -> 1.7447979 | AX103: NaN | AY103: =+BG103/4 -> 2.285 | BD103: 7.7633 | BE103: --- | BF103: 8.66 | BG103: 9.14
A104: 1q95 | B104: 0.59011349 | E104: 2104189.7 | F104: 789257.5 | G104: 309744.8 | H104: 67.179 | J104: =+J105*M104/M105 -> 251357.55 | K104: 59.91 | L104: 6.72 | M104: 146.501 | N104: 1413.188 | O104: 798.733 | P104: 0.99 | Q104: 302.419 | R104: 0.992 | S104: 0.987 | T104: 146.501 | U104: 682.041 | V104: 130.574 | W104: 6.943 | X104: =U104/V104 -> 5.2234059 | Y104: =X104/S104 -> 5.2922045 | Z104: 96.987 | AA104: 108916 | AB104: =O104*P104/S104 -> 801.16076 | AC104: =Q104*R104/S104 -> 303.95101 | AD104: 72.23 | AE104: =E104 -> 2104189.7 | AF104: =F104/H104 -> 11748.575 | AG104: =G104/H104 -> 4610.7385 | AH104: =H104 -> 67.179 | AI104: =+J104 -> 251357.55 | AJ104: =K104/H104 -> 0.89179654 | AK104: =Hours_q!D104 -> 251357.55 | AL104: =100*LN(AE104) -> 1455.9441 | AM104: =AD104 -> 72.23 | AN104: NaN | AO104: =100*LN(AE104/AI104/(AE103/AI103)) -> 0.59011349 | AP104: =100*LN(AF104/AI104/(AF103/AI103)) -> 0.69135222 | AQ104: =100*LN(AG104/AI104/(AG103/AI103)) -> -1.3413777 | AR104: =100*LN(AH104/AH103) -> 0.60975799 | AS104: =100*LN(AM104/AM103) -> 0.66676174 | AT104: =L104/4 -> 1.68 | AU104: =100*LN(AJ104/AJ103) -> 0.00025140593 | AV104: =Hours_q!H104 -> 0.64187765 | AW104: =AV104-AVERAGE($AV$104:$AV$222) -> 1.5974295 | AX104: NaN | AY104: =+BG104/4 -> 2.33 | BD104: 7.7433 | BE104: --- | BF104: 8.54 | BG104: 9.32
A105: 2q95 | B105: 0.51685346 | E105: 2121361.1 | F105: 799975.7 | G105: 310753.7 | H105: 67.452 | J105: =+J106*M105/M106 -> 251549.71 | K105: 60.53 | L105: 7.07 | M105: 146.613 | N105: 1421.597 | O105: 807.939 | P105: 0.996 | Q105: 305.283 | R105: 0.999 | S105: 0.996 | T105: 146.613 | U105: 690.173 | V105: 130.803 | W105: 7.137 | X105: =U105/V105 -> 5.276431 | Y105: =X105/S105 -> 5.2976215 | Z105: 97.573 | AA105: 109072 | AB105: =O105*P105/S105 -> 807.939 | AC105: =Q105*R105/S105 -> 306.20253 | AD105: 72.72 | AE105: =E105 -> 2121361.1 | AF105: =F105/H105 -> 11859.926 | AG105: =G105/H105 -> 4607.0346 | AH105: =H105 -> 67.452 | AI105: =+J105 -> 251549.71 | AJ105: =K105/H105 -> 0.89737888 | AK105: =Hours_q!D105 -> 251549.71 | AL105: =100*LN(AE105) -> 1456.7568 | AM105: =AD105 -> 72.72 | AN105: NaN | AO105: =100*LN(AE105/AI105/(AE104/AI104)) -> 0.73632507 | AP105: =100*LN(AF105/AI105/(AF104/AI104)) -> 0.86689792 | AQ105: =100*LN(AG105/AI105/(AG104/AI104)) -> -0.15678386 | AR105: =100*LN(AH105/AH104) -> 0.40555351 | AS105: =100*LN(AM105/AM104) -> 0.67609778 | AT105: =L105/4 -> 1.7675 | AU105: =100*LN(AJ105/AJ104) -> 0.62401387 | AV105: =Hours_q!H105 -> 0.63638048 | AW105: =AV105-AVERAGE($AV$104:$AV$222) -> 1.5919323 | AX105: NaN | AY105: =+BG105/4 -> 2.2325 | BD105: 7.2 | BE105: --- | BF105: 7.9433 | BG105: 8.93
A106: 3q95 | B106: 0.033259661 | E106: 2126741 | F106: 812523 | G106: 311021.6 | H106: 68.312 | J106: =+J107*M106/M107 -> 252199.98 | K106: 60.96 | L106: 6.66 | M106: 146.992 | N106: 1425.746 | O106: 807.247 | P106: 1.004 | Q106: 304.96 | R106: 1.003 | S106: 1.004 | T106: 146.992 | U106: 696.059 | V106: 130.958 | W106: 6.693 | X106: =U106/V106 -> 5.3151316 | Y106: =X106/S106 -> 5.2939557 | Z106: 98.203 | AA106: 109203 | AB106: =O106*P106/S106 -> 807.247 | AC106: =Q106*R106/S106 -> 304.65625 | AD106: 73.22 | AE106: =E106 -> 2126741 | AF106: =F106/H106 -> 11894.294 | AG106: =G106/H106 -> 4552.957 | AH106: =H106 -> 68.312 | AI106: =+J106 -> 252199.98 | AJ106: =K106/H106 -> 0.89237616 | AK106: =Hours_q!D106 -> 252199.98 | AL106: =100*LN(AE106) -> 1457.0101 | AM106: =AD106 -> 73.22 | AN106: NaN | AO106: =100*LN(AE106/AI106/(AE105/AI105)) -> -0.0048851255 | AP106: =100*LN(AF106/AI106/(AF105/AI105)) -> 0.031195515 | AQ106: =100*LN(AG106/AI106/(AG105/AI105)) -> -1.4389188 | AR106: =100*LN(AH106/AH105) -> 1.2669213 | AS106: =100*LN(AM106/AM105) -> 0.68521578 | AT106: =L106/4 -> 1.665 | AU106: =100*LN(AJ106/AJ105) -> -0.55904113 | AV106: =Hours_q!H106 -> 0.46589583 | AW106: =AV106-AVERAGE($AV$104:$AV$222) -> 1.4214476 | AX106: NaN | AY106: =+BG106/4 -> 2.128325 | BD106: 6.67 | BE106: --- | BF106: 7.4833 | BG106: 8.5133
A107: 4q95 | B107: 0.00823304 | E107: 2131740.6 | F107: 820662.3 | G107: 313899 | H107: 68.824 | J107: =+J108*M107/M108 -> 252894.85 | K107: 61.56 | L107: 6.5 | M107: 147.397 | N107: 1429.792 | O107: 808.131 | P107: 1.01 | Q107: 307.929 | R107: 1.006 | S107: 1.011 | T107: 147.397 | U107: 702.959 | V107: 131.223 | W107: 6.507 | X107: =U107/V107 -> 5.3569801 | Y107: =X107/S107 -> 5.2986945 | Z107: 98.737 | AA107: 109457 | AB107: =O107*P107/S107 -> 807.33166 | AC107: =Q107*R107/S107 -> 306.40611 | AD107: 73.66 | AE107: =E107 -> 2131740.6 | AF107: =F107/H107 -> 11924.072 | AG107: =G107/H107 -> 4560.8945 | AH107: =H107 -> 68.824 | AI107: =+J107 -> 252894.85 | AJ107: =K107/H107 -> 0.89445542 | AK107: =Hours_q!D107 -> 252894.85 | AL107: =100*LN(AE107) -> 1457.2449 | AM107: =AD107 -> 73.66 | AN107: NaN | AO107: =100*LN(AE107/AI107/(AE106/AI106)) -> -0.040339519 | AP107: =100*LN(AF107/AI107/(AF106/AI106)) -> -0.025106226 | AQ107: =100*LN(AG107/AI107/(AG106/AI106)) -> -0.1009623 | AR107: =100*LN(AH107/AH106) -> 0.74670747 | AS107: =100*LN(AM107/AM106) -> 0.59913033 | AT107: =L107/4 -> 1.625 | AU107: =100*LN(AJ107/AJ106) -> 0.23273229 | AV107: =Hours_q!H107 -> 0.39688441 | AW107: =AV107-AVERAGE($AV$104:$AV$222) -> 1.3524362 | AX107: NaN | AY107: =+BG107/4 -> 2.038325 | BD107: 6.04 | BE107: --- | BF107: 6.8267 | BG107: 8.1533
A108: 1q96 | B108: 0.14536009 | E108: 2135022.2 | F108: 834000.5 | G108: 312996.4 | H108: 69.338 | J108: =+J109*M108/M109 -> 252875.98 | K108: 61.78 | L108: 5.67 | M108: 147.386 | N108: 1431.765 | O108: 814.636 | P108: 1.014 | Q108: 301.037 | R108: 1.009 | S108: 1.014 | T108: 147.386 | U108: 705.89 | V108: 131.268 | W108: 5.63 | X108: =U108/V108 -> 5.377472 | Y108: =X108/S108 -> 5.3032269 | Z108: 99.343 | AA108: 109407 | AB108: =O108*P108/S108 -> 814.636 | AC108: =Q108*R108/S108 -> 299.5526 | AD108: 74.07 | AE108: =E108 -> 2135022.2 | AF108: =F108/H108 -> 12028.044 | AG108: =G108/H108 -> 4514.0673 | AH108: =H108 -> 69.338 | AI108: =+J108 -> 252875.98 | AJ108: =K108/H108 -> 0.89099772 | AK108: =Hours_q!D108 -> 252875.98 | AL108: =100*LN(AE108) -> 1457.3988 | AM108: =AD108 -> 74.07 | AN108: NaN | AO108: =100*LN(AE108/AI108/(AE107/AI107)) -> 0.16128468 | AP108: =100*LN(AF108/AI108/(AF107/AI107)) -> 0.87563607 | AQ108: =100*LN(AG108/AI108/(AG107/AI107)) -> -1.0245533 | AR108: =100*LN(AH108/AH107) -> 0.74405751 | AS108: =100*LN(AM108/AM107) -> 0.5550681 | AT108: =L108/4 -> 1.4175 | AU108: =100*LN(AJ108/AJ107) -> -0.38731966 | AV108: =Hours_q!H108 -> 0.22735103 | AW108: =AV108-AVERAGE($AV$104:$AV$222) -> 1.1829028 | AX108: NaN | AY108: =+BG108/4 -> 1.910825 | BD108: 5.46 | BE108: --- | BF108: 6.4133 | BG108: 7.6433
A109: 2q96 | B109: 0.34250016 | E109: 2151475.4 | F109: 842533.7 | G109: 323435.3 | H109: 69.615 | J109: =+J110*M109/M110 -> 253781.89 | K109: 62.02 | L109: 5.19 | M109: 147.914 | N109: 1441.824 | O109: 817.171 | P109: 1.019 | Q109: 312.545 | R109: 1.009 | S109: 1.017 | T109: 147.914 | U109: 710.648 | V109: 131.58 | W109: 5.137 | X109: =U109/V109 -> 5.4008816 | Y109: =X109/S109 -> 5.3106014 | Z109: 99.922 | AA109: 109690 | AB109: =O109*P109/S109 -> 818.77802 | AC109: =Q109*R109/S109 -> 310.08644 | AD109: 74.4 | AE109: =E109 -> 2151475.4 | AF109: =F109/H109 -> 12102.761 | AG109: =G109/H109 -> 4646.0576 | AH109: =H109 -> 69.615 | AI109: =+J109 -> 253781.89 | AJ109: =K109/H109 -> 0.89089995 | AK109: =Hours_q!D109 -> 253781.89 | AL109: =100*LN(AE109) -> 1458.1664 | AM109: =AD109 -> 74.4 | AN109: NaN | AO109: =100*LN(AE109/AI109/(AE108/AI108)) -> 0.41007664 | AP109: =100*LN(AF109/AI109/(AF108/AI108)) -> 0.26166665 | AQ109: =100*LN(AG109/AI109/(AG108/AI108)) -> 2.5244412 | AR109: =100*LN(AH109/AH108) -> 0.39869649 | AS109: =100*LN(AM109/AM108) -> 0.44453498 | AT109: =L109/4 -> 1.2975 | AU109: =100*LN(AJ109/AJ108) -> -0.010973872 | AV109: =Hours_q!H109 -> -0.021899397 | AW109: =AV109-AVERAGE($AV$104:$AV$222) -> 0.93365242 | AX109: NaN | AY109: =+BG109/4 -> 1.884175 | BD109: 5.1067 | BE109: --- | BF109: 6.26 | BG109: 7.5367
A110: 3q96 | B110: 0.41476342 | E110: 2162072.2 | F110: 851419.1 | G110: 326552.4 | H110: 69.918 | J110: =+J111*M110/M111 -> 254361.81 | K110: 62.49 | L110: 5 | M110: 148.252 | N110: 1451.125 | O110: 822.325 | P110: 1.023 | Q110: 314.404 | R110: 1.013 | S110: 1.021 | T110: 148.252 | U110: 718.331 | V110: 131.906 | W110: 5 | X110: =U110/V110 -> 5.4457796 | Y110: =X110/S110 -> 5.3337704 | Z110: 100.192 | AA110: 109977 | AB110: =O110*P110/S110 -> 823.93582 | AC110: =Q110*R110/S110 -> 311.9405 | AD110: 74.66 | AE110: =E110 -> 2162072.2 | AF110: =F110/H110 -> 12177.395 | AG110: =G110/H110 -> 4670.5054 | AH110: =H110 -> 69.918 | AI110: =+J110 -> 254361.81 | AJ110: =K110/H110 -> 0.89376126 | AK110: =Hours_q!D110 -> 254361.81 | AL110: =100*LN(AE110) -> 1458.6578 | AM110: =AD110 -> 74.66 | AN110: NaN | AO110: =100*LN(AE110/AI110/(AE109/AI109)) -> 0.26307696 | AP110: =100*LN(AF110/AI110/(AF109/AI109)) -> 0.38652552 | AQ110: =100*LN(AG110/AI110/(AG109/AI109)) -> 0.29657618 | AR110: =100*LN(AH110/AH109) -> 0.43430655 | AS110: =100*LN(AM110/AM109) -> 0.34885316 | AT110: =L110/4 -> 1.25 | AU110: =100*LN(AJ110/AJ109) -> 0.32065648 | AV110: =Hours_q!H110 -> 0.22279517 | AW110: =AV110-AVERAGE($AV$104:$AV$222) -> 1.178347 | AX110: NaN | AY110: =+BG110/4 -> 1.819175 | BD110: 5.0267 | BE110: --- | BF110: 6.0667 | BG110: 7.2767
A111: 4q96 | B111: 0.31058657 | E111: 2173922.3 | F111: 851518.6 | G111: 323270.7 | H111: 69.786 | J111: =+J112*M111/M112 -> 254655.2 | K111: 62.84 | L111: 4.63 | M111: 148.423 | N111: 1457.318 | O111: 823.308 | P111: 1.027 | Q111: 314.766 | R111: 1.012 | S111: 1.024 | T111: 148.423 | U111: 723.27 | V111: 132.098 | W111: 4.587 | X111: =U111/V111 -> 5.4752532 | Y111: =X111/S111 -> 5.346927 | Z111: 100.53 | AA111: 110196 | AB111: =O111*P111/S111 -> 825.72004 | AC111: =Q111*R111/S111 -> 311.07734 | AD111: 74.93 | AE111: =E111 -> 2173922.3 | AF111: =F111/H111 -> 12201.854 | AG111: =G111/H111 -> 4632.3145 | AH111: =H111 -> 69.786 | AI111: =+J111 -> 254655.2 | AJ111: =K111/H111 -> 0.90046714 | AK111: =Hours_q!D111 -> 254655.2 | AL111: =100*LN(AE111) -> 1459.2044 | AM111: =AD111 -> 74.93 | AN111: NaN | AO111: =100*LN(AE111/AI111/(AE110/AI110)) -> 0.43131571 | AP111: =100*LN(AF111/AI111/(AF110/AI110)) -> 0.085379039 | AQ111: =100*LN(AG111/AI111/(AG110/AI110)) -> -0.93634397 | AR111: =100*LN(AH111/AH110) -> -0.18897102 | AS111: =100*LN(AM111/AM110) -> 0.36098709 | AT111: =L111/4 -> 1.1575 | AU111: =100*LN(AJ111/AJ110) -> 0.74749797 | AV111: =Hours_q!H111 -> 0.28068805 | AW111: =AV111-AVERAGE($AV$104:$AV$222) -> 1.2362399 | AX111: NaN | AY111: =+BG111/4 -> 1.618325 | BD111: 4.3467 | BE111: --- | BF111: 5.23 | BG111: 6.4733
A112: 1q97 | B112: 0.010159497 | E112: 2180437.1 | F112: 852899.6 | G112: 318212 | H112: 69.483 | J112: =+J113*M112/M113 -> 255207.67 | K112: 63.22 | L112: 4.49 | M112: 148.745 | N112: 1460.628 | O112: 826.057 | P112: 1.032 | Q112: 312.171 | R112: 1.018 | S112: 1.028 | T112: 148.745 | U112: 729.448 | V112: 132.41 | W112: 4.44 | X112: =U112/V112 -> 5.5090099 | Y112: =X112/S112 -> 5.358959 | Z112: 100.993 | AA112: 110580 | AB112: =O112*P112/S112 -> 829.27123 | AC112: =Q112*R112/S112 -> 309.13432 | AD112: 75.2 | AE112: =E112 -> 2180437.1 | AF112: =F112/H112 -> 12274.939 | AG112: =G112/H112 -> 4579.7101 | AH112: =H112 -> 69.483 | AI112: =+J112 -> 255207.67 | AJ112: =K112/H112 -> 0.90986284 | AK112: =Hours_q!D112 -> 255207.67 | AL112: =100*LN(AE112) -> 1459.5036 | AM112: =AD112 -> 75.2 | AN112: NaN | AO112: =100*LN(AE112/AI112/(AE111/AI111)) -> 0.082518863 | AP112: =100*LN(AF112/AI112/(AF111/AI111)) -> 0.38046678 | AQ112: =100*LN(AG112/AI112/(AG111/AI111)) -> -1.3588052 | AR112: =100*LN(AH112/AH111) -> -0.43512983 | AS112: =100*LN(AM112/AM111) -> 0.35968866 | AT112: =L112/4 -> 1.1225 | AU112: =100*LN(AJ112/AJ111) -> 1.0380192 | AV112: =Hours_q!H112 -> -0.069167804 | AW112: =AV112-AVERAGE($AV$104:$AV$222) -> 0.88638401 | AX112: NaN | AY112: =+BG112/4 -> 1.550825 | BD112: 4.3133 | BE112: --- | BF112: 5.1067 | BG112: 6.2033
A113: 2q97 | B113: 0.971908 | E113: 2206659.4 | F113: 855503.6 | G113: 329530.8 | H113: 69.307 | J113: =+J114*M113/M114 -> 256003.77 | K113: 63.47 | L113: 4.32 | M113: 149.209 | N113: 1479.494 | O113: 833.174 | P113: 1.034 | Q113: 317.917 | R113: 1.02 | S113: 1.032 | T113: 149.209 | U113: 734.361 | V113: 132.772 | W113: 4.327 | X113: =U113/V113 -> 5.530993 | Y113: =X113/S113 -> 5.3594893 | Z113: 101.294 | AA113: 110880 | AB113: =O113*P113/S113 -> 834.78868 | AC113: =Q113*R113/S113 -> 314.22029 | AD113: 75.44 | AE113: =E113 -> 2206659.4 | AF113: =F113/H113 -> 12343.682 | AG113: =G113/H113 -> 4754.6539 | AH113: =H113 -> 69.307 | AI113: =+J113 -> 256003.77 | AJ113: =K113/H113 -> 0.91578051 | AK113: =Hours_q!D113 -> 256003.77 | AL113: =100*LN(AE113) -> 1460.699 | AM113: =AM112*'Core data'!D4/'Core data'!D3 -> 75.379285 | AN113: NaN | AO113: =100*LN(AE113/AI113/(AE112/AI112)) -> 0.88398497 | AP113: =100*LN(AF113/AI113/(AF112/AI112)) -> 0.24700929 | AQ113: =100*LN(AG113/AI113/(AG112/AI112)) -> 3.4373627 | AR113: =100*LN(AH113/AH112) -> -0.25362071 | AS113: =100*LN(AM113/AM112) -> 0.23812685 | AT113: =L113/4 -> 1.08 | AU113: =100*LN(AJ113/AJ112) -> 0.64828537 | AV113: =Hours_q!H113 -> 0.025241518 | AW113: =AV113-AVERAGE($AV$104:$AV$222) -> 0.98079333 | AX113: NaN | AY113: =+BG113/4 -> 1.555 | BD113: 4.2933 | BE113: --- | BF113: 5.15 | BG113: 6.22
A114: 3q97 | B114: 0.54400159 | E114: 2223783.1 | F114: 863233.3 | G114: 328090.6 | H114: 69.429 | J114: =+J115*M114/M115 -> 256535.65 | K114: 63.74 | L114: 4.29 | M114: 149.519 | N114: 1490.655 | O114: 835.158 | P114: 1.043 | Q114: 319.172 | R114: 1.025 | S114: 1.036 | T114: 149.519 | U114: 740.526 | V114: 133.218 | W114: 4.323 | X114: =U114/V114 -> 5.5587533 | Y114: =X114/S114 -> 5.365592 | Z114: 101.75 | AA114: 111281 | AB114: =O114*P114/S114 -> 840.80096 | AC114: =Q114*R114/S114 -> 315.78311 | AD114: 75.7 | AE114: =E114 -> 2223783.1 | AF114: =F114/H114 -> 12433.325 | AG114: =G114/H114 -> 4725.5556 | AH114: =H114 -> 69.429 | AI114: =+J114 -> 256535.65 | AJ114: =K114/H114 -> 0.91806018 | AK114: =Hours_q!D114 -> 256535.65 | AL114: =100*LN(AE114) -> 1461.472 | AM114: =AM113*'Core data'!D5/'Core data'!D4 -> 75.618331 | AN114: NaN | AO114: =100*LN(AE114/AI114/(AE113/AI113)) -> 0.5654589 | AP114: =100*LN(AF114/AI114/(AF113/AI113)) -> 0.51604853 | AQ114: =100*LN(AG114/AI114/(AG113/AI113)) -> -0.82142386 | AR114: =100*LN(AH114/AH113) -> 0.17587365 | AS114: =100*LN(AM114/AM113) -> 0.31662296 | AT114: =L114/4 -> 1.0725 | AU114: =100*LN(AJ114/AJ113) -> 0.24862192 | AV114: =Hours_q!H114 -> 0.17268777 | AW114: =AV114-AVERAGE($AV$104:$AV$222) -> 1.1282396 | AX114: NaN | AY114: =+BG114/4 -> 1.4525 | BD114: 4.34 | BE114: --- | BF114: 5.03 | BG114: 5.81
A115: 4q97 | B115: 0.87842465 | E115: 2246989.1 | F115: 876907.4 | G115: 335141 | H115: 69.809 | J115: =+J116*M115/M116 -> 257072.68 | K115: 64.01 | L115: 4.38 | M115: 149.832 | N115: 1506.955 | O115: 845.124 | P115: 1.046 | Q115: 326.255 | R115: 1.028 | S115: 1.041 | T115: 149.832 | U115: 746.262 | V115: 133.612 | W115: 4.433 | X115: =U115/V115 -> 5.5852917 | Y115: =X115/S115 -> 5.3653139 | Z115: 102.193 | AA115: 111729 | AB115: =O115*P115/S115 -> 849.18319 | AC115: =Q115*R115/S115 -> 322.18073 | AD115: 75.97 | AE115: =E115 -> 2246989.1 | AF115: =F115/H115 -> 12561.524 | AG115: =G115/H115 -> 4800.828 | AH115: =H115 -> 69.809 | AI115: =+J115 -> 257072.68 | AJ115: =K115/H115 -> 0.91693048 | AK115: =Hours_q!D115 -> 257072.68 | AL115: =100*LN(AE115) -> 1462.5102 | AM115: =AM114*'Core data'!D6/'Core data'!D5 -> 75.857377 | AN115: NaN | AO115: =100*LN(AE115/AI115/(AE114/AI114)) -> 0.82901063 | AP115: =100*LN(AF115/AI115/(AF114/AI114)) -> 0.8166924 | AQ115: =100*LN(AG115/AI115/(AG114/AI114)) -> 1.3712064 | AR115: =100*LN(AH115/AH114) -> 0.54582936 | AS115: =100*LN(AM115/AM114) -> 0.31562362 | AT115: =L115/4 -> 1.095 | AU115: =100*LN(AJ115/AJ114) -> -0.12312815 | AV115: =Hours_q!H115 -> 0.20975516 | AW115: =AV115-AVERAGE($AV$104:$AV$222) -> 1.165307 | AX115: NaN | AY115: =+BG115/4 -> 1.4 | BD115: 4.4367 | BE115: --- | BF115: 5.06 | BG115: 5.6
A116: 1q98 | B116: 0.21650389 | E116: 2263054.5 | F116: 878053.3 | G116: 341400.4 | H116: 69.628 | J116: =+J117*M116/M117 -> 258127.86 | K116: 64.01 | L116: 4.21 | M116: 150.447 | N116: 1516.42 | O116: 850.58 | P116: 1.046 | Q116: 332.879 | R116: 1.028 | S116: 1.044 | T116: 150.447 | U116: 750.236 | V116: 134.405 | W116: 4.203 | X116: =U116/V116 -> 5.5819054 | Y116: =X116/S116 -> 5.3466527 | Z116: 102.503 | AA116: 112414 | AB116: =O116*P116/S116 -> 852.20946 | AC116: =Q116*R116/S116 -> 327.77741 | AD116: 76.23 | AE116: =E116 -> 2263054.5 | AF116: =F116/H116 -> 12610.635 | AG116: =G116/H116 -> 4903.2056 | AH116: =H116 -> 69.628 | AI116: =+J116 -> 258127.86 | AJ116: =K116/H116 -> 0.91931407 | AK116: =Hours_q!D116 -> 258127.86 | AL116: =100*LN(AE116) -> 1463.2226 | AM116: =AM115*'Core data'!D7/'Core data'!D6 -> 76.116344 | AN116: NaN | AO116: =100*LN(AE116/AI116/(AE115/AI115)) -> 0.30281109 | AP116: =100*LN(AF116/AI116/(AF115/AI115)) -> -0.01941419 | AQ116: =100*LN(AG116/AI116/(AG115/AI115)) -> 1.7004603 | AR116: =100*LN(AH116/AH115) -> -0.2596156 | AS116: =100*LN(AM116/AM115) -> 0.34080515 | AT116: =L116/4 -> 1.0525 | AU116: =100*LN(AJ116/AJ115) -> 0.2596156 | AV116: =Hours_q!H116 -> 0.12846773 | AW116: =AV116-AVERAGE($AV$104:$AV$222) -> 1.0840195 | AX116: NaN | AY116: =+BG116/4 -> 1.279175 | BD116: 4.12 | BE116: --- | BF116: 4.59 | BG116: 5.1167
A117: 2q98 | B117: 0.0039161706 | E117: 2272155.6 | F117: 886086.7 | G117: 342946.5 | H117: 70.004 | J117: =+J118*M117/M118 -> 259172.74 | K117: 64.37 | L117: 4.07 | M117: 151.056 | N117: 1522.618 | O117: 856.01 | P117: 1.05 | Q117: 333.577 | R117: 1.03 | S117: 1.051 | T117: 151.056 | U117: 758.58 | V117: 135.089 | W117: 4.057 | X117: =U117/V117 -> 5.6154091 | Y117: =X117/S117 -> 5.3429202 | Z117: 103.031 | AA117: 113062 | AB117: =O117*P117/S117 -> 855.19553 | AC117: =Q117*R117/S117 -> 326.91181 | AD117: 76.52 | AE117: =E117 -> 2272155.6 | AF117: =F117/H117 -> 12657.658 | AG117: =G117/H117 -> 4898.9558 | AH117: =H117 -> 70.004 | AI117: =+J117 -> 259172.74 | AJ117: =K117/H117 -> 0.91951888 | AK117: =Hours_q!D117 -> 259172.74 | AL117: =100*LN(AE117) -> 1463.624 | AM117: =AM116*'Core data'!D8/'Core data'!D7 -> 76.454993 | AN117: NaN | AO117: =100*LN(AE117/AI117/(AE116/AI116)) -> -0.00262313 | AP117: =100*LN(AF117/AI117/(AF116/AI116)) -> -0.031786087 | AQ117: =100*LN(AG117/AI117/(AG116/AI116)) -> -0.4906888 | AR117: =100*LN(AH117/AH116) -> 0.5385598 | AS117: =100*LN(AM117/AM116) -> 0.44392291 | AT117: =L117/4 -> 1.0175 | AU117: =100*LN(AJ117/AJ116) -> 0.022276693 | AV117: =Hours_q!H117 -> 0.42077803 | AW117: =AV117-AVERAGE($AV$104:$AV$222) -> 1.3763298 | AX117: NaN | AY117: =+BG117/4 -> 1.2475 | BD117: 4.1567 | BE117: --- | BF117: 4.61 | BG117: 4.99
A118: 3q98 | B118: 0.15620193 | E118: 2284266.3 | F118: 899205.2 | G118: 350341.3 | H118: 70.332 | J118: =+J119*M118/M119 -> 260227.92 | K118: 64.66 | L118: 3.95 | M118: 151.671 | N118: 1531.207 | O118: 863.891 | P118: 1.053 | Q118: 339.629 | R118: 1.032 | S118: 1.053 | T118: 151.671 | U118: 767.865 | V118: 135.88 | W118: 3.937 | X118: =U118/V118 -> 5.6510524 | Y118: =X118/S118 -> 5.3666215 | Z118: 103.433 | AA118: 113770 | AB118: =O118*P118/S118 -> 863.891 | AC118: =Q118*R118/S118 -> 332.85577 | AD118: 76.78 | AE118: =E118 -> 2284266.3 | AF118: =F118/H118 -> 12785.15 | AG118: =G118/H118 -> 4981.2504 | AH118: =H118 -> 70.332 | AI118: =+J118 -> 260227.92 | AJ118: =K118/H118 -> 0.91935392 | AK118: =Hours_q!D118 -> 260227.92 | AL118: =100*LN(AE118) -> 1464.1555 | AM118: =AM117*'Core data'!D9/'Core data'!D8 -> 76.704 | AN118: NaN | AO118: =100*LN(AE118/AI118/(AE117/AI117)) -> 0.1252822 | AP118: =100*LN(AF118/AI118/(AF117/AI117)) -> 0.59588844 | AQ118: =100*LN(AG118/AI118/(AG117/AI117)) -> 1.2595788 | AR118: =100*LN(AH118/AH117) -> 0.4674504 | AS118: =100*LN(AM118/AM117) -> 0.32516124 | AT118: =L118/4 -> 0.9875 | AU118: =100*LN(AJ118/AJ117) -> -0.017941778 | AV118: =Hours_q!H118 -> 0.6817229 | AW118: =AV118-AVERAGE($AV$104:$AV$222) -> 1.6372747 | AX118: NaN | AY118: =+BG118/4 -> 1.14 | BD118: 3.7567 | BE118: --- | BF118: 4.0633 | BG118: 4.56
A119: 4q98 | B119: 0.018648486 | E119: 2290929.2 | F119: 913433.5 | G119: 356104.8 | H119: 71.052 | J119: =+J120*M119/M120 -> 260886.77 | K119: 65.03 | L119: 3.66 | M119: 152.055 | N119: 1535.37 | O119: 871.828 | P119: 1.054 | Q119: 342.902 | R119: 1.034 | S119: 1.057 | T119: 152.055 | U119: 775.881 | V119: 136.446 | W119: 3.623 | X119: =U119/V119 -> 5.6863594 | Y119: =X119/S119 -> 5.3797156 | Z119: 103.649 | AA119: 114344 | AB119: =O119*P119/S119 -> 869.35356 | AC119: =Q119*R119/S119 -> 335.44056 | AD119: 76.98 | AE119: =E119 -> 2290929.2 | AF119: =F119/H119 -> 12855.845 | AG119: =G119/H119 -> 5011.8899 | AH119: =H119 -> 71.052 | AI119: =+J119 -> 260886.77 | AJ119: =K119/H119 -> 0.91524517 | AK119: =Hours_q!D119 -> 260886.77 | AL119: =100*LN(AE119) -> 1464.4468 | AM119: =AM118*'Core data'!D10/'Core data'!D9 -> 76.913166 | AN119: NaN | AO119: =100*LN(AE119/AI119/(AE118/AI118)) -> 0.038402457 | AP119: =100*LN(AF119/AI119/(AF118/AI118)) -> 0.29856019 | AQ119: =100*LN(AG119/AI119/(AG118/AI118)) -> 0.36035351 | AR119: =100*LN(AH119/AH118) -> 1.0185116 | AS119: =100*LN(AM119/AM118) -> 0.27232073 | AT119: =L119/4 -> 0.915 | AU119: =100*LN(AJ119/AJ118) -> -0.44791865 | AV119: =Hours_q!H119 -> 0.34800412 | AW119: =AV119-AVERAGE($AV$104:$AV$222) -> 1.3035559 | AX119: NaN | AY119: =+BG119/4 -> 1.036675 | BD119: 3.2933 | BE119: --- | BF119: 3.59 | BG119: 4.1467
A120: 1q99 | B120: 0.6985643 | D120: 1.9 | E120: 2314189.8 | F120: 921522.7 | G120: 362463.3 | H120: 71.216 | J120: =+J121*M120/M121 -> 261324.28 | K120: 65.14 | L120: 3.11 | M120: 152.31 | N120: 1548.726 | O120: 877.51 | P120: 1.054 | Q120: 349.384 | R120: 1.033 | S120: 1.058 | T120: 152.31 | U120: 781.582 | V120: 137.085 | W120: 3.089 | X120: =U120/V120 -> 5.7014407 | Y120: =X120/S120 -> 5.3888854 | Z120: 103.891 | AA120: 115025 | AB120: =O120*P120/S120 -> 874.19238 | AC120: =Q120*R120/S120 -> 341.12823 | AD120: 77.17 | AE120: =E120 -> 2314189.8 | AF120: =F120/H120 -> 12939.827 | AG120: =G120/H120 -> 5089.6329 | AH120: =H120 -> 71.216 | AI120: =+J120 -> 261324.28 | AJ120: =K120/H120 -> 0.91468209 | AK120: =Hours_q!D120 -> 261324.28 | AL120: =100*LN(AE120) -> 1465.457 | AM120: =AM119*'Core data'!D11/'Core data'!D10 -> 77.042649 | AN120: NaN | AO120: =100*LN(AE120/AI120/(AE119/AI119)) -> 0.84265283 | AP120: =100*LN(AF120/AI120/(AF119/AI119)) -> 0.48357053 | AQ120: =100*LN(AG120/AI120/(AG119/AI119)) -> 1.3717029 | AR120: =100*LN(AH120/AH119) -> 0.23055089 | AS120: =100*LN(AM120/AM119) -> 0.16820862 | AT120: =L120/4 -> 0.7775 | AU120: =100*LN(AJ120/AJ119) -> -0.061541097 | AV120: =Hours_q!H120 -> 0.27553228 | AW120: =AV120-AVERAGE($AV$104:$AV$222) -> 1.2310841 | AX120: =+D120/4 -> 0.475 | AY120: =+BG120/4 -> 0.9981 | BD120: 3.0437 | BE120: --- | BF120: 3.4206 | BG120: 3.9924
A121: 2q99 | B121: 0.3741608 | D121: --- | E121: 2325263.4 | F121: 932602.5 | G121: 369659.8 | H121: 71.364 | J121: =+J122*M121/M122 -> 262084.35 | K121: 65.76 | L121: 2.62 | M121: 152.753 | N121: 1559.053 | O121: 883.766 | P121: 1.058 | Q121: 354.344 | R121: 1.036 | S121: 1.061 | T121: 152.753 | U121: 793.446 | V121: 137.67 | W121: 2.635 | X121: =U121/V121 -> 5.7633907 | Y121: =X121/S121 -> 5.4320365 | Z121: 104.071 | AA121: 115661 | AB121: =O121*P121/S121 -> 881.26713 | AC121: =Q121*R121/S121 -> 345.99471 | AD121: 77.35 | AE121: =E121 -> 2325263.4 | AF121: =F121/H121 -> 13068.249 | AG121: =G121/H121 -> 5179.9198 | AH121: =H121 -> 71.364 | AI121: =+J121 -> 262084.35 | AJ121: =K121/H121 -> 0.92147301 | AK121: =Hours_q!D121 -> 262084.35 | AL121: =100*LN(AE121) -> 1465.9344 | AM121: =AM120*'Core data'!D12/'Core data'!D11 -> 77.251815 | AN121: NaN | AO121: =100*LN(AE121/AI121/(AE120/AI120)) -> 0.18693549 | AP121: =100*LN(AF121/AI121/(AF120/AI120)) -> 0.69713061 | AQ121: =100*LN(AG121/AI121/(AG120/AI120)) -> 1.4679547 | AR121: =100*LN(AH121/AH120) -> 0.20760282 | AS121: =100*LN(AM121/AM120) -> 0.27112534 | AT121: =L121/4 -> 0.655 | AU121: =100*LN(AJ121/AJ120) -> 0.73969227 | AV121: =Hours_q!H121 -> 1.0526453 | AW121: =AV121-AVERAGE($AV$104:$AV$222) -> 2.0081971 | AX121: NaN | AY121: =+BG121/4 -> 1.06435 | BD121: 2.9017 | BE121: --- | BF121: 3.481 | BG121: 4.2574
A122: 3q99 | B122: 0.72478128 | D122: --- | E122: 2355676.7 | F122: 945895.3 | G122: 377147.8 | H122: 71.429 | J122: =+J123*M122/M123 -> 263064.04 | K122: 66.1 | L122: 2.61 | M122: 153.324 | N122: 1576.264 | O122: 892.321 | P122: 1.063 | Q122: 360.39 | R122: 1.041 | S122: 1.064 | T122: 153.324 | U122: 803.552 | V122: 138.432 | W122: 2.699 | X122: =U122/V122 -> 5.8046694 | Y122: =X122/S122 -> 5.4555164 | Z122: 104.273 | AA122: 116417 | AB122: =O122*P122/S122 -> 891.48235 | AC122: =Q122*R122/S122 -> 352.59961 | AD122: 77.55 | AE122: =E122 -> 2355676.7 | AF122: =F122/H122 -> 13242.455 | AG122: =G122/H122 -> 5280.0375 | AH122: =H122 -> 71.429 | AI122: =+J122 -> 263064.04 | AJ122: =K122/H122 -> 0.92539445 | AK122: =Hours_q!D122 -> 263064.04 | AL122: =100*LN(AE122) -> 1467.2339 | AM122: =AM121*'Core data'!D13/'Core data'!D12 -> 77.45102 | AN122: NaN | AO122: =100*LN(AE122/AI122/(AE121/AI121)) -> 0.92636177 | AP122: =100*LN(AF122/AI122/(AF121/AI121)) -> 0.95113209 | AQ122: =100*LN(AG122/AI122/(AG121/AI121)) -> 1.5412529 | AR122: =100*LN(AH122/AH121) -> 0.091040884 | AS122: =100*LN(AM122/AM121) -> 0.25753298 | AT122: =L122/4 -> 0.6525 | AU122: =100*LN(AJ122/AJ121) -> 0.42465873 | AV122: =Hours_q!H122 -> 0.6081094 | AW122: =AV122-AVERAGE($AV$104:$AV$222) -> 1.5636612 | AX122: NaN | AY122: =+BG122/4 -> 1.262675 | BD122: 3.5044 | BE122: --- | BF122: 4.3548 | BG122: 5.0507
A123: 4q99 | B123: 0.99600255 | D123: --- | E123: 2380371.3 | F123: 957350.6 | G123: 381383.4 | H123: 71.654 | J123: =+J124*M123/M124 -> 263779.5 | K123: 66.65 | L123: 3.11 | M123: 153.741 | N123: 1596.372 | O123: 900.458 | P123: 1.067 | Q123: 363.879 | R123: 1.046 | S123: 1.067 | T123: 153.741 | U123: 813.553 | V123: 139.084 | W123: 3.431 | X123: =U123/V123 -> 5.8493644 | Y123: =X123/S123 -> 5.482066 | Z123: 104.569 | AA123: 117021 | AB123: =O123*P123/S123 -> 900.458 | AC123: =Q123*R123/S123 -> 356.71737 | AD123: 77.71 | AE123: =E123 -> 2380371.3 | AF123: =F123/H123 -> 13360.742 | AG123: =G123/H123 -> 5322.5696 | AH123: =H123 -> 71.654 | AI123: =+J123 -> 263779.5 | AJ123: =K123/H123 -> 0.9301644 | AK123: =Hours_q!D123 -> 263779.5 | AL123: =100*LN(AE123) -> 1468.2767 | AM123: =AM122*'Core data'!D14/'Core data'!D13 -> 77.680106 | AN123: NaN | AO123: =100*LN(AE123/AI123/(AE122/AI122)) -> 0.77124127 | AP123: =100*LN(AF123/AI123/(AF122/AI122)) -> 0.61767219 | AQ123: =100*LN(AG123/AI123/(AG122/AI122)) -> 0.5306946 | AR123: =100*LN(AH123/AH122) -> 0.31450303 | AS123: =100*LN(AM123/AM122) -> 0.29534532 | AT123: =L123/4 -> 0.7775 | AU123: =100*LN(AJ123/AJ122) -> 0.51412695 | AV123: =Hours_q!H123 -> 0.92572206 | AW123: =AV123-AVERAGE($AV$104:$AV$222) -> 1.8812739 | AX123: NaN | AY123: =+BG123/4 -> 1.330025 | BD123: 4.0791 | BE123: --- | BF123: 4.7757 | BG123: 5.3201
A124: 1q00 | B124: 0.64310813 | D124: 1.8 | E124: 2411243.3 | F124: 973681.2 | G124: 394894.9 | H124: 71.987 | J124: =+J125*M124/M125 -> 265026.85 | K124: 67.13 | L124: 3.37 | M124: 154.468 | N124: 1614.269 | O124: 907.468 | P124: 1.076 | Q124: 370.449 | R124: 1.055 | S124: 1.071 | T124: 154.468 | U124: 825.74 | V124: 140.143 | W124: 3.549 | X124: =U124/V124 -> 5.8921245 | Y124: =X124/S124 -> 5.5015168 | Z124: 104.809 | AA124: 118076 | AB124: =O124*P124/S124 -> 911.70455 | AC124: =Q124*R124/S124 -> 364.91475 | AD124: 77.92 | AE124: =E124 -> 2411243.3 | AF124: =F124/H124 -> 13525.792 | AG124: =G124/H124 -> 5485.6419 | AH124: =H124 -> 71.987 | AI124: =+J124 -> 265026.85 | AJ124: =K124/H124 -> 0.93252948 | AK124: =Hours_q!D124 -> 265026.85 | AL124: =100*LN(AE124) -> 1469.5653 | AM124: =AM123*'Core data'!D15/'Core data'!D14 -> 77.82951 | AN124: NaN | AO124: =100*LN(AE124/AI124/(AE123/AI123)) -> 0.81684359 | AP124: =100*LN(AF124/AI124/(AF123/AI123)) -> 0.75601082 | AQ124: =100*LN(AG124/AI124/(AG123/AI123)) -> 2.5460331 | AR124: =100*LN(AH124/AH123) -> 0.46365675 | AS124: =100*LN(AM124/AM123) -> 0.19214763 | AT124: =L124/4 -> 0.8425 | AU124: =100*LN(AJ124/AJ123) -> 0.25394238 | AV124: =Hours_q!H124 -> 1.085029 | AW124: =AV124-AVERAGE($AV$104:$AV$222) -> 2.0405808 | AX124: =+D124/4 -> 0.45 | AY124: =+BG124/4 -> 1.4044 | BD124: 4.5044 | BE124: --- | BF124: 5.1627 | BG124: 5.6176
A125: 2q00 | B125: 0.60223992 | D125: --- | E125: 2432839.9 | F125: 985871.5 | G125: 396684.3 | H125: 72.163 | J125: =+J126*M125/M126 -> 265831.53 | K125: 67.45 | L125: 4.11 | M125: 154.937 | N125: 1628.951 | O125: 915.028 | P125: 1.081 | Q125: 373.072 | R125: 1.064 | S125: 1.074 | T125: 154.937 | U125: 835.079 | V125: 140.931 | W125: 4.285 | X125: =U125/V125 -> 5.9254458 | Y125: =X125/S125 -> 5.5171748 | Z125: 105.017 | AA125: 118804 | AB125: =O125*P125/S125 -> 920.99187 | AC125: =Q125*R125/S125 -> 369.59833 | AD125: 78.04 | AE125: =E125 -> 2432839.9 | AF125: =F125/H125 -> 13661.731 | AG125: =G125/H125 -> 5497.0594 | AH125: =H125 -> 72.163 | AI125: =+J125 -> 265831.53 | AJ125: =K125/H125 -> 0.93468952 | AK125: =Hours_q!D125 -> 265831.53 | AL125: =100*LN(AE125) -> 1470.457 | AM125: =AM124*'Core data'!D16/'Core data'!D15 -> 77.968954 | AN125: NaN | AO125: =100*LN(AE125/AI125/(AE124/AI124)) -> 0.5885124 | AP125: =100*LN(AF125/AI125/(AF124/AI124)) -> 0.6968552 | AQ125: =100*LN(AG125/AI125/(AG124/AI124)) -> -0.095243287 | AR125: =100*LN(AH125/AH124) -> 0.2441902 | AS125: =100*LN(AM125/AM124) -> 0.17900529 | AT125: =L125/4 -> 1.0275 | AU125: =100*LN(AJ125/AJ124) -> 0.23136427 | AV125: =Hours_q!H125 -> 1.0707612 | AW125: =AV125-AVERAGE($AV$104:$AV$222) -> 2.026313 | AX125: NaN | AY125: =+BG125/4 -> 1.356225 | BD125: 4.8662 | BE125: --- | BF125: 5.1969 | BG125: 5.4249
A126: 3q00 | B126: 0.20681069 | D126: --- | E126: 2449229.5 | F126: 997000.7 | G126: 401901.5 | H126: 72.546 | J126: =+J127*M126/M127 -> 266663.66 | K126: 68.03 | L126: 4.56 | M126: 155.422 | N126: 1637.433 | O126: 919.142 | P126: 1.09 | Q126: 377.39 | R126: 1.069 | S126: 1.081 | T126: 155.422 | U126: 846.615 | V126: 141.615 | W126: 4.739 | X126: =U126/V126 -> 5.9782862 | Y126: =X126/S126 -> 5.5303295 | Z126: 105.53 | AA126: 119386 | AB126: =O126*P126/S126 -> 926.79443 | AC126: =Q126*R126/S126 -> 373.20066 | AD126: 78.34 | AE126: =E126 -> 2449229.5 | AF126: =F126/H126 -> 13743.014 | AG126: =G126/H126 -> 5539.954 | AH126: =H126 -> 72.546 | AI126: =+J126 -> 266663.66 | AJ126: =K126/H126 -> 0.93774984 | AK126: =Hours_q!D126 -> 266663.66 | AL126: =100*LN(AE126) -> 1471.1284 | AM126: =AM125*'Core data'!D17/'Core data'!D16 -> 78.21796 | AN126: NaN | AO126: =100*LN(AE126/AI126/(AE125/AI125)) -> 0.35888118 | AP126: =100*LN(AF126/AI126/(AF125/AI125)) -> 0.28066409 | AQ126: =100*LN(AG126/AI126/(AG125/AI125)) -> 0.46474739 | AR126: =100*LN(AH126/AH125) -> 0.52933943 | AS126: =100*LN(AM126/AM125) -> 0.31885749 | AT126: =L126/4 -> 1.14 | AU126: =100*LN(AJ126/AJ125) -> 0.32688075 | AV126: =Hours_q!H126 -> 1.0851614 | AW126: =AV126-AVERAGE($AV$104:$AV$222) -> 2.0407133 | AX126: NaN | AY126: =+BG126/4 -> 1.359925 | BD126: 5.2317 | BE126: --- | BF126: 5.3333 | BG126: 5.4397
A127: 4q00 | B127: 0.64394163 | D127: --- | E127: 2460374.5 | F127: 1007203.3 | G127: 407193.9 | H127: 72.973 | J127: =+J128*M127/M128 -> 267092.6 | K127: 68.49 | L127: 4.91 | M127: 155.672 | N127: 1650.662 | O127: 920.336 | P127: 1.097 | Q127: 378.367 | R127: 1.077 | S127: 1.085 | T127: 155.672 | U127: 855.904 | V127: 142.221 | W127: 5.028 | X127: =U127/V127 -> 6.0181267 | Y127: =X127/S127 -> 5.5466606 | Z127: 106.089 | AA127: 119934 | AB127: =O127*P127/S127 -> 930.51483 | AC127: =Q127*R127/S127 -> 375.5772 | AD127: 78.65 | AE127: =E127 -> 2460374.5 | AF127: =F127/H127 -> 13802.41 | AG127: =G127/H127 -> 5580.0625 | AH127: =H127 -> 72.973 | AI127: =+J127 -> 267092.6 | AJ127: =K127/H127 -> 0.93856632 | AK127: =Hours_q!D127 -> 267092.6 | AL127: =100*LN(AE127) -> 1471.5824 | AM127: =AM126*'Core data'!D18/'Core data'!D17 -> 78.536689 | AN127: NaN | AO127: =100*LN(AE127/AI127/(AE126/AI126)) -> 0.29328572 | AP127: =100*LN(AF127/AI127/(AF126/AI126)) -> 0.27053892 | AQ127: =100*LN(AG127/AI127/(AG126/AI126)) -> 0.56065532 | AR127: =100*LN(AH127/AH126) -> 0.58686663 | AS127: =100*LN(AM127/AM126) -> 0.4066596 | AT127: =L127/4 -> 1.2275 | AU127: =100*LN(AJ127/AJ126) -> 0.087029855 | AV127: =Hours_q!H127 -> 1.2939443 | AW127: =AV127-AVERAGE($AV$104:$AV$222) -> 2.2494962 | AX127: NaN | AY127: =+BG127/4 -> 1.318325 | BD127: 5.0072 | BE127: --- | BF127: 5.0847 | BG127: 5.2733
A128: 1q01 | B128: 0.7868754 | D128: 1.8 | E128: 2487618.5 | F128: 1020974.3 | G128: 413221.8 | H128: 73.516 | J128: =+J129*M128/M129 -> 267185.25 | K128: 68.86 | L128: 4.79 | M128: 155.726 | N128: 1664.279 | O128: 929.783 | P128: 1.102 | Q128: 380.796 | R128: 1.078 | S128: 1.094 | T128: 155.726 | U128: 864.461 | V128: 142.605 | W128: 4.745 | X128: =U128/V128 -> 6.0619263 | Y128: =X128/S128 -> 5.5410661 | Z128: 106.636 | AA128: 120365 | AB128: =O128*P128/S128 -> 936.58214 | AC128: =Q128*R128/S128 -> 375.22677 | AD128: 78.99 | AE128: =E128 -> 2487618.5 | AF128: =F128/H128 -> 13887.784 | AG128: =G128/H128 -> 5620.8417 | AH128: =H128 -> 73.516 | AI128: =+J128 -> 267185.25 | AJ128: =K128/H128 -> 0.93666685 | AK128: =Hours_q!D128 -> 267185.25 | AL128: =100*LN(AE128) -> 1472.6836 | AM128: =AM127*'Core data'!D19/'Core data'!D18 -> 78.765775 | AN128: NaN | AO128: =100*LN(AE128/AI128/(AE127/AI127)) -> 1.066543 | AP128: =100*LN(AF128/AI128/(AF127/AI127)) -> 0.58195044 | AQ128: =100*LN(AG128/AI128/(AG127/AI127)) -> 0.69346271 | AR128: =100*LN(AH128/AH127) -> 0.74135599 | AS128: =100*LN(AM128/AM127) -> 0.29126849 | AT128: =L128/4 -> 1.1975 | AU128: =100*LN(AJ128/AJ127) -> -0.20258512 | AV128: =Hours_q!H128 -> 1.4817937 | AW128: =AV128-AVERAGE($AV$104:$AV$222) -> 2.4373456 | AX128: =+D128/4 -> 0.45 | AY128: =+BG128/4 -> 1.247275 | BD128: 4.461 | BE128: --- | BF128: 4.6388 | BG128: 4.9891
A129: 2q01 | B129: 0.09277619 | D129: 1.8 | E129: 2489052.7 | F129: 1031545.6 | G129: 411109.2 | H129: 73.987 | J129: =+J130*M129/M130 -> 267348.24 | K129: 69.34 | L129: 4.66 | M129: 155.821 | N129: 1666.84 | O129: 932.767 | P129: 1.111 | Q129: 380.58 | R129: 1.082 | S129: 1.101 | T129: 155.821 | U129: 872.475 | V129: 142.782 | W129: 4.589 | X129: =U129/V129 -> 6.1105391 | Y129: =X129/S129 -> 5.5499901 | Z129: 107.692 | AA129: 120542 | AB129: =O129*P129/S129 -> 941.239 | AC129: =Q129*R129/S129 -> 374.01232 | AD129: 79.51 | AE129: =E129 -> 2489052.7 | AF129: =F129/H129 -> 13942.255 | AG129: =G129/H129 -> 5556.5059 | AH129: =H129 -> 73.987 | AI129: =+J129 -> 267348.24 | AJ129: =K129/H129 -> 0.93719167 | AK129: =Hours_q!D129 -> 267348.24 | AL129: =100*LN(AE129) -> 1472.7413 | AM129: =AM128*'Core data'!D20/'Core data'!D19 -> 79.204026 | AN129: NaN | AO129: =100*LN(AE129/AI129/(AE128/AI128)) -> -0.0033490631 | AP129: =100*LN(AF129/AI129/(AF128/AI128)) -> 0.33047002 | AQ129: =100*LN(AG129/AI129/(AG128/AI128)) -> -1.2121815 | AR129: =100*LN(AH129/AH128) -> 0.63863325 | AS129: =100*LN(AM129/AM128) -> 0.5548564 | AT129: =L129/4 -> 1.165 | AU129: =100*LN(AJ129/AJ128) -> 0.056014985 | AV129: =Hours_q!H129 -> 1.1612935 | AW129: =AV129-AVERAGE($AV$104:$AV$222) -> 2.1168453 | AX129: =+D129/4 -> 0.45 | AY129: =+BG129/4 -> 1.297675 | BD129: 4.4344 | BE129: --- | BF129: 4.7193 | BG129: 5.1907
A130: 3q01 | B130: -0.11666327 | D130: 1.8 | E130: 2494152 | F130: 1038465.7 | G130: 407906 | H130: 74.433 | J130: =+J131*M130/M131 -> 267868.11 | K130: 69.8 | L130: 4.34 | M130: 156.124 | N130: 1668.134 | O130: 935.629 | P130: 1.116 | Q130: 378.789 | R130: 1.085 | S130: 1.108 | T130: 156.124 | U130: 881.025 | V130: 143.051 | W130: 4.278 | X130: =U130/V130 -> 6.1588175 | Y130: =X130/S130 -> 5.5584995 | Z130: 108.302 | AA130: 120864 | AB130: =O130*P130/S130 -> 942.38444 | AC130: =Q130*R130/S130 -> 370.92605 | AD130: 79.96 | AE130: =E130 -> 2494152 | AF130: =F130/H130 -> 13951.684 | AG130: =G130/H130 -> 5480.1768 | AH130: =H130 -> 74.433 | AI130: =+J130 -> 267868.11 | AJ130: =K130/H130 -> 0.9377561 | AK130: =Hours_q!D130 -> 267868.11 | AL130: =100*LN(AE130) -> 1472.9459 | AM130: =AM129*'Core data'!D21/'Core data'!D20 -> 79.712 | AN130: NaN | AO130: =100*LN(AE130/AI130/(AE129/AI129)) -> 0.010394459 | AP130: =100*LN(AF130/AI130/(AF129/AI129)) -> -0.12665652 | AQ130: =100*LN(AG130/AI130/(AG129/AI129)) -> -1.5774757 | AR130: =100*LN(AH130/AH129) -> 0.60099898 | AS130: =100*LN(AM130/AM129) -> 0.6393002 | AT130: =L130/4 -> 1.085 | AU130: =100*LN(AJ130/AJ129) -> 0.060207972 | AV130: =Hours_q!H130 -> 1.0261718 | AW130: =AV130-AVERAGE($AV$104:$AV$222) -> 1.9817236 | AX130: =+D130/4 -> 0.45 | AY130: =+BG130/4 -> 1.2788 | BD130: 4.0691 | BE130: --- | BF130: 4.4938 | BG130: 5.1152
A131: 4q01 | B131: -0.039311133 | D131: 1.8 | E131: 2493131.5 | F131: 1046449.2 | G131: 410474.4 | H131: 75.029 | J131: =+J132*M131/M132 -> 268568.13 | K131: 70.34 | L131: 3.52 | M131: 156.532 | N131: 1671.836 | O131: 935.616 | P131: 1.119 | Q131: 377.586 | R131: 1.089 | S131: 1.115 | T131: 156.532 | U131: 889.067 | V131: 143.302 | W131: 3.452 | X131: =U131/V131 -> 6.2041493 | Y131: =X131/S131 -> 5.5642594 | Z131: 109.025 | AA131: 121080 | AB131: =O131*P131/S131 -> 938.97247 | AC131: =Q131*R131/S131 -> 368.7813 | AD131: 80.51 | AE131: =E131 -> 2493131.5 | AF131: =F131/H131 -> 13947.263 | AG131: =G131/H131 -> 5470.8766 | AH131: =H131 -> 75.029 | AI131: =+J131 -> 268568.13 | AJ131: =K131/H131 -> 0.93750417 | AK131: =Hours_q!D131 -> 268568.13 | AL131: =100*LN(AE131) -> 1472.905 | AM131: =AM130*'Core data'!D22/'Core data'!D21 -> 80.200053 | AN131: NaN | AO131: =100*LN(AE131/AI131/(AE130/AI130)) -> -0.30191394 | AP131: =100*LN(AF131/AI131/(AF130/AI130)) -> -0.29268286 | AQ131: =100*LN(AG131/AI131/(AG130/AI130)) -> -0.43084039 | AR131: =100*LN(AH131/AH130) -> 0.79753136 | AS131: =100*LN(AM131/AM130) -> 0.61040364 | AT131: =L131/4 -> 0.88 | AU131: =100*LN(AJ131/AJ130) -> -0.02686963 | AV131: =Hours_q!H131 -> 0.85737757 | AW131: =AV131-AVERAGE($AV$104:$AV$222) -> 1.8129294 | AX131: =+D131/4 -> 0.45 | AY131: =+BG131/4 -> 1.203525 | BD131: 3.4846 | BE131: --- | BF131: 4.1198 | BG131: 4.8141
A132: 1q02 | B132: -0.25626836 | D132: 1.9 | E132: 2498183.4 | F132: 1053918.9 | G132: 408745.1 | H132: 75.543 | J132: =+J133*M132/M133 -> 269552.97 | K132: 70.71 | L132: 3.35 | M132: 157.106 | N132: 1673.672 | O132: 937.067 | P132: 1.125 | Q132: 376.468 | R132: 1.095 | S132: 1.124 | T132: 157.106 | U132: 897.498 | V132: 143.791 | W132: 3.361 | X132: =U132/V132 -> 6.2416841 | Y132: =X132/S132 -> 5.5530997 | Z132: 109.887 | AA132: 121550 | AB132: =O132*P132/S132 -> 937.90069 | AC132: =Q132*R132/S132 -> 366.75486 | AD132: 81.04 | AE132: =E132 -> 2498183.4 | AF132: =F132/H132 -> 13951.245 | AG132: =G132/H132 -> 5410.7608 | AH132: =H132 -> 75.543 | AI132: =+J132 -> 269552.97 | AJ132: =K132/H132 -> 0.93602319 | AK132: =Hours_q!D132 -> 269552.97 | AL132: =100*LN(AE132) -> 1473.1074 | AM132: =AM131*'Core data'!D23/'Core data'!D22 -> 80.82755 | AN132: NaN | AO132: =100*LN(AE132/AI132/(AE131/AI131)) -> -0.16359979 | AP132: =100*LN(AF132/AI132/(AF131/AI131)) -> -0.33748167 | AQ132: =100*LN(AG132/AI132/(AG131/AI131)) -> -1.470943 | AR132: =100*LN(AH132/AH131) -> 0.68273251 | AS132: =100*LN(AM132/AM131) -> 0.77936932 | AT132: =L132/4 -> 0.8375 | AU132: =100*LN(AJ132/AJ131) -> -0.15809465 | AV132: =Hours_q!H132 -> 0.44783579 | AW132: =AV132-AVERAGE($AV$104:$AV$222) -> 1.4033876 | AX132: =+D132/4 -> 0.475 | AY132: =+BG132/4 -> 1.2838 | AZ132: 1553509 | BA132: 296624 | BB132: 1850106 | BC132: =+BB132/AH132 -> 24490.767 | BD132: 4.0163 | BE132: --- | BF132: 4.6573 | BG132: 5.1352
A133: 2q02 | B133: 0.2691611 | D133: 1.9 | E133: 2510461.8 | F133: 1059370.5 | G133: 409392.4 | H133: 75.817 | I133: 270199.8 | J133: =+I133 -> 270199.8 | K133: 71.16 | L133: 3.36 | M133: 157.483 | N133: 1682.21 | O133: 938.459 | P133: 1.131 | Q133: 372.722 | R133: 1.099 | S133: 1.128 | T133: 157.483 | U133: 903.758 | V133: 143.986 | W133: 3.446 | X133: =U133/V133 -> 6.2767075 | Y133: =X133/S133 -> 5.564457 | Z133: 110.412 | AA133: 121729 | AB133: =O133*P133/S133 -> 940.9549 | AC133: =Q133*R133/S133 -> 363.13961 | AD133: 81.51 | AE133: =E133 -> 2510461.8 | AF133: =F133/H133 -> 13972.73 | AG133: =G133/H133 -> 5399.7441 | AH133: =H133 -> 75.817 | AI133: =+J133 -> 270199.8 | AJ133: =K133/H133 -> 0.93857578 | AK133: =Hours_q!D133 -> 270199.8 | AL133: =100*LN(AE133) -> 1473.5977 | AM133: =AM132*'Core data'!D24/'Core data'!D23 -> 81.216 | AN133: =100*LN(BC133/AI133/(BC132/AI132)) -> 0.69547567 | AO133: =100*LN(AE133/AI133/(AE132/AI132)) -> 0.25061134 | AP133: =100*LN(AF133/AI133/(AF132/AI132)) -> -0.085792892 | AQ133: =100*LN(AG133/AI133/(AG132/AI132)) -> -0.44349156 | AR133: =100*LN(AH133/AH132) -> 0.36205114 | AS133: =100*LN(AM133/AM132) -> 0.47944034 | AT133: =L133/4 -> 0.84 | AU133: =100*LN(AJ133/AJ132) -> 0.27233458 | AV133: =Hours_q!H133 -> 0.35597458 | AW133: =AV133-AVERAGE($AV$104:$AV$222) -> 1.3115264 | AX133: =+D133/4 -> 0.475 | AY133: =+BG133/4 -> 1.313775 | AZ133: 1574783 | BA133: 299591 | BB133: 1874262 | BC133: =+BB133/AH133 -> 24720.867 | BD133: 4.187 | BE133: --- | BF133: 4.8153 | BG133: 5.2551
A134: 3q02 | B134: 0.098528507 | D134: 1.9 | E134: 2521531 | F134: 1069081.7 | G134: 411392 | H134: 76.336 | I134: 270687.6 | J134: =+I134 -> 270687.6 | K134: 71.68 | L134: 3.34 | M134: 157.952 | N134: 1688.883 | O134: 943.386 | P134: 1.136 | Q134: 374.575 | R134: 1.101 | S134: 1.135 | T134: 157.952 | U134: 912.112 | V134: 144.18 | W134: 3.359 | X134: =U134/V134 -> 6.3262034 | Y134: =X134/S134 -> 5.5737475 | Z134: 110.904 | AA134: 121860 | AB134: =O134*P134/S134 -> 944.21718 | AC134: =Q134*R134/S134 -> 363.35425 | AD134: 81.96 | AE134: =E134 -> 2521531 | AF134: =F134/H134 -> 14004.948 | AG134: =G134/H134 -> 5389.2266 | AH134: =H134 -> 76.336 | AI134: =+J134 -> 270687.6 | AJ134: =K134/H134 -> 0.9390065 | AK134: =Hours_q!D134 -> 270687.6 | AL134: =100*LN(AE134) -> 1474.0377 | AM134: =AM133*'Core data'!D25/'Core data'!D24 -> 81.664212 | AN134: =100*LN(BC134/AI134/(BC133/AI133)) -> 0.15703327 | AO134: =100*LN(AE134/AI134/(AE133/AI133)) -> 0.25958334 | AP134: =100*LN(AF134/AI134/(AF133/AI133)) -> 0.049938196 | AQ134: =100*LN(AG134/AI134/(AG133/AI133)) -> -0.3753388 | AR134: =100*LN(AH134/AH133) -> 0.68221069 | AS134: =100*LN(AM134/AM133) -> 0.55035912 | AT134: =L134/4 -> 0.835 | AU134: =100*LN(AJ134/AJ133) -> 0.0458799 | AV134: =Hours_q!H134 -> 0.13202623 | AW134: =AV134-AVERAGE($AV$104:$AV$222) -> 1.0875781 | AX134: =+D134/4 -> 0.475 | AY134: =+BG134/4 -> 1.19015 | AZ134: 1591090 | BA134: 302407 | BB134: 1893470 | BC134: =+BB134/AH134 -> 24804.417 | BD134: 3.4873 | BE134: --- | BF134: 4.161 | BG134: 4.7606
A135: 4q02 | B135: -0.016087256 | D135: 1.9 | E135: 2526378.9 | F135: 1080847.7 | G135: 415862.9 | H135: 76.686 | I135: 271198 | J135: =+I135 -> 271198 | K135: 72.13 | L135: 3.17 | M135: 158.244 | N135: 1691.733 | O135: 949.027 | P135: 1.142 | Q135: 376.243 | R135: 1.107 | S135: 1.141 | T135: 158.244 | U135: 917.981 | V135: 144.212 | W135: 3.116 | X135: =U135/V135 -> 6.3654966 | Y135: =X135/S135 -> 5.5788752 | Z135: 111.451 | AA135: 121935 | AB135: =O135*P135/S135 -> 949.85875 | AC135: =Q135*R135/S135 -> 365.03155 | AD135: 82.36 | AE135: =E135 -> 2526378.9 | AF135: =F135/H135 -> 14094.459 | AG135: =G135/H135 -> 5422.9312 | AH135: =H135 -> 76.686 | AI135: =+J135 -> 271198 | AJ135: =K135/H135 -> 0.94058889 | AK135: =Hours_q!D135 -> 271198 | AL135: =100*LN(AE135) -> 1474.2298 | AM135: =AM134*'Core data'!D26/'Core data'!D25 -> 82.032742 | AN135: =100*LN(BC135/AI135/(BC134/AI134)) -> -0.35730688 | AO135: =100*LN(AE135/AI135/(AE134/AI134)) -> 0.0036962948 | AP135: =100*LN(AF135/AI135/(AF134/AI134)) -> 0.44872784 | AQ135: =100*LN(AG135/AI135/(AG134/AI134)) -> 0.43508008 | AR135: =100*LN(AH135/AH134) -> 0.45745136 | AS135: =100*LN(AM135/AM134) -> 0.45025936 | AT135: =L135/4 -> 0.7925 | AU135: =100*LN(AJ135/AJ134) -> 0.16837642 | AV135: =Hours_q!H135 -> -0.073051488 | AW135: =AV135-AVERAGE($AV$104:$AV$222) -> 0.88250033 | AX135: =+D135/4 -> 0.475 | AY135: =+BG135/4 -> 1.1352 | AZ135: 1593613 | BA135: 305233 | BB135: 1898941 | BC135: =+BB135/AH135 -> 24762.551 | BD135: 3.0024 | BE135: --- | BF135: 3.7646 | BG135: 4.5408
...

Sheet Hours_q
C1: Haver | F1: Quarterly generated from annual
C2: J025OETE@EUDATA
C3: Total hours worked | D3: Population | E3: Hours worked per employee | F3: Hours_from Eviews | G3: HOURS | H3: HOURS_demeaned
A4: 1q70 | D4: =Data_input!AI4 -> 211530.09
A5: 2q70 | D5: =Data_input!AI5 -> 211605.58
A6: 3q70 | D6: =Data_input!AI6 -> 211988.19
A7: 4q70 | D7: =Data_input!AI7 -> 212329.62
A8: 1q71 | D8: =Data_input!AI8 -> 212761.99
A9: 2q71 | D9: =Data_input!AI9 -> 213376.22
A10: 3q71 | D10: =Data_input!AI10 -> 212751.7
A11: 4q71 | D11: =Data_input!AI11 -> 213022.78
A12: 1q72 | D12: =Data_input!AI12 -> 213492.89
A13: 2q72 | D13: =Data_input!AI13 -> 213633.59
A14: 3q72 | D14: =Data_input!AI14 -> 214136.3
A15: 4q72 | D15: =Data_input!AI15 -> 214757.39
... A63: 4q84 | D63: =Data_input!AI63 -> 231873.61
A64: 1q85 | D64: =Data_input!AI64 -> 232029.74 | F64: 39.454486 | G64: =G65*F64/F65 -> 230.21231 | H64: =LN(G64/AVERAGE($G$64:$G$222))*100 -> 4.6422508 | J64: 3.0362793e+08 | L64: =G64/J64 -> 7.5820532e-07
A65: 2q85 | D65: =Data_input!AI65 -> 232354.02 | F65: 39.423956 | G65: =G66*F65/F66 -> 230.03417 | H65: =LN(G65/AVERAGE($G$64:$G$222))*100 -> 4.5648392 | J65: 3.0366462e+08 | L65: =G65/J65 -> 7.5752708e-07
