Workbook
Name BoxPlot: "BoxPlot"
Name Bubble: "Bubble"
Name Candlestick: "Candlestick"
Name Chart: "Chart"
Name ChartImage: "ChartImage"
Name ColumnRange: "ColumnRange"
Name Dumbbell: "Dumbbell"
Name Heatmap: "Heatmap"
Name Histogram: "Histogram"
Name Map: "Map"
Name OHLC: "OHLC"
Name PieChart: "PieChart"
Name Scatter: "Scatter"
Name Series: "Series"
Name Stripe: "Stripe"
Name Table: "Table"
Name TreeMap: "TreeMap"
Name Waterfall: "Waterfall"

Sheet Chart NA - DSGE Raw Data
A2: date | B2: obs_gdp | C2: obs_gdpdeflator | D2: obs_nominalrate | F2: obs_longinflation | G2: obs_longrate
A3: 21823 | B3: -0.30408411 | C3: 0.38618932 | D3: 0.8925
A4: 21915 | B4: -0.085396239 | C4: 0.3912113 | D4: 0.9975
A5: 22006 | B5: 1.8569299 | C5: 0.39616873 | D5: 0.9825
A6: 22097 | B6: -0.91034251 | C6: 0.25246817 | D6: 0.925
A7: 22189 | B7: 0.12315845 | C7: 0.34207927 | D7: 0.735
A8: 22281 | B8: -1.6584688 | C8: 0.29595338 | D8: 0.575
A9: 22371 | B9: 0.30422427 | C9: 0.21818657 | D9: 0.4975
A10: 22462 | B10: 1.3165542 | C10: 0.23050337 | D10: 0.4325
A11: 22554 | B11: 1.5360756 | C11: 0.25549324 | D11: 0.42
A12: 22646 | B12: 1.5758415 | C12: 0.31209223 | D12: 0.6
A13: 22736 | B13: 1.399261 | C13: 0.51378122 | D13: 0.615
A14: 22827 | B14: 0.52884844 | C14: 0.16435935 | D14: 0.6525
... A50: 26114 | B50: -0.010363799 | C50: 1.3054021 | D50: 1.1425
A51: 26206 | B51: 0.2690258 | C51: 1.0125119 | D51: 1.37 | G51: 1.5257
A52: 26298 | B52: -0.32043651 | C52: 0.83057731 | D52: 1.1875 | G52: 1.491925
A53: 26389 | B53: 1.2602782 | C53: 1.5126649 | D53: 0.8875 | G53: 1.5448
A54: 26480 | B54: 1.6860456 | C54: 0.62055319 | D54: 1.075 | G54: 1.53105
A55: 26572 | B55: 0.3852877 | C55: 0.9507066 | D55: 1.185 | G55: 1.5853
A56: 26664 | B56: 1.1057907 | C56: 1.2670582 | D56: 1.2875 | G56: 1.569
A57: 26754 | B57: 1.8936626 | C57: 1.1457007 | D57: 1.635 | G57: 1.645375
A58: 26845 | B58: 0.53249332 | C58: 1.5276802 | D58: 1.955 | G58: 1.66725
A59: 26937 | B59: -1.06861 | C59: 1.9262302 | D59: 2.64 | G59: 1.690725
A60: 27029 | B60: 0.40548359 | C60: 1.9731808 | D60: 2.5 | G60: 1.684425
A61: 27119 | B61: -1.3981815 | C61: 1.869599 | D61: 2.3325 | G61: 1.835475
A62: 27210 | B62: -0.29322437 | C62: 2.3358372 | D62: 2.8125 | G62: 1.929325
... A83: 29128 | B83: 0.32743149 | C83: 2.1632932 | D83: 2.735 | G83: 2.270025
A84: 29220 | B84: -0.15362911 | C84: 1.8384466 | D84: 3.395 | F84: 1.6 | G84: 2.4906
A85: 29311 | B85: -0.08319259 | C85: 2.0793092 | D85: 3.7675 | G85: 2.978425
A86: 29402 | B86: -2.4706014 | C86: 2.3510302 | D86: 3.1675 | F86: 1.8375 | G86: 2.4489
A87: 29494 | B87: -0.49739301 | C87: 2.2090655 | D87: 2.455 | G87: 2.878775
A88: 29586 | B88: 1.4763561 | C88: 2.5713717 | D88: 3.9625 | F88: 1.9375 | G88: 2.96035
A89: 29676 | B89: 1.5757765 | C89: 2.6000618 | D89: 4.15 | G89: 3.210275
A90: 29767 | B90: -1.0984483 | C90: 1.9622379 | D90: 4.4475 | F90: 1.825 | G90: 3.264225
A91: 29859 | B91: 0.8416346 | C91: 1.8647478 | D91: 4.3975 | G91: 3.723025
A92: 29951 | B92: -1.4356505 | C92: 1.7132211 | D92: 3.3975 | F92: 1.6375 | G92: 3.37825
A93: 30041 | B93: -1.8983795 | C93: 1.3662426 | D93: 3.5525 | G93: 3.342825
A94: 30132 | B94: 0.12845338 | C94: 1.2906547 | D94: 3.6275 | F94: 1.3 | G94: 3.398
A95: 30224 | B95: -0.70404248 | C95: 1.4087662 | D95: 2.7525 | G95: 2.90445
A96: 30316 | B96: -0.27615918 | C96: 1.0313596 | D96: 2.32 | F96: 1.2875 | G96: 2.6224
A97: 30406 | B97: 0.99738501 | C97: 0.75275151 | D97: 2.165 | F97: 1.2 | G97: 2.653475
A98: 30497 | B98: 1.9450419 | C98: 0.73866867 | D98: 2.2 | G98: 2.7268
A99: 30589 | B99: 1.6751664 | C99: 1.0581219 | D99: 2.365 | G99: 2.837275
A100: 30681 | B100: 1.765739 | C100: 0.7546419 | D100: 2.3575 | F100: 1.175 | G100: 2.9111
A101: 30772 | B101: 1.6376035 | C101: 1.0083772 | D101: 2.4225 | F101: 1.275 | G101: 3.060925
A102: 30863 | B102: 1.4185504 | C102: 0.85164394 | D102: 2.6375 | G102: 3.3661
A103: 30955 | B103: 0.66661449 | C103: 0.88487172 | D103: 2.8475 | G103: 3.021825
A104: 31047 | B104: 0.52562947 | C104: 0.74482992 | D104: 2.315 | F104: 1.175 | G104: 2.86935
A105: 31137 | B105: 0.67391324 | C105: 0.98389258 | D105: 2.12 | F105: 0.9625 | G105: 2.900725
A106: 31228 | B106: 0.58741275 | C106: 0.64138315 | D106: 1.98 | G106: 2.585725
A107: 31320 | B107: 1.2259866 | C107: 0.60199666 | D107: 1.975 | G107: 2.612675
A108: 31412 | B108: 0.45245779 | C108: 0.5574423 | D108: 2.025 | F108: 1.0125 | G108: 2.29525
A109: 31502 | B109: 0.64152083 | C109: 0.49614375 | D109: 1.9575 | F109: 0.875 | G109: 1.877275
A110: 31593 | B110: 0.16244968 | C110: 0.37775003 | D110: 1.73 | G110: 1.93435
A111: 31685 | B111: 0.66664551 | C111: 0.40906955 | D111: 1.5525 | G111: 1.97845
A112: 31777 | B112: 0.24959199 | C112: 0.54347438 | D112: 1.5675 | F112: 0.875 | G112: 1.8907
A113: 31867 | B113: 0.45396977 | C113: 0.63763794 | D113: 1.555 | F113: 0.925 | G113: 1.9158
A114: 31958 | B114: 0.78974225 | C114: 0.69031186 | D114: 1.6625 | G114: 2.12505
A115: 32050 | B115: 0.5808548 | C115: 0.75500476 | D115: 1.71 | G115: 2.410475
A116: 32142 | B116: 1.4206977 | C116: 0.79401824 | D116: 1.73 | F116: 1 | G116: 2.23695
A117: 32233 | B117: 0.23668349 | C117: 0.78037784 | D117: 1.6675 | F117: 0.95 | G117: 2.190725
A118: 32324 | B118: 1.0261362 | C118: 0.96835706 | D118: 1.7875 | G118: 2.223725
A119: 32416 | B119: 0.30526185 | C119: 1.1888239 | D119: 1.995 | G119: 2.2176
A120: 32508 | B120: 1.0471089 | C120: 0.86004237 | D120: 2.1175 | F120: 0.9625 | G120: 2.2516
A121: 32598 | B121: 0.7344863 | C121: 1.037276 | D121: 2.3625 | F121: 0.9375 | G121: 2.268475
A122: 32689 | B122: 0.48391105 | C122: 1.0599653 | D122: 2.4325 | G122: 2.020575
A123: 32781 | B123: 0.46408218 | C123: 0.72716152 | D123: 2.27 | G123: 2.062825
A124: 32873 | B124: -0.077196821 | C124: 0.70980748 | D124: 2.1525 | F124: 0.925 | G124: 1.977675
A125: 32963 | B125: 0.81351513 | C125: 1.0733186 | D125: 2.0625 | F125: 0.8625 | G125: 2.141
A126: 33054 | B126: 0.090763781 | C126: 1.1143835 | D126: 2.06 | G126: 2.096325
A127: 33146 | B127: -0.20120596 | C127: 0.85245976 | D127: 2.04 | G127: 2.2162
A128: 33238 | B128: -1.1813362 | C128: 0.74206882 | D128: 1.935 | F128: 0.9125 | G128: 2.054825
A129: 33328 | B129: -0.73274762 | C129: 0.97434034 | D129: 1.6075 | F129: 0.8875 | G129: 2.0437
A130: 33419 | B130: 0.5147953 | C130: 0.73112351 | D130: 1.465 | G130: 2.110025
A131: 33511 | B131: 0.24333858 | C131: 0.77943226 | D131: 1.4125 | G131: 1.928225
A132: 33603 | B132: 0.091240538 | C132: 0.5911092 | D132: 1.205 | F132: 0.875 | G132: 1.7813
A133: 33694 | B133: 0.93477162 | C133: 0.37069314 | D133: 1.005 | F133: 0.8 | G133: 1.9399
A134: 33785 | B134: 0.82402613 | C134: 0.59986065 | D134: 0.9425 | F134: 0.85 | G134: 1.89465
A135: 33877 | B135: 0.73027323 | C135: 0.48813267 | D135: 0.815 | F135: 0.8125 | G135: 1.751125
A136: 33969 | B136: 0.78730875 | C136: 0.68509712 | D136: 0.7575 | F136: 0.775 | G136: 1.773675
A137: 34059 | B137: -0.083962687 | C137: 0.55949272 | D137: 0.76 | F137: 0.75 | G137: 1.63275
A138: 34150 | B138: 0.33092577 | C138: 0.59388273 | D138: 0.75 | F138: 0.8 | G138: 1.522725
A139: 34242 | B139: 0.2279217 | C139: 0.5919297 | D139: 0.765 | F139: 0.7375 | G139: 1.4198
A140: 34334 | B140: 1.1023308 | C140: 0.54366058 | D140: 0.7475 | F140: 0.7375 | G140: 1.5183
A141: 34424 | B141: 0.71592769 | C141: 0.47771037 | D141: 0.8025 | F141: 0.7375 | G141: 1.7449
A142: 34515 | B142: 1.0969236 | C142: 0.48155909 | D142: 0.985 | F142: 0.75 | G142: 1.87925
A143: 34607 | B143: 0.3315289 | C143: 0.5720883 | D143: 1.1225 | F143: 0.75 | G143: 1.924025
... A265: 45747 | B265: -0.36381372 | C265: 0.92398346 | D265: 1.0825 | F265: 0.45 | G265: 1.064275
A266: 45838 | B266: 0.4932566 | C266: 0.49317485 | D266: 1.0825

Sheet Chart 2 - Real rate gaps
E1: PCECTPI (yoy growth rate inflation) - source:https://fred.stlouisfed.org/series/PCECTPI | F1: GDP percent change yoy | H1: wFG | J1: woFG
A2: observation_date | B2: PCECTPI | C2: NBER Recession | D2: NBER Recession | E2: Inflation (yoy, apr) | F2: GDP (yoy, apr) | G2: Policy rate (%, apr) | H2: Real rate gap - with FG (lhs) | I2: 5-year real rate gap - with FG (rhs) | J2: Real rate gap - without FG (lhs) | K2: 5-year real rate gap - without FG (rhs) | L2: r* (%,apr)
A3: 17258 | B3: 0.8 | F3: 9.3
A4: 17349 | B4: 1.9 | F4: 10.8
A5: 17441 | B5: 2.5 | F5: 11.9
A6: 17533 | B6: 1.1 | E6: 6.4 | F6: 7.9
A7: 17624 | B7: 1 | E7: 6.7 | F7: 3.5
A8: 17715 | B8: 1.5 | E8: 6.3 | F8: -0.4
A9: 17807 | B9: -0.3 | C9: 1 | D9: -1 | E9: 3.4 | F9: -2.3
A10: 17899 | B10: -0.8 | C10: 1 | D10: -1 | E10: 1.4 | F10: -3.5
A11: 17989 | B11: -0.6 | C11: 1 | D11: -1 | E11: -0.2 | F11: 2.1
A12: 18080 | B12: -0.6 | C12: 1 | D12: -1 | E12: -2.3 | F12: 7
A13: 18172 | B13: -0.1 | E13: -2 | F13: 12.9
A14: 18264 | B14: -0.2 | E14: -1.4 | F14: 18.2
A15: 18354 | B15: 0.5 | E15: -0.3 | F15: 19.6
A16: 18445 | B16: 2.1 | E16: 2.3 | F16: 18.5
A17: 18537 | B17: 1.8 | E17: 4.2 | F17: 14
A18: 18629 | B18: 3.2 | E18: 7.7 | F18: 11.3
A19: 18719 | B19: 0.8 | E19: 8.1 | F19: 7.1
A20: 18810 | B20: 0.1 | E20: 6 | F20: 4.9
A21: 18902 | B21: 1.3 | E21: 5.5 | F21: 4.6
A22: 18994 | B22: 0.4 | E22: 2.7 | F22: 6.9
A23: 19085 | B23: 0 | E23: 1.9 | F23: 7.8
A24: 19176 | B24: 0.7 | E24: 2.4 | F24: 8.5
... A27: 19450 | B27: 0.1 | E27: 1.3 | F27: -0.7
A28: 19541 | B28: 0.5 | C28: 1 | D28: -1 | E28: 1.2 | F28: -1.4
A29: 19633 | B29: 0.4 | C29: 1 | D29: -1 | E29: 1.5 | F29: 0
A30: 19725 | B30: 0.5 | C30: 1 | D30: -1 | E30: 1.6 | F30: 3.6
A31: 19815 | B31: -0.1 | E31: 1.3 | F31: 7.2
A32: 19906 | B32: -0.3 | E32: 0.5 | F32: 9.2
A33: 19998 | B33: -0.1 | E33: -0.1 | F33: 10
A34: 20090 | B34: 0.3 | E34: -0.2 | F34: 9.3
A35: 20180 | B35: 0.1 | E35: 0 | F35: 6.5
A36: 20271 | B36: 0.4 | E36: 0.7 | F36: 5.8
A37: 20363 | B37: 0.3 | E37: 1.1 | F37: 4.9
A38: 20455 | B38: 0.4 | E38: 1.2 | F38: 5.3
A39: 20546 | B39: 0.7 | E39: 1.8 | F39: 6.8
A40: 20637 | B40: 1 | E40: 2.4 | F40: 5.8
A41: 20729 | B41: 0.6 | E41: 2.7 | F41: 6.3
A42: 20821 | B42: 0.9 | E42: 3.2 | F42: 3.1
A43: 20911 | B43: 0.6 | E43: 3.1 | F43: -0.5
A44: 21002 | B44: 0.8 | C44: 1 | D44: -1 | E44: 3 | F44: 0
A45: 21094 | B45: 0.5 | C45: 1 | D45: -1 | E45: 2.9 | F45: 1.3
A46: 21186 | B46: 1.2 | C46: 1 | D46: -1 | E46: 3.2 | F46: 5.2
A47: 21276 | B47: 0.2 | E47: 2.8 | F47: 9.2
A48: 21367 | B48: 0.1 | E48: 2 | F48: 10.7
A49: 21459 | B49: 0 | E49: 1.5 | F49: 8.1
A50: 21551 | B50: 0.7 | E50: 0.9 | F50: 5.8
A51: 21641 | B51: 0.4 | E51: 1.1 | F51: 6.3
A52: 21732 | B52: 0.6 | E52: 1.7 | F52: 3.5
A53: 21824 | B53: 0.5 | E53: 2.3 | F53: 3.9 | G53: =+'Chart NA - DSGE Raw Data'!D3*4 -> 3.57
A54: 21916 | B54: 0.1 | E54: 1.7 | F54: 2.2 | G54: =+'Chart NA - DSGE Raw Data'!D4*4 -> 3.99
A55: 22007 | B55: 0.5 | C55: 1 | D55: -1 | E55: 1.8 | F55: 0.4 | G55: =+'Chart NA - DSGE Raw Data'!D5*4 -> 3.93 | H55: =+hist_ExAnteRealRate_wFG!D2-hist_RealNaturalRate_wFG!D2 -> 0.98414473 | I55: =+hist_Forward5YearRealR_wFG!D2-hist_Forward5YearRNatR_wFG!D2 -> 0.215389 | J55: =+hist_ExAnteRealRate_woFG!D2-hist_RealNaturalRate_woFG!D2 -> 0.98874011 | K55: =+hist_Forward5YearRealR_woFG!D2-hist_Forward5YearRNatR_woFG!D2 -> 0.22076957 | L55: =+hist_Forward5YearRNatR_wFG!D2 -> 2.0631498
A56: 22098 | B56: 0.4 | C56: 1 | D56: -1 | E56: 1.6 | F56: 2.7 | G56: =+'Chart NA - DSGE Raw Data'!D6*4 -> 3.7 | H56: =+hist_ExAnteRealRate_wFG!D3-hist_RealNaturalRate_wFG!D3 -> -2.1797773 | I56: =+hist_Forward5YearRealR_wFG!D3-hist_Forward5YearRNatR_wFG!D3 -> 0.29669614 | J56: =+hist_ExAnteRealRate_woFG!D3-hist_RealNaturalRate_woFG!D3 -> -2.1740416 | K56: =+hist_Forward5YearRealR_woFG!D3-hist_Forward5YearRNatR_woFG!D3 -> 0.30217716 | L56: =+hist_Forward5YearRNatR_wFG!D3 -> 2.1205647
A57: 22190 | B57: 0.4 | C57: 1 | D57: -1 | E57: 1.5 | F57: 4 | G57: =+'Chart NA - DSGE Raw Data'!D7*4 -> 2.94 | H57: =+hist_ExAnteRealRate_wFG!D4-hist_RealNaturalRate_wFG!D4 -> 1.4683848 | I57: =+hist_Forward5YearRealR_wFG!D4-hist_Forward5YearRNatR_wFG!D4 -> 0.32520532 | J57: =+hist_ExAnteRealRate_woFG!D4-hist_RealNaturalRate_woFG!D4 -> 1.4753184 | K57: =+hist_Forward5YearRealR_woFG!D4-hist_Forward5YearRNatR_woFG!D4 -> 0.33078535 | L57: =+hist_Forward5YearRNatR_wFG!D4 -> 2.0224967
A58: 22282 | B58: 0.2 | E58: 1.5 | F58: 7.5 | G58: =+'Chart NA - DSGE Raw Data'!D8*4 -> 2.3 | H58: =+hist_ExAnteRealRate_wFG!D5-hist_RealNaturalRate_wFG!D5 -> 1.1932381 | I58: =+hist_Forward5YearRealR_wFG!D5-hist_Forward5YearRNatR_wFG!D5 -> 0.30407804 | J58: =+hist_ExAnteRealRate_woFG!D5-hist_RealNaturalRate_woFG!D5 -> 1.2014514 | K58: =+hist_Forward5YearRealR_woFG!D5-hist_Forward5YearRNatR_woFG!D5 -> 0.3097568 | L58: =+hist_Forward5YearRNatR_wFG!D5 -> 2.1038496
A59: 22372 | B59: 0 | E59: 1 | F59: 9 | G59: =+'Chart NA - DSGE Raw Data'!D9*4 -> 1.99 | H59: =+hist_ExAnteRealRate_wFG!D6-hist_RealNaturalRate_wFG!D6 -> 2.1195851 | I59: =+hist_Forward5YearRealR_wFG!D6-hist_Forward5YearRNatR_wFG!D6 -> 0.3340696 | J59: =+hist_ExAnteRealRate_woFG!D6-hist_RealNaturalRate_woFG!D6 -> 2.129168 | K59: =+hist_Forward5YearRealR_woFG!D6-hist_Forward5YearRNatR_woFG!D6 -> 0.33984786 | L59: =+hist_Forward5YearRNatR_wFG!D6 -> 2.1590386
A60: 22463 | B60: 0.4 | E60: 1 | F60: 8.1 | G60: =+'Chart NA - DSGE Raw Data'!D10*4 -> 1.73 | H60: =+hist_ExAnteRealRate_wFG!D7-hist_RealNaturalRate_wFG!D7 -> 2.3952093 | I60: =+hist_Forward5YearRealR_wFG!D7-hist_Forward5YearRNatR_wFG!D7 -> 0.30636396 | J60: =+hist_ExAnteRealRate_woFG!D7-hist_RealNaturalRate_woFG!D7 -> 2.406256 | K60: =+hist_Forward5YearRealR_woFG!D7-hist_Forward5YearRNatR_woFG!D7 -> 0.31224343 | L60: =+hist_Forward5YearRNatR_wFG!D7 -> 2.1723315
A61: 22555 | B61: 0.1 | E61: 0.6 | F61: 7.3 | G61: =+'Chart NA - DSGE Raw Data'!D11*4 -> 1.68 | H61: =+hist_ExAnteRealRate_wFG!D8-hist_RealNaturalRate_wFG!D8 -> 1.7102926 | I61: =+hist_Forward5YearRealR_wFG!D8-hist_Forward5YearRNatR_wFG!D8 -> 0.29183699 | J61: =+hist_ExAnteRealRate_woFG!D8-hist_RealNaturalRate_woFG!D8 -> 1.7229023 | K61: =+hist_Forward5YearRealR_woFG!D8-hist_Forward5YearRNatR_woFG!D8 -> 0.2978202 | L61: =+hist_Forward5YearRNatR_wFG!D8 -> 2.2626478
A62: 22647 | B62: 0.4 | E62: 0.9 | F62: 5.5 | G62: =+'Chart NA - DSGE Raw Data'!D12*4 -> 2.4 | H62: =+hist_ExAnteRealRate_wFG!D9-hist_RealNaturalRate_wFG!D9 -> -0.93240227 | I62: =+hist_Forward5YearRealR_wFG!D9-hist_Forward5YearRNatR_wFG!D9 -> 0.2624522 | J62: =+hist_ExAnteRealRate_woFG!D9-hist_RealNaturalRate_woFG!D9 -> -0.91812388 | K62: =+hist_Forward5YearRealR_woFG!D9-hist_Forward5YearRNatR_woFG!D9 -> 0.26854246 | L62: =+hist_Forward5YearRNatR_wFG!D9 -> 2.373264
A63: 22737 | B63: 0.4 | E63: 1.3 | F63: 4.7 | G63: =+'Chart NA - DSGE Raw Data'!D13*4 -> 2.46 | H63: =+hist_ExAnteRealRate_wFG!D10-hist_RealNaturalRate_wFG!D10 -> -0.11940061 | I63: =+hist_Forward5YearRealR_wFG!D10-hist_Forward5YearRNatR_wFG!D10 -> 0.27842854 | J63: =+hist_ExAnteRealRate_woFG!D10-hist_RealNaturalRate_woFG!D10 -> -0.10333895 | K63: =+hist_Forward5YearRealR_woFG!D10-hist_Forward5YearRNatR_woFG!D10 -> 0.2846298 | L63: =+hist_Forward5YearRNatR_wFG!D10 -> 2.4914681
A64: 22828 | B64: 0.3 | E64: 1.2 | F64: 4.9 | G64: =+'Chart NA - DSGE Raw Data'!D14*4 -> 2.61 | H64: =+hist_ExAnteRealRate_wFG!D11-hist_RealNaturalRate_wFG!D11 -> -0.89514752 | I64: =+hist_Forward5YearRealR_wFG!D11-hist_Forward5YearRNatR_wFG!D11 -> 0.23230554 | J64: =+hist_ExAnteRealRate_woFG!D11-hist_RealNaturalRate_woFG!D11 -> -0.87717688 | K64: =+hist_Forward5YearRealR_woFG!D11-hist_Forward5YearRNatR_woFG!D11 -> 0.23862237 | L64: =+hist_Forward5YearRNatR_wFG!D11 -> 2.4933496
A65: 22920 | B65: 0.3 | E65: 1.4 | F65: 5.8 | G65: =+'Chart NA - DSGE Raw Data'!D15*4 -> 2.85 | H65: =+hist_ExAnteRealRate_wFG!D12-hist_RealNaturalRate_wFG!D12 -> 0.4821998 | I65: =+hist_Forward5YearRealR_wFG!D12-hist_Forward5YearRNatR_wFG!D12 -> 0.26159565 | J65: =+hist_ExAnteRealRate_woFG!D12-hist_RealNaturalRate_woFG!D12 -> 0.50221873 | K65: =+hist_Forward5YearRealR_woFG!D12-hist_Forward5YearRNatR_woFG!D12 -> 0.26803317 | L65: =+hist_Forward5YearRNatR_wFG!D12 -> 2.5797766
A66: 23012 | B66: 0.3 | E66: 1.2 | F66: 6.8 | G66: =+'Chart NA - DSGE Raw Data'!D16*4 -> 2.92 | H66: =+hist_ExAnteRealRate_wFG!D13-hist_RealNaturalRate_wFG!D13 -> 0.22471561 | I66: =+hist_Forward5YearRealR_wFG!D13-hist_Forward5YearRNatR_wFG!D13 -> 0.277659 | J66: =+hist_ExAnteRealRate_woFG!D13-hist_RealNaturalRate_woFG!D13 -> 0.24693884 | K66: =+hist_Forward5YearRealR_woFG!D13-hist_Forward5YearRNatR_woFG!D13 -> 0.28422277 | L66: =+hist_Forward5YearRNatR_wFG!D13 -> 2.6508134
A67: 23102 | B67: 0.2 | E67: 1 | F67: 7.7 | G67: =+'Chart NA - DSGE Raw Data'!D17*4 -> 2.97 | H67: =+hist_ExAnteRealRate_wFG!D14-hist_RealNaturalRate_wFG!D14 -> 0.36163635 | I67: =+hist_Forward5YearRealR_wFG!D14-hist_Forward5YearRNatR_wFG!D14 -> 0.25422512 | J67: =+hist_ExAnteRealRate_woFG!D14-hist_RealNaturalRate_woFG!D14 -> 0.38624114 | K67: =+hist_Forward5YearRealR_woFG!D14-hist_Forward5YearRNatR_woFG!D14 -> 0.26092114 | L67: =+hist_Forward5YearRNatR_wFG!D14 -> 2.7580187
A68: 23193 | B68: 0.5 | E68: 1.2 | F68: 7.8 | G68: =+'Chart NA - DSGE Raw Data'!D18*4 -> 2.96 | H68: =+hist_ExAnteRealRate_wFG!D15-hist_RealNaturalRate_wFG!D15 -> -0.1579969 | I68: =+hist_Forward5YearRealR_wFG!D15-hist_Forward5YearRNatR_wFG!D15 -> 0.16605339 | J68: =+hist_ExAnteRealRate_woFG!D15-hist_RealNaturalRate_woFG!D15 -> -0.13080359 | K68: =+hist_Forward5YearRealR_woFG!D15-hist_Forward5YearRNatR_woFG!D15 -> 0.17288808 | L68: =+hist_Forward5YearRNatR_wFG!D15 -> 2.8481428
A69: 23285 | B69: 0.4 | E69: 1.3 | F69: 7.4 | G69: =+'Chart NA - DSGE Raw Data'!D19*4 -> 3.33 | H69: =+hist_ExAnteRealRate_wFG!D16-hist_RealNaturalRate_wFG!D16 -> -0.42785808 | I69: =+hist_Forward5YearRealR_wFG!D16-hist_Forward5YearRNatR_wFG!D16 -> 0.18305107 | J69: =+hist_ExAnteRealRate_woFG!D16-hist_RealNaturalRate_woFG!D16 -> -0.39782128 | K69: =+hist_Forward5YearRealR_woFG!D16-hist_Forward5YearRNatR_woFG!D16 -> 0.19003137 | L69: =+hist_Forward5YearRNatR_wFG!D16 -> 2.920799
... A93: 25477 | B93: 1.2 | E93: 4.7 | F93: 5.4 | G93: =+'Chart NA - DSGE Raw Data'!D43*4 -> 8.98 | H93: =+hist_ExAnteRealRate_wFG!D40-hist_RealNaturalRate_wFG!D40 -> -3.1066103 | I93: =+hist_Forward5YearRealR_wFG!D40-hist_Forward5YearRNatR_wFG!D40 -> 0.020357188 | J93: =+hist_ExAnteRealRate_woFG!D40-hist_RealNaturalRate_woFG!D40 -> -3.0804048 | K93: =+hist_Forward5YearRealR_woFG!D40-hist_Forward5YearRNatR_woFG!D40 -> 0.028694894 | L93: =+hist_Forward5YearRNatR_wFG!D40 -> 2.2026074
A94: 25569 | B94: 1.2 | C94: 1 | D94: -1 | E94: 4.9 | F94: 4.9 | G94: =+'Chart NA - DSGE Raw Data'!D44*4 -> 8.94 | H94: =+hist_ExAnteRealRate_wFG!D41-hist_RealNaturalRate_wFG!D41 -> -5.1834509 | I94: =+hist_Forward5YearRealR_wFG!D41-hist_Forward5YearRNatR_wFG!D41 -> 0.081705774 | J94: =+hist_ExAnteRealRate_woFG!D41-hist_RealNaturalRate_woFG!D41 -> -5.1571284 | K94: =+hist_Forward5YearRealR_woFG!D41-hist_Forward5YearRNatR_woFG!D41 -> 0.09006045 | L94: =+hist_Forward5YearRNatR_wFG!D41 -> 2.1943031
A95: 25659 | B95: 1.1 | C95: 1 | D95: -1 | E95: 4.7 | F95: 8 | G95: =+'Chart NA - DSGE Raw Data'!D45*4 -> 8.56 | H95: =+hist_ExAnteRealRate_wFG!D42-hist_RealNaturalRate_wFG!D42 -> -2.7508327 | I95: =+hist_Forward5YearRealR_wFG!D42-hist_Forward5YearRNatR_wFG!D42 -> 0.081626554 | J95: =+hist_ExAnteRealRate_woFG!D42-hist_RealNaturalRate_woFG!D42 -> -2.724402 | K95: =+hist_Forward5YearRealR_woFG!D42-hist_Forward5YearRNatR_woFG!D42 -> 0.089997341 | L95: =+hist_Forward5YearRNatR_wFG!D42 -> 1.8897571
A96: 25750 | B96: 1 | C96: 1 | D96: -1 | E96: 4.5 | F96: 8.3 | G96: =+'Chart NA - DSGE Raw Data'!D46*4 -> 7.88 | H96: =+hist_ExAnteRealRate_wFG!D43-hist_RealNaturalRate_wFG!D43 -> 1.0372343 | I96: =+hist_Forward5YearRealR_wFG!D43-hist_Forward5YearRNatR_wFG!D43 -> 0.1057637 | J96: =+hist_ExAnteRealRate_woFG!D43-hist_RealNaturalRate_woFG!D43 -> 1.0637645 | K96: =+hist_Forward5YearRealR_woFG!D43-hist_Forward5YearRNatR_woFG!D43 -> 0.11414982 | L96: =+hist_Forward5YearRNatR_wFG!D43 -> 1.9178022
A97: 25842 | B97: 1.3 | E97: 4.6 | F97: 8.4 | G97: =+'Chart NA - DSGE Raw Data'!D47*4 -> 6.71 | H97: =+hist_ExAnteRealRate_wFG!D44-hist_RealNaturalRate_wFG!D44 -> 1.4525303 | I97: =+hist_Forward5YearRealR_wFG!D44-hist_Forward5YearRNatR_wFG!D44 -> 0.065601787 | J97: =+hist_ExAnteRealRate_woFG!D44-hist_RealNaturalRate_woFG!D44 -> 1.4791516 | K97: =+hist_Forward5YearRealR_woFG!D44-hist_Forward5YearRNatR_woFG!D44 -> 0.074002536 | L97: =+hist_Forward5YearRNatR_wFG!D44 -> 1.5368141
A98: 25934 | B98: 0.9 | E98: 4.4 | F98: 9.3 | G98: =+'Chart NA - DSGE Raw Data'!D48*4 -> 5.57 | H98: =+hist_ExAnteRealRate_wFG!D45-hist_RealNaturalRate_wFG!D45 -> 1.9101381 | I98: =+hist_Forward5YearRealR_wFG!D45-hist_Forward5YearRNatR_wFG!D45 -> 0.096012508 | J98: =+hist_ExAnteRealRate_woFG!D45-hist_RealNaturalRate_woFG!D45 -> 1.9368419 | K98: =+hist_Forward5YearRealR_woFG!D45-hist_Forward5YearRNatR_woFG!D45 -> 0.10442725 | L98: =+hist_Forward5YearRNatR_wFG!D45 -> 1.3422137
A99: 26024 | B99: 1.1 | E99: 4.4 | F99: 8.4 | G99: =+'Chart NA - DSGE Raw Data'!D49*4 -> 3.86 | H99: =+hist_ExAnteRealRate_wFG!D46-hist_RealNaturalRate_wFG!D46 -> 4.1065232 | I99: =+hist_Forward5YearRealR_wFG!D46-hist_Forward5YearRNatR_wFG!D46 -> 0.033059257 | J99: =+hist_ExAnteRealRate_woFG!D46-hist_RealNaturalRate_woFG!D46 -> 4.1333001 | K99: =+hist_Forward5YearRealR_woFG!D46-hist_Forward5YearRNatR_woFG!D46 -> 0.041487429 | L99: =+hist_Forward5YearRNatR_wFG!D46 -> 1.4527322
A100: 26115 | B100: 1 | E100: 4.4 | F100: 9.5 | G100: =+'Chart NA - DSGE Raw Data'!D50*4 -> 4.57 | H100: =+hist_ExAnteRealRate_wFG!D47-hist_RealNaturalRate_wFG!D47 -> 2.4652834 | I100: =+hist_Forward5YearRealR_wFG!D47-hist_Forward5YearRNatR_wFG!D47 -> 0.01794157 | J100: =+hist_ExAnteRealRate_woFG!D47-hist_RealNaturalRate_woFG!D47 -> 2.4921227 | K100: =+hist_Forward5YearRealR_woFG!D47-hist_Forward5YearRNatR_woFG!D47 -> 0.026382681 | L100: =+hist_Forward5YearRNatR_wFG!D47 -> 1.3677747
A101: 26207 | B101: 0.6 | E101: 3.7 | F101: 9.6 | G101: =+'Chart NA - DSGE Raw Data'!D51*4 -> 5.48 | H101: =+hist_ExAnteRealRate_wFG!D48-hist_RealNaturalRate_wFG!D48 -> 1.4074273 | I101: =+hist_Forward5YearRealR_wFG!D48-hist_Forward5YearRNatR_wFG!D48 -> 0.055784154 | J101: =+hist_ExAnteRealRate_woFG!D48-hist_RealNaturalRate_woFG!D48 -> 1.4343153 | K101: =+hist_Forward5YearRealR_woFG!D48-hist_Forward5YearRNatR_woFG!D48 -> 0.064237839 | L101: =+hist_Forward5YearRNatR_wFG!D48 -> 1.3190477
A102: 26299 | B102: 1.1 | E102: 3.8 | F102: 11.6 | G102: =+'Chart NA - DSGE Raw Data'!D52*4 -> 4.75 | H102: =+hist_ExAnteRealRate_wFG!D49-hist_RealNaturalRate_wFG!D49 -> 0.091487229 | I102: =+hist_Forward5YearRealR_wFG!D49-hist_Forward5YearRNatR_wFG!D49 -> -0.023924673 | J102: =+hist_ExAnteRealRate_woFG!D49-hist_RealNaturalRate_woFG!D49 -> 0.11856188 | K102: =+hist_Forward5YearRealR_woFG!D49-hist_Forward5YearRNatR_woFG!D49 -> -0.01546171 | L102: =+hist_Forward5YearRNatR_wFG!D49 -> 1.3456769
A103: 26390 | B103: 0.6 | E103: 3.3 | F103: 11.9 | G103: =+'Chart NA - DSGE Raw Data'!D53*4 -> 3.55 | H103: =+hist_ExAnteRealRate_wFG!D50-hist_RealNaturalRate_wFG!D50 -> 0.43895532 | I103: =+hist_Forward5YearRealR_wFG!D50-hist_Forward5YearRNatR_wFG!D50 -> -0.067206181 | J103: =+hist_ExAnteRealRate_woFG!D50-hist_RealNaturalRate_woFG!D50 -> 0.46621015 | K103: =+hist_Forward5YearRealR_woFG!D50-hist_Forward5YearRNatR_woFG!D50 -> -0.058734659 | L103: =+hist_Forward5YearRNatR_wFG!D50 -> 1.5187459
A104: 26481 | B104: 0.9 | E104: 3.2 | F104: 11.6 | G104: =+'Chart NA - DSGE Raw Data'!D54*4 -> 4.3 | H104: =+hist_ExAnteRealRate_wFG!D51-hist_RealNaturalRate_wFG!D51 -> -0.21473409 | I104: =+hist_Forward5YearRealR_wFG!D51-hist_Forward5YearRNatR_wFG!D51 -> -0.050812244 | J104: =+hist_ExAnteRealRate_woFG!D51-hist_RealNaturalRate_woFG!D51 -> -0.18730194 | K104: =+hist_Forward5YearRealR_woFG!D51-hist_Forward5YearRNatR_woFG!D51 -> -0.042332805 | L104: =+hist_Forward5YearRNatR_wFG!D51 -> 1.6030396
A105: 26573 | B105: 0.8 | E105: 3.4 | F105: 11.1 | G105: =+'Chart NA - DSGE Raw Data'!D55*4 -> 4.74 | H105: =+hist_ExAnteRealRate_wFG!D52-hist_RealNaturalRate_wFG!D52 -> 1.2480661 | I105: =+hist_Forward5YearRealR_wFG!D52-hist_Forward5YearRNatR_wFG!D52 -> -0.043960713 | J105: =+hist_ExAnteRealRate_woFG!D52-hist_RealNaturalRate_woFG!D52 -> 1.2756756 | K105: =+hist_Forward5YearRealR_woFG!D52-hist_Forward5YearRNatR_woFG!D52 -> -0.035473982 | L105: =+hist_Forward5YearRNatR_wFG!D52 -> 1.5917993
A106: 26665 | B106: 1.2 | E106: 3.5 | F106: 11.1 | G106: =+'Chart NA - DSGE Raw Data'!D56*4 -> 5.15 | H106: =+hist_ExAnteRealRate_wFG!D53-hist_RealNaturalRate_wFG!D53 -> 1.224053 | I106: =+hist_Forward5YearRealR_wFG!D53-hist_Forward5YearRNatR_wFG!D53 -> -0.12395213 | J106: =+hist_ExAnteRealRate_woFG!D53-hist_RealNaturalRate_woFG!D53 -> 1.2518421 | K106: =+hist_Forward5YearRealR_woFG!D53-hist_Forward5YearRNatR_woFG!D53 -> -0.11545875 | L106: =+hist_Forward5YearRNatR_wFG!D53 -> 1.5531729
A107: 26755 | B107: 1.9 | E107: 4.9 | F107: 8.3 | G107: =+'Chart NA - DSGE Raw Data'!D57*4 -> 6.54 | H107: =+hist_ExAnteRealRate_wFG!D54-hist_RealNaturalRate_wFG!D54 -> 0.17938966 | I107: =+hist_Forward5YearRealR_wFG!D54-hist_Forward5YearRNatR_wFG!D54 -> -0.12386814 | J107: =+hist_ExAnteRealRate_woFG!D54-hist_RealNaturalRate_woFG!D54 -> 0.20736261 | K107: =+hist_Forward5YearRealR_woFG!D54-hist_Forward5YearRNatR_woFG!D54 -> -0.11536878 | L107: =+hist_Forward5YearRNatR_wFG!D54 -> 2.1203006
A108: 26846 | B108: 1.8 | E108: 5.9 | F108: 8.2 | G108: =+'Chart NA - DSGE Raw Data'!D58*4 -> 7.82 | H108: =+hist_ExAnteRealRate_wFG!D55-hist_RealNaturalRate_wFG!D55 -> -1.7279991 | I108: =+hist_Forward5YearRealR_wFG!D55-hist_Forward5YearRNatR_wFG!D55 -> -0.05667887 | J108: =+hist_ExAnteRealRate_woFG!D55-hist_RealNaturalRate_woFG!D55 -> -1.6998361 | K108: =+hist_Forward5YearRealR_woFG!D55-hist_Forward5YearRNatR_woFG!D55 -> -0.048174275 | L108: =+hist_Forward5YearRNatR_wFG!D55 -> 2.0331948
A109: 26938 | B109: 2 | C109: 1 | D109: -1 | E109: 7.2 | F109: 8.8 | G109: =+'Chart NA - DSGE Raw Data'!D59*4 -> 10.56 | H109: =+hist_ExAnteRealRate_wFG!D56-hist_RealNaturalRate_wFG!D56 -> -3.5849942 | I109: =+hist_Forward5YearRealR_wFG!D56-hist_Forward5YearRNatR_wFG!D56 -> 0.023106214 | J109: =+hist_ExAnteRealRate_woFG!D56-hist_RealNaturalRate_woFG!D56 -> -3.5566336 | K109: =+hist_Forward5YearRealR_woFG!D56-hist_Forward5YearRNatR_woFG!D56 -> 0.031615247 | L109: =+hist_Forward5YearRNatR_wFG!D56 -> 2.0008364
A110: 27030 | B110: 3 | C110: 1 | D110: -1 | E110: 9.1 | F110: 8.4 | G110: =+'Chart NA - DSGE Raw Data'!D60*4 -> 10 | H110: =+hist_ExAnteRealRate_wFG!D57-hist_RealNaturalRate_wFG!D57 -> -3.5749426 | I110: =+hist_Forward5YearRealR_wFG!D57-hist_Forward5YearRNatR_wFG!D57 -> 0.024017321 | J110: =+hist_ExAnteRealRate_woFG!D57-hist_RealNaturalRate_woFG!D57 -> -3.5463751 | K110: =+hist_Forward5YearRealR_woFG!D57-hist_Forward5YearRNatR_woFG!D57 -> 0.032529907 | L110: =+hist_Forward5YearRNatR_wFG!D57 -> 1.9057608
A111: 27120 | B111: 2.8 | C111: 1 | D111: -1 | E111: 10 | F111: 8.4 | G111: =+'Chart NA - DSGE Raw Data'!D61*4 -> 9.33 | H111: =+hist_ExAnteRealRate_wFG!D58-hist_RealNaturalRate_wFG!D58 -> -2.717 | I111: =+hist_Forward5YearRealR_wFG!D58-hist_Forward5YearRNatR_wFG!D58 -> 0.045274726 | J111: =+hist_ExAnteRealRate_woFG!D58-hist_RealNaturalRate_woFG!D58 -> -2.688215 | K111: =+hist_Forward5YearRealR_woFG!D58-hist_Forward5YearRNatR_woFG!D58 -> 0.053789884 | L111: =+hist_Forward5YearRNatR_wFG!D58 -> 1.9802961
A112: 27211 | B112: 2.7 | C112: 1 | D112: -1 | E112: 11 | F112: 8 | G112: =+'Chart NA - DSGE Raw Data'!D62*4 -> 11.25 | H112: =+hist_ExAnteRealRate_wFG!D59-hist_RealNaturalRate_wFG!D59 -> -3.809393 | I112: =+hist_Forward5YearRealR_wFG!D59-hist_Forward5YearRNatR_wFG!D59 -> 0.12988476 | J112: =+hist_ExAnteRealRate_woFG!D59-hist_RealNaturalRate_woFG!D59 -> -3.7803784 | K112: =+hist_Forward5YearRealR_woFG!D59-hist_Forward5YearRNatR_woFG!D59 -> 0.13840139 | L112: =+hist_Forward5YearRNatR_wFG!D59 -> 1.875816
A113: 27303 | B113: 2.5 | C113: 1 | D113: -1 | E113: 11.5 | F113: 9.6 | G113: =+'Chart NA - DSGE Raw Data'!D63*4 -> 12.1 | H113: =+hist_ExAnteRealRate_wFG!D60-hist_RealNaturalRate_wFG!D60 -> -4.635432 | I113: =+hist_Forward5YearRealR_wFG!D60-hist_Forward5YearRNatR_wFG!D60 -> 0.1914544 | J113: =+hist_ExAnteRealRate_woFG!D60-hist_RealNaturalRate_woFG!D60 -> -4.6061742 | K113: =+hist_Forward5YearRealR_woFG!D60-hist_Forward5YearRNatR_woFG!D60 -> 0.19997129 | L113: =+hist_Forward5YearRNatR_wFG!D60 -> 1.6272735
A114: 27395 | B114: 1.9 | C114: 1 | D114: -1 | E114: 10.3 | F114: 10.1 | G114: =+'Chart NA - DSGE Raw Data'!D64*4 -> 9.34 | H114: =+hist_ExAnteRealRate_wFG!D61-hist_RealNaturalRate_wFG!D61 -> 2.3608444 | I114: =+hist_Forward5YearRealR_wFG!D61-hist_Forward5YearRNatR_wFG!D61 -> 0.25138618 | J114: =+hist_ExAnteRealRate_woFG!D61-hist_RealNaturalRate_woFG!D61 -> 2.3903602 | K114: =+hist_Forward5YearRealR_woFG!D61-hist_Forward5YearRNatR_woFG!D61 -> 0.25990196 | L114: =+hist_Forward5YearRNatR_wFG!D61 -> 1.1352749
A115: 27485 | B115: 1.2 | E115: 8.6 | F115: 12.6 | G115: =+'Chart NA - DSGE Raw Data'!D65*4 -> 6.31 | H115: =+hist_ExAnteRealRate_wFG!D62-hist_RealNaturalRate_wFG!D62 -> 6.0173866 | I115: =+hist_Forward5YearRealR_wFG!D62-hist_Forward5YearRNatR_wFG!D62 -> 0.26086974 | J115: =+hist_ExAnteRealRate_woFG!D62-hist_RealNaturalRate_woFG!D62 -> 6.0471768 | K115: =+hist_Forward5YearRealR_woFG!D62-hist_Forward5YearRNatR_woFG!D62 -> 0.26938286 | L115: =+hist_Forward5YearRNatR_wFG!D62 -> 1.2151432
A116: 27576 | B116: 1.9 | E116: 7.7 | F116: 12.1 | G116: =+'Chart NA - DSGE Raw Data'!D66*4 -> 5.42 | H116: =+hist_ExAnteRealRate_wFG!D63-hist_RealNaturalRate_wFG!D63 -> 5.0363778 | I116: =+hist_Forward5YearRealR_wFG!D63-hist_Forward5YearRNatR_wFG!D63 -> 0.18527753 | J116: =+hist_ExAnteRealRate_woFG!D63-hist_RealNaturalRate_woFG!D63 -> 5.0664603 | K116: =+hist_Forward5YearRealR_woFG!D63-hist_Forward5YearRNatR_woFG!D63 -> 0.19378625 | L116: =+hist_Forward5YearRNatR_wFG!D63 -> 1.4815212
A117: 27668 | B117: 1.7 | E117: 6.8 | F117: 10.3 | G117: =+'Chart NA - DSGE Raw Data'!D67*4 -> 6.16 | H117: =+hist_ExAnteRealRate_wFG!D64-hist_RealNaturalRate_wFG!D64 -> 2.2825797 | I117: =+hist_Forward5YearRealR_wFG!D64-hist_Forward5YearRNatR_wFG!D64 -> 0.15981869 | J117: =+hist_ExAnteRealRate_woFG!D64-hist_RealNaturalRate_woFG!D64 -> 2.3129737 | K117: =+hist_Forward5YearRealR_woFG!D64-hist_Forward5YearRNatR_woFG!D64 -> 0.16832106 | L117: =+hist_Forward5YearRNatR_wFG!D64 -> 1.6890905
A118: 27760 | B118: 1.1 | E118: 6 | F118: 9.8 | G118: =+'Chart NA - DSGE Raw Data'!D68*4 -> 5.41 | H118: =+hist_ExAnteRealRate_wFG!D65-hist_RealNaturalRate_wFG!D65 -> 3.211986 | I118: =+hist_Forward5YearRealR_wFG!D65-hist_Forward5YearRNatR_wFG!D65 -> 0.13859459 | J118: =+hist_ExAnteRealRate_woFG!D65-hist_RealNaturalRate_woFG!D65 -> 3.2427125 | K118: =+hist_Forward5YearRealR_woFG!D65-hist_Forward5YearRNatR_woFG!D65 -> 0.14708841 | L118: =+hist_Forward5YearRNatR_wFG!D65 -> 1.6552998
A119: 27851 | B119: 0.8 | E119: 5.6 | F119: 9.2 | G119: =+'Chart NA - DSGE Raw Data'!D69*4 -> 4.83 | H119: =+hist_ExAnteRealRate_wFG!D66-hist_RealNaturalRate_wFG!D66 -> 1.2153956 | I119: =+hist_Forward5YearRealR_wFG!D66-hist_Forward5YearRNatR_wFG!D66 -> 0.058570677 | J119: =+hist_ExAnteRealRate_woFG!D66-hist_RealNaturalRate_woFG!D66 -> 1.2464768 | K119: =+hist_Forward5YearRealR_woFG!D66-hist_Forward5YearRNatR_woFG!D66 -> 0.067053447 | L119: =+hist_Forward5YearRNatR_wFG!D66 -> 1.7227995
A120: 27942 | B120: 1.5 | E120: 5.2 | F120: 11 | G120: =+'Chart NA - DSGE Raw Data'!D70*4 -> 5.2 | H120: =+hist_ExAnteRealRate_wFG!D67-hist_RealNaturalRate_wFG!D67 -> 2.4552468 | I120: =+hist_Forward5YearRealR_wFG!D67-hist_Forward5YearRNatR_wFG!D67 -> 0.074261411 | J120: =+hist_ExAnteRealRate_woFG!D67-hist_RealNaturalRate_woFG!D67 -> 2.4867068 | K120: =+hist_Forward5YearRealR_woFG!D67-hist_Forward5YearRNatR_woFG!D67 -> 0.082730324 | L120: =+hist_Forward5YearRNatR_wFG!D67 -> 1.9038417
A121: 28034 | B121: 1.6 | E121: 5.1 | F121: 12.3 | G121: =+'Chart NA - DSGE Raw Data'!D71*4 -> 5.28 | H121: =+hist_ExAnteRealRate_wFG!D68-hist_RealNaturalRate_wFG!D68 -> 1.2842735 | I121: =+hist_Forward5YearRealR_wFG!D68-hist_Forward5YearRNatR_wFG!D68 -> 0.10927221 | J121: =+hist_ExAnteRealRate_woFG!D68-hist_RealNaturalRate_woFG!D68 -> 1.3161378 | K121: =+hist_Forward5YearRealR_woFG!D68-hist_Forward5YearRNatR_woFG!D68 -> 0.1177241 | L121: =+hist_Forward5YearRNatR_wFG!D68 -> 1.9607805
A122: 28126 | B122: 1.8 | E122: 5.9 | F122: 11.9 | G122: =+'Chart NA - DSGE Raw Data'!D72*4 -> 4.87 | H122: =+hist_ExAnteRealRate_wFG!D69-hist_RealNaturalRate_wFG!D69 -> 4.4287463 | I122: =+hist_Forward5YearRealR_wFG!D69-hist_Forward5YearRNatR_wFG!D69 -> 0.050634978 | J122: =+hist_ExAnteRealRate_woFG!D69-hist_RealNaturalRate_woFG!D69 -> 4.461042 | K122: =+hist_Forward5YearRealR_woFG!D69-hist_Forward5YearRNatR_woFG!D69 -> 0.059066247 | L122: =+hist_Forward5YearRNatR_wFG!D69 -> 1.8283561
A123: 28216 | B123: 1.7 | E123: 6.8 | F123: 10.8 | G123: =+'Chart NA - DSGE Raw Data'!D73*4 -> 4.66 | H123: =+hist_ExAnteRealRate_wFG!D70-hist_RealNaturalRate_wFG!D70 -> 3.8339751 | I123: =+hist_Forward5YearRealR_wFG!D70-hist_Forward5YearRNatR_wFG!D70 -> 0.028368888 | J123: =+hist_ExAnteRealRate_woFG!D70-hist_RealNaturalRate_woFG!D70 -> 3.8667312 | K123: =+hist_Forward5YearRealR_woFG!D70-hist_Forward5YearRNatR_woFG!D70 -> 0.036775493 | L123: =+hist_Forward5YearRNatR_wFG!D70 -> 2.0284027
A124: 28307 | B124: 1.5 | E124: 6.8 | F124: 13.4 | G124: =+'Chart NA - DSGE Raw Data'!D74*4 -> 5.16 | H124: =+hist_ExAnteRealRate_wFG!D71-hist_RealNaturalRate_wFG!D71 -> 1.1537742 | I124: =+hist_Forward5YearRealR_wFG!D71-hist_Forward5YearRNatR_wFG!D71 -> -0.039144204 | J124: =+hist_ExAnteRealRate_woFG!D71-hist_RealNaturalRate_woFG!D71 -> 1.187021 | K124: =+hist_Forward5YearRealR_woFG!D71-hist_Forward5YearRNatR_woFG!D71 -> -0.030766837 | L124: =+hist_Forward5YearRNatR_wFG!D71 -> 2.1332211
A125: 28399 | B125: 1.4 | E125: 6.6 | F125: 13.1 | G125: =+'Chart NA - DSGE Raw Data'!D75*4 -> 5.82 | H125: =+hist_ExAnteRealRate_wFG!D72-hist_RealNaturalRate_wFG!D72 -> 1.8734213 | I125: =+hist_Forward5YearRealR_wFG!D72-hist_Forward5YearRNatR_wFG!D72 -> 0.0046666571 | J125: =+hist_ExAnteRealRate_woFG!D72-hist_RealNaturalRate_woFG!D72 -> 1.9071908 | K125: =+hist_Forward5YearRealR_woFG!D72-hist_Forward5YearRNatR_woFG!D72 -> 0.013009618 | L125: =+hist_Forward5YearRNatR_wFG!D72 -> 2.2004958
...

Sheet Chart 3 - rstar
A1: Date | B1: DSGE r* (with FG) | C1: DSGE r* (without FG) | D1: HLW r* | E1: LM r* | F1: =+'Chart NA - DSGE Raw Data'!D2 -> obs_nominalrate
A2: =+hist_Forward5YearRNatR_wFG!A2 -> 22006 | B2: =+hist_Forward5YearRNatR_wFG!D2 -> 2.0631498 | C2: =+hist_Forward5YearRNatR_woFG!D2 -> 2.0874644 | F2: =+'Chart NA - DSGE Raw Data'!D5 -> 0.9825
A3: =+hist_Forward5YearRNatR_wFG!A3 -> 22097 | B3: =+hist_Forward5YearRNatR_wFG!D3 -> 2.1205647 | C3: =+hist_Forward5YearRNatR_woFG!D3 -> 2.1450854 | F3: =+'Chart NA - DSGE Raw Data'!D6 -> 0.925
A4: =+hist_Forward5YearRNatR_wFG!A4 -> 22189 | B4: =+hist_Forward5YearRNatR_wFG!D4 -> 2.0224967 | C4: =+hist_Forward5YearRNatR_woFG!D4 -> 2.0472043 | F4: =+'Chart NA - DSGE Raw Data'!D7 -> 0.735
A5: =+hist_Forward5YearRNatR_wFG!A5 -> 22281 | B5: =+hist_Forward5YearRNatR_wFG!D5 -> 2.1038496 | C5: =+hist_Forward5YearRNatR_woFG!D5 -> 2.1287228 | F5: =+'Chart NA - DSGE Raw Data'!D8 -> 0.575
A6: =+hist_Forward5YearRNatR_wFG!A6 -> 22371 | B6: =+hist_Forward5YearRNatR_wFG!D6 -> 2.1590386 | C6: =+hist_Forward5YearRNatR_woFG!D6 -> 2.184054 | D6: =+'HLW - 2025Q2'!K7 -> 5.4405595 | F6: =+'Chart NA - DSGE Raw Data'!D9 -> 0.4975
A7: =+hist_Forward5YearRNatR_wFG!A7 -> 22462 | B7: =+hist_Forward5YearRNatR_wFG!D7 -> 2.1723315 | C7: =+hist_Forward5YearRNatR_woFG!D7 -> 2.1974639 | D7: =+'HLW - 2025Q2'!K8 -> 5.6616372 | F7: =+'Chart NA - DSGE Raw Data'!D10 -> 0.4325
A8: =+hist_Forward5YearRNatR_wFG!A8 -> 22554 | B8: =+hist_Forward5YearRNatR_wFG!D8 -> 2.2626478 | C8: =+hist_Forward5YearRNatR_woFG!D8 -> 2.2878702 | D8: =+'HLW - 2025Q2'!K9 -> 5.56877 | F8: =+'Chart NA - DSGE Raw Data'!D11 -> 0.42
A9: =+hist_Forward5YearRNatR_wFG!A9 -> 22646 | B9: =+hist_Forward5YearRNatR_wFG!D9 -> 2.373264 | C9: =+hist_Forward5YearRNatR_woFG!D9 -> 2.3985468 | D9: =+'HLW - 2025Q2'!K10 -> 5.5381696 | F9: =+'Chart NA - DSGE Raw Data'!D12 -> 0.6
A10: =+hist_Forward5YearRNatR_wFG!A10 -> 22736 | B10: =+hist_Forward5YearRNatR_wFG!D10 -> 2.4914681 | C10: =+hist_Forward5YearRNatR_woFG!D10 -> 2.5167794 | D10: =+'HLW - 2025Q2'!K11 -> 5.3529621 | F10: =+'Chart NA - DSGE Raw Data'!D13 -> 0.615
A11: =+hist_Forward5YearRNatR_wFG!A11 -> 22827 | B11: =+hist_Forward5YearRNatR_wFG!D11 -> 2.4933496 | C11: =+hist_Forward5YearRNatR_woFG!D11 -> 2.5186543 | D11: =+'HLW - 2025Q2'!K12 -> 4.8206328 | F11: =+'Chart NA - DSGE Raw Data'!D14 -> 0.6525
A12: =+hist_Forward5YearRNatR_wFG!A12 -> 22919 | B12: =+hist_Forward5YearRNatR_wFG!D12 -> 2.5797766 | C12: =+hist_Forward5YearRNatR_woFG!D12 -> 2.6050366 | D12: =+'HLW - 2025Q2'!K13 -> 4.7095343 | F12: =+'Chart NA - DSGE Raw Data'!D15 -> 0.7125
A13: =+hist_Forward5YearRNatR_wFG!A13 -> 23011 | B13: =+hist_Forward5YearRNatR_wFG!D13 -> 2.6508134 | C13: =+hist_Forward5YearRNatR_woFG!D13 -> 2.6759866 | D13: =+'HLW - 2025Q2'!K14 -> 4.2590645 | F13: =+'Chart NA - DSGE Raw Data'!D16 -> 0.73
A14: =+hist_Forward5YearRNatR_wFG!A14 -> 23101 | B14: =+hist_Forward5YearRNatR_wFG!D14 -> 2.7580187 | C14: =+hist_Forward5YearRNatR_woFG!D14 -> 2.783059 | D14: =+'HLW - 2025Q2'!K15 -> 4.2440707 | F14: =+'Chart NA - DSGE Raw Data'!D17 -> 0.7425
A15: =+hist_Forward5YearRNatR_wFG!A15 -> 23192 | B15: =+hist_Forward5YearRNatR_wFG!D15 -> 2.8481428 | C15: =+hist_Forward5YearRNatR_woFG!D15 -> 2.8729992 | D15: =+'HLW - 2025Q2'!K16 -> 4.2115101 | F15: =+'Chart NA - DSGE Raw Data'!D18 -> 0.74
A16: =+hist_Forward5YearRNatR_wFG!A16 -> 23284 | B16: =+hist_Forward5YearRNatR_wFG!D16 -> 2.920799 | C16: =+hist_Forward5YearRNatR_woFG!D16 -> 2.9454155 | D16: =+'HLW - 2025Q2'!K17 -> 4.5380331 | F16: =+'Chart NA - DSGE Raw Data'!D19 -> 0.8325
A17: =+hist_Forward5YearRNatR_wFG!A17 -> 23376 | B17: =+hist_Forward5YearRNatR_wFG!D17 -> 3.0040085 | C17: =+hist_Forward5YearRNatR_woFG!D17 -> 3.0283234 | D17: =+'HLW - 2025Q2'!K18 -> 4.2689899 | F17: =+'Chart NA - DSGE Raw Data'!D20 -> 0.8625
... A29: =+hist_Forward5YearRNatR_wFG!A29 -> 24472 | B29: =+hist_Forward5YearRNatR_wFG!D29 -> 2.8636972 | C29: =+hist_Forward5YearRNatR_woFG!D29 -> 2.8868701 | D29: =+'HLW - 2025Q2'!K30 -> 5.0873863 | F29: =+'Chart NA - DSGE Raw Data'!D32 -> 1.39
A30: =+hist_Forward5YearRNatR_wFG!A30 -> 24562 | B30: =+hist_Forward5YearRNatR_wFG!D30 -> 2.8538048 | C30: =+hist_Forward5YearRNatR_woFG!D30 -> 2.8769765 | D30: =+'HLW - 2025Q2'!K31 -> 5.0534309 | E30: =+LM_RealRate!C2 -> 1.6036491 | F30: =+'Chart NA - DSGE Raw Data'!D33 -> 1.205
A31: =+hist_Forward5YearRNatR_wFG!A31 -> 24653 | B31: =+hist_Forward5YearRNatR_wFG!D31 -> 2.8936934 | C31: =+hist_Forward5YearRNatR_woFG!D31 -> 2.9168691 | D31: =+'HLW - 2025Q2'!K32 -> 4.829954 | E31: =+LM_RealRate!C3 -> 1.5611101 | F31: =+'Chart NA - DSGE Raw Data'!D34 -> 0.9975
A32: =+hist_Forward5YearRNatR_wFG!A32 -> 24745 | B32: =+hist_Forward5YearRNatR_wFG!D32 -> 2.8019768 | C32: =+hist_Forward5YearRNatR_woFG!D32 -> 2.8251606 | D32: =+'HLW - 2025Q2'!K33 -> 4.8518558 | E32: =+LM_RealRate!C4 -> 1.5822769 | F32: =+'Chart NA - DSGE Raw Data'!D35 -> 0.9725
A33: =+hist_Forward5YearRNatR_wFG!A33 -> 24837 | B33: =+hist_Forward5YearRNatR_wFG!D33 -> 2.7824148 | C33: =+hist_Forward5YearRNatR_woFG!D33 -> 2.80561 | D33: =+'HLW - 2025Q2'!K34 -> 4.7817679 | E33: =+LM_RealRate!C5 -> 1.5874445 | F33: =+'Chart NA - DSGE Raw Data'!D36 -> 1.0425
A34: =+hist_Forward5YearRNatR_wFG!A34 -> 24928 | B34: =+hist_Forward5YearRNatR_wFG!D34 -> 2.5812702 | C34: =+hist_Forward5YearRNatR_woFG!D34 -> 2.6044794 | D34: =+'HLW - 2025Q2'!K35 -> 5.0033801 | E34: =+LM_RealRate!C6 -> 1.6251452 | F34: =+'Chart NA - DSGE Raw Data'!D37 -> 1.1975
A35: =+hist_Forward5YearRNatR_wFG!A35 -> 25019 | B35: =+hist_Forward5YearRNatR_wFG!D35 -> 2.4793346 | C35: =+hist_Forward5YearRNatR_woFG!D35 -> 2.5025598 | D35: =+'HLW - 2025Q2'!K36 -> 5.0654007 | E35: =+LM_RealRate!C7 -> 1.6449017 | F35: =+'Chart NA - DSGE Raw Data'!D38 -> 1.495
A36: =+hist_Forward5YearRNatR_wFG!A36 -> 25111 | B36: =+hist_Forward5YearRNatR_wFG!D36 -> 2.3898348 | C36: =+hist_Forward5YearRNatR_woFG!D36 -> 2.4130776 | D36: =+'HLW - 2025Q2'!K37 -> 4.9311537 | E36: =+LM_RealRate!C8 -> 1.5864502 | F36: =+'Chart NA - DSGE Raw Data'!D39 -> 1.4875
A37: =+hist_Forward5YearRNatR_wFG!A37 -> 25203 | B37: =+hist_Forward5YearRNatR_wFG!D37 -> 2.4169603 | C37: =+hist_Forward5YearRNatR_woFG!D37 -> 2.4402214 | D37: =+'HLW - 2025Q2'!K38 -> 4.7783574 | E37: =+LM_RealRate!C9 -> 1.5816322 | F37: =+'Chart NA - DSGE Raw Data'!D40 -> 1.48
A38: =+hist_Forward5YearRNatR_wFG!A38 -> 25293 | B38: =+hist_Forward5YearRNatR_wFG!D38 -> 2.4410874 | C38: =+hist_Forward5YearRNatR_woFG!D38 -> 2.4643675 | D38: =+'HLW - 2025Q2'!K39 -> 4.905168 | E38: =+LM_RealRate!C10 -> 1.6453404 | F38: =+'Chart NA - DSGE Raw Data'!D41 -> 1.6425
A39: =+hist_Forward5YearRNatR_wFG!A39 -> 25384 | B39: =+hist_Forward5YearRNatR_wFG!D39 -> 2.2780856 | C39: =+hist_Forward5YearRNatR_woFG!D39 -> 2.3013845 | D39: =+'HLW - 2025Q2'!K40 -> 4.7139562 | E39: =+LM_RealRate!C11 -> 1.712491 | F39: =+'Chart NA - DSGE Raw Data'!D42 -> 2.0825
A40: =+hist_Forward5YearRNatR_wFG!A40 -> 25476 | B40: =+hist_Forward5YearRNatR_wFG!D40 -> 2.2026074 | C40: =+hist_Forward5YearRNatR_woFG!D40 -> 2.2259247 | D40: =+'HLW - 2025Q2'!K41 -> 4.6689004 | E40: =+LM_RealRate!C12 -> 1.700828 | F40: =+'Chart NA - DSGE Raw Data'!D43 -> 2.245
A41: =+hist_Forward5YearRNatR_wFG!A41 -> 25568 | B41: =+hist_Forward5YearRNatR_wFG!D41 -> 2.1943031 | C41: =+hist_Forward5YearRNatR_woFG!D41 -> 2.217638 | D41: =+'HLW - 2025Q2'!K42 -> 4.3921348 | E41: =+LM_RealRate!C13 -> 1.6557247 | F41: =+'Chart NA - DSGE Raw Data'!D44 -> 2.235
... A260: =+hist_Forward5YearRNatR_wFG!A260 -> 45565 | B260: =+hist_Forward5YearRNatR_wFG!D260 -> 1.3305879 | C260: =+hist_Forward5YearRNatR_woFG!D260 -> 1.4693021 | D260: =+'HLW - 2025Q2'!K261 -> 0.81923691 | E260: =+LM_RealRate!C232 -> 2.1404005 | F260: =+'Chart NA - DSGE Raw Data'!D263 -> 1.315
B263: =+CORREL(B2:B260,$F$2:$F$260) -> 0.52477817 | C263: =+CORREL(C2:C260,$F$2:$F$260) -> 0.49861578 | D263: =+CORREL(D2:D260,$F$2:$F$260) -> 0.52995417 | E263: =+CORREL(E2:E260,$F$2:$F$260) -> 0.66706477

Sheet Decomposition
A1: Date | B1: Trend Growth (g), Annualized | C1: Other Determinants (z) | D1: HLW r* | E1: Trend Growth (g), Annualized | F1: Other Determinants (z) | G1: HLW r*
A2: 22282 | B2: =+'HLW - 2025Q2'!C7 -> 4.9495375 | C2: =+'HLW - 2025Q2'!G7 -> 0.005243984 | D2: =+'HLW - 2025Q2'!K7 -> 5.4405595
A3: 22372 | B3: =+'HLW - 2025Q2'!C8 -> 5.1448666 | C3: =+'HLW - 2025Q2'!G8 -> 0.011821837 | D3: =+'HLW - 2025Q2'!K8 -> 5.6616372
A4: 22463 | B4: =+'HLW - 2025Q2'!C9 -> 5.0578663 | C4: =+'HLW - 2025Q2'!G9 -> 0.014493655 | D4: =+'HLW - 2025Q2'!K9 -> 5.56877
A5: 22555 | B5: =+'HLW - 2025Q2'!C10 -> 5.0328481 | C5: =+'HLW - 2025Q2'!G10 -> 0.011366898 | D5: =+'HLW - 2025Q2'!K10 -> 5.5381696
A6: 22647 | B6: =+'HLW - 2025Q2'!C11 -> 4.861899 | C6: =+'HLW - 2025Q2'!G11 -> 0.013886533 | D6: =+'HLW - 2025Q2'!K11 -> 5.3529621
A7: 22737 | B7: =+'HLW - 2025Q2'!C12 -> 4.3830335 | C7: =+'HLW - 2025Q2'!G12 -> 0.0074214461 | D7: =+'HLW - 2025Q2'!K12 -> 4.8206328
A8: 22828 | B8: =+'HLW - 2025Q2'!C13 -> 4.2850229 | C8: =+'HLW - 2025Q2'!G13 -> 0.003952891 | D8: =+'HLW - 2025Q2'!K13 -> 4.7095343
A9: 22920 | B9: =+'HLW - 2025Q2'!C14 -> 3.8884721 | C9: =+'HLW - 2025Q2'!G14 -> -0.011046073 | D9: =+'HLW - 2025Q2'!K14 -> 4.2590645
A10: 23012 | B10: =+'HLW - 2025Q2'!C15 -> 3.8697114 | C10: =+'HLW - 2025Q2'!G15 -> -0.0054378924 | D10: =+'HLW - 2025Q2'!K15 -> 4.2440707
A11: 23102 | B11: =+'HLW - 2025Q2'!C16 -> 3.8368419 | C11: =+'HLW - 2025Q2'!G16 -> -0.0019030078 | D11: =+'HLW - 2025Q2'!K16 -> 4.2115101
A12: 23193 | B12: =+'HLW - 2025Q2'!C17 -> 4.1271433 | C12: =+'HLW - 2025Q2'!G17 -> 0.0058265986 | D12: =+'HLW - 2025Q2'!K17 -> 4.5380331
A13: 23285 | B13: =+'HLW - 2025Q2'!C18 -> 3.8778412 | C13: =+'HLW - 2025Q2'!G18 -> 0.010553546 | D13: =+'HLW - 2025Q2'!K18 -> 4.2689899
... A183: 38808 | B183: =+'HLW - 2025Q2'!C188 -> 2.7416689 | C183: =+'HLW - 2025Q2'!G188 -> -0.3277393 | D183: =+'HLW - 2025Q2'!K188 -> 2.6830138
A184: 38899 | B184: =+'HLW - 2025Q2'!C189 -> 2.7020216 | C184: =+'HLW - 2025Q2'!G189 -> -0.45027647 | D184: =+'HLW - 2025Q2'!K189 -> 2.5169382 | H184: g | I184: z | J184: Growth | K184: Safety+Liquidity | L184: Government | M184: Others
A185: 38991 | B185: =+'HLW - 2025Q2'!C190 -> 2.8096463 | C185: =+'HLW - 2025Q2'!G190 -> -0.5347939 | D185: =+'HLW - 2025Q2'!K190 -> 2.5506084 | E185: =+B185-$B$185 -> 0 | F185: =+C185-$C$185 -> 0 | G185: =+D185-$D$185 -> 0
A186: 39083 | B186: =+'HLW - 2025Q2'!C191 -> 2.7472112 | C186: =+'HLW - 2025Q2'!G191 -> -0.45289724 | D186: =+'HLW - 2025Q2'!K191 -> 2.5639422 | E186: =+B186-$B$185 -> -0.062435073 | F186: =+C186-$C$185 -> 0.081896662 | G186: =+D186-$D$185 -> 0.013333827 | H186: =E186 -> -0.062435073 | I186: =F186 -> 0.081896662 | J186: -0.051272201 | K186: 0.36638119 | L186: -0.091415602 | M186: 0.028175116
A187: 39173 | B187: =+'HLW - 2025Q2'!C192 -> 2.8004912 | C187: =+'HLW - 2025Q2'!G192 -> -0.58665465 | D187: =+'HLW - 2025Q2'!K192 -> 2.4886939 | E187: =+B187-$B$185 -> -0.0091551362 | F187: =+C187-$C$185 -> -0.051860748 | G187: =+D187-$D$185 -> -0.061914425 | H187: =E187 -> -0.0091551362 | I187: =F187 -> -0.051860748 | J187: -0.084617145 | K187: 0.16922339 | L187: -0.095807612 | M187: 0.027817345
A188: 39264 | B188: =+'HLW - 2025Q2'!C193 -> 2.8079719 | C188: =+'HLW - 2025Q2'!G193 -> -0.5772525 | D188: =+'HLW - 2025Q2'!K193 -> 2.5063111 | E188: =+B188-$B$185 -> -0.0016743697 | F188: =+C188-$C$185 -> -0.042458597 | G188: =+D188-$D$185 -> -0.0442973 | H188: =E188 -> -0.0016743697 | I188: =F188 -> -0.042458597 | J188: -0.067763489 | K188: -0.026765674 | L188: -0.092857246 | M188: 0.027464357
A189: 39356 | B189: =+'HLW - 2025Q2'!C194 -> 2.8090337 | C189: =+'HLW - 2025Q2'!G194 -> -0.47714374 | D189: =+'HLW - 2025Q2'!K194 -> 2.6075858 | E189: =+B189-$B$185 -> -0.00061259803 | F189: =+C189-$C$185 -> 0.05765016 | G189: =+D189-$D$185 -> 0.056977438 | H189: =E189 -> -0.00061259803 | I189: =F189 -> 0.05765016 | J189: -0.16942974 | K189: -0.25560965 | L189: -0.094503573 | M189: 0.027116084
A190: 39448 | B190: =+'HLW - 2025Q2'!C195 -> 2.6240108 | C190: =+'HLW - 2025Q2'!G195 -> -0.56349617 | D190: =+'HLW - 2025Q2'!K195 -> 2.3180512 | E190: =+B190-$B$185 -> -0.1856355 | F190: =+C190-$C$185 -> -0.028702265 | G190: =+D190-$D$185 -> -0.23255718 | H190: =E190 -> -0.1856355 | I190: =F190 -> -0.028702265 | J190: -0.2151245 | K190: -0.18959172 | L190: -0.09745303 | M190: 0.026772462
A191: 39539 | B191: =+'HLW - 2025Q2'!C196 -> 2.6679739 | C191: =+'HLW - 2025Q2'!G196 -> -0.61932463 | D191: =+'HLW - 2025Q2'!K196 -> 2.3105006 | E191: =+B191-$B$185 -> -0.14167242 | F191: =+C191-$C$185 -> -0.084530727 | G191: =+D191-$D$185 -> -0.24010775 | H191: =E191 -> -0.14167242 | I191: =F191 -> -0.084530727 | J191: -0.25556557 | K191: -0.32710643 | L191: -0.082949481 | M191: 0.026433429
A192: 39630 | B192: =+'HLW - 2025Q2'!C197 -> 2.4229234 | C192: =+'HLW - 2025Q2'!G197 -> -0.62062313 | D192: =+'HLW - 2025Q2'!K197 -> 2.0401009 | E192: =+B192-$B$185 -> -0.3867229 | F192: =+C192-$C$185 -> -0.085829224 | G192: =+D192-$D$185 -> -0.51050748 | H192: =E192 -> -0.3867229 | I192: =F192 -> -0.085829224 | J192: -0.34029744 | K192: -1.3061164 | L192: -0.050147653 | M192: 0.02609892
A193: 39722 | B193: =+'HLW - 2025Q2'!C198 -> 1.943172 | C193: =+'HLW - 2025Q2'!G198 -> -0.98967899 | D193: =+'HLW - 2025Q2'!K198 -> 1.1442079 | E193: =+B193-$B$185 -> -0.86647427 | F193: =+C193-$C$185 -> -0.45488509 | G193: =+D193-$D$185 -> -1.4064005 | H193: =E193 -> -0.86647427 | I193: =F193 -> -0.45488509 | J193: -0.44568968 | K193: -1.0836385 | L193: -0.035773165 | M193: 0.025768875
A194: 39814 | B194: =+'HLW - 2025Q2'!C199 -> 1.7097646 | C194: =+'HLW - 2025Q2'!G199 -> -1.0492433 | D194: =+'HLW - 2025Q2'!K199 -> 0.82832809 | E194: =+B194-$B$185 -> -1.0998817 | F194: =+C194-$C$185 -> -0.51444939 | G194: =+D194-$D$185 -> -1.7222803 | H194: =E194 -> -1.0998817 | I194: =F194 -> -0.51444939 | J194: -0.4159583 | K194: -0.79361889 | L194: -0.02408911 | M194: 0.025443232
A195: 39904 | B195: =+'HLW - 2025Q2'!C200 -> 1.5954609 | C195: =+'HLW - 2025Q2'!G200 -> -0.87053592 | D195: =+'HLW - 2025Q2'!K200 -> 0.88151327 | E195: =+B195-$B$185 -> -1.2141855 | F195: =+C195-$C$185 -> -0.33574201 | G195: =+D195-$D$185 -> -1.6690951 | H195: =E195 -> -1.2141855 | I195: =F195 -> -0.33574201 | J195: -0.58166051 | K195: -0.53533348 | L195: -0.039925577 | M195: 0.02512193
A196: 39995 | B196: =+'HLW - 2025Q2'!C201 -> 1.5603428 | C196: =+'HLW - 2025Q2'!G201 -> -0.82619721 | D196: =+'HLW - 2025Q2'!K201 -> 0.88728722 | E196: =+B196-$B$185 -> -1.2493035 | F196: =+C196-$C$185 -> -0.2914033 | G196: =+D196-$D$185 -> -1.6633211 | H196: =E196 -> -1.2493035 | I196: =F196 -> -0.2914033 | J196: -0.54156944 | K196: -0.42733054 | L196: -0.027038449 | M196: 0.02480491
A197: 40087 | B197: =+'HLW - 2025Q2'!C202 -> 1.6072745 | C197: =+'HLW - 2025Q2'!G202 -> -0.60830285 | D197: =+'HLW - 2025Q2'!K202 -> 1.1567195 | E197: =+B197-$B$185 -> -1.2023718 | F197: =+C197-$C$185 -> -0.073508945 | G197: =+D197-$D$185 -> -1.3938889 | H197: =E197 -> -1.2023718 | I197: =F197 -> -0.073508945 | J197: -0.81337801 | K197: -0.41276895 | L197: -0.028494114 | M197: 0.024492113
... A259: 45748 | B259: =+'HLW - 2025Q2'!C264 -> 2.4501884 | C259: =+'HLW - 2025Q2'!G264 -> -1.8508269 | D259: =+'HLW - 2025Q2'!K264 -> 0.83983803 | E259: =+B259-$B$185 -> -0.3594579 | F259: =+C259-$C$185 -> -1.316033 | G259: =+D259-$D$185 -> -1.7107703 | H259: =E259 -> -0.3594579 | I259: =F259 -> -1.316033 | J259: -0.45597052 | K259: 0.0704826 | L259: -0.1830374 | M259: 0.011355456
J260: -0.44789026 | K260: 0.067038362 | L260: -0.18085861 | M260: 0.011218732 | N260: 2.73374e-05 | O260: 1.1259527e-06
J261: -0.43939327 | K261: 0.064012899 | L261: -0.17869808 | M261: 0.011083748 | N261: 0.00055720115 | O261: -3.2784654e-05
J262: -0.43057563 | K262: 0.061360536 | L262: -0.17655744 | M262: 0.010950479 | N262: 0.0010264363 | O262: -6.2736088e-05
J263: -0.42152321 | K263: 0.059040063 | L263: -0.17443798 | M263: 0.010818901 | N263: 0.0014429872 | O263: -8.9262324e-05
J264: -0.41231208 | K264: 0.057014312 | L264: -0.17234064 | M264: 0.010688993 | N264: 0.0018133855 | O264: -0.00011280029
J265: -0.4030091 | K265: 0.055249798 | L265: -0.17026615 | M265: 0.01056073 | N265: 0.0021430453 | O265: -0.00013371047
J266: -0.39367252 | K266: 0.053716396 | L266: -0.16821503 | M266: 0.010434092 | N266: 0.0024364891 | O266: -0.00015229263
J267: -0.38435272 | K267: 0.052387042 | L267: -0.16618763 | M267: 0.010309055 | N267: 0.0026975241 | O267: -0.000168798
J268: -0.37509285 | K268: 0.051237465 | L268: -0.16418418 | M268: 0.010185599 | N268: 0.0029293796 | O268: -0.00018343876
J269: -0.36592955 | K269: 0.050245933 | L269: -0.16220482 | M269: 0.010063701 | N269: 0.0031348158 | O269: -0.00019639553
J270: -0.35689359 | K270: 0.049393022 | L270: -0.16024957 | M270: 0.0099433417 | N270: 0.0033162103 | O270: -0.00020782323
J271: -0.34801052 | K271: 0.048661398 | L271: -0.15831841 | M271: 0.0098244988 | N271: 0.0034756273 | O271: -0.00021785587
... J315: -0.13979845 | K315: 0.042231546 | L315: -0.093734333 | M315: 0.0058287268 | N315: 0.0020884528 | O315: -0.00012896147
L316: 0.00073663629 | M316: -0.0027645377 | N316: 0.0021615161 | O316: -0.00013361476
L317: 0.00077226247 | M317: -0.0027317538 | N317: 0.0020884528 | O317: -0.00012896147

Sheet DSGE HVD wFG
A1: date | B1: =+wFG_rstar_shock_decomposition!E1 -> g | C1: =+wFG_rstar_shock_decomposition!F1 -> b_liq | D1: =+wFG_rstar_shock_decomposition!G1 -> b_safe | E1: =+wFG_rstar_shock_decomposition!H1 -> FF | F1: =+wFG_rstar_shock_decomposition!I1 -> z | G1: =+wFG_rstar_shock_decomposition!J1 -> p-mkp | H1: =+wFG_rstar_shock_decomposition!K1 -> w-mkp | I1: =+wFG_rstar_shock_decomposition!L1 -> pol | ... T1: =+wFG_rstar_shock_decomposition!W1 -> dt | U1: DSGE r* | X1: Chart | Y1: Date | Z1: Government | AA1: Liquidity | AB1: Safety | AC1: Technology | AD1: Financial Frictions | AE1: Investment Specific Technology | AF1: Price Markups | AG1: Wage Markups | AH1: Others | AI1: DSGE r* (with FG) | AJ1: Growth | AK1: Safety+Liquidity | AL1: Government | AM1: Others | AN1: Total | AO1: Growth | AP1: Safety+Liquidity | AQ1: Government | AR1: Others | AS1: Total
A2: 39172 | B2: =+wFG_rstar_shock_decomposition!E2 -> -0.10116499 | C2: =+wFG_rstar_shock_decomposition!F2 -> -0.14808542 | D2: =+wFG_rstar_shock_decomposition!G2 -> 0.49991388 | E2: =+wFG_rstar_shock_decomposition!H2 -> -0.023433525 | F2: =+wFG_rstar_shock_decomposition!I2 -> 0.13159807 | G2: =+wFG_rstar_shock_decomposition!J2 -> 3.835998e-16 | H2: =+wFG_rstar_shock_decomposition!K2 -> -3.6594233e-15 | I2: =+wFG_rstar_shock_decomposition!L2 -> 1.4552564e-14 | ... T2: =+wFG_rstar_shock_decomposition!W2 -> 0.028537733 | U2: =+wFG_rstar_shock_decomposition!D2 -> 0.35147615 | Y2: =+A2 -> 39172 | Z2: =+B2 -> -0.10116499 | AA2: =+C2 -> -0.14808542 | AB2: =+D2 -> 0.49991388 | AC2: =+F2+S2 -> 0.14174747 | AD2: =+E2 -> -0.023433525 | AE2: =+Q2 -> -0.046038989 | AF2: =+G2 -> 3.835998e-16 | AG2: =+H2 -> -3.6594233e-15 | AH2: =+SUM(T2,I2:P2) -> 0.028537733 | AI2: =+SUM(Z2:AH2) -> 0.35147615 | AJ2: =SUM(AC2+AE2) -> 0.095708486 | AK2: =AB2+AA2+AD2 -> 0.32839493 | AL2: =Z2 -> -0.10116499 | AM2: =AH2 -> 0.028537733 | AN2: =SUM(AJ2:AM2) -> 0.35147615
A3: 39263 | B3: =+wFG_rstar_shock_decomposition!E3 -> -0.091415602 | C3: =+wFG_rstar_shock_decomposition!F3 -> -0.16817797 | D3: =+wFG_rstar_shock_decomposition!G3 -> 0.55181563 | E3: =+wFG_rstar_shock_decomposition!H3 -> -0.017256471 | F3: =+wFG_rstar_shock_decomposition!I3 -> 0.11475644 | G3: =+wFG_rstar_shock_decomposition!J3 -> 5.4879435e-16 | H3: =+wFG_rstar_shock_decomposition!K3 -> -2.4440355e-15 | I3: =+wFG_rstar_shock_decomposition!L3 -> 1.3433653e-14 | ... T3: =+wFG_rstar_shock_decomposition!W3 -> 0.028175116 | U3: =+wFG_rstar_shock_decomposition!D3 -> 0.25186851 | Y3: =+A3 -> 39263 | Z3: =+B3 -> -0.091415602 | AA3: =+C3 -> -0.16817797 | AB3: =+D3 -> 0.55181563 | AC3: =+F3+S3 -> -0.012256044 | AD3: =+E3 -> -0.017256471 | AE3: =+Q3 -> -0.039016157 | AF3: =+G3 -> 5.4879435e-16 | AG3: =+H3 -> -2.4440355e-15 | AH3: =+SUM(T3,I3:P3) -> 0.028175116 | AI3: =+SUM(Z3:AH3) -> 0.25186851 | AJ3: =SUM(AC3+AE3) -> -0.051272201 | AK3: =AB3+AA3+AD3 -> 0.36638119 | AL3: =Z3 -> -0.091415602 | AM3: =AH3 -> 0.028175116 | AN3: =SUM(AJ3:AM3) -> 0.25186851 | AO3: =(AJ3-AJ2)/($AN3-$AN2) -> 1.4755964 | AP3: =(AK3-AK2)/($AN3-$AN2) -> -0.38135894 | AQ3: =(AL3-AL2)/($AN3-$AN2) -> -0.097877908 | AR3: =(AM3-AM2)/($AN3-$AN2) -> 0.0036404606 | AS3: =(AN3-AN2)/($AN3-$AN2) -> 1
A4: 39355 | B4: =+wFG_rstar_shock_decomposition!E4 -> -0.095807612 | C4: =+wFG_rstar_shock_decomposition!F4 -> -0.33979271 | D4: =+wFG_rstar_shock_decomposition!G4 -> 0.56002226 | E4: =+wFG_rstar_shock_decomposition!H4 -> -0.051006152 | F4: =+wFG_rstar_shock_decomposition!I4 -> 0.13362002 | G4: =+wFG_rstar_shock_decomposition!J4 -> 2.5037011e-16 | H4: =+wFG_rstar_shock_decomposition!K4 -> -1.4001092e-15 | I4: =+wFG_rstar_shock_decomposition!L4 -> 1.3980609e-14 | ... T4: =+wFG_rstar_shock_decomposition!W4 -> 0.027817345 | U4: =+wFG_rstar_shock_decomposition!D4 -> 0.016615982 | Y4: =+A4 -> 39355 | Z4: =+B4 -> -0.095807612 | AA4: =+C4 -> -0.33979271 | AB4: =+D4 -> 0.56002226 | AC4: =+F4+S4 -> -0.028311233 | AD4: =+E4 -> -0.051006152 | AE4: =+Q4 -> -0.056305913 | AF4: =+G4 -> 2.5037011e-16 | AG4: =+H4 -> -1.4001092e-15 | AH4: =+SUM(T4,I4:P4) -> 0.027817345 | AI4: =+SUM(Z4:AH4) -> 0.016615982 | AJ4: =SUM(AC4+AE4) -> -0.084617145 | AK4: =AB4+AA4+AD4 -> 0.16922339 | AL4: =Z4 -> -0.095807612 | AM4: =AH4 -> 0.027817345 | AN4: =SUM(AJ4:AM4) -> 0.016615982 | AO4: =(AJ4-AJ3)/($AN4-$AN3) -> 0.14174107 | AP4: =(AK4-AK3)/($AN4-$AN3) -> 0.83806879 | AQ4: =(AL4-AL3)/($AN4-$AN3) -> 0.018669343 | AR4: =(AM4-AM3)/($AN4-$AN3) -> 0.0015207924 | AS4: =(AN4-AN3)/($AN4-$AN3) -> 1
A5: 39447 | B5: =+wFG_rstar_shock_decomposition!E5 -> -0.092857246 | C5: =+wFG_rstar_shock_decomposition!F5 -> -0.47721599 | D5: =+wFG_rstar_shock_decomposition!G5 -> 0.53555175 | E5: =+wFG_rstar_shock_decomposition!H5 -> -0.085101434 | F5: =+wFG_rstar_shock_decomposition!I5 -> 0.13642795 | G5: =+wFG_rstar_shock_decomposition!J5 -> -2.6306488e-16 | H5: =+wFG_rstar_shock_decomposition!K5 -> -7.9837506e-16 | I5: =+wFG_rstar_shock_decomposition!L5 -> 1.5589942e-14 | ... T5: =+wFG_rstar_shock_decomposition!W5 -> 0.027464357 | U5: =+wFG_rstar_shock_decomposition!D5 -> -0.15992205 | Y5: =+A5 -> 39447 | Z5: =+B5 -> -0.092857246 | AA5: =+C5 -> -0.47721599 | AB5: =+D5 -> 0.53555175 | AC5: =+F5+S5 -> 0.0013142414 | AD5: =+E5 -> -0.085101434 | AE5: =+Q5 -> -0.069077731 | AF5: =+G5 -> -2.6306488e-16 | AG5: =+H5 -> -7.9837506e-16 | AH5: =+SUM(T5,I5:P5) -> 0.027464357 | AI5: =+SUM(Z5:AH5) -> -0.15992205 | AJ5: =SUM(AC5+AE5) -> -0.067763489 | AK5: =AB5+AA5+AD5 -> -0.026765674 | AL5: =Z5 -> -0.092857246 | AM5: =AH5 -> 0.027464357 | AN5: =SUM(AJ5:AM5) -> -0.15992205 | AO5: =(AJ5-AJ4)/($AN5-$AN4) -> -0.095467565 | AP5: =(AK5-AK4)/($AN5-$AN4) -> 1.1101804 | AQ5: =(AL5-AL4)/($AN5-$AN4) -> -0.016712354 | AR5: =(AM5-AM4)/($AN5-$AN4) -> 0.0019995064 | AS5: =(AN5-AN4)/($AN5-$AN4) -> 1
A6: 39538 | B6: =+wFG_rstar_shock_decomposition!E6 -> -0.094503573 | C6: =+wFG_rstar_shock_decomposition!F6 -> -0.63793934 | D6: =+wFG_rstar_shock_decomposition!G6 -> 0.48092883 | E6: =+wFG_rstar_shock_decomposition!H6 -> -0.09859914 | F6: =+wFG_rstar_shock_decomposition!I6 -> 0.14786982 | G6: =+wFG_rstar_shock_decomposition!J6 -> 1.4712008e-17 | H6: =+wFG_rstar_shock_decomposition!K6 -> -1.4965976e-16 | I6: =+wFG_rstar_shock_decomposition!L6 -> 1.6862544e-14 | ... T6: =+wFG_rstar_shock_decomposition!W6 -> 0.027116084 | U6: =+wFG_rstar_shock_decomposition!D6 -> -0.49242688 | Y6: =+A6 -> 39538 | Z6: =+B6 -> -0.094503573 | AA6: =+C6 -> -0.63793934 | AB6: =+D6 -> 0.48092883 | AC6: =+F6+S6 -> -0.10652621 | AD6: =+E6 -> -0.09859914 | AE6: =+Q6 -> -0.06290353 | AF6: =+G6 -> 1.4712008e-17 | AG6: =+H6 -> -1.4965976e-16 | AH6: =+SUM(T6,I6:P6) -> 0.027116084 | AI6: =+SUM(Z6:AH6) -> -0.49242688 | AJ6: =SUM(AC6+AE6) -> -0.16942974 | AK6: =AB6+AA6+AD6 -> -0.25560965 | AL6: =Z6 -> -0.094503573 | AM6: =AH6 -> 0.027116084 | AN6: =SUM(AJ6:AM6) -> -0.49242688 | AO6: =(AJ6-AJ5)/($AN6-$AN5) -> 0.30575871 | AP6: =(AK6-AK5)/($AN6-$AN5) -> 0.68824258 | AQ6: =(AL6-AL5)/($AN6-$AN5) -> 0.0049512883 | AR6: =(AM6-AM5)/($AN6-$AN5) -> 0.0010474221 | AS6: =(AN6-AN5)/($AN6-$AN5) -> 1
A7: 39629 | B7: =+wFG_rstar_shock_decomposition!E7 -> -0.09745303 | C7: =+wFG_rstar_shock_decomposition!F7 -> -0.60173872 | D7: =+wFG_rstar_shock_decomposition!G7 -> 0.51265011 | E7: =+wFG_rstar_shock_decomposition!H7 -> -0.10050311 | F7: =+wFG_rstar_shock_decomposition!I7 -> 0.14329593 | G7: =+wFG_rstar_shock_decomposition!J7 -> 1.2858785e-16 | H7: =+wFG_rstar_shock_decomposition!K7 -> 9.4075693e-16 | I7: =+wFG_rstar_shock_decomposition!L7 -> 1.8164319e-14 | ... T7: =+wFG_rstar_shock_decomposition!W7 -> 0.026772462 | U7: =+wFG_rstar_shock_decomposition!D7 -> -0.47539679 | Y7: =+A7 -> 39629 | Z7: =+B7 -> -0.09745303 | AA7: =+C7 -> -0.60173872 | AB7: =+D7 -> 0.51265011 | AC7: =+F7+S7 -> -0.1512325 | AD7: =+E7 -> -0.10050311 | AE7: =+Q7 -> -0.063892001 | AF7: =+G7 -> 1.2858785e-16 | AG7: =+H7 -> 9.4075693e-16 | AH7: =+SUM(T7,I7:P7) -> 0.026772462 | AI7: =+SUM(Z7:AH7) -> -0.47539679 | AJ7: =SUM(AC7+AE7) -> -0.2151245 | AK7: =AB7+AA7+AD7 -> -0.18959172 | AL7: =Z7 -> -0.09745303 | AM7: =AH7 -> 0.026772462 | AN7: =SUM(AJ7:AM7) -> -0.47539679 | AO7: =(AJ7-AJ6)/($AN7-$AN6) -> -2.6831775 | AP7: =(AK7-AK6)/($AN7-$AN6) -> 3.8765457 | AQ7: =(AL7-AL6)/($AN7-$AN6) -> -0.17319089 | AR7: =(AM7-AM6)/($AN7-$AN6) -> -0.020177304 | AS7: =(AN7-AN6)/($AN7-$AN6) -> 1
A8: 39721 | B8: =+wFG_rstar_shock_decomposition!E8 -> -0.082949481 | C8: =+wFG_rstar_shock_decomposition!F8 -> -0.71012197 | D8: =+wFG_rstar_shock_decomposition!G8 -> 0.48282661 | E8: =+wFG_rstar_shock_decomposition!H8 -> -0.09981108 | F8: =+wFG_rstar_shock_decomposition!I8 -> 0.1425402 | G8: =+wFG_rstar_shock_decomposition!J8 -> -4.384962e-16 | H8: =+wFG_rstar_shock_decomposition!K8 -> 1.7607749e-15 | I8: =+wFG_rstar_shock_decomposition!L8 -> 1.6133421e-14 | ... T8: =+wFG_rstar_shock_decomposition!W8 -> 0.026433429 | U8: =+wFG_rstar_shock_decomposition!D8 -> -0.63918806 | Y8: =+A8 -> 39721 | Z8: =+B8 -> -0.082949481 | AA8: =+C8 -> -0.71012197 | AB8: =+D8 -> 0.48282661 | AC8: =+F8+S8 -> -0.1996818 | AD8: =+E8 -> -0.09981108 | AE8: =+Q8 -> -0.055883769 | AF8: =+G8 -> -4.384962e-16 | AG8: =+H8 -> 1.7607749e-15 | AH8: =+SUM(T8,I8:P8) -> 0.026433429 | AI8: =+SUM(Z8:AH8) -> -0.63918806 | AJ8: =SUM(AC8+AE8) -> -0.25556557 | AK8: =AB8+AA8+AD8 -> -0.32710643 | AL8: =Z8 -> -0.082949481 | AM8: =AH8 -> 0.026433429 | AN8: =SUM(AJ8:AM8) -> -0.63918806 | AO8: =(AJ8-AJ7)/($AN8-$AN7) -> 0.24690615 | AP8: =(AK8-AK7)/($AN8-$AN7) -> 0.83957292 | AQ8: =(AL8-AL7)/($AN8-$AN7) -> -0.088548977 | AR8: =(AM8-AM7)/($AN8-$AN7) -> 0.0020699117 | AS8: =(AN8-AN7)/($AN8-$AN7) -> 1
A9: 39813 | B9: =+wFG_rstar_shock_decomposition!E9 -> -0.050147653 | C9: =+wFG_rstar_shock_decomposition!F9 -> -1.3069466 | D9: =+wFG_rstar_shock_decomposition!G9 -> 0.18081285 | E9: =+wFG_rstar_shock_decomposition!H9 -> -0.17998264 | F9: =+wFG_rstar_shock_decomposition!I9 -> 0.20167215 | G9: =+wFG_rstar_shock_decomposition!J9 -> 1.6922843e-15 | H9: =+wFG_rstar_shock_decomposition!K9 -> 2.3099358e-15 | I9: =+wFG_rstar_shock_decomposition!L9 -> 1.4070252e-14 | ... T9: =+wFG_rstar_shock_decomposition!W9 -> 0.02609892 | U9: =+wFG_rstar_shock_decomposition!D9 -> -1.6704626 | Y9: =+A9 -> 39813 | Z9: =+B9 -> -0.050147653 | AA9: =+C9 -> -1.3069466 | AB9: =+D9 -> 0.18081285 | AC9: =+F9+S9 -> -0.34549921 | AD9: =+E9 -> -0.17998264 | AE9: =+Q9 -> 0.0052017786 | AF9: =+G9 -> 1.6922843e-15 | AG9: =+H9 -> 2.3099358e-15 | AH9: =+SUM(T9,I9:P9) -> 0.02609892 | AI9: =+SUM(Z9:AH9) -> -1.6704626 | AJ9: =SUM(AC9+AE9) -> -0.34029744 | AK9: =AB9+AA9+AD9 -> -1.3061164 | AL9: =Z9 -> -0.050147653 | AM9: =AH9 -> 0.02609892 | AN9: =SUM(AJ9:AM9) -> -1.6704626 | AO9: =(AJ9-AJ8)/($AN9-$AN8) -> 0.082162281 | AP9: =(AK9-AK8)/($AN9-$AN8) -> 0.94932043 | AQ9: =(AL9-AL8)/($AN9-$AN8) -> -0.031807077 | AR9: =(AM9-AM8)/($AN9-$AN8) -> 0.00032436405 | AS9: =(AN9-AN8)/($AN9-$AN8) -> 1
A10: 39903 | B10: =+wFG_rstar_shock_decomposition!E10 -> -0.035773165 | C10: =+wFG_rstar_shock_decomposition!F10 -> -1.085552 | D10: =+wFG_rstar_shock_decomposition!G10 -> 0.23032624 | E10: =+wFG_rstar_shock_decomposition!H10 -> -0.22841274 | F10: =+wFG_rstar_shock_decomposition!I10 -> 0.18945894 | G10: =+wFG_rstar_shock_decomposition!J10 -> 1.9281286e-15 | H10: =+wFG_rstar_shock_decomposition!K10 -> 4.6174674e-15 | I10: =+wFG_rstar_shock_decomposition!L10 -> 1.0887621e-14 | ... T10: =+wFG_rstar_shock_decomposition!W10 -> 0.025768875 | U10: =+wFG_rstar_shock_decomposition!D10 -> -1.5393325 | Y10: =+A10 -> 39903 | Z10: =+B10 -> -0.035773165 | AA10: =+C10 -> -1.085552 | AB10: =+D10 -> 0.23032624 | AC10: =+F10+S10 -> -0.36687725 | AD10: =+E10 -> -0.22841274 | AE10: =+Q10 -> -0.078812432 | AF10: =+G10 -> 1.9281286e-15 | AG10: =+H10 -> 4.6174674e-15 | AH10: =+SUM(T10,I10:P10) -> 0.025768875 | AI10: =+SUM(Z10:AH10) -> -1.5393325 | AJ10: =SUM(AC10+AE10) -> -0.44568968 | AK10: =AB10+AA10+AD10 -> -1.0836385 | AL10: =Z10 -> -0.035773165 | AM10: =AH10 -> 0.025768875 | AN10: =SUM(AJ10:AM10) -> -1.5393325 | AO10: =(AJ10-AJ9)/($AN10-$AN9) -> -0.80372286 | AP10: =(AK10-AK9)/($AN10-$AN9) -> 1.6966197 | AQ10: =(AL10-AL9)/($AN10-$AN9) -> 0.10962006 | AR10: =(AM10-AM9)/($AN10-$AN9) -> -0.0025169303 | AS10: =(AN10-AN9)/($AN10-$AN9) -> 1
A11: 39994 | B11: =+wFG_rstar_shock_decomposition!E11 -> -0.02408911 | C11: =+wFG_rstar_shock_decomposition!F11 -> -0.87630027 | D11: =+wFG_rstar_shock_decomposition!G11 -> 0.24041406 | E11: =+wFG_rstar_shock_decomposition!H11 -> -0.15773268 | F11: =+wFG_rstar_shock_decomposition!I11 -> 0.14864202 | G11: =+wFG_rstar_shock_decomposition!J11 -> 1.7068416e-15 | H11: =+wFG_rstar_shock_decomposition!K11 -> 4.4703201e-15 | I11: =+wFG_rstar_shock_decomposition!L11 -> 9.4894502e-15 | ... T11: =+wFG_rstar_shock_decomposition!W11 -> 0.025443232 | U11: =+wFG_rstar_shock_decomposition!D11 -> -1.2082231 | Y11: =+A11 -> 39994 | Z11: =+B11 -> -0.02408911 | AA11: =+C11 -> -0.87630027 | AB11: =+D11 -> 0.24041406 | AC11: =+F11+S11 -> -0.31115498 | AD11: =+E11 -> -0.15773268 | AE11: =+Q11 -> -0.10480332 | AF11: =+G11 -> 1.7068416e-15 | AG11: =+H11 -> 4.4703201e-15 | AH11: =+SUM(T11,I11:P11) -> 0.025443232 | AI11: =+SUM(Z11:AH11) -> -1.2082231 | AJ11: =SUM(AC11+AE11) -> -0.4159583 | AK11: =AB11+AA11+AD11 -> -0.79361889 | AL11: =Z11 -> -0.02408911 | AM11: =AH11 -> 0.025443232 | AN11: =SUM(AJ11:AM11) -> -1.2082231 | AO11: =(AJ11-AJ10)/($AN11-$AN10) -> 0.089793219 | AP11: =(AK11-AK10)/($AN11-$AN10) -> 0.87590268 | AQ11: =(AL11-AL10)/($AN11-$AN10) -> 0.035287597 | AR11: =(AM11-AM10)/($AN11-$AN10) -> -0.00098349179 | AS11: =(AN11-AN10)/($AN11-$AN10) -> 1
A12: 40086 | B12: =+wFG_rstar_shock_decomposition!E12 -> -0.039925577 | C12: =+wFG_rstar_shock_decomposition!F12 -> -0.66815748 | D12: =+wFG_rstar_shock_decomposition!G12 -> 0.19466108 | E12: =+wFG_rstar_shock_decomposition!H12 -> -0.061837083 | F12: =+wFG_rstar_shock_decomposition!I12 -> 0.12092164 | G12: =+wFG_rstar_shock_decomposition!J12 -> 1.5949461e-15 | H12: =+wFG_rstar_shock_decomposition!K12 -> 4.8995216e-15 | I12: =+wFG_rstar_shock_decomposition!L12 -> 9.569358e-15 | ... T12: =+wFG_rstar_shock_decomposition!W12 -> 0.02512193 | U12: =+wFG_rstar_shock_decomposition!D12 -> -1.1317976 | Y12: =+A12 -> 40086 | Z12: =+B12 -> -0.039925577 | AA12: =+C12 -> -0.66815748 | AB12: =+D12 -> 0.19466108 | AC12: =+F12+S12 -> -0.3911912 | AD12: =+E12 -> -0.061837083 | AE12: =+Q12 -> -0.19046931 | AF12: =+G12 -> 1.5949461e-15 | AG12: =+H12 -> 4.8995216e-15 | AH12: =+SUM(T12,I12:P12) -> 0.02512193 | AI12: =+SUM(Z12:AH12) -> -1.1317976 | AJ12: =SUM(AC12+AE12) -> -0.58166051 | AK12: =AB12+AA12+AD12 -> -0.53533348 | AL12: =Z12 -> -0.039925577 | AM12: =AH12 -> 0.02512193 | AN12: =SUM(AJ12:AM12) -> -1.1317976 | AO12: =(AJ12-AJ11)/($AN12-$AN11) -> -2.1681553 | AP12: =(AK12-AK11)/($AN12-$AN11) -> 3.379574 | AQ12: =(AL12-AL11)/($AN12-$AN11) -> -0.20721461 | AR12: =(AM12-AM11)/($AN12-$AN11) -> -0.0042041224 | AS12: =(AN12-AN11)/($AN12-$AN11) -> 1
A13: 40178 | B13: =+wFG_rstar_shock_decomposition!E13 -> -0.027038449 | C13: =+wFG_rstar_shock_decomposition!F13 -> -0.58178559 | D13: =+wFG_rstar_shock_decomposition!G13 -> 0.15426067 | E13: =+wFG_rstar_shock_decomposition!H13 -> 0.00019437639 | F13: =+wFG_rstar_shock_decomposition!I13 -> 0.063221109 | G13: =+wFG_rstar_shock_decomposition!J13 -> 3.2339767e-16 | H13: =+wFG_rstar_shock_decomposition!K13 -> 5.509702e-15 | I13: =+wFG_rstar_shock_decomposition!L13 -> 6.8087841e-15 | ... T13: =+wFG_rstar_shock_decomposition!W13 -> 0.02480491 | U13: =+wFG_rstar_shock_decomposition!D13 -> -0.97113352 | Y13: =+A13 -> 40178 | Z13: =+B13 -> -0.027038449 | AA13: =+C13 -> -0.58178559 | AB13: =+D13 -> 0.15426067 | AC13: =+F13+S13 -> -0.35921644 | AD13: =+E13 -> 0.00019437639 | AE13: =+Q13 -> -0.182353 | AF13: =+G13 -> 3.2339767e-16 | AG13: =+H13 -> 5.509702e-15 | AH13: =+SUM(T13,I13:P13) -> 0.02480491 | AI13: =+SUM(Z13:AH13) -> -0.97113352 | AJ13: =SUM(AC13+AE13) -> -0.54156944 | AK13: =AB13+AA13+AD13 -> -0.42733054 | AL13: =Z13 -> -0.027038449 | AM13: =AH13 -> 0.02480491 | AN13: =SUM(AJ13:AM13) -> -0.97113352 | AO13: =(AJ13-AJ12)/($AN13-$AN12) -> 0.24953347 | AP13: =(AK13-AK12)/($AN13-$AN12) -> 0.6722281 | AQ13: =(AL13-AL12)/($AN13-$AN12) -> 0.080211611 | AR13: =(AM13-AM12)/($AN13-$AN12) -> -0.0019731848 | AS13: =(AN13-AN12)/($AN13-$AN12) -> 1
A14: 40268 | B14: =+wFG_rstar_shock_decomposition!E14 -> -0.028494114 | C14: =+wFG_rstar_shock_decomposition!F14 -> -0.48620876 | D14: =+wFG_rstar_shock_decomposition!G14 -> 0.095901011 | E14: =+wFG_rstar_shock_decomposition!H14 -> -0.022461201 | F14: =+wFG_rstar_shock_decomposition!I14 -> 0.050777858 | G14: =+wFG_rstar_shock_decomposition!J14 -> 4.2929694e-16 | H14: =+wFG_rstar_shock_decomposition!K14 -> 7.012102e-15 | I14: =+wFG_rstar_shock_decomposition!L14 -> 5.9508456e-15 | ... T14: =+wFG_rstar_shock_decomposition!W14 -> 0.024492113 | U14: =+wFG_rstar_shock_decomposition!D14 -> -1.230149 | Y14: =+A14 -> 40268 | Z14: =+B14 -> -0.028494114 | AA14: =+C14 -> -0.48620876 | AB14: =+D14 -> 0.095901011 | AC14: =+F14+S14 -> -0.56956423 | AD14: =+E14 -> -0.022461201 | AE14: =+Q14 -> -0.24381378 | AF14: =+G14 -> 4.2929694e-16 | AG14: =+H14 -> 7.012102e-15 | AH14: =+SUM(T14,I14:P14) -> 0.024492113 | AI14: =+SUM(Z14:AH14) -> -1.230149 | AJ14: =SUM(AC14+AE14) -> -0.81337801 | AK14: =AB14+AA14+AD14 -> -0.41276895 | AL14: =Z14 -> -0.028494114 | AM14: =AH14 -> 0.024492113 | AN14: =SUM(AJ14:AM14) -> -1.230149 | AO14: =(AJ14-AJ13)/($AN14-$AN13) -> 1.0493914 | AP14: =(AK14-AK13)/($AN14-$AN13) -> -0.056219043 | AQ14: =(AL14-AL13)/($AN14-$AN13) -> 0.0056199919 | AR14: =(AM14-AM13)/($AN14-$AN13) -> 0.0012076381 | AS14: =(AN14-AN13)/($AN14-$AN13) -> 1
... A132: 51043 | B132: =+wFG_rstar_shock_decomposition!E132 -> -0.093734333 | C132: =+wFG_rstar_shock_decomposition!F132 -> -0.084772866 | D132: =+wFG_rstar_shock_decomposition!G132 -> 0.14933986 | E132: =+wFG_rstar_shock_decomposition!H132 -> -0.022335447 | F132: =+wFG_rstar_shock_decomposition!I132 -> -0.015784383 | G132: =+wFG_rstar_shock_decomposition!J132 -> -4.1792313e-15 | H132: =+wFG_rstar_shock_decomposition!K132 -> 4.4624542e-14 | I132: =+wFG_rstar_shock_decomposition!L132 -> -5.2442661e-16 | ... T132: =+wFG_rstar_shock_decomposition!W132 -> 0.0058287268 | U132: =+wFG_rstar_shock_decomposition!D132 -> -0.18547251 | Y132: =+A132 -> 51043 | Z132: =+B132 -> -0.093734333 | AA132: =+C132 -> -0.084772866 | AB132: =+D132 -> 0.14933986 | AC132: =+F132+S132 -> -0.16073564 | AD132: =+E132 -> -0.022335447 | AE132: =+Q132 -> 0.020937194 | AF132: =+G132 -> -4.1792313e-15 | AG132: =+H132 -> 4.4624542e-14 | AH132: =+SUM(T132,I132:P132) -> 0.0058287268 | AI132: =+SUM(Z132:AH132) -> -0.18547251 | AJ132: =SUM(AC132+AE132) -> -0.13979845 | AK132: =AB132+AA132+AD132 -> 0.042231546 | AL132: =Z132 -> -0.093734333 | AM132: =AH132 -> 0.0058287268 | AN132: =SUM(AJ132:AM132) -> -0.18547251 | AO132: =(AJ132-AJ131)/($AN132-$AN131) -> 0.7046142 | AP132: =(AK132-AK131)/($AN132-$AN131) -> -0.053914859 | AQ132: =(AL132-AL131)/($AN132-$AN131) -> 0.37252306 | AR132: =(AM132-AM131)/($AN132-$AN131) -> -0.023222401 | AS132: =(AN132-AN131)/($AN132-$AN131) -> 1

Sheet DSGE HVD woFG
A1: date | B1: g | C1: b_liq | D1: b_safe | E1: FF | F1: z | G1: p-mkp | H1: w-mkp | I1: pol | J1: fg1 | K1: fg2 | L1: fg3 | M1: fg4 | N1: fg5 | O1: fg6 | P1: pi-LR | Q1: mu | R1: me | S1: zp | T1: dt | U1: DSGE r* | X1: Chart | Y1: Date | Z1: Government | AA1: Liquidity | AB1: Safety | AC1: Technology | AD1: Financial Frictions | AE1: Investment Specific Technology | AF1: Price Markups | AG1: Wage Markups | AH1: Others | AI1: DSGE r* (with FG) | AJ1: Growth | AK1: Safety+Liquidity | AL1: Government | AM1: Others | AN1: Total | AO1: Growth | AP1: Safety+Liquidity | AQ1: Government | AR1: Others | AS1: Total
A2: 39172 | B2: -0.099978563 | C2: -0.15498592 | D2: 0.25348034 | E2: -0.027181569 | F2: 0.11049296 | G2: 3.3627176e-16 | H2: -3.5538778e-15 | I2: 1.3552662e-14 | J2: 0 | K2: 0 | L2: 0 | M2: 0 | N2: 0 | O2: 0 | P2: 1.5995333e-13 | Q2: -0.053737086 | R2: 0 | S2: -0.084480241 | T2: 0.032328482 | U2: -0.024061599 | V2: =SUM(B2:T2) -> -0.024061599 | Y2: =+A2 -> 39172 | Z2: =+B2 -> -0.099978563 | AA2: =+C2 -> -0.15498592 | AB2: =+D2 -> 0.25348034 | AC2: =+F2+S2 -> 0.026012714 | AD2: =+E2 -> -0.027181569 | AE2: =+Q2 -> -0.053737086 | AF2: =+G2 -> 3.3627176e-16 | AG2: =+H2 -> -3.5538778e-15 | AH2: =+SUM(T2,I2:P2) -> 0.032328482 | AI2: =+SUM(Z2:AH2) -> -0.024061599 | AJ2: =SUM(AC2+AE2) -> -0.027724372 | AK2: =AB2+AA2+AD2 -> 0.071312855 | AL2: =Z2 -> -0.099978563 | AM2: =AH2 -> 0.032328482 | AN2: =SUM(AJ2:AM2) -> -0.024061599
A3: 39263 | B3: -0.090493735 | C3: -0.17989293 | D3: 0.28516778 | E3: -0.02241135 | F3: 0.091292176 | G3: 5.0574402e-16 | H3: -2.3897018e-15 | I3: 1.2532215e-14 | J3: 0 | K3: 0 | L3: 0 | M3: 0 | N3: 0 | O3: 0 | P3: 1.5987653e-13 | Q3: -0.047822202 | R3: 0 | S3: -0.23677861 | T3: 0.031925747 | U3: -0.16901313 | V3: =SUM(B3:T3) -> -0.16901313 | Y3: =+A3 -> 39263 | Z3: =+B3 -> -0.090493735 | AA3: =+C3 -> -0.17989293 | AB3: =+D3 -> 0.28516778 | AC3: =+F3+S3 -> -0.14548643 | AD3: =+E3 -> -0.02241135 | AE3: =+Q3 -> -0.047822202 | AF3: =+G3 -> 5.0574402e-16 | AG3: =+H3 -> -2.3897018e-15 | AH3: =+SUM(T3,I3:P3) -> 0.031925747 | AI3: =+SUM(Z3:AH3) -> -0.16901313 | AJ3: =SUM(AC3+AE3) -> -0.19330864 | AK3: =AB3+AA3+AD3 -> 0.082863497 | AL3: =Z3 -> -0.090493735 | AM3: =AH3 -> 0.031925747 | AN3: =SUM(AJ3:AM3) -> -0.16901313 | AO3: =(AJ3-AJ2)/($AN3-$AN2) -> 1.1423423 | AP3: =(AK3-AK2)/($AN3-$AN2) -> -0.079686237 | AQ3: =(AL3-AL2)/($AN3-$AN2) -> -0.065434481 | AR3: =(AM3-AM2)/($AN3-$AN2) -> 0.0027784056 | AS3: =(AN3-AN2)/($AN3-$AN2) -> 1
A4: 39355 | B4: -0.095177672 | C4: -0.35852263 | D4: 0.27111908 | E4: -0.057796505 | F4: 0.10745203 | G4: 2.1420713e-16 | H4: -1.4061899e-15 | I4: 1.3193762e-14 | J4: 0 | K4: 0 | L4: 0 | M4: 0 | N4: 0 | O4: 0 | P4: 1.5966689e-13 | Q4: -0.066368457 | R4: 0 | S4: -0.28913043 | T4: 0.031528307 | U4: -0.45689628 | V4: =SUM(B4:T4) -> -0.45689628 | Y4: =+A4 -> 39355 | Z4: =+B4 -> -0.095177672 | AA4: =+C4 -> -0.35852263 | AB4: =+D4 -> 0.27111908 | AC4: =+F4+S4 -> -0.1816784 | AD4: =+E4 -> -0.057796505 | AE4: =+Q4 -> -0.066368457 | AF4: =+G4 -> 2.1420713e-16 | AG4: =+H4 -> -1.4061899e-15 | AH4: =+SUM(T4,I4:P4) -> 0.031528307 | AI4: =+SUM(Z4:AH4) -> -0.45689628 | AJ4: =SUM(AC4+AE4) -> -0.24804686 | AK4: =AB4+AA4+AD4 -> -0.14520006 | AL4: =Z4 -> -0.095177672 | AM4: =AH4 -> 0.031528307 | AN4: =SUM(AJ4:AM4) -> -0.45689628 | AO4: =(AJ4-AJ3)/($AN4-$AN3) -> 0.19014041 | AP4: =(AK4-AK3)/($AN4-$AN3) -> 0.79220876 | AQ4: =(AL4-AL3)/($AN4-$AN3) -> 0.016270272 | AR4: =(AM4-AM3)/($AN4-$AN3) -> 0.0013805604 | AS4: =(AN4-AN3)/($AN4-$AN3) -> 1
A5: 39447 | B5: -0.092548084 | C5: -0.50609848 | D5: 0.22217413 | E5: -0.093789741 | F5: 0.10715544 | G5: -2.8771882e-16 | H5: -8.7528509e-16 | I5: 1.4934957e-14 | J5: 0 | K5: 0 | L5: 0 | M5: 0 | N5: 0 | O5: 0 | P5: 1.5828987e-13 | Q5: -0.080581712 | R5: 0 | S5: -0.28249002 | T5: 0.03113609 | U5: -0.69504238 | V5: =SUM(B5:T5) -> -0.69504238 | Y5: =+A5 -> 39447 | Z5: =+B5 -> -0.092548084 | AA5: =+C5 -> -0.50609848 | AB5: =+D5 -> 0.22217413 | AC5: =+F5+S5 -> -0.17533458 | AD5: =+E5 -> -0.093789741 | AE5: =+Q5 -> -0.080581712 | AF5: =+G5 -> -2.8771882e-16 | AG5: =+H5 -> -8.7528509e-16 | AH5: =+SUM(T5,I5:P5) -> 0.03113609 | AI5: =+SUM(Z5:AH5) -> -0.69504238 | AJ5: =SUM(AC5+AE5) -> -0.25591629 | AK5: =AB5+AA5+AD5 -> -0.37771409 | AL5: =Z5 -> -0.092548084 | AM5: =AH5 -> 0.03113609 | AN5: =SUM(AJ5:AM5) -> -0.69504238 | AO5: =(AJ5-AJ4)/($AN5-$AN4) -> 0.033044583 | AP5: =(AK5-AK4)/($AN5-$AN4) -> 0.97635037 | AQ5: =(AL5-AL4)/($AN5-$AN4) -> -0.01104191 | AR5: =(AM5-AM4)/($AN5-$AN4) -> 0.0016469617 | AS5: =(AN5-AN4)/($AN5-$AN4) -> 1
A6: 39538 | B6: -0.094542248 | C6: -0.68145357 | D6: 0.14069022 | E6: -0.1094861 | F6: 0.11501723 | G6: 9.6958303e-18 | H6: -3.0911534e-16 | I6: 1.6357192e-14 | J6: 0 | K6: 0 | L6: 0 | M6: 0 | N6: 0 | O6: 0 | P6: 1.5690382e-13 | Q6: -0.076086186 | R6: 0 | S6: -0.42528638 | T6: 0.030749024 | U6: -1.100398 | V6: =SUM(B6:T6) -> -1.100398 | Y6: =+A6 -> 39538 | Z6: =+B6 -> -0.094542248 | AA6: =+C6 -> -0.68145357 | AB6: =+D6 -> 0.14069022 | AC6: =+F6+S6 -> -0.31026915 | AD6: =+E6 -> -0.1094861 | AE6: =+Q6 -> -0.076086186 | AF6: =+G6 -> 9.6958303e-18 | AG6: =+H6 -> -3.0911534e-16 | AH6: =+SUM(T6,I6:P6) -> 0.030749024 | AI6: =+SUM(Z6:AH6) -> -1.100398 | AJ6: =SUM(AC6+AE6) -> -0.38635534 | AK6: =AB6+AA6+AD6 -> -0.65024945 | AL6: =Z6 -> -0.094542248 | AM6: =AH6 -> 0.030749024 | AN6: =SUM(AJ6:AM6) -> -1.100398 | AO6: =(AJ6-AJ5)/($AN6-$AN5) -> 0.32178914 | AP6: =(AK6-AK5)/($AN6-$AN5) -> 0.67233644 | AQ6: =(AL6-AL5)/($AN6-$AN5) -> 0.0049195403 | AR6: =(AM6-AM5)/($AN6-$AN5) -> 0.00095487878 | AS6: =(AN6-AN5)/($AN6-$AN5) -> 1
A7: 39629 | B7: -0.097854645 | C7: -0.66629665 | D7: 0.1430214 | E7: -0.11393175 | F7: 0.10627694 | G7: 1.5710799e-16 | H7: 6.8567457e-16 | I7: 1.7825543e-14 | J7: 0 | K7: 0 | L7: 0 | M7: 0 | N7: 0 | O7: 0 | P7: 1.5551938e-13 | Q7: -0.079067412 | R7: 0 | S7: -0.49307039 | T7: 0.030367041 | U7: -1.1705555 | V7: =SUM(B7:T7) -> -1.1705555 | Y7: =+A7 -> 39629 | Z7: =+B7 -> -0.097854645 | AA7: =+C7 -> -0.66629665 | AB7: =+D7 -> 0.1430214 | AC7: =+F7+S7 -> -0.38679345 | AD7: =+E7 -> -0.11393175 | AE7: =+Q7 -> -0.079067412 | AF7: =+G7 -> 1.5710799e-16 | AG7: =+H7 -> 6.8567457e-16 | AH7: =+SUM(T7,I7:P7) -> 0.030367041 | AI7: =+SUM(Z7:AH7) -> -1.1705555 | AJ7: =SUM(AC7+AE7) -> -0.46586086 | AK7: =AB7+AA7+AD7 -> -0.637207 | AL7: =Z7 -> -0.097854645 | AM7: =AH7 -> 0.030367041 | AN7: =SUM(AJ7:AM7) -> -1.1705555 | AO7: =(AJ7-AJ6)/($AN7-$AN6) -> 1.1332441 | AP7: =(AK7-AK6)/($AN7-$AN6) -> -0.18590253 | AQ7: =(AL7-AL6)/($AN7-$AN6) -> 0.047213758 | AR7: =(AM7-AM6)/($AN7-$AN6) -> 0.0054446548 | AS7: =(AN7-AN6)/($AN7-$AN6) -> 1
A8: 39721 | B8: -0.083694546 | C8: -0.80494647 | D8: 0.081173996 | E8: -0.11616631 | F8: 0.10059179 | G8: -3.5447993e-16 | H8: 1.3955055e-15 | I8: 1.5975287e-14 | J8: 0 | K8: 0 | L8: 0 | M8: 0 | N8: 0 | O8: 0 | P8: 1.5225991e-13 | Q8: -0.073477843 | R8: 0 | S8: -0.57361505 | T8: 0.029990072 | U8: -1.4401444 | V8: =SUM(B8:T8) -> -1.4401444 | Y8: =+A8 -> 39721 | Z8: =+B8 -> -0.083694546 | AA8: =+C8 -> -0.80494647 | AB8: =+D8 -> 0.081173996 | AC8: =+F8+S8 -> -0.47302326 | AD8: =+E8 -> -0.11616631 | AE8: =+Q8 -> -0.073477843 | AF8: =+G8 -> -3.5447993e-16 | AG8: =+H8 -> 1.3955055e-15 | AH8: =+SUM(T8,I8:P8) -> 0.029990072 | AI8: =+SUM(Z8:AH8) -> -1.4401444 | AJ8: =SUM(AC8+AE8) -> -0.5465011 | AK8: =AB8+AA8+AD8 -> -0.83993878 | AL8: =Z8 -> -0.083694546 | AM8: =AH8 -> 0.029990072 | AN8: =SUM(AJ8:AM8) -> -1.4401444 | AO8: =(AJ8-AJ7)/($AN8-$AN7) -> 0.29912299 | AP8: =(AK8-AK7)/($AN8-$AN7) -> 0.75200348 | AQ8: =(AL8-AL7)/($AN8-$AN7) -> -0.05252479 | AR8: =(AM8-AM7)/($AN8-$AN7) -> 0.0013983126 | AS8: =(AN8-AN7)/($AN8-$AN7) -> 1
A9: 39813 | B9: -0.051162174 | C9: -1.4348626 | D9: -0.25044652 | E9: -0.19974584 | F9: 0.1538426 | G9: 1.8820057e-15 | H9: 1.8210976e-15 | I9: 1.412852e-14 | J9: -5.4457331e-16 | K9: -2.1611639e-16 | L9: 1.368641e-16 | M9: -1.3785038e-16 | N9: -1.0958804e-17 | O9: -4.3720389e-17 | P9: 1.5221413e-13 | Q9: -0.020281188 | R9: 0 | S9: -0.81453912 | T9: 0.029618048 | U9: -2.5875768 | V9: =SUM(B9:T9) -> -2.5875768 | Y9: =+A9 -> 39813 | Z9: =+B9 -> -0.051162174 | AA9: =+C9 -> -1.4348626 | AB9: =+D9 -> -0.25044652 | AC9: =+F9+S9 -> -0.66069652 | AD9: =+E9 -> -0.19974584 | AE9: =+Q9 -> -0.020281188 | AF9: =+G9 -> 1.8820057e-15 | AG9: =+H9 -> 1.8210976e-15 | AH9: =+SUM(T9,I9:P9) -> 0.029618048 | AI9: =+SUM(Z9:AH9) -> -2.5875768 | AJ9: =SUM(AC9+AE9) -> -0.68097771 | AK9: =AB9+AA9+AD9 -> -1.8850549 | AL9: =Z9 -> -0.051162174 | AM9: =AH9 -> 0.029618048 | AN9: =SUM(AJ9:AM9) -> -2.5875768 | AO9: =(AJ9-AJ8)/($AN9-$AN8) -> 0.11719785 | AP9: =(AK9-AK8)/($AN9-$AN8) -> 0.91083025 | AQ9: =(AL9-AL8)/($AN9-$AN8) -> -0.028352321 | AR9: =(AM9-AM8)/($AN9-$AN8) -> 0.00032422285 | AS9: =(AN9-AN8)/($AN9-$AN8) -> 1
A10: 39903 | B10: -0.037464436 | C10: -1.2203241 | D10: -0.1817542 | E10: -0.24990049 | F10: 0.13619796 | G10: 2.1298368e-15 | H10: 3.9846044e-15 | I10: 1.0352372e-14 | J10: -1.0755173e-15 | K10: -4.3361978e-16 | L10: -2.8013837e-16 | M10: -3.9365195e-16 | N10: -2.3549082e-16 | O10: -1.5707528e-16 | P10: 1.533697e-13 | Q10: -0.095038466 | R10: 0 | S10: -0.82281479 | T10: 0.029250903 | U10: -2.4418476 | V10: =SUM(B10:T10) -> -2.4418476 | Y10: =+A10 -> 39903 | Z10: =+B10 -> -0.037464436 | AA10: =+C10 -> -1.2203241 | AB10: =+D10 -> -0.1817542 | AC10: =+F10+S10 -> -0.68661682 | AD10: =+E10 -> -0.24990049 | AE10: =+Q10 -> -0.095038466 | AF10: =+G10 -> 2.1298368e-15 | AG10: =+H10 -> 3.9846044e-15 | AH10: =+SUM(T10,I10:P10) -> 0.029250903 | AI10: =+SUM(Z10:AH10) -> -2.4418476 | AJ10: =SUM(AC10+AE10) -> -0.78165529 | AK10: =AB10+AA10+AD10 -> -1.6519788 | AL10: =Z10 -> -0.037464436 | AM10: =AH10 -> 0.029250903 | AN10: =SUM(AJ10:AM10) -> -2.4418476 | AO10: =(AJ10-AJ9)/($AN10-$AN9) -> -0.69085406 | AP10: =(AK10-AK9)/($AN10-$AN9) -> 1.5993789 | AQ10: =(AL10-AL9)/($AN10-$AN9) -> 0.093994485 | AR10: =(AM10-AM9)/($AN10-$AN9) -> -0.0025193657 | AS10: =(AN10-AN9)/($AN10-$AN9) -> 1
A11: 39994 | B11: -0.026473776 | C11: -0.99360085 | D11: -0.10457848 | E11: -0.18003743 | F11: 0.090604717 | G11: 1.87539e-15 | H11: 3.6850301e-15 | I11: 8.364169e-15 | J11: -1.2011701e-15 | K11: -7.9411366e-16 | L11: -5.4702722e-16 | M11: -7.1514748e-16 | N11: -5.6991559e-16 | O11: -4.5635577e-16 | P11: 1.4886767e-13 | Q11: -0.10050156 | R11: 0 | S11: -0.68818055 | T11: 0.02888857 | U11: -1.9738793 | V11: =SUM(B11:T11) -> -1.9738793 | Y11: =+A11 -> 39994 | Z11: =+B11 -> -0.026473776 | AA11: =+C11 -> -0.99360085 | AB11: =+D11 -> -0.10457848 | AC11: =+F11+S11 -> -0.59757583 | AD11: =+E11 -> -0.18003743 | AE11: =+Q11 -> -0.10050156 | AF11: =+G11 -> 1.87539e-15 | AG11: =+H11 -> 3.6850301e-15 | AH11: =+SUM(T11,I11:P11) -> 0.02888857 | AI11: =+SUM(Z11:AH11) -> -1.9738793 | AJ11: =SUM(AC11+AE11) -> -0.69807739 | AK11: =AB11+AA11+AD11 -> -1.2782168 | AL11: =Z11 -> -0.026473776 | AM11: =AH11 -> 0.02888857 | AN11: =SUM(AJ11:AM11) -> -1.9738793 | AO11: =(AJ11-AJ10)/($AN11-$AN10) -> 0.17859738 | AP11: =(AK11-AK10)/($AN11-$AN10) -> 0.79869097 | AQ11: =(AL11-AL10)/($AN11-$AN10) -> 0.02348591 | AR11: =(AM11-AM10)/($AN11-$AN10) -> -0.0007742671 | AS11: =(AN11-AN10)/($AN11-$AN10) -> 1
A12: 40086 | B12: -0.043317567 | C12: -0.68899371 | D12: 0.033900907 | E12: -0.082437085 | F12: 0.061241773 | G12: 1.5956308e-15 | H12: 3.9661818e-15 | I12: 8.0421596e-15 | J12: -1.4622254e-15 | K12: -1.0238027e-15 | L12: -8.4425511e-16 | M12: -1.0459959e-15 | N12: -9.0225641e-16 | O12: -4.9509332e-16 | P12: 1.4274201e-13 | Q12: -0.13806507 | R12: 0 | S12: -0.60241173 | T12: 0.028530985 | U12: -1.4315515 | V12: =SUM(B12:T12) -> -1.4315515 | Y12: =+A12 -> 40086 | Z12: =+B12 -> -0.043317567 | AA12: =+C12 -> -0.68899371 | AB12: =+D12 -> 0.033900907 | AC12: =+F12+S12 -> -0.54116995 | AD12: =+E12 -> -0.082437085 | AE12: =+Q12 -> -0.13806507 | AF12: =+G12 -> 1.5956308e-15 | AG12: =+H12 -> 3.9661818e-15 | AH12: =+SUM(T12,I12:P12) -> 0.028530985 | AI12: =+SUM(Z12:AH12) -> -1.4315515 | AJ12: =SUM(AC12+AE12) -> -0.67923503 | AK12: =AB12+AA12+AD12 -> -0.73752989 | AL12: =Z12 -> -0.043317567 | AM12: =AH12 -> 0.028530985 | AN12: =SUM(AJ12:AM12) -> -1.4315515 | AO12: =(AJ12-AJ11)/($AN12-$AN11) -> 0.034743483 | AP12: =(AK12-AK11)/($AN12-$AN11) -> 0.99697419 | AQ12: =(AL12-AL11)/($AN12-$AN11) -> -0.031058318 | AR12: =(AM12-AM11)/($AN12-$AN11) -> -0.00065935216 | AS12: =(AN12-AN11)/($AN12-$AN11) -> 1
A13: 40178 | B13: -0.030099008 | C13: -0.60245974 | D13: 0.060911429 | E13: -0.021856784 | F13: 0.00078641999 | G13: 3.9066384e-16 | H13: 4.4551475e-15 | I13: 6.2207741e-15 | J13: -1.7555505e-15 | K13: -1.3605621e-15 | L13: -1.168117e-15 | M13: -1.3450277e-15 | N13: -9.3612443e-16 | O13: -1.0425318e-15 | P13: 1.3591277e-13 | Q13: -0.12254587 | R13: 0 | S13: -0.48058538 | T13: 0.028178083 | U13: -1.1676709 | V13: =SUM(B13:T13) -> -1.1676709 | Y13: =+A13 -> 40178 | Z13: =+B13 -> -0.030099008 | AA13: =+C13 -> -0.60245974 | AB13: =+D13 -> 0.060911429 | AC13: =+F13+S13 -> -0.47979896 | AD13: =+E13 -> -0.021856784 | AE13: =+Q13 -> -0.12254587 | AF13: =+G13 -> 3.9066384e-16 | AG13: =+H13 -> 4.4551475e-15 | AH13: =+SUM(T13,I13:P13) -> 0.028178083 | AI13: =+SUM(Z13:AH13) -> -1.1676709 | AJ13: =SUM(AC13+AE13) -> -0.60234483 | AK13: =AB13+AA13+AD13 -> -0.5634051 | AL13: =Z13 -> -0.030099008 | AM13: =AH13 -> 0.028178083 | AN13: =SUM(AJ13:AM13) -> -1.1676709 | AO13: =(AJ13-AJ12)/($AN13-$AN12) -> 0.29138249 | AP13: =(AK13-AK12)/($AN13-$AN12) -> 0.65986192 | AQ13: =(AL13-AL12)/($AN13-$AN12) -> 0.050092946 | AR13: =(AM13-AM12)/($AN13-$AN12) -> -0.0013373548 | AS13: =(AN13-AN12)/($AN13-$AN12) -> 1
A14: 40268 | B14: -0.031649797 | C14: -0.46842205 | D14: 0.12401342 | E14: -0.044504198 | F14: -0.012096584 | G14: 4.6556231e-16 | H14: 5.843492e-15 | I14: 5.8218777e-15 | J14: -1.8572438e-15 | K14: -1.4689412e-15 | L14: -1.2298706e-15 | M14: -1.1325431e-15 | N14: -1.112011e-15 | O14: -1.3895386e-15 | P14: 1.3662116e-13 | Q14: -0.16200655 | R14: 0 | S14: -0.59961401 | T14: 0.027829801 | U14: -1.16645 | V14: =SUM(B14:T14) -> -1.16645 | Y14: =+A14 -> 40268 | Z14: =+B14 -> -0.031649797 | AA14: =+C14 -> -0.46842205 | AB14: =+D14 -> 0.12401342 | AC14: =+F14+S14 -> -0.61171059 | AD14: =+E14 -> -0.044504198 | AE14: =+Q14 -> -0.16200655 | AF14: =+G14 -> 4.6556231e-16 | AG14: =+H14 -> 5.843492e-15 | AH14: =+SUM(T14,I14:P14) -> 0.027829801 | AI14: =+SUM(Z14:AH14) -> -1.16645 | AJ14: =SUM(AC14+AE14) -> -0.77371714 | AK14: =AB14+AA14+AD14 -> -0.38891283 | AL14: =Z14 -> -0.031649797 | AM14: =AH14 -> 0.027829801 | AN14: =SUM(AJ14:AM14) -> -1.16645 | AO14: =(AJ14-AJ13)/($AN14-$AN13) -> -140.36715 | AP14: =(AK14-AK13)/($AN14-$AN13) -> 142.92264 | AQ14: =(AL14-AL13)/($AN14-$AN13) -> -1.2702165 | AR14: =(AM14-AM13)/($AN14-$AN13) -> -0.28527036 | AS14: =(AN14-AN13)/($AN14-$AN13) -> 1
... A132: 51043 | B132: -0.084608619 | C132: -0.070189722 | D132: 0.26077834 | E132: -0.016689636 | F132: -0.014700397 | G132: -4.2256513e-15 | H132: 4.6129552e-14 | I132: 2.3122145e-15 | J132: -2.4736448e-16 | K132: -3.995226e-16 | L132: -5.8621374e-16 | M132: -8.8535017e-16 | N132: -1.0941128e-15 | O132: -1.2963744e-15 | P132: 6.7566725e-14 | Q132: 0.0017702803 | R132: 0 | S132: -0.20923111 | T132: 0.0068179135 | U132: -0.12605296 | V132: =SUM(B132:T132) -> -0.12605296 | Y132: =+A132 -> 51043 | Z132: =+B132 -> -0.084608619 | AA132: =+C132 -> -0.070189722 | AB132: =+D132 -> 0.26077834 | AC132: =+F132+S132 -> -0.22393151 | AD132: =+E132 -> -0.016689636 | AE132: =+Q132 -> 0.0017702803 | AF132: =+G132 -> -4.2256513e-15 | AG132: =+H132 -> 4.6129552e-14 | AH132: =+SUM(T132,I132:P132) -> 0.0068179135 | AI132: =+SUM(Z132:AH132) -> -0.12605296 | AJ132: =SUM(AC132+AE132) -> -0.22216123 | AK132: =AB132+AA132+AD132 -> 0.17389898 | AL132: =Z132 -> -0.084608619 | AM132: =AH132 -> 0.0068179135 | AN132: =SUM(AJ132:AM132) -> -0.12605296 | AO132: =(AJ132-AJ131)/($AN132-$AN131) -> 1.2758034 | AP132: =(AK132-AK131)/($AN132-$AN131) -> -0.67217438 | AQ132: =(AL132-AL131)/($AN132-$AN131) -> 0.43044311 | AR132: =(AM132-AM131)/($AN132-$AN131) -> -0.034072092 | AS132: =(AN132-AN131)/($AN132-$AN131) -> 1

Sheet US_output_withoutFG
A1: date | B1: g_sh | C1: b_liqtil_sh | D1: b_liqp_sh | E1: b_safetil_sh | F1: b_safep_sh | G1: mu_sh | H1: z_sh | I1: lambda_f_sh | J1: lambda_w_sh | K1: rm_sh | L1: sigma_omega_sh | M1: mu_e_sh | N1: gamma_sh | O1: pi_star_sh | P1: lr_sh | Q1: zp_sh | R1: tfp_sh | S1: gdpdef_sh | T1: corepce_sh | U1: gdp_sh | V1: gdi_sh | W1: BBB_sh | X1: AAA_sh | Y1: rm_shl1 | Z1: rm_shl2 | AA1: rm_shl3 | AB1: rm_shl4 | AC1: rm_shl5 | AD1: rm_shl6 | AE1: dettrend | AF1: detrendedMean | AG1: Ouput | AH1: Output without FG
A2: 39172 | B2: -1.0215877 | C2: 0.14738424 | D2: -0.044907453 | E2: 0.56515568 | F2: 0.33471877 | G2: 1.4053436 | H2: 0.54693072 | I2: -0.65393335 | J2: 0.64232717 | K2: 1.7750614 | L2: 1.2826525 | M2: 0 | N2: 0 | O2: 0.3278555 | P2: 0 | Q2: 0.11087454 | R2: 0 | S2: 0 | T2: 0 | U2: 0 | V2: 0 | W2: 0 | X2: 0 | Y2: 0 | Z2: 0 | AA2: 0 | AB2: 0 | AC2: 0 | AD2: 0 | AE2: 0.13099711 | AF2: 5.5488727 | AG2: =AF2 -> 5.5488727 | AH2: =AG2-SUM(Y2:AD2) -> 5.5488727
A3: 39263 | B3: -0.87702165 | C3: 0.14867978 | D3: -0.050839217 | E3: 0.5967583 | F3: 0.35694143 | G3: 1.4459149 | H3: 0.10615582 | I3: -0.67075329 | J3: 0.60096046 | K3: 1.5688765 | L3: 1.2418066 | M3: 0 | N3: 0 | O3: 0.33267031 | P3: 0 | Q3: 0.070231968 | R3: 0 | S3: 0 | T3: 0 | U3: 0 | V3: 0 | W3: 0 | X3: 0 | Y3: 0 | Z3: 0 | AA3: 0 | AB3: 0 | AC3: 0 | AD3: 0 | AE3: 0.13039267 | AF3: 5.0007746 | AG3: =AF3 -> 5.0007746 | AH3: =AG3-SUM(Y3:AD3) -> 5.0007746
A4: 39355 | B4: -1.040355 | C4: 0.13425109 | D4: -0.14587387 | E4: 0.69031317 | F4: 0.37191894 | G4: 1.4503632 | H4: 0.31183503 | I4: -0.6798581 | J4: 0.61019793 | K4: 1.5086958 | L4: 1.1510338 | M4: 0 | N4: 0 | O4: 0.37118543 | P4: 0 | Q4: 0.037371485 | R4: 0 | S4: 0 | T4: 0 | U4: 0 | V4: 0 | W4: 0 | X4: 0 | Y4: 0 | Z4: 0 | AA4: 0 | AB4: 0 | AC4: 0 | AD4: 0 | AE4: 0.12978091 | AF4: 4.9008599 | AG4: =AF4 -> 4.9008599 | AH4: =AG4-SUM(Y4:AD4) -> 4.9008599
A5: 39447 | B5: -0.99330901 | C5: 0.14258815 | D5: -0.26310356 | E5: 0.73768743 | F5: 0.36639612 | G5: 1.4317096 | H5: 0.21867959 | I5: -0.68920012 | J5: 0.66599438 | K5: 1.7274198 | L5: 1.0093212 | M5: 0 | N5: 0 | O5: 0.40724837 | P5: 0 | Q5: 0.016106972 | R5: 0 | S5: 0 | T5: 0 | U5: 0 | V5: 0 | W5: 0 | X5: 0 | Y5: 0 | Z5: 0 | AA5: 0 | AB5: 0 | AC5: 0 | AD5: 0 | AE5: 0.12916218 | AF5: 4.9067011 | AG5: =AF5 -> 4.9067011 | AH5: =AG5-SUM(Y5:AD5) -> 4.9067011
A6: 39538 | B6: -1.0476842 | C6: 0.03061779 | D6: -0.40243934 | E6: 0.39311962 | F6: 0.33629364 | G6: 1.42832 | H6: 0.27379584 | I6: -0.67868028 | J6: 0.70115772 | K6: 2.0053504 | L6: 0.85487701 | M6: 0 | N6: 0 | O6: 0.44493982 | P6: 0 | Q6: -0.019590161 | R6: 0 | S6: 0 | T6: 0 | U6: 0 | V6: 0 | W6: 0 | X6: 0 | Y6: 0 | Z6: 0 | AA6: 0 | AB6: 0 | AC6: 0 | AD6: 0 | AE6: 0.12853685 | AF6: 4.4486148 | AG6: =AF6 -> 4.4486148 | AH6: =AG6-SUM(Y6:AD6) -> 4.4486148
A7: 39629 | B7: -1.1086433 | C7: -0.033609602 | D7: -0.44750789 | E7: 0.09339584 | F7: 0.34011857 | G7: 1.4242313 | H7: 0.099730651 | I7: -0.64918611 | J7: 0.69311266 | K7: 2.3003353 | L7: 0.71023288 | M7: 0 | N7: 0 | O7: 0.48647302 | P7: 0 | Q7: -0.047607001 | R7: 0 | S7: 0 | T7: 0 | U7: 0 | V7: 0 | W7: 0 | X7: 0 | Y7: 0 | Z7: 0 | AA7: 0 | AB7: 0 | AC7: 0 | AD7: 0 | AE7: 0.12790526 | AF7: 3.9889816 | AG7: =AF7 -> 3.9889816 | AH7: =AG7-SUM(Y7:AD7) -> 3.9889816
A8: 39721 | B8: -0.80373451 | C8: -0.20400532 | D8: -0.52579161 | E8: -0.37809506 | F8: 0.32715602 | G8: 1.4371073 | H8: 0.049769223 | I8: -0.6241057 | J8: 0.72601851 | K8: 1.9637541 | L8: 0.57993927 | M8: 0 | N8: 0 | O8: 0.49767707 | P8: 0 | Q8: -0.074978682 | R8: 0 | S8: 0 | T8: 0 | U8: 0 | V8: 0 | W8: 0 | X8: 0 | Y8: 0 | Z8: 0 | AA8: 0 | AB8: 0 | AC8: 0 | AD8: 0 | AE8: 0.12726775 | AF8: 3.0979785 | AG8: =AF8 -> 3.0979785 | AH8: =AG8-SUM(Y8:AD8) -> 3.0979785
A9: 39813 | B9: -0.21677727 | C9: -0.56638658 | D9: -0.87656555 | E9: -1.0760328 | F9: 0.163132 | G9: 1.567453 | H9: 0.77708187 | I9: -0.52720457 | J9: 0.77689645 | K9: 1.3356925 | L9: 0.32530383 | M9: 0 | N9: 0 | O9: 0.56267499 | P9: 0 | Q9: -0.12285996 | R9: 0 | S9: 0 | T9: 0 | U9: 0 | V9: 0 | W9: 0 | X9: 0 | Y9: -0.18334085 | Z9: -0.085809019 | AA9: -0.014995051 | AB9: -0.0025678522 | AC9: -0.0010749068 | AD9: -0.0015146036 | AE9: 0.12662465 | AF9: 1.9597303 | AG9: =AF9 -> 1.9597303 | AH9: =AG9-SUM(Y9:AD9) -> 2.2490326
A10: 39903 | B10: -0.13539004 | C10: -0.65246513 | D10: -0.91826335 | E10: -1.4441778 | F10: 0.115455 | G10: 1.5230468 | H10: 0.27896396 | I10: -0.40325188 | J10: 0.66681609 | K10: 0.39863999 | L10: 0.0012907793 | M10: 0 | N10: 0 | O10: 0.65980691 | P10: 0 | Q10: -0.15244255 | R10: 0 | S10: 0 | T10: 0 | U10: 0 | V10: 0 | W10: 0 | X10: 0 | Y10: -0.40182322 | Z10: -0.21133372 | AA10: -0.064564658 | AB10: -0.0076746478 | AC10: -0.0097111472 | AD10: -0.013463276 | AE10: 0.12597629 | AF10: -0.64456556 | AG10: =AF10 -> -0.64456556 | AH10: =AG10-SUM(Y10:AD10) -> 0.064005108
A11: 39994 | B11: -0.073128195 | C11: -0.59127453 | D11: -0.82556116 | E11: -1.5731642 | F11: 0.099746456 | G11: 1.4374342 | H11: -0.35522693 | I11: -0.28293943 | J11: 0.84351191 | K11: -0.30041232 | L11: -0.18272965 | M11: 0 | N11: 0 | O11: 0.6458429 | P11: 0 | Q11: -0.16787271 | R11: 0 | S11: 0 | T11: 0 | U11: 0 | V11: 0 | W11: 0 | X11: 0 | Y11: -0.51335586 | Z11: -0.31584038 | AA11: -0.13962108 | AB11: -0.03410106 | AC11: -0.016607341 | AD11: -0.041339223 | AE11: 0.12532296 | AF11: -2.2613156 | AG11: =AF11 -> -2.2613156 | AH11: =AG11-SUM(Y11:AD11) -> -1.2004507
A12: 40086 | B12: -0.53090932 | C12: -0.26450707 | D12: -0.67212326 | E12: -1.5028278 | F12: 0.069033869 | G12: 1.1961043 | H12: -0.54411897 | I12: -0.18186777 | J12: 0.89049329 | K12: -0.56877654 | L12: -0.18360036 | M12: 0 | N12: 0 | O12: 0.48885426 | P12: 0 | Q12: -0.2019199 | R12: 0 | S12: 0 | T12: 0 | U12: 0 | V12: 0 | W12: 0 | X12: 0 | Y12: -0.43225273 | Z12: -0.32122089 | AA12: -0.17245864 | AB12: -0.050099817 | AC12: -0.0204331 | AD12: -0.08404302 | AE12: 0.12466498 | AF12: -2.9620085 | AG12: =AF12 -> -2.9620085 | AH12: =AG12-SUM(Y12:AD12) -> -1.8815003
A13: 40178 | B13: -0.25242317 | C13: -0.21161538 | D13: -0.55513346 | E13: -1.5319895 | F13: 0.034934349 | G13: 0.99553621 | H13: -1.0349527 | I13: -0.1401452 | J13: 0.90746758 | K13: -1.1530786 | L13: -0.071269525 | M13: 0 | N13: 0 | O13: 0.29361464 | P13: 0 | Q13: -0.2238056 | R13: 0 | S13: 0 | T13: 0 | U13: 0 | V13: 0 | W13: 0 | X13: 0 | Y13: -0.35928238 | Z13: -0.28959157 | AA13: -0.22762518 | AB13: -0.069279424 | AC13: -0.028449793 | AD13: -0.14778106 | AE13: 0.12400264 | AF13: -3.9408671 | AG13: =AF13 -> -3.9408671 | AH13: =AG13-SUM(Y13:AD13) -> -2.8188577
... A132: 51043 | B132: -1.1485256 | C132: 0.00012590441 | D132: -0.042684349 | E132: -0.00047395337 | F132: 0.10831097 | G132: -0.17615887 | H132: 0.054636968 | I132: 0.15047017 | J132: 0.26718227 | K132: 0.0018162856 | L132: 0.37632535 | M132: 0 | N132: 0 | O132: 0.54539942 | P132: 0 | Q132: -0.20667783 | R132: 0 | S132: 0 | T132: 0 | U132: 0 | V132: 0 | W132: 0 | X132: 0 | Y132: -0.0016294185 | Z132: 0.0019674278 | AA132: -0.00054863095 | AB132: 0.00047969275 | AC132: -0.0015716835 | AD132: -0.0046451761 | AE132: 0.053433982 | AF132: -0.022767062 | AG132: =AF132 -> -0.022767062 | AH132: =AG132-SUM(Y132:AD132) -> -0.016819274

Sheet US_inflation
A1: date | B1: g_sh | C1: b_liqtil_sh | D1: b_liqp_sh | E1: b_safetil_sh | F1: b_safep_sh | G1: mu_sh | H1: z_sh | I1: lambda_f_sh | J1: lambda_w_sh | K1: rm_sh | L1: sigma_omega_sh | M1: mu_e_sh | N1: gamma_sh | O1: pi_star_sh | P1: lr_sh | Q1: zp_sh | R1: tfp_sh | S1: gdpdef_sh | T1: corepce_sh | U1: gdp_sh | V1: gdi_sh | W1: BBB_sh | X1: AAA_sh | Y1: rm_shl1 | Z1: rm_shl2 | AA1: rm_shl3 | AB1: rm_shl4 | AC1: rm_shl5 | AD1: rm_shl6 | AE1: dettrend | AF1: detrendedMean | AG1: mean | AH1: obs_gdp_deflator | AI1: obs_gdp_deflator_woFG
A2: 39172 | B2: -0.048452569 | C2: 6.956186e-05 | D2: -0.12596471 | E2: 0.0057819246 | F2: 0.30764279217205814 | G2: -0.10127441 | H2: 0.2524793268297909 | I2: 1.0614473044399553 | J2: -0.98836056 | K2: 0.032680851 | L2: -0.12099639 | M2: 0 | N2: 0 | O2: 0.64621873 | P2: 0 | Q2: -0.030041462 | R2: 0 | S2: 1.1943931 | T2: 0 | U2: 0 | V2: 0 | W2: 0 | X2: 0 | Y2: 0 | Z2: 0 | AA2: 0 | AB2: 0 | AC2: 0 | AD2: 0 | AE2: -0.28251638 | AF2: 1.8343792 | AG2: 2.0234399 | AH2: =AG2+AF2 -> 3.8578191 | AI2: =AH2-SUM(Y2:AD2) -> 3.8578191
A3: 39263 | B3: -0.04304674 | C3: -0.00025589908 | D3: -0.12923926 | E3: 0.0046296636 | F3: 0.3206851089922136 | G3: -0.10984266 | H3: 0.20315466224327672 | I3: 0.5205227392903078 | J3: -1.1343671 | K3: 0.02915578 | L3: -0.12080217 | M3: 0 | N3: 0 | O3: 0.6709562 | P3: 0 | Q3: 0.073122896 | R3: 0 | S3: 0.77783407 | T3: 0 | U3: 0 | V3: 0 | W3: 0 | X3: 0 | Y3: 0 | Z3: 0 | AA3: 0 | AB3: 0 | AC3: 0 | AD3: 0 | AE3: -0.2797659 | AF3: 0.78685396 | AG3: 2.0234399 | AH3: =AG3+AF3 -> 2.8102938 | AI3: =AH3-SUM(Y3:AD3) -> 2.8102938
A4: 39355 | B4: -0.044425358 | C4: -0.00056248494 | D4: -0.18218745 | E4: 0.0036621089 | F4: 0.32534987427106365 | G4: -0.102425 | H4: 0.23334963423156108 | I4: 0.5834063922266708 | J4: -1.2595975 | K4: 0.029854841 | L4: -0.10725495 | M4: 0 | N4: 0 | O4: 0.71701871 | P4: 0 | Q4: 0.13147026 | R4: 0 | S4: 0.14044998 | T4: 0 | U4: 0 | V4: 0 | W4: 0 | X4: 0 | Y4: 0 | Z4: 0 | AA4: 0 | AB4: 0 | AC4: 0 | AD4: 0 | AE4: -0.27703878 | AF4: 0.18090141 | AG4: 2.0234399 | AH4: =AG4+AF4 -> 2.2043413 | AI4: =AH4-SUM(Y4:AD4) -> 2.2043413
A5: 39447 | B5: -0.043188455 | C5: -0.00087451046 | D5: -0.23547227 | E5: 0.0025590054 | F5: 0.3182483818176429 | G5: -0.093204544 | H5: 0.23530732915948427 | I5: 0.7490166955690603 | J5: -1.2202736 | K5: 0.034965704 | L5: -0.089036787 | M5: 0 | N5: 0 | O5: 0.74052883 | P5: 0 | Q5: 0.11683875 | R5: 0 | S5: -0.61063095 | T5: 0 | U5: 0 | V5: 0 | W5: 0 | X5: 0 | Y5: 0 | Z5: 0 | AA5: 0 | AB5: 0 | AC5: 0 | AD5: 0 | AE5: -0.27433494 | AF5: -0.39310494 | AG5: 2.0234399 | AH5: =AG5+AF5 -> 1.6303349 | AI5: =AH5-SUM(Y5:AD5) -> 1.6303349
A6: 39538 | B6: -0.043863888 | C6: -0.00096951179 | D6: -0.29643595 | E6: 0.00059613668 | F6: 0.29968029810361063 | G6: -0.095791932 | H6: 0.2548423327698002 | I6: 0.2744687323622541 | J6: -1.177315 | K6: 0.039678177 | L6: -0.075259412 | M6: 0 | N6: 0 | O6: 0.76126939 | P6: 0 | Q6: 0.23824572 | R6: 0 | S6: -0.41980046 | T6: 0 | U6: 0 | V6: 0 | W6: 0 | X6: 0 | Y6: 0 | Z6: 0 | AA6: 0 | AB6: 0 | AC6: 0 | AD6: 0 | AE6: -0.2716543 | AF6: -0.53462025 | AG6: 2.0234399 | AH6: =AG6+AF6 -> 1.4888196 | AI6: =AH6-SUM(Y6:AD6) -> 1.4888196
A7: 39629 | B7: -0.045564202 | C7: -0.00095399343 | D7: -0.29871009 | E7: -0.00072812948 | F7: 0.3050939054992874 | G7: -0.096279285 | H7: 0.23540125065368844 | I7: 0.13006775569885942 | J7: -1.2837054 | K7: 0.044084017 | L7: -0.065578552 | M7: 0 | N7: 0 | O7: 0.78379269 | P7: 0 | Q7: 0.30558016 | R7: 0 | S7: 0.20014434 | T7: 0 | U7: 0 | V7: 0 | W7: 0 | X7: 0 | Y7: 0 | Z7: 0 | AA7: 0 | AB7: 0 | AC7: 0 | AD7: 0 | AE7: -0.26899676 | AF7: -0.071501295 | AG7: 2.0234399 | AH7: =AG7+AF7 -> 1.9519386 | AI7: =AH7-SUM(Y7:AD7) -> 1.9519386
A8: 39721 | B8: -0.038274436 | C8: -0.00059586681 | D8: -0.33319859 | E8: -0.0019875726 | F8: 0.2967386667727556 | G8: -0.10262775 | H8: 0.2204882321778845 | I8: 0.49979898093051034 | J8: -1.3108128 | K8: 0.03730586 | L8: -0.057334941 | M8: 0 | N8: 0 | O8: 0.76476147 | P8: 0 | Q8: 0.36958955 | R8: 0 | S8: 0.94107404 | T8: 0 | U8: 0 | V8: 0 | W8: 0 | X8: 0 | Y8: 0 | Z8: 0 | AA8: 0 | AB8: 0 | AC8: 0 | AD8: 0 | AE8: -0.26636223 | AF8: 1.0243038 | AG8: 2.0234399 | AH8: =AG8+AF8 -> 3.0477437 | AI8: =AH8-SUM(Y8:AD8) -> 3.0477437
A9: 39813 | B9: -0.019822374 | C9: 0.00040984838 | D9: -0.52521137 | E9: -0.0031110567 | F9: 0.20113536911661178 | G9: -0.14891708 | H9: 0.3632275739553714 | I9: -1.2268068 | J9: -1.2349652 | K9: 0.028452427 | L9: -0.020533167 | M9: 0 | N9: 0 | O9: 0.82491404 | P9: 0 | Q9: 0.5957789 | R9: 0 | S9: 0.42701207 | T9: 0 | U9: 0 | V9: 0 | W9: 0 | X9: 0 | Y9: -0.0048487102 | Z9: -0.0033850197 | AA9: -0.00088330923 | AB9: -0.0002296464 | AC9: -0.00014989164 | AD9: -0.00034076114 | AE9: -0.26375062 | AF9: -1.0515812 | AG9: 2.0234399 | AH9: =AG9+AF9 -> 0.97185871 | AI9: =AH9-SUM(Y9:AD9) -> 0.98169605
A10: 39903 | B10: -0.0092431642 | C10: 0.0015831522 | D10: -0.49984026 | E10: -0.0025773909 | F10: 0.19494353015609978 | G10: -0.10630843 | H10: 0.34113623334772747 | I10: -0.8667215 | J10: -1.7197252 | K10: 0.016283178 | L10: 0.015099645 | M10: 0 | N10: 0 | O10: 0.90554825 | P10: 0 | Q10: 0.65199018 | R10: 0 | S10: -0.92662267 | T10: 0 | U10: 0 | V10: 0 | W10: 0 | X10: 0 | Y10: -0.0079323256 | Z10: -0.0063234714 | AA10: -0.0032430392 | AB10: -0.00053175183 | AC10: -0.0012477988 | AD10: -0.0027773664 | AE10: -0.26116183 | AF10: -2.3390464 | AG10: 2.0234399 | AH10: =AG10+AF10 -> -0.31560651 | AI10: =AH10-SUM(Y10:AD10) -> -0.29355076
A11: 39994 | B11: -0.0017055839 | C11: 0.0027645837 | D11: -0.43206594 | E11: -0.0010673593 | F11: 0.1952802366854245 | G11: -0.078257789 | H11: 0.2164772529555936 | I11: -0.46919752 | J11: -1.4302583 | K11: 0.010279258 | L11: 0.011002093 | M11: 0 | N11: 0 | O11: 0.82679768 | P11: 0 | Q11: 0.56402464 | R11: 0 | S11: -1.7584788 | T11: 0 | U11: 0 | V11: 0 | W11: 0 | X11: 0 | Y11: -0.0080348704 | Z11: -0.0067132131 | AA11: -0.0055821385 | AB11: -0.0025203586 | AC11: -0.0013048456 | AD11: -0.0069315516 | AE11: -0.25859575 | AF11: -2.685872 | AG11: 2.0234399 | AH11: =AG11+AF11 -> -0.66243217 | AI11: =AH11-SUM(Y11:AD11) -> -0.63134519
A12: 40086 | B12: -0.0092170509 | C12: 0.003402693 | D12: -0.35496823 | E12: 0.00098504891 | F12: 0.1796640905652458 | G12: -0.0076626801 | H12: 0.11589176519291033 | I12: -0.34226991 | J12: -1.24954 | K12: 0.011161051 | L12: -0.013410929 | M12: 0 | N12: 0 | O12: 0.60908737 | P12: 0 | Q12: 0.6017894 | R12: 0 | S12: -0.77455306 | T12: 0 | U12: 0 | V12: 0 | W12: 0 | X12: 0 | Y12: -0.0045927201 | Z12: -0.0042188067 | AA12: -0.0038507311 | AB12: -0.0021944104 | AC12: -0.00072933069 | AD12: -0.01079188 | AE12: -0.25605228 | AF12: -1.547458 | AG12: 2.0234399 | AH12: =AG12+AF12 -> 0.47598186 | AI12: =AH12-SUM(Y12:AD12) -> 0.50235974
A13: 40178 | B13: -0.0042928253 | C13: 0.0039297117 | D13: -0.31274866 | E13: 0.0026182224 | F13: 0.16250628 | G13: 0.014023996 | H13: -0.050718513 | I13: 0.5828226873249909 | J13: -1.1744365 | K13: 0.0045709106 | L13: -0.034802619 | M13: 0 | N13: 0 | O13: 0.41511608 | P13: 0 | Q13: 0.51863692 | R13: 0 | S13: -0.5697879 | T13: 0 | U13: 0 | V13: 0 | W13: 0 | X13: 0 | Y13: -0.0039556528 | Z13: -0.0033057199 | AA13: -0.0047909625 | AB13: -0.0021844599 | AC13: -0.00093787634 | AD13: -0.01501008 | AE13: -0.25353131 | AF13: -0.75189897 | AG13: 2.0234399 | AH13: =AG13+AF13 -> 1.2715409 | AI13: =AH13-SUM(Y13:AD13) -> 1.3017257
A14: 40268 | B14: -0.0045653944 | C14: 0.0041103121 | D14: -0.27469652 | E14: 0.0043349845 | F14: 0.13924303630610257 | G14: 0.075240866 | H14: -0.10164893 | I14: 0.15993815119257349 | J14: -1.4155369 | K14: 0.0031256094 | L14: -0.028992397 | M14: 0 | N14: 0 | O14: 0.37796854 | P14: 0 | Q14: 0.70952103 | R14: 0 | S14: -0.21228643 | T14: 0 | U14: 0 | V14: 0 | W14: 0 | X14: 0 | Y14: -0.0026268875 | Z14: -0.0011853741 | AA14: -0.002737565 | AB14: -0.00094288139 | AC14: 0.00044586031 | AD14: -0.019106695 | AE14: -0.25103273 | AF14: -0.86958608 | AG14: 2.0234399 | AH14: =AG14+AF14 -> 1.1538538 | AI14: =AH14-SUM(Y14:AD14) -> 1.1800073
A15: 40359 | B15: -0.0049286489 | C15: 0.0038186665 | D15: -0.31432153 | E15: 0.0062964574 | F15: 0.055305097598479236 | G15: 0.095633185 | H15: -0.11169417 | I15: -0.027963427 | J15: -1.4024512 | K15: 0.0075279121 | L15: -0.04146178 | M15: 0 | N15: 0 | O15: 0.23949443 | P15: 0 | Q15: 0.97200099 | R15: 0 | S15: 0.7419492 | T15: 0 | U15: 0 | V15: 0 | W15: 0 | X15: 0 | Y15: 0.00093272317 | Z15: 0.0019260657 | AA15: 0.0018005332 | AB15: 0.003250832 | AC15: 0.0057704093 | AD15: -0.019473147 | AE15: -0.24855642 | AF15: -0.054805653 | AG15: 2.0234399 | AH15: =AG15+AF15 -> 1.9686342 | AI15: =AH15-SUM(Y15:AD15) -> 1.9744268
A16: 40451 | B16: -0.00065450678 | C16: 0.0034803388 | D16: -0.34215992 | E16: 0.0078752679 | F16: 0.024228537078108126 | G16: 0.13782710498906336 | H16: -0.17641503 | I16: -0.27972026 | J16: -1.3906489 | K16: 0.0070695421 | L16: -0.023839638 | M16: 0 | N16: 0 | O16: 0.22070424 | P16: 0 | Q16: 0.94974845 | R16: 0 | S16: 0.33702384 | T16: 0 | U16: 0 | V16: 0 | W16: 0 | X16: 0 | Y16: 0.0007499975 | Z16: 0.0020536177 | AA16: 0.002856127 | AB16: 0.0035243328 | AC16: 0.0079300524 | AD16: -0.017986626 | AE16: -0.24610227 | AF16: -0.80184686 | AG16: 2.0234399 | AH16: =AG16+AF16 -> 1.221593 | AI16: =AH16-SUM(Y16:AD16) -> 1.2224655
A17: 40543 | B17: -0.011832821 | C17: 0.0031465126 | D17: -0.34137405 | E17: 0.0089876303 | F17: 0.020537242 | G17: 0.1461063366590576 | H17: -0.21631209 | I17: 0.4659558221624227 | J17: -1.4370284 | K17: 0.0063744559 | L17: -0.033350938 | M17: 0 | N17: 0 | O17: 0.17318695 | P17: 0 | Q17: 0.91626508 | R17: 0 | S17: 0.87847465 | T17: 0 | U17: 0 | V17: 0 | W17: 0 | X17: 0 | Y17: 0.00080802249 | Z17: 0.0019635097 | AA17: 0.0028718362 | AB17: 0.0031859404 | AC17: 0.006614633 | AD17: -0.017779684 | AE17: -0.24367016 | AF17: 0.31904726 | AG17: 2.0234399 | AH17: =AG17+AF17 -> 2.3424871 | AI17: =AH17-SUM(Y17:AD17) -> 2.3448229
A18: 40633 | B18: -0.023323334 | C18: 0.0028459585 | D18: -0.29088778 | E18: 0.0092307371 | F18: 0.018688313227332998 | G18: 0.19202491465022398 | H18: -0.17311384 | I18: 0.4350567860972765 | J18: -1.2346792 | K18: 0.0088652404 | L18: -0.024858959 | M18: 0 | N18: 0 | O18: 0.14068792 | P18: 0 | Q18: 0.80005385 | R18: 0 | S18: 0.44314082 | T18: 0 | U18: 0 | V18: 0 | W18: 0 | X18: 0 | Y18: 0.00021037771 | Z18: 0.0011273197 | AA18: 0.00119938 | AB18: 0.0015384826 | AC18: 0.0058556676 | AD18: -0.019586326 | AE18: -0.24125997 | AF18: 0.039659981 | AG18: 2.0234399 | AH18: =AG18+AF18 -> 2.0630999 | AI18: =AH18-SUM(Y18:AD18) -> 2.072755
A19: 40724 | B19: -0.028349217 | C19: 0.0024698998 | D19: -0.32691111 | E19: 0.0097203699 | F19: -0.013577383 | G19: 0.2129800953529548 | H19: -0.19576457 | I19: 1.026435062916109 | J19: -1.430877 | K19: 0.010043966 | L19: -0.039966721 | M19: 0 | N19: 0 | O19: 0.099372852 | P19: 0 | Q19: 1.0750906 | R19: 0 | S19: 0.49611733 | T19: 0 | U19: 0 | V19: 0 | W19: 0 | X19: 0 | Y19: 0.0018701404 | Z19: 0.0025587824 | AA19: 0.0035886564 | AB19: 0.0028006782 | AC19: 0.008490833 | AD19: -0.020005323 | AE19: -0.23887157 | AF19: 0.6482453 | AG19: 2.0234399 | AH19: =AG19+AF19 -> 2.6716852 | AI19: =AH19-SUM(Y19:AD19) -> 2.6723814
A20: 40816 | B20: -0.041144488 | C20: 0.002030522 | D20: -0.3927486 | E20: 0.010152501 | F20: -0.073564142 | G20: 0.2129739025003241 | H20: -0.18142343 | I20: 0.7506142994457843 | J20: -1.4789454 | K20: 0.01060412 | L20: -0.055352924 | M20: 0 | N20: 0 | O20: 0.036002886 | P20: 0 | Q20: 1.3218654 | R20: 0 | S20: 0.52796491 | T20: 0 | U20: 0 | V20: 0 | W20: 0 | X20: 0 | Y20: 0.0031682172 | Z20: 0.004171783 | AA20: 0.0056002919 | AB20: 0.0047509093 | AC20: 0.010606708 | AD20: -0.01693199 | AE20: -0.23650484 | AF20: 0.40736161 | AG20: 2.0234399 | AH20: =AG20+AF20 -> 2.4308015 | AI20: =AH20-SUM(Y20:AD20) -> 2.4194356
A21: 40908 | B21: -0.041397859 | C21: 0.0016751654 | D21: -0.40850416 | E21: 0.010517161466272462 | F21: -0.082078423 | G21: 0.2180477794060387 | H21: -0.19871573 | I21: 0.4045344929766381 | J21: -1.8020608 | K21: 0.011299203 | L21: -0.04842194 | M21: 0 | N21: 0 | O21: 0.16086411 | P21: 0 | Q21: 1.5189601 | R21: 0 | S21: -1.0157043 | T21: 0 | U21: 0 | V21: 0 | W21: 0 | X21: 0 | Y21: 0.0027858453 | Z21: 0.0035779828 | AA21: 0.0050151562 | AB21: 0.0054330456 | AC21: 0.0087651691 | AD21: -0.013803697 | AE21: -0.23415966 | AF21: -1.5480421 | AG21: 2.0234399 | AH21: =AG21+AF21 -> 0.47539783 | AI21: =AH21-SUM(Y21:AD21) -> 0.46362433
A22: 40999 | B22: -0.040182373 | C22: 0.0012155482 | D22: -0.40617515 | E22: 0.010250412087331462 | F22: -0.10287613 | G22: 0.22720540170388936 | H22: -0.26731634 | I22: 1.1494211929739429 | J22: -1.5929608 | K22: 0.015634328 | L22: -0.051875417 | M22: 0 | N22: 0 | O22: 0.094257688 | P22: 0 | Q22: 1.3238852 | R22: 0 | S22: 0.22715006 | T22: 0 | U22: 0 | V22: 0 | W22: 0 | X22: 0 | Y22: 0.0032858537 | Z22: 0.0036075908 | AA22: 0.0036986243 | AB22: 0.0065556896 | AC22: 0.0063736528 | AD22: -0.011058441 | AE22: -0.23183589 | AF22: 0.34552793 | AG22: 2.0234399 | AH22: =AG22+AF22 -> 2.3689678 | AI22: =AH22-SUM(Y22:AD22) -> 2.3565048
A23: 41090 | B23: -0.042687982 | C23: 0.00092759871 | D23: -0.43158649 | E23: 0.0095969182 | F23: -0.11330361 | G23: 0.24067179632887292 | H23: -0.27308878 | I23: 0.5519723869845672 | J23: -1.5269137 | K23: 0.013499818 | L23: -0.054154267 | M23: 0 | N23: 0 | O23: 0.12161021 | P23: 0 | Q23: 1.4343299 | R23: 0 | S23: -0.041642408 | T23: 0 | U23: 0 | V23: 0 | W23: 0 | X23: 0 | Y23: 0.001756452 | Z23: 0.0036784679 | AA23: 0.0026565554 | AB23: 0.0075108885 | AC23: 0.005194498 | AD23: -0.01017148 | AE23: -0.2295334 | AF23: -0.36173887 | AG23: 2.0234399 | AH23: =AG23+AF23 -> 1.661701 | AI23: =AH23-SUM(Y23:AD23) -> 1.6510756
A24: 41182 | B24: -0.04665733 | C24: 0.00067521144 | D24: -0.4121087 | E24: 0.0083652009 | F24: -0.13140542 | G24: 0.2632844363045672 | H24: -0.19641208 | I24: 0.42923854405880757 | J24: -1.6153899 | K24: 0.013683483 | L24: -0.05271867 | M24: 0 | N24: 0 | O24: 0.095619955 | P24: 0 | Q24: 1.4082038 | R24: 0 | S24: 0.66505092 | T24: 0 | U24: 0 | V24: 0 | W24: 0 | X24: 0 | Y24: 0.00075410251 | Z24: 0.0031056699 | AA24: 0.0022943731 | AB24: 0.00779642 | AC24: 0.0063001542 | AD24: -0.0079876286 | AE24: -0.22725207 | AF24: 0.19045036 | AG24: 2.0234399 | AH24: =AG24+AF24 -> 2.2138902 | AI24: =AH24-SUM(Y24:AD24) -> 2.2016271
A25: 41274 | B25: -0.044352611 | C25: 0.00031825953 | D25: -0.41140733 | E25: 0.0076878018 | F25: -0.14180862 | G25: 0.2907152155126713 | H25: -0.20917982 | I25: 0.3417062455340014 | J25: -1.2996789 | K25: 0.017280105 | L25: -0.062592489 | M25: 0 | N25: 0 | O25: 0.0068516177 | P25: 0 | Q25: 1.2661869 | R25: 0 | S25: 0.46398755 | T25: 0 | U25: 0 | V25: 0 | W25: 0 | X25: 0 | Y25: 0.0016586562 | Z25: 0.0033519785 | AA25: 0.0025075061 | AB25: 0.0078807469 | AC25: 0.0064424759 | AD25: -0.0068885156 | AE25: -0.22499176 | AF25: -0.0044127786 | AG25: 2.0234399 | AH25: =AG25+AF25 -> 2.0190271 | AI25: =AH25-SUM(Y25:AD25) -> 2.0040743
A26: 41364 | B26: -0.050390282 | C26: -2.4316751e-05 | D26: -0.41186825 | E26: 0.0072421782 | F26: -0.13077216 | G26: 0.30218167380156036 | H26: -0.26055429 | I26: 0.5465164410890067 | J26: -1.537189 | K26: 0.014487205 | L26: -0.072908605 | M26: 0 | N26: 0 | O26: 0.039548157 | P26: 0 | Q26: 1.360459 | R26: 0 | S26: 0.0082457134 | T26: 0 | U26: 0 | V26: 0 | W26: 0 | X26: 0 | Y26: 0.002209783 | Z26: 0.0027731836 | AA26: 0.0020333626 | AB26: 0.0072175468 | AC26: 0.0059307435 | AD26: -0.0049703692 | AE26: -0.22275233 | AF26: -0.42476594 | AG26: 2.0234399 | AH26: =AG26+AF26 -> 1.5986739 | AI26: =AH26-SUM(Y26:AD26) -> 1.5834797
A27: 41455 | B27: -0.048459056 | C27: -0.00021946766 | D27: -0.40719128 | E27: 0.0065285755 | F27: -0.10979728 | G27: 0.30308153741402943 | H27: -0.28455534 | I27: 0.16404198038495466 | J27: -1.5674248 | K27: 0.01093532 | L27: -0.081651619 | M27: 0 | N27: 0 | O27: 0.083295851 | P27: 0 | Q27: 1.3495488 | R27: 0 | S27: -0.32616426 | T27: 0 | U27: 0 | V27: 0 | W27: 0 | X27: 0 | Y27: 0.0015165631 | Z27: 0.0010272834 | AA27: 0.0016143955 | AB27: 0.0064054301 | AC27: 0.004123373 | AD27: -0.0046367654 | AE27: -0.22053365 | AF27: -1.1591876 | AG27: 2.0234399 | AH27: =AG27+AF27 -> 0.8642523 | AI27: =AH27-SUM(Y27:AD27) -> 0.85420202
A28: 41547 | B28: -0.050281618 | C28: -0.0004689841 | D28: -0.39527142 | E28: 0.0056391572 | F28: -0.11833607 | G28: 0.3076417645542673 | H28: -0.33323304 | I28: 0.7448460649187583 | J28: -1.7067997 | K28: 0.0082880571 | L28: -0.09540704 | M28: 0 | N28: 0 | O28: 0.057743374 | P28: 0 | Q28: 1.3754684 | R28: 0 | S28: 0.38690506 | T28: 0 | U28: 0 | V28: 0 | W28: 0 | X28: 0 | Y28: 0.0025737018 | Z28: 0.0010632157 | AA28: 0.0031594729 | AB28: 0.0063773075 | AC28: 0.0053668834 | AD28: -0.0045602403 | AE28: -0.21833559 | AF28: -0.048380435 | AG28: 2.0234399 | AH28: =AG28+AF28 -> 1.9750594 | AI28: =AH28-SUM(Y28:AD28) -> 1.9610791
A29: 41639 | B29: -0.056233494 | C29: -0.00066221527 | D29: -0.38929887 | E29: 0.0050774589 | F29: -0.10854166 | G29: 0.3203872006084074 | H29: -0.41183203 | I29: 0.8797795721716462 | J29: -1.718091 | K29: 0.0056687414 | L29: -0.10278738 | M29: 0 | N29: 0 | O29: 0.091915763 | P29: 0 | Q29: 1.4028546 | R29: 0 | S29: 0.42027859 | T29: 0 | U29: 0 | V29: 0 | W29: 0 | X29: 0 | Y29: 0.0033025421 | Z29: 0.0015938666 | AA29: 0.0048173042 | AB29: 0.0050466636 | AC29: 0.0058730377 | AD29: -0.0044938425 | AE29: -0.216158 | AF29: 0.10877644 | AG29: 2.0234399 | AH29: =AG29+AF29 -> 2.1322163 | AI29: =AH29-SUM(Y29:AD29) -> 2.1160767
A30: 41729 | B30: -0.064244288 | C30: -0.00082225147 | D30: -0.37830983 | E30: 0.0045191477 | F30: -0.11185507 | G30: 0.3300286808235464 | H30: -0.37830003 | I30: 0.2723976010059914 | J30: -1.4919383 | K30: 0.0050810904 | L30: -0.11244597 | M30: 0 | N30: 0 | O30: 0.064710461 | P30: 0 | Q30: 1.3339957 | R30: 0 | S30: 0.26071024 | T30: 0 | U30: 0 | V30: 0 | W30: 0 | X30: 0 | Y30: 0.0027965461 | Z30: 0.0020511718 | AA30: 0.0064299929 | AB30: 0.0046468564 | AC30: 0.0048603069 | AD30: -0.0058702832 | AE30: -0.21400075 | AF30: -0.49737741 | AG30: 2.0234399 | AH30: =AG30+AF30 -> 1.5260625 | AI30: =AH30-SUM(Y30:AD30) -> 1.5111479
A31: 41820 | B31: -0.062019428 | C31: -0.0010286397 | D31: -0.38130092 | E31: 0.004654898 | F31: -0.10851954 | G31: 0.3296538511825542 | H31: -0.40861871 | I31: 0.8777272807984904 | J31: -1.6106853 | K31: 0.0070905086 | L31: -0.12261427 | M31: 0 | N31: 0 | O31: 0.088802365 | P31: 0 | Q31: 1.3317665 | R31: 0 | S31: 0.53603774 | T31: 0 | U31: 0 | V31: 0 | W31: 0 | X31: 0 | Y31: 0.0034653639 | Z31: 0.0023969224 | AA31: 0.0065239783 | AB31: 0.0052207488 | AC31: 0.0037355586 | AD31: -0.0070227354 | AE31: -0.2118637 | AF31: 0.25917423 | AG31: 2.0234399 | AH31: =AG31+AF31 -> 2.2826141 | AI31: =AH31-SUM(Y31:AD31) -> 2.2682943
A32: 41912 | B32: -0.063694694 | C32: -0.0012057019 | D32: -0.39725264 | E32: 0.0046762355 | F32: -0.10529124 | G32: 0.3272456831570958 | H32: -0.46317742 | I32: 0.7380634719899248 | J32: -1.6560808 | K32: 0.0059367122 | L32: -0.12735902 | M32: 0 | N32: 0 | O32: 0.12772968 | P32: 0 | Q32: 1.3107877 | R32: 0 | S32: 0.16206261 | T32: 0 | U32: 0 | V32: 0 | W32: 0 | X32: 0 | Y32: 0.0035503104 | Z32: 0.0032894449 | AA32: 0.0059993178 | AB32: 0.0049147971 | AC32: 0.0032431781 | AD32: -0.0078687172 | AE32: -0.2097467 | AF32: -0.36892496 | AG32: 2.0234399 | AH32: =AG32+AF32 -> 1.6545149 | AI32: =AH32-SUM(Y32:AD32) -> 1.6413866
A33: 42004 | B33: -0.066169367 | C33: -0.0014242378 | D33: -0.4303407 | E33: 0.004671158 | F33: -0.11833906 | G33: 0.3256253955592703 | H33: -0.44308295 | I33: 0.16136934284767257 | J33: -1.5437056 | K33: 0.0078722101 | L33: -0.12024922 | M33: 0 | N33: 0 | O33: 0.17935955 | P33: 0 | Q33: 1.2568933 | R33: 0 | S33: -0.60048053 | T33: 0 | U33: 0 | V33: 0 | W33: 0 | X33: 0 | Y33: 0.0034626928 | Z33: 0.0033790248 | AA33: 0.0060269875 | AB33: 0.0051402184 | AC33: 0.0032923227 | AD33: -0.0072935166 | AE33: -0.20764962 | AF33: -1.6258508 | AG33: 2.0234399 | AH33: =AG33+AF33 -> 0.39758912 | AI33: =AH33-SUM(Y33:AD33) -> 0.3835814
A34: 42094 | B34: -0.064427222 | C34: -0.0015680556 | D34: -0.45852956 | E34: 0.0040927579 | F34: -0.13108758 | G34: 0.3197344795067947 | H34: -0.47109027 | I34: -0.25145757 | J34: -1.337412 | K34: 0.0044722474 | L34: -0.12083588 | M34: 0 | N34: 0 | O34: 0.1671031 | P34: 0 | Q34: 1.1515272 | R34: 0 | S34: -0.81840342 | T34: 0 | U34: 0 | V34: 0 | W34: 0 | X34: 0 | Y34: 0.0029359663 | Z34: 0.003346946 | AA34: 0.0058450329 | AB34: 0.0049599992 | AC34: 0.003761481 | AD34: -0.0071572574 | AE34: -0.20557232 | AF34: -2.2422187 | AG34: 2.0234399 | AH34: =AG34+AF34 -> -0.21877878 | AI34: =AH34-SUM(Y34:AD34) -> -0.23247095
A35: 42185 | B35: -0.065681971 | C35: -0.0016401549 | D35: -0.47161153 | E35: 0.0034880092 | F35: -0.12926598 | G35: 0.3172250509040131 | H35: -0.49212779 | I35: 0.8553492202115764 | J35: -1.1987232 | K35: 0.0042986223 | L35: -0.12046029 | M35: 0 | N35: 0 | O35: 0.17707014 | P35: 0 | Q35: 1.0432664 | R35: 0 | S35: 0.57912927 | T35: 0 | U35: 0 | V35: 0 | W35: 0 | X35: 0 | Y35: 0.0024125733 | Z35: 0.0031002737 | AA35: 0.0052403641 | AB35: 0.0051722935 | AC35: 0.0039668913 | AD35: -0.0069243128 | AE35: -0.20351464 | AF35: 0.29470022 | AG35: 2.0234399 | AH35: =AG35+AF35 -> 2.3181401 | AI35: =AH35-SUM(Y35:AD35) -> 2.305172
A36: 42277 | B36: -0.069914089 | C36: -0.0016652694 | D36: -0.51997881 | E36: 0.0031682068 | F36: -0.14363329 | G36: 0.30580498273886647 | H36: -0.46408422 | I36: 0.30633637859560636 | J36: -1.1323023 | K36: 0.0065239412 | L36: -0.11672762 | M36: 0 | N36: 0 | O36: 0.21745984 | P36: 0 | Q36: 1.0484011 | R36: 0 | S36: -0.18084385 | T36: 0 | U36: 0 | V36: 0 | W36: 0 | X36: 0 | Y36: 0.0025665193 | Z36: 0.0031132797 | AA36: 0.0055807073 | AB36: 0.0055199133 | AC36: 0.0045371114 | AD36: -0.0065760925 | AE36: -0.20147646 | AF36: -0.95885126 | AG36: 2.0234399 | AH36: =AG36+AF36 -> 1.0645886 | AI36: =AH36-SUM(Y36:AD36) -> 1.0498472
A37: 42369 | B37: -0.069484059 | C37: -0.0016202204 | D37: -0.52772172 | E37: 0.0024072046 | F37: -0.15340956 | G37: 0.2995912380585608 | H37: -0.40395347 | I37: -0.013093373 | J37: -1.1864277 | K37: 0.006122417 | L37: -0.10963838 | M37: 0 | N37: 0 | O37: 0.26242957 | P37: 0 | Q37: 1.056706 | R37: 0 | S37: -0.96823363 | T37: 0 | U37: 0 | V37: 0 | W37: 0 | X37: 0 | Y37: 0.0021622771 | Z37: 0.0032440367 | AA37: 0.0054946842 | AB37: 0.0057477052 | AC37: 0.0048620844 | AD37: -0.0063997361 | AE37: -0.19945762 | AF37: -2.0316378 | AG37: 2.0234399 | AH37: =AG37+AF37 -> -0.008197896 | AI37: =AH37-SUM(Y37:AD37) -> -0.023308947
A38: 42460 | B38: -0.06857156 | C38: -0.0015844285 | D38: -0.57911584 | E38: 0.0025001229 | F38: -0.16010208 | G38: 0.29806389807720546 | H38: -0.39491695 | I38: 0.2557900215861775 | J38: -1.2103506 | K38: 0.0076176192 | L38: -0.10389852 | M38: 0 | N38: 0 | O38: 0.30786359 | P38: 0 | Q38: 1.040377 | R38: 0 | S38: -1.5367435 | T38: 0 | U38: 0 | V38: 0 | W38: 0 | X38: 0 | Y38: 0.0027581791 | Z38: 0.0036445689 | AA38: 0.0058578777 | AB38: 0.0061148676 | AC38: 0.0052643523 | AD38: -0.0061317793 | AE38: -0.19745798 | AF38: -2.3714134 | AG38: 2.0234399 | AH38: =AG38+AF38 -> -0.34797349 | AI38: =AH38-SUM(Y38:AD38) -> -0.36548156
A39: 42551 | B39: -0.074995251 | C39: -0.0015117118 | D39: -0.55014221 | E39: 0.0017907553 | F39: -0.15220451 | G39: 0.3044505589981039 | H39: -0.33947028 | I39: 1.2627911398559677 | J39: -1.2684034 | K39: 0.0064031979 | L39: -0.11573178 | M39: 0 | N39: 0 | O39: 0.28497996 | P39: 0 | Q39: 1.0557019 | R39: 0 | S39: 0.49987409 | T39: 0 | U39: 0 | V39: 0 | W39: 0 | X39: 0 | Y39: 0.0024172774 | Z39: 0.0034108716 | AA39: 0.0054521081 | AB39: 0.0057727962 | AC39: 0.0049512662 | AD39: -0.0062291955 | AE39: -0.1954774 | AF39: 0.724544 | AG39: 2.0234399 | AH39: =AG39+AF39 -> 2.7479839 | AI39: =AH39-SUM(Y39:AD39) -> 2.7322087
A40: 42643 | B40: -0.076621509 | C40: -0.0014589212 | D40: -0.53297539 | E40: 0.001524449 | F40: -0.13887963 | G40: 0.30673717015501367 | H40: -0.35191053 | I40: 0.6041596969335261 | J40: -1.3202516 | K40: 0.0059570732 | L40: -0.12274352 | M40: 0 | N40: 0 | O40: 0.30012214 | P40: 0 | Q40: 1.0417559 | R40: 0 | S40: -0.49870324 | T40: 0 | U40: 0 | V40: 0 | W40: 0 | X40: 0 | Y40: 0.0024422084 | Z40: 0.0033288667 | AA40: 0.0051921855 | AB40: 0.0055477416 | AC40: 0.005031098 | AD40: -0.0058523861 | AE40: -0.19351573 | AF40: -0.9966797 | AG40: 2.0234399 | AH40: =AG40+AF40 -> 1.0267602 | AI40: =AH40-SUM(Y40:AD40) -> 1.0110705
A41: 42735 | B41: -0.07784644 | C41: -0.0013365918 | D41: -0.48482714 | E41: 0.00082474633 | F41: -0.11893854 | G41: 0.3043322 | H41: -0.36322233 | I41: 0.5705624828837852 | J41: -1.2726177 | K41: 0.0034555036 | L41: -0.13143387 | M41: 0 | N41: 0 | O41: 0.3121704 | P41: 0 | Q41: 1.0122814 | R41: 0 | S41: 0.36988291 | T41: 0 | U41: 0 | V41: 0 | W41: 0 | X41: 0 | Y41: 0.0020135068 | Z41: 0.0028609341 | AA41: 0.0046190719 | AB41: 0.0053186926 | AC41: 0.0051645738 | AD41: -0.006111643 | AE41: -0.19157284 | AF41: -0.074594429 | AG41: 2.0234399 | AH41: =AG41+AF41 -> 1.9488454 | AI41: =AH41-SUM(Y41:AD41) -> 1.9349803
A42: 42825 | B42: -0.081322961 | C42: -0.0012651062 | D42: -0.44423232 | E42: 0.00052169315 | F42: -0.10927601 | G42: 0.3120530040410463 | H42: -0.36537453 | I42: 0.7028603320001325 | J42: -1.2018549 | K42: 0.003352206 | L42: -0.13490314 | M42: 0 | N42: 0 | O42: 0.32347082 | P42: 0 | Q42: 0.98363826 | R42: 0 | S42: 0.23636252 | T42: 0 | U42: 0 | V42: 0 | W42: 0 | X42: 0 | Y42: 0.0020045156 | Z42: 0.0027273264 | AA42: 0.0046078142 | AB42: 0.0055815558 | AC42: 0.0051106786 | AD42: -0.0062644569 | AE42: -0.18964857 | AF42: 0.030910682 | AG42: 2.0234399 | AH42: =AG42+AF42 -> 2.0543506 | AI42: =AH42-SUM(Y42:AD42) -> 2.0405831
A43: 42916 | B43: -0.079591585 | C43: -0.0011819274 | D43: -0.42590135 | E43: 0.00014761247 | F43: -0.11172094 | G43: 0.3091861307358057 | H43: -0.32988476 | I43: 0.15289535651752395 | J43: -1.1728799 | K43: 0.0033250436 | L43: -0.13975257 | M43: 0 | N43: 0 | O43: 0.32533567 | P43: 0 | Q43: 0.98909869 | R43: 0 | S43: -0.28835828 | T43: 0 | U43: 0 | V43: 0 | W43: 0 | X43: 0 | Y43: 0.0020751173 | Z43: 0.0028854647 | AA43: 0.0049276388 | AB43: 0.00552856 | AC43: 0.0049355121 | AD43: -0.0063959853 | AE43: -0.18774277 | AF43: -0.97294384 | AG43: 2.0234399 | AH43: =AG43+AF43 -> 1.050496 | AI43: =AH43-SUM(Y43:AD43) -> 1.0365397
A44: 43008 | B44: -0.07928668 | C44: -0.0010942113 | D44: -0.39726261 | E44: -0.00038355423 | F44: -0.11672059 | G44: 0.31301133447860785 | H44: -0.3420035 | I44: 0.29538504012383004 | J44: -1.0647028 | K44: 0.0018614315 | L44: -0.14062955 | M44: 0 | N44: 0 | O44: 0.29735094 | P44: 0 | Q44: 0.89585539 | R44: 0 | S44: 0.57239755 | T44: 0 | U44: 0 | V44: 0 | W44: 0 | X44: 0 | Y44: 0.0021160241 | Z44: 0.0030773689 | AA44: 0.0047645915 | AB44: 0.0052908075 | AC44: 0.0047418183 | AD44: -0.0067779054 | AE44: -0.18585532 | AF44: 0.047646943 | AG44: 2.0234399 | AH44: =AG44+AF44 -> 2.0710868 | AI44: =AH44-SUM(Y44:AD44) -> 2.0578741
A45: 43100 | B45: -0.081973966 | C45: -0.0011129659 | D45: -0.36282393 | E45: -0.00051034352 | F45: -0.12583435 | G45: 0.3058082063159384 | H45: -0.40019258 | I45: 0.6599808451930311 | J45: -0.93377832 | K45: 0.0026424845 | L45: -0.14567065 | M45: 0 | N45: 0 | O45: 0.25618757 | P45: 0 | Q45: 0.79354907 | R45: 0 | S45: 0.66834505 | T45: 0 | U45: 0 | V45: 0 | W45: 0 | X45: 0 | Y45: 0.0026347078 | Z45: 0.0031888578 | AA45: 0.0047064171 | AB45: 0.0052130777 | AC45: 0.0043868362 | AD45: -0.0069621156 | AE45: -0.18398605 | AF45: 0.45936186 | AG45: 2.0234399 | AH45: =AG45+AF45 -> 2.4828017 | AI45: =AH45-SUM(Y45:AD45) -> 2.469634
A46: 43190 | B46: -0.082611816 | C46: -0.0012016518 | D46: -0.32833388 | E46: -0.00077920854 | F46: -0.12930874 | G46: 0.30128461729641565 | H46: -0.38668637 | I46: 1.0780034257121152 | J46: -0.92223798 | K46: 0.0031674746 | L46: -0.14912403 | M46: 0 | N46: 0 | O46: 0.24130276 | P46: 0 | Q46: 0.77326226 | R46: 0 | S46: 0.32116966 | T46: 0 | U46: 0 | V46: 0 | W46: 0 | X46: 0 | Y46: 0.0026483854 | Z46: 0.0030576965 | AA46: 0.0045667916 | AB46: 0.0048632734 | AC46: 0.0041360845 | AD46: -0.0061691295 | AE46: -0.18213483 | AF46: 0.54514298 | AG46: 2.0234399 | AH46: =AG46+AF46 -> 2.5685829 | AI46: =AH46-SUM(Y46:AD46) -> 2.5554798
A47: 43281 | B47: -0.080109412 | C47: -0.001270972 | D47: -0.33654566 | E47: -0.0012022435 | F47: -0.13748639 | G47: 0.29558741540698374 | H47: -0.3659854 | I47: 1.024527519437779 | J47: -0.99309482 | K47: 0.0023719703 | L47: -0.14676232 | M47: 0 | N47: 0 | O47: 0.26675686 | P47: 0 | Q47: 0.83741369 | R47: 0 | S47: 0.63354588 | T47: 0 | U47: 0 | V47: 0 | W47: 0 | X47: 0 | Y47: 0.0026079215 | Z47: 0.0030105594 | AA47: 0.0043191076 | AB47: 0.0047468587 | AC47: 0.0048697235 | AD47: -0.0042258441 | AE47: -0.18030151 | AF47: 0.83456244 | AG47: 2.0234399 | AH47: =AG47+AF47 -> 2.8580023 | AI47: =AH47-SUM(Y47:AD47) -> 2.842674
A48: 43373 | B48: -0.075080161 | C48: -0.0013592191 | D48: -0.33010841 | E48: -0.0016385989 | F48: -0.14569196 | G48: 0.29480686352831853 | H48: -0.37395909 | I48: 0.34562376904105907 | J48: -0.99795232 | K48: 0.00044317931 | L48: -0.14305931 | M48: 0 | N48: 0 | O48: 0.26107474 | P48: 0 | Q48: 0.80764089 | R48: 0 | S48: 0.25273876 | T48: 0 | U48: 0 | V48: 0 | W48: 0 | X48: 0 | Y48: 0.0024569607 | Z48: 0.0026861939 | AA48: 0.0041270507 | AB48: 0.0053326997 | AC48: 0.0064407823 | AD48: -0.0042966772 | AE48: -0.17848595 | AF48: -0.2851128 | AG48: 2.0234399 | AH48: =AG48+AF48 -> 1.7383271 | AI48: =AH48-SUM(Y48:AD48) -> 1.7215801
A49: 43465 | B49: -0.071642485 | C49: -0.0014678454 | D49: -0.343888 | E49: -0.0019842227 | F49: -0.16462917 | G49: 0.2922228324950371 | H49: -0.31566533 | I49: 0.6622444008576922 | J49: -1.0547226 | K49: 5.1347224e-05 | L49: -0.13885207 | M49: 0 | N49: 0 | O49: 0.259948 | P49: 0 | Q49: 0.8361712 | R49: 0 | S49: -0.071867218 | T49: 0 | U49: 0 | V49: 0 | W49: 0 | X49: 0 | Y49: 0.0024053187 | Z49: 0.0027092177 | AA49: 0.0048996852 | AB49: 0.0068395087 | AC49: 0.0063634931 | AD49: -0.0022505863 | AE49: -0.176688 | AF49: -0.28868431 | AG49: 2.0234399 | AH49: =AG49+AF49 -> 1.7347556 | AI49: =AH49-SUM(Y49:AD49) -> 1.7137889
A50: 43555 | B50: -0.063285083 | C50: -0.001582741 | D50: -0.36033487 | E50: -0.0025719625 | F50: -0.1928648 | G50: 0.28492452590145323 | H50: -0.34389478 | I50: 0.19589118883480694 | J50: -0.77787864 | K50: -0.0019442807 | L50: -0.13749424 | M50: 0 | N50: 0 | O50: 0.20683296 | P50: 0 | Q50: 0.7906206 | R50: 0 | S50: -0.24191567 | T50: 0 | U50: 0 | V50: 0 | W50: 0 | X50: 0 | Y50: 0.0023150231 | Z50: 0.0032546263 | AA50: 0.006291975 | AB50: 0.0066560776 | AC50: 0.0078993727 | AD50: -0.0023170998 | AE50: -0.17490751 | AF50: -0.81825238 | AG50: 2.0234399 | AH50: =AG50+AF50 -> 1.2051875 | AI50: =AH50-SUM(Y50:AD50) -> 1.1810875
A51: 43646 | B51: -0.0703667 | C51: -0.0017905924 | D51: -0.3693624 | E51: -0.0026918601 | F51: -0.20359679 | G51: 0.28352316214830253 | H51: -0.3942509 | I51: 0.5747815189666827 | J51: -0.80588588 | K51: -0.0027440152 | L51: -0.14176258 | M51: 0 | N51: 0 | O51: 0.18246889 | P51: 0 | Q51: 0.84826375 | R51: 0 | S51: 0.31965086 | T51: 0 | U51: 0 | V51: 0 | W51: 0 | X51: 0 | Y51: 0.0029501183 | Z51: 0.0044980771 | AA51: 0.0061343232 | AB51: 0.0079765972 | AC51: 0.0076371807 | AD51: -0.0021364209 | AE51: -0.17314435 | AF51: 0.059843864 | AG51: 2.0234399 | AH51: =AG51+AF51 -> 2.0832837 | AI51: =AH51-SUM(Y51:AD51) -> 2.0562239
A52: 43738 | B52: -0.071647185 | C52: -0.002105057 | D52: -0.37152321 | E52: -0.0030551495 | F52: -0.20898721 | G52: 0.30048242319229423 | H52: -0.41525923 | I52: 0.36532973772454014 | J52: -0.91452217 | K52: -0.002273531 | L52: -0.13616786 | M52: 0 | N52: 0 | O52: 0.18238978 | P52: 0 | Q52: 0.90819217 | R52: 0 | S52: -0.21107469 | T52: 0 | U52: 0 | V52: 0 | W52: 0 | X52: 0 | Y52: 0.0038806183 | Z52: 0.0041172888 | AA52: 0.0073034338 | AB52: 0.0076862886 | AC52: 0.0076687116 | AD52: -0.0015208064 | AE52: -0.17139837 | AF52: -0.74645274 | AG52: 2.0234399 | AH52: =AG52+AF52 -> 1.2769871 | AI52: =AH52-SUM(Y52:AD52) -> 1.2478516
A53: 43830 | B53: -0.067761735 | C53: -0.002550686 | D53: -0.35388201 | E53: -0.0040228402 | F53: -0.21601679 | G53: 0.3247028533085672 | H53: -0.40875945 | I53: 0.15301549286157456 | J53: -0.75704308 | K53: -0.0018793723 | L53: -0.12559575 | M53: 0 | N53: 0 | O53: 0.13762718 | P53: 0 | Q53: 0.8320012 | R53: 0 | S53: -0.1213471 | T53: 0 | U53: 0 | V53: 0 | W53: 0 | X53: 0 | Y53: 0.0029589568 | Z53: 0.0046654594 | AA53: 0.0066479616 | AB53: 0.0074536338 | AC53: 0.0078622439 | AD53: -0.00064001905 | AE53: -0.16966943 | AF53: -0.77376842 | AG53: 2.0234399 | AH53: =AG53+AF53 -> 1.2496715 | AI53: =AH53-SUM(Y53:AD53) -> 1.2207232
A54: 43921 | B54: -0.069462585 | C54: -0.0027074776 | D54: -0.41552406 | E54: -0.0064574106 | F54: -0.25691318 | G54: 0.3423081578463716 | H54: -0.33745286 | I54: 0.39903146686557367 | J54: -0.62415698 | K54: -0.0091012777 | L54: -0.11931778 | M54: 0 | N54: 0 | O54: 0.033925786 | P54: 0 | Q54: 0.90098234 | R54: 0 | S54: 0.15436322 | T54: 0 | U54: 0 | V54: 0 | W54: 0 | X54: 0 | Y54: 0.003072283 | Z54: 0.0037045521 | AA54: 0.0060585386 | AB54: 0.007285407 | AC54: 0.0081056165 | AD54: 0.00073494536 | AE54: -0.16795738 | AF54: -0.16206569 | AG54: 2.0234399 | AH54: =AG54+AF54 -> 1.8613742 | AI54: =AH54-SUM(Y54:AD54) -> 1.8324128
A55: 44012 | B55: -0.072480524 | C55: -0.0025275105 | D55: -0.45090212 | E55: -0.0072033586 | F55: -0.28444485 | G55: 0.3106365 | H55: -0.24278687 | I55: -1.5591509 | J55: -0.44141867 | K55: -0.019251244 | L55: -0.11659105 | M55: 0 | N55: 0 | O55: 0.0068158875 | P55: 0 | Q55: 0.93438032 | R55: 0 | S55: -1.3704209 | T55: 0 | U55: 0 | V55: 0 | W55: 0 | X55: 0 | Y55: 0.00067926824 | Z55: 0.0033535723 | AA55: 0.0063569821 | AB55: 0.0080764885 | AC55: 0.0091246498 | AD55: 0.0032654261 | AE55: -0.16626209 | AF55: -3.4896088 | AG55: 2.0234399 | AH55: =AG55+AF55 -> -1.4661689 | AI55: =AH55-SUM(Y55:AD55) -> -1.4970253
A56: 44104 | B56: -0.078828478 | C56: -0.0022075932 | D56: -0.41667435 | E56: -0.0075645439 | F56: -0.30589463 | G56: 0.31633067310994356 | H56: -0.20242313 | I56: 1.424923843088366 | J56: -0.33353545 | K56: -0.021216561 | L56: -0.13066789 | M56: 0 | N56: 0 | O56: -0.17658663 | P56: 0 | Q56: 0.78948676 | R56: 0 | S56: 0.76640796 | T56: 0 | U56: 0 | V56: 0 | W56: 0 | X56: 0 | Y56: 0.0015197267 | Z56: 0.0049771367 | AA56: 0.0082694042 | AB56: 0.009946577 | AC56: 0.010717777 | AD56: 0.0068855702 | AE56: -0.1645834 | AF56: 1.5213728 | AG56: 2.0234399 | AH56: =AG56+AF56 -> 3.5448127 | AI56: =AH56-SUM(Y56:AD56) -> 3.5024965
A57: 44196 | B57: -0.075495372 | C57: -0.0021275741 | D57: -0.38336624 | E57: -0.0059159668 | F57: -0.32410139 | G57: 0.3051323937020234 | H57: -0.33980788 | I57: 0.5780679618979434 | J57: -0.029411043 | K57: -0.016613763 | L57: -0.14703174 | M57: 0 | N57: 0 | O57: -0.27335771 | P57: 0 | Q57: 0.79253929 | R57: 0 | S57: 0.7377333 | T57: 0 | U57: 0 | V57: 0 | W57: 0 | X57: 0 | Y57: 0.0060527901 | Z57: 0.0087483573 | AA57: 0.011304082 | AB57: 0.012247131 | AC57: 0.012722781 | AD57: 0.011413878 | AE57: -0.16292118 | AF57: 0.72217256 | AG57: 2.0234399 | AH57: =AG57+AF57 -> 2.7456124 | AI57: =AH57-SUM(Y57:AD57) -> 2.6831234
A58: 44286 | B58: -0.089512368 | C58: -0.0021312546 | D58: -0.33714424 | E58: -0.0045032696 | F58: -0.29961502 | G58: 0.33721043770096326 | H58: -0.40548057 | I58: 2.2074869248508877 | J58: -0.10271872 | K58: -0.012642088 | L58: -0.13640094 | M58: 0 | N58: 0 | O58: -0.27028745 | P58: 0 | Q58: 0.73035611 | R58: 0 | S58: 1.5455325 | T58: 0 | U58: 0 | V58: 0 | W58: 0 | X58: 0 | Y58: 0.0096796229 | Z58: 0.011062865 | AA58: 0.013168001 | AB58: 0.01309205 | AC58: 0.013279747 | AD58: 0.0149379 | AE58: -0.16127529 | AF58: 3.1412577 | AG58: 2.0234399 | AH58: =AG58+AF58 -> 5.1646976 | AI58: =AH58-SUM(Y58:AD58) -> 5.0894774
A59: 44377 | B59: -0.11285607 | C59: -0.0025162685 | D59: -0.31008378 | E59: -0.0027446822 | F59: -0.28869866 | G59: 0.38072035814129546 | H59: -0.4598622 | I59: 3.750169112208268 | J59: -0.097018194 | K59: -0.0037712936 | L59: -0.11125941 | M59: 0 | N59: 0 | O59: -0.24819073 | P59: 0 | Q59: 0.62681877 | R59: 0 | S59: 1.178136 | T59: 0 | U59: 0 | V59: 0 | W59: 0 | X59: 0 | Y59: 0.013784719 | Z59: 0.013091498 | AA59: 0.014326853 | AB59: 0.01329953 | AC59: 0.01320497 | AD59: 0.017021975 | AE59: -0.15964558 | AF59: 4.315801 | AG59: 2.0234399 | AH59: =AG59+AF59 -> 6.3392408 | AI59: =AH59-SUM(Y59:AD59) -> 6.2545113
A60: 44469 | B60: -0.10924347 | C60: -0.0025197062 | D60: -0.26136632 | E60: -0.0017110082 | F60: -0.23346243 | G60: 0.3552877347858141 | H60: -0.43454715 | I60: 3.4823440597381294 | J60: -0.16257459 | K60: -0.0062167583 | L60: -0.11061941 | M60: 0 | N60: 0 | O60: -0.16434163 | P60: 0 | Q60: 0.62369473 | R60: 0 | S60: 1.1433775 | T60: 0 | U60: 0 | V60: 0 | W60: 0 | X60: 0 | Y60: 0.011563369 | Z60: 0.0093167494 | AA60: 0.012385953 | AB60: 0.010377692 | AC60: 0.010636052 | AD60: 0.016041672 | AE60: -0.15803192 | AF60: 4.1211847 | AG60: 2.0234399 | AH60: =AG60+AF60 -> 6.1446246 | AI60: =AH60-SUM(Y60:AD60) -> 6.0743031
A61: 44561 | B61: -0.097918285 | C61: -0.0027681282 | D61: -0.26628254 | E61: -0.00038972292 | F61: -0.22266275 | G61: 0.3569255288905282 | H61: -0.43371125 | I61: 3.6689661744005786 | J61: -0.26283067 | K61: 0.0013925653 | L61: -0.10295649 | M61: 0 | N61: 0 | O61: -0.11902644 | P61: 0 | Q61: 0.7219213 | R61: 0 | S61: 1.8251186 | T61: 0 | U61: 0 | V61: 0 | W61: 0 | X61: 0 | Y61: 0.014729347 | Z61: 0.0089981765 | AA61: 0.013629331 | AB61: 0.010567784 | AC61: 0.010372239 | AD61: 0.014685828 | AE61: -0.15643416 | AF61: 5.1180238 | AG61: 2.0234399 | AH61: =AG61+AF61 -> 7.1414636 | AI61: =AH61-SUM(Y61:AD61) -> 7.0684809
A62: 44651 | B62: -0.094292349 | C62: -0.0027927876 | D62: -0.29710177 | E62: 0.0011389795 | F62: -0.18984604 | G62: 0.2985008603912487 | H62: -0.31919804 | I62: 4.429854847877768 | J62: -0.59288925 | K62: 0.0070905489 | L62: -0.11245187 | M62: 0 | N62: 0 | O62: -0.04209671 | P62: 0 | Q62: 0.80560167 | R62: 0 | S62: 2.3709091 | T62: 0 | U62: 0 | V62: 0 | W62: 0 | X62: 0 | Y62: 0.012618746 | Z62: 0.0087626339 | AA62: 0.012050066 | AB62: 0.0095891046 | AC62: 0.010236857 | AD62: 0.013547705 | AE62: -0.15485217 | AF62: 6.3570894 | AG62: 2.0234399 | AH62: =AG62+AF62 -> 8.3805293 | AI62: =AH62-SUM(Y62:AD62) -> 8.3137242
A63: 44742 | B63: -0.095705291 | C63: -0.0024177323 | D63: -0.23277342 | E63: 0.0028010581 | F63: -0.08389644 | G63: 0.24175922186908672 | H63: -0.23469171 | I63: 4.483473750492029 | J63: -1.1199247 | K63: 0.0084734312 | L63: -0.099805636 | M63: 0 | N63: 0 | O63: 0.29801534 | P63: 0 | Q63: 0.89045177 | R63: 0 | S63: 3.1916996 | T63: 0 | U63: 0 | V63: 0 | W63: 0 | X63: 0 | Y63: 0.0086206174 | Z63: 0.002010707 | AA63: 0.0056977799 | AB63: 0.00089079485 | AC63: 0.0081641914 | AD63: 0.010865492 | AE63: -0.1532858 | AF63: 7.3659747 | AG63: 2.0234399 | AH63: =AG63+AF63 -> 9.3894146 | AI63: =AH63-SUM(Y63:AD63) -> 9.353165
A64: 44834 | B64: -0.090615517 | C64: -0.0022070556 | D64: -0.22093893 | E64: 0.0039533714 | F64: -0.054035901 | G64: 0.2193179861267769 | H64: -0.27532111 | I64: 3.332532796830545 | J64: -1.2688454 | K64: 0.0027193533 | L64: -0.086930224 | M64: 0 | N64: 0 | O64: 0.44162457 | P64: 0 | Q64: 0.94729633 | R64: 0 | S64: -0.28617602 | T64: 0 | U64: 0 | V64: 0 | W64: 0 | X64: 0 | Y64: 0.0093141725 | Z64: -0.0010205299 | AA64: 0.0090570876 | AB64: -0.00049645796 | AC64: 0.0084550461 | AD64: 0.010174512 | AE64: -0.15173493 | AF64: 2.5584314 | AG64: 2.0234399 | AH64: =AG64+AF64 -> 4.5818713 | AI64: =AH64-SUM(Y64:AD64) -> 4.5463874
A65: 44926 | B65: -0.089777435 | C65: -0.001770014 | D65: -0.18068899 | E65: 0.0049470381 | F65: 0.010833773787788381 | G65: 0.18223638535099784 | H65: -0.29501964 | I65: 3.2078632906106908 | J65: -1.5156976 | K65: -0.0048211281 | L65: -0.076784662 | M65: 0 | N65: 0 | O65: 0.66547107 | P65: 0 | Q65: 0.98825432 | R65: 0 | S65: -1.0203729 | T65: 0 | U65: 0 | V65: 0 | W65: 0 | X65: 0 | Y65: 0.0070291171 | Z65: -0.0053989538 | AA65: 0.0052266648 | AB65: -0.00029967832 | AC65: 0.0084409181 | AD65: 0.01125705 | AE65: -0.15019941 | AF65: 1.7238036 | AG65: 2.0234399 | AH65: =AG65+AF65 -> 3.7472435 | AI65: =AH65-SUM(Y65:AD65) -> 3.7209884
A66: 45016 | B66: -0.089543341 | C66: -0.001554171 | D66: -0.16540687 | E66: 0.0052497359 | F66: 0.035122597 | G66: 0.14596068662553474 | H66: -0.22125352 | I66: 3.206407892140928 | J66: -1.6748856 | K66: 0.00422159 | L66: -0.074901871 | M66: 0 | N66: 0 | O66: 0.67565508 | P66: 0 | Q66: 0.63312875 | R66: 0 | S66: -0.65315289 | T66: 0 | U66: 0 | V66: 0 | W66: 0 | X66: 0 | Y66: 0.0068442396 | Z66: -0.0064554808 | AA66: 0.00091366329 | AB66: -0.0023785076 | AC66: 0.0072837731 | AD66: 0.011208075 | AE66: -0.1486791 | AF66: 1.6685025 | AG66: 2.0234399 | AH66: =AG66+AF66 -> 3.6919424 | AI66: =AH66-SUM(Y66:AD66) -> 3.6745266
A67: 45107 | B67: -0.092282952 | C67: -0.001303666 | D67: -0.16653761 | E67: 0.0041972074 | F67: 0.056494426 | G67: 0.10407800110028287 | H67: -0.2685015 | I67: 2.264751207318816 | J67: -1.6298765 | K67: 0.0014413951 | L67: -0.083479144 | M67: 0 | N67: 0 | O67: 0.70602438 | P67: 0 | Q67: 0.59074113 | R67: 0 | S67: -1.4810665 | T67: 0 | U67: 0 | V67: 0 | W67: 0 | X67: 0 | Y67: 0.0051374997 | Z67: -0.0067732909 | AA67: -8.015787e-05 | AB67: -0.0034447723 | AC67: 0.0072079358 | AD67: 0.012120574 | AE67: -0.14717388 | AF67: -0.18660657 | AG67: 2.0234399 | AH67: =AG67+AF67 -> 1.8368333 | AI67: =AH67-SUM(Y67:AD67) -> 1.8226655
A68: 45199 | B68: -0.087560498 | C68: -0.00097406109 | D68: -0.10326698 | E68: 0.002486251 | F68: 0.10850264352506578 | G68: 0.086322884 | H68: -0.28672882 | I68: 1.7783121963760307 | J68: -1.5879448 | K68: 0.00061514386 | L68: -0.076400802 | M68: 0 | N68: 0 | O68: 0.80273516 | P68: 0 | Q68: 0.45465906 | R68: 0 | S68: 0.23885164 | T68: 0 | U68: 0 | V68: 0 | W68: 0 | X68: 0 | Y68: 0.0029534133 | Z68: -0.0093808092 | AA68: -0.0028496339 | AB68: -0.0058283997 | AC68: 0.0040195757 | AD68: 0.010826478 | AE68: -0.14568359 | AF68: 1.1800827 | AG68: 2.0234399 | AH68: =AG68+AF68 -> 3.2035226 | AI68: =AH68-SUM(Y68:AD68) -> 3.2037819
A69: 45291 | B69: -0.086432642 | C69: -0.00080616213 | D69: -0.092607344 | E69: 0.0010406574 | F69: 0.11344647224815763 | G69: 0.082789187 | H69: -0.35571169 | I69: 1.0610968149085798 | J69: -1.5293057 | K69: -0.00082638019 | L69: -0.074245558 | M69: 0 | N69: 0 | O69: 0.81633683 | P69: 0 | Q69: 0.47561432 | R69: 0 | S69: -0.70766737 | T69: 0 | U69: 0 | V69: 0 | W69: 0 | X69: 0 | Y69: 0.0025737185 | Z69: -0.0093375702 | AA69: -0.0029987906 | AB69: -0.0044993223 | AC69: 0.0047506995 | AD69: 0.011222501 | AE69: -0.14420812 | AF69: -0.47339235 | AG69: 2.0234399 | AH69: =AG69+AF69 -> 1.5500475 | AI69: =AH69-SUM(Y69:AD69) -> 1.5483363
A70: 45382 | B70: -0.090987562 | C70: -0.0005527695 | D70: -0.099324431 | E70: -0.00078801319 | F70: 0.12139269068744962 | G70: 0.066052605 | H70: -0.40783618 | I70: 2.0557571407400443 | J70: -1.2514255 | K70: -0.0036788974 | L70: -0.082562452 | M70: 0 | N70: 0 | O70: 0.72553793 | P70: 0 | Q70: 0.28199366 | R70: 0 | S70: -0.15689412 | T70: 0 | U70: 0 | V70: 0 | W70: 0 | X70: 0 | Y70: 0.0020682227 | Z70: -0.0089607567 | AA70: -0.0040705891 | AB70: -0.0054523882 | AC70: 0.0030615243 | AD70: 0.010587856 | AE70: -0.14274732 | AF70: 1.0028202 | AG70: 2.0234399 | AH70: =AG70+AF70 -> 3.0262601 | AI70: =AH70-SUM(Y70:AD70) -> 3.0290262
A71: 45473 | B71: -0.092475302 | C71: -0.00049949446 | D71: -0.12119541 | E71: -0.0024013838 | F71: 0.10769486589872201 | G71: 0.083243834 | H71: -0.43810932 | I71: 1.4679023594616147 | J71: -1.2965812 | K71: -0.0068607604 | L71: -0.07816796 | M71: 0 | N71: 0 | O71: 0.69592242 | P71: 0 | Q71: 0.42268767 | R71: 0 | S71: -0.083344 | T71: 0 | U71: 0 | V71: 0 | W71: 0 | X71: 0 | Y71: 0.0030501566 | Z71: -0.005246012 | AA71: -0.00085198581 | AB71: -0.0026787703 | AC71: 0.0039339708 | AD71: 0.010790278 | AE71: -0.14130107 | AF71: 0.51316393 | AG71: 2.0234399 | AH71: =AG71+AF71 -> 2.5366038 | AI71: =AH71-SUM(Y71:AD71) -> 2.5276062
A72: 45565 | B72: -0.096830756 | C72: -0.0005557662 | D72: -0.1429102 | E72: -0.0033763512 | F72: 0.09182547 | G72: 0.087543293 | H72: -0.44596839 | I72: 1.0405349604046599 | J72: -1.4121661 | K72: -0.010319803 | L72: -0.075276783 | M72: 0 | N72: 0 | O72: 0.67610735 | P72: 0 | Q72: 0.55301663 | R72: 0 | S72: -0.24283107 | T72: 0 | U72: 0 | V72: 0 | W72: 0 | X72: 0 | Y72: 0.0039239661 | Z72: -0.0030641944 | AA72: 0.0026065343 | AB72: 0.00018303909 | AC72: 0.0050946633 | AD72: 0.01121271 | AE72: -0.13986922 | AF72: -0.12440414 | AG72: 2.0234399 | AH72: =AG72+AF72 -> 1.8990357 | AI72: =AH72-SUM(Y72:AD72) -> 1.879079
A73: 45657 | B73: -0.096248696 | C73: -0.00064206318 | D73: -0.14565409 | E73: -0.0041826178 | F73: 0.088800549 | G73: 0.08291003 | H73: -0.41326473 | I73: 0.7104069147484848 | J73: -1.4001934 | K73: -0.010684187 | L73: -0.071652199 | M73: 0 | N73: 0 | O73: 0.67023158 | P73: 0 | Q73: 0.57544896 | R73: 0 | S73: -0.12306603 | T73: 0 | U73: 0 | V73: 0 | W73: 0 | X73: 0 | Y73: 0.0043189365 | Z73: -0.0019729215 | AA73: 0.0038018304 | AB73: 0.0012642727 | AC73: 0.0054179686 | AD73: 0.011084601 | AE73: -0.13845166 | AF73: -0.27499072 | AG73: 2.0234399 | AH73: =AG73+AF73 -> 1.7484492 | AI73: =AH73-SUM(Y73:AD73) -> 1.7245345
A74: 45747 | B74: -0.094769215 | C74: -0.00073393104 | D74: -0.14445377 | E74: -0.0047617855 | F74: 0.088453553 | G74: 0.076830398 | H74: -0.37452941 | I74: 0.46862322721807903 | J74: -1.3642121 | K74: -0.01022471 | L74: -0.067948601 | M74: 0 | N74: 0 | O74: 0.6671618 | P74: 0 | Q74: 0.57546217 | R74: 0 | S74: -0.062351027 | T74: 0 | U74: 0 | V74: 0 | W74: 0 | X74: 0 | Y74: 0.0045677064 | Z74: -0.0013065307 | AA74: 0.0043879588 | AB74: 0.0018603371 | AC74: 0.0055850762 | AD74: 0.010861537 | AE74: -0.13704824 | AF74: -0.38080974 | AG74: 2.0234399 | AH74: =AG74+AF74 -> 1.6426301 | AI74: =AH74-SUM(Y74:AD74) -> 1.6166741
A75: 45838 | B75: -0.093178396 | C75: -0.00080423473 | D75: -0.14244201 | E75: -0.0051246007 | F75: 0.088666295 | G75: 0.070826721 | H75: -0.33667468 | I75: 0.2788875534619706 | J75: -1.3247623 | K75: -0.0095336576 | L75: -0.064284715 | M75: 0 | N75: 0 | O75: 0.66459503 | P75: 0 | Q75: 0.57081052 | R75: 0 | S75: -0.031585221 | T75: 0 | U75: 0 | V75: 0 | W75: 0 | X75: 0 | Y75: 0.0047509348 | Z75: -0.00088516525 | AA75: 0.0046898651 | AB75: 0.002237193 | AC75: 0.005705996 | AD75: 0.010648066 | AE75: -0.13565884 | AF75: -0.46525994 | AG75: 2.0234399 | AH75: =AG75+AF75 -> 1.5581799 | AI75: =AH75-SUM(Y75:AD75) -> 1.5310331
A76: 45930 | B76: -0.091615062 | C76: -0.00084762787 | D76: -0.14027731 | E76: -0.0053040658 | F76: 0.088993741 | G76: 0.065185737 | H76: -0.30095335 | I76: 0.12742983182318923 | J76: -1.2857663 | K76: -0.0087954376 | L76: -0.060674358 | M76: 0 | N76: 0 | O76: 0.66206041 | P76: 0 | Q76: 0.56518986 | R76: 0 | S76: -0.015998941 | T76: 0 | U76: 0 | V76: 0 | W76: 0 | X76: 0 | Y76: 0.0048928675 | Z76: -0.00062933386 | AA76: 0.0048026023 | AB76: 0.0024390962 | AC76: 0.005796126 | AD76: 0.01045938 | AE76: -0.13428332 | AF76: -0.53001148 | AG76: 2.0234399 | AH76: =AG76+AF76 -> 1.4934284 | AI76: =AH76-SUM(Y76:AD76) -> 1.4656677
A77: 46022 | B77: -0.090096999 | C77: -0.00086849832 | D77: -0.13810103 | E77: -0.0053370049 | F77: 0.089339903 | G77: 0.059939432 | H77: -0.2674822 | I77: 0.0063009948 | J77: -1.2478963 | K77: -0.0080784709 | L77: -0.057114315 | M77: 0 | N77: 0 | O77: 0.65946695 | P77: 0 | Q77: 0.55937918 | R77: 0 | S77: -0.0081036723 | T77: 0 | U77: 0 | V77: 0 | W77: 0 | X77: 0 | Y77: 0.0050028986 | Z77: -0.00049273585 | AA77: 0.0047950111 | AB77: 0.0024985948 | AC77: 0.0058410453 | AD77: 0.010298487 | AE77: -0.13292156 | AF77: -0.57568421 | AG77: 2.0234399 | AH77: =AG77+AF77 -> 1.4477557 | AI77: =AH77-SUM(Y77:AD77) -> 1.4198124
A78: 46112 | B78: -0.088622872 | C78: -0.00087311732 | D78: -0.1359453 | E78: -0.0052572732 | F78: 0.089682172 | G78: 0.05506855 | H78: -0.23616503 | I78: -0.090297198 | J78: -1.211218 | K78: -0.0074109373 | L78: -0.053601343 | M78: 0 | N78: 0 | O78: 0.65680187 | P78: 0 | Q78: 0.55355053 | R78: 0 | S78: -0.0041045356 | T78: 0 | U78: 0 | V78: 0 | W78: 0 | X78: 0 | Y78: 0.0050857306 | Z78: -0.00044493792 | AA78: 0.0047142726 | AB78: 0.0024607573 | AC78: 0.0058396217 | AD78: 0.010159989 | AE78: -0.13157344 | AF78: -0.60404971 | AG78: 2.0234399 | AH78: =AG78+AF78 -> 1.4193902 | AI78: =AH78-SUM(Y78:AD78) -> 1.3915747
A79: 46203 | B79: -0.08718996 | C79: -0.00086679808 | D79: -0.13381853 | E79: -0.0050937227 | F79: 0.090013678 | G79: 0.050544879812752797 | H79: -0.20687636 | I79: -0.16694894 | J79: -1.1756952 | K79: -0.0068041652 | L79: -0.050134718 | M79: 0 | N79: 0 | O79: 0.65406783 | P79: 0 | Q79: 0.54774798 | R79: 0 | S79: -0.0020789398 | T79: 0 | U79: 0 | V79: 0 | W79: 0 | X79: 0 | Y79: 0.0051443717 | Z79: -0.00046424466 | AA79: 0.0045896147 | AB79: 0.0023612701 | AC79: 0.005804083 | AD79: 0.010041397 | AE79: -0.13023882 | AF79: -0.61752735 | AG79: 2.0234399 | AH79: =AG79+AF79 -> 1.4059125 | AI79: =AH79-SUM(Y79:AD79) -> 1.378436
A80: 46295 | B80: -0.085796313 | C80: -0.00085337012 | D80: -0.13172367 | E80: -0.0048700446 | F80: 0.090331141 | G80: 0.046340046 | H80: -0.17949527 | I80: -0.22736197 | J80: -1.1412799 | K80: -0.0062613761 | L80: -0.046715986 | M80: 0 | N80: 0 | O80: 0.65126992 | P80: 0 | Q80: 0.54198722 | R80: 0 | S80: -0.0010529739 | T80: 0 | U80: 0 | V80: 0 | W80: 0 | X80: 0 | Y80: 0.0051811727 | Z80: -0.00053415432 | AA80: 0.0044386965 | AB80: 0.0022238555 | AC80: 0.0057457062 | AD80: 0.0099446452 | AE80: -0.12891758 | AF80: -0.61865234 | AG80: 2.0234399 | AH80: =AG80+AF80 -> 1.4047875 | AI80: =AH80-SUM(Y80:AD80) -> 1.3777876
A81: 46387 | B81: -0.084440535 | C81: -0.00083541203 | D81: -0.12966214 | E81: -0.0046052828 | F81: 0.090632265 | G81: 0.042427330844718725 | H81: -0.15391004 | I81: -0.27455386 | J81: -1.1079264 | K81: -0.0057815443 | L81: -0.04334831 | M81: 0 | N81: 0 | O81: 0.64841302 | P81: 0 | Q81: 0.53627646 | R81: 0 | S81: -0.00053332533 | T81: 0 | U81: 0 | V81: 0 | W81: 0 | X81: 0 | Y81: 0.0051982124 | Z81: -0.00064154225 | AA81: 0.0042724755 | AB81: 0.0020637619 | AC81: 0.0056719735 | AD81: 0.0098695218 | AE81: -0.12760959 | AF81: -0.60979088 | AG81: 2.0234399 | AH81: =AG81+AF81 -> 1.413649 | AI81: =AH81-SUM(Y81:AD81) -> 1.3872146
A82: 46477 | B82: -0.083121465 | C82: -0.00081461614 | D82: -0.12763479 | E82: -0.0043145235 | F82: 0.090915175 | G82: 0.038782012 | H82: -0.13001757 | I82: -0.31098497 | J82: -1.0755917 | K82: -0.0053613345 | L82: -0.040035874 | M82: 0 | N82: 0 | O82: 0.64550134 | P82: 0 | Q82: 0.53062108 | R82: 0 | S82: -0.00027012592 | T82: 0 | U82: 0 | V82: 0 | W82: 0 | X82: 0 | Y82: 0.005197436 | Z82: -0.00077570972 | AA82: 0.0040980916 | AB82: 0.001891047 | AC82: 0.0055874768 | AD82: 0.0098132356 | AE82: -0.12631473 | AF82: -0.59302267 | AG82: 2.0234399 | AH82: =AG82+AF82 -> 1.4304172 | AI82: =AH82-SUM(Y82:AD82) -> 1.4046056
A83: 46568 | B83: -0.081838013 | C83: -0.00079209199 | D83: -0.12564216 | E83: -0.0040095726 | F83: 0.091178279 | G83: 0.035381379253562883 | H83: -0.10772224 | I83: -0.3386626 | J83: -1.0442358 | K83: -0.004996175 | L83: -0.036783402 | M83: 0 | N83: 0 | O83: 0.64253846 | P83: 0 | Q83: 0.52502482 | R83: 0 | S83: -0.00013681699 | T83: 0 | U83: 0 | V83: 0 | W83: 0 | X83: 0 | Y83: 0.005180697 | Z83: -0.00092785288 | AA83: 0.0039204263 | AB83: 0.0017126359 | AC83: 0.005495097 | AD83: 0.0097716182 | AE83: -0.12503287 | AF83: -0.57011469 | AG83: 2.0234399 | AH83: =AG83+AF83 -> 1.4533252 | AI83: =AH83-SUM(Y83:AD83) -> 1.4281726
A84: 46660 | B84: -0.080589088 | C84: -0.00076857771 | D84: -0.12368455 | E84: -0.0036995547 | F84: 0.09142023 | G84: 0.032204657 | H84: -0.086934842 | I84: -0.35922488 | J84: -1.0138214 | K84: -0.0046808969 | L84: -0.0335958 | M84: 0 | N84: 0 | O84: 0.63952736 | P84: 0 | Q84: 0.51949024 | R84: 0 | S84: -6.9296875e-05 | T84: 0 | U84: 0 | V84: 0 | W84: 0 | X84: 0 | Y84: 0.0051497627 | Z84: -0.0010907313 | AA84: 0.0037429323 | AB84: 0.0015334717 | AC84: 0.0053967696 | AD84: 0.0097401379 | AE84: -0.12376389 | AF84: -0.54253826 | AG84: 2.0234399 | AH84: =AG84+AF84 -> 1.4809016 | AI84: =AH84-SUM(Y84:AD84) -> 1.4564293
A85: 46752 | B85: -0.079373587 | C85: -0.00074457587 | D85: -0.12176211 | E85: -0.0033914198 | F85: 0.091639916 | G85: 0.029232908 | H85: -0.067571862 | I85: -0.37400898 | J85: -0.98431326 | K85: -0.0044101351 | L85: -0.030477889 | M85: 0 | N85: 0 | O85: 0.63647058 | P85: 0 | Q85: 0.514019 | R85: 0 | S85: -3.509839e-05 | T85: 0 | U85: 0 | V85: 0 | W85: 0 | X85: 0 | Y85: 0.0051063075 | Z85: -0.0012584324 | AA85: 0.0035680917 | AB85: 0.0013571545 | AC85: 0.0052939013 | AD85: 0.0097144784 | AE85: -0.12250768 | AF85: -0.51150291 | AG85: 2.0234399 | AH85: =AG85+AF85 -> 1.511937 | AI85: =AH85-SUM(Y85:AD85) -> 1.4881555
A86: 46843 | B86: -0.078190398 | C86: -0.00072043763 | D86: -0.11987482 | E86: -0.0030903643 | F86: 0.091836438 | G86: 0.026448914278676128 | H86: -0.049554765 | I86: -0.38410647 | J86: -0.9556783 | K86: -0.0041785858 | L86: -0.027434216 | M86: 0 | N86: 0 | O86: 0.63337026 | P86: 0 | Q86: 0.50861203 | R86: 0 | S86: -1.7777092e-05 | T86: 0 | U86: 0 | V86: 0 | W86: 0 | X86: 0 | Y86: 0.0050519047 | Z86: -0.001426184 | AA86: 0.0033976862 | AB86: 0.001186312 | AC86: 0.0051875835 | AD86: 0.0096908097 | AE86: -0.1212641 | AF86: -0.47799424 | AG86: 2.0234399 | AH86: =AG86+AF86 -> 1.5454456 | AI86: =AH86-SUM(Y86:AD86) -> 1.5223575
A87: 46934 | B87: -0.077038406 | C87: -0.00069641407 | D87: -0.11802256 | E87: -0.0028001776 | F87: 0.092009101 | G87: 0.023837061025799855 | H87: -0.032809505 | I87: -0.3904086 | J87: -0.92788551 | K87: -0.003981172 | L87: -0.024468925 | M87: 0 | N87: 0 | O87: 0.63022826 | P87: 0 | Q87: 0.50326973 | R87: 0 | S87: -9.0039735e-06 | T87: 0 | U87: 0 | V87: 0 | W87: 0 | X87: 0 | Y87: 0.0049880203 | Z87: -0.0015901965 | AA87: 0.0032329722 | AB87: 0.0010228346 | AC87: 0.0050787024 | AD87: 0.0096658867 | AE87: -0.12003304 | AF87: -0.44281009 | AG87: 2.0234399 | AH87: =AG87+AF87 -> 1.5806298 | AI87: =AH87-SUM(Y87:AD87) -> 1.5582316
A88: 47026 | B88: -0.07591651 | C88: -0.0006726877 | D88: -0.11620507 | E88: -0.0025235253 | F88: 0.092157399 | G88: 0.021383215 | H88: -0.01726609 | I88: -0.39364309 | J88: -0.90090571 | K88: -0.0038131456 | L88: -0.021585675 | M88: 0 | N88: 0 | O88: 0.62704618 | P88: 0 | Q88: 0.49799204 | R88: 0 | S88: -4.56045e-06 | T88: 0 | U88: 0 | V88: 0 | W88: 0 | X88: 0 | Y88: 0.0049160092 | Z88: -0.0017475227 | AA88: 0.003074803 | AB88: 0.00086803778 | AC88: 0.0049679975 | AD88: 0.0096370607 | AE88: -0.11881439 | AF88: -0.40659259 | AG88: 2.0234399 | AH88: =AG88+AF88 -> 1.6168473 | AI88: =AH88-SUM(Y88:AD88) -> 1.5951309
A89: 47118 | B89: -0.074823626 | C89: -0.00064939216 | D89: -0.11442206 | E89: -0.0022621804 | F89: 0.092280994 | G89: 0.019074603505098153 | H89: -0.002858227 | I89: -0.39440423 | J89: -0.87471141 | K89: -0.0036701474 | L89: -0.018787593 | M89: 0 | N89: 0 | O89: 0.62382548 | P89: 0 | Q89: 0.49277859 | R89: 0 | S89: -2.3098362e-06 | T89: 0 | U89: 0 | V89: 0 | W89: 0 | X89: 0 | Y89: 0.0048371149 | Z89: -0.0018959345 | AA89: 0.002923719 | AB89: 0.00072278266 | AC89: 0.0048560956 | AD89: 0.0096022462 | AE89: -0.11760801 | AF89: -0.36985573 | AG89: 2.0234399 | AH89: =AG89+AF89 -> 1.6535841 | AI89: =AH89-SUM(Y89:AD89) -> 1.6325381
A90: 47208 | B90: -0.073758698 | C90: -0.00062662501 | D90: -0.11267311 | E90: -0.0020172127 | F90: 0.092379705 | G90: 0.016899700924399852 | H90: 0.010476974726936206 | I90: -0.39317741 | J90: -0.84927668 | K90: -0.0035482343 | L90: -0.016077255 | M90: 0 | N90: 0 | O90: 0.62056745 | P90: 0 | Q90: 0.48762877 | R90: 0 | S90: -1.1699159e-06 | T90: 0 | U90: 0 | V90: 0 | W90: 0 | X90: 0 | Y90: 0.0047524707 | Z90: -0.0020338122 | AA90: 0.0027800182 | AB90: 0.00058757014 | AC90: 0.0047435325 | AD90: 0.0095598702 | AE90: -0.11641379 | AF90: -0.33300848 | AG90: 2.0234399 | AH90: =AG90+AF90 -> 1.6904314 | AI90: =AH90-SUM(Y90:AD90) -> 1.6700418
A91: 47299 | B91: -0.072720701 | C91: -0.00060445635 | D91: -0.11095779 | E91: -0.0017891424 | F91: 0.092453489 | G91: 0.014848115255228223 | H91: 0.022799252332994513 | I91: -0.3903591 | J91: -0.82457702 | K91: -0.0034438863 | L91: -0.013456687 | M91: 0 | N91: 0 | O91: 0.61727333 | P91: 0 | Q91: 0.48254177 | R91: 0 | S91: -5.9255427e-07 | T91: 0 | U91: 0 | V91: 0 | W91: 0 | X91: 0 | Y91: 0.0046631034 | Z91: -0.0021600467 | AA91: 0.0026438108 | AB91: 0.00046261692 | AC91: 0.0046307681 | AD91: 0.0095088126 | AE91: -0.11523162 | AF91: -0.29637401 | AG91: 2.0234399 | AH91: =AG91+AF91 -> 1.7270659 | AI91: =AH91-SUM(Y91:AD91) -> 1.7073168
A92: 47391 | B92: -0.071708646 | C92: -0.00058293494 | D92: -0.10927559 | E92: -0.0015780654 | F92: 0.092502427 | G92: 0.012910484228711994 | H92: 0.034165402544172885 | I92: -0.3862732 | J92: -0.80058924 | K92: -0.0033539967 | L92: -0.010927381 | M92: 0 | N92: 0 | O92: 0.61394426 | P92: 0 | Q92: 0.47751667 | R92: 0 | S92: -3.0012459e-07 | T92: 0 | U92: 0 | V92: 0 | W92: 0 | X92: 0 | Y92: 0.0045699374 | Z92: -0.0022739531 | AA92: 0.0025150642 | AB92: 0.00034791747 | AC92: 0.0045181974 | AD92: 0.0094483458 | AE92: -0.11406139 | AF92: -0.2602056 | AG92: 2.0234399 | AH92: =AG92+AF92 -> 1.7632343 | AI92: =AH92-SUM(Y92:AD92) -> 1.7441088
A93: 47483 | B93: -0.070721579 | C93: -0.00056209275 | D93: -0.10762599 | E93: -0.0013837545 | F93: 0.092526705 | G93: 0.011078376541417967 | H93: 0.044629463 | I93: -0.38118439 | J93: -0.7772913 | K93: -0.0032758538 | L93: -0.0084903241 | M93: 0 | N93: 0 | O93: 0.61058137 | P93: 0 | Q93: 0.47255244 | R93: 0 | S93: -1.5201103e-07 | T93: 0 | U93: 0 | V93: 0 | W93: 0 | X93: 0 | Y93: 0.0044738011 | Z93: -0.0023751948 | AA93: 0.0023936381 | AB93: 0.00024329497 | AC93: 0.00440616 | AD93: 0.009378076 | AE93: -0.11290297 | AF93: -0.22469963 | AG93: 2.0234399 | AH93: =AG93+AF93 -> 1.7987402 | AI93: =AH93-SUM(Y93:AD93) -> 1.7802205
A94: 47573 | B94: -0.069758585 | C94: -0.00054194841 | D94: -0.10600841 | E94: -0.0012057422 | F94: 0.092526608 | G94: 0.0093442002 | H94: 0.054242867116149895 | I94: -0.37530892 | J94: -0.75466226 | K94: -0.0032071141 | L94: -0.0061460286 | M94: 0 | N94: 0 | O94: 0.60718575 | P94: 0 | Q94: 0.46764803 | R94: 0 | S94: -7.6992546e-08 | T94: 0 | U94: 0 | V94: 0 | W94: 0 | X94: 0 | Y94: 0.0043754321 | Z94: -0.0024637173 | AA94: 0.0022793133 | AB94: 0.00014844326 | AC94: 0.0042949469 | AD94: 0.009297889 | AE94: -0.11175625 | AF94: -0.19000631 | AG94: 2.0234399 | AH94: =AG94+AF94 -> 1.8334336 | AI94: =AH94-SUM(Y94:AD94) -> 1.8155013
A95: 47664 | B95: -0.068818786 | C95: -0.00052250997 | D95: -0.10442226 | E95: -0.0010433864 | F95: 0.092502497 | G95: 0.0077011178 | H95: 0.063054585 | I95: -0.36882359 | J95: -0.7326821 | K95: -0.0031457734 | L95: -0.0038945722 | M95: 0 | N95: 0 | O95: 0.60375851 | P95: 0 | Q95: 0.46280233 | R95: 0 | S95: -3.8996184e-08 | T95: 0 | U95: 0 | V95: 0 | W95: 0 | X95: 0 | Y95: 0.0042754844 | Z95: -0.0025396917 | AA95: 0.0021718142 | AB95: 6.2961174e-05 | AC95: 0.0041848071 | AD95: 0.0092078997 | AE95: -0.11062111 | AF95: -0.15623842 | AG95: 2.0234399 | AH95: =AG95+AF95 -> 1.8672015 | AI95: =AH95-SUM(Y95:AD95) -> 1.8498382
A96: 47756 | B96: -0.067901342 | C96: -0.00050377712 | D96: -0.10286695 | E96: -0.00089592396 | F96: 0.092454804 | G96: 0.0061429689 | H96: 0.071111242 | I96: -0.36187287 | J96: -0.71133174 | K96: -0.0030901351 | L96: -0.0017356374 | M96: 0 | N96: 0 | O96: 0.60030074 | P96: 0 | Q96: 0.45801423 | R96: 0 | S96: -1.9751312e-08 | T96: 0 | U96: 0 | V96: 0 | W96: 0 | X96: 0 | Y96: 0.0041745343 | Z96: -0.0026034651 | AA96: 0.0020708275 | AB96: -1.3619339e-05 | AC96: 0.0040759525 | AD96: 0.0091084074 | AE96: -0.10949746 | AF96: -0.12347845 | AG96: 2.0234399 | AH96: =AG96+AF96 -> 1.8999614 | AI96: =AH96-SUM(Y96:AD96) -> 1.8831488
A97: 47848 | B97: -0.067005447 | C97: -0.00048574299 | D97: -0.10134185 | E97: -0.00076251253 | F97: 0.092384021 | G97: 0.0046641985 | H97: 0.078457228 | I97: -0.35457488 | J97: -0.69059284 | K97: -0.0030387782 | L97: 0.0003314474 | M97: 0 | N97: 0 | O97: 0.59681357 | P97: 0 | Q97: 0.45328264 | R97: 0 | S97: -1.0003909e-08 | T97: 0 | U97: 0 | V97: 0 | W97: 0 | X97: 0 | Y97: 0.0040730874 | Z97: -0.0026555194 | AA97: 0.0019760161 | AB97: -8.1810486e-05 | AC97: 0.0039685626 | AD97: 0.0089998562 | AE97: -0.10838517 | AF97: -0.091784465 | AG97: 2.0234399 | AH97: =AG97+AF97 -> 1.9316554 | AI97: =AH97-SUM(Y97:AD97) -> 1.9153752
A98: 47938 | B98: -0.066130333 | C98: -0.00046839563 | D98: -0.099846334 | E98: -0.0006422644 | F98: 0.092290684 | G98: 0.0032597929 | H98: 0.085134794 | I98: -0.34702618 | J98: -0.67044783 | K98: -0.0029905266 | L98: 0.0023076677 | M98: 0 | N98: 0 | O98: 0.59329813 | P98: 0 | Q98: 0.44860647 | R98: 0 | S98: -5.0668802e-09 | T98: 0 | U98: 0 | V98: 0 | W98: 0 | X98: 0 | Y98: 0.0039715843 | Z98: -0.0026964356 | AA98: 0.0018870311 | AB98: -0.00014215029 | AC98: 0.0038627884 | AD98: 0.0088828001 | AE98: -0.10728413 | AF98: -0.061194835 | AG98: 2.0234399 | AH98: =AG98+AF98 -> 1.962245 | AI98: =AH98-SUM(Y98:AD98) -> 1.9464794
A99: 48029 | B99: -0.065275262 | C99: -0.00045171922 | D99: -0.09837978 | E99: -0.00053427252 | F99: 0.09217537 | G99: 0.0019252205 | H99: 0.09118415 | I99: -0.33930566 | J99: -0.65087978 | K99: -0.0029444195 | L99: 0.0041942838 | M99: 0 | N99: 0 | O99: 0.58975558 | P99: 0 | Q99: 0.44398466 | R99: 0 | S99: -2.5663471e-09 | T99: 0 | U99: 0 | V99: 0 | W99: 0 | X99: 0 | Y99: 0.0038704069 | Z99: -0.0027268646 | AA99: 0.0018035196 | AB99: -0.00019518803 | AC99: 0.0037587557 | AD99: 0.008757873 | AE99: -0.10619424 | AF99: -0.031732147 | AG99: 2.0234399 | AH99: =AG99+AF99 -> 1.9917077 | AI99: =AH99-SUM(Y99:AD99) -> 1.9764392
A100: 48121 | B100: -0.064439531 | C100: -0.0004356951 | D100: -0.096941557 | E100: -0.00043763075 | F100: 0.092038689 | G100: 0.00065637933 | H100: 0.096643541 | I100: -0.33147779 | J100: -0.63187238 | K100: -0.0028996833 | L100: 0.0059927932 | M100: 0 | N100: 0 | O100: 0.58618709 | P100: 0 | Q100: 0.43941616 | R100: 0 | S100: -1.2998491e-09 | T100: 0 | U100: 0 | V100: 0 | W100: 0 | X100: 0 | Y100: 0.0037698843 | Z100: -0.0027475025 | AA100: 0.0017251322 | AB100: -0.00024147276 | AC100: 0.003656568 | AD100: 0.0086257629 | AE100: -0.10511538 | AF100: -0.0034063631 | AG100: 2.0234399 | AH100: =AG100+AF100 -> 2.0200335 | AI100: =AH100-SUM(Y100:AD100) -> 2.0052451
...

Sheet US_policy_rarte_vs_shadow_rate
A1: date | B1: g_sh | C1: b_liqtil_sh | D1: b_liqp_sh | E1: b_safetil_sh | F1: b_safep_sh | G1: mu_sh | H1: z_sh | I1: lambda_f_sh | J1: lambda_w_sh | K1: rm_sh | L1: sigma_omega_sh | M1: mu_e_sh | N1: gamma_sh | O1: pi_star_sh | P1: lr_sh | Q1: zp_sh | R1: tfp_sh | S1: gdpdef_sh | T1: corepce_sh | U1: gdp_sh | V1: gdi_sh | W1: BBB_sh | X1: AAA_sh | Y1: rm_shl1 | Z1: rm_shl2 | AA1: rm_shl3 | AB1: rm_shl4 | AC1: rm_shl5 | AD1: rm_shl6 | AE1: dettrend | AF1: detrendedMean | AG1: Trend | AH1: Trend+Mean | AI1: Obs_nominal_Rate | AJ1: Policy rate | AK1: Shadow Rate
A2: 39172 | B2: -0.11401048 | C2: 0.20535127743701143 | D2: -0.30209741 | E2: 0.8474755039376002 | F2: 0.9007043203677197 | G2: 0.041937669 | H2: 0.8011986850604833 | I2: 0.5101117021091058 | J2: -1.027226 | K2: -1.0879287 | L2: 0.1797763975690379 | M2: 0 | N2: 0 | O2: 0.5606850469492229 | P2: 0 | Q2: 0.069366088 | R2: 0 | S2: 0 | T2: 0 | U2: 0 | V2: 0 | W2: 0 | X2: 0 | Y2: 0 | Z2: 0 | AA2: 0 | AB2: 0 | AC2: 0 | AD2: 0 | AE2: -0.23818946 | AF2: 1.3471547 | AG2: 3.9028453 | AH2: =AF2+AG2 -> 5.25 | AI2: 1.3125 | AJ2: =+AI2*4 -> 5.25 | AK2: =AJ2-SUM(Y2:AD2,K2) -> 6.3379287
A3: 39263 | B3: -0.0829638 | C3: 0.19793159921395656 | D3: -0.30632052 | E3: 0.84832418 | F3: 0.9323641587383997 | G3: 0.051456624622572535 | H3: 0.5040473915239414 | I3: 0.4510784401403198 | J3: -1.1432998 | K3: -0.57113226 | L3: 0.12953399988079267 | M3: 0 | N3: 0 | O3: 0.5699949085979459 | P3: 0 | Q3: 0.0021416526 | R3: 0 | S3: 0 | T3: 0 | U3: 0 | V3: 0 | W3: 0 | X3: 0 | Y3: 0 | Z3: 0 | AA3: 0 | AB3: 0 | AC3: 0 | AD3: 0 | AE3: -0.23600196 | AF3: 1.3471547 | AG3: 3.9028453 | AH3: =AF3+AG3 -> 5.25 | AI3: 1.3125 | AJ3: =+AI3*4 -> 5.25 | AK3: =AJ3-SUM(Y3:AD3,K3) -> 5.8211323
A4: 39355 | B4: -0.15392337 | C4: 0.16990305239245632 | D4: -0.44946874 | E4: 0.9398166029693221 | F4: 0.9537482315782074 | G4: 0.063708809 | H4: 0.6174156262953905 | I4: 0.42669807 | J4: -1.2125307 | K4: -0.64943507 | L4: 0.11571594197458508 | M4: 0 | N4: 0 | O4: 0.6114174843760871 | P4: 0 | Q4: -0.032081448 | R4: 0 | S4: 0 | T4: 0 | U4: 0 | V4: 0 | W4: 0 | X4: 0 | Y4: 0 | Z4: 0 | AA4: 0 | AB4: 0 | AC4: 0 | AD4: 0 | AE4: -0.23382987 | AF4: 1.1671547 | AG4: 3.9028453 | AH4: =AF4+AG4 -> 5.07 | AI4: 1.2675 | AJ4: =+AI4*4 -> 5.07 | AK4: =AJ4-SUM(Y4:AD4,K4) -> 5.7194351
A5: 39447 | B5: -0.15363652 | C5: 0.17558103142419937 | D5: -0.630747 | E5: 0.96697803 | F5: 0.9436403714641093 | G5: 0.062024370826520965 | H5: 0.5934619846707068 | I5: 0.45002707495790817 | J5: -1.1937889 | K5: -1.0906308 | L5: 0.088389876 | M5: 0 | N5: 0 | O5: 0.6447922692353181 | P5: 0 | Q5: -0.027263892 | R5: 0 | S5: 0 | T5: 0 | U5: 0 | V5: 0 | W5: 0 | X5: 0 | Y5: 0 | Z5: 0 | AA5: 0 | AB5: 0 | AC5: 0 | AD5: 0 | AE5: -0.23167323 | AF5: 0.59715465 | AG5: 3.9028453 | AH5: =AF5+AG5 -> 4.5 | AI5: 1.125 | AJ5: =+AI5*4 -> 4.5 | AK5: =AJ5-SUM(Y5:AD5,K5) -> 5.5906308
A6: 39538 | B6: -0.17654154 | C6: 0.014279886243278389 | D6: -0.84968192 | E6: 0.45145767650222646 | F6: 0.8949198166577434 | G6: 0.049151621 | H6: 0.6542247326726934 | I6: 0.36489 | J6: -1.1859989 | K6: -1.3356229 | L6: 0.025228523501136114 | M6: 0 | N6: 0 | O6: 0.6749752142591242 | P6: 0 | Q6: -0.074595448 | R6: 0 | S6: 0 | T6: 0 | U6: 0 | V6: 0 | W6: 0 | X6: 0 | Y6: 0 | Z6: 0 | AA6: 0 | AB6: 0 | AC6: 0 | AD6: 0 | AE6: -0.22953208 | AF6: -0.72284535 | AG6: 3.9028453 | AH6: =AF6+AG6 -> 3.18 | AI6: 0.795 | AJ6: =+AI6*4 -> 3.18 | AK6: =AJ6-SUM(Y6:AD6,K6) -> 4.5156229
A7: 39629 | B7: -0.20191707 | C7: -0.072830785 | D7: -0.92562239 | E7: 0.024837465151856142 | F7: 0.8978124824696581 | G7: 0.039769291 | H7: 0.5553545979257674 | I7: 0.28096769922374754 | J7: -1.2640069 | K7: -1.497997 | L7: -0.053407566 | M7: 0 | N7: 0 | O7: 0.7051008782934766 | P7: 0 | Q7: -0.083499592 | R7: 0 | S7: 0 | T7: 0 | U7: 0 | V7: 0 | W7: 0 | X7: 0 | Y7: 0 | Z7: 0 | AA7: 0 | AB7: 0 | AC7: 0 | AD7: 0 | AE7: -0.22740646 | AF7: -1.8228453 | AG7: 3.9028453 | AH7: =AF7+AG7 -> 2.08 | AI7: 0.52 | AJ7: =+AI7*4 -> 2.08 | AK7: =AJ7-SUM(Y7:AD7,K7) -> 3.577997
A8: 39721 | B8: -0.089411128 | C8: -0.30391018 | D8: -1.0525338 | E8: -0.62106526 | F8: 0.8751808533619965 | G8: 0.032332229 | H8: 0.5094032691653232 | I8: 0.3107526310373403 | J8: -1.2818167 | K8: -0.60798148 | L8: -0.12702577 | M8: 0 | N8: 0 | O8: 0.70140354 | P8: 0 | Q8: -0.082877244 | R8: 0 | S8: 0 | T8: 0 | U8: 0 | V8: 0 | W8: 0 | X8: 0 | Y8: 0 | Z8: 0 | AA8: 0 | AB8: 0 | AC8: 0 | AD8: 0 | AE8: -0.22529638 | AF8: -1.9628453 | AG8: 3.9028453 | AH8: =AF8+AG8 -> 1.94 | AI8: 0.485 | AJ8: =+AI8*4 -> 1.94 | AK8: =AJ8-SUM(Y8:AD8,K8) -> 2.5479815
A9: 39813 | B9: 0.13485818289924795 | C9: -0.79217761 | D9: -1.6043944 | E9: -1.5547182 | F9: 0.6174571300163227 | G9: 0.036130617 | H9: 1.080846774222828 | I9: -0.041293101 | J9: -1.2454774 | K9: 0.12813139056669148 | L9: -0.1382118 | M9: 0 | N9: 0 | O9: 0.7520407299389487 | P9: 0 | Q9: -0.13766645 | R9: 0 | S9: 0 | T9: 0 | U9: 0 | V9: 0 | W9: 0 | X9: 0 | Y9: -0.25638525 | Z9: -0.12030565 | AA9: -0.021104289 | AB9: -0.0036357936 | AC9: -0.0015368701 | AD9: -0.0022014941 | AE9: -0.22320187 | AF9: -3.3928453 | AG9: 3.9028453 | AH9: =AF9+AG9 -> 0.51 | AI9: 0.1275 | AJ9: =+AI9*4 -> 0.51 | AK9: =AJ9-SUM(Y9:AD9,K9) -> 0.91516934
A10: 39903 | B10: 0.16168339330569836 | C10: -0.87584388 | D10: -1.6876661 | E10: -1.9921387 | F10: 0.5345737629715667 | G10: 0.07776 | H10: 0.8672465007855784 | I10: -0.18521718 | J10: -1.5674078 | K10: 0.9609186217732131 | L10: -0.21059841 | M10: 0 | N10: 0 | O10: 0.8305851755010393 | P10: 0 | Q10: -0.10143052 | R10: 0 | S10: 0 | T10: 0 | U10: 0 | V10: 0 | W10: 0 | X10: 0 | Y10: 0.11106691870480037 | Z10: -0.29123047 | AA10: -0.089995246 | AB10: -0.010718854 | AC10: -0.013823975 | AD10: -0.019485595 | AE10: -0.22112295 | AF10: -3.7228453 | AG10: 3.9028453 | AH10: =AF10+AG10 -> 0.18 | AI10: 0.045 | AJ10: =+AI10*4 -> 0.18 | AK10: =AJ10-SUM(Y10:AD10,K10) -> 0.60525414
A11: 39994 | B11: 0.14543892437162054 | C11: -0.75459901 | D11: -1.5585879 | E11: -2.0853044 | F11: 0.5017650938776251 | G11: 0.062438846895756454 | H11: 0.35467143244626853 | I11: -0.18173936 | J11: -1.3758204 | K11: 1.0274071923132058 | L11: -0.39438341 | M11: 0 | N11: 0 | O11: 0.79029194 | P11: 0 | Q11: -0.013172518 | R11: 0 | S11: 0 | T11: 0 | U11: 0 | V11: 0 | W11: 0 | X11: 0 | Y11: 0.33599818976034695 | Z11: -0.036183899 | AA11: -0.19193871 | AB11: -0.047698813 | AC11: -0.023130777 | AD11: -0.059238196 | AE11: -0.21905963 | AF11: -3.7228453 | AG11: 3.9028453 | AH11: =AF11+AG11 -> 0.18 | AI11: 0.045 | AJ11: =+AI11*4 -> 0.18 | AK11: =AJ11-SUM(Y11:AD11,K11) -> 0.53819039
A12: 40086 | B12: -0.062353511 | C12: -0.27312012 | D12: -1.3292818 | E12: -1.9060385 | F12: 0.4464271521298693 | G12: 0.012925012156559671 | H12: 0.080859986 | I12: -0.15167571 | J12: -1.3163403 | K12: 0.56616084 | L12: -0.54183291 | M12: 0 | N12: 0 | O12: 0.61082403 | P12: 0 | Q12: 0.0016531346 | R12: 0 | S12: 0 | T12: 0 | U12: 0 | V12: 0 | W12: 0 | X12: 0 | Y12: 0.41404851096503054 | Z12: 0.26792165685900027 | AA12: -0.14115197 | AB12: -0.068417176 | AC12: -0.027625262 | AD12: -0.11881657 | AE12: -0.21701192 | AF12: -3.7528453 | AG12: 3.9028453 | AH12: =AF12+AG12 -> 0.15 | AI12: 0.0375 | AJ12: =+AI12*4 -> 0.15 | AK12: =AJ12-SUM(Y12:AD12,K12) -> -0.060149856
A13: 40178 | B13: 0.00050746881 | C13: -0.19682351 | D13: -1.1508529 | E13: -1.8816935 | F13: 0.38547560647494883 | G13: -0.095120943 | H13: -0.39911134 | I13: 0.063178418 | J13: -1.2794913 | K13: 1.0641138495409654 | L13: -0.57081218 | M13: 0 | N13: 0 | O13: 0.41206863573209046 | P13: 0 | Q13: 0.055765932 | R13: 0 | S13: 0 | T13: 0 | U13: 0 | V13: 0 | W13: 0 | X13: 0 | Y13: 0.019309171349784236 | Z13: 0.30395990378418153 | AA13: 0.017642377 | AB13: -0.071919374 | AC13: -0.037899564 | AD13: -0.20616227 | AE13: -0.2149798 | AF13: -3.7828453 | AG13: 3.9028453 | AH13: =AF13+AG13 -> 0.12 | AI13: 0.03 | AJ13: =+AI13*4 -> 0.12 | AK13: =AJ13-SUM(Y13:AD13,K13) -> 0.41833883
A14: 40268 | B14: -0.028939895 | C14: -0.051269978 | D14: -0.98753204 | E14: -1.7680483 | F14: 0.3069539352232068 | G14: -0.19954777 | H14: -0.34223789 | I14: 0.10476432717022577 | J14: -1.4203065 | K14: 0.9586729691184699 | L14: -0.47232637 | M14: 0 | N14: 0 | O14: 0.3294719286581883 | P14: 0 | Q14: -0.01284846 | R14: 0 | S14: 0 | T14: 0 | U14: 0 | V14: 0 | W14: 0 | X14: 0 | Y14: 0.074458846 | Z14: 0.1109324157661161 | AA14: 0.2363392764919489 | AB14: -0.051590742 | AC14: -0.021705277 | AD14: -0.32512256 | AE14: -0.21296329 | AF14: -3.7728453 | AG14: 3.9028453 | AH14: =AF14+AG14 -> 0.13 | AI14: 0.0325 | AJ14: =+AI14*4 -> 0.13 | AK14: =AJ14-SUM(Y14:AD14,K14) -> 0.45395973
A15: 40359 | B15: -0.043014321 | C15: 0.2680138781672768 | D15: -1.0350654 | E15: -1.409629 | F15: 0.06327667 | G15: -0.32939735 | H15: -0.20240447 | I15: 0.084143029 | J15: -1.3895245 | K15: 0.41681747598462215 | L15: -0.41788475 | M15: 0 | N15: 0 | O15: 0.19418336815571774 | P15: 0 | Q15: -0.084192942 | R15: 0 | S15: 0 | T15: 0 | U15: 0 | V15: 0 | W15: 0 | X15: 0 | Y15: 0.15617288348936234 | Z15: 0.20153995635887656 | AA15: 0.15125699723451355 | AB15: 0.18136977396581624 | AC15: 0.12289009961126868 | AD15: -0.43043437 | AE15: -0.21096238 | AF15: -3.7128453 | AG15: 3.9028453 | AH15: =AF15+AG15 -> 0.19 | AI15: 0.0475 | AJ15: =+AI15*4 -> 0.19 | AK15: =AJ15-SUM(Y15:AD15,K15) -> 0.62043437
A16: 40451 | B16: 0.016901071683739874 | C16: 0.2541868207592806 | D16: -1.106641 | E16: -1.0555547 | F16: -0.083681175 | G16: -0.43696366 | H16: -0.35053065 | I16: 0.016052342955123602 | J16: -1.3933836 | K16: 0.5557148347657815 | L16: -0.28315857 | M16: 0 | N16: 0 | O16: 0.14697229123179903 | P16: 0 | Q16: -0.015194587 | R16: 0 | S16: 0 | T16: 0 | U16: 0 | V16: 0 | W16: 0 | X16: 0 | Y16: -0.19684477 | Z16: 0.095743905 | AA16: 0.3476213396711247 | AB16: 0.18480564608277644 | AC16: 0.18580721503318795 | AD16: -0.38572109 | AE16: -0.20897704 | AF16: -3.7128453 | AG16: 3.9028453 | AH16: =AF16+AG16 -> 0.19 | AI16: 0.0475 | AJ16: =+AI16*4 -> 0.19 | AK16: =AJ16-SUM(Y16:AD16,K16) -> 0.67682195
A17: 40543 | B17: -0.1620586 | C17: 0.15028008198689616 | D17: -1.1197271 | E17: -0.75421026 | F17: -0.14149381 | G17: -0.54061919 | H17: -0.38757123 | I17: 0.13392194555484507 | J17: -1.4305545 | K17: 0.6582169831294579 | L17: -0.25198257 | M17: 0 | N17: 0 | O17: 0.097634949 | P17: 0 | Q17: 0.044257497732707644 | R17: 0 | S17: 0 | T17: 0 | U17: 0 | V17: 0 | W17: 0 | X17: 0 | Y17: -0.075179984 | Z17: -0.15091048 | AA17: 0.23802469094638273 | AB17: 0.22835070983181002 | AC17: 0.18860734853740738 | AD17: -0.23082451 | AE17: -0.20700727 | AF17: -3.7128453 | AG17: 3.9028453 | AH17: =AF17+AG17 -> 0.19 | AI17: 0.0475 | AJ17: =+AI17*4 -> 0.19 | AK17: =AJ17-SUM(Y17:AD17,K17) -> 0.64691497
A18: 40633 | B18: -0.27063806 | C18: 0.094345706 | D18: -0.98952181 | E18: -0.77790685 | F18: -0.1677141 | G18: -0.6096063 | H18: -0.12465079 | I18: 0.20230750580218976 | J18: -1.3055222 | K18: 0.4296022713068277 | L18: -0.17072292 | M18: 0 | N18: 0 | O18: 0.063130256 | P18: 0 | Q18: 0.11609176745606571 | R18: 0 | S18: 0 | T18: 0 | U18: 0 | V18: 0 | W18: 0 | X18: 0 | Y18: -0.074197511 | Z18: -0.11277081 | AA18: -0.15023663 | AB18: 0.14746394843836594 | AC18: 0.2689223849342874 | AD18: -0.11616813 | AE18: -0.20505304 | AF18: -3.7528453 | AG18: 3.9028453 | AH18: =AF18+AG18 -> 0.15 | AI18: 0.0375 | AJ18: =+AI18*4 -> 0.15 | AK18: =AJ18-SUM(Y18:AD18,K18) -> 0.60337308
A19: 40724 | B19: -0.24716093 | C19: 0.16802888810658898 | D19: -1.0503695 | E19: -0.61748199 | F19: -0.26053262 | G19: -0.68365801 | H19: -0.21057138 | I19: 0.36788454964591555 | J19: -1.441784 | K19: 0.40644857374007004 | L19: -0.1601851 | M19: 0 | N19: 0 | O19: 0.025550735911271796 | P19: 0 | Q19: 0.014414826414430662 | R19: 0 | S19: 0 | T19: 0 | U19: 0 | V19: 0 | W19: 0 | X19: 0 | Y19: 0.096171497 | Z19: -0.028304958 | AA19: -0.12098978 | AB19: -0.1639029 | AC19: 0.25420528307091544 | AD19: 0.042505794808235235 | AE19: -0.20311433 | AF19: -3.8128453 | AG19: 3.9028453 | AH19: =AF19+AG19 -> 0.09 | AI19: 0.0225 | AJ19: =+AI19*4 -> 0.09 | AK19: =AJ19-SUM(Y19:AD19,K19) -> 0.30702613
A20: 40816 | B20: -0.34942558 | C20: 0.23707243517618334 | D20: -1.2321974 | E20: -0.3715986 | F20: -0.44075242 | G20: -0.73417221 | H20: -0.1337518 | I20: 0.4114511474446587 | J20: -1.4544735 | K20: 0.4321375118140882 | L20: -0.11728644 | M20: 0 | N20: 0 | O20: -0.0299582 | P20: 0 | Q20: -0.041218417 | R20: 0 | S20: 0 | T20: 0 | U20: 0 | V20: 0 | W20: 0 | X20: 0 | Y20: -0.02327198 | Z20: 0.1528020476509143 | AA20: -0.00030324919 | AB20: -0.095360741 | AC20: -0.069070423 | AD20: 0.2377236105788645 | AE20: -0.20119112 | AF20: -3.8228453 | AG20: 3.9028453 | AH20: =AF20+AG20 -> 0.08 | AI20: 0.02 | AJ20: =+AI20*4 -> 0.08 | AK20: =AJ20-SUM(Y20:AD20,K20) -> 0.26800639
A21: 40908 | B21: -0.24269043 | C21: 0.1602124383039225 | D21: -1.3205626 | E21: -0.0092503343 | F21: -0.50942716 | G21: -0.7454993 | H21: -0.20948523 | I21: 0.36115993650229394 | J21: -1.6692977 | K21: 0.4189443220069519 | L21: -0.0091482652 | M21: 0 | N21: 0 | O21: 0.061097609 | P21: 0 | Q21: -0.047210866 | R21: 0 | S21: 0 | T21: 0 | U21: 0 | V21: 0 | W21: 0 | X21: 0 | Y21: -0.15258272 | Z21: 0.015223178687986033 | AA21: 0.22487413112576166 | AB21: -0.0010225508 | AC21: -0.15163881 | AD21: 0.19274239992113856 | AE21: -0.19928337 | AF21: -3.8328453 | AG21: 3.9028453 | AH21: =AF21+AG21 -> 0.07 | AI21: 0.0175 | AJ21: =+AI21*4 -> 0.07 | AK21: =AJ21-SUM(Y21:AD21,K21) -> 0.37524408
A22: 40999 | B22: -0.16910534 | C22: 0.22506235529062285 | D22: -1.344846 | E22: 0.1792879725109558 | F22: -0.5865714 | G22: -0.73264701 | H22: -0.46548189 | I22: 0.4887724525954793 | J22: -1.5432142 | K22: 0.057267967 | L22: 0.042421176374950825 | M22: 0 | N22: 0 | O22: 0.033535609 | P22: 0 | Q22: 0.1088889663087036 | R22: 0 | S22: 0 | T22: 0 | U22: 0 | V22: 0 | W22: 0 | X22: 0 | Y22: -0.042002918 | Z22: -0.13203093 | AA22: -0.0063894408 | AB22: 0.2079009729761101 | AC22: 0.011870103846476743 | AD22: 0.06182727 | AE22: -0.19739104 | AF22: -3.8028453 | AG22: 3.9028453 | AH22: =AF22+AG22 -> 0.1 | AI22: 0.025 | AJ22: =+AI22*4 -> 0.1 | AK22: =AJ22-SUM(Y22:AD22,K22) -> 0.16132806
A23: 41090 | B23: -0.18557062 | C23: 0.10978073676458493 | D23: -1.4232477 | E23: 0.24722463149778942 | F23: -0.63320812 | G23: -0.70750079 | H23: -0.41967811 | I23: 0.4434595438793053 | J23: -1.5479904 | K23: 0.40477400446689327 | L23: 0.087517828 | M23: 0 | N23: 0 | O23: 0.057049156 | P23: 0 | Q23: 0.10504945234232274 | R23: 0 | S23: 0 | T23: 0 | U23: 0 | V23: 0 | W23: 0 | X23: 0 | Y23: -0.16881982 | Z23: -0.033538437 | AA23: -0.20679686 | AB23: 0.15074215963558052 | AC23: 0.095876324 | AD23: 0.067545766 | AE23: -0.1955141 | AF23: -3.7528453 | AG23: 3.9028453 | AH23: =AF23+AG23 -> 0.15 | AI23: 0.0375 | AJ23: =+AI23*4 -> 0.15 | AK23: =AJ23-SUM(Y23:AD23,K23) -> 0.39573303
A24: 41182 | B24: -0.22076694 | C24: 0.07249473 | D24: -1.392063 | E24: 0.0070781531 | F24: -0.6913678 | G24: -0.67978508 | H24: -0.09168242 | I24: 0.3860003755941546 | J24: -1.616548 | K24: 0.37544889457622665 | L24: 0.12942378288681888 | M24: 0 | N24: 0 | O24: 0.046221746813399106 | P24: 0 | Q24: 0.15196761141900358 | R24: 0 | S24: 0 | T24: 0 | U24: 0 | V24: 0 | W24: 0 | X24: 0 | Y24: -0.041278441 | Z24: -0.04859971 | AA24: -0.15517745 | AB24: 0.036434274572561806 | AC24: -0.10131809 | AD24: 0.2643244493002306 | AE24: -0.1936525 | AF24: -3.7628453 | AG24: 3.9028453 | AH24: =AF24+AG24 -> 0.14 | AI24: 0.035 | AJ24: =+AI24*4 -> 0.14 | AK24: =AJ24-SUM(Y24:AD24,K24) -> 0.48637369
A25: 41274 | B25: -0.15751055 | C25: 0.1873098019542356 | D25: -1.3843874 | E25: -0.018502967 | F25: -0.72998311 | G25: -0.66070984 | H25: -0.20924631 | I25: 0.3331431366550546 | J25: -1.4149761 | K25: 0.030512933963075528 | L25: 0.13414566129868793 | M25: 0 | N25: 0 | O25: -0.022322654 | P25: 0 | Q25: 0.22613608539614416 | R25: 0 | S25: 0 | T25: 0 | U25: 0 | V25: 0 | W25: 0 | X25: 0 | Y25: 0.086885011 | Z25: -0.057212726 | AA25: -0.042665624 | AB25: 0.037713927974702084 | AC25: -0.26413871 | AD25: 0.3747701965084595 | AE25: -0.19180621 | AF25: -3.7428453 | AG25: 3.9028453 | AH25: =AF25+AG25 -> 0.16 | AI25: 0.04 | AJ25: =+AI25*4 -> 0.16 | AK25: =AJ25-SUM(Y25:AD25,K25) -> 0.43713205
A26: 41364 | B26: -0.24090052 | C26: 0.20249719846945052 | D26: -1.3803909 | E26: 0.074809368 | F26: -0.7065862 | G26: -0.65191558 | H26: -0.43387198 | I26: 0.34538088639708964 | J26: -1.5809726 | K26: 0.3859933210080404 | L26: 0.15212612463328296 | M26: 0 | N26: 0 | O26: -0.0085838024 | P26: 0 | Q26: 0.18236289122052368 | R26: 0 | S26: 0 | T26: 0 | U26: 0 | V26: 0 | W26: 0 | X26: 0 | Y26: -0.019373756 | Z26: -0.017834223 | AA26: 0.017600760480327174 | AB26: -0.021611307 | AC26: -0.12341052 | AD26: 0.2518107456851162 | AE26: -0.18997518 | AF26: -3.7628453 | AG26: 3.9028453 | AH26: =AF26+AG26 -> 0.14 | AI26: 0.035 | AJ26: =+AI26*4 -> 0.14 | AK26: =AJ26-SUM(Y26:AD26,K26) -> 0.32222981
A27: 41455 | B27: -0.18111057 | C27: 0.070223703 | D27: -1.363647 | E27: 0.038553052198080945 | F27: -0.63962603 | G27: -0.63456126 | H27: -0.49542019 | I27: 0.27205166011508797 | J27: -1.5708594 | K27: 0.65349478 | L27: 0.1853224564345408 | M27: 0 | N27: 0 | O27: 0.031999706016331037 | P27: 0 | Q27: 0.1872261143962611 | R27: 0 | S27: 0 | T27: 0 | U27: 0 | V27: 0 | W27: 0 | X27: 0 | Y27: -0.11327876 | Z27: -0.12670078 | AA27: 0.0065218777 | AB27: -0.082856607 | AC27: 0.021653737697315614 | AD27: 0.14632748707311832 | AE27: -0.18815935 | AF27: -3.7828453 | AG27: 3.9028453 | AH27: =AF27+AG27 -> 0.12 | AI27: 0.03 | AJ27: =+AI27*4 -> 0.12 | AK27: =AJ27-SUM(Y27:AD27,K27) -> -0.21718051
A28: 41547 | B28: -0.20164687 | C28: 0.10899360854498276 | D28: -1.3244699 | E28: -0.13984856 | F28: -0.6361726 | G28: -0.60110261 | H28: -0.65147432 | I28: 0.34975169497612757 | J28: -1.664758 | K28: 0.7437810197860703 | L28: 0.21421606188329279 | M28: 0 | N28: 0 | O28: 0.026090130768649928 | P28: 0 | Q28: 0.17558289907846508 | R28: 0 | S28: 0 | T28: 0 | U28: 0 | V28: 0 | W28: 0 | X28: 0 | Y28: 0.031316576 | Z28: -0.10666546 | AA28: -0.010478947 | AB28: -0.092252983 | AC28: 0.081267082 | AD28: 0.071384537 | AE28: -0.18635868 | AF28: -3.8128453 | AG28: 3.9028453 | AH28: =AF28+AG28 -> 0.09 | AI28: 0.0225 | AJ28: =+AI28*4 -> 0.09 | AK28: =AJ28-SUM(Y28:AD28,K28) -> 0.11542919
A29: 41639 | B29: -0.27405359 | C29: 0.1033502934152323 | D29: -1.2946951 | E29: -0.22864195 | F29: -0.59746992 | G29: -0.56100248 | H29: -0.89689674 | I29: 0.4290126286905276 | J29: -1.6775779 | K29: 0.81947015 | L29: 0.2683023297874632 | M29: 0 | N29: 0 | O29: 0.057717376197604864 | P29: 0 | Q29: 0.16627733433851655 | R29: 0 | S29: 0 | T29: 0 | U29: 0 | V29: 0 | W29: 0 | X29: 0 | Y29: -0.056341221 | Z29: 0.069029569 | AA29: 0.0771139 | AB29: -0.1202317 | AC29: -0.039077463 | AD29: 0.12744218699022367 | AE29: -0.18457311 | AF29: -3.8128453 | AG29: 3.9028453 | AH29: =AF29+AG29 -> 0.09 | AI29: 0.0225 | AJ29: =+AI29*4 -> 0.09 | AK29: =AJ29-SUM(Y29:AD29,K29) -> -0.65996323
A30: 41729 | B30: -0.34835023 | C30: 0.082448572 | D30: -1.2527573 | E30: -0.38134708 | F30: -0.5872393 | G30: -0.52521241 | H30: -0.66672452 | I30: 0.34664914607571284 | J30: -1.553897 | K30: 0.7008326600911763 | L30: 0.3119476139191053 | M30: 0 | N30: 0 | O30: 0.047396949323329905 | P30: 0 | Q30: 0.19600674266671236 | R30: 0 | S30: 0 | T30: 0 | U30: 0 | V30: 0 | W30: 0 | X30: 0 | Y30: -0.1449513 | Z30: 0.053976861469534704 | AA30: 0.18604479117843378 | AB30: -0.090322369 | AC30: -0.078983109 | AD30: 0.054438463800556544 | AE30: -0.18280258 | AF30: -3.8328453 | AG30: 3.9028453 | AH30: =AF30+AG30 -> 0.07 | AI30: 0.0175 | AJ30: =+AI30*4 -> 0.07 | AK30: =AJ30-SUM(Y30:AD30,K30) -> 0.38425678
A31: 41820 | B31: -0.25303453 | C31: 0.12736968232785295 | D31: -1.2452022 | E31: -0.20936656 | F31: -0.5656513 | G31: -0.49017576 | H31: -0.77728236 | I31: 0.42309825497239495 | J31: -1.6502355 | K31: 0.40110493880971165 | L31: 0.3530006599081701 | M31: 0 | N31: 0 | O31: 0.068807917 | P31: 0 | Q31: 0.18998436718756262 | R31: 0 | S31: 0 | T31: 0 | U31: 0 | V31: 0 | W31: 0 | X31: 0 | Y31: -0.030619262 | Z31: 0.0051268591 | AA31: 0.089009078 | AB31: -0.044231316 | AC31: -0.070423707 | AD31: 0.046922402 | AE31: -0.18104703 | AF31: -3.8128453 | AG31: 3.9028453 | AH31: =AF31+AG31 -> 0.09 | AI31: 0.0225 | AJ31: =+AI31*4 -> 0.09 | AK31: =AJ31-SUM(Y31:AD31,K31) -> 0.094215946
A32: 41912 | B32: -0.25716512 | C32: 0.11787980003147759 | D32: -1.2805684 | E32: -0.037292209 | F32: -0.54293002 | G32: -0.44696582 | H32: -0.96110619 | I32: 0.4441317062202598 | J32: -1.6663959 | K32: 0.5019279086210908 | L32: 0.40229250936681904 | M32: 0 | N32: 0 | O32: 0.10822613585611972 | P32: 0 | Q32: 0.19072816605250079 | R32: 0 | S32: 0 | T32: 0 | U32: 0 | V32: 0 | W32: 0 | X32: 0 | Y32: -0.10049578 | Z32: 0.00087673539 | AA32: -0.025282228 | AB32: -0.079712405 | AC32: 0.047180929 | AD32: -0.048868771 | AE32: -0.1793064 | AF32: -3.8128453 | AG32: 3.9028453 | AH32: =AF32+AG32 -> 0.09 | AI32: 0.0225 | AJ32: =+AI32*4 -> 0.09 | AK32: =AJ32-SUM(Y32:AD32,K32) -> 0.29630151
A33: 42004 | B33: -0.27499829 | C33: 0.14784647865953365 | D33: -1.3744658 | E33: 0.19237926594776922 | F33: -0.5630971 | G33: -0.39705354 | H33: -0.82413538 | I33: 0.33220209027289727 | J33: -1.597999 | K33: 0.2597639293778806 | L33: 0.4567222393302373 | M33: 0 | N33: 0 | O33: 0.16281697207586351 | P33: 0 | Q33: 0.20218796792085328 | R33: 0 | S33: 0 | T33: 0 | U33: 0 | V33: 0 | W33: 0 | X33: 0 | Y33: -0.10048406 | Z33: -0.0020780271 | AA33: -0.13480723 | AB33: 0.013862685336897503 | AC33: -0.084982503 | AD33: -0.038945426 | AE33: -0.17758064 | AF33: -3.8028453 | AG33: 3.9028453 | AH33: =AF33+AG33 -> 0.1 | AI33: 0.025 | AJ33: =+AI33*4 -> 0.1 | AK33: =AJ33-SUM(Y33:AD33,K33) -> 0.46129724
A34: 42094 | B34: -0.22960694 | C34: 0.095675006 | D34: -1.4731926 | E34: 0.1784106776734135 | F34: -0.59376898 | G34: -0.3442837 | H34: -0.93346481 | I34: 0.17320357884960194 | J34: -1.4764244 | K34: 0.5868652268695016 | L34: 0.45503274406274585 | M34: 0 | N34: 0 | O34: 0.17015662336766385 | P34: 0 | Q34: 0.22703007677560272 | R34: 0 | S34: 0 | T34: 0 | U34: 0 | V34: 0 | W34: 0 | X34: 0 | Y34: -0.11059415 | Z34: -0.076559074 | AA34: -0.11058499 | AB34: 0.021543636293338622 | AC34: -0.13977288 | AD34: -0.036640744 | AE34: -0.17586967 | AF34: -3.7928453 | AG34: 3.9028453 | AH34: =AF34+AG34 -> 0.11 | AI34: 0.0275 | AJ34: =+AI34*4 -> 0.11 | AK34: =AJ34-SUM(Y34:AD34,K34) -> 0.58415183
A35: 42185 | B35: -0.24757309 | C35: 0.035697631562102115 | D35: -1.5366473 | E35: 0.12995499322303006 | F35: -0.59105089 | G35: -0.28759635 | H35: -0.99534246 | I35: 0.31396205176001407 | J35: -1.3859424 | K35: 0.4765193717033297 | L35: 0.44095487955302576 | M35: 0 | N35: 0 | O35: 0.18386597658111833 | P35: 0 | Q35: 0.2406967563358196 | R35: 0 | S35: 0 | T35: 0 | U35: 0 | V35: 0 | W35: 0 | X35: 0 | Y35: -0.078805476 | Z35: -0.073494757 | AA35: -0.058645212 | AB35: -0.043790151 | AC35: -0.069942527 | AD35: -0.05149291 | AE35: -0.17417342 | AF35: -3.7728453 | AG35: 3.9028453 | AH35: =AF35+AG35 -> 0.13 | AI35: 0.0325 | AJ35: =+AI35*4 -> 0.13 | AK35: =AJ35-SUM(Y35:AD35,K35) -> 0.50617103
A36: 42277 | B36: -0.30164237 | C36: 0.012756578901211891 | D36: -1.6859878 | E36: 0.2170901677160181 | F36: -0.62401203 | G36: -0.23229996 | H36: -0.86628503 | I36: 0.28820625596147065 | J36: -1.3201813 | K36: 0.18615034375119247 | L36: 0.42208949629692893 | M36: 0 | N36: 0 | O36: 0.22148615 | P36: 0 | Q36: 0.20185447625242295 | R36: 0 | S36: 0 | T36: 0 | U36: 0 | V36: 0 | W36: 0 | X36: 0 | Y36: -0.023828344 | Z36: -0.062883959 | AA36: -0.062716485 | AB36: -0.014608104 | AC36: 0.0092434208 | AD36: 0.035214993 | AE36: -0.17249183 | AF36: -3.7728453 | AG36: 3.9028453 | AH36: =AF36+AG36 -> 0.13 | AI36: 0.0325 | AJ36: =+AI36*4 -> 0.13 | AK36: =AJ36-SUM(Y36:AD36,K36) -> 0.24957848
A37: 42369 | B37: -0.26988226 | C37: -0.022036955 | D37: -1.7475623 | E37: 0.064730959 | F37: -0.65275931 | G37: -0.17204609 | H37: -0.66246149 | I37: 0.19896005242208106 | J37: -1.3218542 | K37: 0.23405356916857573 | L37: 0.3944278111840986 | M37: 0 | N37: 0 | O37: 0.26827442213871333 | P37: 0 | Q37: 0.17123872380359928 | R37: 0 | S37: 0 | T37: 0 | U37: 0 | V37: 0 | W37: 0 | X37: 0 | Y37: -0.07755596 | Z37: -0.029577166 | AA37: -0.054797165 | AB37: -0.030247081 | AC37: 0.040362692 | AD37: 0.096711215 | AE37: -0.17082483 | AF37: -3.7428453 | AG37: 3.9028453 | AH37: =AF37+AG37 -> 0.16 | AI37: 0.04 | AJ37: =+AI37*4 -> 0.16 | AK37: =AJ37-SUM(Y37:AD37,K37) -> 0.21510347
A38: 42460 | B38: -0.24677793 | C38: -0.0020798212 | D38: -1.906728 | E38: 0.3387361596761605 | F38: -0.67401879 | G38: -0.11545836 | H38: -0.71240191 | I38: 0.2014595112883618 | J38: -1.304376 | K38: 0.062267722 | L38: 0.3465335571346303 | M38: 0 | N38: 0 | O38: 0.31808418 | P38: 0 | Q38: 0.16055360160090143 | R38: 0 | S38: 0 | T38: 0 | U38: 0 | V38: 0 | W38: 0 | X38: 0 | Y38: -0.0043145471 | Z38: -0.016463581 | AA38: 0.0043348696 | AB38: -0.00029892432 | AC38: 0.038807395005766195 | AD38: 0.13846791978874304 | AE38: -0.16917234 | AF38: -3.5428453 | AG38: 3.9028453 | AH38: =AF38+AG38 -> 0.36 | AI38: 0.09 | AJ38: =+AI38*4 -> 0.36 | AK38: =AJ38-SUM(Y38:AD38,K38) -> 0.31447446
A39: 42551 | B39: -0.3379953 | C39: -0.016953436 | D39: -1.8728765 | E39: 0.24705578806161166 | F39: -0.65492174 | G39: -0.068963593 | H39: -0.55859877 | I39: 0.4200654665864897 | J39: -1.3234208 | K39: 0.18379164088446728 | L39: 0.25974541338614704 | M39: 0 | N39: 0 | O39: 0.3138398754114705 | P39: 0 | Q39: 0.14379541 | R39: 0 | S39: 0 | T39: 0 | U39: 0 | V39: 0 | W39: 0 | X39: 0 | Y39: -0.096390632 | Z39: -0.03041953 | AA39: -0.043584768 | AB39: -0.012886705 | AC39: 0.0061575716 | AD39: 0.077249508 | AE39: -0.16753429 | AF39: -3.5328453 | AG39: 3.9028453 | AH39: =AF39+AG39 -> 0.37 | AI39: 0.0925 | AJ39: =+AI39*4 -> 0.37 | AK39: =AJ39-SUM(Y39:AD39,K39) -> 0.46987455
A40: 42643 | B40: -0.32622696 | C40: -0.0014490214 | D40: -1.8246497 | E40: 0.3624232000642007 | F40: -0.61081472 | G40: -0.038748424 | H40: -0.70295169 | I40: 0.41634039734783757 | J40: -1.3458314 | K40: 0.16637853053560803 | L40: 0.2216396124785608 | M40: 0 | N40: 0 | O40: 0.32652767031934526 | P40: 0 | Q40: 0.1467070576231654 | R40: 0 | S40: 0 | T40: 0 | U40: 0 | V40: 0 | W40: 0 | X40: 0 | Y40: -0.047316741 | Z40: -0.074139807 | AA40: -0.044780551 | AB40: -0.037675983 | AC40: 0.003673233 | AD40: 0.063960518 | AE40: -0.16591061 | AF40: -3.5128453 | AG40: 3.9028453 | AH40: =AF40+AG40 -> 0.39 | AI40: 0.0975 | AJ40: =+AI40*4 -> 0.39 | AK40: =AJ40-SUM(Y40:AD40,K40) -> 0.52627933
A41: 42735 | B41: -0.31669744 | C41: -0.051860206 | D41: -1.6806939 | E41: 0.25569595521761807 | F41: -0.54069014 | G41: -0.017178857 | H41: -0.78961363 | I41: 0.40161109087240426 | J41: -1.3144108 | K41: 0.33620826338696214 | L41: 0.20273809174151428 | M41: 0 | N41: 0 | O41: 0.3386765345264651 | P41: 0 | Q41: 0.15826394179464445 | R41: 0 | S41: 0 | T41: 0 | U41: 0 | V41: 0 | W41: 0 | X41: 0 | Y41: -0.074217158 | Z41: -0.060893123 | AA41: -0.10139322 | AB41: -0.053874864 | AC41: -0.02587948 | AD41: 0.045664815 | AE41: -0.16430121 | AF41: -3.4528453 | AG41: 3.9028453 | AH41: =AF41+AG41 -> 0.45 | AI41: 0.1125 | AJ41: =+AI41*4 -> 0.45 | AK41: =AJ41-SUM(Y41:AD41,K41) -> 0.72059303
A42: 42825 | B42: -0.34597994 | C42: -0.015368174 | D42: -1.5292826 | E42: 0.3187437441533457 | F42: -0.48955666 | G42: 0.0011647255 | H42: -0.81667891 | I42: 0.4220960088956626 | J42: -1.2761328 | K42: 0.21733704181977623 | L42: 0.21353266495867926 | M42: 0 | N42: 0 | O42: 0.3502780070518281 | P42: 0 | Q42: 0.16873705262813352 | R42: 0 | S42: 0 | T42: 0 | U42: 0 | V42: 0 | W42: 0 | X42: 0 | Y42: -0.026537337 | Z42: -0.066132082 | AA42: -0.073510405 | AB42: -0.07977149 | AC42: -0.034896676 | AD42: 0.021818531403375058 | AE42: -0.16270603 | AF42: -3.2028453 | AG42: 3.9028453 | AH42: =AF42+AG42 -> 0.7 | AI42: 0.175 | AJ42: =+AI42*4 -> 0.7 | AK42: =AJ42-SUM(Y42:AD42,K42) -> 0.98084799
A43: 42916 | B43: -0.29331686 | C43: -0.012364696 | D43: -1.4295778 | E43: 0.3525871481695067 | F43: -0.47394814 | G43: 0.0081705944 | H43: -0.69455729 | I43: 0.3181647717209521 | J43: -1.2589054 | K43: 0.1398786270905517 | L43: 0.2239001350372293 | M43: 0 | N43: 0 | O43: 0.3540556001858463 | P43: 0 | Q43: 0.16546769854294446 | R43: 0 | S43: 0 | T43: 0 | U43: 0 | V43: 0 | W43: 0 | X43: 0 | Y43: -0.029138664 | Z43: -0.018927787 | AA43: -0.055204037 | AB43: -0.046370823 | AC43: -0.054733325 | AD43: 0.013099839473021534 | AE43: -0.16112497 | AF43: -2.9528453 | AG43: 3.9028453 | AH43: =AF43+AG43 -> 0.95 | AI43: 0.2375 | AJ43: =+AI43*4 -> 0.95 | AK43: =AJ43-SUM(Y43:AD43,K43) -> 1.1543746
A44: 43008 | B44: -0.28523191 | C44: -0.022796783 | D44: -1.3143435 | E44: 0.29018106084297113 | F44: -0.4751896 | G44: 0.015942374080303943 | H44: -0.79206901 | I44: 0.28337238060006753 | J44: -1.1836734 | K44: 0.2198941554881842 | L44: 0.24466399904799563 | M44: 0 | N44: 0 | O44: 0.3318590293019019 | P44: 0 | Q44: 0.20288658005639945 | R44: 0 | S44: 0 | T44: 0 | U44: 0 | V44: 0 | W44: 0 | X44: 0 | Y44: -0.036448597 | Z44: -0.0043671622 | AA44: -0.011032604 | AB44: -0.031637764 | AC44: -0.020124412 | AD44: -0.0051722178 | AE44: -0.15955797 | AF44: -2.7528453 | AG44: 3.9028453 | AH44: =AF44+AG44 -> 1.15 | AI44: 0.2875 | AJ44: =+AI44*4 -> 1.15 | AK44: =AJ44-SUM(Y44:AD44,K44) -> 1.2587828
A45: 43100 | B45: -0.32423909 | C45: 0.058332041 | D45: -1.1823672 | E45: 0.4247557517737634 | F45: -0.49398925 | G45: 0.019103739392961033 | H45: -1.0356493 | I45: 0.3423382188708738 | J45: -1.0943325 | K45: 0.056732921 | L45: 0.2503154582181623 | M45: 0 | N45: 0 | O45: 0.2924136443874879 | P45: 0 | Q45: 0.2326074430939753 | R45: 0 | S45: 0 | T45: 0 | U45: 0 | V45: 0 | W45: 0 | X45: 0 | Y45: -0.0108838 | Z45: -0.017706721 | AA45: -0.021026363 | AB45: -0.016982469 | AC45: -0.026951586 | AD45: 0.0026886556 | AE45: -0.15800494 | AF45: -2.7028453 | AG45: 3.9028453 | AH45: =AF45+AG45 -> 1.2 | AI45: 0.3 | AJ45: =+AI45*4 -> 1.2 | AK45: =AJ45-SUM(Y45:AD45,K45) -> 1.2341294
A46: 43190 | B46: -0.31971092 | C46: 0.11704291740605656 | D46: -1.046131 | E46: 0.5242876831768398 | F46: -0.5039685 | G46: 0.028950686936752443 | H46: -0.94033352 | I46: 0.4689505238380973 | J46: -1.0720867 | K46: -0.025485855 | L46: 0.2623300870835253 | M46: 0 | N46: 0 | O46: 0.26893349676415446 | P46: 0 | Q46: 0.21999527888518636 | R46: 0 | S46: 0 | T46: 0 | U46: 0 | V46: 0 | W46: 0 | X46: 0 | Y46: -0.063036592 | Z46: -0.037602545 | AA46: -0.061013784 | AB46: -0.051359748 | AC46: -0.041582856 | AD46: -0.024558137 | AE46: -0.15646579 | AF46: -2.4528453 | AG46: 3.9028453 | AH46: =AF46+AG46 -> 1.45 | AI46: 0.3625 | AJ46: =+AI46*4 -> 1.45 | AK46: =AJ46-SUM(Y46:AD46,K46) -> 1.7546395
A47: 43281 | B47: -0.27450008 | C47: 0.082999718 | D47: -1.0220163 | E47: 0.5645851207488903 | F47: -0.52563247 | G47: 0.041231183462727965 | H47: -0.8597156 | I47: 0.5354333704207652 | J47: -1.0910608 | K47: 0.032419746 | L47: 0.2834968188786932 | M47: 0 | N47: 0 | O47: 0.2811372681913811 | P47: 0 | Q47: 0.17874034856620274 | R47: 0 | S47: 0 | T47: 0 | U47: 0 | V47: 0 | W47: 0 | X47: 0 | Y47: -0.051730126 | Z47: -0.047450295 | AA47: -0.052709031 | AB47: -0.054580835 | AC47: -0.034520236 | AD47: 0.005967295 | AE47: -0.15494045 | AF47: -2.1628453 | AG47: 3.9028453 | AH47: =AF47+AG47 -> 1.74 | AI47: 0.435 | AJ47: =+AI47*4 -> 1.74 | AK47: =AJ47-SUM(Y47:AD47,K47) -> 1.9426035
A48: 43373 | B48: -0.21351261 | C48: 0.077395741 | D48: -0.98813721 | E48: 0.6014809529232101 | F48: -0.55042091 | G48: 0.055370418 | H48: -0.91624447 | I48: 0.4294523122385427 | J48: -1.0725806 | K48: 0.16253330711098016 | L48: 0.2913743402206243 | M48: 0 | N48: 0 | O48: 0.27773858580218713 | P48: 0 | Q48: 0.18904871921561162 | R48: 0 | S48: 0 | T48: 0 | U48: 0 | V48: 0 | W48: 0 | X48: 0 | Y48: -0.046637584 | Z48: -0.041781258 | AA48: -0.05723294 | AB48: -0.031403074 | AC48: -0.0064627094 | AD48: 0.020602487844354672 | AE48: -0.15342882 | AF48: -1.9728453 | AG48: 3.9028453 | AH48: =AF48+AG48 -> 1.93 | AI48: 0.4825 | AJ48: =+AI48*4 -> 1.93 | AK48: =AJ48-SUM(Y48:AD48,K48) -> 2.1135176
A49: 43465 | B49: -0.19942506 | C49: 0.096554959 | D49: -1.0119348 | E49: 0.6960726949236329 | F49: -0.60525298 | G49: 0.065800203 | H49: -0.70112714 | I49: 0.4302040777659501 | J49: -1.1011288 | K49: 0.10119267088936446 | L49: 0.28439552192091183 | M49: 0 | N49: 0 | O49: 0.27549715 | P49: 0 | Q49: 0.17860431758777284 | R49: 0 | S49: 0 | T49: 0 | U49: 0 | V49: 0 | W49: 0 | X49: 0 | Y49: -0.028314414 | Z49: -0.041705631 | AA49: -0.032512877 | AB49: -0.0025790873 | AC49: 0.016153945022218133 | AD49: 0.048590800642321255 | AE49: -0.15193084 | AF49: -1.6828453 | AG49: 3.9028453 | AH49: =AF49+AG49 -> 2.22 | AI49: 0.555 | AJ49: =+AI49*4 -> 2.22 | AK49: =AJ49-SUM(Y49:AD49,K49) -> 2.325112
A50: 43555 | B50: -0.11961292 | C50: 0.10416148441840886 | D50: -1.0590453 | E50: 0.6743185127199101 | F50: -0.6929354 | G50: 0.075161857 | H50: -0.88015992 | I50: 0.33419909853930135 | J50: -0.92043235 | K50: 0.21835497764454753 | L50: 0.2598653196404099 | M50: 0 | N50: 0 | O50: 0.2314321281215881 | P50: 0 | Q50: 0.20336935916210677 | R50: 0 | S50: 0 | T50: 0 | U50: 0 | V50: 0 | W50: 0 | X50: 0 | Y50: -0.027142326 | Z50: 0.009763891 | AA50: 0.029253109176937738 | AB50: 0.040979483916210396 | AC50: 0.070888219 | AD50: 0.09518179 | AE50: -0.1504464 | AF50: -1.5028453 | AG50: 3.9028453 | AH50: =AF50+AG50 -> 2.4 | AI50: 0.6 | AJ50: =+AI50*4 -> 2.4 | AK50: =AJ50-SUM(Y50:AD50,K50) -> 2.2513084
A51: 43646 | B51: -0.28514146 | C51: 0.17484534415894973 | D51: -1.096137 | E51: 0.9088055298303473 | F51: -0.74430887 | G51: 0.087416376 | H51: -1.0843869 | I51: 0.35506899724503715 | J51: -0.94553566 | K51: 0.18755604 | L51: 0.22430069438689992 | M51: 0 | N51: 0 | O51: 0.2001997660507918 | P51: 0 | Q51: 0.1850680585492531 | R51: 0 | S51: 0 | T51: 0 | U51: 0 | V51: 0 | W51: 0 | X51: 0 | Y51: 0.016918513 | Z51: 0.057688446718641546 | AA51: 0.069435491 | AB51: 0.087667742 | AC51: 0.11280135484375399 | AD51: 0.1338675855797758 | AE51: -0.14897542 | AF51: -1.5028453 | AG51: 3.9028453 | AH51: =AF51+AG51 -> 2.4 | AI51: 0.6 | AJ51: =+AI51*4 -> 2.4 | AK51: =AJ51-SUM(Y51:AD51,K51) -> 2.0384222
A52: 43738 | B52: -0.29679419 | C52: 0.26035294829159417 | D52: -1.1146556 | E52: 1.0964308829854836 | F52: -0.77416757 | G52: 0.094046178 | H52: -1.1247468 | I52: 0.3255256212223233 | J52: -0.98766717 | K52: 0.061891145 | L52: 0.22073029048033185 | M52: 0 | N52: 0 | O52: 0.1902677092333764 | P52: 0 | Q52: 0.17606905433945988 | R52: 0 | S52: 0 | T52: 0 | U52: 0 | V52: 0 | W52: 0 | X52: 0 | Y52: -0.0035201736 | Z52: 0.014875101 | AA52: 0.044624863 | AB52: 0.062731007 | AC52: 0.080068604 | AD52: 0.10861054440623459 | AE52: -0.14751782 | AF52: -1.7128453 | AG52: 3.9028453 | AH52: =AF52+AG52 -> 2.19 | AI52: 0.5475 | AJ52: =+AI52*4 -> 2.19 | AK52: =AJ52-SUM(Y52:AD52,K52) -> 1.9293295
A53: 43830 | B53: -0.2294554 | C53: 0.35186936812619357 | D53: -1.0758471 | E53: 0.9932498411909156 | F53: -0.80128908 | G53: 0.077831993 | H53: -1.0631762 | I53: 0.2602118495773927 | J53: -0.86946429 | K53: -0.005540442 | L53: 0.21400986542163247 | M53: 0 | N53: 0 | O53: 0.1502309563556947 | P53: 0 | Q53: 0.22722347456297048 | R53: 0 | S53: 0 | T53: 0 | U53: 0 | V53: 0 | W53: 0 | X53: 0 | Y53: -0.13861962 | Z53: -0.082718961 | AA53: -0.0657535 | AB53: -0.042934291 | AC53: -0.013666747 | AD53: 0.0070664477 | AE53: -0.1460735 | AF53: -2.2528453 | AG53: 3.9028453 | AH53: =AF53+AG53 -> 1.65 | AI53: 0.4125 | AJ53: =+AI53*4 -> 1.65 | AK53: =AJ53-SUM(Y53:AD53,K53) -> 1.9921671
A54: 43921 | B54: -0.26770706 | C54: 0.10301048054786877 | D54: -1.2322878 | E54: -0.077060323 | F54: -0.91611456 | G54: 0.038721146656648976 | H54: -0.78083877 | I54: 0.27231418898611104 | J54: -0.7870084 | K54: 0.6559042179493226 | L54: 0.17803414848438223 | M54: 0 | N54: 0 | O54: 0.056564852 | P54: 0 | Q54: 0.21140017730361982 | R54: 0 | S54: 0 | T54: 0 | U54: 0 | V54: 0 | W54: 0 | X54: 0 | Y54: -0.0030641652 | Z54: -0.040911246 | AA54: -0.02971052 | AB54: 0.0049288479 | AC54: 0.033568002 | AD54: 0.072053805 | AE54: -0.14464238 | AF54: -2.6528453 | AG54: 3.9028453 | AH54: =AF54+AG54 -> 1.25 | AI54: 0.3125 | AJ54: =+AI54*4 -> 1.25 | AK54: =AJ54-SUM(Y54:AD54,K54) -> 1.2131353
A55: 44012 | B55: -0.30795599 | C55: -0.19678092 | D55: -1.3661008 | E55: -0.69090192 | F55: -1.0174799 | G55: -0.0044973783 | H55: -0.48920041 | I55: -0.14331733 | J55: -0.65710936 | K55: 1.3597757435452773 | L55: 0.13083082189420456 | M55: 0 | N55: 0 | O55: 0.010646599404515282 | P55: 0 | Q55: 0.21727526831298863 | R55: 0 | S55: 0 | T55: 0 | U55: 0 | V55: 0 | W55: 0 | X55: 0 | Y55: -0.14856995 | Z55: -0.11720587 | AA55: -0.12682331 | AB55: -0.080518393 | AC55: -0.052338688 | AD55: -0.019349252 | AE55: -0.14322438 | AF55: -3.8428453 | AG55: 3.9028453 | AH55: =AF55+AG55 -> 0.06 | AI55: 0.015 | AJ55: =+AI55*4 -> 0.06 | AK55: =AJ55-SUM(Y55:AD55,K55) -> 0.60480546
A56: 44104 | B56: -0.37841766 | C56: -0.2602782 | D56: -1.318233 | E56: -1.4143263 | F56: -1.1034942 | G56: -0.0051375745 | H56: -0.46983322 | I56: 0.23691965573243196 | J56: -0.5657257 | K56: 1.113977860356052 | L56: 0.061686786194622686 | M56: 0 | N56: 0 | O56: -0.15067672 | P56: 0 | Q56: 0.2925628088415432 | R56: 0 | S56: 0 | T56: 0 | U56: 0 | V56: 0 | W56: 0 | X56: 0 | Y56: 0.15815412797383174 | Z56: 0.039363371782985254 | AA56: -0.0030169993 | AB56: 0.0014951241 | AC56: 0.021957925 | AD56: 0.071995969 | AE56: -0.14181939 | AF56: -3.8128453 | AG56: 3.9028453 | AH56: =AF56+AG56 -> 0.09 | AI56: 0.0225 | AJ56: =+AI56*4 -> 0.09 | AK56: =AJ56-SUM(Y56:AD56,K56) -> -0.0024320185
A57: 44196 | B57: -0.28576866 | C57: 0.016621187885746846 | D57: -1.2266035 | E57: -1.3085233 | F57: -1.1769241 | G57: -0.0072321649 | H57: -1.1114581 | I57: 0.30401938575743426 | J57: -0.33760535 | K57: 0.4368712725540467 | L57: 0.037992316 | M57: 0 | N57: 0 | O57: -0.26841279 | P57: 0 | Q57: 0.2880331111558625 | R57: 0 | S57: 0 | T57: 0 | U57: 0 | V57: 0 | W57: 0 | X57: 0 | Y57: 0.25436860319354887 | Z57: 0.22872646630268179 | AA57: 0.1548811403105413 | AB57: 0.091954215 | AC57: 0.076602409 | AD57: 0.1600397782651623 | AE57: -0.14042734 | AF57: -3.8128453 | AG57: 3.9028453 | AH57: =AF57+AG57 -> 0.09 | AI57: 0.0225 | AJ57: =+AI57*4 -> 0.09 | AK57: =AJ57-SUM(Y57:AD57,K57) -> -0.078556624
A58: 44286 | B58: -0.47762882 | C58: 0.1295191707169266 | D58: -1.0798775 | E58: -1.3065447 | F58: -1.1325843 | G58: 0.0001658663 | H58: -1.2838656 | I58: 0.6802286702646845 | J58: -0.34852669 | K58: 0.10230721233194384 | L58: 0.10664687046755228 | M58: 0 | N58: 0 | O58: -0.29803146 | P58: 0 | Q58: 0.3067977572384854 | R58: 0 | S58: 0 | T58: 0 | U58: 0 | V58: 0 | W58: 0 | X58: 0 | Y58: -0.052982747 | Z58: 0.2167141660845595 | AA58: 0.23601084655731788 | AB58: 0.17263831398759408 | AC58: 0.11374554 | AD58: 0.23147025747060448 | AE58: -0.13904813 | AF58: -3.8228453 | AG58: 3.9028453 | AH58: =AF58+AG58 -> 0.08 | AI58: 0.02 | AJ58: =+AI58*4 -> 0.08 | AK58: =AJ58-SUM(Y58:AD58,K58) -> 0.019237204
A59: 44377 | B59: -0.72534585 | C59: 0.38053624790467544 | D59: -0.96552534 | E59: -1.0896947 | F59: -1.0928302 | G59: -0.02809675 | H59: -1.3925776 | I59: 1.2386615775759275 | J59: -0.2829431 | K59: -0.58828676 | L59: 0.16618612183810721 | M59: 0 | N59: 0 | O59: -0.28881951 | P59: 0 | Q59: 0.3327764649337764 | R59: 0 | S59: 0 | T59: 0 | U59: 0 | V59: 0 | W59: 0 | X59: 0 | Y59: -0.13265704 | Z59: -0.0055201336 | AA59: 0.16806286645842172 | AB59: 0.16684806147100836 | AC59: 0.1453031763449316 | AD59: 0.29875878371215103 | AE59: -0.13768166 | AF59: -3.8328453 | AG59: 3.9028453 | AH59: =AF59+AG59 -> 0.07 | AI59: 0.0175 | AJ59: =+AI59*4 -> 0.07 | AK59: =AJ59-SUM(Y59:AD59,K59) -> 0.79646393
A60: 44469 | B60: -0.50172352 | C60: 0.044927371 | D60: -0.79816691 | E60: -1.1859974 | F60: -0.92995267 | G60: -0.086884901 | H60: -1.1918761 | I60: 1.5270092353912281 | J60: -0.28664595 | K60: -0.030221183 | L60: 0.11596182880916935 | M60: 0 | N60: 0 | O60: -0.21677069 | P60: 0 | Q60: 0.30828299451084135 | R60: 0 | S60: 0 | T60: 0 | U60: 0 | V60: 0 | W60: 0 | X60: 0 | Y60: -0.5742456 | Z60: -0.24249278 | AA60: -0.067290889 | AB60: 0.020793550252538505 | AC60: 0.088869836 | AD60: 0.3299063536115468 | AE60: -0.13632786 | AF60: -3.8128453 | AG60: 3.9028453 | AH60: =AF60+AG60 -> 0.09 | AI60: 0.0225 | AJ60: =+AI60*4 -> 0.09 | AK60: =AJ60-SUM(Y60:AD60,K60) -> 0.91538062
A61: 44561 | B61: -0.27471455 | C61: 0.16070264692033415 | D61: -0.76065967 | E61: -1.1277257 | F61: -0.85215438 | G61: -0.10255628 | H61: -1.1673795 | I61: 1.7388868870880378 | J61: -0.32097483 | K61: -0.68105227 | L61: 0.087385526 | M61: 0 | N61: 0 | O61: -0.15884375 | P61: 0 | Q61: 0.2503980017488121 | R61: 0 | S61: 0 | T61: 0 | U61: 0 | V61: 0 | W61: 0 | X61: 0 | Y61: -0.018657681 | Z61: -0.44238514 | AA61: -0.14534689 | AB61: -0.14327749 | AC61: -0.0071571826 | AD61: 0.27765350612520334 | AE61: -0.13498663 | AF61: -3.8228453 | AG61: 3.9028453 | AH61: =AF61+AG61 -> 0.08 | AI61: 0.02 | AJ61: =+AI61*4 -> 0.08 | AK61: =AJ61-SUM(Y61:AD61,K61) -> 1.5178767
A62: 44651 | B62: -0.25776927 | C62: 0.051057926 | D62: -0.82316737 | E62: -0.87883331 | F62: -0.73120639 | G62: -0.10375397 | H62: -0.71852187 | I62: 2.0306794129701564 | J62: -0.51443423 | K62: -0.95326469 | L62: 0.023519499413673886 | M62: 0 | N62: 0 | O62: -0.077198415 | P62: 0 | Q62: 0.21880743537315003 | R62: 0 | S62: 0 | T62: 0 | U62: 0 | V62: 0 | W62: 0 | X62: 0 | Y62: -0.46260274 | Z62: -0.019691292 | AA62: -0.23001709 | AB62: -0.20295339 | AC62: -0.14283886 | AD62: 0.14300113957363367 | AE62: -0.13365787 | AF62: -3.7828453 | AG62: 3.9028453 | AH62: =AF62+AG62 -> 0.12 | AI62: 0.03 | AJ62: =+AI62*4 -> 0.12 | AK62: =AJ62-SUM(Y62:AD62,K62) -> 2.1313681
A63: 44742 | B63: -0.32040798 | C63: -0.28242881 | D63: -0.66523834 | E63: -0.382509 | F63: -0.40836075 | G63: -0.037954315 | H63: -0.5105653 | I63: 2.2285418600887406 | J63: -0.84442859 | K63: -0.79864368 | L63: 0.038083897789302656 | M63: 0 | N63: 0 | O63: 0.22005562512320062 | P63: 0 | Q63: 0.2033139407377899 | R63: 0 | S63: 0 | T63: 0 | U63: 0 | V63: 0 | W63: 0 | X63: 0 | Y63: -0.36834562 | Z63: -0.26871238 | AA63: -0.16939077 | AB63: -0.36002147 | AC63: -0.19111394 | AD63: -0.082378218 | AE63: -0.1323415 | AF63: -3.1328453 | AG63: 3.9028453 | AH63: =AF63+AG63 -> 0.77 | AI63: 0.1925 | AJ63: =+AI63*4 -> 0.77 | AK63: =AJ63-SUM(Y63:AD63,K63) -> 3.0086061
A64: 44834 | B64: -0.26482745 | C64: -0.13696089 | D64: -0.59683872 | E64: 0.099154953 | F64: -0.23418386 | G64: 0.070824889 | H64: -0.81400294 | I64: 2.1161889675398706 | J64: -0.9667304 | K64: -0.10572394 | L64: 0.030538594 | M64: 0 | N64: 0 | O64: 0.4115390233867267 | P64: 0 | Q64: 0.21094774578196512 | R64: 0 | S64: 0 | T64: 0 | U64: 0 | V64: 0 | W64: 0 | X64: 0 | Y64: 0.091905092 | Z64: -0.51457023 | AA64: -0.31702579 | AB64: -0.22477021 | AC64: -0.19721472 | AD64: -0.25005803 | AE64: -0.13103742 | AF64: -1.7228453 | AG64: 3.9028453 | AH64: =AF64+AG64 -> 2.18 | AI64: 0.545 | AJ64: =+AI64*4 -> 2.18 | AK64: =AJ64-SUM(Y64:AD64,K64) -> 3.6974578
A65: 44926 | B65: -0.29004857 | C65: -0.22673835 | D65: -0.46638485 | E65: 0.77342314 | F65: 0.0046206721 | G65: 0.17492395109534115 | H65: -0.92451808 | I65: 2.024139658049159 | J65: -1.2038802 | K65: 0.4759199705078415 | L65: -0.0016606573 | M65: 0 | N65: 0 | O65: 0.6468233690636522 | P65: 0 | Q65: 0.22935223710705355 | R65: 0 | S65: 0 | T65: 0 | U65: 0 | V65: 0 | W65: 0 | X65: 0 | Y65: -0.19994241 | Z65: -0.095994329 | AA65: -0.30535709 | AB65: -0.38606995 | AC65: -0.014907879 | AD65: -0.33680046 | AE65: -0.12974555 | AF65: -0.25284535 | AG65: 3.9028453 | AH65: =AF65+AG65 -> 3.65 | AI65: 0.9125 | AJ65: =+AI65*4 -> 3.65 | AK65: =AJ65-SUM(Y65:AD65,K65) -> 4.9890721
A66: 45016 | B66: -0.31096768 | C66: -0.068795535 | D66: -0.38919231 | E66: 1.4109054244536354 | F66: 0.1462050479210775 | G66: 0.28414375574654166 | H66: -0.64166889 | I66: 1.9773571752348016 | J66: -1.3789222 | K66: -0.65779845 | L66: -0.055590471 | M66: 0 | N66: 0 | O66: 0.7171871860028054 | P66: 0 | Q66: 0.3947597001116767 | R66: 0 | S66: 0 | T66: 0 | U66: 0 | V66: 0 | W66: 0 | X66: 0 | Y66: 0.013659672808269387 | Z66: -0.055708605 | AA66: 0.11235827379686701 | AB66: -0.47643198 | AC66: -0.05167185 | AD66: -0.2342078 | AE66: -0.12846579 | AF66: 0.60715465 | AG66: 3.9028453 | AH66: =AF66+AG66 -> 4.51 | AI66: 1.1275 | AJ66: =+AI66*4 -> 4.51 | AK66: =AJ66-SUM(Y66:AD66,K66) -> 5.9858187
