Workbook
Name BoxPlot: "BoxPlot"
Name Bubble: "Bubble"
Name Candlestick: "Candlestick"
Name Chart: "Chart"
Name ChartImage: "ChartImage"
Name ColumnRange: "ColumnRange"
Name DLX1.USE: #REF!
Name Dumbbell: "Dumbbell"
Name fame1: #REF!
Name fame2: #REF!
Name fame3: #REF!
Name Heatmap: "Heatmap"
Name Histogram: "Histogram"
Name Map: "Map"
Name OHLC: "OHLC"
Name PieChart: "PieChart"
Name Scatter: "Scatter"
Name Series: "Series"
Name Stripe: "Stripe"
Name Table: "Table"
Name TreeMap: "TreeMap"
Name Waterfall: "Waterfall"

Sheet All Chart

Sheet drstar_Table
A1: date | B1: g_sh | C1: b_liqtil_sh | D1: b_liqp_sh | E1: b_safetil_sh | F1: b_safep_sh | G1: mu_sh | H1: z_sh | I1: lambda_f_sh | J1: lambda_w_sh | K1: rm_sh | L1: sigma_omega_sh | M1: mu_e_sh | N1: gamma_sh | O1: pi_star_sh | P1: lr_sh | Q1: zp_sh | R1: tfp_sh | S1: gdpdef_sh | T1: corepce_sh | U1: gdp_sh | V1: gdi_sh | W1: BBB_sh | X1: AAA_sh | Y1: rm_shl1 | Z1: rm_shl2 | AA1: rm_shl3 | AB1: rm_shl4 | AC1: rm_shl5 | AD1: rm_shl6 | AE1: dettrend | AF1: detrendedMean | AG1: trend | AH1: Hist | AI1: Hist Check | AJ1: r* | AK1: 1999Q1-2019Q4 | AL1: =$AF$121-$AF$38 -> -3.2029798 | AM1: 2020Q1-2024Q3 | AN1: =AF139-$AF$122 -> 1.672298
A2: 32963 | B2: 0.022857106 | C2: -1.2659806e-08 | D2: 1.8912494 | E2: -0.02240701 | F2: 1.3871634 | G2: 0.31928117 | H2: 0.00035326532 | I2: 5.7968303e-15 | J2: -9.158653e-15 | K2: -9.7580563e-15 | L2: 0.04102846 | M2: 0 | N2: 0 | O2: 4.4430119e-15 | P2: 0 | Q2: 0.034888619 | R2: 0 | S2: 0 | T2: 0 | U2: 0 | V2: 0 | W2: 0 | X2: 0 | Y2: 0 | Z2: 0 | AA2: 0 | AB2: 0 | AC2: 0 | AD2: 0 | AE2: 0.74137884 | AF2: 4.4157933 | AG2: 1.0508022 | AH2: =+AF2+$AG$2 -> 5.4665955 | AI2: 5.4665955 | AJ2: cy | AL2: =SUM($C$121:$F$121)+SUM($C$38:$F$38) -> -2.5068045 | AN2: =SUM($C$139:$F$139)-SUM($C$122:$F$122) -> 1.7776856
A3: 33054 | B3: 0.031388765 | C3: -2.8744524e-08 | D3: 1.8577923 | E3: -0.058292627 | F3: 1.3633833 | G3: 0.27078716 | H3: 0.00033297928 | I3: 5.5767535e-15 | J3: -9.4119372e-15 | K3: -8.7979062e-15 | L3: -0.017738699 | M3: 0 | N3: 0 | O3: 6.0573515e-15 | P3: 0 | Q3: 0.029167752 | R3: 0 | S3: 0 | T3: 0 | U3: 0 | V3: 0 | W3: 0 | X3: 0 | Y3: 0 | Z3: 0 | AA3: 0 | AB3: 0 | AC3: 0 | AD3: 0 | AE3: 0.72988043 | AF3: 4.2067014 | AH3: =+AF3+$AG$2 -> 5.2575036 | AI3: 5.2575036 | AJ3: Other | AL3: =AL1-AL2 -> -0.69617528 | AN3: =AN1-AN2 -> -0.10538752
A4: 33146 | B4: 0.03536748 | C4: -1.6807462e-08 | D4: 1.8815404 | E4: -0.041551059 | F4: 1.3958833 | G4: 0.26835115 | H4: 0.00064458601 | I4: 4.5936694e-15 | J4: -1.060451e-14 | K4: -1.0070513e-14 | L4: -0.0090666522 | M4: 0 | N4: 0 | O4: 7.5410462e-15 | P4: 0 | Q4: 0.027730932 | R4: 0 | S4: 0 | T4: 0 | U4: 0 | V4: 0 | W4: 0 | X4: 0 | Y4: 0 | Z4: 0 | AA4: 0 | AB4: 0 | AC4: 0 | AD4: 0 | AE4: 0.71858231 | AF4: 4.2774824 | AH4: =+AF4+$AG$2 -> 5.3282846 | AI4: 5.3282846
A5: 33238 | B5: 0.027450198 | C5: 1.9378621e-09 | D5: 1.9347906 | E5: -0.0093954249 | F5: 1.4495209 | G5: 0.26681506 | H5: 0.00045264437 | I5: 4.9913935e-15 | J5: -9.3997373e-15 | K5: -1.1302592e-14 | L5: -0.013731569 | M5: 0 | N5: 0 | O5: 8.6228976e-15 | P5: 0 | Q5: 0.02128952 | R5: 0 | S5: 0 | T5: 0 | U5: 0 | V5: 0 | W5: 0 | X5: 0 | Y5: 0 | Z5: 0 | AA5: 0 | AB5: 0 | AC5: 0 | AD5: 0 | AE5: 0.70748044 | AF5: 4.3846723 | AH5: =+AF5+$AG$2 -> 5.4354745 | AI5: 5.4354745
A6: 33328 | B6: 0.032044802 | C6: 4.0733036e-10 | D6: 1.8600488 | E6: -0.0096801325 | F6: 1.4076577 | G6: 0.22860568 | H6: 0.00027248192 | I6: 4.9339146e-15 | J6: -1.5054316e-14 | K6: -1.1217833e-14 | L6: -0.034196845 | M6: 0 | N6: 0 | O6: 1.0145715e-14 | P6: 0 | Q6: 0.014500433 | R6: 0 | S6: 0 | T6: 0 | U6: 0 | V6: 0 | W6: 0 | X6: 0 | Y6: 0 | Z6: 0 | AA6: 0 | AB6: 0 | AC6: 0 | AD6: 0 | AE6: 0.69657088 | AF6: 4.1958238 | AH6: =+AF6+$AG$2 -> 5.246626 | AI6: 5.246626
A7: 33419 | B7: 0.024927776 | C7: -5.7320426e-09 | D7: 1.8029822 | E7: -0.0093853259 | F7: 1.3804813 | G7: 0.23810998 | H7: 0.00015603003 | I7: 4.772759e-15 | J7: -1.3148657e-14 | K7: -8.8711668e-15 | L7: -0.024326299 | M7: 0 | N7: 0 | O7: 1.1371642e-14 | P7: 0 | Q7: 0.011425074 | R7: 0 | S7: 0 | T7: 0 | U7: 0 | V7: 0 | W7: 0 | X7: 0 | Y7: 0 | Z7: 0 | AA7: 0 | AB7: 0 | AC7: 0 | AD7: 0 | AE7: 0.68584979 | AF7: 4.1102205 | AH7: =+AF7+$AG$2 -> 5.1610227 | AI7: 5.1610227
A8: 33511 | B8: 0.027345833 | C8: -1.2045444e-08 | D8: 1.7910849 | E8: -0.0071588175 | F8: 1.3838698 | G8: 0.23902883 | H8: -0.00037903202 | I8: 4.6041055e-15 | J8: -1.5238373e-14 | K8: -1.0115235e-14 | L8: -0.023942685 | M8: 0 | N8: 0 | O8: 1.2969875e-14 | P8: 0 | Q8: 0.0078188552 | R8: 0 | S8: 0 | T8: 0 | U8: 0 | V8: 0 | W8: 0 | X8: 0 | Y8: 0 | Z8: 0 | AA8: 0 | AB8: 0 | AC8: 0 | AD8: 0 | AE8: 0.67531342 | AF8: 4.092981 | AH8: =+AF8+$AG$2 -> 5.1437832 | AI8: 5.1437832
A9: 33603 | B9: 0.020169641 | C9: 6.4132382e-09 | D9: 1.7637174 | E9: 0.024213456 | F9: 1.3856542 | G9: 0.22121379 | H9: -0.0002961815 | I9: 4.5862787e-15 | J9: -1.9323573e-14 | K9: -1.0014256e-14 | L9: -0.035113723 | M9: 0 | N9: 0 | O9: 1.4390821e-14 | P9: 0 | Q9: 0.018473286 | R9: 0 | S9: 0 | T9: 0 | U9: 0 | V9: 0 | W9: 0 | X9: 0 | Y9: 0 | Z9: 0 | AA9: 0 | AB9: 0 | AC9: 0 | AD9: 0 | AE9: 0.66495814 | AF9: 4.06299 | AH9: =+AF9+$AG$2 -> 5.1137922 | AI9: 5.1137922
A10: 33694 | B10: 0.02430367 | C10: -3.9929391e-09 | D10: 1.6915992 | E10: 0.027012828 | F10: 1.3506908 | G10: 0.18707553 | H10: 0.00092963257 | I10: 3.8520642e-15 | J10: -1.7076081e-14 | K10: -1.1507505e-14 | L10: 0.0014841263 | M10: 0 | N10: 0 | O10: 1.6000505e-14 | P10: 0 | Q10: 0.025856657 | R10: 0 | S10: 0 | T10: 0 | U10: 0 | V10: 0 | W10: 0 | X10: 0 | Y10: 0 | Z10: 0 | AA10: 0 | AB10: 0 | AC10: 0 | AD10: 0 | AE10: 0.65478039 | AF10: 3.9637328 | AH10: =+AF10+$AG$2 -> 5.0145349 | AI10: 5.0145349
A11: 33785 | B11: 0.014569147 | C11: -2.7279109e-09 | D11: 1.6721591 | E11: 0.03398723 | F11: 1.348484 | G11: 0.11650581 | H11: 0.00030380421 | I11: 3.656673e-15 | J11: -1.9261495e-14 | K11: -1.25036e-14 | L11: -0.052781583 | M11: 0 | N11: 0 | O11: 1.7699841e-14 | P11: 0 | Q11: 0.0089487143 | R11: 0 | S11: 0 | T11: 0 | U11: 0 | V11: 0 | W11: 0 | X11: 0 | Y11: 0 | Z11: 0 | AA11: 0 | AB11: 0 | AC11: 0 | AD11: 0 | AE11: 0.64477668 | AF11: 3.7869529 | AH11: =+AF11+$AG$2 -> 4.8377551 | AI11: 4.8377551
A12: 33877 | B12: 0.014631182 | C12: 1.2981577e-08 | D12: 1.7026994 | E12: 0.06674222 | F12: 1.3892 | G12: 0.11709162 | H12: 1.0305409e-05 | I12: 3.1462477e-15 | J12: -1.1598776e-14 | K12: -1.6017038e-14 | L12: -0.033579983 | M12: 0 | N12: 0 | O12: 1.9202818e-14 | P12: 0 | Q12: 0.0032617358 | R12: 0 | S12: 0 | T12: 0 | U12: 0 | V12: 0 | W12: 0 | X12: 0 | Y12: 0 | Z12: 0 | AA12: 0 | AB12: 0 | AC12: 0 | AD12: 0 | AE12: 0.63494362 | AF12: 3.8950001 | AH12: =+AF12+$AG$2 -> 4.9458022 | AI12: 4.9458022
A13: 33969 | B13: -0.0091678174 | C13: 3.163372e-08 | D13: 1.6598722 | E13: 0.081335429 | F13: 1.3696645 | G13: 0.026855485 | H13: 0.00029203132 | I13: 3.0056667e-15 | J13: -1.1592775e-14 | K13: -1.2689021e-14 | L13: -0.041864722 | M13: 0 | N13: 0 | O13: 2.0907691e-14 | P13: 0 | Q13: 0.00042245796 | R13: 0 | S13: 0 | T13: 0 | U13: 0 | V13: 0 | W13: 0 | X13: 0 | Y13: 0 | Z13: 0 | AA13: 0 | AB13: 0 | AC13: 0 | AD13: 0 | AE13: 0.62527792 | AF13: 3.7126876 | AH13: =+AF13+$AG$2 -> 4.7634898 | AI13: 4.7634898
A14: 34059 | B14: 0.012552441 | C14: -8.5112958e-09 | D14: 1.4143677 | E14: 0.013337835 | F14: 1.1875767 | G14: -0.04328688 | H14: -0.00031146208 | I14: 3.478245e-15 | J14: -1.2213262e-14 | K14: -1.3420644e-14 | L14: -0.024032038 | M14: 0 | N14: 0 | O14: 2.3065063e-14 | P14: 0 | Q14: -0.016107588 | R14: 0 | S14: 0 | T14: 0 | U14: 0 | V14: 0 | W14: 0 | X14: 0 | Y14: 0 | Z14: 0 | AA14: 0 | AB14: 0 | AC14: 0 | AD14: 0 | AE14: 0.61577632 | AF14: 3.159873 | AH14: =+AF14+$AG$2 -> 4.2106752 | AI14: 4.2106752
A15: 34150 | B15: 0.017364219 | C15: -1.8137702e-08 | D15: 1.2923794 | E15: -0.0090850213 | F15: 1.1079561 | G15: -0.05864888 | H15: -0.00015081061 | I15: 2.8742788e-15 | J15: -1.0224049e-14 | K15: -8.8417949e-15 | L15: -0.010839152 | M15: 0 | N15: 0 | O15: 2.4872655e-14 | P15: 0 | Q15: -0.014862895 | R15: 0 | S15: 0 | T15: 0 | U15: 0 | V15: 0 | W15: 0 | X15: 0 | Y15: 0 | Z15: 0 | AA15: 0 | AB15: 0 | AC15: 0 | AD15: 0 | AE15: 0.60643567 | AF15: 2.9305486 | AH15: =+AF15+$AG$2 -> 3.9813508 | AI15: 3.9813508
... A139: 45473 | B139: 0.023805847 | C139: 1.180587e-09 | D139: 0.36771947 | E139: 0.079310158 | F139: -1.4291997 | G139: -0.26107878 | H139: -0.0001238051 | I139: 2.9657765e-15 | J139: 2.9894859e-15 | K139: 1.9349385e-16 | L139: -0.095994205 | M139: 0 | N139: 0 | O139: 4.3891449e-14 | P139: 0 | Q139: -0.03109361 | R139: 0 | S139: 0 | T139: 0 | U139: 0 | V139: 0 | W139: 0 | X139: 0 | Y139: -2.9123808e-15 | Z139: 2.1346027e-15 | AA139: 8.5186111e-16 | AB139: 3.1604158e-16 | AC139: 2.3866541e-16 | AD139: -1.8741331e-15 | AE139: 0.10912298 | AF139: -1.2375316 | AH139: =+AF139+$AG$2 -> -0.18672942 | AI139: -0.18672942
A140: 45565 | B140: 0.022195873 | C140: 5.2171189e-10 | D140: 0.36253966 | E140: 0.066995125 | F140: -1.40025 | G140: -0.25217081 | H140: -0.00012741782 | I140: 3.2927811e-15 | J140: 3.0269323e-15 | K140: 2.480455e-16 | L140: -0.098902914 | M140: 0 | N140: 0 | O140: 4.3429426e-14 | P140: 0 | Q140: -0.028208454 | R140: 0 | S140: 0 | T140: 0 | U140: 0 | V140: 0 | W140: 0 | X140: 0 | Y140: -2.7483321e-15 | Z140: 2.1083848e-15 | AA140: 8.4941531e-16 | AB140: 3.0156634e-16 | AC140: 2.3668085e-16 | AD140: -1.9117221e-15 | AE140: 0.10778836 | AF140: -1.2201406 | AH140: =+AF140+$AG$2 -> -0.16933837
A141: 45657 | B141: 0.020692349 | C141: 2.3054934e-10 | D141: 0.35743282 | E141: 0.056592333 | F141: -1.3718867 | G141: -0.24333883 | H141: -0.0001282605 | I141: 3.5959681e-15 | J141: 3.0609833e-15 | K141: 3.0544171e-16 | L141: -0.10083382 | M141: 0 | N141: 0 | O141: 4.2969715e-14 | P141: 0 | Q141: -0.025484297 | R141: 0 | S141: 0 | T141: 0 | U141: 0 | V141: 0 | W141: 0 | X141: 0 | Y141: -2.5939269e-15 | Z141: 2.0824632e-15 | AA141: 8.4572076e-16 | AB141: 2.8688547e-16 | AC141: 2.3343461e-16 | AD141: -1.9444939e-15 | AE141: 0.10647323 | AF141: -1.2004812 | AH141: =+AF141+$AG$2 -> -0.14967902
A142: 45747 | B142: 0.019287685 | C142: 1.0188211e-10 | D142: 0.35239791 | E142: 0.047804853 | F142: -1.344098 | G142: -0.23459197 | H142: -0.00012685235 | I142: 3.8749296e-15 | J142: 3.0914721e-15 | K142: 3.6496197e-16 | L142: -0.10189865 | M142: 0 | N142: 0 | O142: 4.2512775e-14 | P142: 0 | Q142: -0.022932454 | R142: 0 | S142: 0 | T142: 0 | U142: 0 | V142: 0 | W142: 0 | X142: 0 | Y142: -2.4493006e-15 | Z142: 2.0568916e-15 | AA142: 8.4093127e-16 | AB142: 2.7220259e-16 | AC142: 2.2915649e-16 | AD142: -1.9725767e-15 | AE142: 0.10517729 | AF142: -1.1789802 | AH142: =+AF142+$AG$2 -> -0.12817798
A143: 45838 | B143: 0.017975021 | C143: 4.5022949e-11 | D143: 0.34743392 | E143: 0.040381865 | F143: -1.3168721 | G143: -0.22594061 | H143: -0.00012365006 | I143: 4.1295943e-15 | J143: 3.1182658e-15 | K143: 4.259275e-16 | L143: -0.10220359 | M143: 0 | N143: 0 | O143: 4.2059004e-14 | P143: 0 | Q143: -0.020559358 | R143: 0 | S143: 0 | T143: 0 | U143: 0 | V143: 0 | W143: 0 | X143: 0 | Y143: -2.3144286e-15 | Z143: 2.0317098e-15 | AA143: 8.351919e-16 | AB143: 2.5768971e-16 | AC143: 2.2405566e-16 | AD143: -1.9961358e-15 | AE143: 0.10390024 | AF143: -1.1560083 | AH143: =+AF143+$AG$2 -> -0.10520607
A144: 45930 | B144: 0.016748132 | C144: 1.9896393e-11 | D144: 0.34253986 | E144: 0.034111496 | F144: -1.2901977 | G144: -0.21739582 | H144: -0.00011905227 | I144: 4.360182e-15 | J144: 3.1412684e-15 | K144: 4.8770984e-16 | L144: -0.10184857 | M144: 0 | N144: 0 | O144: 4.1608744e-14 | P144: 0 | Q144: -0.018367387 | R144: 0 | S144: 0 | T144: 0 | U144: 0 | V144: 0 | W144: 0 | X144: 0 | Y144: -2.1891547e-15 | Z144: 2.0069454e-15 | AA144: 8.2863799e-16 | AB144: 2.4348939e-16 | AC144: 2.1832026e-16 | AD144: -2.0153666e-15 | AE144: 0.10264182 | AF144: -1.1318873 | AH144: =+AF144+$AG$2 -> -0.081085075
A145: 46022 | B145: 0.015601343 | C145: 8.7927459e-12 | D145: 0.33771474 | E145: 0.02881477 | F145: -1.2640637 | G145: -0.20896893 | H145: -0.00011340403 | I145: 4.5671608e-15 | J145: 3.1604226e-15 | K145: 5.497364e-16 | L145: -0.10092676 | M145: 0 | N145: 0 | O145: 4.1162283e-14 | P145: 0 | Q145: -0.016355591 | R145: 0 | S145: 0 | T145: 0 | U145: 0 | V145: 0 | W145: 0 | X145: 0 | Y145: -2.0732164e-15 | Z145: 1.9826159e-15 | AA145: 8.2139451e-16 | AB145: 2.2971716e-16 | AC145: 2.1211745e-16 | AD145: -2.0304874e-15 | AE145: 0.10140172 | AF145: -1.1068958 | AH145: =+AF145+$AG$2 -> -0.056093586
A146: 46112 | B146: 0.014529458 | C146: 3.8859424e-12 | D146: 0.33295758 | E146: 0.024340503 | F146: -1.238459 | G146: -0.2006711 | H146: -0.00010700143 | I146: 4.7512051e-15 | J146: 3.1757089e-15 | K146: 6.1149355e-16 | L146: -0.09952424 | M146: 0 | N146: 0 | O146: 4.0719858e-14 | P146: 0 | Q146: -0.014520334 | R146: 0 | S146: 0 | T146: 0 | U146: 0 | V146: 0 | W146: 0 | X146: 0 | Y146: -1.9662676e-15 | Z146: 1.9587304e-15 | AA146: 8.1357576e-16 | AB146: 2.1646404e-16 | AC146: 2.0559398e-16 | AD146: -2.0417334e-15 | AE146: 0.10017968 | AF146: -1.0812744 | AH146: =+AF146+$AG$2 -> -0.030472218
A147: 46203 | B147: 0.013527702 | C147: 1.717577e-12 | D147: 0.32826744 | E147: 0.020560986 | F147: -1.2133729 | G147: -0.19251304 | H147: -0.00010009612 | I147: 4.9131571e-15 | J147: 3.1871436e-15 | K147: 6.7252764e-16 | L147: -0.097719945 | M147: 0 | N147: 0 | O147: 4.0281665e-14 | P147: 0 | Q147: -0.012855866 | R147: 0 | S147: 0 | T147: 0 | U147: 0 | V147: 0 | W147: 0 | X147: 0 | Y147: -1.8678986e-15 | Z147: 1.9352906e-15 | AA147: 8.0528542e-16 | AB147: 2.037991e-16 | AC147: 1.9887712e-16 | AD147: -2.0493508e-15 | AE147: 0.098975431 | AF147: -1.0552303 | AH147: =+AF147+$AG$2 -> -0.0044281079
A148: 46295 | B148: 0.012591666 | C148: 7.5935093e-13 | D148: 0.32364337 | E148: 0.017368341 | F148: -1.188795 | G148: -0.18450481 | H148: -9.2899648e-05 | I148: 5.0539917e-15 | J148: 3.1947769e-15 | K148: 7.3244438e-16 | L148: -0.095585646 | M148: 0 | N148: 0 | O148: 3.9847859e-14 | P148: 0 | Q148: -0.011354815 | R148: 0 | S148: 0 | T148: 0 | U148: 0 | V148: 0 | W148: 0 | X148: 0 | Y148: -1.7776536e-15 | Z148: 1.9122929e-15 | AA148: 7.9661664e-16 | AB148: 1.9177196e-16 | AC148: 1.920758e-16 | AD148: -2.0535925e-15 | AE148: 0.097788695 | AF148: -1.0289411 | AH148: =+AF148+$AG$2 -> 0.021861088
A149: 46387 | B149: 0.011717262 | C149: 3.3589573e-13 | D149: 0.31908443 | E149: 0.014671439 | F149: -1.1647149 | G149: -0.17665562 | H149: -8.5587674e-05 | I149: 5.1747837e-15 | J149: 3.1986889e-15 | K149: 7.9090714e-16 | L149: -0.093186104 | M149: 0 | N149: 0 | O149: 3.941856e-14 | P149: 0 | Q149: -0.01000861 | R149: 0 | S149: 0 | T149: 0 | U149: 0 | V149: 0 | W149: 0 | X149: 0 | Y149: -1.695046e-15 | Z149: 1.8897289e-15 | AA149: 7.8765249e-16 | AB149: 1.8041531e-16 | AC149: 1.8528185e-16 | AD149: -2.0547132e-15 | AE149: 0.096619212 | AF149: -1.0025585 | AH149: =+AF149+$AG$2 -> 0.048243679
A150: 46477 | B150: 0.010900691 | C150: 1.4876042e-13 | D150: 0.3145897 | E150: 0.012393304 | F150: -1.1411226 | G150: -0.16897372 | H150: -7.8303977e-05 | I150: 5.2766792e-15 | J150: 3.1989865e-15 | K150: 8.4763411e-16 | L150: -0.090579296 | M150: 0 | N150: 0 | O150: 3.8993858e-14 | P150: 0 | Q150: -0.0088078512 | R150: 0 | S150: 0 | T150: 0 | U150: 0 | V150: 0 | W150: 0 | X150: 0 | Y150: -1.619571e-15 | Z150: 1.8675868e-15 | AA150: 7.7846635e-16 | AB150: 1.6974717e-16 | AC150: 1.7857146e-16 | AD150: -2.0529662e-15 | AE150: 0.095466723 | AF150: -0.97621136 | AH150: =+AF150+$AG$2 -> 0.074590821
A151: 46568 | B151: 0.010138404 | C151: 6.6056928e-14 | D151: 0.3101583 | E151: 0.010468911 | F151: -1.1180082 | G151: -0.16146632 | H151: -7.1164182e-05 | I151: 5.3608703e-15 | J151: 3.1957993e-15 | K151: 9.02395e-16 | L151: -0.087816712 | M151: 0 | N151: 0 | O151: 3.8573813e-14 | P151: 0 | Q151: -0.0077426155 | R151: 0 | S151: 0 | T151: 0 | U151: 0 | V151: 0 | W151: 0 | X151: 0 | Y151: -1.5507165e-15 | Z151: 1.8458523e-15 | AA151: 7.6912251e-16 | AB151: 1.5977309e-16 | AC151: 1.7200662e-16 | AD151: -2.0486002e-15 | AE151: 0.094330972 | AF151: -0.95000841 | AH151: =+AF151+$AG$2 -> 0.10079376
... A199: 50951 | B199: 0.00038239024 | C199: 2.030721e-16 | D199: 0.15698224 | E199: 3.1782806e-06 | F199: -0.41865214 | G199: 0.014330778 | H199: -1.2429666e-06 | I199: 3.2993309e-15 | J199: 1.7193339e-15 | K199: 1.5341422e-15 | L199: -0.01345945 | M199: 0 | N199: 0 | O199: 2.313633e-14 | P199: 0 | Q199: -0.00081741983 | R199: 0 | S199: 0 | T199: 0 | U199: 0 | V199: 0 | W199: 0 | X199: 0 | Y199: -6.1230701e-16 | Z199: 1.0611579e-15 | AA199: 4.1704245e-16 | AB199: 4.2520851e-17 | AC199: 6.2312259e-17 | AD199: -1.1732242e-15 | AE199: 0.055353085 | AF199: -0.20587859 | AH199: =+AF199+$AG$2 -> 0.84492359

Sheet Counterfactual_charts
A1: date | B1: obs_gdp | C1: obs_hours | D1: obs_wages | E1: obs_gdpdeflator | F1: obs_corepce | G1: obs_nominalrate | H1: obs_consumption | I1: obs_investment | J1: obs_BBBspread | K1: obs_longinflation | L1: obs_longrate | M1: obs_tfp | N1: obs_gdi | O1: obs_AAAspread | P1: obs_nominalrate1 | Q1: obs_nominalrate2 | R1: obs_nominalrate3 | S1: obs_nominalrate4 | T1: obs_nominalrate5 | U1: obs_nominalrate6 | V1: ex_ante_real_rate | W1: ex_post_real_rate | X1: ex_post_real_rate_core | Y1: HLW r* (25Q3) | Z1: DSGE r* wFG | AA1: Delta_Rstar_HLW | AB1: Delta_Rstar_DSGE | AC1: date | AD1: ex_ante_real_rate | AE1: Delta_Rstar_DSGE | AF1: date | AG1: ex_ante_real_rate | AH1: actual_MP_stance | AK1: CHART | AS1: date | AU1: Date | AV1: HLW | AW1: DSGE | AX1: Actual Real Rate Gap | AY1: Counterfactual Real Rate Gap | AZ1: Actual Output Growth | BA1: Counterfactual Output Growth | BB1: Output (deviation from baseline) | BC1: Inflation (deviation from baseline)
A2: 25749 | B2: 1.87 | C2: NaN | D2: 2.62 | E2: 1.81 | F2: NaN | G2: 1.99 | H2: 0.58 | I2: 5.67 | J2: NaN | K2: NaN | L2: 2.06 | M2: NaN | N2: NaN | O2: NaN | P2: NaN | Q2: NaN | R2: NaN | S2: NaN | T2: NaN | U2: NaN | W2: =+(G2-E2)*4 -> 0.72 | AC2: 21823 | AF2: =+A2 -> 25749 | AS2: =A2 -> 25749
A3: 25841 | B3: 1.02 | C3: NaN | D3: 2.03 | E3: 1.78 | F3: NaN | G3: 1.9 | H3: 0.99 | I3: 0.7 | J3: NaN | K3: NaN | L3: 2.1 | M3: NaN | N3: NaN | O3: NaN | P3: NaN | Q3: NaN | R3: NaN | S3: NaN | T3: NaN | U3: NaN | W3: =+(G3-E3)*4 -> 0.48 | AC3: 21915 | AF3: =+A3 -> 25841 | AS3: =A3 -> 25841
A4: 25933 | B4: 1.04 | C4: NaN | D4: 2.26 | E4: 1.17 | F4: NaN | G4: 1.81 | H4: 1.75 | I4: -0.04 | J4: NaN | K4: NaN | L4: 2.09 | M4: NaN | N4: NaN | O4: NaN | P4: NaN | Q4: NaN | R4: NaN | S4: NaN | T4: NaN | U4: NaN | W4: =+(G4-E4)*4 -> 2.56 | AC4: 22006 | AF4: =+A4 -> 25933 | AS4: =A4 -> 25933
A5: 26023 | B5: -0.38 | C5: NaN | D5: 0.97 | E5: 2.3 | F5: NaN | G5: 1.63 | H5: -0.11 | I5: -0.82 | J5: NaN | K5: NaN | L5: 1.97 | M5: NaN | N5: NaN | O5: NaN | P5: NaN | Q5: NaN | R5: NaN | S5: NaN | T5: NaN | U5: NaN | W5: =+(G5-E5)*4 -> -2.68 | AC5: 22097 | AF5: =+A5 -> 26023 | AS5: =A5 -> 26023
A6: 26114 | B6: 0.98 | C6: NaN | D6: 0.84 | E6: 1.13 | F6: NaN | G6: 1.48 | H6: 1.18 | I6: 2.83 | J6: NaN | K6: NaN | L6: 1.98 | M6: NaN | N6: NaN | O6: NaN | P6: NaN | Q6: NaN | R6: NaN | S6: NaN | T6: NaN | U6: NaN | W6: =+(G6-E6)*4 -> 1.4 | AC6: 22189 | AF6: =+A6 -> 26114 | AS6: =A6 -> 26114
A7: 26206 | B7: 1.84 | C7: NaN | D7: 1.95 | E7: 1.67 | F7: NaN | G7: 1.56 | H7: 1.15 | I7: 0.17 | J7: NaN | K7: NaN | L7: 2.01 | M7: NaN | N7: NaN | O7: NaN | P7: NaN | Q7: NaN | R7: NaN | S7: NaN | T7: NaN | U7: NaN | W7: =+(G7-E7)*4 -> -0.44 | AC7: 22281 | AF7: =+A7 -> 26206 | AS7: =A7 -> 26206
A8: 26298 | B8: 0.66 | C8: NaN | D8: 1.64 | E8: 1.1 | F8: NaN | G8: 1.5 | H8: 1.01 | I8: 1.6 | J8: NaN | K8: NaN | L8: 1.96 | M8: NaN | N8: NaN | O8: NaN | P8: NaN | Q8: NaN | R8: NaN | S8: NaN | T8: NaN | U8: NaN | W8: =+(G8-E8)*4 -> 1.6 | AC8: 22371 | AF8: =+A8 -> 26298 | AS8: =A8 -> 26298
A9: 26389 | B9: 1.25 | C9: NaN | D9: 1.97 | E9: 2.16 | F9: NaN | G9: 1.26 | H9: 0.92 | I9: 0.36 | J9: NaN | K9: NaN | L9: 1.9 | M9: NaN | N9: NaN | O9: NaN | P9: NaN | Q9: NaN | R9: NaN | S9: NaN | T9: NaN | U9: NaN | W9: =+(G9-E9)*4 -> -3.6 | Y9: 3.3617854 | AC9: 22462 | AF9: =+A9 -> 26389 | AS9: =A9 -> 26389
A10: 26480 | B10: 0.61 | C10: NaN | D10: 0.44 | E10: 1.59 | F10: NaN | G10: 1.19 | H10: 0.37 | I10: 1.28 | J10: NaN | K10: NaN | L10: 1.89 | M10: NaN | N10: NaN | O10: NaN | P10: NaN | Q10: NaN | R10: NaN | S10: NaN | T10: NaN | U10: NaN | W10: =+(G10-E10)*4 -> -1.6 | Y10: 2.4726543 | Z10: 3.8039334 | AC10: 22554 | AF10: =+A10 -> 26480 | AS10: =A10 -> 26480
A11: 26572 | B11: 1.12 | C11: NaN | D11: 0.92 | E11: 1.57 | F11: NaN | G11: 1.21 | H11: 2.07 | I11: 0.57 | J11: NaN | K11: NaN | L11: 1.9 | M11: NaN | N11: NaN | O11: NaN | P11: NaN | Q11: NaN | R11: NaN | S11: NaN | T11: NaN | U11: NaN | V11: 1.0149957 | W11: =+(G11-E11)*4 -> -1.44 | Y11: 2.5754349 | Z11: 3.9836896 | AC11: 22646 | AD11: =+V11 -> 1.0149957 | AF11: =+A11 -> 26572 | AG11: =+AD11 -> 1.0149957 | AS11: =A11 -> 26572
A12: 26664 | B12: 1.16 | C12: NaN | D12: 1.45 | E12: 1.54 | F12: NaN | G12: 1.6 | H12: 0.71 | I12: 2.02 | J12: NaN | K12: NaN | L12: 1.95 | M12: NaN | N12: NaN | O12: NaN | P12: NaN | Q12: NaN | R12: NaN | S12: NaN | T12: NaN | U12: NaN | V12: 0.99620506 | W12: =+(G12-E12)*4 -> 0.24 | Y12: 2.743556 | Z12: 4.3206825 | AC12: 22736 | AD12: =+V12 -> 0.99620506 | AF12: =+A12 -> 26664 | AG12: =+AD12 -> 0.99620506 | AS12: =A12 -> 26664
A13: 26754 | B13: 1.65 | C13: NaN | D13: 1.47 | E13: 3.51 | F13: NaN | G13: 1.7 | H13: 0.32 | I13: 1.26 | J13: NaN | K13: NaN | L13: 1.99 | M13: NaN | N13: NaN | O13: NaN | P13: NaN | Q13: NaN | R13: NaN | S13: NaN | T13: NaN | U13: NaN | V13: 2.382294 | W13: =+(G13-E13)*4 -> -7.24 | Y13: 3.355047 | Z13: 4.3759537 | AC13: 22827 | AD13: =+V13 -> 2.382294 | AF13: =+A13 -> 26754 | AG13: =+AD13 -> 2.382294 | AS13: =A13 -> 26754
A14: 26845 | B14: 0.5 | C14: NaN | D14: 0.77 | E14: 2.43 | F14: NaN | G14: 2.12 | H14: 0.82 | I14: 0.29 | J14: NaN | K14: NaN | L14: 2.08 | M14: NaN | N14: NaN | O14: NaN | P14: NaN | Q14: NaN | R14: NaN | S14: NaN | T14: NaN | U14: NaN | V14: 1.883329 | W14: =+(G14-E14)*4 -> -1.24 | Y14: 3.0451464 | Z14: 4.6791313 | AC14: 22919 | AD14: =+V14 -> 1.883329 | AF14: =+A14 -> 26845 | AG14: =+AD14 -> 1.883329 | AS14: =A14 -> 26845
A15: 26937 | B15: 1.19 | C15: NaN | D15: 1.51 | E15: 2.38 | F15: NaN | G15: 2.55 | H15: 0.35 | I15: 1.21 | J15: NaN | K15: NaN | L15: 2.15 | M15: NaN | N15: NaN | O15: NaN | P15: NaN | Q15: NaN | R15: NaN | S15: NaN | T15: NaN | U15: NaN | V15: 3.7119285 | W15: =+(G15-E15)*4 -> 0.68 | Y15: 3.1512224 | Z15: 4.9922555 | AC15: 23011 | AD15: =+V15 -> 3.7119285 | AF15: =+A15 -> 26937 | AG15: =+AD15 -> 3.7119285 | AS15: =A15 -> 26937
A16: 27029 | B16: 0.84 | C16: NaN | D16: 1.68 | E16: 2.32 | F16: NaN | G16: 2.77 | H16: 1.67 | I16: 0.85 | J16: NaN | K16: NaN | L16: 2.18 | M16: NaN | N16: NaN | O16: NaN | P16: NaN | Q16: NaN | R16: NaN | S16: NaN | T16: NaN | U16: NaN | V16: 5.4656472 | W16: =+(G16-E16)*4 -> 1.8 | Y16: 3.0581261 | Z16: 5.2172569 | AC16: 23101 | AD16: =+V16 -> 5.4656472 | AF16: =+A16 -> 27029 | AG16: =+AD16 -> 5.4656472 | AS16: =A16 -> 27029
A17: 27119 | B17: 0.87 | C17: NaN | D17: 0.97 | E17: 3.16 | F17: NaN | G17: 2.81 | H17: 0.42 | I17: 1.1 | J17: NaN | K17: NaN | L17: 2.34 | M17: NaN | N17: NaN | O17: NaN | P17: NaN | Q17: NaN | R17: NaN | S17: NaN | T17: NaN | U17: NaN | V17: 6.2960412 | W17: =+(G17-E17)*4 -> -1.4 | Y17: 3.0365806 | Z17: 5.3314811 | AC17: 23192 | AD17: =+V17 -> 6.2960412 | AF17: =+A17 -> 27119 | AG17: =+AD17 -> 6.2960412 | AS17: =A17 -> 27119
A18: 27210 | B18: 0.25 | C18: NaN | D18: 1.69 | E18: 3.49 | F18: NaN | G18: 2.87 | H18: 1.4 | I18: -1.62 | J18: NaN | K18: NaN | L18: 2.52 | M18: NaN | N18: NaN | O18: NaN | P18: NaN | Q18: NaN | R18: NaN | S18: NaN | T18: NaN | U18: NaN | V18: 5.9361561 | W18: =+(G18-E18)*4 -> -2.48 | Y18: 2.7779297 | Z18: 5.5611755 | AC18: 23284 | AD18: =+V18 -> 5.9361561 | AF18: =+A18 -> 27210 | AG18: =+AD18 -> 5.9361561 | AS18: =A18 -> 27210
A19: 27302 | B19: 0.63 | C19: NaN | D19: 0.52 | E19: 3.38 | F19: NaN | G19: 2.88 | H19: 0.14 | I19: 0.97 | J19: NaN | K19: NaN | L19: 2.67 | M19: NaN | N19: NaN | O19: NaN | P19: NaN | Q19: NaN | R19: NaN | S19: NaN | T19: NaN | U19: NaN | V19: 5.9219283 | W19: =+(G19-E19)*4 -> -2 | Y19: 2.8841953 | Z19: 5.695278 | AC19: 23376 | AD19: =+V19 -> 5.9219283 | AF19: =+A19 -> 27302 | AG19: =+AD19 -> 5.9219283 | AS19: =A19 -> 27302
A20: 27394 | B20: -1.79 | C20: NaN | D20: 1.26 | E20: 3.27 | F20: NaN | G20: 2.67 | H20: -0.78 | I20: -3.05 | J20: NaN | K20: NaN | L20: 2.65 | M20: NaN | N20: NaN | O20: NaN | P20: NaN | Q20: NaN | R20: NaN | S20: NaN | T20: NaN | U20: NaN | V20: 5.8587809 | W20: =+(G20-E20)*4 -> -2.4 | Y20: 2.0943443 | Z20: 5.3896745 | AC20: 23467 | AD20: =+V20 -> 5.8587809 | AF20: =+A20 -> 27394 | AG20: =+AD20 -> 5.8587809 | AS20: =A20 -> 27394
A21: 27484 | B21: -0.88 | C21: NaN | D21: 0.39 | E21: 2.77 | F21: NaN | G21: 2.2 | H21: 0.29 | I21: -1.95 | J21: NaN | K21: NaN | L21: 2.47 | M21: NaN | N21: NaN | O21: NaN | P21: NaN | Q21: NaN | R21: NaN | S21: NaN | T21: NaN | U21: NaN | V21: 5.233664 | W21: =+(G21-E21)*4 -> -2.28 | Y21: 1.9937668 | Z21: 5.0569891 | AC21: 23558 | AD21: =+V21 -> 5.233664 | AF21: =+A21 -> 27484 | AG21: =+AD21 -> 5.233664 | AS21: =A21 -> 27484
A22: 27575 | B22: 0.81 | C22: NaN | D22: 1.68 | E22: 2.32 | F22: NaN | G22: 1.76 | H22: 1.68 | I22: -1.61 | J22: NaN | K22: NaN | L22: 2.39 | M22: NaN | N22: NaN | O22: NaN | P22: NaN | Q22: NaN | R22: NaN | S22: NaN | T22: NaN | U22: NaN | V22: 3.67475 | W22: =+(G22-E22)*4 -> -2.24 | Y22: 2.201963 | Z22: 5.0199626 | AC22: 23650 | AD22: =+V22 -> 3.67475 | AF22: =+A22 -> 27575 | AG22: =+AD22 -> 3.67475 | AS22: =A22 -> 27575
... A60: 31047 | B60: 0.42 | C60: NaN | D60: 0.69 | E60: 1.11 | F60: NaN | G60: 2.53 | H60: 0.51 | I60: 1.23 | J60: NaN | K60: NaN | L60: 2.85 | M60: NaN | N60: NaN | O60: NaN | P60: NaN | Q60: NaN | R60: NaN | S60: NaN | T60: NaN | U60: NaN | V60: 6.7600301 | W60: =+(G60-E60)*4 -> 5.68 | Y60: 1.7611247 | Z60: 6.1339007 | AC60: 27119 | AD60: =+V60 -> 6.7600301 | AF60: =+A60 -> 31047 | AG60: =+AD60 -> 6.7600301 | AS60: =A60 -> 31047
A61: 31137 | B61: 0.16 | C61: 5.6 | D61: 0.43 | E61: 1.56 | F61: NaN | G61: 2.47 | H61: 0.91 | I61: -1.64 | J61: NaN | K61: NaN | L61: 2.74 | M61: NaN | N61: NaN | O61: NaN | P61: NaN | Q61: NaN | R61: NaN | S61: NaN | T61: NaN | U61: NaN | V61: 6.7806939 | W61: =+(G61-E61)*4 -> 3.64 | Y61: 1.7424814 | Z61: 5.9347699 | AC61: 27210 | AD61: =+V61 -> 6.7806939 | AF61: =+A61 -> 31137 | AG61: =+AD61 -> 6.7806939 | AS61: =A61 -> 31137
A62: 31228 | B62: 0.81 | C62: 5.52 | D62: 0.06 | E62: 1.39 | F62: NaN | G62: 2.49 | H62: 0.34 | I62: 1.35 | J62: NaN | K62: NaN | L62: 2.71 | M62: NaN | N62: NaN | O62: NaN | P62: NaN | Q62: NaN | R62: NaN | S62: NaN | T62: NaN | U62: NaN | V62: 6.3991596 | W62: =+(G62-E62)*4 -> 4.4 | Y62: 1.8260628 | Z62: 5.9211855 | AC62: 27302 | AD62: =+V62 -> 6.3991596 | AF62: =+A62 -> 31228 | AG62: =+AD62 -> 6.3991596 | AS62: =A62 -> 31228
A63: 31320 | B63: 0.63 | C63: 5.38 | D63: 0.49 | E63: 1.52 | F63: NaN | G63: 2.34 | H63: 0.38 | I63: 1.3 | J63: NaN | K63: NaN | L63: 2.67 | M63: NaN | N63: NaN | O63: NaN | P63: NaN | Q63: NaN | R63: NaN | S63: NaN | T63: NaN | U63: NaN | V63: 6.5046641 | W63: =+(G63-E63)*4 -> 3.28 | Y63: 1.5783718 | Z63: 5.7742924 | AC63: 27394 | AD63: =+V63 -> 6.5046641 | AF63: =+A63 -> 31320 | AG63: =+AD63 -> 6.5046641 | AS63: =A63 -> 31320
A64: 31412 | B64: 0.3 | C64: 5.18 | D64: -0.02 | E64: 1.49 | F64: NaN | G64: 2.16 | H64: 0.12 | I64: 0.92 | J64: NaN | K64: NaN | L64: 2.57 | M64: NaN | N64: NaN | O64: NaN | P64: NaN | Q64: NaN | R64: NaN | S64: NaN | T64: NaN | U64: NaN | V64: 5.9159244 | W64: =+(G64-E64)*4 -> 2.68 | Y64: 1.5726696 | Z64: 5.5374687 | AC64: 27484 | AD64: =+V64 -> 5.9159244 | AF64: =+A64 -> 31412 | AG64: =+AD64 -> 5.9159244 | AS64: =A64 -> 31412
A65: 31502 | B65: -0.63 | C65: 4.95 | D65: -0.39 | E65: 1.76 | F65: NaN | G65: 2.19 | H65: -0.84 | I65: -2.48 | J65: NaN | K65: NaN | L65: 2.44 | M65: NaN | N65: NaN | O65: NaN | P65: NaN | Q65: NaN | R65: NaN | S65: NaN | T65: NaN | U65: NaN | V65: 5.1987007 | W65: =+(G65-E65)*4 -> 1.72 | Y65: 1.2239614 | Z65: 5.2647753 | AC65: 27575 | AD65: =+V65 -> 5.1987007 | AF65: =+A65 -> 31502 | AG65: =+AD65 -> 5.1987007 | AS65: =A65 -> 31502
A66: 31593 | B66: 1.55 | C66: 4.78 | D66: 0.22 | E66: 1.3 | F66: NaN | G66: 2.01 | H66: 0.8 | I66: 1.99 | J66: NaN | K66: NaN | L66: 2.15 | M66: NaN | N66: NaN | O66: NaN | P66: NaN | Q66: NaN | R66: NaN | S66: NaN | T66: NaN | U66: NaN | V66: 5.2075525 | W66: =+(G66-E66)*4 -> 2.84 | Y66: 1.3749519 | Z66: 5.0448919 | AC66: 27667 | AD66: =+V66 -> 5.2075525 | AF66: =+A66 -> 31593 | AG66: =+AD66 -> 5.2075525 | AS66: =A66 -> 31593
A67: 31685 | B67: 0.18 | C67: 4.7 | D67: 0.12 | E67: 1.14 | F67: NaN | G67: 1.94 | H67: -0.17 | I67: 0.36 | J67: NaN | K67: NaN | L67: 2.1 | M67: NaN | N67: NaN | O67: NaN | P67: NaN | Q67: NaN | R67: NaN | S67: NaN | T67: NaN | U67: NaN | V67: 4.8244061 | W67: =+(G67-E67)*4 -> 3.2 | Y67: 1.2983166 | Z67: 4.8969846 | AC67: 27759 | AD67: =+V67 -> 4.8244061 | AF67: =+A67 -> 31685 | AG67: =+AD67 -> 4.8244061 | AS67: =A67 -> 31685
A68: 31777 | B68: -0.16 | C68: 4.67 | D68: 0.14 | E68: 0.85 | F68: NaN | G68: 1.97 | H68: 0.5 | I68: 0.57 | J68: NaN | K68: NaN | L68: 2.12 | M68: NaN | N68: NaN | O68: NaN | P68: NaN | Q68: NaN | R68: NaN | S68: NaN | T68: NaN | U68: NaN | V68: 4.7220469 | W68: =+(G68-E68)*4 -> 4.48 | Y68: 1.2102238 | Z68: 5.036552 | AC68: 27850 | AD68: =+V68 -> 4.7220469 | AF68: =+A68 -> 31777 | AG68: =+AD68 -> 4.7220469 | AS68: =A68 -> 31777
A69: 31867 | B69: -0.73 | C69: 4.73 | D69: 0.11 | E69: 0.84 | F69: NaN | G69: 2.03 | H69: -0.22 | I69: -1.82 | J69: NaN | K69: NaN | L69: 2.12 | M69: NaN | N69: NaN | O69: NaN | P69: NaN | Q69: NaN | R69: NaN | S69: NaN | T69: NaN | U69: NaN | V69: 5.0143179 | W69: =+(G69-E69)*4 -> 4.76 | Y69: 1.1729481 | Z69: 5.0312545 | AC69: 27941 | AD69: =+V69 -> 5.0143179 | AF69: =+A69 -> 31867 | AG69: =+AD69 -> 5.0143179 | AS69: =A69 -> 31867
A70: 31958 | B70: 1.36 | C70: 4.76 | D70: 0.96 | E70: 0.84 | F70: NaN | G70: 2.11 | H70: 1.55 | I70: 2.92 | J70: NaN | K70: NaN | L70: 2.17 | M70: NaN | N70: NaN | O70: NaN | P70: NaN | Q70: NaN | R70: NaN | S70: NaN | T70: NaN | U70: NaN | V70: 5.318176 | W70: =+(G70-E70)*4 -> 5.08 | Y70: 1.4883935 | Z70: 5.3521411 | AC70: 28033 | AD70: =+V70 -> 5.318176 | AF70: =+A70 -> 31958 | AG70: =+AD70 -> 5.318176 | AS70: =A70 -> 31958
A71: 32050 | B71: 0.82 | C71: 4.73 | D71: 0.61 | E71: 0.69 | F71: NaN | G71: 2.12 | H71: 0.75 | I71: 2.01 | J71: NaN | K71: NaN | L71: 2.37 | M71: NaN | N71: NaN | O71: NaN | P71: NaN | Q71: NaN | R71: NaN | S71: NaN | T71: NaN | U71: NaN | V71: 5.7226882 | W71: =+(G71-E71)*4 -> 5.72 | Y71: 1.5836338 | Z71: 5.4449257 | AC71: 28125 | AD71: =+V71 -> 5.7226882 | AF71: =+A71 -> 32050 | AG71: =+AD71 -> 5.7226882 | AS71: =A71 -> 32050
A72: 32142 | B72: 1.09 | C72: 4.68 | D72: 0.23 | E72: 1.23 | F72: NaN | G72: 2.11 | H72: 0.53 | I72: 1.51 | J72: NaN | K72: NaN | L72: 2.4 | M72: NaN | N72: NaN | O72: NaN | P72: NaN | Q72: NaN | R72: NaN | S72: NaN | T72: NaN | U72: NaN | V72: 5.8040639 | W72: =+(G72-E72)*4 -> 3.52 | Y72: 1.667646 | Z72: 5.3824644 | AC72: 28215 | AD72: =+V72 -> 5.8040639 | AF72: =+A72 -> 32142 | AG72: =+AD72 -> 5.8040639 | AS72: =A72 -> 32142
A73: 32233 | B73: 0.18 | C73: 4.58 | D73: 0.4 | E73: 0.95 | F73: 0.57 | G73: 1.86 | H73: -0.58 | I73: 1.05 | J73: NaN | K73: NaN | L73: 2.25 | M73: NaN | N73: NaN | O73: NaN | P73: NaN | Q73: NaN | R73: NaN | S73: NaN | T73: NaN | U73: NaN | V73: 5.4987128 | W73: =+(G73-E73)*4 -> 3.64 | X73: =+(G73-F73)*4 -> 5.16 | Y73: 1.6047869 | Z73: 5.0438207 | AC73: 28306 | AD73: =+V73 -> 5.4987128 | AF73: =+A73 -> 32233 | AG73: =+AD73 -> 5.4987128 | AS73: =A73 -> 32233
A74: 32324 | B74: 0.62 | C74: 4.49 | D74: 0.23 | E74: 1.07 | F74: 0.61 | G74: 1.82 | H74: 0.39 | I74: 1.64 | J74: NaN | K74: NaN | L74: 2.22 | M74: NaN | N74: NaN | O74: NaN | P74: NaN | Q74: NaN | R74: NaN | S74: NaN | T74: NaN | U74: NaN | V74: 4.6944193 | W74: =+(G74-E74)*4 -> 3 | X74: =+(G74-F74)*4 -> 4.84 | Y74: 1.6694676 | Z74: 5.0689868 | AC74: 28398 | AD74: =+V74 -> 4.6944193 | AF74: =+A74 -> 32324 | AG74: =+AD74 -> 4.6944193 | AS74: =A74 -> 32324
A75: 32416 | B75: 1.08 | C75: 4.44 | D75: 0.46 | E75: 0.93 | F75: 0.73 | G75: 1.99 | H75: 1.28 | I75: 1.84 | J75: NaN | K75: NaN | L75: 2.26 | M75: NaN | N75: NaN | O75: NaN | P75: NaN | Q75: NaN | R75: NaN | S75: NaN | T75: NaN | U75: NaN | V75: 4.4784821 | W75: =+(G75-E75)*4 -> 4.24 | X75: =+(G75-F75)*4 -> 5.04 | Y75: 1.8614584 | Z75: 5.2338877 | AC75: 28490 | AD75: =+V75 -> 4.4784821 | AF75: =+A75 -> 32416 | AG75: =+AD75 -> 4.4784821 | AS75: =A75 -> 32416
A76: 32508 | B76: 0.82 | C76: 4.42 | D76: 0.09 | E76: 1.31 | F76: 0.84 | G76: 2.12 | H76: 0.39 | I76: 1.38 | J76: NaN | K76: NaN | L76: 2.25 | M76: NaN | N76: NaN | O76: NaN | P76: NaN | Q76: NaN | R76: NaN | S76: NaN | T76: NaN | U76: NaN | V76: 5.1119031 | W76: =+(G76-E76)*4 -> 3.24 | X76: =+(G76-F76)*4 -> 5.12 | Y76: 1.9518661 | Z76: 5.178072 | AC76: 28580 | AD76: =+V76 -> 5.1119031 | AF76: =+A76 -> 32508 | AG76: =+AD76 -> 5.1119031 | AS76: =A76 -> 32508
A77: 32598 | B77: 0.83 | C77: 4.37 | D77: 0.7 | E77: 1.17 | F77: 0.86 | G77: 2.38 | H77: 0.63 | I77: 2.15 | J77: NaN | K77: NaN | L77: 2.35 | M77: NaN | N77: NaN | O77: NaN | P77: NaN | Q77: NaN | R77: NaN | S77: NaN | T77: NaN | U77: NaN | V77: 5.4495343 | W77: =+(G77-E77)*4 -> 4.84 | X77: =+(G77-F77)*4 -> 6.08 | Y77: 2.0873396 | Z77: 5.417534 | AC77: 28671 | AD77: =+V77 -> 5.4495343 | AF77: =+A77 -> 32598 | AG77: =+AD77 -> 5.4495343 | AS77: =A77 -> 32598
A78: 32689 | B78: 0.67 | C78: 4.25 | D78: 0.25 | E78: 0.9 | F78: 0.96 | G78: 2.42 | H78: 0.87 | I78: 1.02 | J78: NaN | K78: NaN | L78: 2.41 | M78: NaN | N78: NaN | O78: NaN | P78: NaN | Q78: NaN | R78: NaN | S78: NaN | T78: NaN | U78: NaN | V78: 6.5483177 | W78: =+(G78-E78)*4 -> 6.08 | X78: =+(G78-F78)*4 -> 5.84 | Y78: 2.206842 | Z78: 5.4176939 | AC78: 28763 | AD78: =+V78 -> 6.5483177 | AF78: =+A78 -> 32689 | AG78: =+AD78 -> 6.5483177 | AS78: =A78 -> 32689
A79: 32781 | B79: 0.21 | C79: 4.01 | D79: 0.55 | E79: 1.02 | F79: 0.8 | G79: 2.53 | H79: 0.77 | I79: -0.1 | J79: NaN | K79: NaN | L79: 2.4 | M79: NaN | N79: NaN | O79: NaN | P79: NaN | Q79: NaN | R79: NaN | S79: NaN | T79: NaN | U79: NaN | V79: 6.7214533 | W79: =+(G79-E79)*4 -> 6.04 | X79: =+(G79-F79)*4 -> 6.92 | Y79: 2.1521802 | Z79: 5.4347124 | AC79: 28855 | AD79: =+V79 -> 6.7214533 | AF79: =+A79 -> 32781 | AG79: =+AD79 -> 6.7214533 | AS79: =A79 -> 32781
A80: 32873 | B80: 0.48 | C80: 3.66 | D80: 0.18 | E80: 1.38 | F80: 0.95 | G80: 2.77 | H80: 0.1 | I80: 1.69 | J80: NaN | K80: NaN | L80: 2.52 | M80: NaN | N80: NaN | O80: NaN | P80: NaN | Q80: NaN | R80: NaN | S80: NaN | T80: NaN | U80: NaN | V80: 7.2250458 | W80: =+(G80-E80)*4 -> 5.56 | X80: =+(G80-F80)*4 -> 7.28 | Y80: 2.3003108 | Z80: 5.601554 | AC80: 28945 | AD80: =+V80 -> 7.2250458 | AF80: =+A80 -> 32873 | AG80: =+AD80 -> 7.2250458 | AS80: =A80 -> 32873
A81: 32963 | B81: 0.87 | C81: 3.26 | D81: 0.93 | E81: 1.36 | F81: 1 | G81: 2.81 | H81: -0.03 | I81: 2.49 | J81: NaN | K81: NaN | L81: 2.7 | M81: NaN | N81: NaN | O81: NaN | P81: NaN | Q81: NaN | R81: NaN | S81: NaN | T81: NaN | U81: NaN | V81: 7.8923922 | W81: =+(G81-E81)*4 -> 5.8 | X81: =+(G81-F81)*4 -> 7.24 | Y81: 2.4910331 | Z81: 5.711308 | AC81: 29036 | AD81: =+V81 -> 7.8923922 | AF81: =+A81 -> 32963 | AG81: =+AD81 -> 7.8923922 | AS81: =A81 -> 32963
A82: 33054 | B82: 0.11 | C82: 2.98 | D82: 0.54 | E82: 1.47 | F82: 0.85 | G82: 2.65 | H82: -0.06 | I82: -1 | J82: NaN | K82: NaN | L82: 2.7 | M82: NaN | N82: NaN | O82: NaN | P82: NaN | Q82: NaN | R82: NaN | S82: NaN | T82: NaN | U82: NaN | V82: 8.0288857 | W82: =+(G82-E82)*4 -> 4.72 | X82: =+(G82-F82)*4 -> 7.2 | Y82: 2.410006 | Z82: 5.4739371 | AC82: 29128 | AD82: =+V82 -> 8.0288857 | AF82: =+A82 -> 33054 | AG82: =+AD82 -> 8.0288857 | AS82: =A82 -> 33054
A83: 33146 | B83: 0.59 | C83: 2.89 | D83: 0.54 | E83: 0.84 | F83: 0.57 | G83: 2.63 | H83: 0.38 | I83: -0.03 | J83: NaN | K83: NaN | L83: 2.72 | M83: NaN | N83: NaN | O83: NaN | P83: NaN | Q83: NaN | R83: NaN | S83: NaN | T83: NaN | U83: NaN | V83: 7.4660664 | W83: =+(G83-E83)*4 -> 7.16 | X83: =+(G83-F83)*4 -> 8.24 | Y83: 2.4505956 | Z83: 5.5227118 | AC83: 29220 | AD83: =+V83 -> 7.4660664 | AF83: =+A83 -> 33146 | AG83: =+AD83 -> 7.4660664 | AS83: =A83 -> 33146
A84: 33238 | B84: 0.13 | C84: 2.92 | D84: 0.65 | E84: 1.19 | F84: 1.13 | G84: 2.76 | H84: 0.69 | I84: 0.14 | J84: NaN | K84: NaN | L84: 2.74 | M84: NaN | N84: NaN | O84: NaN | P84: NaN | Q84: NaN | R84: NaN | S84: NaN | T84: NaN | U84: NaN | V84: 7.7820674 | W84: =+(G84-E84)*4 -> 6.28 | X84: =+(G84-F84)*4 -> 6.52 | Y84: 2.5527806 | Z84: 5.629574 | AC84: 29311 | AD84: =+V84 -> 7.7820674 | AF84: =+A84 -> 33238 | AG84: =+AD84 -> 7.7820674 | AS84: =A84 -> 33238
... A111: 35703 | B111: 0.57 | C111: 1.13 | D111: 0.25 | E111: 0.18 | F111: 0.32 | G111: 1.07 | H111: 0.52 | I111: -0.82 | J111: NaN | K111: NaN | L111: 1.45 | M111: NaN | N111: NaN | O111: NaN | P111: NaN | Q111: NaN | R111: NaN | S111: NaN | T111: NaN | U111: NaN | V111: 3.05401 | W111: =+(G111-E111)*4 -> 3.56 | X111: =+(G111-F111)*4 -> 3 | Y111: 2.1439408 | Z111: 2.1654905 | AC111: 31777 | AD111: =+V111 -> 3.05401 | AF111: =+A111 -> 35703 | AG111: =+AD111 -> 3.05401 | AS111: =A111 -> 35703
A112: 35795 | B112: 0.83 | C112: 1.17 | D112: -0.12 | E112: 0.55 | F112: 0.32 | G112: 1.1 | H112: 0.82 | I112: 1.37 | J112: 1.57 | K112: NaN | L112: 1.4 | M112: NaN | N112: NaN | O112: NaN | P112: NaN | Q112: NaN | R112: NaN | S112: NaN | T112: NaN | U112: NaN | V112: 2.7482625 | W112: =+(G112-E112)*4 -> 2.2 | X112: =+(G112-F112)*4 -> 3.12 | Y112: 2.2262569 | Z112: 2.0916898 | AC112: 31867 | AD112: =+V112 -> 2.7482625 | AF112: =+A112 -> 35795 | AG112: =+AD112 -> 2.7482625 | AS112: =A112 -> 35795
A113: 35885 | B113: 0.3 | C113: 1.08 | D113: 0.26 | E113: -0.26 | F113: 0.34 | G113: 1.05 | H113: -0.02 | I113: 1.7 | J113: 1.45 | K113: NaN | L113: 1.28 | M113: NaN | N113: NaN | O113: NaN | P113: NaN | Q113: NaN | R113: NaN | S113: NaN | T113: NaN | U113: NaN | V113: 2.6709204 | W113: =+(G113-E113)*4 -> 5.24 | X113: =+(G113-F113)*4 -> 2.84 | Y113: 2.1257695 | Z113: 1.8397229 | AC113: 31958 | AD113: =+V113 -> 2.6709204 | AF113: =+A113 -> 35885 | AG113: =+AD113 -> 2.6709204 | AS113: =A113 -> 35885
A114: 35976 | B114: 0 | C114: 1.38 | D114: 0.02 | E114: 0.54 | F114: 0.44 | G114: 1.02 | H114: -0.03 | I114: -0.49 | J114: 1.36 | K114: NaN | L114: 1.25 | M114: -3.0577898 | N114: NaN | O114: NaN | P114: NaN | Q114: NaN | R114: NaN | S114: NaN | T114: NaN | U114: NaN | V114: 2.7025696 | W114: =+(G114-E114)*4 -> 1.92 | X114: =+(G114-F114)*4 -> 2.32 | Y114: 2.2107502 | Z114: 1.6725378 | AC114: 32050 | AD114: =+V114 -> 2.7025696 | AF114: =+A114 -> 35976 | AG114: =+AD114 -> 2.7025696 | AS114: =A114 -> 35976
A115: 36068 | B115: 0.13 | C115: 1.64 | D115: -0.02 | E115: 0.47 | F115: 0.33 | G115: 0.99 | H115: 0.6 | I115: 1.26 | J115: 1.78 | K115: NaN | L115: 1.14 | M115: -1.3258551 | N115: NaN | O115: NaN | P115: NaN | Q115: NaN | R115: NaN | S115: NaN | T115: NaN | U115: NaN | V115: 2.2314227 | W115: =+(G115-E115)*4 -> 2.08 | X115: =+(G115-F115)*4 -> 2.64 | Y115: 2.1336152 | Z115: 1.6830584 | AC115: 32142 | AD115: =+V115 -> 2.2314227 | AF115: =+A115 -> 36068 | AG115: =+AD115 -> 2.2314227 | AS115: =A115 -> 36068
A116: 36160 | B116: 0.04 | C116: 1.3 | D116: -0.45 | E116: 1.02 | F116: 0.27 | G116: 0.92 | H116: 0.3 | I116: 0.36 | J116: 2.13 | K116: NaN | L116: 1.04 | M116: 2.4829315 | N116: NaN | O116: NaN | P116: NaN | Q116: NaN | R116: NaN | S116: NaN | T116: NaN | U116: NaN | V116: 2.1017807 | W116: =+(G116-E116)*4 -> -0.4 | X116: =+(G116-F116)*4 -> 2.6 | Y116: 1.9493399 | Z116: 1.4724572 | AC116: 32233 | AD116: =+V116 -> 2.1017807 | AF116: =+A116 -> 36160 | AG116: =+AD116 -> 2.1017807 | AS116: =A116 -> 36160
A117: 36250 | B117: 0.84 | C117: 1.23 | D117: -0.06 | E117: 0.23 | F117: 0.17 | G117: 0.78 | H117: 0.48 | I117: 1.37 | J117: 1.86 | K117: 0.48 | L117: 1 | M117: 4.1108515 | N117: NaN | O117: NaN | P117: NaN | Q117: NaN | R117: NaN | S117: NaN | T117: NaN | U117: NaN | V117: 1.6371137 | W117: =+(G117-E117)*4 -> 2.2 | X117: =+(G117-F117)*4 -> 2.44 | Y117: 2.0351751 | Z117: 1.2728381 | AC117: 32324 | AD117: =+V117 -> 1.6371137 | AF117: =+A117 -> 36250 | AG117: =+AD117 -> 1.6371137 | AS117: =A117 -> 36250
A118: 36341 | B118: 0.19 | C118: 2.01 | D118: 0.74 | E118: 0.21 | F118: 0.27 | G118: 0.66 | H118: 0.7 | I118: 1.47 | J118: 1.7 | K118: NaN | L118: 1.06 | M118: -2.074513 | N118: NaN | O118: NaN | P118: NaN | Q118: NaN | R118: NaN | S118: NaN | T118: NaN | U118: NaN | V118: 1.3894528 | W118: =+(G118-E118)*4 -> 1.8 | X118: =+(G118-F118)*4 -> 1.56 | Y118: 1.9411904 | Z118: 1.2421784 | AC118: 32416 | AD118: =+V118 -> 1.3894528 | AF118: =+A118 -> 36341 | AG118: =+AD118 -> 1.3894528 | AS118: =A118 -> 36341
A119: 36433 | B119: 0.93 | C119: 1.56 | D119: 0.42 | E119: 0.09 | F119: 0.26 | G119: 0.65 | H119: 0.95 | I119: 1.54 | J119: 1.56 | K119: NaN | L119: 1.26 | M119: 4.0050909 | N119: NaN | O119: NaN | P119: NaN | Q119: NaN | R119: NaN | S119: NaN | T119: NaN | U119: NaN | V119: 0.99789865 | W119: =+(G119-E119)*4 -> 2.24 | X119: =+(G119-F119)*4 -> 1.56 | Y119: 2.0698398 | Z119: 1.2539379 | AC119: 32508 | AD119: =+V119 -> 0.99789865 | AF119: =+A119 -> 36433 | AG119: =+AD119 -> 0.99789865 | AS119: =A119 -> 36433
A120: 36525 | B120: 0.77 | C120: 1.88 | D120: 0.51 | E120: 0.31 | F120: 0.3 | G120: 0.78 | H120: 0.62 | I120: 0.53 | J120: 1.46 | K120: NaN | L120: 1.33 | M120: 0.50876453 | N120: NaN | O120: NaN | P120: NaN | Q120: NaN | R120: NaN | S120: NaN | T120: NaN | U120: NaN | V120: 1.0390893 | W120: =+(G120-E120)*4 -> 1.88 | X120: =+(G120-F120)*4 -> 1.92 | Y120: 2.1598827 | Z120: 1.2036688 | AC120: 32598 | AD120: =+V120 -> 1.0390893 | AF120: =+A120 -> 36525 | AG120: =+AD120 -> 1.0390893 | AS120: =A120 -> 36525
A121: 36616 | B121: 0.82 | C121: 2.04 | D121: 0.25 | E121: 0.46 | F121: 0.19 | G121: 0.84 | H121: 0.76 | I121: 2.55 | J121: 1.34 | K121: 0.45 | L121: 1.4 | M121: 2.3880325 | N121: NaN | O121: 0.09 | P121: NaN | Q121: NaN | R121: NaN | S121: NaN | T121: NaN | U121: NaN | V121: 1.4873655 | W121: =+(G121-E121)*4 -> 1.52 | X121: =+(G121-F121)*4 -> 2.6 | Y121: 2.2425751 | Z121: 1.1843866 | AC121: 32689 | AD121: =+V121 -> 1.4873655 | AF121: =+A121 -> 36616 | AG121: =+AD121 -> 1.4873655 | AS121: =A121 -> 36616
A122: 36707 | B122: 0.59 | C122: 2.03 | D122: 0.23 | E122: 0.24 | F122: 0.18 | G122: 1.03 | H122: 0.7 | I122: -0.1 | J122: 1.64 | K122: NaN | L122: 1.36 | M122: 0.90464363 | N122: NaN | O122: 0.11 | P122: NaN | Q122: NaN | R122: NaN | S122: NaN | T122: NaN | U122: NaN | V122: 1.7767588 | W122: =+(G122-E122)*4 -> 3.16 | X122: =+(G122-F122)*4 -> 3.4 | Y122: 2.2381216 | Z122: 1.1774776 | AC122: 32781 | AD122: =+V122 -> 1.7767588 | AF122: =+A122 -> 36707 | AG122: =+AD122 -> 1.7767588 | AS122: =A122 -> 36707
A123: 36799 | B123: 0.36 | C123: 2.04 | D123: 0.33 | E123: 0.53 | F123: 0.32 | G123: 1.14 | H123: 0.28 | I123: 0.46 | J123: 1.9 | K123: NaN | L123: 1.36 | M123: 0.27598946 | N123: NaN | O123: 0.12 | P123: NaN | Q123: NaN | R123: NaN | S123: NaN | T123: NaN | U123: NaN | V123: 2.5211067 | W123: =+(G123-E123)*4 -> 2.44 | X123: =+(G123-F123)*4 -> 3.28 | Y123: 2.4166369 | Z123: 1.2345947 | AC123: 32873 | AD123: =+V123 -> 2.5211067 | AF123: =+A123 -> 36799 | AG123: =+AD123 -> 2.5211067 | AS123: =A123 -> 36799
A124: 36891 | B124: 0.29 | C124: 2.25 | D124: 0.09 | E124: 0.59 | F124: 0.41 | G124: 1.23 | H124: 0.27 | I124: 0.56 | J124: 2.62 | K124: NaN | L124: 1.32 | M124: 0.079371181 | N124: NaN | O124: 0.14 | P124: NaN | Q124: NaN | R124: NaN | S124: NaN | T124: NaN | U124: NaN | V124: 2.7773832 | W124: =+(G124-E124)*4 -> 2.56 | X124: =+(G124-F124)*4 -> 3.28 | Y124: 2.4386474 | Z124: 1.3752398 | AC124: 32963 | AD124: =+V124 -> 2.7773832 | AF124: =+A124 -> 36891 | AG124: =+AD124 -> 2.7773832 | AS124: =A124 -> 36891
A125: 36981 | B125: 1.07 | C125: 2.44 | D125: -0.2 | E125: 0.74 | F125: 0.29 | G125: 1.2 | H125: 0.58 | I125: 0.69 | J125: 2.58 | K125: 0.45 | L125: 1.25 | M125: 3.9475743 | N125: NaN | O125: 0.11 | P125: NaN | Q125: NaN | R125: NaN | S125: NaN | T125: NaN | U125: NaN | V125: 3.0232499 | W125: =+(G125-E125)*4 -> 1.84 | X125: =+(G125-F125)*4 -> 3.64 | Y125: 2.6164489 | Z125: 1.3098732 | AC125: 33054 | AD125: =+V125 -> 3.0232499 | AF125: =+A125 -> 36981 | AG125: =+AD125 -> 3.0232499 | AS125: =A125 -> 36981
A126: 37072 | B126: 0 | C126: 2.12 | D126: 0.06 | E126: 0.64 | F126: 0.55 | G126: 1.17 | H126: 0.33 | I126: -1.21 | J126: 2.78 | K126: 0.45 | L126: 1.3 | M126: 0.99657234 | N126: NaN | O126: 0.09 | P126: NaN | Q126: NaN | R126: NaN | S126: NaN | T126: NaN | U126: NaN | V126: 2.9124853 | W126: =+(G126-E126)*4 -> 2.12 | X126: =+(G126-F126)*4 -> 2.48 | Y126: 2.8758428 | Z126: 1.3249628 | AC126: 33146 | AD126: =+V126 -> 2.9124853 | AF126: =+A126 -> 37072 | AG126: =+AD126 -> 2.9124853 | AS126: =A126 -> 37072
A127: 37164 | B127: 0.01 | C127: 1.98 | D127: 0.06 | E127: 0.6 | F127: 0.64 | G127: 1.09 | H127: -0.13 | I127: -1.58 | J127: 3.2 | K127: 0.45 | L127: 1.28 | M127: 0.81998426 | N127: NaN | O127: 0.1 | P127: NaN | Q127: NaN | R127: NaN | S127: NaN | T127: NaN | U127: NaN | V127: 2.7241392 | W127: =+(G127-E127)*4 -> 1.96 | X127: =+(G127-F127)*4 -> 1.8 | Y127: 2.6199747 | Z127: 1.3910176 | AC127: 33238 | AD127: =+V127 -> 2.7241392 | AF127: =+A127 -> 37164 | AG127: =+AD127 -> 2.7241392 | AS127: =A127 -> 37164
A128: 37256 | B128: -0.3 | C128: 1.81 | D128: -0.03 | E128: 0.8 | F128: 0.61 | G128: 0.88 | H128: -0.29 | I128: -0.43 | J128: 3.6 | K128: 0.45 | L128: 1.2 | M128: -0.16012123 | N128: NaN | O128: 0.06 | P128: NaN | Q128: NaN | R128: NaN | S128: NaN | T128: NaN | U128: NaN | V128: 2.3909845 | W128: =+(G128-E128)*4 -> 0.32 | X128: =+(G128-F128)*4 -> 1.08 | Y128: 2.5371678 | Z128: 1.4806557 | AC128: 33328 | AD128: =+V128 -> 2.3909845 | AF128: =+A128 -> 37256 | AG128: =+AD128 -> 2.3909845 | AS128: =A128 -> 37256
A129: 37346 | B129: -0.16 | C129: 1.4 | D129: -0.16 | E129: 0.68 | F129: 0.78 | G129: 0.84 | H129: -0.34 | I129: -1.47 | J129: 3.03 | K129: 0.48 | L129: 1.28 | M129: 0.15720301 | N129: NaN | O129: -0.06 | P129: NaN | Q129: NaN | R129: NaN | S129: NaN | T129: NaN | U129: NaN | V129: 1.5546034 | W129: =+(G129-E129)*4 -> 0.64 | X129: =+(G129-F129)*4 -> 0.24 | Y129: 2.6352632 | Z129: 1.581495 | AC129: 33419 | AD129: =+V129 -> 1.5546034 | AF129: =+A129 -> 37346 | AG129: =+AD129 -> 1.5546034 | AS129: =A129 -> 37346
A130: 37437 | B130: 0.25 | C130: 1.31 | D130: 0.27 | E130: 0.36 | F130: 0.48 | G130: 0.84 | H130: -0.09 | I130: -0.44 | J130: 2.76 | K130: 0.48 | L130: 1.31 | M130: 0.74408785 | N130: 0.7 | O130: -0.1 | P130: NaN | Q130: NaN | R130: NaN | S130: NaN | T130: NaN | U130: NaN | V130: 1.1905865 | W130: =+(G130-E130)*4 -> 1.92 | X130: =+(G130-F130)*4 -> 1.44 | Y130: 2.4166503 | Z130: 1.6174713 | AC130: 33511 | AD130: =+V130 -> 1.1905865 | AF130: =+A130 -> 37437 | AG130: =+AD130 -> 1.1905865 | AS130: =A130 -> 37437
A131: 37529 | B131: 0.26 | C131: 1.09 | D131: 0.05 | E131: 0.68 | F131: 0.55 | G131: 0.84 | H131: 0.05 | I131: -0.38 | J131: 3.02 | K131: 0.48 | L131: 1.19 | M131: 0.16933724 | N131: 0.16 | O131: 0.04 | P131: NaN | Q131: NaN | R131: NaN | S131: NaN | T131: NaN | U131: NaN | V131: 1.4739675 | W131: =+(G131-E131)*4 -> 0.64 | X131: =+(G131-F131)*4 -> 1.16 | Y131: 2.3442732 | Z131: 1.3548984 | AC131: 33603 | AD131: =+V131 -> 1.4739675 | AF131: =+A131 -> 37529 | AG131: =+AD131 -> 1.4739675 | AS131: =A131 -> 37529
A132: 37621 | B132: 0 | C132: 0.88 | D132: 0.17 | E132: 0.46 | F132: 0.45 | G132: 0.79 | H132: 0.45 | I132: 0.44 | J132: 2.88 | K132: 0.48 | L132: 1.14 | M132: 0.70248106 | N132: -0.36 | O132: 0.09 | P132: NaN | Q132: NaN | R132: NaN | S132: NaN | T132: NaN | U132: NaN | V132: 1.3281434 | W132: =+(G132-E132)*4 -> 1.32 | X132: =+(G132-F132)*4 -> 1.36 | Y132: 2.2327294 | Z132: 1.1559941 | AC132: 33694 | AD132: =+V132 -> 1.3281434 | AF132: =+A132 -> 37621 | AG132: =+AD132 -> 1.3281434 | AS132: =A132 -> 37621
A133: 37711 | B133: -0.45 | C133: 0.79 | D133: -0.26 | E133: 0.62 | F133: 0.53 | G133: 0.69 | H133: 0.22 | I133: -0.79 | J133: 2.1 | K133: 0.48 | L133: 1.04 | M133: -2.6613263 | N133: -0.18 | O133: 0.16 | P133: NaN | Q133: NaN | R133: NaN | S133: NaN | T133: NaN | U133: NaN | V133: 1.2095964 | W133: =+(G133-E133)*4 -> 0.28 | X133: =+(G133-F133)*4 -> 0.64 | Y133: 2.0798214 | Z133: 0.61639985 | AC133: 33785 | AD133: =+V133 -> 1.2095964 | AF133: =+A133 -> 37711 | AG133: =+AD133 -> 1.2095964 | AS133: =A133 -> 37711
A134: 37802 | B134: -0.16 | C134: 0.52 | D134: -0.01 | E134: 0.59 | F134: 0.48 | G134: 0.61 | H134: -0.3 | I134: -0.67 | J134: 1.54 | K134: 0.48 | L134: 0.99 | M134: -0.78390576 | N134: -0.65 | O134: 0.16 | P134: NaN | Q134: NaN | R134: NaN | S134: NaN | T134: NaN | U134: NaN | V134: 0.72374578 | W134: =+(G134-E134)*4 -> 0.08 | X134: =+(G134-F134)*4 -> 0.52 | Y134: 2.0750262 | Z134: 0.36560821 | AC134: 33877 | AD134: =+V134 -> 0.72374578 | AF134: =+A134 -> 37802 | AG134: =+AD134 -> 0.72374578 | AS134: =A134 -> 37802
A135: 37894 | B135: 0.51 | C135: 0.57 | D135: 0.58 | E135: 0.63 | F135: 0.41 | G135: 0.53 | H135: 0.3 | I135: 1.25 | J135: 1.21 | K135: 0.48 | L135: 1.04 | M135: 0.8827365 | N135: 1.06 | O135: 0.05 | P135: NaN | Q135: NaN | R135: NaN | S135: NaN | T135: NaN | U135: NaN | V135: 0.44825999 | W135: =+(G135-E135)*4 -> -0.4 | X135: =+(G135-F135)*4 -> 0.48 | Y135: 2.1472237 | Z135: 0.5479402 | AC135: 33969 | AD135: =+V135 -> 0.44825999 | AF135: =+A135 -> 37894 | AG135: =+AD135 -> 0.44825999 | AS135: =A135 -> 37894
A136: 37986 | B136: 0.48 | C136: 0.66 | D136: -0.16 | E136: 0.24 | F136: 0.48 | G136: 0.53 | H136: 0.4 | I136: 0.49 | J136: 0.96 | K136: 0.48 | L136: 1.09 | M136: 0.78001171 | N136: 0.4 | O136: -0.07 | P136: NaN | Q136: NaN | R136: NaN | S136: NaN | T136: NaN | U136: NaN | V136: 0.25215831 | W136: =+(G136-E136)*4 -> 1.16 | X136: =+(G136-F136)*4 -> 0.2 | Y136: 2.1589359 | Z136: 0.692427 | AC136: 34059 | AD136: =+V136 -> 0.25215831 | AF136: =+A136 -> 37986 | AG136: =+AD136 -> 0.25215831 | AS136: =A136 -> 37986
A137: 38077 | B137: 0.42 | C137: 0.45 | D137: 0.25 | E137: 0.46 | F137: 0.64 | G137: 0.52 | H137: 0.45 | I137: 0.55 | J137: 0.93 | K137: 0.48 | L137: 1.04 | M137: 0.62234895 | N137: 0.87 | O137: -0.08 | P137: NaN | Q137: NaN | R137: NaN | S137: NaN | T137: NaN | U137: NaN | V137: 0.33950473 | W137: =+(G137-E137)*4 -> 0.24 | X137: =+(G137-F137)*4 -> -0.48 | Y137: 2.1229446 | Z137: 0.72612137 | AC137: 34150 | AD137: =+V137 -> 0.33950473 | AF137: =+A137 -> 38077 | AG137: =+AD137 -> 0.33950473 | AS137: =A137 -> 38077
A138: 38168 | B138: 0.45 | C138: 0.6 | D138: -0.04 | E138: 0.62 | F138: 0.57 | G138: 0.52 | H138: 0.16 | I138: 0.81 | J138: 0.88 | K138: 0.48 | L138: 1.09 | M138: 2.5864402 | N138: 0.08 | O138: -0.19 | P138: NaN | Q138: NaN | R138: NaN | S138: NaN | T138: NaN | U138: NaN | V138: 0.2019431 | W138: =+(G138-E138)*4 -> -0.4 | X138: =+(G138-F138)*4 -> -0.2 | Y138: 2.1426969 | Z138: 0.87329972 | AC138: 34242 | AD138: =+V138 -> 0.2019431 | AF138: =+A138 -> 38168 | AG138: =+AD138 -> 0.2019431 | AS138: =A138 -> 38168
A139: 38260 | B139: 0.04 | C139: 0.46 | D139: -0.11 | E139: 0.46 | F139: 0.4 | G139: 0.52 | H139: -0.02 | I139: 0.38 | J139: 0.87 | K139: 0.48 | L139: 1.05 | M139: -1.6474789 | N139: 0.56 | O139: -0.19 | P139: NaN | Q139: NaN | R139: NaN | S139: NaN | T139: NaN | U139: NaN | V139: 0.19781737 | W139: =+(G139-E139)*4 -> 0.24 | X139: =+(G139-F139)*4 -> 0.48 | Y139: 1.9452419 | Z139: 0.8264187 | AC139: 34334 | AD139: =+V139 -> 0.19781737 | AF139: =+A139 -> 38260 | AG139: =+AD139 -> 0.19781737 | AS139: =A139 -> 38260
A140: 38352 | B140: 0.21 | C140: 0.48 | D140: -0.1 | E140: 0.58 | F140: 0.34 | G140: 0.53 | H140: 0.48 | I140: 0.22 | J140: 0.76 | K140: 0.48 | L140: 0.96 | M140: 0.72712726 | N140: 0.34 | O140: -0.12 | P140: NaN | Q140: NaN | R140: NaN | S140: NaN | T140: NaN | U140: NaN | V140: 0.27255065 | W140: =+(G140-E140)*4 -> -0.2 | X140: =+(G140-F140)*4 -> 0.76 | Y140: 1.8404336 | Z140: 0.60054521 | AC140: 34424 | AD140: =+V140 -> 0.27255065 | AF140: =+A140 -> 38352 | AG140: =+AD140 -> 0.27255065 | AS140: =A140 -> 38352
A141: 38442 | B141: 0.05 | C141: 0.31 | D141: 0.07 | E141: 0.35 | F141: 0.37 | G141: 0.53 | H141: 0.31 | I141: -0.65 | J141: 0.68 | K141: 0.48 | L141: 0.92 | M141: 2.1386717 | N141: -0.86 | O141: -0.07 | P141: NaN | Q141: NaN | R141: NaN | S141: NaN | T141: NaN | U141: NaN | V141: 0.29430714 | W141: =+(G141-E141)*4 -> 0.72 | X141: =+(G141-F141)*4 -> 0.64 | Y141: 1.7652277 | Z141: 0.34032341 | AC141: 34515 | AD141: =+V141 -> 0.29430714 | AF141: =+A141 -> 38442 | AG141: =+AD141 -> 0.29430714 | AS141: =A141 -> 38442
... A156: 39813 | B156: -1.82 | C156: 2.53 | D156: -0.03 | E156: 0.29 | F156: 0.42 | G156: 0.97 | H156: -1.56 | I156: -4.21 | J156: 5.01 | K156: 0.5 | L156: 1.04 | M156: -5.9653394 | N156: -2.69 | O156: 0.45 | P156: NaN | Q156: NaN | R156: NaN | S156: NaN | T156: NaN | U156: NaN | V156: 2.7307856 | W156: =+(G156-E156)*4 -> 2.72 | X156: =+(G156-F156)*4 -> 2.2 | Y156: 1.3712865 | Z156: -0.0043881013 | AC156: 35885 | AD156: =+V156 -> 2.7307856 | AF156: =+A156 -> 39813 | AG156: =+AD156 -> 2.7307856 | AS156: =A156 -> 39813
A157: 39903 | B157: -3.2 | C157: 0.59 | D157: -0.44 | E157: 0.37 | F157: 0.25 | G157: 0.42 | H157: -1.69 | I157: -6.47 | J157: 5.03 | K157: 0.48 | L157: 1.04 | M157: -4.5364652 | N157: -2.07 | O157: 0.39 | P157: 0.26333333 | Q157: 0.25083333 | R157: 0.25404906 | S157: 0.26166667 | T157: 0.2736387 | U157: 0.29295662 | V157: 1.918184 | W157: =+(G157-E157)*4 -> 0.2 | X157: =+(G157-F157)*4 -> 0.68 | Y157: 0.65804159 | Z157: -0.38481294 | AC157: 35976 | AD157: =+V157 -> 1.918184 | AF157: =+A157 -> 39903 | AG157: =+AD157 -> 1.918184 | AS157: =A157 -> 39903
A158: 39994 | B158: -0.14 | C158: -0.4 | D158: 0.43 | E158: 0.04 | F158: 0.3 | G158: 0.23 | H158: -0.07 | I158: -3.05 | J158: 4.24 | K158: 0.48 | L158: 1.05 | M158: 8.8832751 | N158: -0.03 | O158: 0.31 | P158: 0.18666667 | Q158: 0.1875 | R158: 0.19718905 | S158: 0.215 | T158: 0.23513583 | U158: 0.26021333 | V158: -0.056538811 | W158: =+(G158-E158)*4 -> 0.76 | X158: =+(G158-F158)*4 -> -0.28 | Y158: 0.72602799 | Z158: -0.38142541 | AC158: 36068 | AD158: =+V158 -> -0.056538811 | AF158: =+A158 -> 39994 | AG158: =+AD158 -> -0.056538811 | AS158: =A158 -> 39994
A159: 40086 | B159: 0.38 | C159: -0.8 | D159: 0.62 | E159: 0.08 | F159: 0.2 | G159: 0.13 | H159: 0.1 | I159: -0.19 | J159: 2.85 | K159: 0.5 | L159: 0.99 | M159: 1.5513997 | N159: 1.08 | O159: 0.14 | P159: 0.1075 | Q159: 0.12166667 | R159: 0.14445908 | S159: 0.17333333 | T159: 0.20501927 | U159: 0.2403875 | V159: -0.67538813 | W159: =+(G159-E159)*4 -> 0.2 | X159: =+(G159-F159)*4 -> -0.28 | Y159: 0.8070002 | Z159: -0.41900073 | AC159: 36160 | AD159: =+V159 -> -0.67538813 | AF159: =+A159 -> 40086 | AG159: =+AD159 -> -0.67538813 | AS159: =A159 -> 40086
A160: 40178 | B160: 0.4 | C160: -1.12 | D160: 0.4 | E160: 0.21 | F160: 0.22 | G160: 0.11 | H160: 0.34 | I160: -0.73 | J160: 2.06 | K160: 0.48 | L160: 0.96 | M160: -0.23200323 | N160: 0.28 | O160: 0.11 | P160: 0.10666667 | Q160: 0.12333333 | R160: 0.15181279 | S160: 0.18583333 | T160: 0.21806869 | U160: 0.25087587 | V160: -1.0948138 | W160: =+(G160-E160)*4 -> -0.4 | X160: =+(G160-F160)*4 -> -0.44 | Y160: 0.88014083 | Z160: -0.63373039 | AC160: 36250 | AD160: =+V160 -> -1.0948138 | AF160: =+A160 -> 40178 | AG160: =+AD160 -> -1.0948138 | AS160: =A160 -> 40178
A161: 40268 | B161: 0.81 | C161: -0.79 | D161: 0.25 | E161: 0.11 | F161: 0.21 | G161: 0.11 | H161: 0.9 | I161: -0.37 | J161: 1.74 | K161: 0.48 | L161: 1.02 | M161: 1.9522559 | N161: 0.44 | O161: 0.04 | P161: 0.090833333 | Q161: 0.10916667 | R161: 0.1347544 | S161: 0.16333333 | T161: 0.19016495 | U161: 0.21690588 | V161: -1.0362078 | W161: =+(G161-E161)*4 -> 0 | X161: =+(G161-F161)*4 -> -0.4 | Y161: 0.94110271 | Z161: -0.62751995 | AC161: 36341 | AD161: =+V161 -> -1.0362078 | AF161: =+A161 -> 40268 | AG161: =+AD161 -> -1.0362078 | AS161: =A161 -> 40268
A162: 40359 | B162: 0.82 | C162: -0.65 | D162: 0.52 | E162: 0.25 | F162: 0.24 | G162: 0.11 | H162: 0.49 | I162: 2.99 | J162: 1.79 | K162: 0.48 | L162: 0.96 | M162: -0.8384604 | N162: 0.89 | O162: 0.04 | P162: 0.10166667 | Q162: 0.11833333 | R162: 0.1314981 | S162: 0.14416667 | T162: 0.15810032 | U162: 0.17257065 | V162: -1.0070636 | W162: =+(G162-E162)*4 -> -0.56 | X162: =+(G162-F162)*4 -> -0.52 | Y162: 1.069073 | Z162: -0.621579 | AC162: 36433 | AD162: =+V162 -> -1.0070636 | AF162: =+A162 -> 40359 | AG162: =+AD162 -> -1.0070636 | AS162: =A162 -> 40359
A163: 40451 | B163: 0.37 | C163: -0.74 | D163: 0.02 | E163: 0.34 | F163: 0.33 | G163: 0.15 | H163: 0.32 | I163: -0.9 | J163: 1.67 | K163: 0.5 | L163: 0.88 | M163: -2.882261 | N163: 0.35 | O163: 0.05 | P163: 0.13333333 | Q163: 0.1475 | R163: 0.1604494 | S163: 0.1725 | T163: 0.18376842 | U163: 0.19455341 | V163: -1.067499 | W163: =+(G163-E163)*4 -> -0.76 | X163: =+(G163-F163)*4 -> -0.72 | Y163: 1.1481379 | Z163: -0.76714917 | AC163: 36525 | AD163: =+V163 -> -1.067499 | AF163: =+A163 -> 40451 | AG163: =+AD163 -> -1.067499 | AS163: =A163 -> 40451
A164: 40543 | B164: 0.57 | C164: -0.74 | D164: 0.27 | E164: 0.15 | F164: 0.35 | G164: 0.2 | H164: 0.76 | I164: 0.33 | J164: 1.44 | K164: 0.48 | L164: 0.93 | M164: 1.2214726 | N164: 0.88 | O164: 0.06 | P164: 0.17916667 | Q164: 0.195 | R164: 0.20780619 | S164: 0.22 | T164: 0.23305564 | U164: 0.24641983 | V164: -1.1652472 | W164: =+(G164-E164)*4 -> 0.2 | X164: =+(G164-F164)*4 -> -0.6 | Y164: 1.1296803 | Z164: -0.83258483 | AC164: 36616 | AD164: =+V164 -> -1.1652472 | AF164: =+A164 -> 40543 | AG164: =+AD164 -> -1.1652472 | AS164: =A164 -> 40543
A165: 40633 | B165: 0.99 | C165: -0.11 | D165: 0.45 | E165: 0.39 | F165: 0.45 | G165: 0.22 | H165: 0.28 | I165: 1.84 | J165: 1.3 | K165: 0.5 | L165: 1.08 | M165: 0.53895563 | N165: 0.71 | O165: 0.05 | P165: 0.20583333 | Q165: 0.23583333 | R165: 0.26485046 | S165: 0.2925 | T165: 0.3184866 | U165: 0.34356216 | V165: -0.74399331 | W165: =+(G165-E165)*4 -> -0.68 | X165: =+(G165-F165)*4 -> -0.92 | Y165: 1.3066659 | Z165: -0.62501334 | AC165: 36707 | AD165: =+V165 -> -0.74399331 | AF165: =+A165 -> 40633 | AG165: =+AD165 -> -0.74399331 | AS165: =A165 -> 40633
A166: 40724 | B166: -0.05 | C166: -0.49 | D166: 0.3 | E166: 0.21 | F166: 0.47 | G166: 0.31 | H166: 0.15 | I166: 0.05 | J166: 1.28 | K166: 0.5 | L166: 1.12 | M166: -1.1722821 | N166: 0.14 | O166: -0.01 | P166: 0.29583333 | Q166: 0.32916667 | R166: 0.35681095 | S166: 0.38083333 | T166: 0.40249786 | U166: 0.42268328 | V166: -0.85772008 | W166: =+(G166-E166)*4 -> 0.4 | X166: =+(G166-F166)*4 -> -0.64 | Y166: 1.2994991 | Z166: -0.53590421 | AC166: 36799 | AD166: =+V166 -> -0.85772008 | AF166: =+A166 -> 40724 | AG166: =+AD166 -> -0.85772008 | AS166: =A166 -> 40724
A167: 40816 | B167: -0.04 | C167: -0.7 | D167: -0.06 | E167: 0.32 | F167: 0.48 | G167: 0.35 | H167: -0.17 | I167: -0.91 | J167: 1.92 | K167: 0.5 | L167: 1.07 | M167: -0.27935922 | N167: -0.49 | O167: -0.08 | P167: 0.24916667 | Q167: 0.245 | R167: 0.24360584 | S167: 0.24416667 | T167: 0.24707524 | U167: 0.25091873 | V167: -0.4382743 | W167: =+(G167-E167)*4 -> 0.12 | X167: =+(G167-F167)*4 -> -0.52 | Y167: 1.03818 | Z167: -0.57237115 | AC167: 36891 | AD167: =+V167 -> -0.4382743 | AF167: =+A167 -> 40816 | AG167: =+AD167 -> -0.4382743 | AS167: =A167 -> 40816
A168: 40908 | B168: -0.37 | C168: -1.11 | D168: 0.25 | E168: 0.23 | F168: 0.49 | G168: 0.31 | H168: -0.18 | I168: -0.53 | J168: 2.32 | K168: 0.5 | L168: 1.05 | M168: -1.4867223 | N168: -0.31 | O168: -0.06 | P168: 0.15416667 | Q168: 0.14083333 | R168: 0.13779245 | S168: 0.13666667 | T168: 0.13809896 | U168: 0.14229167 | V168: -0.34157532 | W168: =+(G168-E168)*4 -> 0.32 | X168: =+(G168-F168)*4 -> -0.72 | Y168: 1.1106378 | Z168: -0.59858879 | AC168: 36981 | AD168: =+V168 -> -0.34157532 | AF168: =+A168 -> 40908 | AG168: =+AD168 -> -0.34157532 | AS168: =A168 -> 40908
... A200: 43830 | B200: -0.14 | C200: 1.03 | D200: -0.32 | E200: 0.52 | F200: 0.34 | G200: -0.11 | H200: -0.18 | I200: 5.16 | J200: 0.88 | K200: 0.43 | L200: 0.07 | M200: 0.13418479 | N200: -1.32 | O200: 0.08 | P200: -0.11333333 | Q200: -0.11583333 | R200: -0.11859894 | S200: -0.12083333 | T200: -0.12200278 | U200: -0.1230071 | V200: -2.1419231 | W200: =+(G200-E200)*4 -> -2.52 | X200: =+(G200-F200)*4 -> -1.8 | Y200: 0.41620908 | Z200: -1.9247404 | AC200: 39903 | AD200: =+V200 -> -2.1419231 | AF200: =+A200 -> 43830 | AG200: =+AD200 -> -2.1419231 | AS200: =A200 -> 43830
A201: 43921 | E201: 0.6 | F201: 0.12 | G201: -0.12 | J201: 1.08 | K201: 0.43 | L201: 0.07 | O201: 0.08 | P201: -0.11916667 | Q201: -0.1225 | R201: -0.12556208 | S201: -0.1275 | T201: -0.12781808 | U201: -0.12799107 | V201: -2.2390573 | W201: =+(G201-E201)*4 -> -2.88 | X201: =+(G201-F201)*4 -> -0.96 | Y201: 0.14208487 | Z201: -2.0057933 | AC201: 39994 | AD201: =+V201 -> -2.2390573 | AF201: =+A201 -> 43921 | AG201: =+AD201 -> -2.2390573 | AS201: =A201 -> 43921 | AT201: 1q20 | AU201: ="20"&RIGHT(AT201,2)&"Q"&LEFT(AT201,1) -> 2020Q1
A202: 44012 | E202: 1.1 | F202: 0.3 | G202: -0.12 | J202: 1.5 | K202: 0.43 | L202: 0.12 | O202: 0.08 | P202: -0.11666667 | Q202: -0.11916667 | R202: -0.12182175 | S202: -0.12416667 | T202: -0.1259922 | U202: -0.12764122 | V202: -2.2626273 | W202: =+(G202-E202)*4 -> -4.88 | X202: =+(G202-F202)*4 -> -1.68 | Y202: 0.13207053 | Z202: -1.9907029 | AC202: 40086 | AD202: =+V202 -> -2.2626273 | AF202: =+A202 -> 44012 | AG202: =+AD202 -> -2.2626273 | AS202: =A202 -> 44012 | AT202: 2q20 | AU202: ="20"&RIGHT(AT202,2)&"Q"&LEFT(AT202,1) -> 2020Q2
A203: 44104 | E203: -1 | F203: -0.07 | G203: -0.13 | J203: 1.17 | K203: 0.4 | L203: 0.04 | O203: 0.02 | P203: -0.11666667 | Q203: -0.12 | R203: -0.12273521 | S203: -0.125 | T203: -0.12682553 | U203: -0.12847455 | V203: -2.451332 | W203: =+(G203-E203)*4 -> 3.48 | X203: =+(G203-F203)*4 -> -0.24 | Y203: 0.14535133 | Z203: -1.9801808 | AC203: 40178 | AD203: =+V203 -> -2.451332 | AF203: =+A203 -> 44104 | AG203: =+AD203 -> -2.451332 | AS203: =A203 -> 44104 | AT203: 3q20 | AU203: ="20"&RIGHT(AT203,2)&"Q"&LEFT(AT203,1) -> 2020Q3 | BE203: Date | BF203: InflationYoY | BG203: Output | BH203: Date | BI203: TargetedPath | BJ203: PolicyRate | BK203: InflationYoY | BL203: Output | BM203: ExAnteRealRate_Annualized | BN203: obs_gdp
A204: 44196 | B204: 0.32 | C204: -5.41 | D204: -0.03 | E204: 0.7 | F204: 0.06 | G204: -0.14 | H204: -3.18 | I204: 1 | J204: 1.01 | K204: 0.43 | L204: -0.01 | M204: -5.6621607 | N204: -0.04 | O204: 0.03 | P204: -0.12 | Q204: -0.1225 | R204: -0.12557309 | S204: -0.12833333 | T204: -0.13028946 | U204: -0.13201656 | V204: -1.581962 | W204: =+(G204-E204)*4 -> -3.36 | X204: =+(G204-F204)*4 -> -0.8 | Y204: 0.14033232 | Z204: -1.9841297 | AA204: =+Y204-$Y$204 -> 0 | AB204: =+Z204-$Z$204 -> 0 | AC204: 40268 | AD204: =+V204 -> -1.581962 | AE204: =+AA204-AB204 -> 0 | AF204: =+A204 -> 44196 | AG204: =+AD204 -> -1.581962 | AS204: =A204 -> 44196 | AT204: 4q20 | AU204: ="20"&RIGHT(AT204,2)&"Q"&LEFT(AT204,1) -> 2020Q4 | AV204: =+AA204 -> 0 | AW204: =+AB204 -> 0 | AX204: =+AD204 -> -1.581962 | AY204: =+AX204-AE204 -> -1.581962 | AZ204: =+B204*4 -> 1.28 | BA204: =+AZ204+BN204 -> 1.28 | BB204: =+BL204 -> 0 | BC204: =+BK204 -> 0 | BE204: 44196 | BF204: 0 | BG204: 0 | BH204: 44196 | BI204: 0 | BJ204: 0 | BK204: 0 | BL204: 0 | BM204: 0 | BN204: 0
A205: 44286 | B205: 0.62 | C205: -5.26 | D205: -0.42 | E205: 0.64 | F205: 0.74 | G205: -0.14 | H205: -1.13 | I205: 0.43 | J205: 0.82 | K205: 0.43 | L205: 0.01 | M205: 0.66754119 | N205: 1.17 | O205: 0.06 | P205: -0.12 | Q205: -0.12166667 | R205: -0.12246795 | S205: -0.12333333 | T205: -0.12409455 | U205: -0.1249359 | V205: -2.2039436 | W205: =+(G205-E205)*4 -> -3.12 | X205: =+(G205-F205)*4 -> -3.52 | Y205: 0.37458055 | Z205: -2.0864302 | AA205: =+Y205-$Y$204 -> 0.23424823 | AB205: =+Z205-$Z$204 -> -0.10230059 | AC205: 40359 | AD205: =+V205 -> -2.2039436 | AE205: =+AA205-AB205 -> 0.33654881 | AF205: =+A205 -> 44286 | AG205: =+AD205 -> -2.2039436 | AS205: =A205 -> 44286 | AT205: 1q21 | AV205: =+AA205 -> 0.23424823 | AW205: =+AB205 -> -0.10230059 | AX205: =+AD205 -> -2.2039436 | AY205: =+AX205-AE205 -> -2.5404924 | AZ205: =+B205*4 -> 2.48 | BA205: =+AZ205+BN205 -> 3.2935965 | BB205: =+BL205 -> 0.20339912 | BC205: =+BK205 -> 0.0048023422 | BE205: 44286 | BF205: -0.0035323193 | BG205: -0.20481554 | BH205: 44286 | BI205: -0.064137869 | BJ205: -0.063580731 | BK205: 0.0048023422 | BL205: 0.20339912 | BM205: -0.064137869 | BN205: 0.81359647 | BO205: =+BN205/4 -> 0.20339912 | BP205: =+SUM($BO$205:BO205) -> 0.20339912
A206: 44377 | B206: 2.18 | C206: -2.13 | D206: 0.58 | E206: 0.31 | F206: 0.14 | G206: -0.14 | H206: 3.96 | I206: 2.64 | J206: 0.75 | K206: 0.43 | L206: 0.07 | M206: -1.8656649 | N206: 3.47 | O206: 0.06 | P206: -0.12 | Q206: -0.12 | R206: -0.12125 | S206: -0.1225 | T206: -0.12248047 | U206: -0.12234375 | V206: -2.5361337 | W206: =+(G206-E206)*4 -> -1.8 | X206: =+(G206-F206)*4 -> -1.12 | Y206: 0.24991106 | Z206: -1.6854719 | AA206: =+Y206-$Y$204 -> 0.10957874 | AB206: =+Z206-$Z$204 -> 0.29865774 | AC206: 40451 | AD206: =+V206 -> -2.5361337 | AE206: =+AA206-AB206 -> -0.189079 | AF206: =+A206 -> 44377 | AG206: =+AD206 -> -2.5361337 | AS206: =A206 -> 44377 | AT206: 2q21 | AV206: =+AA206 -> 0.10957874 | AW206: =+AB206 -> 0.29865774 | AX206: =+AD206 -> -2.5361337 | AY206: =+AX206-AE206 -> -2.3470547 | AZ206: =+B206*4 -> 8.72 | BA206: =+AZ206+BN206 -> 7.17949 | BB206: =+BL206 -> -0.18172837 | BC206: =+BK206 -> -0.005037169 | BE206: 44377 | BF206: -0.0055357904 | BG206: -0.37921807 | BH206: 44377 | BI206: 0.071684896 | BJ206: 0.070979138 | BK206: -0.005037169 | BL206: -0.18172837 | BM206: 0.071684896 | BN206: -1.54051 | BO206: =+BN206/4 -> -0.38512749 | BP206: =+SUM($BO$205:BO206) -> -0.18172837
A207: 44469 | B207: 1.77 | C207: -0.77 | D207: 0.67 | E207: 1.22 | F207: 0.69 | G207: -0.14 | H207: 3.62 | I207: 0.87 | J207: 0.75 | K207: 0.45 | L207: 0.04 | M207: -0.65900646 | N207: 1.03 | O207: 0.05 | P207: -0.12 | Q207: -0.12 | R207: -0.12125 | S207: -0.1225 | T207: -0.12248047 | U207: -0.12234375 | V207: -2.1082716 | W207: =+(G207-E207)*4 -> -5.44 | X207: =+(G207-F207)*4 -> -3.32 | Y207: 0.22497577 | Z207: -1.694325 | AA207: =+Y207-$Y$204 -> 0.084643454 | AB207: =+Z207-$Z$204 -> 0.28980462 | AC207: 40543 | AD207: =+V207 -> -2.1082716 | AE207: =+AA207-AB207 -> -0.20516117 | AF207: =+A207 -> 44469 | AG207: =+AD207 -> -2.1082716 | AS207: =A207 -> 44469 | AT207: 3q21 | AV207: =+AA207 -> 0.084643454 | AW207: =+AB207 -> 0.28980462 | AX207: =+AD207 -> -2.1082716 | AY207: =+AX207-AE207 -> -1.9031105 | AZ207: =+B207*4 -> 7.08 | BA207: =+AZ207+BN207 -> 6.8577163 | BB207: =+BL207 -> -0.2372993 | BC207: =+BK207 -> -0.0048627347 | BE207: 44469 | BF207: -0.005782808 | BG207: -0.45601259 | BH207: 44469 | BI207: 0.067056493 | BJ207: 0.066616388 | BK207: -0.0048627347 | BL207: -0.2372993 | BM207: 0.067056493 | BN207: -0.22228372 | BO207: =+BN207/4 -> -0.055570929 | BP207: =+SUM($BO$205:BO207) -> -0.2372993
A208: 44561 | B208: 0.68 | C208: -0.15 | D208: -0.23 | E208: 1.15 | F208: 0.84 | G208: -0.15 | H208: 0.39 | I208: 0.57 | J208: 0.83 | K208: 0.48 | L208: 0.08 | M208: -0.28819237 | N208: 0 | O208: 0.07 | P208: -0.12 | Q208: -0.12 | R208: -0.12 | S208: -0.12 | T208: NaN | U208: NaN | V208: -2.6894907 | W208: =+(G208-E208)*4 -> -5.2 | X208: =+(G208-F208)*4 -> -3.96 | Y208: 0.33566261 | Z208: -1.5958002 | AA208: =+Y208-$Y$204 -> 0.19533029 | AB208: =+Z208-$Z$204 -> 0.38832948 | AC208: 40633 | AD208: =+V208 -> -2.6894907 | AE208: =+AA208-AB208 -> -0.19299919 | AF208: =+A208 -> 44561 | AG208: =+AD208 -> -2.6894907 | AS208: =A208 -> 44561 | AT208: 4q21 | AU208: ="20"&RIGHT(AT208,2)&"Q"&LEFT(AT208,1) -> 2021Q4 | AV208: =+AA208 -> 0.19533029 | AW208: =+AB208 -> 0.38832948 | AX208: =+AD208 -> -2.6894907 | AY208: =+AX208-AE208 -> -2.4964915 | AZ208: =+B208*4 -> 2.72 | BA208: =+AZ208+BN208 -> 2.856 | BB208: =+BL208 -> -0.20329931 | BC208: =+BK208 -> -0.003773372 | BE208: 44561 | BF208: -0.0010964712 | BG208: -0.22271519 | BH208: 44561 | BI208: 0.044951834 | BJ208: 0.044637981 | BK208: -0.003773372 | BL208: -0.20329931 | BM208: 0.044951834 | BN208: 0.13599998 | BO208: =+BN208/4 -> 0.033999996 | BP208: =+SUM($BO$205:BO208) -> -0.20329931
...

Sheet Ex_post_real_rate_gaps
A1: date | B1: obs_gdp | C1: obs_hours | D1: obs_wages | E1: obs_gdpdeflator | F1: obs_corepce | G1: obs_nominalrate | H1: obs_consumption | I1: obs_investment | J1: obs_BBBspread | K1: obs_longinflation | L1: obs_longrate | M1: obs_tfp | N1: obs_gdi | O1: obs_AAAspread | P1: obs_nominalrate1 | Q1: obs_nominalrate2 | R1: obs_nominalrate3 | S1: obs_nominalrate4 | T1: obs_nominalrate5 | U1: obs_nominalrate6 | V1: ex_ante_real_rate | W1: ex_post_real_rate | X1: ex_post_real_rate_core | Y1: HLW r* (25Q3) | Z1: DSGE r* wFG | AA1: Delta_Rstar_HLW | AB1: Delta_Rstar_DSGE | AC1: date | AD1: ex_ante_real_rate | AE1: actual_MP_stance
A2: 25749 | B2: 1.87 | C2: NaN | D2: 2.62 | E2: 1.81 | F2: NaN | G2: 1.99 | H2: 0.58 | I2: 5.67 | J2: NaN | K2: NaN | L2: 2.06 | M2: NaN | N2: NaN | O2: NaN | P2: NaN | Q2: NaN | R2: NaN | S2: NaN | T2: NaN | U2: NaN | W2: =+(G2-E2)*4 -> 0.72 | AC2: 21823
A3: 25841 | B3: 1.02 | C3: NaN | D3: 2.03 | E3: 1.78 | F3: NaN | G3: 1.9 | H3: 0.99 | I3: 0.7 | J3: NaN | K3: NaN | L3: 2.1 | M3: NaN | N3: NaN | O3: NaN | P3: NaN | Q3: NaN | R3: NaN | S3: NaN | T3: NaN | U3: NaN | W3: =+(G3-E3)*4 -> 0.48 | AC3: 21915
A4: 25933 | B4: 1.04 | C4: NaN | D4: 2.26 | E4: 1.17 | F4: NaN | G4: 1.81 | H4: 1.75 | I4: -0.04 | J4: NaN | K4: NaN | L4: 2.09 | M4: NaN | N4: NaN | O4: NaN | P4: NaN | Q4: NaN | R4: NaN | S4: NaN | T4: NaN | U4: NaN | W4: =+(G4-E4)*4 -> 2.56 | AC4: 22006
A5: 26023 | B5: -0.38 | C5: NaN | D5: 0.97 | E5: 2.3 | F5: NaN | G5: 1.63 | H5: -0.11 | I5: -0.82 | J5: NaN | K5: NaN | L5: 1.97 | M5: NaN | N5: NaN | O5: NaN | P5: NaN | Q5: NaN | R5: NaN | S5: NaN | T5: NaN | U5: NaN | W5: =+(G5-E5)*4 -> -2.68 | AC5: 22097
A6: 26114 | B6: 0.98 | C6: NaN | D6: 0.84 | E6: 1.13 | F6: NaN | G6: 1.48 | H6: 1.18 | I6: 2.83 | J6: NaN | K6: NaN | L6: 1.98 | M6: NaN | N6: NaN | O6: NaN | P6: NaN | Q6: NaN | R6: NaN | S6: NaN | T6: NaN | U6: NaN | W6: =+(G6-E6)*4 -> 1.4 | AC6: 22189
A7: 26206 | B7: 1.84 | C7: NaN | D7: 1.95 | E7: 1.67 | F7: NaN | G7: 1.56 | H7: 1.15 | I7: 0.17 | J7: NaN | K7: NaN | L7: 2.01 | M7: NaN | N7: NaN | O7: NaN | P7: NaN | Q7: NaN | R7: NaN | S7: NaN | T7: NaN | U7: NaN | W7: =+(G7-E7)*4 -> -0.44 | AC7: 22281
A8: 26298 | B8: 0.66 | C8: NaN | D8: 1.64 | E8: 1.1 | F8: NaN | G8: 1.5 | H8: 1.01 | I8: 1.6 | J8: NaN | K8: NaN | L8: 1.96 | M8: NaN | N8: NaN | O8: NaN | P8: NaN | Q8: NaN | R8: NaN | S8: NaN | T8: NaN | U8: NaN | W8: =+(G8-E8)*4 -> 1.6 | AC8: 22371
A9: 26389 | B9: 1.25 | C9: NaN | D9: 1.97 | E9: 2.16 | F9: NaN | G9: 1.26 | H9: 0.92 | I9: 0.36 | J9: NaN | K9: NaN | L9: 1.9 | M9: NaN | N9: NaN | O9: NaN | P9: NaN | Q9: NaN | R9: NaN | S9: NaN | T9: NaN | U9: NaN | W9: =+(G9-E9)*4 -> -3.6 | Y9: 3.3617854 | AC9: 22462
A10: 26480 | B10: 0.61 | C10: NaN | D10: 0.44 | E10: 1.59 | F10: NaN | G10: 1.19 | H10: 0.37 | I10: 1.28 | J10: NaN | K10: NaN | L10: 1.89 | M10: NaN | N10: NaN | O10: NaN | P10: NaN | Q10: NaN | R10: NaN | S10: NaN | T10: NaN | U10: NaN | W10: =+(G10-E10)*4 -> -1.6 | Y10: 2.4726543 | Z10: 3.8039334 | AC10: 22554
A11: 26572 | B11: 1.12 | C11: NaN | D11: 0.92 | E11: 1.57 | F11: NaN | G11: 1.21 | H11: 2.07 | I11: 0.57 | J11: NaN | K11: NaN | L11: 1.9 | M11: NaN | N11: NaN | O11: NaN | P11: NaN | Q11: NaN | R11: NaN | S11: NaN | T11: NaN | U11: NaN | V11: 1.0149957 | W11: =+(G11-E11)*4 -> -1.44 | Y11: 2.5754349 | Z11: 3.9836896 | AC11: 22646 | AD11: =+V11 -> 1.0149957
A12: 26664 | B12: 1.16 | C12: NaN | D12: 1.45 | E12: 1.54 | F12: NaN | G12: 1.6 | H12: 0.71 | I12: 2.02 | J12: NaN | K12: NaN | L12: 1.95 | M12: NaN | N12: NaN | O12: NaN | P12: NaN | Q12: NaN | R12: NaN | S12: NaN | T12: NaN | U12: NaN | V12: 0.99620506 | W12: =+(G12-E12)*4 -> 0.24 | Y12: 2.743556 | Z12: 4.3206825 | AC12: 22736 | AD12: =+V12 -> 0.99620506
A13: 26754 | B13: 1.65 | C13: NaN | D13: 1.47 | E13: 3.51 | F13: NaN | G13: 1.7 | H13: 0.32 | I13: 1.26 | J13: NaN | K13: NaN | L13: 1.99 | M13: NaN | N13: NaN | O13: NaN | P13: NaN | Q13: NaN | R13: NaN | S13: NaN | T13: NaN | U13: NaN | V13: 2.382294 | W13: =+(G13-E13)*4 -> -7.24 | Y13: 3.355047 | Z13: 4.3759537 | AC13: 22827 | AD13: =+V13 -> 2.382294
A14: 26845 | B14: 0.5 | C14: NaN | D14: 0.77 | E14: 2.43 | F14: NaN | G14: 2.12 | H14: 0.82 | I14: 0.29 | J14: NaN | K14: NaN | L14: 2.08 | M14: NaN | N14: NaN | O14: NaN | P14: NaN | Q14: NaN | R14: NaN | S14: NaN | T14: NaN | U14: NaN | V14: 1.883329 | W14: =+(G14-E14)*4 -> -1.24 | Y14: 3.0451464 | Z14: 4.6791313 | AC14: 22919 | AD14: =+V14 -> 1.883329
A15: 26937 | B15: 1.19 | C15: NaN | D15: 1.51 | E15: 2.38 | F15: NaN | G15: 2.55 | H15: 0.35 | I15: 1.21 | J15: NaN | K15: NaN | L15: 2.15 | M15: NaN | N15: NaN | O15: NaN | P15: NaN | Q15: NaN | R15: NaN | S15: NaN | T15: NaN | U15: NaN | V15: 3.7119285 | W15: =+(G15-E15)*4 -> 0.68 | Y15: 3.1512224 | Z15: 4.9922555 | AC15: 23011 | AD15: =+V15 -> 3.7119285
A16: 27029 | B16: 0.84 | C16: NaN | D16: 1.68 | E16: 2.32 | F16: NaN | G16: 2.77 | H16: 1.67 | I16: 0.85 | J16: NaN | K16: NaN | L16: 2.18 | M16: NaN | N16: NaN | O16: NaN | P16: NaN | Q16: NaN | R16: NaN | S16: NaN | T16: NaN | U16: NaN | V16: 5.4656472 | W16: =+(G16-E16)*4 -> 1.8 | Y16: 3.0581261 | Z16: 5.2172569 | AC16: 23101 | AD16: =+V16 -> 5.4656472
A17: 27119 | B17: 0.87 | C17: NaN | D17: 0.97 | E17: 3.16 | F17: NaN | G17: 2.81 | H17: 0.42 | I17: 1.1 | J17: NaN | K17: NaN | L17: 2.34 | M17: NaN | N17: NaN | O17: NaN | P17: NaN | Q17: NaN | R17: NaN | S17: NaN | T17: NaN | U17: NaN | V17: 6.2960412 | W17: =+(G17-E17)*4 -> -1.4 | Y17: 3.0365806 | Z17: 5.3314811 | AC17: 23192 | AD17: =+V17 -> 6.2960412
A18: 27210 | B18: 0.25 | C18: NaN | D18: 1.69 | E18: 3.49 | F18: NaN | G18: 2.87 | H18: 1.4 | I18: -1.62 | J18: NaN | K18: NaN | L18: 2.52 | M18: NaN | N18: NaN | O18: NaN | P18: NaN | Q18: NaN | R18: NaN | S18: NaN | T18: NaN | U18: NaN | V18: 5.9361561 | W18: =+(G18-E18)*4 -> -2.48 | Y18: 2.7779297 | Z18: 5.5611755 | AC18: 23284 | AD18: =+V18 -> 5.9361561
A19: 27302 | B19: 0.63 | C19: NaN | D19: 0.52 | E19: 3.38 | F19: NaN | G19: 2.88 | H19: 0.14 | I19: 0.97 | J19: NaN | K19: NaN | L19: 2.67 | M19: NaN | N19: NaN | O19: NaN | P19: NaN | Q19: NaN | R19: NaN | S19: NaN | T19: NaN | U19: NaN | V19: 5.9219283 | W19: =+(G19-E19)*4 -> -2 | Y19: 2.8841953 | Z19: 5.695278 | AC19: 23376 | AD19: =+V19 -> 5.9219283
A20: 27394 | B20: -1.79 | C20: NaN | D20: 1.26 | E20: 3.27 | F20: NaN | G20: 2.67 | H20: -0.78 | I20: -3.05 | J20: NaN | K20: NaN | L20: 2.65 | M20: NaN | N20: NaN | O20: NaN | P20: NaN | Q20: NaN | R20: NaN | S20: NaN | T20: NaN | U20: NaN | V20: 5.8587809 | W20: =+(G20-E20)*4 -> -2.4 | Y20: 2.0943443 | Z20: 5.3896745 | AC20: 23467 | AD20: =+V20 -> 5.8587809
A21: 27484 | B21: -0.88 | C21: NaN | D21: 0.39 | E21: 2.77 | F21: NaN | G21: 2.2 | H21: 0.29 | I21: -1.95 | J21: NaN | K21: NaN | L21: 2.47 | M21: NaN | N21: NaN | O21: NaN | P21: NaN | Q21: NaN | R21: NaN | S21: NaN | T21: NaN | U21: NaN | V21: 5.233664 | W21: =+(G21-E21)*4 -> -2.28 | Y21: 1.9937668 | Z21: 5.0569891 | AC21: 23558 | AD21: =+V21 -> 5.233664
A22: 27575 | B22: 0.81 | C22: NaN | D22: 1.68 | E22: 2.32 | F22: NaN | G22: 1.76 | H22: 1.68 | I22: -1.61 | J22: NaN | K22: NaN | L22: 2.39 | M22: NaN | N22: NaN | O22: NaN | P22: NaN | Q22: NaN | R22: NaN | S22: NaN | T22: NaN | U22: NaN | V22: 3.67475 | W22: =+(G22-E22)*4 -> -2.24 | Y22: 2.201963 | Z22: 5.0199626 | AC22: 23650 | AD22: =+V22 -> 3.67475
... A60: 31047 | B60: 0.42 | C60: NaN | D60: 0.69 | E60: 1.11 | F60: NaN | G60: 2.53 | H60: 0.51 | I60: 1.23 | J60: NaN | K60: NaN | L60: 2.85 | M60: NaN | N60: NaN | O60: NaN | P60: NaN | Q60: NaN | R60: NaN | S60: NaN | T60: NaN | U60: NaN | V60: 6.7600301 | W60: =+(G60-E60)*4 -> 5.68 | Y60: 1.7611247 | Z60: 6.1339007 | AC60: 27119 | AD60: =+V60 -> 6.7600301
A61: 31137 | B61: 0.16 | C61: 5.6 | D61: 0.43 | E61: 1.56 | F61: NaN | G61: 2.47 | H61: 0.91 | I61: -1.64 | J61: NaN | K61: NaN | L61: 2.74 | M61: NaN | N61: NaN | O61: NaN | P61: NaN | Q61: NaN | R61: NaN | S61: NaN | T61: NaN | U61: NaN | V61: 6.7806939 | W61: =+(G61-E61)*4 -> 3.64 | Y61: 1.7424814 | Z61: 5.9347699 | AC61: 27210 | AD61: =+V61 -> 6.7806939
A62: 31228 | B62: 0.81 | C62: 5.52 | D62: 0.06 | E62: 1.39 | F62: NaN | G62: 2.49 | H62: 0.34 | I62: 1.35 | J62: NaN | K62: NaN | L62: 2.71 | M62: NaN | N62: NaN | O62: NaN | P62: NaN | Q62: NaN | R62: NaN | S62: NaN | T62: NaN | U62: NaN | V62: 6.3991596 | W62: =+(G62-E62)*4 -> 4.4 | Y62: 1.8260628 | Z62: 5.9211855 | AC62: 27302 | AD62: =+V62 -> 6.3991596
A63: 31320 | B63: 0.63 | C63: 5.38 | D63: 0.49 | E63: 1.52 | F63: NaN | G63: 2.34 | H63: 0.38 | I63: 1.3 | J63: NaN | K63: NaN | L63: 2.67 | M63: NaN | N63: NaN | O63: NaN | P63: NaN | Q63: NaN | R63: NaN | S63: NaN | T63: NaN | U63: NaN | V63: 6.5046641 | W63: =+(G63-E63)*4 -> 3.28 | Y63: 1.5783718 | Z63: 5.7742924 | AC63: 27394 | AD63: =+V63 -> 6.5046641
A64: 31412 | B64: 0.3 | C64: 5.18 | D64: -0.02 | E64: 1.49 | F64: NaN | G64: 2.16 | H64: 0.12 | I64: 0.92 | J64: NaN | K64: NaN | L64: 2.57 | M64: NaN | N64: NaN | O64: NaN | P64: NaN | Q64: NaN | R64: NaN | S64: NaN | T64: NaN | U64: NaN | V64: 5.9159244 | W64: =+(G64-E64)*4 -> 2.68 | Y64: 1.5726696 | Z64: 5.5374687 | AC64: 27484 | AD64: =+V64 -> 5.9159244
A65: 31502 | B65: -0.63 | C65: 4.95 | D65: -0.39 | E65: 1.76 | F65: NaN | G65: 2.19 | H65: -0.84 | I65: -2.48 | J65: NaN | K65: NaN | L65: 2.44 | M65: NaN | N65: NaN | O65: NaN | P65: NaN | Q65: NaN | R65: NaN | S65: NaN | T65: NaN | U65: NaN | V65: 5.1987007 | W65: =+(G65-E65)*4 -> 1.72 | Y65: 1.2239614 | Z65: 5.2647753 | AC65: 27575 | AD65: =+V65 -> 5.1987007
A66: 31593 | B66: 1.55 | C66: 4.78 | D66: 0.22 | E66: 1.3 | F66: NaN | G66: 2.01 | H66: 0.8 | I66: 1.99 | J66: NaN | K66: NaN | L66: 2.15 | M66: NaN | N66: NaN | O66: NaN | P66: NaN | Q66: NaN | R66: NaN | S66: NaN | T66: NaN | U66: NaN | V66: 5.2075525 | W66: =+(G66-E66)*4 -> 2.84 | Y66: 1.3749519 | Z66: 5.0448919 | AC66: 27667 | AD66: =+V66 -> 5.2075525
A67: 31685 | B67: 0.18 | C67: 4.7 | D67: 0.12 | E67: 1.14 | F67: NaN | G67: 1.94 | H67: -0.17 | I67: 0.36 | J67: NaN | K67: NaN | L67: 2.1 | M67: NaN | N67: NaN | O67: NaN | P67: NaN | Q67: NaN | R67: NaN | S67: NaN | T67: NaN | U67: NaN | V67: 4.8244061 | W67: =+(G67-E67)*4 -> 3.2 | Y67: 1.2983166 | Z67: 4.8969846 | AC67: 27759 | AD67: =+V67 -> 4.8244061
A68: 31777 | B68: -0.16 | C68: 4.67 | D68: 0.14 | E68: 0.85 | F68: NaN | G68: 1.97 | H68: 0.5 | I68: 0.57 | J68: NaN | K68: NaN | L68: 2.12 | M68: NaN | N68: NaN | O68: NaN | P68: NaN | Q68: NaN | R68: NaN | S68: NaN | T68: NaN | U68: NaN | V68: 4.7220469 | W68: =+(G68-E68)*4 -> 4.48 | Y68: 1.2102238 | Z68: 5.036552 | AC68: 27850 | AD68: =+V68 -> 4.7220469
A69: 31867 | B69: -0.73 | C69: 4.73 | D69: 0.11 | E69: 0.84 | F69: NaN | G69: 2.03 | H69: -0.22 | I69: -1.82 | J69: NaN | K69: NaN | L69: 2.12 | M69: NaN | N69: NaN | O69: NaN | P69: NaN | Q69: NaN | R69: NaN | S69: NaN | T69: NaN | U69: NaN | V69: 5.0143179 | W69: =+(G69-E69)*4 -> 4.76 | Y69: 1.1729481 | Z69: 5.0312545 | AC69: 27941 | AD69: =+V69 -> 5.0143179
A70: 31958 | B70: 1.36 | C70: 4.76 | D70: 0.96 | E70: 0.84 | F70: NaN | G70: 2.11 | H70: 1.55 | I70: 2.92 | J70: NaN | K70: NaN | L70: 2.17 | M70: NaN | N70: NaN | O70: NaN | P70: NaN | Q70: NaN | R70: NaN | S70: NaN | T70: NaN | U70: NaN | V70: 5.318176 | W70: =+(G70-E70)*4 -> 5.08 | Y70: 1.4883935 | Z70: 5.3521411 | AC70: 28033 | AD70: =+V70 -> 5.318176
A71: 32050 | B71: 0.82 | C71: 4.73 | D71: 0.61 | E71: 0.69 | F71: NaN | G71: 2.12 | H71: 0.75 | I71: 2.01 | J71: NaN | K71: NaN | L71: 2.37 | M71: NaN | N71: NaN | O71: NaN | P71: NaN | Q71: NaN | R71: NaN | S71: NaN | T71: NaN | U71: NaN | V71: 5.7226882 | W71: =+(G71-E71)*4 -> 5.72 | Y71: 1.5836338 | Z71: 5.4449257 | AC71: 28125 | AD71: =+V71 -> 5.7226882
A72: 32142 | B72: 1.09 | C72: 4.68 | D72: 0.23 | E72: 1.23 | F72: NaN | G72: 2.11 | H72: 0.53 | I72: 1.51 | J72: NaN | K72: NaN | L72: 2.4 | M72: NaN | N72: NaN | O72: NaN | P72: NaN | Q72: NaN | R72: NaN | S72: NaN | T72: NaN | U72: NaN | V72: 5.8040639 | W72: =+(G72-E72)*4 -> 3.52 | Y72: 1.667646 | Z72: 5.3824644 | AC72: 28215 | AD72: =+V72 -> 5.8040639
A73: 32233 | B73: 0.18 | C73: 4.58 | D73: 0.4 | E73: 0.95 | F73: 0.57 | G73: 1.86 | H73: -0.58 | I73: 1.05 | J73: NaN | K73: NaN | L73: 2.25 | M73: NaN | N73: NaN | O73: NaN | P73: NaN | Q73: NaN | R73: NaN | S73: NaN | T73: NaN | U73: NaN | V73: 5.4987128 | W73: =+(G73-E73)*4 -> 3.64 | X73: =+(G73-F73)*4 -> 5.16 | Y73: 1.6047869 | Z73: 5.0438207 | AC73: 28306 | AD73: =+V73 -> 5.4987128
A74: 32324 | B74: 0.62 | C74: 4.49 | D74: 0.23 | E74: 1.07 | F74: 0.61 | G74: 1.82 | H74: 0.39 | I74: 1.64 | J74: NaN | K74: NaN | L74: 2.22 | M74: NaN | N74: NaN | O74: NaN | P74: NaN | Q74: NaN | R74: NaN | S74: NaN | T74: NaN | U74: NaN | V74: 4.6944193 | W74: =+(G74-E74)*4 -> 3 | X74: =+(G74-F74)*4 -> 4.84 | Y74: 1.6694676 | Z74: 5.0689868 | AC74: 28398 | AD74: =+V74 -> 4.6944193
A75: 32416 | B75: 1.08 | C75: 4.44 | D75: 0.46 | E75: 0.93 | F75: 0.73 | G75: 1.99 | H75: 1.28 | I75: 1.84 | J75: NaN | K75: NaN | L75: 2.26 | M75: NaN | N75: NaN | O75: NaN | P75: NaN | Q75: NaN | R75: NaN | S75: NaN | T75: NaN | U75: NaN | V75: 4.4784821 | W75: =+(G75-E75)*4 -> 4.24 | X75: =+(G75-F75)*4 -> 5.04 | Y75: 1.8614584 | Z75: 5.2338877 | AC75: 28490 | AD75: =+V75 -> 4.4784821
A76: 32508 | B76: 0.82 | C76: 4.42 | D76: 0.09 | E76: 1.31 | F76: 0.84 | G76: 2.12 | H76: 0.39 | I76: 1.38 | J76: NaN | K76: NaN | L76: 2.25 | M76: NaN | N76: NaN | O76: NaN | P76: NaN | Q76: NaN | R76: NaN | S76: NaN | T76: NaN | U76: NaN | V76: 5.1119031 | W76: =+(G76-E76)*4 -> 3.24 | X76: =+(G76-F76)*4 -> 5.12 | Y76: 1.9518661 | Z76: 5.178072 | AC76: 28580 | AD76: =+V76 -> 5.1119031
A77: 32598 | B77: 0.83 | C77: 4.37 | D77: 0.7 | E77: 1.17 | F77: 0.86 | G77: 2.38 | H77: 0.63 | I77: 2.15 | J77: NaN | K77: NaN | L77: 2.35 | M77: NaN | N77: NaN | O77: NaN | P77: NaN | Q77: NaN | R77: NaN | S77: NaN | T77: NaN | U77: NaN | V77: 5.4495343 | W77: =+(G77-E77)*4 -> 4.84 | X77: =+(G77-F77)*4 -> 6.08 | Y77: 2.0873396 | Z77: 5.417534 | AC77: 28671 | AD77: =+V77 -> 5.4495343
A78: 32689 | B78: 0.67 | C78: 4.25 | D78: 0.25 | E78: 0.9 | F78: 0.96 | G78: 2.42 | H78: 0.87 | I78: 1.02 | J78: NaN | K78: NaN | L78: 2.41 | M78: NaN | N78: NaN | O78: NaN | P78: NaN | Q78: NaN | R78: NaN | S78: NaN | T78: NaN | U78: NaN | V78: 6.5483177 | W78: =+(G78-E78)*4 -> 6.08 | X78: =+(G78-F78)*4 -> 5.84 | Y78: 2.206842 | Z78: 5.4176939 | AC78: 28763 | AD78: =+V78 -> 6.5483177
A79: 32781 | B79: 0.21 | C79: 4.01 | D79: 0.55 | E79: 1.02 | F79: 0.8 | G79: 2.53 | H79: 0.77 | I79: -0.1 | J79: NaN | K79: NaN | L79: 2.4 | M79: NaN | N79: NaN | O79: NaN | P79: NaN | Q79: NaN | R79: NaN | S79: NaN | T79: NaN | U79: NaN | V79: 6.7214533 | W79: =+(G79-E79)*4 -> 6.04 | X79: =+(G79-F79)*4 -> 6.92 | Y79: 2.1521802 | Z79: 5.4347124 | AC79: 28855 | AD79: =+V79 -> 6.7214533
A80: 32873 | B80: 0.48 | C80: 3.66 | D80: 0.18 | E80: 1.38 | F80: 0.95 | G80: 2.77 | H80: 0.1 | I80: 1.69 | J80: NaN | K80: NaN | L80: 2.52 | M80: NaN | N80: NaN | O80: NaN | P80: NaN | Q80: NaN | R80: NaN | S80: NaN | T80: NaN | U80: NaN | V80: 7.2250458 | W80: =+(G80-E80)*4 -> 5.56 | X80: =+(G80-F80)*4 -> 7.28 | Y80: 2.3003108 | Z80: 5.601554 | AC80: 28945 | AD80: =+V80 -> 7.2250458
A81: 32963 | B81: 0.87 | C81: 3.26 | D81: 0.93 | E81: 1.36 | F81: 1 | G81: 2.81 | H81: -0.03 | I81: 2.49 | J81: NaN | K81: NaN | L81: 2.7 | M81: NaN | N81: NaN | O81: NaN | P81: NaN | Q81: NaN | R81: NaN | S81: NaN | T81: NaN | U81: NaN | V81: 7.8923922 | W81: =+(G81-E81)*4 -> 5.8 | X81: =+(G81-F81)*4 -> 7.24 | Y81: 2.4910331 | Z81: 5.711308 | AC81: 29036 | AD81: =+V81 -> 7.8923922
A82: 33054 | B82: 0.11 | C82: 2.98 | D82: 0.54 | E82: 1.47 | F82: 0.85 | G82: 2.65 | H82: -0.06 | I82: -1 | J82: NaN | K82: NaN | L82: 2.7 | M82: NaN | N82: NaN | O82: NaN | P82: NaN | Q82: NaN | R82: NaN | S82: NaN | T82: NaN | U82: NaN | V82: 8.0288857 | W82: =+(G82-E82)*4 -> 4.72 | X82: =+(G82-F82)*4 -> 7.2 | Y82: 2.410006 | Z82: 5.4739371 | AC82: 29128 | AD82: =+V82 -> 8.0288857
A83: 33146 | B83: 0.59 | C83: 2.89 | D83: 0.54 | E83: 0.84 | F83: 0.57 | G83: 2.63 | H83: 0.38 | I83: -0.03 | J83: NaN | K83: NaN | L83: 2.72 | M83: NaN | N83: NaN | O83: NaN | P83: NaN | Q83: NaN | R83: NaN | S83: NaN | T83: NaN | U83: NaN | V83: 7.4660664 | W83: =+(G83-E83)*4 -> 7.16 | X83: =+(G83-F83)*4 -> 8.24 | Y83: 2.4505956 | Z83: 5.5227118 | AC83: 29220 | AD83: =+V83 -> 7.4660664
A84: 33238 | B84: 0.13 | C84: 2.92 | D84: 0.65 | E84: 1.19 | F84: 1.13 | G84: 2.76 | H84: 0.69 | I84: 0.14 | J84: NaN | K84: NaN | L84: 2.74 | M84: NaN | N84: NaN | O84: NaN | P84: NaN | Q84: NaN | R84: NaN | S84: NaN | T84: NaN | U84: NaN | V84: 7.7820674 | W84: =+(G84-E84)*4 -> 6.28 | X84: =+(G84-F84)*4 -> 6.52 | Y84: 2.5527806 | Z84: 5.629574 | AC84: 29311 | AD84: =+V84 -> 7.7820674
... A111: 35703 | B111: 0.57 | C111: 1.13 | D111: 0.25 | E111: 0.18 | F111: 0.32 | G111: 1.07 | H111: 0.52 | I111: -0.82 | J111: NaN | K111: NaN | L111: 1.45 | M111: NaN | N111: NaN | O111: NaN | P111: NaN | Q111: NaN | R111: NaN | S111: NaN | T111: NaN | U111: NaN | V111: 3.05401 | W111: =+(G111-E111)*4 -> 3.56 | X111: =+(G111-F111)*4 -> 3 | Y111: 2.1439408 | Z111: 2.1654905 | AC111: 31777 | AD111: =+V111 -> 3.05401
A112: 35795 | B112: 0.83 | C112: 1.17 | D112: -0.12 | E112: 0.55 | F112: 0.32 | G112: 1.1 | H112: 0.82 | I112: 1.37 | J112: 1.57 | K112: NaN | L112: 1.4 | M112: NaN | N112: NaN | O112: NaN | P112: NaN | Q112: NaN | R112: NaN | S112: NaN | T112: NaN | U112: NaN | V112: 2.7482625 | W112: =+(G112-E112)*4 -> 2.2 | X112: =+(G112-F112)*4 -> 3.12 | Y112: 2.2262569 | Z112: 2.0916898 | AC112: 31867 | AD112: =+V112 -> 2.7482625
A113: 35885 | B113: 0.3 | C113: 1.08 | D113: 0.26 | E113: -0.26 | F113: 0.34 | G113: 1.05 | H113: -0.02 | I113: 1.7 | J113: 1.45 | K113: NaN | L113: 1.28 | M113: NaN | N113: NaN | O113: NaN | P113: NaN | Q113: NaN | R113: NaN | S113: NaN | T113: NaN | U113: NaN | V113: 2.6709204 | W113: =+(G113-E113)*4 -> 5.24 | X113: =+(G113-F113)*4 -> 2.84 | Y113: 2.1257695 | Z113: 1.8397229 | AC113: 31958 | AD113: =+V113 -> 2.6709204
A114: 35976 | B114: 0 | C114: 1.38 | D114: 0.02 | E114: 0.54 | F114: 0.44 | G114: 1.02 | H114: -0.03 | I114: -0.49 | J114: 1.36 | K114: NaN | L114: 1.25 | M114: -3.0577898 | N114: NaN | O114: NaN | P114: NaN | Q114: NaN | R114: NaN | S114: NaN | T114: NaN | U114: NaN | V114: 2.7025696 | W114: =+(G114-E114)*4 -> 1.92 | X114: =+(G114-F114)*4 -> 2.32 | Y114: 2.2107502 | Z114: 1.6725378 | AC114: 32050 | AD114: =+V114 -> 2.7025696
A115: 36068 | B115: 0.13 | C115: 1.64 | D115: -0.02 | E115: 0.47 | F115: 0.33 | G115: 0.99 | H115: 0.6 | I115: 1.26 | J115: 1.78 | K115: NaN | L115: 1.14 | M115: -1.3258551 | N115: NaN | O115: NaN | P115: NaN | Q115: NaN | R115: NaN | S115: NaN | T115: NaN | U115: NaN | V115: 2.2314227 | W115: =+(G115-E115)*4 -> 2.08 | X115: =+(G115-F115)*4 -> 2.64 | Y115: 2.1336152 | Z115: 1.6830584 | AC115: 32142 | AD115: =+V115 -> 2.2314227
A116: 36160 | B116: 0.04 | C116: 1.3 | D116: -0.45 | E116: 1.02 | F116: 0.27 | G116: 0.92 | H116: 0.3 | I116: 0.36 | J116: 2.13 | K116: NaN | L116: 1.04 | M116: 2.4829315 | N116: NaN | O116: NaN | P116: NaN | Q116: NaN | R116: NaN | S116: NaN | T116: NaN | U116: NaN | V116: 2.1017807 | W116: =+(G116-E116)*4 -> -0.4 | X116: =+(G116-F116)*4 -> 2.6 | Y116: 1.9493399 | Z116: 1.4724572 | AC116: 32233 | AD116: =+V116 -> 2.1017807
A117: 36250 | B117: 0.84 | C117: 1.23 | D117: -0.06 | E117: 0.23 | F117: 0.17 | G117: 0.78 | H117: 0.48 | I117: 1.37 | J117: 1.86 | K117: 0.48 | L117: 1 | M117: 4.1108515 | N117: NaN | O117: NaN | P117: NaN | Q117: NaN | R117: NaN | S117: NaN | T117: NaN | U117: NaN | V117: 1.6371137 | W117: =+(G117-E117)*4 -> 2.2 | X117: =+(G117-F117)*4 -> 2.44 | Y117: 2.0351751 | Z117: 1.2728381 | AC117: 32324 | AD117: =+V117 -> 1.6371137
A118: 36341 | B118: 0.19 | C118: 2.01 | D118: 0.74 | E118: 0.21 | F118: 0.27 | G118: 0.66 | H118: 0.7 | I118: 1.47 | J118: 1.7 | K118: NaN | L118: 1.06 | M118: -2.074513 | N118: NaN | O118: NaN | P118: NaN | Q118: NaN | R118: NaN | S118: NaN | T118: NaN | U118: NaN | V118: 1.3894528 | W118: =+(G118-E118)*4 -> 1.8 | X118: =+(G118-F118)*4 -> 1.56 | Y118: 1.9411904 | Z118: 1.2421784 | AC118: 32416 | AD118: =+V118 -> 1.3894528
A119: 36433 | B119: 0.93 | C119: 1.56 | D119: 0.42 | E119: 0.09 | F119: 0.26 | G119: 0.65 | H119: 0.95 | I119: 1.54 | J119: 1.56 | K119: NaN | L119: 1.26 | M119: 4.0050909 | N119: NaN | O119: NaN | P119: NaN | Q119: NaN | R119: NaN | S119: NaN | T119: NaN | U119: NaN | V119: 0.99789865 | W119: =+(G119-E119)*4 -> 2.24 | X119: =+(G119-F119)*4 -> 1.56 | Y119: 2.0698398 | Z119: 1.2539379 | AC119: 32508 | AD119: =+V119 -> 0.99789865
A120: 36525 | B120: 0.77 | C120: 1.88 | D120: 0.51 | E120: 0.31 | F120: 0.3 | G120: 0.78 | H120: 0.62 | I120: 0.53 | J120: 1.46 | K120: NaN | L120: 1.33 | M120: 0.50876453 | N120: NaN | O120: NaN | P120: NaN | Q120: NaN | R120: NaN | S120: NaN | T120: NaN | U120: NaN | V120: 1.0390893 | W120: =+(G120-E120)*4 -> 1.88 | X120: =+(G120-F120)*4 -> 1.92 | Y120: 2.1598827 | Z120: 1.2036688 | AC120: 32598 | AD120: =+V120 -> 1.0390893
A121: 36616 | B121: 0.82 | C121: 2.04 | D121: 0.25 | E121: 0.46 | F121: 0.19 | G121: 0.84 | H121: 0.76 | I121: 2.55 | J121: 1.34 | K121: 0.45 | L121: 1.4 | M121: 2.3880325 | N121: NaN | O121: 0.09 | P121: NaN | Q121: NaN | R121: NaN | S121: NaN | T121: NaN | U121: NaN | V121: 1.4873655 | W121: =+(G121-E121)*4 -> 1.52 | X121: =+(G121-F121)*4 -> 2.6 | Y121: 2.2425751 | Z121: 1.1843866 | AC121: 32689 | AD121: =+V121 -> 1.4873655
A122: 36707 | B122: 0.59 | C122: 2.03 | D122: 0.23 | E122: 0.24 | F122: 0.18 | G122: 1.03 | H122: 0.7 | I122: -0.1 | J122: 1.64 | K122: NaN | L122: 1.36 | M122: 0.90464363 | N122: NaN | O122: 0.11 | P122: NaN | Q122: NaN | R122: NaN | S122: NaN | T122: NaN | U122: NaN | V122: 1.7767588 | W122: =+(G122-E122)*4 -> 3.16 | X122: =+(G122-F122)*4 -> 3.4 | Y122: 2.2381216 | Z122: 1.1774776 | AC122: 32781 | AD122: =+V122 -> 1.7767588
A123: 36799 | B123: 0.36 | C123: 2.04 | D123: 0.33 | E123: 0.53 | F123: 0.32 | G123: 1.14 | H123: 0.28 | I123: 0.46 | J123: 1.9 | K123: NaN | L123: 1.36 | M123: 0.27598946 | N123: NaN | O123: 0.12 | P123: NaN | Q123: NaN | R123: NaN | S123: NaN | T123: NaN | U123: NaN | V123: 2.5211067 | W123: =+(G123-E123)*4 -> 2.44 | X123: =+(G123-F123)*4 -> 3.28 | Y123: 2.4166369 | Z123: 1.2345947 | AC123: 32873 | AD123: =+V123 -> 2.5211067
A124: 36891 | B124: 0.29 | C124: 2.25 | D124: 0.09 | E124: 0.59 | F124: 0.41 | G124: 1.23 | H124: 0.27 | I124: 0.56 | J124: 2.62 | K124: NaN | L124: 1.32 | M124: 0.079371181 | N124: NaN | O124: 0.14 | P124: NaN | Q124: NaN | R124: NaN | S124: NaN | T124: NaN | U124: NaN | V124: 2.7773832 | W124: =+(G124-E124)*4 -> 2.56 | X124: =+(G124-F124)*4 -> 3.28 | Y124: 2.4386474 | Z124: 1.3752398 | AC124: 32963 | AD124: =+V124 -> 2.7773832
A125: 36981 | B125: 1.07 | C125: 2.44 | D125: -0.2 | E125: 0.74 | F125: 0.29 | G125: 1.2 | H125: 0.58 | I125: 0.69 | J125: 2.58 | K125: 0.45 | L125: 1.25 | M125: 3.9475743 | N125: NaN | O125: 0.11 | P125: NaN | Q125: NaN | R125: NaN | S125: NaN | T125: NaN | U125: NaN | V125: 3.0232499 | W125: =+(G125-E125)*4 -> 1.84 | X125: =+(G125-F125)*4 -> 3.64 | Y125: 2.6164489 | Z125: 1.3098732 | AC125: 33054 | AD125: =+V125 -> 3.0232499
A126: 37072 | B126: 0 | C126: 2.12 | D126: 0.06 | E126: 0.64 | F126: 0.55 | G126: 1.17 | H126: 0.33 | I126: -1.21 | J126: 2.78 | K126: 0.45 | L126: 1.3 | M126: 0.99657234 | N126: NaN | O126: 0.09 | P126: NaN | Q126: NaN | R126: NaN | S126: NaN | T126: NaN | U126: NaN | V126: 2.9124853 | W126: =+(G126-E126)*4 -> 2.12 | X126: =+(G126-F126)*4 -> 2.48 | Y126: 2.8758428 | Z126: 1.3249628 | AC126: 33146 | AD126: =+V126 -> 2.9124853
A127: 37164 | B127: 0.01 | C127: 1.98 | D127: 0.06 | E127: 0.6 | F127: 0.64 | G127: 1.09 | H127: -0.13 | I127: -1.58 | J127: 3.2 | K127: 0.45 | L127: 1.28 | M127: 0.81998426 | N127: NaN | O127: 0.1 | P127: NaN | Q127: NaN | R127: NaN | S127: NaN | T127: NaN | U127: NaN | V127: 2.7241392 | W127: =+(G127-E127)*4 -> 1.96 | X127: =+(G127-F127)*4 -> 1.8 | Y127: 2.6199747 | Z127: 1.3910176 | AC127: 33238 | AD127: =+V127 -> 2.7241392
A128: 37256 | B128: -0.3 | C128: 1.81 | D128: -0.03 | E128: 0.8 | F128: 0.61 | G128: 0.88 | H128: -0.29 | I128: -0.43 | J128: 3.6 | K128: 0.45 | L128: 1.2 | M128: -0.16012123 | N128: NaN | O128: 0.06 | P128: NaN | Q128: NaN | R128: NaN | S128: NaN | T128: NaN | U128: NaN | V128: 2.3909845 | W128: =+(G128-E128)*4 -> 0.32 | X128: =+(G128-F128)*4 -> 1.08 | Y128: 2.5371678 | Z128: 1.4806557 | AC128: 33328 | AD128: =+V128 -> 2.3909845
A129: 37346 | B129: -0.16 | C129: 1.4 | D129: -0.16 | E129: 0.68 | F129: 0.78 | G129: 0.84 | H129: -0.34 | I129: -1.47 | J129: 3.03 | K129: 0.48 | L129: 1.28 | M129: 0.15720301 | N129: NaN | O129: -0.06 | P129: NaN | Q129: NaN | R129: NaN | S129: NaN | T129: NaN | U129: NaN | V129: 1.5546034 | W129: =+(G129-E129)*4 -> 0.64 | X129: =+(G129-F129)*4 -> 0.24 | Y129: 2.6352632 | Z129: 1.581495 | AC129: 33419 | AD129: =+V129 -> 1.5546034
A130: 37437 | B130: 0.25 | C130: 1.31 | D130: 0.27 | E130: 0.36 | F130: 0.48 | G130: 0.84 | H130: -0.09 | I130: -0.44 | J130: 2.76 | K130: 0.48 | L130: 1.31 | M130: 0.74408785 | N130: 0.7 | O130: -0.1 | P130: NaN | Q130: NaN | R130: NaN | S130: NaN | T130: NaN | U130: NaN | V130: 1.1905865 | W130: =+(G130-E130)*4 -> 1.92 | X130: =+(G130-F130)*4 -> 1.44 | Y130: 2.4166503 | Z130: 1.6174713 | AC130: 33511 | AD130: =+V130 -> 1.1905865
A131: 37529 | B131: 0.26 | C131: 1.09 | D131: 0.05 | E131: 0.68 | F131: 0.55 | G131: 0.84 | H131: 0.05 | I131: -0.38 | J131: 3.02 | K131: 0.48 | L131: 1.19 | M131: 0.16933724 | N131: 0.16 | O131: 0.04 | P131: NaN | Q131: NaN | R131: NaN | S131: NaN | T131: NaN | U131: NaN | V131: 1.4739675 | W131: =+(G131-E131)*4 -> 0.64 | X131: =+(G131-F131)*4 -> 1.16 | Y131: 2.3442732 | Z131: 1.3548984 | AC131: 33603 | AD131: =+V131 -> 1.4739675
A132: 37621 | B132: 0 | C132: 0.88 | D132: 0.17 | E132: 0.46 | F132: 0.45 | G132: 0.79 | H132: 0.45 | I132: 0.44 | J132: 2.88 | K132: 0.48 | L132: 1.14 | M132: 0.70248106 | N132: -0.36 | O132: 0.09 | P132: NaN | Q132: NaN | R132: NaN | S132: NaN | T132: NaN | U132: NaN | V132: 1.3281434 | W132: =+(G132-E132)*4 -> 1.32 | X132: =+(G132-F132)*4 -> 1.36 | Y132: 2.2327294 | Z132: 1.1559941 | AC132: 33694 | AD132: =+V132 -> 1.3281434
A133: 37711 | B133: -0.45 | C133: 0.79 | D133: -0.26 | E133: 0.62 | F133: 0.53 | G133: 0.69 | H133: 0.22 | I133: -0.79 | J133: 2.1 | K133: 0.48 | L133: 1.04 | M133: -2.6613263 | N133: -0.18 | O133: 0.16 | P133: NaN | Q133: NaN | R133: NaN | S133: NaN | T133: NaN | U133: NaN | V133: 1.2095964 | W133: =+(G133-E133)*4 -> 0.28 | X133: =+(G133-F133)*4 -> 0.64 | Y133: 2.0798214 | Z133: 0.61639985 | AC133: 33785 | AD133: =+V133 -> 1.2095964
A134: 37802 | B134: -0.16 | C134: 0.52 | D134: -0.01 | E134: 0.59 | F134: 0.48 | G134: 0.61 | H134: -0.3 | I134: -0.67 | J134: 1.54 | K134: 0.48 | L134: 0.99 | M134: -0.78390576 | N134: -0.65 | O134: 0.16 | P134: NaN | Q134: NaN | R134: NaN | S134: NaN | T134: NaN | U134: NaN | V134: 0.72374578 | W134: =+(G134-E134)*4 -> 0.08 | X134: =+(G134-F134)*4 -> 0.52 | Y134: 2.0750262 | Z134: 0.36560821 | AC134: 33877 | AD134: =+V134 -> 0.72374578
A135: 37894 | B135: 0.51 | C135: 0.57 | D135: 0.58 | E135: 0.63 | F135: 0.41 | G135: 0.53 | H135: 0.3 | I135: 1.25 | J135: 1.21 | K135: 0.48 | L135: 1.04 | M135: 0.8827365 | N135: 1.06 | O135: 0.05 | P135: NaN | Q135: NaN | R135: NaN | S135: NaN | T135: NaN | U135: NaN | V135: 0.44825999 | W135: =+(G135-E135)*4 -> -0.4 | X135: =+(G135-F135)*4 -> 0.48 | Y135: 2.1472237 | Z135: 0.5479402 | AC135: 33969 | AD135: =+V135 -> 0.44825999
A136: 37986 | B136: 0.48 | C136: 0.66 | D136: -0.16 | E136: 0.24 | F136: 0.48 | G136: 0.53 | H136: 0.4 | I136: 0.49 | J136: 0.96 | K136: 0.48 | L136: 1.09 | M136: 0.78001171 | N136: 0.4 | O136: -0.07 | P136: NaN | Q136: NaN | R136: NaN | S136: NaN | T136: NaN | U136: NaN | V136: 0.25215831 | W136: =+(G136-E136)*4 -> 1.16 | X136: =+(G136-F136)*4 -> 0.2 | Y136: 2.1589359 | Z136: 0.692427 | AC136: 34059 | AD136: =+V136 -> 0.25215831
A137: 38077 | B137: 0.42 | C137: 0.45 | D137: 0.25 | E137: 0.46 | F137: 0.64 | G137: 0.52 | H137: 0.45 | I137: 0.55 | J137: 0.93 | K137: 0.48 | L137: 1.04 | M137: 0.62234895 | N137: 0.87 | O137: -0.08 | P137: NaN | Q137: NaN | R137: NaN | S137: NaN | T137: NaN | U137: NaN | V137: 0.33950473 | W137: =+(G137-E137)*4 -> 0.24 | X137: =+(G137-F137)*4 -> -0.48 | Y137: 2.1229446 | Z137: 0.72612137 | AC137: 34150 | AD137: =+V137 -> 0.33950473
A138: 38168 | B138: 0.45 | C138: 0.6 | D138: -0.04 | E138: 0.62 | F138: 0.57 | G138: 0.52 | H138: 0.16 | I138: 0.81 | J138: 0.88 | K138: 0.48 | L138: 1.09 | M138: 2.5864402 | N138: 0.08 | O138: -0.19 | P138: NaN | Q138: NaN | R138: NaN | S138: NaN | T138: NaN | U138: NaN | V138: 0.2019431 | W138: =+(G138-E138)*4 -> -0.4 | X138: =+(G138-F138)*4 -> -0.2 | Y138: 2.1426969 | Z138: 0.87329972 | AC138: 34242 | AD138: =+V138 -> 0.2019431
A139: 38260 | B139: 0.04 | C139: 0.46 | D139: -0.11 | E139: 0.46 | F139: 0.4 | G139: 0.52 | H139: -0.02 | I139: 0.38 | J139: 0.87 | K139: 0.48 | L139: 1.05 | M139: -1.6474789 | N139: 0.56 | O139: -0.19 | P139: NaN | Q139: NaN | R139: NaN | S139: NaN | T139: NaN | U139: NaN | V139: 0.19781737 | W139: =+(G139-E139)*4 -> 0.24 | X139: =+(G139-F139)*4 -> 0.48 | Y139: 1.9452419 | Z139: 0.8264187 | AC139: 34334 | AD139: =+V139 -> 0.19781737
A140: 38352 | B140: 0.21 | C140: 0.48 | D140: -0.1 | E140: 0.58 | F140: 0.34 | G140: 0.53 | H140: 0.48 | I140: 0.22 | J140: 0.76 | K140: 0.48 | L140: 0.96 | M140: 0.72712726 | N140: 0.34 | O140: -0.12 | P140: NaN | Q140: NaN | R140: NaN | S140: NaN | T140: NaN | U140: NaN | V140: 0.27255065 | W140: =+(G140-E140)*4 -> -0.2 | X140: =+(G140-F140)*4 -> 0.76 | Y140: 1.8404336 | Z140: 0.60054521 | AC140: 34424 | AD140: =+V140 -> 0.27255065
A141: 38442 | B141: 0.05 | C141: 0.31 | D141: 0.07 | E141: 0.35 | F141: 0.37 | G141: 0.53 | H141: 0.31 | I141: -0.65 | J141: 0.68 | K141: 0.48 | L141: 0.92 | M141: 2.1386717 | N141: -0.86 | O141: -0.07 | P141: NaN | Q141: NaN | R141: NaN | S141: NaN | T141: NaN | U141: NaN | V141: 0.29430714 | W141: =+(G141-E141)*4 -> 0.72 | X141: =+(G141-F141)*4 -> 0.64 | Y141: 1.7652277 | Z141: 0.34032341 | AC141: 34515 | AD141: =+V141 -> 0.29430714
... A156: 39813 | B156: -1.82 | C156: 2.53 | D156: -0.03 | E156: 0.29 | F156: 0.42 | G156: 0.97 | H156: -1.56 | I156: -4.21 | J156: 5.01 | K156: 0.5 | L156: 1.04 | M156: -5.9653394 | N156: -2.69 | O156: 0.45 | P156: NaN | Q156: NaN | R156: NaN | S156: NaN | T156: NaN | U156: NaN | V156: 2.7307856 | W156: =+(G156-E156)*4 -> 2.72 | X156: =+(G156-F156)*4 -> 2.2 | Y156: 1.3712865 | Z156: -0.0043881013 | AC156: 35885 | AD156: =+V156 -> 2.7307856
A157: 39903 | B157: -3.2 | C157: 0.59 | D157: -0.44 | E157: 0.37 | F157: 0.25 | G157: 0.42 | H157: -1.69 | I157: -6.47 | J157: 5.03 | K157: 0.48 | L157: 1.04 | M157: -4.5364652 | N157: -2.07 | O157: 0.39 | P157: 0.26333333 | Q157: 0.25083333 | R157: 0.25404906 | S157: 0.26166667 | T157: 0.2736387 | U157: 0.29295662 | V157: 1.918184 | W157: =+(G157-E157)*4 -> 0.2 | X157: =+(G157-F157)*4 -> 0.68 | Y157: 0.65804159 | Z157: -0.38481294 | AC157: 35976 | AD157: =+V157 -> 1.918184
A158: 39994 | B158: -0.14 | C158: -0.4 | D158: 0.43 | E158: 0.04 | F158: 0.3 | G158: 0.23 | H158: -0.07 | I158: -3.05 | J158: 4.24 | K158: 0.48 | L158: 1.05 | M158: 8.8832751 | N158: -0.03 | O158: 0.31 | P158: 0.18666667 | Q158: 0.1875 | R158: 0.19718905 | S158: 0.215 | T158: 0.23513583 | U158: 0.26021333 | V158: -0.056538811 | W158: =+(G158-E158)*4 -> 0.76 | X158: =+(G158-F158)*4 -> -0.28 | Y158: 0.72602799 | Z158: -0.38142541 | AC158: 36068 | AD158: =+V158 -> -0.056538811
A159: 40086 | B159: 0.38 | C159: -0.8 | D159: 0.62 | E159: 0.08 | F159: 0.2 | G159: 0.13 | H159: 0.1 | I159: -0.19 | J159: 2.85 | K159: 0.5 | L159: 0.99 | M159: 1.5513997 | N159: 1.08 | O159: 0.14 | P159: 0.1075 | Q159: 0.12166667 | R159: 0.14445908 | S159: 0.17333333 | T159: 0.20501927 | U159: 0.2403875 | V159: -0.67538813 | W159: =+(G159-E159)*4 -> 0.2 | X159: =+(G159-F159)*4 -> -0.28 | Y159: 0.8070002 | Z159: -0.41900073 | AC159: 36160 | AD159: =+V159 -> -0.67538813
A160: 40178 | B160: 0.4 | C160: -1.12 | D160: 0.4 | E160: 0.21 | F160: 0.22 | G160: 0.11 | H160: 0.34 | I160: -0.73 | J160: 2.06 | K160: 0.48 | L160: 0.96 | M160: -0.23200323 | N160: 0.28 | O160: 0.11 | P160: 0.10666667 | Q160: 0.12333333 | R160: 0.15181279 | S160: 0.18583333 | T160: 0.21806869 | U160: 0.25087587 | V160: -1.0948138 | W160: =+(G160-E160)*4 -> -0.4 | X160: =+(G160-F160)*4 -> -0.44 | Y160: 0.88014083 | Z160: -0.63373039 | AC160: 36250 | AD160: =+V160 -> -1.0948138
A161: 40268 | B161: 0.81 | C161: -0.79 | D161: 0.25 | E161: 0.11 | F161: 0.21 | G161: 0.11 | H161: 0.9 | I161: -0.37 | J161: 1.74 | K161: 0.48 | L161: 1.02 | M161: 1.9522559 | N161: 0.44 | O161: 0.04 | P161: 0.090833333 | Q161: 0.10916667 | R161: 0.1347544 | S161: 0.16333333 | T161: 0.19016495 | U161: 0.21690588 | V161: -1.0362078 | W161: =+(G161-E161)*4 -> 0 | X161: =+(G161-F161)*4 -> -0.4 | Y161: 0.94110271 | Z161: -0.62751995 | AC161: 36341 | AD161: =+V161 -> -1.0362078
A162: 40359 | B162: 0.82 | C162: -0.65 | D162: 0.52 | E162: 0.25 | F162: 0.24 | G162: 0.11 | H162: 0.49 | I162: 2.99 | J162: 1.79 | K162: 0.48 | L162: 0.96 | M162: -0.8384604 | N162: 0.89 | O162: 0.04 | P162: 0.10166667 | Q162: 0.11833333 | R162: 0.1314981 | S162: 0.14416667 | T162: 0.15810032 | U162: 0.17257065 | V162: -1.0070636 | W162: =+(G162-E162)*4 -> -0.56 | X162: =+(G162-F162)*4 -> -0.52 | Y162: 1.069073 | Z162: -0.621579 | AC162: 36433 | AD162: =+V162 -> -1.0070636
A163: 40451 | B163: 0.37 | C163: -0.74 | D163: 0.02 | E163: 0.34 | F163: 0.33 | G163: 0.15 | H163: 0.32 | I163: -0.9 | J163: 1.67 | K163: 0.5 | L163: 0.88 | M163: -2.882261 | N163: 0.35 | O163: 0.05 | P163: 0.13333333 | Q163: 0.1475 | R163: 0.1604494 | S163: 0.1725 | T163: 0.18376842 | U163: 0.19455341 | V163: -1.067499 | W163: =+(G163-E163)*4 -> -0.76 | X163: =+(G163-F163)*4 -> -0.72 | Y163: 1.1481379 | Z163: -0.76714917 | AC163: 36525 | AD163: =+V163 -> -1.067499
A164: 40543 | B164: 0.57 | C164: -0.74 | D164: 0.27 | E164: 0.15 | F164: 0.35 | G164: 0.2 | H164: 0.76 | I164: 0.33 | J164: 1.44 | K164: 0.48 | L164: 0.93 | M164: 1.2214726 | N164: 0.88 | O164: 0.06 | P164: 0.17916667 | Q164: 0.195 | R164: 0.20780619 | S164: 0.22 | T164: 0.23305564 | U164: 0.24641983 | V164: -1.1652472 | W164: =+(G164-E164)*4 -> 0.2 | X164: =+(G164-F164)*4 -> -0.6 | Y164: 1.1296803 | Z164: -0.83258483 | AC164: 36616 | AD164: =+V164 -> -1.1652472
A165: 40633 | B165: 0.99 | C165: -0.11 | D165: 0.45 | E165: 0.39 | F165: 0.45 | G165: 0.22 | H165: 0.28 | I165: 1.84 | J165: 1.3 | K165: 0.5 | L165: 1.08 | M165: 0.53895563 | N165: 0.71 | O165: 0.05 | P165: 0.20583333 | Q165: 0.23583333 | R165: 0.26485046 | S165: 0.2925 | T165: 0.3184866 | U165: 0.34356216 | V165: -0.74399331 | W165: =+(G165-E165)*4 -> -0.68 | X165: =+(G165-F165)*4 -> -0.92 | Y165: 1.3066659 | Z165: -0.62501334 | AC165: 36707 | AD165: =+V165 -> -0.74399331
A166: 40724 | B166: -0.05 | C166: -0.49 | D166: 0.3 | E166: 0.21 | F166: 0.47 | G166: 0.31 | H166: 0.15 | I166: 0.05 | J166: 1.28 | K166: 0.5 | L166: 1.12 | M166: -1.1722821 | N166: 0.14 | O166: -0.01 | P166: 0.29583333 | Q166: 0.32916667 | R166: 0.35681095 | S166: 0.38083333 | T166: 0.40249786 | U166: 0.42268328 | V166: -0.85772008 | W166: =+(G166-E166)*4 -> 0.4 | X166: =+(G166-F166)*4 -> -0.64 | Y166: 1.2994991 | Z166: -0.53590421 | AC166: 36799 | AD166: =+V166 -> -0.85772008
A167: 40816 | B167: -0.04 | C167: -0.7 | D167: -0.06 | E167: 0.32 | F167: 0.48 | G167: 0.35 | H167: -0.17 | I167: -0.91 | J167: 1.92 | K167: 0.5 | L167: 1.07 | M167: -0.27935922 | N167: -0.49 | O167: -0.08 | P167: 0.24916667 | Q167: 0.245 | R167: 0.24360584 | S167: 0.24416667 | T167: 0.24707524 | U167: 0.25091873 | V167: -0.4382743 | W167: =+(G167-E167)*4 -> 0.12 | X167: =+(G167-F167)*4 -> -0.52 | Y167: 1.03818 | Z167: -0.57237115 | AC167: 36891 | AD167: =+V167 -> -0.4382743
A168: 40908 | B168: -0.37 | C168: -1.11 | D168: 0.25 | E168: 0.23 | F168: 0.49 | G168: 0.31 | H168: -0.18 | I168: -0.53 | J168: 2.32 | K168: 0.5 | L168: 1.05 | M168: -1.4867223 | N168: -0.31 | O168: -0.06 | P168: 0.15416667 | Q168: 0.14083333 | R168: 0.13779245 | S168: 0.13666667 | T168: 0.13809896 | U168: 0.14229167 | V168: -0.34157532 | W168: =+(G168-E168)*4 -> 0.32 | X168: =+(G168-F168)*4 -> -0.72 | Y168: 1.1106378 | Z168: -0.59858879 | AC168: 36981 | AD168: =+V168 -> -0.34157532
... A200: 43830 | B200: -0.14 | C200: 1.03 | D200: -0.32 | E200: 0.52 | F200: 0.34 | G200: -0.11 | H200: -0.18 | I200: 5.16 | J200: 0.88 | K200: 0.43 | L200: 0.07 | M200: 0.13418479 | N200: -1.32 | O200: 0.08 | P200: -0.11333333 | Q200: -0.11583333 | R200: -0.11859894 | S200: -0.12083333 | T200: -0.12200278 | U200: -0.1230071 | V200: -2.1419231 | W200: =+(G200-E200)*4 -> -2.52 | X200: =+(G200-F200)*4 -> -1.8 | Y200: 0.41620908 | Z200: -1.9247404 | AC200: 39903 | AD200: =+V200 -> -2.1419231
A201: 43921 | E201: 0.6 | F201: 0.12 | G201: -0.12 | J201: 1.08 | K201: 0.43 | L201: 0.07 | O201: 0.08 | P201: -0.11916667 | Q201: -0.1225 | R201: -0.12556208 | S201: -0.1275 | T201: -0.12781808 | U201: -0.12799107 | V201: -2.2390573 | W201: =+(G201-E201)*4 -> -2.88 | X201: =+(G201-F201)*4 -> -0.96 | Y201: 0.14208487 | Z201: -2.0057933 | AC201: 39994 | AD201: =+V201 -> -2.2390573
A202: 44012 | E202: 1.1 | F202: 0.3 | G202: -0.12 | J202: 1.5 | K202: 0.43 | L202: 0.12 | O202: 0.08 | P202: -0.11666667 | Q202: -0.11916667 | R202: -0.12182175 | S202: -0.12416667 | T202: -0.1259922 | U202: -0.12764122 | V202: -2.2626273 | W202: =+(G202-E202)*4 -> -4.88 | X202: =+(G202-F202)*4 -> -1.68 | Y202: 0.13207053 | Z202: -1.9907029 | AC202: 40086 | AD202: =+V202 -> -2.2626273
A203: 44104 | E203: -1 | F203: -0.07 | G203: -0.13 | J203: 1.17 | K203: 0.4 | L203: 0.04 | O203: 0.02 | P203: -0.11666667 | Q203: -0.12 | R203: -0.12273521 | S203: -0.125 | T203: -0.12682553 | U203: -0.12847455 | V203: -2.451332 | W203: =+(G203-E203)*4 -> 3.48 | X203: =+(G203-F203)*4 -> -0.24 | Y203: 0.14535133 | Z203: -1.9801808 | AC203: 40178 | AD203: =+V203 -> -2.451332
A204: 44196 | B204: 0.32 | C204: -5.41 | D204: -0.03 | E204: 0.7 | F204: 0.06 | G204: -0.14 | H204: -3.18 | I204: 1 | J204: 1.01 | K204: 0.43 | L204: -0.01 | M204: -5.6621607 | N204: -0.04 | O204: 0.03 | P204: -0.12 | Q204: -0.1225 | R204: -0.12557309 | S204: -0.12833333 | T204: -0.13028946 | U204: -0.13201656 | V204: -1.581962 | W204: =+(G204-E204)*4 -> -3.36 | X204: =+(G204-F204)*4 -> -0.8 | Y204: 0.14033232 | Z204: -1.9841297 | AA204: =+Y204-$Y$204 -> 0 | AB204: =+Z204-$Z$204 -> 0 | AC204: 40268 | AD204: =+V204 -> -1.581962 | AE204: =-AA204+AB204 -> 0
A205: 44286 | B205: 0.62 | C205: -5.26 | D205: -0.42 | E205: 0.64 | F205: 0.74 | G205: -0.14 | H205: -1.13 | I205: 0.43 | J205: 0.82 | K205: 0.43 | L205: 0.01 | M205: 0.66754119 | N205: 1.17 | O205: 0.06 | P205: -0.12 | Q205: -0.12166667 | R205: -0.12246795 | S205: -0.12333333 | T205: -0.12409455 | U205: -0.1249359 | V205: -2.2039436 | W205: =+(G205-E205)*4 -> -3.12 | X205: =+(G205-F205)*4 -> -3.52 | Y205: 0.37458055 | Z205: -2.0864302 | AA205: =+Y205-$Y$204 -> 0.23424823 | AB205: =+Z205-$Z$204 -> -0.10230059 | AC205: 40359 | AD205: =+V205 -> -2.2039436 | AE205: =-AA205+AB205 -> -0.33654881
A206: 44377 | B206: 2.18 | C206: -2.13 | D206: 0.58 | E206: 0.31 | F206: 0.14 | G206: -0.14 | H206: 3.96 | I206: 2.64 | J206: 0.75 | K206: 0.43 | L206: 0.07 | M206: -1.8656649 | N206: 3.47 | O206: 0.06 | P206: -0.12 | Q206: -0.12 | R206: -0.12125 | S206: -0.1225 | T206: -0.12248047 | U206: -0.12234375 | V206: -2.5361337 | W206: =+(G206-E206)*4 -> -1.8 | X206: =+(G206-F206)*4 -> -1.12 | Y206: 0.24991106 | Z206: -1.6854719 | AA206: =+Y206-$Y$204 -> 0.10957874 | AB206: =+Z206-$Z$204 -> 0.29865774 | AC206: 40451 | AD206: =+V206 -> -2.5361337 | AE206: =-AA206+AB206 -> 0.189079
A207: 44469 | B207: 1.77 | C207: -0.77 | D207: 0.67 | E207: 1.22 | F207: 0.69 | G207: -0.14 | H207: 3.62 | I207: 0.87 | J207: 0.75 | K207: 0.45 | L207: 0.04 | M207: -0.65900646 | N207: 1.03 | O207: 0.05 | P207: -0.12 | Q207: -0.12 | R207: -0.12125 | S207: -0.1225 | T207: -0.12248047 | U207: -0.12234375 | V207: -2.1082716 | W207: =+(G207-E207)*4 -> -5.44 | X207: =+(G207-F207)*4 -> -3.32 | Y207: 0.22497577 | Z207: -1.694325 | AA207: =+Y207-$Y$204 -> 0.084643454 | AB207: =+Z207-$Z$204 -> 0.28980462 | AC207: 40543 | AD207: =+V207 -> -2.1082716 | AE207: =-AA207+AB207 -> 0.20516117
A208: 44561 | B208: 0.68 | C208: -0.15 | D208: -0.23 | E208: 1.15 | F208: 0.84 | G208: -0.15 | H208: 0.39 | I208: 0.57 | J208: 0.83 | K208: 0.48 | L208: 0.08 | M208: -0.28819237 | N208: 0 | O208: 0.07 | P208: -0.12 | Q208: -0.12 | R208: -0.12 | S208: -0.12 | T208: NaN | U208: NaN | V208: -2.6894907 | W208: =+(G208-E208)*4 -> -5.2 | X208: =+(G208-F208)*4 -> -3.96 | Y208: 0.33566261 | Z208: -1.5958002 | AA208: =+Y208-$Y$204 -> 0.19533029 | AB208: =+Z208-$Z$204 -> 0.38832948 | AC208: 40633 | AD208: =+V208 -> -2.6894907 | AE208: =-AA208+AB208 -> 0.19299919
...

Sheet ConvenienceYield_fullsample
A1: Date | B1: ConvenienceYield_EA | C1: Euro area Convenience Yield | D1: ConvenienceYield_US | E1: US Convenience Yield | F1: Euro area Convenience Yield
A2: 25933 | B2: 0.19705207 | C2: 0.78820828
A3: 26023 | B3: 0.25928649 | C3: 1.0371459
A4: 26114 | B4: 0.0071246574 | C4: 0.02849863
A5: 26206 | B5: 0.074842244 | C5: 0.29936898 | D5: 0.020592286 | E5: 0.082369144
A6: 26298 | B6: 0.12684548 | C6: 0.50738191 | D6: -0.27546809 | E6: -1.1018723
A7: 26389 | B7: 0.090544924 | C7: 0.3621797 | D7: -0.26937696 | E7: -1.0775078
A8: 26480 | B8: -0.064440652 | C8: -0.25776261 | D8: -0.1959892 | E8: -0.7839568
A9: 26572 | B9: -0.090438669 | C9: -0.36175467 | D9: -0.12756202 | E9: -0.51024809
A10: 26664 | B10: 0.084285096 | C10: 0.33714038 | D10: -0.09161451 | E10: -0.36645804
A11: 26754 | B11: 0.19941552 | C11: 0.79766206 | D11: -0.26337683 | E11: -1.0535073
A12: 26845 | B12: 0.072136016 | C12: 0.28854406 | D12: -0.059254174 | E12: -0.2370167
A13: 26937 | B13: 0.32860025 | C13: 1.314401 | D13: -0.09063779 | E13: -0.36255116
A14: 27029 | B14: 0.43112249 | C14: 1.7244899 | D14: 0.043436992 | E14: 0.17374797
A15: 27119 | B15: 0.57994139 | C15: 2.3197656 | D15: 0.19347952 | E15: 0.77391809
A16: 27210 | B16: 0.43512458 | C16: 1.7404983 | D16: 0.099058446 | E16: 0.39623379
... A217: 45565 | B217: 0.068277438 | C217: 0.27310975 | D217: 0.12220019 | E217: 0.48880075
A218: 45657 | D218: 0.10860395 | E218: 0.43441581
A219: 45747 | D219: 0.060178762 | E219: 0.24071505
A220: 45838 | D220: 0.063904098 | E220: 0.25561639

Sheet EA_output_obs_with_text
A1: date | B1: g_sh | C1: b_liqtil_sh | D1: b_liqp_sh | E1: b_safetil_sh | F1: b_safep_sh | G1: mu_sh | H1: z_sh | I1: lambda_f_sh | J1: lambda_w_sh | K1: rm_sh | L1: sigma_omega_sh | M1: mu_e_sh | N1: gamma_sh | O1: pi_star_sh | P1: lr_sh | Q1: zp_sh | R1: tfp_sh | S1: gdpdef_sh | T1: corepce_sh | U1: gdp_sh | V1: gdi_sh | W1: BBB_sh | X1: AAA_sh | Y1: rm_shl1 | Z1: rm_shl2 | AA1: rm_shl3 | AB1: rm_shl4 | AC1: rm_shl5 | AD1: rm_shl6 | AE1: dettrend | AF1: detrendedMean | AH1: rm_sh | AI1: =Y1 -> rm_shl1 | AJ1: =Z1 -> rm_shl2 | AK1: =AA1 -> rm_shl3 | AL1: =AB1 -> rm_shl4 | AM1: =AC1 -> rm_shl5 | AN1: =AD1 -> rm_shl6 | AQ1: Plot | AR1: =A1 -> date | AS1: =AF1 -> detrendedMean | AT1: Surprise Policy (t) | AU1: Fgsum | AV1: Anticipated (t+1|t) | AW1: Anticipated (t+2|t) | AX1: Anticipated (t+3|t) | AY1: Anticipated (t+4|t) | AZ1: Anticipated (t+5|t) | BA1: Anticipated (t+6|t) | BB1: Combined | BC1: date | BD1: rm_sh | BE1: Fgsum
A2: 39172 | B2: 0.79440409 | C2: 0.02411441 | D2: -0.18874911 | E2: 1.9449427 | F2: -0.70213708 | G2: -4.2282539 | H2: -0.014989197 | I2: -0.08556396 | J2: 0.0021457165 | K2: 0.75451741 | L2: 1.2749568 | M2: 0 | N2: 0 | O2: -1.162726 | P2: 0 | Q2: -0.10386809 | R2: 0 | S2: 0 | T2: 0 | U2: 0 | V2: 0 | W2: 0 | X2: 0 | Y2: 0 | Z2: 0 | AA2: 0 | AB2: 0 | AC2: 0 | AD2: 0 | AE2: -7.2979494 | AF2: -8.9891556 | AH2: =K2+Y2-Y2/100 -> 0.75451741 | AI2: =Y2 -> 0 | AJ2: =Z2 -> 0 | AK2: =AA2 -> 0 | AL2: =AB2 -> 0 | AM2: =AC2 -> 0 | AN2: =AD2 -> 0 | AR2: =A2 -> 39172 | AS2: =AF2*4+2 -> -33.956622 | AU2: =SUM(AV2:BA2) -> 0 | AV2: =AI2 -> 0 | AW2: =AJ2 -> 0 | AX2: =AK2 -> 0 | AY2: =AL2 -> 0 | AZ2: =AM2 -> 0 | BA2: =AN2 -> 0 | BB2: =SUM(AT2:BA2) -> 0 | BC2: =AR2 -> 39172 | BD2: =AT2-$AT$2 -> 0 | BE2: =AU2-$AU$2 -> 0
A3: 39263 | B3: 0.54565261 | C3: 0.047237273 | D3: -0.24871527 | E3: 2.3787568 | F3: -0.64132794 | G3: -4.514584 | H3: -0.0029421649 | I3: -0.098584141 | J3: 0.001271583 | K3: 0.85061535 | L3: 1.3178767 | M3: 0 | N3: 0 | O3: -1.1139904 | P3: 0 | Q3: -0.091694204 | R3: 0 | S3: 0 | T3: 0 | U3: 0 | V3: 0 | W3: 0 | X3: 0 | Y3: 0 | Z3: 0 | AA3: 0 | AB3: 0 | AC3: 0 | AD3: 0 | AE3: -7.3083574 | AF3: -8.8787852 | AH3: =K3+Y3-Y3/100 -> 0.85061535 | AI3: =Y3 -> 0 | AJ3: =Z3 -> 0 | AK3: =AA3 -> 0 | AL3: =AB3 -> 0 | AM3: =AC3 -> 0 | AN3: =AD3 -> 0 | AR3: =A3 -> 39263 | AS3: =AF3*4+2 -> -33.515141 | AU3: =SUM(AV3:BA3) -> 0 | AV3: =AI3 -> 0 | AW3: =AJ3 -> 0 | AX3: =AK3 -> 0 | AY3: =AL3 -> 0 | AZ3: =AM3 -> 0 | BA3: =AN3 -> 0 | BB3: =SUM(AT3:BA3) -> 0 | BC3: =AR3 -> 39263 | BD3: =AT3-$AT$2 -> 0 | BE3: =AU3 -> 0
A4: 39355 | B4: 0.54705815 | C4: 0.028123435 | D4: -0.36446568 | E4: 2.5384113 | F4: -0.58576346 | G4: -4.7104491 | H4: 0.0068425824 | I4: -0.10249897 | J4: -9.7226422e-05 | K4: 0.76040116 | L4: 1.356224 | M4: 0 | N4: 0 | O4: -0.93968395 | P4: 0 | Q4: -0.013590541 | R4: 0 | S4: 0 | T4: 0 | U4: 0 | V4: 0 | W4: 0 | X4: 0 | Y4: 0 | Z4: 0 | AA4: 0 | AB4: 0 | AC4: 0 | AD4: 0 | AE4: -7.3186178 | AF4: -8.7981061 | AH4: =K4+Y4-Y4/100 -> 0.76040116 | AI4: =Y4 -> 0 | AJ4: =Z4 -> 0 | AK4: =AA4 -> 0 | AL4: =AB4 -> 0 | AM4: =AC4 -> 0 | AN4: =AD4 -> 0 | AR4: =A4 -> 39355 | AS4: =AF4*4+2 -> -33.192424 | AU4: =SUM(AV4:BA4) -> 0 | AV4: =AI4 -> 0 | AW4: =AJ4 -> 0 | AX4: =AK4 -> 0 | AY4: =AL4 -> 0 | AZ4: =AM4 -> 0 | BA4: =AN4 -> 0 | BB4: =SUM(AT4:BA4) -> 0 | BC4: =AR4 -> 39355 | BD4: =AT4-$AT$2 -> 0 | BE4: =AU4 -> 0
A5: 39447 | B5: 0.41308918 | C5: 0.047267991 | D5: -0.60637151 | E5: 2.932617 | F5: -0.58276727 | G5: -4.8678855 | H5: 0.00043125868 | I5: -0.10810363 | J5: -0.00011608262 | K5: 0.81504165 | L5: 1.4063924 | M5: 0 | N5: 0 | O5: -0.89426047 | P5: 0 | Q5: -0.028454827 | R5: 0 | S5: 0 | T5: 0 | U5: 0 | V5: 0 | W5: 0 | X5: 0 | Y5: 0 | Z5: 0 | AA5: 0 | AB5: 0 | AC5: 0 | AD5: 0 | AE5: -7.3287315 | AF5: -8.8018512 | AH5: =K5+Y5-Y5/100 -> 0.81504165 | AI5: =Y5 -> 0 | AJ5: =Z5 -> 0 | AK5: =AA5 -> 0 | AL5: =AB5 -> 0 | AM5: =AC5 -> 0 | AN5: =AD5 -> 0 | AR5: =A5 -> 39447 | AS5: =AF5*4+2 -> -33.207405 | AU5: =SUM(AV5:BA5) -> 0 | AV5: =AI5 -> 0 | AW5: =AJ5 -> 0 | AX5: =AK5 -> 0 | AY5: =AL5 -> 0 | AZ5: =AM5 -> 0 | BA5: =AN5 -> 0 | BB5: =SUM(AT5:BA5) -> 0 | BC5: =AR5 -> 39447 | BD5: =AT5-$AT$2 -> 0 | BE5: =AU5 -> 0
A6: 39538 | B6: 0.38144958 | C6: 0.040044207 | D6: -0.76261568 | E6: 2.9440803 | F6: -0.60451552 | G6: -4.9183402 | H6: -0.0049381687 | I6: -0.11784446 | J6: 0.0030439982 | K6: 0.97095784 | L6: 1.408865 | M6: 0 | N6: 0 | O6: -0.71988047 | P6: 0 | Q6: 0.013774859 | R6: 0 | S6: 0 | T6: 0 | U6: 0 | V6: 0 | W6: 0 | X6: 0 | Y6: 0 | Z6: 0 | AA6: 0 | AB6: 0 | AC6: 0 | AD6: 0 | AE6: -7.3386994 | AF6: -8.7046181 | AH6: =K6+Y6-Y6/100 -> 0.97095784 | AI6: =Y6 -> 0 | AJ6: =Z6 -> 0 | AK6: =AA6 -> 0 | AL6: =AB6 -> 0 | AM6: =AC6 -> 0 | AN6: =AD6 -> 0 | AR6: =A6 -> 39538 | AS6: =AF6*4+2 -> -32.818472 | AU6: =SUM(AV6:BA6) -> 0 | AV6: =AI6 -> 0 | AW6: =AJ6 -> 0 | AX6: =AK6 -> 0 | AY6: =AL6 -> 0 | AZ6: =AM6 -> 0 | BA6: =AN6 -> 0 | BB6: =SUM(AT6:BA6) -> 0 | BC6: =AR6 -> 39538 | BD6: =AT6-$AT$2 -> 0 | BE6: =AU6 -> 0
A7: 39629 | B7: 0.27911994 | C7: 0.055219855 | D7: -0.87797518 | E7: 2.9986394 | F7: -0.64437232 | G7: -5.0257811 | H7: -0.0041234996 | I7: -0.11677837 | J7: 0.00044371178 | K7: 0.74062639 | L7: 1.4092967 | M7: 0 | N7: 0 | O7: -0.68379726 | P7: 0 | Q7: 0.087977681 | R7: 0 | S7: 0 | T7: 0 | U7: 0 | V7: 0 | W7: 0 | X7: 0 | Y7: 0 | Z7: 0 | AA7: 0 | AB7: 0 | AC7: 0 | AD7: 0 | AE7: -7.3485225 | AF7: -9.1300265 | AH7: =K7+Y7-Y7/100 -> 0.74062639 | AI7: =Y7 -> 0 | AJ7: =Z7 -> 0 | AK7: =AA7 -> 0 | AL7: =AB7 -> 0 | AM7: =AC7 -> 0 | AN7: =AD7 -> 0 | AR7: =A7 -> 39629 | AS7: =AF7*4+2 -> -34.520106 | AU7: =SUM(AV7:BA7) -> 0 | AV7: =AI7 -> 0 | AW7: =AJ7 -> 0 | AX7: =AK7 -> 0 | AY7: =AL7 -> 0 | AZ7: =AM7 -> 0 | BA7: =AN7 -> 0 | BB7: =SUM(AT7:BA7) -> 0 | BC7: =AR7 -> 39629 | BD7: =AT7-$AT$2 -> 0 | BE7: =AU7 -> 0
A8: 39721 | B8: -0.027537173 | C8: 0.069966171 | D8: -0.94524939 | E8: 2.8937613 | F8: -0.66448329 | G8: -5.0063443 | H8: -0.023667347 | I8: -0.098479418 | J8: 0.0045890535 | K8: 0.44959469 | L8: 1.3685364 | M8: 0 | N8: 0 | O8: -0.49492961 | P8: 0 | Q8: 0.17729326 | R8: 0 | S8: 0 | T8: 0 | U8: 0 | V8: 0 | W8: 0 | X8: 0 | Y8: 0 | Z8: 0 | AA8: 0 | AB8: 0 | AC8: 0 | AD8: 0 | AE8: -7.3582018 | AF8: -9.6551515 | AH8: =K8+Y8-Y8/100 -> 0.44959469 | AI8: =Y8 -> 0 | AJ8: =Z8 -> 0 | AK8: =AA8 -> 0 | AL8: =AB8 -> 0 | AM8: =AC8 -> 0 | AN8: =AD8 -> 0 | AR8: =A8 -> 39721 | AS8: =AF8*4+2 -> -36.620606 | AT8: =AH8-$AH$8 -> 0 | AU8: =SUM(AV8:BA8) -> 0 | AV8: =AI8 -> 0 | AW8: =AJ8 -> 0 | AX8: =AK8 -> 0 | AY8: =AL8 -> 0 | AZ8: =AM8 -> 0 | BA8: =AN8 -> 0 | BB8: =SUM(AT8:BA8) -> 0 | BC8: =AR8 -> 39721 | BD8: =AT8-$AT$2 -> 0 | BE8: =AU8 -> 0
A9: 39813 | B9: -0.099277021 | C9: 0.017249607 | D9: -1.3049743 | E9: 2.1501178 | F9: -0.84702014 | G9: -4.4528781 | H9: 0.027128099 | I9: -0.078488213 | J9: 0.0033151854 | K9: 0.32622877 | L9: 1.241816 | M9: 0 | N9: 0 | O9: -0.2507942 | P9: 0 | Q9: 0.46263743 | R9: 0 | S9: 0 | T9: 0 | U9: 0 | V9: 0 | W9: 0 | X9: 0 | Y9: 0.096951586 | Z9: -0.014225866 | AA9: -0.026628583 | AB9: -0.0060620762 | AC9: -0.0037695085 | AD9: -0.0032380133 | AE9: -7.3677382 | AF9: -10.12965 | AH9: =K9+Y9-Y9/100 -> 0.42221084 | AI9: =Y9/1010 -> 9.5991669e-05 | AJ9: =Z9 -> -0.014225866 | AK9: =AA9 -> -0.026628583 | AL9: =AB9 -> -0.0060620762 | AM9: =AC9 -> -0.0037695085 | AN9: =AD9 -> -0.0032380133 | AR9: =A9 -> 39813 | AS9: =AF9*4+2 -> -38.518599 | AT9: =AH9-$AH$8 -> -0.027383852 | AU9: =SUM(AV9:BA9) -> -0.053828055 | AV9: =AI9 -> 9.5991669e-05 | AW9: =AJ9 -> -0.014225866 | AX9: =AK9 -> -0.026628583 | AY9: =AL9 -> -0.0060620762 | AZ9: =AM9 -> -0.0037695085 | BA9: =AN9 -> -0.0032380133 | BB9: =SUM(AT9:AU9) -> -0.081211908 | BC9: =AR9 -> 39813 | BD9: =AT9-$AT$2 -> -0.027383852 | BE9: =AU9 -> -0.053828055
A10: 39903 | B10: -0.67955928 | C10: -0.04411321 | D10: -1.4120102 | E10: 1.1343119 | F10: -1.0676786 | G10: -4.0521954 | H10: 0.068855711 | I10: -0.048194982 | J10: -0.0027616026 | K10: 0.52735071 | L10: 1.0659297 | M10: 0 | N10: 0 | O10: -0.18402324 | P10: 0 | Q10: 0.60718337 | R10: 0 | S10: 0 | T10: 0 | U10: 0 | V10: 0 | W10: 0 | X10: 0 | Y10: 0.085468601 | Z10: -0.078568102 | AA10: -0.066043133 | AB10: -0.025775416 | AC10: -0.018493377 | AD10: -0.020410625 | AE10: -7.3771328 | AF10: -11.58786 | AH10: =K10+Y10-Y10/100 -> 0.61196463 | AI10: =Y10/1010 -> 8.4622378e-05 | AJ10: =Z10 -> -0.078568102 | AK10: =AA10 -> -0.066043133 | AL10: =AB10 -> -0.025775416 | AM10: =AC10 -> -0.018493377 | AN10: =AD10 -> -0.020410625 | AR10: =A10 -> 39903 | AS10: =AF10*4+2 -> -44.35144 | AT10: =AH10-$AH$8 -> 0.16236993 | AU10: =SUM(AV10:BA10) -> -0.20920603 | AV10: =AI10 -> 8.4622378e-05 | AW10: =AJ10 -> -0.078568102 | AX10: =AK10 -> -0.066043133 | AY10: =AL10 -> -0.025775416 | AZ10: =AM10 -> -0.018493377 | BA10: =AN10 -> -0.020410625 | BB10: =SUM(AT10:AU10) -> -0.046836096 | BC10: =AR10 -> 39903 | BD10: =AT10-$AT$2 -> 0.16236993 | BE10: =AU10 -> -0.20920603
A11: 39994 | B11: -0.62404783 | C11: -0.036317994 | D11: -1.2041256 | E11: 0.54841505 | F11: -1.2345088 | G11: -3.81943 | H11: 0.0099364832 | I11: -0.0020104602 | J11: -0.0044683656 | K11: 0.56962848 | L11: 0.92830503 | M11: 0 | N11: 0 | O11: -0.16251692 | P11: 0 | Q11: 0.34641923 | R11: 0 | S11: 0 | T11: 0 | U11: 0 | V11: 0 | W11: 0 | X11: 0 | Y11: 0.1089347 | Z11: -0.11513068 | AA11: -0.084555692 | AB11: -0.035476589 | AC11: -0.021715243 | AD11: -0.043017455 | AE11: -7.3863865 | AF11: -12.262069 | AH11: =K11+Y11-Y11/100 -> 0.67747384 | AI11: =Y11/1010 -> 0.00010785614 | AJ11: =Z11 -> -0.11513068 | AK11: =AA11 -> -0.084555692 | AL11: =AB11 -> -0.035476589 | AM11: =AC11 -> -0.021715243 | AN11: =AD11 -> -0.043017455 | AR11: =A11 -> 39994 | AS11: =AF11*4+2 -> -47.048277 | AT11: =AH11-$AH$8 -> 0.22787914 | AU11: =SUM(AV11:BA11) -> -0.2997878 | AV11: =AI11 -> 0.00010785614 | AW11: =AJ11 -> -0.11513068 | AX11: =AK11 -> -0.084555692 | AY11: =AL11 -> -0.035476589 | AZ11: =AM11 -> -0.021715243 | BA11: =AN11 -> -0.043017455 | BB11: =SUM(AT11:AU11) -> -0.071908661 | BC11: =AR11 -> 39994 | BD11: =AT11-$AT$2 -> 0.22787914 | BE11: =AU11 -> -0.2997878
A12: 40086 | B12: -0.40423119 | C12: -0.029048409 | D12: -0.74062671 | E12: 0.0047839767 | F12: -1.3873767 | G12: -3.8241107 | H12: -0.0068837807 | I12: 0.053772874 | J12: -0.0032065645 | K12: 0.54255724 | L12: 0.86612763 | M12: 0 | N12: 0 | O12: -0.11028082 | P12: 0 | Q12: 0.16697301 | R12: 0 | S12: 0 | T12: 0 | U12: 0 | V12: 0 | W12: 0 | X12: 0 | Y12: 0.15049233 | Z12: -0.13620158 | AA12: -0.090292884 | AB12: -0.039718513 | AC12: -0.02097176 | AD12: -0.069045326 | AE12: -7.3955005 | AF12: -12.472788 | AH12: =K12+Y12-Y12/100 -> 0.69154464 | AI12: =Y12/1010 -> 0.0001490023 | AJ12: =Z12 -> -0.13620158 | AK12: =AA12 -> -0.090292884 | AL12: =AB12 -> -0.039718513 | AM12: =AC12 -> -0.02097176 | AN12: =AD12 -> -0.069045326 | AR12: =A12 -> 40086 | AS12: =AF12*4+2 -> -47.891153 | AT12: =AH12-$AH$8 -> 0.24194995 | AU12: =SUM(AV12:BA12) -> -0.35608106 | AV12: =AI12 -> 0.0001490023 | AW12: =AJ12 -> -0.13620158 | AX12: =AK12 -> -0.090292884 | AY12: =AL12 -> -0.039718513 | AZ12: =AM12 -> -0.02097176 | BA12: =AN12 -> -0.069045326 | BB12: =SUM(AT12:AU12) -> -0.11413111 | BC12: =AR12 -> 40086 | BD12: =AT12-$AT$2 -> 0.24194995 | BE12: =AU12 -> -0.35608106
A13: 40178 | B13: -0.37614461 | C13: -0.0068644489 | D13: -0.37886897 | E13: -0.060594233 | F13: -1.5276178 | G13: -3.9205731 | H13: -0.0074823561 | I13: 0.11158562 | J13: -0.0014223044 | K13: 0.40289107 | L13: 0.82621701 | M13: 0 | N13: 0 | O13: -0.21303655 | P13: 0 | Q13: 0.043308906 | R13: 0 | S13: 0 | T13: 0 | U13: 0 | V13: 0 | W13: 0 | X13: 0 | Y13: 0.18127184 | Z13: -0.14969153 | AA13: -0.10309557 | AB13: -0.054744619 | AC13: -0.024861411 | AD13: -0.10207291 | AE13: -7.4044757 | AF13: -12.766272 | AH13: =K13+Y13-Y13/100 -> 0.58235019 | AI13: =Y13/1010 -> 0.00017947707 | AJ13: =Z13 -> -0.14969153 | AK13: =AA13 -> -0.10309557 | AL13: =AB13 -> -0.054744619 | AM13: =AC13 -> -0.024861411 | AN13: =AD13 -> -0.10207291 | AR13: =A13 -> 40178 | AS13: =AF13*4+2 -> -49.065087 | AT13: =AH13-$AH$8 -> 0.1327555 | AU13: =SUM(AV13:BA13) -> -0.43428656 | AV13: =AI13 -> 0.00017947707 | AW13: =AJ13 -> -0.14969153 | AX13: =AK13 -> -0.10309557 | AY13: =AL13 -> -0.054744619 | AZ13: =AM13 -> -0.024861411 | BA13: =AN13 -> -0.10207291 | BB13: =SUM(AT13:AU13) -> -0.30153106 | BC13: =AR13 -> 40178 | BD13: =AT13-$AT$2 -> 0.1327555 | BE13: =AU13 -> -0.43428656
A14: 40268 | B14: -0.31119265 | C14: 0.036297767 | D14: -0.062877436 | E14: -0.015785847 | F14: -1.6574653 | G14: -4.0241992 | H14: 0.0092446644 | I14: 0.16795652 | J14: -0.00098834581 | K14: 0.43460997 | L14: 0.78950016 | M14: 0 | N14: 0 | O14: -0.2886525 | P14: 0 | Q14: -0.028568436 | R14: 0 | S14: 0 | T14: 0 | U14: 0 | V14: 0 | W14: 0 | X14: 0 | Y14: 0.25787195 | Z14: -0.13637123 | AA14: -0.083466983 | AB14: -0.055640568 | AC14: -0.018913075 | AD14: -0.13434148 | AE14: -7.4133131 | AF14: -12.536295 | AH14: =K14+Y14-Y14/100 -> 0.6899032 | AI14: =Y14/1010 -> 0.00025531876 | AJ14: =Z14 -> -0.13637123 | AK14: =AA14 -> -0.083466983 | AL14: =AB14 -> -0.055640568 | AM14: =AC14 -> -0.018913075 | AN14: =AD14 -> -0.13434148 | AR14: =A14 -> 40268 | AS14: =AF14*4+2 -> -48.145181 | AT14: =AH14-$AH$8 -> 0.2403085 | AU14: =SUM(AV14:BA14) -> -0.42847802 | AV14: =AI14 -> 0.00025531876 | AW14: =AJ14 -> -0.13637123 | AX14: =AK14 -> -0.083466983 | AY14: =AL14 -> -0.055640568 | AZ14: =AM14 -> -0.018913075 | BA14: =AN14 -> -0.13434148 | BB14: =SUM(AT14:AU14) -> -0.18816952 | BC14: =AR14 -> 40268 | BD14: =AT14-$AT$2 -> 0.2403085 | BE14: =AU14 -> -0.42847802
A15: 40359 | B15: -0.25841717 | C15: 0.040478337 | D15: 0.084694475 | E15: -0.059974843 | F15: -1.81255 | G15: -4.0652931 | H15: -0.0068168954 | I15: 0.21350918 | J15: 0.0018549858 | K15: 0.32946089 | L15: 0.82323493 | M15: 0 | N15: 0 | O15: -0.31149803 | P15: 0 | Q15: -0.086432922 | R15: 0 | S15: 0 | T15: 0 | U15: 0 | V15: 0 | W15: 0 | X15: 0 | Y15: 0.34787302 | Z15: -0.11096693 | AA15: -0.039260613 | AB15: -0.035196864 | AC15: -0.0026064321 | AD15: -0.15934935 | AE15: -7.4220138 | AF15: -12.529271 | AH15: =K15+Y15-Y15/100 -> 0.67385517 | AI15: =Y15/1010 -> 0.00034442873 | AJ15: =Z15 -> -0.11096693 | AK15: =AA15 -> -0.039260613 | AL15: =AB15 -> -0.035196864 | AM15: =AC15 -> -0.0026064321 | AN15: =AD15 -> -0.15934935 | AR15: =A15 -> 40359 | AS15: =AF15*4+2 -> -48.117085 | AT15: =AH15-$AH$8 -> 0.22426048 | AU15: =SUM(AV15:BA15) -> -0.34703576 | AV15: =AI15 -> 0.00034442873 | AW15: =AJ15 -> -0.11096693 | AX15: =AK15 -> -0.039260613 | AY15: =AL15 -> -0.035196864 | AZ15: =AM15 -> -0.0026064321 | BA15: =AN15 -> -0.15934935 | BB15: =SUM(AT15:AU15) -> -0.12277529 | BC15: =AR15 -> 40359 | BD15: =AT15-$AT$2 -> 0.22426048 | BE15: =AU15 -> -0.34703576
A16: 40451 | B16: -0.23169858 | C16: 0.029387499 | D16: 0.17250025 | E16: -0.096591527 | F16: -1.9068042 | G16: -4.1622252 | H16: 0.0038856093 | I16: 0.23426002 | J16: 0.001651618 | K16: 0.10224962 | L16: 0.81099059 | M16: 0 | N16: 0 | O16: -0.24377691 | P16: 0 | Q16: -0.088917267 | R16: 0 | S16: 0 | T16: 0 | U16: 0 | V16: 0 | W16: 0 | X16: 0 | Y16: 0.43361075 | Z16: -0.11986079 | AA16: -0.019025206 | AB16: -0.024389866 | AC16: 0.010078268 | AD16: -0.18392932 | AE16: -7.430579 | AF16: -12.709184 | AH16: =K16+Y16-Y16/100 -> 0.53152427 | AI16: =Y16/1010 -> 0.00042931758 | AJ16: =Z16 -> -0.11986079 | AK16: =AA16 -> -0.019025206 | AL16: =AB16 -> -0.024389866 | AM16: =AC16 -> 0.010078268 | AN16: =AD16 -> -0.18392932 | AR16: =A16 -> 40451 | AS16: =AF16*4+2 -> -48.836734 | AT16: =AH16-$AH$8 -> 0.081929577 | AU16: =SUM(AV16:BA16) -> -0.3366976 | AV16: =AI16 -> 0.00042931758 | AW16: =AJ16 -> -0.11986079 | AX16: =AK16 -> -0.019025206 | AY16: =AL16 -> -0.024389866 | AZ16: =AM16 -> 0.010078268 | BA16: =AN16 -> -0.18392932 | BB16: =SUM(AT16:AU16) -> -0.25476802 | BC16: =AR16 -> 40451 | BD16: =AT16-$AT$2 -> 0.081929577 | BE16: =AU16 -> -0.3366976
A17: 40543 | B17: -0.32301048 | C17: 0.041795618 | D17: 0.20308203 | E17: 0.22975325 | F17: -1.9488754 | G17: -4.2894388 | H17: -0.0068388177 | I17: 0.25247478 | J17: 0.0020089001 | K17: -0.10717795 | L17: 0.81576081 | M17: 0 | N17: 0 | O17: -0.28833756 | P17: 0 | Q17: -0.1396419 | R17: 0 | S17: 0 | T17: 0 | U17: 0 | V17: 0 | W17: 0 | X17: 0 | Y17: 0.52952553 | Z17: -0.15312226 | AA17: -0.0090265201 | AB17: -0.023526577 | AC17: 0.015475587 | AD17: -0.20848881 | AE17: -7.4390095 | AF17: -12.846618 | AH17: =K17+Y17-Y17/100 -> 0.41705232 | AI17: =Y17/1010 -> 0.0005242827 | AJ17: =Z17 -> -0.15312226 | AK17: =AA17 -> -0.0090265201 | AL17: =AB17 -> -0.023526577 | AM17: =AC17 -> 0.015475587 | AN17: =AD17 -> -0.20848881 | AR17: =A17 -> 40543 | AS17: =AF17*4+2 -> -49.386472 | AT17: =AH17-$AH$8 -> -0.032542371 | AU17: =SUM(AV17:BA17) -> -0.37816429 | AV17: =AI17 -> 0.0005242827 | AW17: =AJ17 -> -0.15312226 | AX17: =AK17 -> -0.0090265201 | AY17: =AL17 -> -0.023526577 | AZ17: =AM17 -> 0.015475587 | BA17: =AN17 -> -0.20848881 | BB17: =SUM(AT17:AU17) -> -0.41070667 | BC17: =AR17 -> 40543 | BD17: =AT17-$AT$2 -> -0.032542371 | BE17: =AU17 -> -0.37816429
A18: 40633 | B18: 0.04285985 | C18: 0.028766929 | D18: 0.32115709 | E18: 0.31857464 | F18: -1.9553983 | G18: -4.4209373 | H18: 0.00046041605 | I18: 0.26062413 | J18: 0.0046516948 | K18: -0.19035776 | L18: 0.857245 | M18: 0 | N18: 0 | O18: -0.25281243 | P18: 0 | Q18: -0.10213928 | R18: 0 | S18: 0 | T18: 0 | U18: 0 | V18: 0 | W18: 0 | X18: 0 | Y18: 0.61736783 | Z18: -0.21231471 | AA18: -0.012888007 | AB18: -0.02641626 | AC18: 0.014727271 | AD18: -0.23324886 | AE18: -7.4473065 | AF18: -12.387385 | AH18: =K18+Y18-Y18/100 -> 0.42083639 | AI18: =Y18/1010 -> 0.00061125528 | AJ18: =Z18 -> -0.21231471 | AK18: =AA18 -> -0.012888007 | AL18: =AB18 -> -0.02641626 | AM18: =AC18 -> 0.014727271 | AN18: =AD18 -> -0.23324886 | AR18: =A18 -> 40633 | AS18: =AF18*4+2 -> -47.549539 | AT18: =AH18-$AH$8 -> -0.028758308 | AU18: =SUM(AV18:BA18) -> -0.46952932 | AV18: =AI18 -> 0.00061125528 | AW18: =AJ18 -> -0.21231471 | AX18: =AK18 -> -0.012888007 | AY18: =AL18 -> -0.02641626 | AZ18: =AM18 -> 0.014727271 | BA18: =AN18 -> -0.23324886 | BB18: =SUM(AT18:AU18) -> -0.49828763 | BC18: =AR18 -> 40633 | BD18: =AT18-$AT$2 -> -0.028758308 | BE18: =AU18 -> -0.46952932
A19: 40724 | B19: -0.19219843 | C19: 0.040816832 | D19: 0.51069165 | E19: 0.36637076 | F19: -2.0248131 | G19: -4.5596408 | H19: -0.0044641094 | I19: 0.26652108 | J19: 0.0072421513 | K19: -0.51738656 | L19: 0.88724014 | M19: 0 | N19: 0 | O19: -0.24927115 | P19: 0 | Q19: -0.094130747 | R19: 0 | S19: 0 | T19: 0 | U19: 0 | V19: 0 | W19: 0 | X19: 0 | Y19: 0.73124536 | Z19: -0.29190339 | AA19: -0.034467829 | AB19: -0.034623491 | AC19: 0.012088177 | AD19: -0.25736418 | AE19: -7.4554711 | AF19: -12.893519 | AH19: =K19+Y19-Y19/100 -> 0.20654635 | AI19: =Y19/1010 -> 0.00072400531 | AJ19: =Z19 -> -0.29190339 | AK19: =AA19 -> -0.034467829 | AL19: =AB19 -> -0.034623491 | AM19: =AC19 -> 0.012088177 | AN19: =AD19 -> -0.25736418 | AR19: =A19 -> 40724 | AS19: =AF19*4+2 -> -49.574075 | AT19: =AH19-$AH$8 -> -0.24304835 | AU19: =SUM(AV19:BA19) -> -0.6055467 | AV19: =AI19 -> 0.00072400531 | AW19: =AJ19 -> -0.29190339 | AX19: =AK19 -> -0.034467829 | AY19: =AL19 -> -0.034623491 | AZ19: =AM19 -> 0.012088177 | BA19: =AN19 -> -0.25736418 | BB19: =SUM(AT19:AU19) -> -0.84859505 | BC19: =AR19 -> 40724 | BD19: =AT19-$AT$2 -> -0.24304835 | BE19: =AU19 -> -0.6055467
A20: 40816 | B20: -0.17812251 | C20: 0.081421187 | D20: 0.64600126 | E20: 0.045189314 | F20: -2.2713872 | G20: -4.5801027 | H20: 0.010513239 | I20: 0.26794332 | J20: 0.0064863059 | K20: -0.80933701 | L20: 0.89324384 | M20: 0 | N20: 0 | O20: -0.23182197 | P20: 0 | Q20: -0.042579694 | R20: 0 | S20: 0 | T20: 0 | U20: 0 | V20: 0 | W20: 0 | X20: 0 | Y20: 1.0004461 | Z20: -0.33776465 | AA20: -0.019760237 | AB20: -0.017679147 | AC20: 0.030207454 | AD20: -0.25880112 | AE20: -7.4635044 | AF20: -13.229409 | AH20: =K20+Y20-Y20/100 -> 0.18110459 | AI20: =Y20/1010 -> 0.00099054066 | AJ20: =Z20 -> -0.33776465 | AK20: =AA20 -> -0.019760237 | AL20: =AB20 -> -0.017679147 | AM20: =AC20 -> 0.030207454 | AN20: =AD20 -> -0.25880112 | AR20: =A20 -> 40816 | AS20: =AF20*4+2 -> -50.917635 | AT20: =AH20-$AH$8 -> -0.2684901 | AU20: =SUM(AV20:BA20) -> -0.60280716 | AV20: =AI20 -> 0.00099054066 | AW20: =AJ20 -> -0.33776465 | AX20: =AK20 -> -0.019760237 | AY20: =AL20 -> -0.017679147 | AZ20: =AM20 -> 0.030207454 | BA20: =AN20 -> -0.25880112 | BB20: =SUM(AT20:AU20) -> -0.87129726 | BC20: =AR20 -> 40816 | BD20: =AT20-$AT$2 -> -0.2684901 | BE20: =AU20 -> -0.60280716
... A132: 51043 | B132: -0.043141873 | C132: -0.00014191675 | D132: -0.060150045 | E132: 0.00016375639 | F132: 0.077003819 | G132: -0.017761409 | H132: 0.10657899 | I132: -0.12938709 | J132: -0.23383062 | K132: -0.0013647494 | L132: 0.028622522 | M132: 0 | N132: 0 | O132: 0.44750605 | P132: 0 | Q132: 0.30446726 | R132: 0 | S132: 0 | T132: 0 | U132: 0 | V132: 0 | W132: 0 | X132: 0 | Y132: 0.0014171204 | Z132: -0.0014470184 | AA132: 0.00054189822 | AB132: -0.00029329794 | AC132: 0.0013717805 | AD132: 0.0037302372 | AE132: -0.072867892 | AF132: 0.418171 | AH132: =K132+Y132-Y132/100 -> 3.8199787e-05 | AI132: =Y132/1010 -> 1.4030895e-06 | AJ132: =Z132 -> -0.0014470184 | AK132: =AA132 -> 0.00054189822 | AL132: =AB132 -> -0.00029329794 | AM132: =AC132 -> 0.0013717805 | AN132: =AD132 -> 0.0037302372 | AR132: =A132 -> 51043 | AS132: =AF132*4+2 -> 3.672684 | AT132: =AH132-$AH$8 -> -0.44955649 | AU132: =SUM(AV132:BA132) -> 0.0039050027 | AV132: =AI132 -> 1.4030895e-06 | AW132: =AJ132 -> -0.0014470184 | AX132: =AK132 -> 0.00054189822 | AY132: =AL132 -> -0.00029329794 | AZ132: =AM132 -> 0.0013717805 | BA132: =AN132 -> 0.0037302372 | BB132: =SUM(AT132:AU132) -> -0.44565149 | BC132: =AR132 -> 51043 | BD132: =AT132-$AT$2 -> -0.44955649 | BE132: =AU132 -> 0.0039050027

Sheet EA_output_obs_with_text_backup
A1: date | B1: g_sh | C1: b_liqtil_sh | D1: b_liqp_sh | E1: b_safetil_sh | F1: b_safep_sh | G1: mu_sh | H1: z_sh | I1: lambda_f_sh | J1: lambda_w_sh | K1: rm_sh | L1: sigma_omega_sh | M1: mu_e_sh | N1: gamma_sh | O1: pi_star_sh | P1: lr_sh | Q1: zp_sh | R1: tfp_sh | S1: gdpdef_sh | T1: corepce_sh | U1: gdp_sh | V1: gdi_sh | W1: BBB_sh | X1: AAA_sh | Y1: rm_shl1 | Z1: rm_shl2 | AA1: rm_shl3 | AB1: rm_shl4 | AC1: rm_shl5 | AD1: rm_shl6 | AE1: dettrend | AF1: detrendedMean | AH1: rm_sh | AI1: =Y1 -> rm_shl1 | AJ1: =Z1 -> rm_shl2 | AK1: =AA1 -> rm_shl3 | AL1: =AB1 -> rm_shl4 | AM1: =AC1 -> rm_shl5 | AN1: =AD1 -> rm_shl6 | AQ1: Plot | AR1: =A1 -> date | AS1: =AF1 -> detrendedMean | AT1: Monetary Policy | AU1: Fgsum | AV1: FG1 | AW1: FG2 | AX1: FG3 | AY1: FG4 | AZ1: FG5 | BA1: FG6 | BC1: date | BD1: rm_sh | BE1: Fgsum
A2: 39172 | B2: 2.5363082 | C2: -0.18049422 | D2: -5.026568 | E2: -0.00051095038 | F2: 6.5669289 | G2: 14.167348 | H2: -0.028136165 | I2: 0.24489409 | J2: -0.05757504 | K2: 2.5748891 | L2: 0.26640205 | M2: 0 | N2: 0 | O2: 0.43018806 | P2: 0 | Q2: -0.017234495 | R2: 0 | S2: 0 | T2: 0 | U2: 0 | V2: 0 | W2: 0 | X2: 0 | Y2: 0 | Z2: 0 | AA2: 0 | AB2: 0 | AC2: 0 | AD2: 0 | AE2: 7.4683269 | AF2: 28.944766 | AH2: =K2+Y2-Y2/100 -> 2.5748891 | AI2: =Y2 -> 0 | AJ2: =Z2 -> 0 | AK2: =AA2 -> 0 | AL2: =AB2 -> 0 | AM2: =AC2 -> 0 | AN2: =AD2 -> 0 | AR2: =A2 -> 39172 | AS2: =AF2*4+2 -> 117.77907 | AT2: =AH2 -> 2.5748891 | AU2: =SUM(AV2:BA2) -> 0 | AV2: =AI2 -> 0 | AW2: =AJ2 -> 0 | AX2: =AK2 -> 0 | AY2: =AL2 -> 0 | AZ2: =AM2 -> 0 | BA2: =AN2 -> 0 | BC2: =AR2 -> 39172 | BD2: =AT2-$AT$2 -> 0 | BE2: =AU2-$AU$2 -> 0
A3: 39263 | B3: 2.1888377 | C3: -0.10201437 | D3: -5.4151599 | E3: 0.000432913 | F3: 7.4635098 | G3: 14.09681 | H3: -0.017718534 | I3: 0.23729294 | J3: -0.058482715 | K3: 2.6753132 | L3: 0.30577422 | M3: 0 | N3: 0 | O3: 0.44487798 | P3: 0 | Q3: -0.025392488 | R3: 0 | S3: 0 | T3: 0 | U3: 0 | V3: 0 | W3: 0 | X3: 0 | Y3: 0 | Z3: 0 | AA3: 0 | AB3: 0 | AC3: 0 | AD3: 0 | AE3: 7.445194 | AF3: 29.239275 | AH3: =K3+Y3-Y3/100 -> 2.6753132 | AI3: =Y3 -> 0 | AJ3: =Z3 -> 0 | AK3: =AA3 -> 0 | AL3: =AB3 -> 0 | AM3: =AC3 -> 0 | AN3: =AD3 -> 0 | AR3: =A3 -> 39263 | AS3: =AF3*4+2 -> 118.9571 | AT3: =AH3 -> 2.6753132 | AU3: =SUM(AV3:BA3) -> 0 | AV3: =AI3 -> 0 | AW3: =AJ3 -> 0 | AX3: =AK3 -> 0 | AY3: =AL3 -> 0 | AZ3: =AM3 -> 0 | BA3: =AN3 -> 0 | BC3: =AR3 -> 39263 | BD3: =AT3-$AT$2 -> 0.10042406 | BE3: =AU3 -> 0
A4: 39355 | B4: 2.3018784 | C4: -0.18582521 | D4: -5.7797078 | E4: -0.00024449342 | F4: 8.1065585 | G4: 14.1473 | H4: 0.0099248504 | I4: 0.31153154 | J4: -0.061960515 | K4: 2.506994 | L4: 0.30064004 | M4: 0 | N4: 0 | O4: 0.46631618 | P4: 0 | Q4: -0.040553603 | R4: 0 | S4: 0 | T4: 0 | U4: 0 | V4: 0 | W4: 0 | X4: 0 | Y4: 0 | Z4: 0 | AA4: 0 | AB4: 0 | AC4: 0 | AD4: 0 | AE4: 7.4221487 | AF4: 29.505 | AH4: =K4+Y4-Y4/100 -> 2.506994 | AI4: =Y4 -> 0 | AJ4: =Z4 -> 0 | AK4: =AA4 -> 0 | AL4: =AB4 -> 0 | AM4: =AC4 -> 0 | AN4: =AD4 -> 0 | AR4: =A4 -> 39355 | AS4: =AF4*4+2 -> 120.02 | AT4: =AH4 -> 2.506994 | AU4: =SUM(AV4:BA4) -> 0 | AV4: =AI4 -> 0 | AW4: =AJ4 -> 0 | AX4: =AK4 -> 0 | AY4: =AL4 -> 0 | AZ4: =AM4 -> 0 | BA4: =AN4 -> 0 | BC4: =AR4 -> 39355 | BD4: =AT4-$AT$2 -> -0.067895149 | BE4: =AU4 -> 0
A5: 39447 | B5: 2.0031345 | C5: -0.059805901 | D5: -6.0906698 | E5: 0.00065881996 | F5: 8.5748649 | G5: 14.245587 | H5: 0.01546791 | I5: 0.248964 | J5: -0.063329388 | K5: 2.6392114 | L5: 0.34661216 | M5: 0 | N5: 0 | O5: 0.47709801 | P5: 0 | Q5: -0.045182361 | R5: 0 | S5: 0 | T5: 0 | U5: 0 | V5: 0 | W5: 0 | X5: 0 | Y5: 0 | Z5: 0 | AA5: 0 | AB5: 0 | AC5: 0 | AD5: 0 | AE5: 7.3991902 | AF5: 29.691802 | AH5: =K5+Y5-Y5/100 -> 2.6392114 | AI5: =Y5 -> 0 | AJ5: =Z5 -> 0 | AK5: =AA5 -> 0 | AL5: =AB5 -> 0 | AM5: =AC5 -> 0 | AN5: =AD5 -> 0 | AR5: =A5 -> 39447 | AS5: =AF5*4+2 -> 120.76721 | AT5: =AH5 -> 2.6392114 | AU5: =SUM(AV5:BA5) -> 0 | AV5: =AI5 -> 0 | AW5: =AJ5 -> 0 | AX5: =AK5 -> 0 | AY5: =AL5 -> 0 | AZ5: =AM5 -> 0 | BA5: =AN5 -> 0 | BC5: =AR5 -> 39447 | BD5: =AT5-$AT$2 -> 0.064322263 | BE5: =AU5 -> 0
A6: 39538 | B6: 2.0564368 | C6: -0.17410702 | D6: -6.2409237 | E6: -8.1488331e-05 | F6: 8.7254233 | G6: 14.470225 | H6: -0.053129904 | I6: 0.30778976 | J6: -0.066874845 | K6: 2.9688718 | L6: 0.14427824 | M6: 0 | N6: 0 | O6: 0.49713924 | P6: 0 | Q6: -0.050515251 | R6: 0 | S6: 0 | T6: 0 | U6: 0 | V6: 0 | W6: 0 | X6: 0 | Y6: 0 | Z6: 0 | AA6: 0 | AB6: 0 | AC6: 0 | AD6: 0 | AE6: 7.376318 | AF6: 29.96085 | AH6: =K6+Y6-Y6/100 -> 2.9688718 | AI6: =Y6 -> 0 | AJ6: =Z6 -> 0 | AK6: =AA6 -> 0 | AL6: =AB6 -> 0 | AM6: =AC6 -> 0 | AN6: =AD6 -> 0 | AR6: =A6 -> 39538 | AS6: =AF6*4+2 -> 121.8434 | AT6: =AH6 -> 2.9688718 | AU6: =SUM(AV6:BA6) -> 0 | AV6: =AI6 -> 0 | AW6: =AJ6 -> 0 | AX6: =AK6 -> 0 | AY6: =AL6 -> 0 | AZ6: =AM6 -> 0 | BA6: =AN6 -> 0 | BC6: =AR6 -> 39538 | BD6: =AT6-$AT$2 -> 0.39398266 | BE6: =AU6 -> 0
A7: 39629 | B7: 1.9437086 | C7: -0.25968328 | D7: -6.4409474 | E7: 0.00050280931 | F7: 9.1352305 | G7: 14.602996 | H7: -0.0028221986 | I7: 0.2461009 | J7: -0.063600816 | K7: 2.6992023 | L7: 0.031560885 | M7: 0 | N7: 0 | O7: 0.50964208 | P7: 0 | Q7: -0.07357073 | R7: 0 | S7: 0 | T7: 0 | U7: 0 | V7: 0 | W7: 0 | X7: 0 | Y7: 0 | Z7: 0 | AA7: 0 | AB7: 0 | AC7: 0 | AD7: 0 | AE7: 7.3535315 | AF7: 29.681851 | AH7: =K7+Y7-Y7/100 -> 2.6992023 | AI7: =Y7 -> 0 | AJ7: =Z7 -> 0 | AK7: =AA7 -> 0 | AL7: =AB7 -> 0 | AM7: =AC7 -> 0 | AN7: =AD7 -> 0 | AR7: =A7 -> 39629 | AS7: =AF7*4+2 -> 120.7274 | AT7: =AH7 -> 2.6992023 | AU7: =SUM(AV7:BA7) -> 0 | AV7: =AI7 -> 0 | AW7: =AJ7 -> 0 | AX7: =AK7 -> 0 | AY7: =AL7 -> 0 | AZ7: =AM7 -> 0 | BA7: =AN7 -> 0 | BC7: =AR7 -> 39629 | BD7: =AT7-$AT$2 -> 0.12431319 | BE7: =AU7 -> 0
A8: 39721 | B8: 1.5553725 | C8: -0.47264141 | D8: -6.5811779 | E8: 0.00045985532 | F8: 9.4802157 | G8: 14.927721 | H8: 0.027059605 | I8: 0.29587019 | J8: -0.068185466 | K8: 2.5210749 | L8: -0.16240357 | M8: 0 | N8: 0 | O8: 0.53344519 | P8: 0 | Q8: -0.081467541 | R8: 0 | S8: 0 | T8: 0 | U8: 0 | V8: 0 | W8: 0 | X8: 0 | Y8: 0 | Z8: 0 | AA8: 0 | AB8: 0 | AC8: 0 | AD8: 0 | AE8: 7.3308301 | AF8: 29.306173 | AH8: =K8+Y8-Y8/100 -> 2.5210749 | AI8: =Y8 -> 0 | AJ8: =Z8 -> 0 | AK8: =AA8 -> 0 | AL8: =AB8 -> 0 | AM8: =AC8 -> 0 | AN8: =AD8 -> 0 | AR8: =A8 -> 39721 | AS8: =AF8*4+2 -> 119.22469 | AT8: =AH8 -> 2.5210749 | AU8: =SUM(AV8:BA8) -> 0 | AV8: =AI8 -> 0 | AW8: =AJ8 -> 0 | AX8: =AK8 -> 0 | AY8: =AL8 -> 0 | AZ8: =AM8 -> 0 | BA8: =AN8 -> 0 | BC8: =AR8 -> 39721 | BD8: =AT8-$AT$2 -> -0.05381425 | BE8: =AU8 -> 0
A9: 39813 | B9: 2.2206634 | C9: -0.98689403 | D9: -6.9466266 | E9: -0.0002896115 | F9: 8.9449095 | G9: 15.944444 | H9: 0.11808668 | I9: 0.33695797 | J9: -0.065994594 | K9: 2.2587813 | L9: -0.68091049 | M9: 0 | N9: 0 | O9: 0.55671627 | P9: 0 | Q9: -0.073561543 | R9: 0 | S9: 0 | T9: 0 | U9: 0 | V9: 0 | W9: 0 | X9: 0 | Y9: 0.073690921 | Z9: -0.13359577 | AA9: 0.092384556 | AB9: -0.0071129062 | AC9: -0.014969052 | AD9: -0.028973438 | AE9: 7.3082133 | AF9: 28.91592 | AH9: =K9+Y9-Y9/100 -> 2.3317353 | AI9: =Y9/1010 -> 7.2961308e-05 | AJ9: =Z9 -> -0.13359577 | AK9: =AA9 -> 0.092384556 | AL9: =AB9 -> -0.0071129062 | AM9: =AC9 -> -0.014969052 | AN9: =AD9 -> -0.028973438 | AR9: =A9 -> 39813 | AS9: =AF9*4+2 -> 117.66368 | AT9: =AH9 -> 2.3317353 | AU9: =SUM(AV9:BA9) -> -0.092193645 | AV9: =AI9 -> 7.2961308e-05 | AW9: =AJ9 -> -0.13359577 | AX9: =AK9 -> 0.092384556 | AY9: =AL9 -> -0.0071129062 | AZ9: =AM9 -> -0.014969052 | BA9: =AN9 -> -0.028973438 | BC9: =AR9 -> 39813 | BD9: =AT9-$AT$2 -> -0.2431538 | BE9: =AU9 -> -0.092193645
A10: 39903 | B10: 2.4024061 | C10: -1.2606797 | D10: -6.8199197 | E10: -0.0001738059 | F10: 8.6027343 | G10: 16.652521 | H10: 0.06749249 | I10: 0.27634318 | J10: -0.060941639 | K10: 2.7785999 | L10: -1.1798196 | M10: 0 | N10: 0 | O10: 0.57206768 | P10: 0 | Q10: -0.025279014 | R10: 0 | S10: 0 | T10: 0 | U10: 0 | V10: 0 | W10: 0 | X10: 0 | Y10: -1.7973575 | Z10: 0.013721478 | AA10: 0.12529789 | AB10: -0.030395868 | AC10: -0.051108838 | AD10: -0.13660702 | AE10: 7.2856806 | AF10: 27.414582 | AH10: =K10+Y10-Y10/100 -> 0.99921591 | AI10: =Y10/1010 -> -0.0017795619 | AJ10: =Z10 -> 0.013721478 | AK10: =AA10 -> 0.12529789 | AL10: =AB10 -> -0.030395868 | AM10: =AC10 -> -0.051108838 | AN10: =AD10 -> -0.13660702 | AR10: =A10 -> 39903 | AS10: =AF10*4+2 -> 111.65833 | AT10: =AH10 -> 0.99921591 | AU10: =SUM(AV10:BA10) -> -0.080871912 | AV10: =AI10 -> -0.0017795619 | AW10: =AJ10 -> 0.013721478 | AX10: =AK10 -> 0.12529789 | AY10: =AL10 -> -0.030395868 | AZ10: =AM10 -> -0.051108838 | BA10: =AN10 -> -0.13660702 | BC10: =AR10 -> 39903 | BD10: =AT10-$AT$2 -> -1.5756732 | BE10: =AU10 -> -0.080871912
A11: 39994 | B11: 2.4277616 | C11: -1.6490085 | D11: -6.3861468 | E11: -0.00049595052 | F11: 7.9593532 | G11: 17.059181 | H11: -0.089907165 | I11: 0.25785819 | J11: -0.059151639 | K11: 5.406976 | L11: -1.4181606 | M11: 0 | N11: 0 | O11: 0.58667403 | P11: 0 | Q11: 0.016546462 | R11: 0 | S11: 0 | T11: 0 | U11: 0 | V11: 0 | W11: 0 | X11: 0 | Y11: -4.5109297 | Z11: 0.25520858 | AA11: 0.13462049 | AB11: -0.078483828 | AC11: -0.067382708 | AD11: -0.30713781 | AE11: 7.2632314 | AF11: 26.800606 | AH11: =K11+Y11-Y11/100 -> 0.94115568 | AI11: =Y11/1010 -> -0.004466267 | AJ11: =Z11 -> 0.25520858 | AK11: =AA11 -> 0.13462049 | AL11: =AB11 -> -0.078483828 | AM11: =AC11 -> -0.067382708 | AN11: =AD11 -> -0.30713781 | AR11: =A11 -> 39994 | AS11: =AF11*4+2 -> 109.20242 | AT11: =AH11 -> 0.94115568 | AU11: =SUM(AV11:BA11) -> -0.067641554 | AV11: =AI11 -> -0.004466267 | AW11: =AJ11 -> 0.25520858 | AX11: =AK11 -> 0.13462049 | AY11: =AL11 -> -0.078483828 | AZ11: =AM11 -> -0.067382708 | BA11: =AN11 -> -0.30713781 | BC11: =AR11 -> 39994 | BD11: =AT11-$AT$2 -> -1.6337335 | BE11: =AU11 -> -0.067641554
A12: 40086 | B12: 2.4217085 | C12: -2.0203722 | D12: -5.5802494 | E12: -0.0013006478 | F12: 7.1417549 | G12: 17.135333 | H12: -0.0426744 | I12: 0.322457 | J12: -0.056528372 | K12: 7.9652821 | L12: -1.4766757 | M12: 0 | N12: 0 | O12: 0.60460848 | P12: 0 | Q12: 0.00073509913 | R12: 0 | S12: 0 | T12: 0 | U12: 0 | V12: 0 | W12: 0 | X12: 0 | Y12: -6.6481835 | Z12: 0.43002849 | AA12: 0.11092325 | AB12: -0.16598199 | AC12: -0.11796388 | AD12: -0.56485065 | AE12: 7.2408652 | AF12: 26.698915 | AH12: =K12+Y12-Y12/100 -> 1.3835804 | AI12: =Y12/1010 -> -0.0065823599 | AJ12: =Z12 -> 0.43002849 | AK12: =AA12 -> 0.11092325 | AL12: =AB12 -> -0.16598199 | AM12: =AC12 -> -0.11796388 | AN12: =AD12 -> -0.56485065 | AR12: =A12 -> 40086 | AS12: =AF12*4+2 -> 108.79566 | AT12: =AH12 -> 1.3835804 | AU12: =SUM(AV12:BA12) -> -0.31442715 | AV12: =AI12 -> -0.0065823599 | AW12: =AJ12 -> 0.43002849 | AX12: =AK12 -> 0.11092325 | AY12: =AL12 -> -0.16598199 | AZ12: =AM12 -> -0.11796388 | BA12: =AN12 -> -0.56485065 | BC12: =AR12 -> 40086 | BD12: =AT12-$AT$2 -> -1.1913087 | BE12: =AU12 -> -0.31442715
A13: 40178 | B13: 2.0701525 | C13: -1.9632677 | D13: -4.963927 | E13: -0.00080920876 | F13: 6.7932403 | G13: 17.165547 | H13: 0.018838774 | I13: 0.252927 | J13: -0.046777776 | K13: 9.6680861 | L13: -1.4944411 | M13: 0 | N13: 0 | O13: 0.61475522 | P13: 0 | Q13: -0.017101425 | R13: 0 | S13: 0 | T13: 0 | U13: 0 | V13: 0 | W13: 0 | X13: 0 | Y13: -8.2298802 | Z13: 0.64538339 | AA13: 0.075587373 | AB13: -0.24389615 | AC13: -0.13783327 | AD13: -0.86962231 | AE13: 7.2185815 | AF13: 26.555543 | AH13: =K13+Y13-Y13/100 -> 1.5205047 | AI13: =Y13/1010 -> -0.0081483962 | AJ13: =Z13 -> 0.64538339 | AK13: =AA13 -> 0.075587373 | AL13: =AB13 -> -0.24389615 | AM13: =AC13 -> -0.13783327 | AN13: =AD13 -> -0.86962231 | AR13: =A13 -> 40178 | AS13: =AF13*4+2 -> 108.22217 | AT13: =AH13 -> 1.5205047 | AU13: =SUM(AV13:BA13) -> -0.53852936 | AV13: =AI13 -> -0.0081483962 | AW13: =AJ13 -> 0.64538339 | AX13: =AK13 -> 0.075587373 | AY13: =AL13 -> -0.24389615 | AZ13: =AM13 -> -0.13783327 | BA13: =AN13 -> -0.86962231 | BC13: =AR13 -> 40178 | BD13: =AT13-$AT$2 -> -1.0543844 | BE13: =AU13 -> -0.53852936
A14: 40268 | B14: 1.9292619 | C14: -1.9152574 | D14: -4.6209409 | E14: -9.3285765e-05 | F14: 6.2885873 | G14: 17.194811 | H14: -0.0097242431 | I14: 0.24468576 | J14: -0.033630541 | K14: 11.391705 | L14: -1.5295778 | M14: 0 | N14: 0 | O14: 0.62748077 | P14: 0 | Q14: -0.021055782 | R14: 0 | S14: 0 | T14: 0 | U14: 0 | V14: 0 | W14: 0 | X14: 0 | Y14: -9.2842199 | Z14: 0.93375033 | AA14: 0.13528553 | AB14: -0.26251041 | AC14: -0.11896933 | AD14: -1.185558 | AE14: 7.1963798 | AF14: 26.96041 | AH14: =K14+Y14-Y14/100 -> 2.2003272 | AI14: =Y14/1010 -> -0.0091922969 | AJ14: =Z14 -> 0.93375033 | AK14: =AA14 -> 0.13528553 | AL14: =AB14 -> -0.26251041 | AM14: =AC14 -> -0.11896933 | AN14: =AD14 -> -1.185558 | AR14: =A14 -> 40268 | AS14: =AF14*4+2 -> 109.84164 | AT14: =AH14 -> 2.2003272 | AU14: =SUM(AV14:BA14) -> -0.50719413 | AV14: =AI14 -> -0.0091922969 | AW14: =AJ14 -> 0.93375033 | AX14: =AK14 -> 0.13528553 | AY14: =AL14 -> -0.26251041 | AZ14: =AM14 -> -0.11896933 | BA14: =AN14 -> -1.185558 | BC14: =AR14 -> 40268 | BD14: =AT14-$AT$2 -> -0.37456194 | BE14: =AU14 -> -0.50719413
A15: 40359 | B15: 1.7114594 | C15: -1.7910189 | D15: -4.417112 | E15: -0.00034034385 | F15: 5.508496 | G15: 17.284895 | H15: 0.036125033 | I15: 0.25452995 | J15: -0.025443457 | K15: 12.624267 | L15: -1.4630845 | M15: 0 | N15: 0 | O15: 0.64041987 | P15: 0 | Q15: -0.024373029 | R15: 0 | S15: 0 | T15: 0 | U15: 0 | V15: 0 | W15: 0 | X15: 0 | Y15: -10.235004 | Z15: 1.2587611 | AA15: 0.30474392 | AB15: -0.17869597 | AC15: -0.03951587 | AD15: -1.4723622 | AE15: 7.1742596 | AF15: 27.151007 | AH15: =K15+Y15-Y15/100 -> 2.4916135 | AI15: =Y15/1010 -> -0.010133667 | AJ15: =Z15 -> 1.2587611 | AK15: =AA15 -> 0.30474392 | AL15: =AB15 -> -0.17869597 | AM15: =AC15 -> -0.03951587 | AN15: =AD15 -> -1.4723622 | AR15: =A15 -> 40359 | AS15: =AF15*4+2 -> 110.60403 | AT15: =AH15 -> 2.4916135 | AU15: =SUM(AV15:BA15) -> -0.13720259 | AV15: =AI15 -> -0.010133667 | AW15: =AJ15 -> 1.2587611 | AX15: =AK15 -> 0.30474392 | AY15: =AL15 -> -0.17869597 | AZ15: =AM15 -> -0.03951587 | BA15: =AN15 -> -1.4723622 | BC15: =AR15 -> 40359 | BD15: =AT15-$AT$2 -> -0.083275637 | BE15: =AU15 -> -0.13720259
A16: 40451 | B16: 1.6689236 | C16: -1.669287 | D16: -4.2631128 | E16: -0.00047472158 | F16: 5.3252985 | G16: 17.33458 | H16: 0.0056531455 | I16: 0.3395956 | J16: -0.01579766 | K16: 13.592728 | L16: -1.5563826 | M16: 0 | N16: 0 | O16: 0.65967139 | P16: 0 | Q16: -0.017203497 | R16: 0 | S16: 0 | T16: 0 | U16: 0 | V16: 0 | W16: 0 | X16: 0 | Y16: -11.450592 | Z16: 1.4891879 | AA16: 0.38887175 | AB16: -0.13286861 | AC16: 0.019233067 | AD16: -1.7498602 | AE16: 7.1522205 | AF16: 27.120385 | AH16: =K16+Y16-Y16/100 -> 2.2566424 | AI16: =Y16/1010 -> -0.011337219 | AJ16: =Z16 -> 1.4891879 | AK16: =AA16 -> 0.38887175 | AL16: =AB16 -> -0.13286861 | AM16: =AC16 -> 0.019233067 | AN16: =AD16 -> -1.7498602 | AR16: =A16 -> 40451 | AS16: =AF16*4+2 -> 110.48154 | AT16: =AH16 -> 2.2566424 | AU16: =SUM(AV16:BA16) -> 0.0032267014 | AV16: =AI16 -> -0.011337219 | AW16: =AJ16 -> 1.4891879 | AX16: =AK16 -> 0.38887175 | AY16: =AL16 -> -0.13286861 | AZ16: =AM16 -> 0.019233067 | BA16: =AN16 -> -1.7498602 | BC16: =AR16 -> 40451 | BD16: =AT16-$AT$2 -> -0.3182467 | BE16: =AU16 -> 0.0032267014
A17: 40543 | B17: 1.3754459 | C17: -1.4731984 | D17: -4.3372803 | E17: -0.00016910156 | F17: 6.0283243 | G17: 17.375538 | H17: -0.03695678 | I17: 0.26961923 | J17: -0.0084062676 | K17: 14.927038 | L17: -1.5514464 | M17: 0 | N17: 0 | O17: 0.6729625 | P17: 0 | Q17: -0.010960892 | R17: 0 | S17: 0 | T17: 0 | U17: 0 | V17: 0 | W17: 0 | X17: 0 | Y17: -13.193123 | Z17: 1.6728789 | AA17: 0.4341946 | AB17: -0.11512471 | AC17: 0.031882889 | AD17: -2.0389967 | AE17: 7.1302619 | AF17: 27.152484 | AH17: =K17+Y17-Y17/100 -> 1.8658466 | AI17: =Y17/1010 -> -0.013062498 | AJ17: =Z17 -> 1.6728789 | AK17: =AA17 -> 0.4341946 | AL17: =AB17 -> -0.11512471 | AM17: =AC17 -> 0.031882889 | AN17: =AD17 -> -2.0389967 | AR17: =A17 -> 40543 | AS17: =AF17*4+2 -> 110.60994 | AT17: =AH17 -> 1.8658466 | AU17: =SUM(AV17:BA17) -> -0.028227444 | AV17: =AI17 -> -0.013062498 | AW17: =AJ17 -> 1.6728789 | AX17: =AK17 -> 0.4341946 | AY17: =AL17 -> -0.11512471 | AZ17: =AM17 -> 0.031882889 | BA17: =AN17 -> -2.0389967 | BC17: =AR17 -> 40543 | BD17: =AT17-$AT$2 -> -0.70904253 | BE17: =AU17 -> -0.028227444
A18: 40633 | B18: 1.9043017 | C18: -1.5433038 | D18: -4.5069513 | E18: -0.0012869151 | F18: 7.4268885 | G18: 17.45478 | H18: -0.036961388 | I18: 0.30813711 | J18: -0.0078414583 | K18: 16.675365 | L18: -1.4894906 | M18: 0 | N18: 0 | O18: 0.69313123 | P18: 0 | Q18: -0.023400021 | R18: 0 | S18: 0 | T18: 0 | U18: 0 | V18: 0 | W18: 0 | X18: 0 | Y18: -15.514005 | Z18: 1.6560904 | AA18: 0.29727136 | AB18: -0.20292069 | AC18: -0.027254571 | AD18: -2.3847288 | AE18: 7.1083835 | AF18: 27.786204 | AH18: =K18+Y18-Y18/100 -> 1.3164998 | AI18: =Y18/1010 -> -0.015360401 | AJ18: =Z18 -> 1.6560904 | AK18: =AA18 -> 0.29727136 | AL18: =AB18 -> -0.20292069 | AM18: =AC18 -> -0.027254571 | AN18: =AD18 -> -2.3847288 | AR18: =A18 -> 40633 | AS18: =AF18*4+2 -> 113.14482 | AT18: =AH18 -> 1.3164998 | AU18: =SUM(AV18:BA18) -> -0.67690276 | AV18: =AI18 -> -0.015360401 | AW18: =AJ18 -> 1.6560904 | AX18: =AK18 -> 0.29727136 | AY18: =AL18 -> -0.20292069 | AZ18: =AM18 -> -0.027254571 | BA18: =AN18 -> -2.3847288 | BC18: =AR18 -> 40633 | BD18: =AT18-$AT$2 -> -1.2583893 | BE18: =AU18 -> -0.67690276
A19: 40724 | B19: 1.467808 | C19: -1.2043497 | D19: -4.3924235 | E19: -0.0010583469 | F19: 8.406255 | G19: 17.546427 | H19: 0.07324742 | I19: 0.30268883 | J19: -0.0051230818 | K19: 18.729266 | L19: -1.555679 | M19: 0 | N19: 0 | O19: 0.71288761 | P19: 0 | Q19: -0.035226888 | R19: 0 | S19: 0 | T19: 0 | U19: 0 | V19: 0 | W19: 0 | X19: 0 | Y19: -18.615704 | Z19: 1.7520007 | AA19: 0.18453734 | AB19: -0.23254533 | AC19: -0.029947737 | AD19: -2.709168 | AE19: 7.0865847 | AF19: 27.480477 | AH19: =K19+Y19-Y19/100 -> 0.29971978 | AI19: =Y19/1010 -> -0.01843139 | AJ19: =Z19 -> 1.7520007 | AK19: =AA19 -> 0.18453734 | AL19: =AB19 -> -0.23254533 | AM19: =AC19 -> -0.029947737 | AN19: =AD19 -> -2.709168 | AR19: =A19 -> 40724 | AS19: =AF19*4+2 -> 111.92191 | AT19: =AH19 -> 0.29971978 | AU19: =SUM(AV19:BA19) -> -1.0535544 | AV19: =AI19 -> -0.01843139 | AW19: =AJ19 -> 1.7520007 | AX19: =AK19 -> 0.18453734 | AY19: =AL19 -> -0.23254533 | AZ19: =AM19 -> -0.029947737 | BA19: =AN19 -> -2.709168 | BC19: =AR19 -> 40724 | BD19: =AT19-$AT$2 -> -2.2751694 | BE19: =AU19 -> -1.0535544
A20: 40816 | B20: 1.8241286 | C20: -1.0959542 | D20: -4.2580249 | E20: -0.00028471595 | F20: 6.5846466 | G20: 17.671886 | H20: -0.047348455 | I20: 0.34776192 | J20: 0.0012598254 | K20: 21.668795 | L20: -1.6269307 | M20: 0 | N20: 0 | O20: 0.72603408 | P20: 0 | Q20: -0.021518547 | R20: 0 | S20: 0 | T20: 0 | U20: 0 | V20: 0 | W20: 0 | X20: 0 | Y20: -21.294037 | Z20: 2.3087563 | AA20: 0.35473861 | AB20: -0.080751504 | AC20: 0.099261868 | AD20: -2.8984711 | AE20: 7.0648651 | AF20: 27.328812 | AH20: =K20+Y20-Y20/100 -> 0.58769775 | AI20: =Y20/1010 -> -0.021083205 | AJ20: =Z20 -> 2.3087563 | AK20: =AA20 -> 0.35473861 | AL20: =AB20 -> -0.080751504 | AM20: =AC20 -> 0.099261868 | AN20: =AD20 -> -2.8984711 | AR20: =A20 -> 40816 | AS20: =AF20*4+2 -> 111.31525 | AT20: =AH20 -> 0.58769775 | AU20: =SUM(AV20:BA20) -> -0.23754899 | AV20: =AI20 -> -0.021083205 | AW20: =AJ20 -> 2.3087563 | AX20: =AK20 -> 0.35473861 | AY20: =AL20 -> -0.080751504 | AZ20: =AM20 -> 0.099261868 | BA20: =AN20 -> -2.8984711 | BC20: =AR20 -> 40816 | BD20: =AT20-$AT$2 -> -1.9871914 | BE20: =AU20 -> -0.23754899
... A132: 51043 | B132: -0.043141873 | C132: -0.00014191675 | D132: -0.060150045 | E132: 0.00016375639 | F132: 0.077003819 | G132: -0.017761409 | H132: 0.10657899 | I132: -0.12938709 | J132: -0.23383062 | K132: -0.0013647494 | L132: 0.028622522 | M132: 0 | N132: 0 | O132: 0.44750605 | P132: 0 | Q132: 0.30446726 | R132: 0 | S132: 0 | T132: 0 | U132: 0 | V132: 0 | W132: 0 | X132: 0 | Y132: 0.0014171204 | Z132: -0.0014470184 | AA132: 0.00054189822 | AB132: -0.00029329794 | AC132: 0.0013717805 | AD132: 0.0037302372 | AE132: -0.072867892 | AF132: 0.418171 | AH132: =K132+Y132-Y132/100 -> 3.8199787e-05 | AI132: =Y132/1010 -> 1.4030895e-06 | AJ132: =Z132 -> -0.0014470184 | AK132: =AA132 -> 0.00054189822 | AL132: =AB132 -> -0.00029329794 | AM132: =AC132 -> 0.0013717805 | AN132: =AD132 -> 0.0037302372 | AR132: =A132 -> 51043 | AS132: =AF132*4+2 -> 3.672684 | AT132: =AH132 -> 3.8199787e-05 | AU132: =SUM(AV132:BA132) -> 0.0039050027 | AV132: =AI132 -> 1.4030895e-06 | AW132: =AJ132 -> -0.0014470184 | AX132: =AK132 -> 0.00054189822 | AY132: =AL132 -> -0.00029329794 | AZ132: =AM132 -> 0.0013717805 | BA132: =AN132 -> 0.0037302372 | BC132: =AR132 -> 51043 | BD132: =AT132-$AT$2 -> -2.5748509 | BE132: =AU132 -> 0.0039050027

Sheet EA_output_policy
A1: date | B1: g_sh | C1: b_liqtil_sh | D1: b_liqp_sh | E1: b_safetil_sh | F1: b_safep_sh | G1: mu_sh | H1: z_sh | I1: lambda_f_sh | J1: lambda_w_sh | K1: rm_sh | L1: sigma_omega_sh | M1: mu_e_sh | N1: gamma_sh | O1: pi_star_sh | P1: lr_sh | Q1: zp_sh | R1: tfp_sh | S1: gdpdef_sh | T1: corepce_sh | U1: gdp_sh | V1: gdi_sh | W1: BBB_sh | X1: AAA_sh | Y1: rm_shl1 | Z1: rm_shl2 | AA1: rm_shl3 | AB1: rm_shl4 | AC1: rm_shl5 | AD1: rm_shl6 | AE1: dettrend | AF1: detrendedMean | AH1: rm_sh | AI1: =Y1 -> rm_shl1 | AJ1: =Z1 -> rm_shl2 | AK1: =AA1 -> rm_shl3 | AL1: =AB1 -> rm_shl4 | AM1: =AC1 -> rm_shl5 | AN1: =AD1 -> rm_shl6 | AQ1: Plot | AR1: =A1 -> date | AS1: =AF1 -> detrendedMean | AT1: Monetary Policy | AU1: Fgsum | AV1: FG1 | AW1: FG2 | AX1: FG3 | AY1: FG4 | AZ1: FG5 | BA1: FG6 | BC1: date | BD1: rm_sh | BE1: Fgsum
A2: 39172 | B2: 2.5363082 | C2: -0.18049422 | D2: -5.026568 | E2: -0.00051095038 | F2: 6.5669289 | G2: 14.167348 | H2: -0.028136165 | I2: 0.24489409 | J2: -0.05757504 | K2: 2.5748891 | L2: 0.26640205 | M2: 0 | N2: 0 | O2: 0.43018806 | P2: 0 | Q2: -0.017234495 | R2: 0 | S2: 0 | T2: 0 | U2: 0 | V2: 0 | W2: 0 | X2: 0 | Y2: 0 | Z2: 0 | AA2: 0 | AB2: 0 | AC2: 0 | AD2: 0 | AE2: 7.4683269 | AF2: 28.944766 | AH2: =K2+Y2-Y2/100 -> 2.5748891 | AI2: =Y2 -> 0 | AJ2: =Z2 -> 0 | AK2: =AA2 -> 0 | AL2: =AB2 -> 0 | AM2: =AC2 -> 0 | AN2: =AD2 -> 0 | AR2: =A2 -> 39172 | AS2: =AF2*4+2 -> 117.77907 | AT2: =AH2-$AH$2 -> 0 | AU2: =SUM(AV2:BA2) -> 0 | AV2: =AI2 -> 0 | AW2: =AJ2 -> 0 | AX2: =AK2 -> 0 | AY2: =AL2 -> 0 | AZ2: =AM2 -> 0 | BA2: =AN2 -> 0 | BC2: =AR2 -> 39172 | BD2: =AT2 -> 0 | BE2: =AU2 -> 0
A3: 39263 | B3: 2.1888377 | C3: -0.10201437 | D3: -5.4151599 | E3: 0.000432913 | F3: 7.4635098 | G3: 14.09681 | H3: -0.017718534 | I3: 0.23729294 | J3: -0.058482715 | K3: 2.6753132 | L3: 0.30577422 | M3: 0 | N3: 0 | O3: 0.44487798 | P3: 0 | Q3: -0.025392488 | R3: 0 | S3: 0 | T3: 0 | U3: 0 | V3: 0 | W3: 0 | X3: 0 | Y3: 0 | Z3: 0 | AA3: 0 | AB3: 0 | AC3: 0 | AD3: 0 | AE3: 7.445194 | AF3: 29.239275 | AH3: =K3+Y3-Y3/100 -> 2.6753132 | AI3: =Y3 -> 0 | AJ3: =Z3 -> 0 | AK3: =AA3 -> 0 | AL3: =AB3 -> 0 | AM3: =AC3 -> 0 | AN3: =AD3 -> 0 | AR3: =A3 -> 39263 | AS3: =AF3*4+2 -> 118.9571 | AT3: =AH3-$AH$2 -> 0.10042406 | AU3: =SUM(AV3:BA3) -> 0 | AV3: =AI3 -> 0 | AW3: =AJ3 -> 0 | AX3: =AK3 -> 0 | AY3: =AL3 -> 0 | AZ3: =AM3 -> 0 | BA3: =AN3 -> 0 | BC3: =AR3 -> 39263 | BD3: =AT3 -> 0.10042406 | BE3: =AU3 -> 0
A4: 39355 | B4: 2.3018784 | C4: -0.18582521 | D4: -5.7797078 | E4: -0.00024449342 | F4: 8.1065585 | G4: 14.1473 | H4: 0.0099248504 | I4: 0.31153154 | J4: -0.061960515 | K4: 2.506994 | L4: 0.30064004 | M4: 0 | N4: 0 | O4: 0.46631618 | P4: 0 | Q4: -0.040553603 | R4: 0 | S4: 0 | T4: 0 | U4: 0 | V4: 0 | W4: 0 | X4: 0 | Y4: 0 | Z4: 0 | AA4: 0 | AB4: 0 | AC4: 0 | AD4: 0 | AE4: 7.4221487 | AF4: 29.505 | AH4: =K4+Y4-Y4/100 -> 2.506994 | AI4: =Y4 -> 0 | AJ4: =Z4 -> 0 | AK4: =AA4 -> 0 | AL4: =AB4 -> 0 | AM4: =AC4 -> 0 | AN4: =AD4 -> 0 | AR4: =A4 -> 39355 | AS4: =AF4*4+2 -> 120.02 | AT4: =AH4-$AH$2 -> -0.067895149 | AU4: =SUM(AV4:BA4) -> 0 | AV4: =AI4 -> 0 | AW4: =AJ4 -> 0 | AX4: =AK4 -> 0 | AY4: =AL4 -> 0 | AZ4: =AM4 -> 0 | BA4: =AN4 -> 0 | BC4: =AR4 -> 39355 | BD4: =AT4 -> -0.067895149 | BE4: =AU4 -> 0
A5: 39447 | B5: 2.0031345 | C5: -0.059805901 | D5: -6.0906698 | E5: 0.00065881996 | F5: 8.5748649 | G5: 14.245587 | H5: 0.01546791 | I5: 0.248964 | J5: -0.063329388 | K5: 2.6392114 | L5: 0.34661216 | M5: 0 | N5: 0 | O5: 0.47709801 | P5: 0 | Q5: -0.045182361 | R5: 0 | S5: 0 | T5: 0 | U5: 0 | V5: 0 | W5: 0 | X5: 0 | Y5: 0 | Z5: 0 | AA5: 0 | AB5: 0 | AC5: 0 | AD5: 0 | AE5: 7.3991902 | AF5: 29.691802 | AH5: =K5+Y5-Y5/100 -> 2.6392114 | AI5: =Y5 -> 0 | AJ5: =Z5 -> 0 | AK5: =AA5 -> 0 | AL5: =AB5 -> 0 | AM5: =AC5 -> 0 | AN5: =AD5 -> 0 | AR5: =A5 -> 39447 | AS5: =AF5*4+2 -> 120.76721 | AT5: =AH5-$AH$2 -> 0.064322263 | AU5: =SUM(AV5:BA5) -> 0 | AV5: =AI5 -> 0 | AW5: =AJ5 -> 0 | AX5: =AK5 -> 0 | AY5: =AL5 -> 0 | AZ5: =AM5 -> 0 | BA5: =AN5 -> 0 | BC5: =AR5 -> 39447 | BD5: =AT5 -> 0.064322263 | BE5: =AU5 -> 0
A6: 39538 | B6: 2.0564368 | C6: -0.17410702 | D6: -6.2409237 | E6: -8.1488331e-05 | F6: 8.7254233 | G6: 14.470225 | H6: -0.053129904 | I6: 0.30778976 | J6: -0.066874845 | K6: 2.9688718 | L6: 0.14427824 | M6: 0 | N6: 0 | O6: 0.49713924 | P6: 0 | Q6: -0.050515251 | R6: 0 | S6: 0 | T6: 0 | U6: 0 | V6: 0 | W6: 0 | X6: 0 | Y6: 0 | Z6: 0 | AA6: 0 | AB6: 0 | AC6: 0 | AD6: 0 | AE6: 7.376318 | AF6: 29.96085 | AH6: =K6+Y6-Y6/100 -> 2.9688718 | AI6: =Y6 -> 0 | AJ6: =Z6 -> 0 | AK6: =AA6 -> 0 | AL6: =AB6 -> 0 | AM6: =AC6 -> 0 | AN6: =AD6 -> 0 | AR6: =A6 -> 39538 | AS6: =AF6*4+2 -> 121.8434 | AT6: =AH6-$AH$2 -> 0.39398266 | AU6: =SUM(AV6:BA6) -> 0 | AV6: =AI6 -> 0 | AW6: =AJ6 -> 0 | AX6: =AK6 -> 0 | AY6: =AL6 -> 0 | AZ6: =AM6 -> 0 | BA6: =AN6 -> 0 | BC6: =AR6 -> 39538 | BD6: =AT6 -> 0.39398266 | BE6: =AU6 -> 0
A7: 39629 | B7: 1.9437086 | C7: -0.25968328 | D7: -6.4409474 | E7: 0.00050280931 | F7: 9.1352305 | G7: 14.602996 | H7: -0.0028221986 | I7: 0.2461009 | J7: -0.063600816 | K7: 2.6992023 | L7: 0.031560885 | M7: 0 | N7: 0 | O7: 0.50964208 | P7: 0 | Q7: -0.07357073 | R7: 0 | S7: 0 | T7: 0 | U7: 0 | V7: 0 | W7: 0 | X7: 0 | Y7: 0 | Z7: 0 | AA7: 0 | AB7: 0 | AC7: 0 | AD7: 0 | AE7: 7.3535315 | AF7: 29.681851 | AH7: =K7+Y7-Y7/100 -> 2.6992023 | AI7: =Y7 -> 0 | AJ7: =Z7 -> 0 | AK7: =AA7 -> 0 | AL7: =AB7 -> 0 | AM7: =AC7 -> 0 | AN7: =AD7 -> 0 | AR7: =A7 -> 39629 | AS7: =AF7*4+2 -> 120.7274 | AT7: =AH7-$AH$2 -> 0.12431319 | AU7: =SUM(AV7:BA7) -> 0 | AV7: =AI7 -> 0 | AW7: =AJ7 -> 0 | AX7: =AK7 -> 0 | AY7: =AL7 -> 0 | AZ7: =AM7 -> 0 | BA7: =AN7 -> 0 | BC7: =AR7 -> 39629 | BD7: =AT7 -> 0.12431319 | BE7: =AU7 -> 0
A8: 39721 | B8: 1.5553725 | C8: -0.47264141 | D8: -6.5811779 | E8: 0.00045985532 | F8: 9.4802157 | G8: 14.927721 | H8: 0.027059605 | I8: 0.29587019 | J8: -0.068185466 | K8: 2.5210749 | L8: -0.16240357 | M8: 0 | N8: 0 | O8: 0.53344519 | P8: 0 | Q8: -0.081467541 | R8: 0 | S8: 0 | T8: 0 | U8: 0 | V8: 0 | W8: 0 | X8: 0 | Y8: 0 | Z8: 0 | AA8: 0 | AB8: 0 | AC8: 0 | AD8: 0 | AE8: 7.3308301 | AF8: 29.306173 | AH8: =K8+Y8-Y8/100 -> 2.5210749 | AI8: =Y8 -> 0 | AJ8: =Z8 -> 0 | AK8: =AA8 -> 0 | AL8: =AB8 -> 0 | AM8: =AC8 -> 0 | AN8: =AD8 -> 0 | AR8: =A8 -> 39721 | AS8: =AF8*4+2 -> 119.22469 | AT8: =AH8-$AH$2 -> -0.05381425 | AU8: =SUM(AV8:BA8) -> 0 | AV8: =AI8 -> 0 | AW8: =AJ8 -> 0 | AX8: =AK8 -> 0 | AY8: =AL8 -> 0 | AZ8: =AM8 -> 0 | BA8: =AN8 -> 0 | BC8: =AR8 -> 39721 | BD8: =AT8 -> -0.05381425 | BE8: =AU8 -> 0
A9: 39813 | B9: 2.2206634 | C9: -0.98689403 | D9: -6.9466266 | E9: -0.0002896115 | F9: 8.9449095 | G9: 15.944444 | H9: 0.11808668 | I9: 0.33695797 | J9: -0.065994594 | K9: 2.2587813 | L9: -0.68091049 | M9: 0 | N9: 0 | O9: 0.55671627 | P9: 0 | Q9: -0.073561543 | R9: 0 | S9: 0 | T9: 0 | U9: 0 | V9: 0 | W9: 0 | X9: 0 | Y9: 0.073690921 | Z9: -0.13359577 | AA9: 0.092384556 | AB9: -0.0071129062 | AC9: -0.014969052 | AD9: -0.028973438 | AE9: 7.3082133 | AF9: 28.91592 | AH9: =K9+Y9-Y9/100 -> 2.3317353 | AI9: =Y9/1010 -> 7.2961308e-05 | AJ9: =Z9 -> -0.13359577 | AK9: =AA9 -> 0.092384556 | AL9: =AB9 -> -0.0071129062 | AM9: =AC9 -> -0.014969052 | AN9: =AD9 -> -0.028973438 | AR9: =A9 -> 39813 | AS9: =AF9*4+2 -> 117.66368 | AT9: =AH9-$AH$2 -> -0.2431538 | AU9: =SUM(AV9:BA9) -> -0.092193645 | AV9: =AI9 -> 7.2961308e-05 | AW9: =AJ9 -> -0.13359577 | AX9: =AK9 -> 0.092384556 | AY9: =AL9 -> -0.0071129062 | AZ9: =AM9 -> -0.014969052 | BA9: =AN9 -> -0.028973438 | BC9: =AR9 -> 39813 | BD9: =AT9 -> -0.2431538 | BE9: =AU9 -> -0.092193645
A10: 39903 | B10: 2.4024061 | C10: -1.2606797 | D10: -6.8199197 | E10: -0.0001738059 | F10: 8.6027343 | G10: 16.652521 | H10: 0.06749249 | I10: 0.27634318 | J10: -0.060941639 | K10: 2.7785999 | L10: -1.1798196 | M10: 0 | N10: 0 | O10: 0.57206768 | P10: 0 | Q10: -0.025279014 | R10: 0 | S10: 0 | T10: 0 | U10: 0 | V10: 0 | W10: 0 | X10: 0 | Y10: -1.7973575 | Z10: 0.013721478 | AA10: 0.12529789 | AB10: -0.030395868 | AC10: -0.051108838 | AD10: -0.13660702 | AE10: 7.2856806 | AF10: 27.414582 | AH10: =K10+Y10-Y10/100 -> 0.99921591 | AI10: =Y10/1010 -> -0.0017795619 | AJ10: =Z10 -> 0.013721478 | AK10: =AA10 -> 0.12529789 | AL10: =AB10 -> -0.030395868 | AM10: =AC10 -> -0.051108838 | AN10: =AD10 -> -0.13660702 | AR10: =A10 -> 39903 | AS10: =AF10*4+2 -> 111.65833 | AT10: =AH10-$AH$2 -> -1.5756732 | AU10: =SUM(AV10:BA10) -> -0.080871912 | AV10: =AI10 -> -0.0017795619 | AW10: =AJ10 -> 0.013721478 | AX10: =AK10 -> 0.12529789 | AY10: =AL10 -> -0.030395868 | AZ10: =AM10 -> -0.051108838 | BA10: =AN10 -> -0.13660702 | BC10: =AR10 -> 39903 | BD10: =AT10 -> -1.5756732 | BE10: =AU10 -> -0.080871912
A11: 39994 | B11: 2.4277616 | C11: -1.6490085 | D11: -6.3861468 | E11: -0.00049595052 | F11: 7.9593532 | G11: 17.059181 | H11: -0.089907165 | I11: 0.25785819 | J11: -0.059151639 | K11: 5.406976 | L11: -1.4181606 | M11: 0 | N11: 0 | O11: 0.58667403 | P11: 0 | Q11: 0.016546462 | R11: 0 | S11: 0 | T11: 0 | U11: 0 | V11: 0 | W11: 0 | X11: 0 | Y11: -4.5109297 | Z11: 0.25520858 | AA11: 0.13462049 | AB11: -0.078483828 | AC11: -0.067382708 | AD11: -0.30713781 | AE11: 7.2632314 | AF11: 26.800606 | AH11: =K11+Y11-Y11/100 -> 0.94115568 | AI11: =Y11/1010 -> -0.004466267 | AJ11: =Z11 -> 0.25520858 | AK11: =AA11 -> 0.13462049 | AL11: =AB11 -> -0.078483828 | AM11: =AC11 -> -0.067382708 | AN11: =AD11 -> -0.30713781 | AR11: =A11 -> 39994 | AS11: =AF11*4+2 -> 109.20242 | AT11: =AH11-$AH$2 -> -1.6337335 | AU11: =SUM(AV11:BA11) -> -0.067641554 | AV11: =AI11 -> -0.004466267 | AW11: =AJ11 -> 0.25520858 | AX11: =AK11 -> 0.13462049 | AY11: =AL11 -> -0.078483828 | AZ11: =AM11 -> -0.067382708 | BA11: =AN11 -> -0.30713781 | BC11: =AR11 -> 39994 | BD11: =AT11 -> -1.6337335 | BE11: =AU11 -> -0.067641554
A12: 40086 | B12: 2.4217085 | C12: -2.0203722 | D12: -5.5802494 | E12: -0.0013006478 | F12: 7.1417549 | G12: 17.135333 | H12: -0.0426744 | I12: 0.322457 | J12: -0.056528372 | K12: 7.9652821 | L12: -1.4766757 | M12: 0 | N12: 0 | O12: 0.60460848 | P12: 0 | Q12: 0.00073509913 | R12: 0 | S12: 0 | T12: 0 | U12: 0 | V12: 0 | W12: 0 | X12: 0 | Y12: -6.6481835 | Z12: 0.43002849 | AA12: 0.11092325 | AB12: -0.16598199 | AC12: -0.11796388 | AD12: -0.56485065 | AE12: 7.2408652 | AF12: 26.698915 | AH12: =K12+Y12-Y12/100 -> 1.3835804 | AI12: =Y12/1010 -> -0.0065823599 | AJ12: =Z12 -> 0.43002849 | AK12: =AA12 -> 0.11092325 | AL12: =AB12 -> -0.16598199 | AM12: =AC12 -> -0.11796388 | AN12: =AD12 -> -0.56485065 | AR12: =A12 -> 40086 | AS12: =AF12*4+2 -> 108.79566 | AT12: =AH12-$AH$2 -> -1.1913087 | AU12: =SUM(AV12:BA12) -> -0.31442715 | AV12: =AI12 -> -0.0065823599 | AW12: =AJ12 -> 0.43002849 | AX12: =AK12 -> 0.11092325 | AY12: =AL12 -> -0.16598199 | AZ12: =AM12 -> -0.11796388 | BA12: =AN12 -> -0.56485065 | BC12: =AR12 -> 40086 | BD12: =AT12 -> -1.1913087 | BE12: =AU12 -> -0.31442715
A13: 40178 | B13: 2.0701525 | C13: -1.9632677 | D13: -4.963927 | E13: -0.00080920876 | F13: 6.7932403 | G13: 17.165547 | H13: 0.018838774 | I13: 0.252927 | J13: -0.046777776 | K13: 9.6680861 | L13: -1.4944411 | M13: 0 | N13: 0 | O13: 0.61475522 | P13: 0 | Q13: -0.017101425 | R13: 0 | S13: 0 | T13: 0 | U13: 0 | V13: 0 | W13: 0 | X13: 0 | Y13: -8.2298802 | Z13: 0.64538339 | AA13: 0.075587373 | AB13: -0.24389615 | AC13: -0.13783327 | AD13: -0.86962231 | AE13: 7.2185815 | AF13: 26.555543 | AH13: =K13+Y13-Y13/100 -> 1.5205047 | AI13: =Y13/1010 -> -0.0081483962 | AJ13: =Z13 -> 0.64538339 | AK13: =AA13 -> 0.075587373 | AL13: =AB13 -> -0.24389615 | AM13: =AC13 -> -0.13783327 | AN13: =AD13 -> -0.86962231 | AR13: =A13 -> 40178 | AS13: =AF13*4+2 -> 108.22217 | AT13: =AH13-$AH$2 -> -1.0543844 | AU13: =SUM(AV13:BA13) -> -0.53852936 | AV13: =AI13 -> -0.0081483962 | AW13: =AJ13 -> 0.64538339 | AX13: =AK13 -> 0.075587373 | AY13: =AL13 -> -0.24389615 | AZ13: =AM13 -> -0.13783327 | BA13: =AN13 -> -0.86962231 | BC13: =AR13 -> 40178 | BD13: =AT13 -> -1.0543844 | BE13: =AU13 -> -0.53852936
A14: 40268 | B14: 1.9292619 | C14: -1.9152574 | D14: -4.6209409 | E14: -9.3285765e-05 | F14: 6.2885873 | G14: 17.194811 | H14: -0.0097242431 | I14: 0.24468576 | J14: -0.033630541 | K14: 11.391705 | L14: -1.5295778 | M14: 0 | N14: 0 | O14: 0.62748077 | P14: 0 | Q14: -0.021055782 | R14: 0 | S14: 0 | T14: 0 | U14: 0 | V14: 0 | W14: 0 | X14: 0 | Y14: -9.2842199 | Z14: 0.93375033 | AA14: 0.13528553 | AB14: -0.26251041 | AC14: -0.11896933 | AD14: -1.185558 | AE14: 7.1963798 | AF14: 26.96041 | AH14: =K14+Y14-Y14/100 -> 2.2003272 | AI14: =Y14/1010 -> -0.0091922969 | AJ14: =Z14 -> 0.93375033 | AK14: =AA14 -> 0.13528553 | AL14: =AB14 -> -0.26251041 | AM14: =AC14 -> -0.11896933 | AN14: =AD14 -> -1.185558 | AR14: =A14 -> 40268 | AS14: =AF14*4+2 -> 109.84164 | AT14: =AH14-$AH$2 -> -0.37456194 | AU14: =SUM(AV14:BA14) -> -0.50719413 | AV14: =AI14 -> -0.0091922969 | AW14: =AJ14 -> 0.93375033 | AX14: =AK14 -> 0.13528553 | AY14: =AL14 -> -0.26251041 | AZ14: =AM14 -> -0.11896933 | BA14: =AN14 -> -1.185558 | BC14: =AR14 -> 40268 | BD14: =AT14 -> -0.37456194 | BE14: =AU14 -> -0.50719413
A15: 40359 | B15: 1.7114594 | C15: -1.7910189 | D15: -4.417112 | E15: -0.00034034385 | F15: 5.508496 | G15: 17.284895 | H15: 0.036125033 | I15: 0.25452995 | J15: -0.025443457 | K15: 12.624267 | L15: -1.4630845 | M15: 0 | N15: 0 | O15: 0.64041987 | P15: 0 | Q15: -0.024373029 | R15: 0 | S15: 0 | T15: 0 | U15: 0 | V15: 0 | W15: 0 | X15: 0 | Y15: -10.235004 | Z15: 1.2587611 | AA15: 0.30474392 | AB15: -0.17869597 | AC15: -0.03951587 | AD15: -1.4723622 | AE15: 7.1742596 | AF15: 27.151007 | AH15: =K15+Y15-Y15/100 -> 2.4916135 | AI15: =Y15/1010 -> -0.010133667 | AJ15: =Z15 -> 1.2587611 | AK15: =AA15 -> 0.30474392 | AL15: =AB15 -> -0.17869597 | AM15: =AC15 -> -0.03951587 | AN15: =AD15 -> -1.4723622 | AR15: =A15 -> 40359 | AS15: =AF15*4+2 -> 110.60403 | AT15: =AH15-$AH$2 -> -0.083275637 | AU15: =SUM(AV15:BA15) -> -0.13720259 | AV15: =AI15 -> -0.010133667 | AW15: =AJ15 -> 1.2587611 | AX15: =AK15 -> 0.30474392 | AY15: =AL15 -> -0.17869597 | AZ15: =AM15 -> -0.03951587 | BA15: =AN15 -> -1.4723622 | BC15: =AR15 -> 40359 | BD15: =AT15 -> -0.083275637 | BE15: =AU15 -> -0.13720259
A16: 40451 | B16: 1.6689236 | C16: -1.669287 | D16: -4.2631128 | E16: -0.00047472158 | F16: 5.3252985 | G16: 17.33458 | H16: 0.0056531455 | I16: 0.3395956 | J16: -0.01579766 | K16: 13.592728 | L16: -1.5563826 | M16: 0 | N16: 0 | O16: 0.65967139 | P16: 0 | Q16: -0.017203497 | R16: 0 | S16: 0 | T16: 0 | U16: 0 | V16: 0 | W16: 0 | X16: 0 | Y16: -11.450592 | Z16: 1.4891879 | AA16: 0.38887175 | AB16: -0.13286861 | AC16: 0.019233067 | AD16: -1.7498602 | AE16: 7.1522205 | AF16: 27.120385 | AH16: =K16+Y16-Y16/100 -> 2.2566424 | AI16: =Y16/1010 -> -0.011337219 | AJ16: =Z16 -> 1.4891879 | AK16: =AA16 -> 0.38887175 | AL16: =AB16 -> -0.13286861 | AM16: =AC16 -> 0.019233067 | AN16: =AD16 -> -1.7498602 | AR16: =A16 -> 40451 | AS16: =AF16*4+2 -> 110.48154 | AT16: =AH16-$AH$2 -> -0.3182467 | AU16: =SUM(AV16:BA16) -> 0.0032267014 | AV16: =AI16 -> -0.011337219 | AW16: =AJ16 -> 1.4891879 | AX16: =AK16 -> 0.38887175 | AY16: =AL16 -> -0.13286861 | AZ16: =AM16 -> 0.019233067 | BA16: =AN16 -> -1.7498602 | BC16: =AR16 -> 40451 | BD16: =AT16 -> -0.3182467 | BE16: =AU16 -> 0.0032267014
A17: 40543 | B17: 1.3754459 | C17: -1.4731984 | D17: -4.3372803 | E17: -0.00016910156 | F17: 6.0283243 | G17: 17.375538 | H17: -0.03695678 | I17: 0.26961923 | J17: -0.0084062676 | K17: 14.927038 | L17: -1.5514464 | M17: 0 | N17: 0 | O17: 0.6729625 | P17: 0 | Q17: -0.010960892 | R17: 0 | S17: 0 | T17: 0 | U17: 0 | V17: 0 | W17: 0 | X17: 0 | Y17: -13.193123 | Z17: 1.6728789 | AA17: 0.4341946 | AB17: -0.11512471 | AC17: 0.031882889 | AD17: -2.0389967 | AE17: 7.1302619 | AF17: 27.152484 | AH17: =K17+Y17-Y17/100 -> 1.8658466 | AI17: =Y17/1010 -> -0.013062498 | AJ17: =Z17 -> 1.6728789 | AK17: =AA17 -> 0.4341946 | AL17: =AB17 -> -0.11512471 | AM17: =AC17 -> 0.031882889 | AN17: =AD17 -> -2.0389967 | AR17: =A17 -> 40543 | AS17: =AF17*4+2 -> 110.60994 | AT17: =AH17-$AH$2 -> -0.70904253 | AU17: =SUM(AV17:BA17) -> -0.028227444 | AV17: =AI17 -> -0.013062498 | AW17: =AJ17 -> 1.6728789 | AX17: =AK17 -> 0.4341946 | AY17: =AL17 -> -0.11512471 | AZ17: =AM17 -> 0.031882889 | BA17: =AN17 -> -2.0389967 | BC17: =AR17 -> 40543 | BD17: =AT17 -> -0.70904253 | BE17: =AU17 -> -0.028227444
A18: 40633 | B18: 1.9043017 | C18: -1.5433038 | D18: -4.5069513 | E18: -0.0012869151 | F18: 7.4268885 | G18: 17.45478 | H18: -0.036961388 | I18: 0.30813711 | J18: -0.0078414583 | K18: 16.675365 | L18: -1.4894906 | M18: 0 | N18: 0 | O18: 0.69313123 | P18: 0 | Q18: -0.023400021 | R18: 0 | S18: 0 | T18: 0 | U18: 0 | V18: 0 | W18: 0 | X18: 0 | Y18: -15.514005 | Z18: 1.6560904 | AA18: 0.29727136 | AB18: -0.20292069 | AC18: -0.027254571 | AD18: -2.3847288 | AE18: 7.1083835 | AF18: 27.786204 | AH18: =K18+Y18-Y18/100 -> 1.3164998 | AI18: =Y18/1010 -> -0.015360401 | AJ18: =Z18 -> 1.6560904 | AK18: =AA18 -> 0.29727136 | AL18: =AB18 -> -0.20292069 | AM18: =AC18 -> -0.027254571 | AN18: =AD18 -> -2.3847288 | AR18: =A18 -> 40633 | AS18: =AF18*4+2 -> 113.14482 | AT18: =AH18-$AH$2 -> -1.2583893 | AU18: =SUM(AV18:BA18) -> -0.67690276 | AV18: =AI18 -> -0.015360401 | AW18: =AJ18 -> 1.6560904 | AX18: =AK18 -> 0.29727136 | AY18: =AL18 -> -0.20292069 | AZ18: =AM18 -> -0.027254571 | BA18: =AN18 -> -2.3847288 | BC18: =AR18 -> 40633 | BD18: =AT18 -> -1.2583893 | BE18: =AU18 -> -0.67690276
A19: 40724 | B19: 1.467808 | C19: -1.2043497 | D19: -4.3924235 | E19: -0.0010583469 | F19: 8.406255 | G19: 17.546427 | H19: 0.07324742 | I19: 0.30268883 | J19: -0.0051230818 | K19: 18.729266 | L19: -1.555679 | M19: 0 | N19: 0 | O19: 0.71288761 | P19: 0 | Q19: -0.035226888 | R19: 0 | S19: 0 | T19: 0 | U19: 0 | V19: 0 | W19: 0 | X19: 0 | Y19: -18.615704 | Z19: 1.7520007 | AA19: 0.18453734 | AB19: -0.23254533 | AC19: -0.029947737 | AD19: -2.709168 | AE19: 7.0865847 | AF19: 27.480477 | AH19: =K19+Y19-Y19/100 -> 0.29971978 | AI19: =Y19/1010 -> -0.01843139 | AJ19: =Z19 -> 1.7520007 | AK19: =AA19 -> 0.18453734 | AL19: =AB19 -> -0.23254533 | AM19: =AC19 -> -0.029947737 | AN19: =AD19 -> -2.709168 | AR19: =A19 -> 40724 | AS19: =AF19*4+2 -> 111.92191 | AT19: =AH19-$AH$2 -> -2.2751694 | AU19: =SUM(AV19:BA19) -> -1.0535544 | AV19: =AI19 -> -0.01843139 | AW19: =AJ19 -> 1.7520007 | AX19: =AK19 -> 0.18453734 | AY19: =AL19 -> -0.23254533 | AZ19: =AM19 -> -0.029947737 | BA19: =AN19 -> -2.709168 | BC19: =AR19 -> 40724 | BD19: =AT19 -> -2.2751694 | BE19: =AU19 -> -1.0535544
A20: 40816 | B20: 1.8241286 | C20: -1.0959542 | D20: -4.2580249 | E20: -0.00028471595 | F20: 6.5846466 | G20: 17.671886 | H20: -0.047348455 | I20: 0.34776192 | J20: 0.0012598254 | K20: 21.668795 | L20: -1.6269307 | M20: 0 | N20: 0 | O20: 0.72603408 | P20: 0 | Q20: -0.021518547 | R20: 0 | S20: 0 | T20: 0 | U20: 0 | V20: 0 | W20: 0 | X20: 0 | Y20: -21.294037 | Z20: 2.3087563 | AA20: 0.35473861 | AB20: -0.080751504 | AC20: 0.099261868 | AD20: -2.8984711 | AE20: 7.0648651 | AF20: 27.328812 | AH20: =K20+Y20-Y20/100 -> 0.58769775 | AI20: =Y20/1010 -> -0.021083205 | AJ20: =Z20 -> 2.3087563 | AK20: =AA20 -> 0.35473861 | AL20: =AB20 -> -0.080751504 | AM20: =AC20 -> 0.099261868 | AN20: =AD20 -> -2.8984711 | AR20: =A20 -> 40816 | AS20: =AF20*4+2 -> 111.31525 | AT20: =AH20-$AH$2 -> -1.9871914 | AU20: =SUM(AV20:BA20) -> -0.23754899 | AV20: =AI20 -> -0.021083205 | AW20: =AJ20 -> 2.3087563 | AX20: =AK20 -> 0.35473861 | AY20: =AL20 -> -0.080751504 | AZ20: =AM20 -> 0.099261868 | BA20: =AN20 -> -2.8984711 | BC20: =AR20 -> 40816 | BD20: =AT20 -> -1.9871914 | BE20: =AU20 -> -0.23754899
... A132: 51043 | B132: -0.043141873 | C132: -0.00014191675 | D132: -0.060150045 | E132: 0.00016375639 | F132: 0.077003819 | G132: -0.017761409 | H132: 0.10657899 | I132: -0.12938709 | J132: -0.23383062 | K132: -0.0013647494 | L132: 0.028622522 | M132: 0 | N132: 0 | O132: 0.44750605 | P132: 0 | Q132: 0.30446726 | R132: 0 | S132: 0 | T132: 0 | U132: 0 | V132: 0 | W132: 0 | X132: 0 | Y132: 0.0014171204 | Z132: -0.0014470184 | AA132: 0.00054189822 | AB132: -0.00029329794 | AC132: 0.0013717805 | AD132: 0.0037302372 | AE132: -0.072867892 | AF132: 0.418171 | AH132: =K132+Y132-Y132/100 -> 3.8199787e-05 | AI132: =Y132/1010 -> 1.4030895e-06 | AJ132: =Z132 -> -0.0014470184 | AK132: =AA132 -> 0.00054189822 | AL132: =AB132 -> -0.00029329794 | AM132: =AC132 -> 0.0013717805 | AN132: =AD132 -> 0.0037302372 | AR132: =A132 -> 51043 | AS132: =AF132*4+2 -> 3.672684 | AT132: =AH132-$AH$2 -> -2.5748509 | AU132: =SUM(AV132:BA132) -> 0.0039050027 | AV132: =AI132 -> 1.4030895e-06 | AW132: =AJ132 -> -0.0014470184 | AX132: =AK132 -> 0.00054189822 | AY132: =AL132 -> -0.00029329794 | AZ132: =AM132 -> 0.0013717805 | BA132: =AN132 -> 0.0037302372 | BC132: =AR132 -> 51043 | BD132: =AT132 -> -2.5748509 | BE132: =AU132 -> 0.0039050027

Sheet EA_core_obs_text
A1: date | B1: g_sh | C1: b_liqtil_sh | D1: b_liqp_sh | E1: b_safetil_sh | F1: b_safep_sh | G1: mu_sh | H1: z_sh | I1: lambda_f_sh | J1: lambda_w_sh | K1: rm_sh | L1: sigma_omega_sh | M1: mu_e_sh | N1: gamma_sh | O1: pi_star_sh | P1: lr_sh | Q1: zp_sh | R1: tfp_sh | S1: gdpdef_sh | T1: corepce_sh | U1: gdp_sh | V1: gdi_sh | W1: BBB_sh | X1: AAA_sh | Y1: rm_shl1 | Z1: rm_shl2 | AA1: rm_shl3 | AB1: rm_shl4 | AC1: rm_shl5 | AD1: rm_shl6 | AE1: dettrend | AF1: detrendedMean | AH1: rm_sh | AI1: =Y1 -> rm_shl1 | AJ1: =Z1 -> rm_shl2 | AK1: =AA1 -> rm_shl3 | AL1: =AB1 -> rm_shl4 | AM1: =AC1 -> rm_shl5 | AN1: =AD1 -> rm_shl6 | AQ1: Plot | AR1: =A1 -> date | AS1: =AF1 -> detrendedMean | AT1: Surprise Policy (t) | AU1: Fgsum | AV1: Anticipated (t+1|t) | AW1: Anticipated (t+2|t) | AX1: Anticipated (t+3|t) | AY1: Anticipated (t+4|t) | AZ1: Anticipated (t+5|t) | BA1: Anticipated (t+6|t) | BB1: Combined | BC1: date | BD1: rm_sh | BE1: Fgsum
A2: 39172 | B2: 0.0021404024 | C2: -0.00021531842 | D2: -0.027406535 | E2: 0.010716026 | F2: -0.10259181 | G2: -0.005672916 | H2: 4.7504164e-06 | I2: 0.40749559 | J2: -0.046122599 | K2: 0.009787271 | L2: -0.0025163728 | M2: 0 | N2: 0 | O2: -0.4012209 | P2: 0 | Q2: -0.015969127 | R2: 0 | S2: 0 | T2: -0.047570565 | U2: 0 | V2: 0 | W2: 0 | X2: 0 | Y2: 0 | Z2: 0 | AA2: 0 | AB2: 0 | AC2: 0 | AD2: 0 | AE2: 0.52221691 | AF2: 0.30621359 | AH2: =K2+Y2-Y2/100 -> 0.009787271 | AI2: =Y2 -> 0 | AJ2: =Z2 -> 0 | AK2: =AA2 -> 0 | AL2: =AB2 -> 0 | AM2: =AC2 -> 0 | AN2: =AD2 -> 0 | AR2: =A2 -> 39172 | AS2: =AF2*4+2 -> 3.2248543 | AU2: =SUM(AV2:BA2) -> 0 | AV2: =AI2 -> 0 | AW2: =AJ2 -> 0 | AX2: =AK2 -> 0 | AY2: =AL2 -> 0 | AZ2: =AM2 -> 0 | BA2: =AN2 -> 0 | BB2: =SUM(AT2:BA2) -> 0 | BC2: =AR2 -> 39172 | BD2: =AT2-$AT$2 -> 0 | BE2: =AU2-$AU$2 -> 0
A3: 39263 | B3: 0.0021451928 | C3: -0.00032902244 | D3: -0.042334438 | E3: 0.013430215 | F3: -0.093627333 | G3: -0.0059884011 | H3: 3.8397724e-05 | I3: 0.10077733 | J3: -0.046105392 | K3: 0.010563829 | L3: -0.0027263725 | M3: 0 | N3: 0 | O3: -0.37674819 | P3: 0 | Q3: -0.016199221 | R3: 0 | S3: 0 | T3: 0.12248615 | U3: 0 | V3: 0 | W3: 0 | X3: 0 | Y3: 0 | Z3: 0 | AA3: 0 | AB3: 0 | AC3: 0 | AD3: 0 | AE3: 0.516852 | AF3: 0.1836179 | AH3: =K3+Y3-Y3/100 -> 0.010563829 | AI3: =Y3 -> 0 | AJ3: =Z3 -> 0 | AK3: =AA3 -> 0 | AL3: =AB3 -> 0 | AM3: =AC3 -> 0 | AN3: =AD3 -> 0 | AR3: =A3 -> 39263 | AS3: =AF3*4+2 -> 2.7344716 | AU3: =SUM(AV3:BA3) -> 0 | AV3: =AI3 -> 0 | AW3: =AJ3 -> 0 | AX3: =AK3 -> 0 | AY3: =AL3 -> 0 | AZ3: =AM3 -> 0 | BA3: =AN3 -> 0 | BB3: =SUM(AT3:BA3) -> 0 | BC3: =AR3 -> 39263 | BD3: =AT3-$AT$2 -> 0 | BE3: =AU3 -> 0
A4: 39355 | B4: 0.002239871 | C4: -0.00033670633 | D4: -0.066613193 | E4: 0.014532153 | F4: -0.087427047 | G4: -0.0036365746 | H4: 5.9389261e-05 | I4: 0.10268079 | J4: -0.044171096 | K4: 0.0094272456 | L4: -0.0029365251 | M4: 0 | N4: 0 | O4: -0.28640048 | P4: 0 | Q4: -0.011052169 | R4: 0 | S4: 0 | T4: -0.2756901 | U4: 0 | V4: 0 | W4: 0 | X4: 0 | Y4: 0 | Z4: 0 | AA4: 0 | AB4: 0 | AC4: 0 | AD4: 0 | AE4: 0.51154515 | AF4: -0.1425856 | AH4: =K4+Y4-Y4/100 -> 0.0094272456 | AI4: =Y4 -> 0 | AJ4: =Z4 -> 0 | AK4: =AA4 -> 0 | AL4: =AB4 -> 0 | AM4: =AC4 -> 0 | AN4: =AD4 -> 0 | AR4: =A4 -> 39355 | AS4: =AF4*4+2 -> 1.4296576 | AU4: =SUM(AV4:BA4) -> 0 | AV4: =AI4 -> 0 | AW4: =AJ4 -> 0 | AX4: =AK4 -> 0 | AY4: =AL4 -> 0 | AZ4: =AM4 -> 0 | BA4: =AN4 -> 0 | BB4: =SUM(AT4:BA4) -> 0 | BC4: =AR4 -> 39355 | BD4: =AT4-$AT$2 -> 0 | BE4: =AU4 -> 0
A5: 39447 | B5: 0.0020895456 | C5: -0.00044563956 | D5: -0.11570005 | E5: 0.017055831 | F5: -0.089192005 | G5: -0.0012842472 | H5: 6.0969983e-05 | I5: 0.21162615 | J5: -0.043441925 | K5: 0.0098250144 | L5: -0.0031397243 | M5: 0 | N5: 0 | O5: -0.28843663 | P5: 0 | Q5: -0.011200943 | R5: 0 | S5: 0 | T5: 0.75072854 | U5: 0 | V5: 0 | W5: 0 | X5: 0 | Y5: 0 | Z5: 0 | AA5: 0 | AB5: 0 | AC5: 0 | AD5: 0 | AE5: 0.50629568 | AF5: 0.96254764 | AH5: =K5+Y5-Y5/100 -> 0.0098250144 | AI5: =Y5 -> 0 | AJ5: =Z5 -> 0 | AK5: =AA5 -> 0 | AL5: =AB5 -> 0 | AM5: =AC5 -> 0 | AN5: =AD5 -> 0 | AR5: =A5 -> 39447 | AS5: =AF5*4+2 -> 5.8501905 | AU5: =SUM(AV5:BA5) -> 0 | AV5: =AI5 -> 0 | AW5: =AJ5 -> 0 | AX5: =AK5 -> 0 | AY5: =AL5 -> 0 | AZ5: =AM5 -> 0 | BA5: =AN5 -> 0 | BB5: =SUM(AT5:BA5) -> 0 | BC5: =AR5 -> 39447 | BD5: =AT5-$AT$2 -> 0 | BE5: =AU5 -> 0
A6: 39538 | B6: 0.0019958552 | C6: -0.00049335007 | D6: -0.1425724 | E6: 0.017384132 | F6: -0.093433999 | G6: 0.00275346 | H6: 6.5818318e-05 | I6: 0.25644436 | J6: -0.049259309 | K6: 0.010941807 | L6: -0.0033309896 | M6: 0 | N6: 0 | O6: -0.20573428 | P6: 0 | Q6: -0.007384913 | R6: 0 | S6: 0 | T6: 0.85712488 | U6: 0 | V6: 0 | W6: 0 | X6: 0 | Y6: 0 | Z6: 0 | AA6: 0 | AB6: 0 | AC6: 0 | AD6: 0 | AE6: 0.50110294 | AF6: 1.168515 | AH6: =K6+Y6-Y6/100 -> 0.010941807 | AI6: =Y6 -> 0 | AJ6: =Z6 -> 0 | AK6: =AA6 -> 0 | AL6: =AB6 -> 0 | AM6: =AC6 -> 0 | AN6: =AD6 -> 0 | AR6: =A6 -> 39538 | AS6: =AF6*4+2 -> 6.6740598 | AU6: =SUM(AV6:BA6) -> 0 | AV6: =AI6 -> 0 | AW6: =AJ6 -> 0 | AX6: =AK6 -> 0 | AY6: =AL6 -> 0 | AZ6: =AM6 -> 0 | BA6: =AN6 -> 0 | BB6: =SUM(AT6:BA6) -> 0 | BC6: =AR6 -> 39538 | BD6: =AT6-$AT$2 -> 0 | BE6: =AU6 -> 0
A7: 39629 | B7: 0.0017753856 | C7: -0.00060589952 | D7: -0.16292177 | E7: 0.018065582 | F7: -0.099512223 | G7: 0.0034935131 | H7: 8.0499007e-05 | I7: 0.01983603 | J7: -0.046054517 | K7: 0.0084977391 | L7: -0.0035062797 | M7: 0 | N7: 0 | O7: -0.21646614 | P7: 0 | Q7: -0.00035211988 | R7: 0 | S7: 0 | T7: 0.20356844 | U7: 0 | V7: 0 | W7: 0 | X7: 0 | Y7: 0 | Z7: 0 | AA7: 0 | AB7: 0 | AC7: 0 | AD7: 0 | AE7: 0.49596629 | AF7: 0.22446679 | AH7: =K7+Y7-Y7/100 -> 0.0084977391 | AI7: =Y7 -> 0 | AJ7: =Z7 -> 0 | AK7: =AA7 -> 0 | AL7: =AB7 -> 0 | AM7: =AC7 -> 0 | AN7: =AD7 -> 0 | AR7: =A7 -> 39629 | AS7: =AF7*4+2 -> 2.8978671 | AU7: =SUM(AV7:BA7) -> 0 | AV7: =AI7 -> 0 | AW7: =AJ7 -> 0 | AX7: =AK7 -> 0 | AY7: =AL7 -> 0 | AZ7: =AM7 -> 0 | BA7: =AN7 -> 0 | BB7: =SUM(AT7:BA7) -> 0 | BC7: =AR7 -> 39629 | BD7: =AT7-$AT$2 -> 0 | BE7: =AU7 -> 0
A8: 39721 | B8: 0.0010982528 | C8: -0.00073744287 | D8: -0.17512871 | E8: 0.017793986 | F8: -0.10212107 | G8: 0.0071746401 | H8: 0.0001009147 | I8: -0.16270357 | J8: -0.05322819 | K8: 0.0060906817 | L8: -0.0036569868 | M8: 0 | N8: 0 | O8: -0.12602885 | P8: 0 | Q8: 0.0092882743 | R8: 0 | S8: 0 | T8: 0.11287197 | U8: 0 | V8: 0 | W8: 0 | X8: 0 | Y8: 0 | Z8: 0 | AA8: 0 | AB8: 0 | AC8: 0 | AD8: 0 | AE8: 0.49088508 | AF8: 0.020385671 | AH8: =K8+Y8-Y8/100 -> 0.0060906817 | AI8: =Y8 -> 0 | AJ8: =Z8 -> 0 | AK8: =AA8 -> 0 | AL8: =AB8 -> 0 | AM8: =AC8 -> 0 | AN8: =AD8 -> 0 | AR8: =A8 -> 39721 | AS8: =AF8*4+2 -> 2.0815427 | AT8: =AH8-$AH$8 -> 0 | AU8: =SUM(AV8:BA8) -> 0 | AV8: =AI8 -> 0 | AW8: =AJ8 -> 0 | AX8: =AK8 -> 0 | AY8: =AL8 -> 0 | AZ8: =AM8 -> 0 | BA8: =AN8 -> 0 | BB8: =SUM(AT8:BA8) -> 0 | BC8: =AR8 -> 39721 | BD8: =AT8-$AT$2 -> 0 | BE8: =AU8 -> 0
A9: 39813 | B9: 0.00061932951 | C9: -0.00067053634 | D9: -0.25188489 | E9: 0.013903552 | F9: -0.12900538 | G9: 0.022400038 | H9: 0.00015142344 | I9: -0.039783289 | J9: -0.053466747 | K9: 0.0052719687 | L9: -0.0037697997 | M9: 0 | N9: 0 | O9: -0.02123707 | P9: 0 | Q9: 0.035488892 | R9: 0 | S9: 0 | T9: -0.2815676 | U9: 0 | V9: 0 | W9: 0 | X9: 0 | Y9: 0.0012966502 | Z9: -0.00027349225 | AA9: -0.00071186815 | AB9: -0.00022021115 | AC9: -0.00018299763 | AD9: -0.00020751636 | AE9: 0.48585869 | AF9: -0.2239735 | AH9: =K9+Y9-Y9/100 -> 0.0065556525 | AI9: =Y9/1010 -> 1.2838121e-06 | AJ9: =Z9 -> -0.00027349225 | AK9: =AA9 -> -0.00071186815 | AL9: =AB9 -> -0.00022021115 | AM9: =AC9 -> -0.00018299763 | AN9: =AD9 -> -0.00020751636 | AR9: =A9 -> 39813 | AS9: =AF9*4+2 -> 1.104106 | AT9: =AH9-$AH$8 -> 0.0004649708 | AU9: =SUM(AV9:BA9) -> -0.0015948017 | AV9: =AI9 -> 1.2838121e-06 | AW9: =AJ9 -> -0.00027349225 | AX9: =AK9 -> -0.00071186815 | AY9: =AL9 -> -0.00022021115 | AZ9: =AM9 -> -0.00018299763 | BA9: =AN9 -> -0.00020751636 | BB9: =SUM(AT9:AU9) -> -0.0011298309 | BC9: =AR9 -> 39813 | BD9: =AT9-$AT$2 -> 0.0004649708 | BE9: =AU9 -> -0.0015948017
A10: 39903 | B10: -0.0007526867 | C10: -0.00050328922 | D10: -0.26677297 | E10: 0.0085203876 | F10: -0.15833019 | G10: 0.025985186 | H10: 0.00012524313 | I10: -0.28947041 | J10: -0.041107256 | K10: 0.006998787 | L10: -0.003827811 | M10: 0 | N10: 0 | O10: -0.030905419 | P10: 0 | Q10: 0.056782421 | R10: 0 | S10: 0 | T10: -0.67807726 | U10: 0 | V10: 0 | W10: 0 | X10: 0 | Y10: 0.00068444091 | Z10: -0.0014127671 | AA10: -0.0015084975 | AB10: -0.00085595595 | AC10: -0.00083036181 | AD10: -0.0012309648 | AE10: 0.48088649 | AF10: -0.91314815 | AH10: =K10+Y10-Y10/100 -> 0.0076763835 | AI10: =Y10/1010 -> 6.7766427e-07 | AJ10: =Z10 -> -0.0014127671 | AK10: =AA10 -> -0.0015084975 | AL10: =AB10 -> -0.00085595595 | AM10: =AC10 -> -0.00083036181 | AN10: =AD10 -> -0.0012309648 | AR10: =A10 -> 39903 | AS10: =AF10*4+2 -> -1.6525926 | AT10: =AH10-$AH$8 -> 0.0015857018 | AU10: =SUM(AV10:BA10) -> -0.0058378694 | AV10: =AI10 -> 6.7766427e-07 | AW10: =AJ10 -> -0.0014127671 | AX10: =AK10 -> -0.0015084975 | AY10: =AL10 -> -0.00085595595 | AZ10: =AM10 -> -0.00083036181 | BA10: =AN10 -> -0.0012309648 | BB10: =SUM(AT10:AU10) -> -0.0042521676 | BC10: =AR10 -> 39903 | BD10: =AT10-$AT$2 -> 0.0015857018 | BE10: =AU10 -> -0.0058378694
A11: 39994 | B11: -0.0013879828 | C11: -0.00046833096 | D11: -0.22080451 | E11: 0.005351674 | F11: -0.17851166 | G11: 0.023378385 | H11: 2.7229515e-06 | I11: -0.49182801 | J11: -0.030927551 | K11: 0.0067767368 | L11: -0.0038247275 | M11: 0 | N11: 0 | O11: -0.046415867 | P11: 0 | Q11: 0.04967237 | R11: 0 | S11: 0 | T11: -0.27799551 | U11: 0 | V11: 0 | W11: 0 | X11: 0 | Y11: 0.0010915713 | Z11: -0.0016191498 | AA11: -0.0014790691 | AB11: -0.0009019387 | AC11: -0.00068537068 | AD11: -0.0022271421 | AE11: 0.47596787 | AF11: -0.71093598 | AH11: =K11+Y11-Y11/100 -> 0.0078573924 | AI11: =Y11/1010 -> 1.0807636e-06 | AJ11: =Z11 -> -0.0016191498 | AK11: =AA11 -> -0.0014790691 | AL11: =AB11 -> -0.0009019387 | AM11: =AC11 -> -0.00068537068 | AN11: =AD11 -> -0.0022271421 | AR11: =A11 -> 39994 | AS11: =AF11*4+2 -> -0.8437439 | AT11: =AH11-$AH$8 -> 0.0017667107 | AU11: =SUM(AV11:BA11) -> -0.0069115896 | AV11: =AI11 -> 1.0807636e-06 | AW11: =AJ11 -> -0.0016191498 | AX11: =AK11 -> -0.0014790691 | AY11: =AL11 -> -0.0009019387 | AZ11: =AM11 -> -0.00068537068 | BA11: =AN11 -> -0.0022271421 | BB11: =SUM(AT11:AU11) -> -0.0051448789 | BC11: =AR11 -> 39994 | BD11: =AT11-$AT$2 -> 0.0017667107 | BE11: =AU11 -> -0.0069115896
A12: 40086 | B12: -0.0014089763 | C12: -0.00043044352 | D12: -0.13110504 | E12: 0.0019804701 | F12: -0.1978415 | G12: 0.016001799 | H12: -6.6489928e-05 | I12: -0.56839525 | J12: -0.025650639 | K12: 0.0061611895 | L12: -0.0037728321 | M12: 0 | N12: 0 | O12: -0.031905407 | P12: 0 | Q12: 0.041906267 | R12: 0 | S12: 0 | T12: -0.66597775 | U12: 0 | V12: 0 | W12: 0 | X12: 0 | Y12: 0.0015957069 | Z12: -0.0015571071 | AA12: -0.0011298881 | AB12: -0.00074591147 | AC12: -0.00041362834 | AD12: -0.0030907383 | AE12: 0.47110222 | AF12: -1.1149563 | AH12: =K12+Y12-Y12/100 -> 0.0077409393 | AI12: =Y12/1010 -> 1.5799078e-06 | AJ12: =Z12 -> -0.0015571071 | AK12: =AA12 -> -0.0011298881 | AL12: =AB12 -> -0.00074591147 | AM12: =AC12 -> -0.00041362834 | AN12: =AD12 -> -0.0030907383 | AR12: =A12 -> 40086 | AS12: =AF12*4+2 -> -2.4598252 | AT12: =AH12-$AH$8 -> 0.0016502576 | AU12: =SUM(AV12:BA12) -> -0.0069356934 | AV12: =AI12 -> 1.5799078e-06 | AW12: =AJ12 -> -0.0015571071 | AX12: =AK12 -> -0.0011298881 | AY12: =AL12 -> -0.00074591147 | AZ12: =AM12 -> -0.00041362834 | BA12: =AN12 -> -0.0030907383 | BB12: =SUM(AT12:AU12) -> -0.0052854358 | BC12: =AR12 -> 40086 | BD12: =AT12-$AT$2 -> 0.0016502576 | BE12: =AU12 -> -0.0069356934
A13: 40178 | B13: -0.001473814 | C13: -0.0004474703 | D13: -0.072329441 | E13: 0.0010479111 | F13: -0.21617533 | G13: 0.0099442155 | H13: -9.1896698e-05 | I13: -0.59908415 | J13: -0.022727934 | K13: 0.0047292371 | L13: -0.0036915182 | M13: 0 | N13: 0 | O13: -0.10529871 | P13: 0 | Q13: 0.03351911 | R13: 0 | S13: 0 | T13: -0.50308559 | U13: 0 | V13: 0 | W13: 0 | X13: 0 | Y13: 0.0018675717 | Z13: -0.0016994617 | AA13: -0.0012798721 | AB13: -0.0010192944 | AC13: -0.00044191849 | AD13: -0.0040707193 | AE13: 0.46628894 | AF13: -1.0342815 | AH13: =K13+Y13-Y13/100 -> 0.0065781331 | AI13: =Y13/1010 -> 1.8490809e-06 | AJ13: =Z13 -> -0.0016994617 | AK13: =AA13 -> -0.0012798721 | AL13: =AB13 -> -0.0010192944 | AM13: =AC13 -> -0.00044191849 | AN13: =AD13 -> -0.0040707193 | AR13: =A13 -> 40178 | AS13: =AF13*4+2 -> -2.1371259 | AT13: =AH13-$AH$8 -> 0.00048745142 | AU13: =SUM(AV13:BA13) -> -0.0085094169 | AV13: =AI13 -> 1.8490809e-06 | AW13: =AJ13 -> -0.0016994617 | AX13: =AK13 -> -0.0012798721 | AY13: =AL13 -> -0.0010192944 | AZ13: =AM13 -> -0.00044191849 | BA13: =AN13 -> -0.0040707193 | BB13: =SUM(AT13:AU13) -> -0.0080219654 | BC13: =AR13 -> 40178 | BD13: =AT13-$AT$2 -> 0.00048745142 | BE13: =AU13 -> -0.0085094169
A14: 40268 | B14: -0.0014513222 | C14: -0.00056281404 | D14: -0.020963363 | E14: 0.00048442719 | F14: -0.23367379 | G14: 0.0067159083 | H14: -0.00010099051 | I14: -0.63770638 | J14: -0.018181034 | K14: 0.0050069653 | L14: -0.0035950004 | M14: 0 | N14: 0 | O14: -0.14057276 | P14: 0 | Q14: 0.026054662 | R14: 0 | S14: 0 | T14: -0.49356445 | U14: 0 | V14: 0 | W14: 0 | X14: 0 | Y14: 0.0028192917 | Z14: -0.0014779849 | AA14: -0.00081833133 | AB14: -0.00072008531 | AC14: 5.955309e-05 | AD14: -0.0045739171 | AE14: 0.46152744 | AF14: -1.074627 | AH14: =K14+Y14-Y14/100 -> 0.0077980641 | AI14: =Y14/1010 -> 2.7913779e-06 | AJ14: =Z14 -> -0.0014779849 | AK14: =AA14 -> -0.00081833133 | AL14: =AB14 -> -0.00072008531 | AM14: =AC14 -> 5.955309e-05 | AN14: =AD14 -> -0.0045739171 | AR14: =A14 -> 40268 | AS14: =AF14*4+2 -> -2.2985079 | AT14: =AH14-$AH$8 -> 0.0017073824 | AU14: =SUM(AV14:BA14) -> -0.0075279742 | AV14: =AI14 -> 2.7913779e-06 | AW14: =AJ14 -> -0.0014779849 | AX14: =AK14 -> -0.00081833133 | AY14: =AL14 -> -0.00072008531 | AZ14: =AM14 -> 5.955309e-05 | BA14: =AN14 -> -0.0045739171 | BB14: =SUM(AT14:AU14) -> -0.0058205918 | BC14: =AR14 -> 40268 | BD14: =AT14-$AT$2 -> 0.0017073824 | BE14: =AU14 -> -0.0075279742
A15: 40359 | B15: -0.0013898119 | C15: -0.00061328467 | D15: -0.0024096786 | E15: -0.00059269014 | F15: -0.25545268 | G15: 0.0066907065 | H15: -0.00012822335 | I15: -0.51971019 | J15: -0.018280792 | K15: 0.0038314525 | L15: -0.0034963732 | M15: 0 | N15: 0 | O15: -0.14139511 | P15: 0 | Q15: 0.018244904 | R15: 0 | S15: 0 | T15: -0.47723536 | U15: 0 | V15: 0 | W15: 0 | X15: 0 | Y15: 0.0037493586 | Z15: -0.0011710937 | AA15: -1.354924e-05 | AB15: -3.2427473e-06 | AC15: 0.00083244139 | AD15: -0.0043052865 | AE15: 0.45681713 | AF15: -0.95354208 | AH15: =K15+Y15-Y15/100 -> 0.0075433175 | AI15: =Y15/1010 -> 3.7122363e-06 | AJ15: =Z15 -> -0.0011710937 | AK15: =AA15 -> -1.354924e-05 | AL15: =AB15 -> -3.2427473e-06 | AM15: =AC15 -> 0.00083244139 | AN15: =AD15 -> -0.0043052865 | AR15: =A15 -> 40359 | AS15: =AF15*4+2 -> -1.8141683 | AT15: =AH15-$AH$8 -> 0.0014526358 | AU15: =SUM(AV15:BA15) -> -0.0046570186 | AV15: =AI15 -> 3.7122363e-06 | AW15: =AJ15 -> -0.0011710937 | AX15: =AK15 -> -1.354924e-05 | AY15: =AL15 -> -3.2427473e-06 | AZ15: =AM15 -> 0.00083244139 | BA15: =AN15 -> -0.0043052865 | BB15: =SUM(AT15:AU15) -> -0.0032043828 | BC15: =AR15 -> 40359 | BD15: =AT15-$AT$2 -> 0.0014526358 | BE15: =AU15 -> -0.0046570186
A16: 40451 | B16: -0.0013418968 | C16: -0.00062607812 | D16: 0.010076335 | E16: -0.0015144793 | F16: -0.26804806 | G16: 0.0053497403 | H16: -0.00013701466 | I16: -0.23323882 | J16: -0.014429497 | K16: 0.001744028 | L16: -0.0034000237 | M16: 0 | N16: 0 | O16: -0.09554398 | P16: 0 | Q16: 0.013792848 | R16: 0 | S16: 0 | T16: -0.4418238 | U16: 0 | V16: 0 | W16: 0 | X16: 0 | Y16: 0.0045877459 | Z16: -0.0016699259 | AA16: -6.8778233e-05 | AB16: -2.0697933e-05 | AC16: 0.00085671281 | AD16: -0.0040227767 | AE16: 0.45215744 | AF16: -0.5894144 | AH16: =K16+Y16-Y16/100 -> 0.0062858964 | AI16: =Y16/1010 -> 4.5423227e-06 | AJ16: =Z16 -> -0.0016699259 | AK16: =AA16 -> -6.8778233e-05 | AL16: =AB16 -> -2.0697933e-05 | AM16: =AC16 -> 0.00085671281 | AN16: =AD16 -> -0.0040227767 | AR16: =A16 -> 40451 | AS16: =AF16*4+2 -> -0.35765761 | AT16: =AH16-$AH$8 -> 0.00019521475 | AU16: =SUM(AV16:BA16) -> -0.0049209236 | AV16: =AI16 -> 4.5423227e-06 | AW16: =AJ16 -> -0.0016699259 | AX16: =AK16 -> -6.8778233e-05 | AY16: =AL16 -> -2.0697933e-05 | AZ16: =AM16 -> 0.00085671281 | BA16: =AN16 -> -0.0040227767 | BB16: =SUM(AT16:AU16) -> -0.0047257088 | BC16: =AR16 -> 40451 | BD16: =AT16-$AT$2 -> 0.00019521475 | BE16: =AU16 -> -0.0049209236
A17: 40543 | B17: -0.0015103358 | C17: -0.0007026594 | D17: 0.014122611 | E17: -0.00031423703 | F17: -0.27431258 | G17: 0.0040606013 | H17: -0.00015491314 | I17: -0.48794745 | J17: -0.010547862 | K17: -1.1337006e-05 | L17: -0.0033099743 | M17: 0 | N17: 0 | O17: -0.12714963 | P17: 0 | Q17: 0.0061475483 | R17: 0 | S17: 0 | T17: -0.062019444 | U17: 0 | V17: 0 | W17: 0 | X17: 0 | Y17: 0.0056269822 | Z17: -0.0023950547 | AA17: -0.00035144439 | AB17: -0.00036478838 | AC17: 0.0004326719 | AD17: -0.0041743896 | AE17: 0.4475478 | AF17: -0.50831897 | AH17: =K17+Y17-Y17/100 -> 0.0055593753 | AI17: =Y17/1010 -> 5.5712695e-06 | AJ17: =Z17 -> -0.0023950547 | AK17: =AA17 -> -0.00035144439 | AL17: =AB17 -> -0.00036478838 | AM17: =AC17 -> 0.0004326719 | AN17: =AD17 -> -0.0041743896 | AR17: =A17 -> 40543 | AS17: =AF17*4+2 -> -0.033275872 | AT17: =AH17-$AH$8 -> -0.00053130633 | AU17: =SUM(AV17:BA17) -> -0.0068474338 | AV17: =AI17 -> 5.5712695e-06 | AW17: =AJ17 -> -0.0023950547 | AX17: =AK17 -> -0.00035144439 | AY17: =AL17 -> -0.00036478838 | AZ17: =AM17 -> 0.0004326719 | BA17: =AN17 -> -0.0041743896 | BB17: =SUM(AT17:AU17) -> -0.0073787402 | BC17: =AR17 -> 40543 | BD17: =AT17-$AT$2 -> -0.00053130633 | BE17: =AU17 -> -0.0068474338
A18: 40633 | B18: -0.00092162476 | C18: -0.0007127858 | D18: 0.039641604 | E18: -0.00044608078 | F18: -0.27677658 | G18: 0.003491467 | H18: -0.00015927566 | I18: -0.27290472 | J18: -0.011397202 | K18: -0.00071516596 | L18: -0.0032281028 | M18: 0 | N18: 0 | O18: -0.10171719 | P18: 0 | Q18: 0.0046155339 | R18: 0 | S18: 0 | T18: 0.083287589 | U18: 0 | V18: 0 | W18: 0 | X18: 0 | Y18: 0.006551125 | Z18: -0.0032528712 | AA18: -0.00076879447 | AB18: -0.00081241022 | AC18: -8.5334119e-05 | AD18: -0.0048461499 | AE18: 0.44298763 | AF18: -0.10186722 | AH18: =K18+Y18-Y18/100 -> 0.0057704478 | AI18: =Y18/1010 -> 6.4862624e-06 | AJ18: =Z18 -> -0.0032528712 | AK18: =AA18 -> -0.00076879447 | AL18: =AB18 -> -0.00081241022 | AM18: =AC18 -> -8.5334119e-05 | AN18: =AD18 -> -0.0048461499 | AR18: =A18 -> 40633 | AS18: =AF18*4+2 -> 1.5925311 | AT18: =AH18-$AH$8 -> -0.00032023387 | AU18: =SUM(AV18:BA18) -> -0.0097590737 | AV18: =AI18 -> 6.4862624e-06 | AW18: =AJ18 -> -0.0032528712 | AX18: =AK18 -> -0.00076879447 | AY18: =AL18 -> -0.00081241022 | AZ18: =AM18 -> -8.5334119e-05 | BA18: =AN18 -> -0.0048461499 | BB18: =SUM(AT18:AU18) -> -0.010079308 | BC18: =AR18 -> 40633 | BD18: =AT18-$AT$2 -> -0.00032023387 | BE18: =AU18 -> -0.0097590737
A19: 40724 | B19: -0.0010904756 | C19: -0.00078801673 | D19: 0.078534787 | E19: -0.00060414642 | F19: -0.28950415 | G19: 0.0032192428 | H19: -0.00016952726 | I19: -0.38000355 | J19: -0.01460072 | K19: -0.0038232942 | L19: -0.0031584225 | M19: 0 | N19: 0 | O19: -0.1020958 | P19: 0 | Q19: 0.0021449803 | R19: 0 | S19: 0 | T19: 0.26121232 | U19: 0 | V19: 0 | W19: 0 | X19: 0 | Y19: 0.0078998258 | Z19: -0.0042743591 | AA19: -0.0012073613 | AB19: -0.0012510342 | AC19: -0.00052708748 | AD19: -0.0058619746 | AE19: 0.4384764 | AF19: -0.020381595 | AH19: =K19+Y19-Y19/100 -> 0.0039975333 | AI19: =Y19/1010 -> 7.8216097e-06 | AJ19: =Z19 -> -0.0042743591 | AK19: =AA19 -> -0.0012073613 | AL19: =AB19 -> -0.0012510342 | AM19: =AC19 -> -0.00052708748 | AN19: =AD19 -> -0.0058619746 | AR19: =A19 -> 40724 | AS19: =AF19*4+2 -> 1.9184736 | AT19: =AH19-$AH$8 -> -0.0020931483 | AU19: =SUM(AV19:BA19) -> -0.013113995 | AV19: =AI19 -> 7.8216097e-06 | AW19: =AJ19 -> -0.0042743591 | AX19: =AK19 -> -0.0012073613 | AY19: =AL19 -> -0.0012510342 | AZ19: =AM19 -> -0.00052708748 | BA19: =AN19 -> -0.0058619746 | BB19: =SUM(AT19:AU19) -> -0.015207144 | BC19: =AR19 -> 40724 | BD19: =AT19-$AT$2 -> -0.0020931483 | BE19: =AU19 -> -0.013113995
A20: 40816 | B20: -0.001127368 | C20: -0.00097188345 | D20: 0.10348755 | E20: -0.0027083119 | F20: -0.32715509 | G20: 0.006225712 | H20: -0.00017554476 | I20: -0.29194471 | J20: -0.012858406 | K20: -0.006334894 | L20: -0.0031001499 | M20: 0 | N20: 0 | O20: -0.092475461 | P20: 0 | Q20: 0.0035692275 | R20: 0 | S20: 0 | T20: 0.21319531 | U20: 0 | V20: 0 | W20: 0 | X20: 0 | Y20: 0.011236053 | Z20: -0.0045156428 | AA20: -0.00038647654 | AB20: -0.00033736246 | AC20: 0.00037777057 | AD20: -0.0057859113 | AE20: 0.43401353 | AF20: 0.020385671 | AH20: =K20+Y20-Y20/100 -> 0.004788798 | AI20: =Y20/1010 -> 1.1124804e-05 | AJ20: =Z20 -> -0.0045156428 | AK20: =AA20 -> -0.00038647654 | AL20: =AB20 -> -0.00033736246 | AM20: =AC20 -> 0.00037777057 | AN20: =AD20 -> -0.0057859113 | AR20: =A20 -> 40816 | AS20: =AF20*4+2 -> 2.0815427 | AT20: =AH20-$AH$8 -> -0.0013018836 | AU20: =SUM(AV20:BA20) -> -0.010636498 | AV20: =AI20 -> 1.1124804e-05 | AW20: =AJ20 -> -0.0045156428 | AX20: =AK20 -> -0.00038647654 | AY20: =AL20 -> -0.00033736246 | AZ20: =AM20 -> 0.00037777057 | BA20: =AN20 -> -0.0057859113 | BB20: =SUM(AT20:AU20) -> -0.011938381 | BC20: =AR20 -> 40816 | BD20: =AT20-$AT$2 -> -0.0013018836 | BE20: =AU20 -> -0.010636498
... A132: 51043 | B132: -0.043141873 | C132: -0.00014191675 | D132: -0.060150045 | E132: 0.00016375639 | F132: 0.077003819 | G132: -0.017761409 | H132: 0.10657899 | I132: -0.12938709 | J132: -0.23383062 | K132: -0.0013647494 | L132: 0.028622522 | M132: 0 | N132: 0 | O132: 0.44750605 | P132: 0 | Q132: 0.30446726 | R132: 0 | S132: 0 | T132: 0 | U132: 0 | V132: 0 | W132: 0 | X132: 0 | Y132: 0.0014171204 | Z132: -0.0014470184 | AA132: 0.00054189822 | AB132: -0.00029329794 | AC132: 0.0013717805 | AD132: 0.0037302372 | AE132: -0.072867892 | AF132: 0.418171 | AH132: =K132+Y132-Y132/100 -> 3.8199787e-05 | AI132: =Y132/1010 -> 1.4030895e-06 | AJ132: =Z132 -> -0.0014470184 | AK132: =AA132 -> 0.00054189822 | AL132: =AB132 -> -0.00029329794 | AM132: =AC132 -> 0.0013717805 | AN132: =AD132 -> 0.0037302372 | AR132: =A132 -> 51043 | AS132: =AF132*4+2 -> 3.672684 | AT132: =AH132-$AH$8 -> -0.0060524819 | AU132: =SUM(AV132:BA132) -> 0.0039050027 | AV132: =AI132 -> 1.4030895e-06 | AW132: =AJ132 -> -0.0014470184 | AX132: =AK132 -> 0.00054189822 | AY132: =AL132 -> -0.00029329794 | AZ132: =AM132 -> 0.0013717805 | BA132: =AN132 -> 0.0037302372 | BB132: =SUM(AT132:AU132) -> -0.0021474791 | BC132: =AR132 -> 51043 | BD132: =AT132-$AT$2 -> -0.0060524819 | BE132: =AU132 -> 0.0039050027

Sheet EA_contributio_to_nominal_PR
A1: date | B1: g_sh | C1: b_liqtil_sh | D1: b_liqp_sh | E1: b_safetil_sh | F1: b_safep_sh | G1: mu_sh | H1: z_sh | I1: lambda_f_sh | J1: lambda_w_sh | K1: rm_sh | L1: sigma_omega_sh | M1: mu_e_sh | N1: gamma_sh | O1: pi_star_sh | P1: lr_sh | Q1: zp_sh | R1: tfp_sh | S1: gdpdef_sh | T1: corepce_sh | U1: gdp_sh | V1: gdi_sh | W1: BBB_sh | X1: AAA_sh | Y1: rm_shl1 | Z1: rm_shl2 | AA1: rm_shl3 | AB1: rm_shl4 | AC1: rm_shl5 | AD1: rm_shl6 | AE1: dettrend | AF1: detrendedMean | AH1: rm_sh | AI1: =Y1 -> rm_shl1 | AJ1: =Z1 -> rm_shl2 | AK1: =AA1 -> rm_shl3 | AL1: =AB1 -> rm_shl4 | AM1: =AC1 -> rm_shl5 | AN1: =AD1 -> rm_shl6 | AQ1: Plot | AR1: =A1 -> date | AS1: Surprise Policy (t) | AT1: Anticipated (t+1|t) | AU1: Anticipated (t+2|t) | AV1: Anticipated (t+3|t) | AW1: Anticipated (t+4|t) | AX1: Anticipated (t+5|t) | AY1: Anticipated (t+6|t) | AZ1: Combined | BA1: date | BB1: rm_sh | BC1: Fgsum
A2: 39172 | B2: 0.24173754 | C2: 0.024954963 | D2: -0.19052514 | E2: 2.0828963 | F2: -0.95242625 | G2: -0.72806334 | H2: -0.01118487 | I2: 0.14899175 | J2: -0.048530525 | K2: -0.49684021 | L2: 0.23835072 | M2: 0 | N2: 0 | O2: -0.31964138 | P2: 0 | Q2: -0.01474927 | R2: 0 | S2: 0 | T2: 0 | U2: 0 | V2: 0 | W2: 0 | X2: 0 | Y2: 0 | Z2: 0 | AA2: 0 | AB2: 0 | AC2: 0 | AD2: 0 | AE2: 0.79422749 | AF2: 0.76919782 | AH2: =K2 -> -0.49684021 | AI2: =Y2 -> 0 | AJ2: =Z2 -> 0 | AK2: =AA2 -> 0 | AL2: =AB2 -> 0 | AM2: =AC2 -> 0 | AN2: =AD2 -> 0 | AR2: =A2 -> 39172 | AS2: =AH2-AH$2 -> 0 | AT2: =AI2-AI$2 -> 0 | AU2: =AJ2-AJ$2 -> 0 | AV2: =AK2-AK$2 -> 0 | AW2: =AL2-AL$2 -> 0 | AX2: =AM2-AM$2 -> 0 | AY2: =AN2-AN$2 -> 0 | AZ2: =SUM(AS2:AY2) -> 0 | BA2: =AR2 -> 39172 | BB2: =AS2-$AS$2 -> 0 | BC2: =#REF!-#REF! -> #REF!
A3: 39263 | B3: 0.19457157 | C3: 0.047835113 | D3: -0.26469996 | E3: 2.5375078 | F3: -0.89887042 | G3: -0.77670133 | H3: -0.0066258697 | I3: 0.125834 | J3: -0.054030222 | K3: -0.65028981 | L3: 0.28508463 | M3: 0 | N3: 0 | O3: -0.30013635 | P3: 0 | Q3: -0.014980799 | R3: 0 | S3: 0 | T3: 0 | U3: 0 | V3: 0 | W3: 0 | X3: 0 | Y3: 0 | Z3: 0 | AA3: 0 | AB3: 0 | AC3: 0 | AD3: 0 | AE3: 0.78469946 | AF3: 1.0091978 | AH3: =K3 -> -0.65028981 | AI3: =Y3 -> 0 | AJ3: =Z3 -> 0 | AK3: =AA3 -> 0 | AL3: =AB3 -> 0 | AM3: =AC3 -> 0 | AN3: =AD3 -> 0 | AR3: =A3 -> 39263 | AS3: =AH3-AH$2 -> -0.1534496 | AT3: =AI3-AI$2 -> 0 | AU3: =AJ3-AJ$2 -> 0 | AV3: =AK3-AK$2 -> 0 | AW3: =AL3-AL$2 -> 0 | AX3: =AM3-AM$2 -> 0 | AY3: =AN3-AN$2 -> 0 | AZ3: =SUM(AS3:AY3) -> -0.1534496 | BA3: =AR3 -> 39263 | BB3: =AS3-$AS$2 -> -0.1534496 | BC3: =#REF! -> #REF!
A4: 39355 | B4: 0.18284602 | C4: 0.030295818 | D4: -0.39898662 | E4: 2.7340157 | F4: -0.84610169 | G4: -0.73780512 | H4: 0.00045142161 | I4: 0.11321804 | J4: -0.05882311 | K4: -0.52463597 | L4: 0.29379024 | M4: 0 | N4: 0 | O4: -0.21149963 | P4: 0 | Q4: -0.02286607 | R4: 0 | S4: 0 | T4: 0 | U4: 0 | V4: 0 | W4: 0 | X4: 0 | Y4: 0 | Z4: 0 | AA4: 0 | AB4: 0 | AC4: 0 | AD4: 0 | AE4: 0.77529881 | AF4: 1.3291978 | AH4: =K4 -> -0.52463597 | AI4: =Y4 -> 0 | AJ4: =Z4 -> 0 | AK4: =AA4 -> 0 | AL4: =AB4 -> 0 | AM4: =AC4 -> 0 | AN4: =AD4 -> 0 | AR4: =A4 -> 39355 | AS4: =AH4-AH$2 -> -0.027795757 | AT4: =AI4-AI$2 -> 0 | AU4: =AJ4-AJ$2 -> 0 | AV4: =AK4-AK$2 -> 0 | AW4: =AL4-AL$2 -> 0 | AX4: =AM4-AM$2 -> 0 | AY4: =AN4-AN$2 -> 0 | AZ4: =SUM(AS4:AY4) -> -0.027795757 | BA4: =AR4 -> 39355 | BB4: =AS4-$AS$2 -> -0.027795757 | BC4: =#REF! -> #REF!
