Workbook
Name BoxPlot: "BoxPlot"
Name Bubble: "Bubble"
Name Candlestick: "Candlestick"
Name Chart: "Chart"
Name ChartImage: "ChartImage"
Name ColumnRange: "ColumnRange"
Name Dumbbell: "Dumbbell"
Name Heatmap: "Heatmap"
Name Histogram: "Histogram"
Name Map: "Map"
Name OHLC: "OHLC"
Name PieChart: "PieChart"
Name Scatter: "Scatter"
Name Series: "Series"
Name Stripe: "Stripe"
Name Table: "Table"
Name TreeMap: "TreeMap"
Name Waterfall: "Waterfall"

Sheet All Chart

Sheet EA_output_policy
A1: date | B1: g_sh | C1: b_liqtil_sh | D1: b_liqp_sh | E1: b_safetil_sh | F1: b_safep_sh | G1: mu_sh | H1: z_sh | I1: lambda_f_sh | J1: lambda_w_sh | K1: rm_sh | L1: sigma_omega_sh | M1: mu_e_sh | N1: gamma_sh | O1: pi_star_sh | P1: lr_sh | Q1: zp_sh | R1: tfp_sh | S1: gdpdef_sh | T1: corepce_sh | U1: gdp_sh | V1: gdi_sh | W1: BBB_sh | X1: AAA_sh | Y1: rm_shl1 | Z1: rm_shl2 | AA1: rm_shl3 | AB1: rm_shl4 | AC1: rm_shl5 | AD1: rm_shl6 | AE1: dettrend | AF1: detrendedMean | AH1: rm_sh | AI1: =Y1 -> rm_shl1 | AJ1: =Z1 -> rm_shl2 | AK1: =AA1 -> rm_shl3 | AL1: =AB1 -> rm_shl4 | AM1: =AC1 -> rm_shl5 | AN1: =AD1 -> rm_shl6 | AQ1: Plot | AR1: =A1 -> date | AS1: =AF1 -> detrendedMean | AT1: Monetary Policy | AU1: Fgsum | AV1: FG1 | AW1: FG2 | AX1: FG3 | AY1: FG4 | AZ1: FG5 | BA1: FG6 | BC1: date | BD1: rm_sh | BE1: Fgsum
A2: 39172 | B2: 2.5363082 | C2: -0.18049422 | D2: -5.026568 | E2: -0.00051095038 | F2: 6.5669289 | G2: 14.167348 | H2: -0.028136165 | I2: 0.24489409 | J2: -0.05757504 | K2: 2.5748891 | L2: 0.26640205 | M2: 0 | N2: 0 | O2: 0.43018806 | P2: 0 | Q2: -0.017234495 | R2: 0 | S2: 0 | T2: 0 | U2: 0 | V2: 0 | W2: 0 | X2: 0 | Y2: 0 | Z2: 0 | AA2: 0 | AB2: 0 | AC2: 0 | AD2: 0 | AE2: 7.4683269 | AF2: 28.944766 | AH2: =K2+Y2-Y2/100 -> 2.5748891 | AI2: =Y2 -> 0 | AJ2: =Z2 -> 0 | AK2: =AA2 -> 0 | AL2: =AB2 -> 0 | AM2: =AC2 -> 0 | AN2: =AD2 -> 0 | AR2: =A2 -> 39172 | AS2: =AF2*4+2 -> 117.77907 | AT2: =AH2 -> 2.5748891 | AU2: =SUM(AV2:BA2) -> 0 | AV2: =AI2 -> 0 | AW2: =AJ2 -> 0 | AX2: =AK2 -> 0 | AY2: =AL2 -> 0 | AZ2: =AM2 -> 0 | BA2: =AN2 -> 0 | BC2: =AR2 -> 39172 | BD2: =AT2 -> 2.5748891 | BE2: =AU2 -> 0
A3: 39263 | B3: 2.1888377 | C3: -0.10201437 | D3: -5.4151599 | E3: 0.000432913 | F3: 7.4635098 | G3: 14.09681 | H3: -0.017718534 | I3: 0.23729294 | J3: -0.058482715 | K3: 2.6753132 | L3: 0.30577422 | M3: 0 | N3: 0 | O3: 0.44487798 | P3: 0 | Q3: -0.025392488 | R3: 0 | S3: 0 | T3: 0 | U3: 0 | V3: 0 | W3: 0 | X3: 0 | Y3: 0 | Z3: 0 | AA3: 0 | AB3: 0 | AC3: 0 | AD3: 0 | AE3: 7.445194 | AF3: 29.239275 | AH3: =K3+Y3-Y3/100 -> 2.6753132 | AI3: =Y3 -> 0 | AJ3: =Z3 -> 0 | AK3: =AA3 -> 0 | AL3: =AB3 -> 0 | AM3: =AC3 -> 0 | AN3: =AD3 -> 0 | AR3: =A3 -> 39263 | AS3: =AF3*4+2 -> 118.9571 | AT3: =AH3 -> 2.6753132 | AU3: =SUM(AV3:BA3) -> 0 | AV3: =AI3 -> 0 | AW3: =AJ3 -> 0 | AX3: =AK3 -> 0 | AY3: =AL3 -> 0 | AZ3: =AM3 -> 0 | BA3: =AN3 -> 0 | BC3: =AR3 -> 39263 | BD3: =AT3 -> 2.6753132 | BE3: =AU3 -> 0
A4: 39355 | B4: 2.3018784 | C4: -0.18582521 | D4: -5.7797078 | E4: -0.00024449342 | F4: 8.1065585 | G4: 14.1473 | H4: 0.0099248504 | I4: 0.31153154 | J4: -0.061960515 | K4: 2.506994 | L4: 0.30064004 | M4: 0 | N4: 0 | O4: 0.46631618 | P4: 0 | Q4: -0.040553603 | R4: 0 | S4: 0 | T4: 0 | U4: 0 | V4: 0 | W4: 0 | X4: 0 | Y4: 0 | Z4: 0 | AA4: 0 | AB4: 0 | AC4: 0 | AD4: 0 | AE4: 7.4221487 | AF4: 29.505 | AH4: =K4+Y4-Y4/100 -> 2.506994 | AI4: =Y4 -> 0 | AJ4: =Z4 -> 0 | AK4: =AA4 -> 0 | AL4: =AB4 -> 0 | AM4: =AC4 -> 0 | AN4: =AD4 -> 0 | AR4: =A4 -> 39355 | AS4: =AF4*4+2 -> 120.02 | AT4: =AH4 -> 2.506994 | AU4: =SUM(AV4:BA4) -> 0 | AV4: =AI4 -> 0 | AW4: =AJ4 -> 0 | AX4: =AK4 -> 0 | AY4: =AL4 -> 0 | AZ4: =AM4 -> 0 | BA4: =AN4 -> 0 | BC4: =AR4 -> 39355 | BD4: =AT4 -> 2.506994 | BE4: =AU4 -> 0
A5: 39447 | B5: 2.0031345 | C5: -0.059805901 | D5: -6.0906698 | E5: 0.00065881996 | F5: 8.5748649 | G5: 14.245587 | H5: 0.01546791 | I5: 0.248964 | J5: -0.063329388 | K5: 2.6392114 | L5: 0.34661216 | M5: 0 | N5: 0 | O5: 0.47709801 | P5: 0 | Q5: -0.045182361 | R5: 0 | S5: 0 | T5: 0 | U5: 0 | V5: 0 | W5: 0 | X5: 0 | Y5: 0 | Z5: 0 | AA5: 0 | AB5: 0 | AC5: 0 | AD5: 0 | AE5: 7.3991902 | AF5: 29.691802 | AH5: =K5+Y5-Y5/100 -> 2.6392114 | AI5: =Y5 -> 0 | AJ5: =Z5 -> 0 | AK5: =AA5 -> 0 | AL5: =AB5 -> 0 | AM5: =AC5 -> 0 | AN5: =AD5 -> 0 | AR5: =A5 -> 39447 | AS5: =AF5*4+2 -> 120.76721 | AT5: =AH5 -> 2.6392114 | AU5: =SUM(AV5:BA5) -> 0 | AV5: =AI5 -> 0 | AW5: =AJ5 -> 0 | AX5: =AK5 -> 0 | AY5: =AL5 -> 0 | AZ5: =AM5 -> 0 | BA5: =AN5 -> 0 | BC5: =AR5 -> 39447 | BD5: =AT5 -> 2.6392114 | BE5: =AU5 -> 0
A6: 39538 | B6: 2.0564368 | C6: -0.17410702 | D6: -6.2409237 | E6: -8.1488331e-05 | F6: 8.7254233 | G6: 14.470225 | H6: -0.053129904 | I6: 0.30778976 | J6: -0.066874845 | K6: 2.9688718 | L6: 0.14427824 | M6: 0 | N6: 0 | O6: 0.49713924 | P6: 0 | Q6: -0.050515251 | R6: 0 | S6: 0 | T6: 0 | U6: 0 | V6: 0 | W6: 0 | X6: 0 | Y6: 0 | Z6: 0 | AA6: 0 | AB6: 0 | AC6: 0 | AD6: 0 | AE6: 7.376318 | AF6: 29.96085 | AH6: =K6+Y6-Y6/100 -> 2.9688718 | AI6: =Y6 -> 0 | AJ6: =Z6 -> 0 | AK6: =AA6 -> 0 | AL6: =AB6 -> 0 | AM6: =AC6 -> 0 | AN6: =AD6 -> 0 | AR6: =A6 -> 39538 | AS6: =AF6*4+2 -> 121.8434 | AT6: =AH6 -> 2.9688718 | AU6: =SUM(AV6:BA6) -> 0 | AV6: =AI6 -> 0 | AW6: =AJ6 -> 0 | AX6: =AK6 -> 0 | AY6: =AL6 -> 0 | AZ6: =AM6 -> 0 | BA6: =AN6 -> 0 | BC6: =AR6 -> 39538 | BD6: =AT6 -> 2.9688718 | BE6: =AU6 -> 0
A7: 39629 | B7: 1.9437086 | C7: -0.25968328 | D7: -6.4409474 | E7: 0.00050280931 | F7: 9.1352305 | G7: 14.602996 | H7: -0.0028221986 | I7: 0.2461009 | J7: -0.063600816 | K7: 2.6992023 | L7: 0.031560885 | M7: 0 | N7: 0 | O7: 0.50964208 | P7: 0 | Q7: -0.07357073 | R7: 0 | S7: 0 | T7: 0 | U7: 0 | V7: 0 | W7: 0 | X7: 0 | Y7: 0 | Z7: 0 | AA7: 0 | AB7: 0 | AC7: 0 | AD7: 0 | AE7: 7.3535315 | AF7: 29.681851 | AH7: =K7+Y7-Y7/100 -> 2.6992023 | AI7: =Y7 -> 0 | AJ7: =Z7 -> 0 | AK7: =AA7 -> 0 | AL7: =AB7 -> 0 | AM7: =AC7 -> 0 | AN7: =AD7 -> 0 | AR7: =A7 -> 39629 | AS7: =AF7*4+2 -> 120.7274 | AT7: =AH7 -> 2.6992023 | AU7: =SUM(AV7:BA7) -> 0 | AV7: =AI7 -> 0 | AW7: =AJ7 -> 0 | AX7: =AK7 -> 0 | AY7: =AL7 -> 0 | AZ7: =AM7 -> 0 | BA7: =AN7 -> 0 | BC7: =AR7 -> 39629 | BD7: =AT7 -> 2.6992023 | BE7: =AU7 -> 0
A8: 39721 | B8: 1.5553725 | C8: -0.47264141 | D8: -6.5811779 | E8: 0.00045985532 | F8: 9.4802157 | G8: 14.927721 | H8: 0.027059605 | I8: 0.29587019 | J8: -0.068185466 | K8: 2.5210749 | L8: -0.16240357 | M8: 0 | N8: 0 | O8: 0.53344519 | P8: 0 | Q8: -0.081467541 | R8: 0 | S8: 0 | T8: 0 | U8: 0 | V8: 0 | W8: 0 | X8: 0 | Y8: 0 | Z8: 0 | AA8: 0 | AB8: 0 | AC8: 0 | AD8: 0 | AE8: 7.3308301 | AF8: 29.306173 | AH8: =K8+Y8-Y8/100 -> 2.5210749 | AI8: =Y8 -> 0 | AJ8: =Z8 -> 0 | AK8: =AA8 -> 0 | AL8: =AB8 -> 0 | AM8: =AC8 -> 0 | AN8: =AD8 -> 0 | AR8: =A8 -> 39721 | AS8: =AF8*4+2 -> 119.22469 | AT8: =AH8 -> 2.5210749 | AU8: =SUM(AV8:BA8) -> 0 | AV8: =AI8 -> 0 | AW8: =AJ8 -> 0 | AX8: =AK8 -> 0 | AY8: =AL8 -> 0 | AZ8: =AM8 -> 0 | BA8: =AN8 -> 0 | BC8: =AR8 -> 39721 | BD8: =AT8 -> 2.5210749 | BE8: =AU8 -> 0
A9: 39813 | B9: 2.2206634 | C9: -0.98689403 | D9: -6.9466266 | E9: -0.0002896115 | F9: 8.9449095 | G9: 15.944444 | H9: 0.11808668 | I9: 0.33695797 | J9: -0.065994594 | K9: 2.2587813 | L9: -0.68091049 | M9: 0 | N9: 0 | O9: 0.55671627 | P9: 0 | Q9: -0.073561543 | R9: 0 | S9: 0 | T9: 0 | U9: 0 | V9: 0 | W9: 0 | X9: 0 | Y9: 0.073690921 | Z9: -0.13359577 | AA9: 0.092384556 | AB9: -0.0071129062 | AC9: -0.014969052 | AD9: -0.028973438 | AE9: 7.3082133 | AF9: 28.91592 | AH9: =K9+Y9-Y9/100 -> 2.3317353 | AI9: =Y9/1010 -> 7.2961308e-05 | AJ9: =Z9 -> -0.13359577 | AK9: =AA9 -> 0.092384556 | AL9: =AB9 -> -0.0071129062 | AM9: =AC9 -> -0.014969052 | AN9: =AD9 -> -0.028973438 | AR9: =A9 -> 39813 | AS9: =AF9*4+2 -> 117.66368 | AT9: =AH9 -> 2.3317353 | AU9: =SUM(AV9:BA9) -> -0.092193645 | AV9: =AI9 -> 7.2961308e-05 | AW9: =AJ9 -> -0.13359577 | AX9: =AK9 -> 0.092384556 | AY9: =AL9 -> -0.0071129062 | AZ9: =AM9 -> -0.014969052 | BA9: =AN9 -> -0.028973438 | BC9: =AR9 -> 39813 | BD9: =AT9 -> 2.3317353 | BE9: =AU9 -> -0.092193645
A10: 39903 | B10: 2.4024061 | C10: -1.2606797 | D10: -6.8199197 | E10: -0.0001738059 | F10: 8.6027343 | G10: 16.652521 | H10: 0.06749249 | I10: 0.27634318 | J10: -0.060941639 | K10: 2.7785999 | L10: -1.1798196 | M10: 0 | N10: 0 | O10: 0.57206768 | P10: 0 | Q10: -0.025279014 | R10: 0 | S10: 0 | T10: 0 | U10: 0 | V10: 0 | W10: 0 | X10: 0 | Y10: -1.7973575 | Z10: 0.013721478 | AA10: 0.12529789 | AB10: -0.030395868 | AC10: -0.051108838 | AD10: -0.13660702 | AE10: 7.2856806 | AF10: 27.414582 | AH10: =K10+Y10-Y10/100 -> 0.99921591 | AI10: =Y10/1010 -> -0.0017795619 | AJ10: =Z10 -> 0.013721478 | AK10: =AA10 -> 0.12529789 | AL10: =AB10 -> -0.030395868 | AM10: =AC10 -> -0.051108838 | AN10: =AD10 -> -0.13660702 | AR10: =A10 -> 39903 | AS10: =AF10*4+2 -> 111.65833 | AT10: =AH10 -> 0.99921591 | AU10: =SUM(AV10:BA10) -> -0.080871912 | AV10: =AI10 -> -0.0017795619 | AW10: =AJ10 -> 0.013721478 | AX10: =AK10 -> 0.12529789 | AY10: =AL10 -> -0.030395868 | AZ10: =AM10 -> -0.051108838 | BA10: =AN10 -> -0.13660702 | BC10: =AR10 -> 39903 | BD10: =AT10 -> 0.99921591 | BE10: =AU10 -> -0.080871912
A11: 39994 | B11: 2.4277616 | C11: -1.6490085 | D11: -6.3861468 | E11: -0.00049595052 | F11: 7.9593532 | G11: 17.059181 | H11: -0.089907165 | I11: 0.25785819 | J11: -0.059151639 | K11: 5.406976 | L11: -1.4181606 | M11: 0 | N11: 0 | O11: 0.58667403 | P11: 0 | Q11: 0.016546462 | R11: 0 | S11: 0 | T11: 0 | U11: 0 | V11: 0 | W11: 0 | X11: 0 | Y11: -4.5109297 | Z11: 0.25520858 | AA11: 0.13462049 | AB11: -0.078483828 | AC11: -0.067382708 | AD11: -0.30713781 | AE11: 7.2632314 | AF11: 26.800606 | AH11: =K11+Y11-Y11/100 -> 0.94115568 | AI11: =Y11/1010 -> -0.004466267 | AJ11: =Z11 -> 0.25520858 | AK11: =AA11 -> 0.13462049 | AL11: =AB11 -> -0.078483828 | AM11: =AC11 -> -0.067382708 | AN11: =AD11 -> -0.30713781 | AR11: =A11 -> 39994 | AS11: =AF11*4+2 -> 109.20242 | AT11: =AH11 -> 0.94115568 | AU11: =SUM(AV11:BA11) -> -0.067641554 | AV11: =AI11 -> -0.004466267 | AW11: =AJ11 -> 0.25520858 | AX11: =AK11 -> 0.13462049 | AY11: =AL11 -> -0.078483828 | AZ11: =AM11 -> -0.067382708 | BA11: =AN11 -> -0.30713781 | BC11: =AR11 -> 39994 | BD11: =AT11 -> 0.94115568 | BE11: =AU11 -> -0.067641554
A12: 40086 | B12: 2.4217085 | C12: -2.0203722 | D12: -5.5802494 | E12: -0.0013006478 | F12: 7.1417549 | G12: 17.135333 | H12: -0.0426744 | I12: 0.322457 | J12: -0.056528372 | K12: 7.9652821 | L12: -1.4766757 | M12: 0 | N12: 0 | O12: 0.60460848 | P12: 0 | Q12: 0.00073509913 | R12: 0 | S12: 0 | T12: 0 | U12: 0 | V12: 0 | W12: 0 | X12: 0 | Y12: -6.6481835 | Z12: 0.43002849 | AA12: 0.11092325 | AB12: -0.16598199 | AC12: -0.11796388 | AD12: -0.56485065 | AE12: 7.2408652 | AF12: 26.698915 | AH12: =K12+Y12-Y12/100 -> 1.3835804 | AI12: =Y12/1010 -> -0.0065823599 | AJ12: =Z12 -> 0.43002849 | AK12: =AA12 -> 0.11092325 | AL12: =AB12 -> -0.16598199 | AM12: =AC12 -> -0.11796388 | AN12: =AD12 -> -0.56485065 | AR12: =A12 -> 40086 | AS12: =AF12*4+2 -> 108.79566 | AT12: =AH12 -> 1.3835804 | AU12: =SUM(AV12:BA12) -> -0.31442715 | AV12: =AI12 -> -0.0065823599 | AW12: =AJ12 -> 0.43002849 | AX12: =AK12 -> 0.11092325 | AY12: =AL12 -> -0.16598199 | AZ12: =AM12 -> -0.11796388 | BA12: =AN12 -> -0.56485065 | BC12: =AR12 -> 40086 | BD12: =AT12 -> 1.3835804 | BE12: =AU12 -> -0.31442715
A13: 40178 | B13: 2.0701525 | C13: -1.9632677 | D13: -4.963927 | E13: -0.00080920876 | F13: 6.7932403 | G13: 17.165547 | H13: 0.018838774 | I13: 0.252927 | J13: -0.046777776 | K13: 9.6680861 | L13: -1.4944411 | M13: 0 | N13: 0 | O13: 0.61475522 | P13: 0 | Q13: -0.017101425 | R13: 0 | S13: 0 | T13: 0 | U13: 0 | V13: 0 | W13: 0 | X13: 0 | Y13: -8.2298802 | Z13: 0.64538339 | AA13: 0.075587373 | AB13: -0.24389615 | AC13: -0.13783327 | AD13: -0.86962231 | AE13: 7.2185815 | AF13: 26.555543 | AH13: =K13+Y13-Y13/100 -> 1.5205047 | AI13: =Y13/1010 -> -0.0081483962 | AJ13: =Z13 -> 0.64538339 | AK13: =AA13 -> 0.075587373 | AL13: =AB13 -> -0.24389615 | AM13: =AC13 -> -0.13783327 | AN13: =AD13 -> -0.86962231 | AR13: =A13 -> 40178 | AS13: =AF13*4+2 -> 108.22217 | AT13: =AH13 -> 1.5205047 | AU13: =SUM(AV13:BA13) -> -0.53852936 | AV13: =AI13 -> -0.0081483962 | AW13: =AJ13 -> 0.64538339 | AX13: =AK13 -> 0.075587373 | AY13: =AL13 -> -0.24389615 | AZ13: =AM13 -> -0.13783327 | BA13: =AN13 -> -0.86962231 | BC13: =AR13 -> 40178 | BD13: =AT13 -> 1.5205047 | BE13: =AU13 -> -0.53852936
A14: 40268 | B14: 1.9292619 | C14: -1.9152574 | D14: -4.6209409 | E14: -9.3285765e-05 | F14: 6.2885873 | G14: 17.194811 | H14: -0.0097242431 | I14: 0.24468576 | J14: -0.033630541 | K14: 11.391705 | L14: -1.5295778 | M14: 0 | N14: 0 | O14: 0.62748077 | P14: 0 | Q14: -0.021055782 | R14: 0 | S14: 0 | T14: 0 | U14: 0 | V14: 0 | W14: 0 | X14: 0 | Y14: -9.2842199 | Z14: 0.93375033 | AA14: 0.13528553 | AB14: -0.26251041 | AC14: -0.11896933 | AD14: -1.185558 | AE14: 7.1963798 | AF14: 26.96041 | AH14: =K14+Y14-Y14/100 -> 2.2003272 | AI14: =Y14/1010 -> -0.0091922969 | AJ14: =Z14 -> 0.93375033 | AK14: =AA14 -> 0.13528553 | AL14: =AB14 -> -0.26251041 | AM14: =AC14 -> -0.11896933 | AN14: =AD14 -> -1.185558 | AR14: =A14 -> 40268 | AS14: =AF14*4+2 -> 109.84164 | AT14: =AH14 -> 2.2003272 | AU14: =SUM(AV14:BA14) -> -0.50719413 | AV14: =AI14 -> -0.0091922969 | AW14: =AJ14 -> 0.93375033 | AX14: =AK14 -> 0.13528553 | AY14: =AL14 -> -0.26251041 | AZ14: =AM14 -> -0.11896933 | BA14: =AN14 -> -1.185558 | BC14: =AR14 -> 40268 | BD14: =AT14 -> 2.2003272 | BE14: =AU14 -> -0.50719413
A15: 40359 | B15: 1.7114594 | C15: -1.7910189 | D15: -4.417112 | E15: -0.00034034385 | F15: 5.508496 | G15: 17.284895 | H15: 0.036125033 | I15: 0.25452995 | J15: -0.025443457 | K15: 12.624267 | L15: -1.4630845 | M15: 0 | N15: 0 | O15: 0.64041987 | P15: 0 | Q15: -0.024373029 | R15: 0 | S15: 0 | T15: 0 | U15: 0 | V15: 0 | W15: 0 | X15: 0 | Y15: -10.235004 | Z15: 1.2587611 | AA15: 0.30474392 | AB15: -0.17869597 | AC15: -0.03951587 | AD15: -1.4723622 | AE15: 7.1742596 | AF15: 27.151007 | AH15: =K15+Y15-Y15/100 -> 2.4916135 | AI15: =Y15/1010 -> -0.010133667 | AJ15: =Z15 -> 1.2587611 | AK15: =AA15 -> 0.30474392 | AL15: =AB15 -> -0.17869597 | AM15: =AC15 -> -0.03951587 | AN15: =AD15 -> -1.4723622 | AR15: =A15 -> 40359 | AS15: =AF15*4+2 -> 110.60403 | AT15: =AH15 -> 2.4916135 | AU15: =SUM(AV15:BA15) -> -0.13720259 | AV15: =AI15 -> -0.010133667 | AW15: =AJ15 -> 1.2587611 | AX15: =AK15 -> 0.30474392 | AY15: =AL15 -> -0.17869597 | AZ15: =AM15 -> -0.03951587 | BA15: =AN15 -> -1.4723622 | BC15: =AR15 -> 40359 | BD15: =AT15 -> 2.4916135 | BE15: =AU15 -> -0.13720259
A16: 40451 | B16: 1.6689236 | C16: -1.669287 | D16: -4.2631128 | E16: -0.00047472158 | F16: 5.3252985 | G16: 17.33458 | H16: 0.0056531455 | I16: 0.3395956 | J16: -0.01579766 | K16: 13.592728 | L16: -1.5563826 | M16: 0 | N16: 0 | O16: 0.65967139 | P16: 0 | Q16: -0.017203497 | R16: 0 | S16: 0 | T16: 0 | U16: 0 | V16: 0 | W16: 0 | X16: 0 | Y16: -11.450592 | Z16: 1.4891879 | AA16: 0.38887175 | AB16: -0.13286861 | AC16: 0.019233067 | AD16: -1.7498602 | AE16: 7.1522205 | AF16: 27.120385 | AH16: =K16+Y16-Y16/100 -> 2.2566424 | AI16: =Y16/1010 -> -0.011337219 | AJ16: =Z16 -> 1.4891879 | AK16: =AA16 -> 0.38887175 | AL16: =AB16 -> -0.13286861 | AM16: =AC16 -> 0.019233067 | AN16: =AD16 -> -1.7498602 | AR16: =A16 -> 40451 | AS16: =AF16*4+2 -> 110.48154 | AT16: =AH16 -> 2.2566424 | AU16: =SUM(AV16:BA16) -> 0.0032267014 | AV16: =AI16 -> -0.011337219 | AW16: =AJ16 -> 1.4891879 | AX16: =AK16 -> 0.38887175 | AY16: =AL16 -> -0.13286861 | AZ16: =AM16 -> 0.019233067 | BA16: =AN16 -> -1.7498602 | BC16: =AR16 -> 40451 | BD16: =AT16 -> 2.2566424 | BE16: =AU16 -> 0.0032267014
A17: 40543 | B17: 1.3754459 | C17: -1.4731984 | D17: -4.3372803 | E17: -0.00016910156 | F17: 6.0283243 | G17: 17.375538 | H17: -0.03695678 | I17: 0.26961923 | J17: -0.0084062676 | K17: 14.927038 | L17: -1.5514464 | M17: 0 | N17: 0 | O17: 0.6729625 | P17: 0 | Q17: -0.010960892 | R17: 0 | S17: 0 | T17: 0 | U17: 0 | V17: 0 | W17: 0 | X17: 0 | Y17: -13.193123 | Z17: 1.6728789 | AA17: 0.4341946 | AB17: -0.11512471 | AC17: 0.031882889 | AD17: -2.0389967 | AE17: 7.1302619 | AF17: 27.152484 | AH17: =K17+Y17-Y17/100 -> 1.8658466 | AI17: =Y17/1010 -> -0.013062498 | AJ17: =Z17 -> 1.6728789 | AK17: =AA17 -> 0.4341946 | AL17: =AB17 -> -0.11512471 | AM17: =AC17 -> 0.031882889 | AN17: =AD17 -> -2.0389967 | AR17: =A17 -> 40543 | AS17: =AF17*4+2 -> 110.60994 | AT17: =AH17 -> 1.8658466 | AU17: =SUM(AV17:BA17) -> -0.028227444 | AV17: =AI17 -> -0.013062498 | AW17: =AJ17 -> 1.6728789 | AX17: =AK17 -> 0.4341946 | AY17: =AL17 -> -0.11512471 | AZ17: =AM17 -> 0.031882889 | BA17: =AN17 -> -2.0389967 | BC17: =AR17 -> 40543 | BD17: =AT17 -> 1.8658466 | BE17: =AU17 -> -0.028227444
A18: 40633 | B18: 1.9043017 | C18: -1.5433038 | D18: -4.5069513 | E18: -0.0012869151 | F18: 7.4268885 | G18: 17.45478 | H18: -0.036961388 | I18: 0.30813711 | J18: -0.0078414583 | K18: 16.675365 | L18: -1.4894906 | M18: 0 | N18: 0 | O18: 0.69313123 | P18: 0 | Q18: -0.023400021 | R18: 0 | S18: 0 | T18: 0 | U18: 0 | V18: 0 | W18: 0 | X18: 0 | Y18: -15.514005 | Z18: 1.6560904 | AA18: 0.29727136 | AB18: -0.20292069 | AC18: -0.027254571 | AD18: -2.3847288 | AE18: 7.1083835 | AF18: 27.786204 | AH18: =K18+Y18-Y18/100 -> 1.3164998 | AI18: =Y18/1010 -> -0.015360401 | AJ18: =Z18 -> 1.6560904 | AK18: =AA18 -> 0.29727136 | AL18: =AB18 -> -0.20292069 | AM18: =AC18 -> -0.027254571 | AN18: =AD18 -> -2.3847288 | AR18: =A18 -> 40633 | AS18: =AF18*4+2 -> 113.14482 | AT18: =AH18 -> 1.3164998 | AU18: =SUM(AV18:BA18) -> -0.67690276 | AV18: =AI18 -> -0.015360401 | AW18: =AJ18 -> 1.6560904 | AX18: =AK18 -> 0.29727136 | AY18: =AL18 -> -0.20292069 | AZ18: =AM18 -> -0.027254571 | BA18: =AN18 -> -2.3847288 | BC18: =AR18 -> 40633 | BD18: =AT18 -> 1.3164998 | BE18: =AU18 -> -0.67690276
A19: 40724 | B19: 1.467808 | C19: -1.2043497 | D19: -4.3924235 | E19: -0.0010583469 | F19: 8.406255 | G19: 17.546427 | H19: 0.07324742 | I19: 0.30268883 | J19: -0.0051230818 | K19: 18.729266 | L19: -1.555679 | M19: 0 | N19: 0 | O19: 0.71288761 | P19: 0 | Q19: -0.035226888 | R19: 0 | S19: 0 | T19: 0 | U19: 0 | V19: 0 | W19: 0 | X19: 0 | Y19: -18.615704 | Z19: 1.7520007 | AA19: 0.18453734 | AB19: -0.23254533 | AC19: -0.029947737 | AD19: -2.709168 | AE19: 7.0865847 | AF19: 27.480477 | AH19: =K19+Y19-Y19/100 -> 0.29971978 | AI19: =Y19/1010 -> -0.01843139 | AJ19: =Z19 -> 1.7520007 | AK19: =AA19 -> 0.18453734 | AL19: =AB19 -> -0.23254533 | AM19: =AC19 -> -0.029947737 | AN19: =AD19 -> -2.709168 | AR19: =A19 -> 40724 | AS19: =AF19*4+2 -> 111.92191 | AT19: =AH19 -> 0.29971978 | AU19: =SUM(AV19:BA19) -> -1.0535544 | AV19: =AI19 -> -0.01843139 | AW19: =AJ19 -> 1.7520007 | AX19: =AK19 -> 0.18453734 | AY19: =AL19 -> -0.23254533 | AZ19: =AM19 -> -0.029947737 | BA19: =AN19 -> -2.709168 | BC19: =AR19 -> 40724 | BD19: =AT19 -> 0.29971978 | BE19: =AU19 -> -1.0535544
A20: 40816 | B20: 1.8241286 | C20: -1.0959542 | D20: -4.2580249 | E20: -0.00028471595 | F20: 6.5846466 | G20: 17.671886 | H20: -0.047348455 | I20: 0.34776192 | J20: 0.0012598254 | K20: 21.668795 | L20: -1.6269307 | M20: 0 | N20: 0 | O20: 0.72603408 | P20: 0 | Q20: -0.021518547 | R20: 0 | S20: 0 | T20: 0 | U20: 0 | V20: 0 | W20: 0 | X20: 0 | Y20: -21.294037 | Z20: 2.3087563 | AA20: 0.35473861 | AB20: -0.080751504 | AC20: 0.099261868 | AD20: -2.8984711 | AE20: 7.0648651 | AF20: 27.328812 | AH20: =K20+Y20-Y20/100 -> 0.58769775 | AI20: =Y20/1010 -> -0.021083205 | AJ20: =Z20 -> 2.3087563 | AK20: =AA20 -> 0.35473861 | AL20: =AB20 -> -0.080751504 | AM20: =AC20 -> 0.099261868 | AN20: =AD20 -> -2.8984711 | AR20: =A20 -> 40816 | AS20: =AF20*4+2 -> 111.31525 | AT20: =AH20 -> 0.58769775 | AU20: =SUM(AV20:BA20) -> -0.23754899 | AV20: =AI20 -> -0.021083205 | AW20: =AJ20 -> 2.3087563 | AX20: =AK20 -> 0.35473861 | AY20: =AL20 -> -0.080751504 | AZ20: =AM20 -> 0.099261868 | BA20: =AN20 -> -2.8984711 | BC20: =AR20 -> 40816 | BD20: =AT20 -> 0.58769775 | BE20: =AU20 -> -0.23754899
... A132: 51043 | B132: -0.043141873 | C132: -0.00014191675 | D132: -0.060150045 | E132: 0.00016375639 | F132: 0.077003819 | G132: -0.017761409 | H132: 0.10657899 | I132: -0.12938709 | J132: -0.23383062 | K132: -0.0013647494 | L132: 0.028622522 | M132: 0 | N132: 0 | O132: 0.44750605 | P132: 0 | Q132: 0.30446726 | R132: 0 | S132: 0 | T132: 0 | U132: 0 | V132: 0 | W132: 0 | X132: 0 | Y132: 0.0014171204 | Z132: -0.0014470184 | AA132: 0.00054189822 | AB132: -0.00029329794 | AC132: 0.0013717805 | AD132: 0.0037302372 | AE132: -0.072867892 | AF132: 0.418171 | AH132: =K132+Y132-Y132/100 -> 3.8199787e-05 | AI132: =Y132/1010 -> 1.4030895e-06 | AJ132: =Z132 -> -0.0014470184 | AK132: =AA132 -> 0.00054189822 | AL132: =AB132 -> -0.00029329794 | AM132: =AC132 -> 0.0013717805 | AN132: =AD132 -> 0.0037302372 | AR132: =A132 -> 51043 | AS132: =AF132*4+2 -> 3.672684 | AT132: =AH132 -> 3.8199787e-05 | AU132: =SUM(AV132:BA132) -> 0.0039050027 | AV132: =AI132 -> 1.4030895e-06 | AW132: =AJ132 -> -0.0014470184 | AX132: =AK132 -> 0.00054189822 | AY132: =AL132 -> -0.00029329794 | AZ132: =AM132 -> 0.0013717805 | BA132: =AN132 -> 0.0037302372 | BC132: =AR132 -> 51043 | BD132: =AT132 -> 3.8199787e-05 | BE132: =AU132 -> 0.0039050027

Sheet EA_core_obs_with_text
A1: date | B1: g_sh | C1: b_liqtil_sh | D1: b_liqp_sh | E1: b_safetil_sh | F1: b_safep_sh | G1: mu_sh | H1: z_sh | I1: lambda_f_sh | J1: lambda_w_sh | K1: rm_sh | L1: sigma_omega_sh | M1: mu_e_sh | N1: gamma_sh | O1: pi_star_sh | P1: lr_sh | Q1: zp_sh | R1: tfp_sh | S1: gdpdef_sh | T1: corepce_sh | U1: gdp_sh | V1: gdi_sh | W1: BBB_sh | X1: AAA_sh | Y1: rm_shl1 | Z1: rm_shl2 | AA1: rm_shl3 | AB1: rm_shl4 | AC1: rm_shl5 | AD1: rm_shl6 | AE1: dettrend | AF1: detrendedMean | AH1: rm_sh | AI1: =Y1 -> rm_shl1 | AJ1: =Z1 -> rm_shl2 | AK1: =AA1 -> rm_shl3 | AL1: =AB1 -> rm_shl4 | AM1: =AC1 -> rm_shl5 | AN1: =AD1 -> rm_shl6 | AQ1: Plot | AR1: =A1 -> date | AS1: =AF1 -> detrendedMean | AT1: Monetary Policy | AU1: Fgsum | AV1: FG1 | AW1: FG2 | AX1: FG3 | AY1: FG4 | AZ1: FG5 | BA1: FG6 | BC1: date | BD1: rm_sh | BE1: Fgsum
A2: 39172 | B2: -0.0019508847 | C2: -0.00044949594 | D2: -0.13911193 | E2: 2.6700597e-07 | F2: 0.18028947 | G2: -0.0092832979 | H2: -9.5227129e-06 | I2: -0.33420427 | J2: -0.060491883 | K2: 0.024806955 | L2: -0.00020267534 | M2: 0 | N2: 0 | O2: 0.019158519 | P2: 0 | Q2: 7.7258442e-05 | R2: 0 | S2: 0 | T2: 0.50261524 | U2: 0 | V2: 0 | W2: 0 | X2: 0 | Y2: 0 | Z2: 0 | AA2: 0 | AB2: 0 | AC2: 0 | AD2: 0 | AE2: 0.036435471 | AF2: 0.22016319 | AH2: =K2+Y2-Y2/100 -> 0.024806955 | AI2: =Y2 -> 0 | AJ2: =Z2 -> 0 | AK2: =AA2 -> 0 | AL2: =AB2 -> 0 | AM2: =AC2 -> 0 | AN2: =AD2 -> 0 | AR2: =A2 -> 39172 | AS2: =AF2*4+2 -> 2.8806528 | AT2: =AH2 -> 0.024806955 | AU2: =SUM(AV2:BA2) -> 0 | AV2: =AI2 -> 0 | AW2: =AJ2 -> 0 | AX2: =AK2 -> 0 | AY2: =AL2 -> 0 | AZ2: =AM2 -> 0 | BA2: =AN2 -> 0 | BC2: =AR2 -> 39172 | BD2: =AT2 -> 0.024806955 | BE2: =AU2 -> 0
A3: 39263 | B3: -0.001910232 | C3: -0.00033353949 | D3: -0.14952585 | E3: 1.8081252e-07 | F3: 0.20476775 | G3: -0.0092487068 | H3: -1.5875485e-05 | I3: -0.40434241 | J3: -0.065233156 | K3: 0.025255502 | L3: -0.00021052273 | M3: 0 | N3: 0 | O3: 0.020245405 | P3: 0 | Q3: 9.7038271e-05 | R3: 0 | S3: 0 | T3: 0.41534977 | U3: 0 | V3: 0 | W3: 0 | X3: 0 | Y3: 0 | Z3: 0 | AA3: 0 | AB3: 0 | AC3: 0 | AD3: 0 | AE3: 0.035954254 | AF3: 0.070229362 | AH3: =K3+Y3-Y3/100 -> 0.025255502 | AI3: =Y3 -> 0 | AJ3: =Z3 -> 0 | AK3: =AA3 -> 0 | AL3: =AB3 -> 0 | AM3: =AC3 -> 0 | AN3: =AD3 -> 0 | AR3: =A3 -> 39263 | AS3: =AF3*4+2 -> 2.2809174 | AT3: =AH3 -> 0.025255502 | AU3: =SUM(AV3:BA3) -> 0 | AV3: =AI3 -> 0 | AW3: =AJ3 -> 0 | AX3: =AK3 -> 0 | AY3: =AL3 -> 0 | AZ3: =AM3 -> 0 | BA3: =AN3 -> 0 | BC3: =AR3 -> 39263 | BD3: =AT3 -> 0.025255502 | BE3: =AU3 -> 0
A4: 39355 | B4: -0.0019527526 | C4: -0.00042054317 | D4: -0.15990279 | E4: 2.0866553e-07 | F4: 0.22376056 | G4: -0.009266434 | H4: -6.2988432e-06 | I4: -0.009955934 | J4: -0.0645373 | K4: 0.023798391 | L4: -0.00017549804 | M4: 0 | N4: 0 | O4: 0.022058994 | P4: 0 | Q4: 0.00013361978 | R4: 0 | S4: 0 | T4: -0.31246178 | U4: 0 | V4: 0 | W4: 0 | X4: 0 | Y4: 0 | Z4: 0 | AA4: 0 | AB4: 0 | AC4: 0 | AD4: 0 | AE4: 0.035480661 | AF4: -0.25915581 | AH4: =K4+Y4-Y4/100 -> 0.023798391 | AI4: =Y4 -> 0 | AJ4: =Z4 -> 0 | AK4: =AA4 -> 0 | AL4: =AB4 -> 0 | AM4: =AC4 -> 0 | AN4: =AD4 -> 0 | AR4: =A4 -> 39355 | AS4: =AF4*4+2 -> 0.96337677 | AT4: =AH4 -> 0.023798391 | AU4: =SUM(AV4:BA4) -> 0 | AV4: =AI4 -> 0 | AW4: =AJ4 -> 0 | AX4: =AK4 -> 0 | AY4: =AL4 -> 0 | AZ4: =AM4 -> 0 | BA4: =AN4 -> 0 | BC4: =AR4 -> 39355 | BD4: =AT4 -> 0.023798391 | BE4: =AU4 -> 0
A5: 39447 | B5: -0.001819592 | C5: -0.00026552038 | D5: -0.1690069 | E5: 6.1493388e-08 | F5: 0.23796722 | G5: -0.0093067312 | H5: 1.4725119e-06 | I5: -0.51029866 | J5: -0.065204379 | K5: 0.024733448 | L5: -0.00022667152 | M5: 0 | N5: 0 | O5: 0.022562176 | P5: 0 | Q5: 0.00016303021 | R5: 0 | S5: 0 | T5: 1.294007 | U5: 0 | V5: 0 | W5: 0 | X5: 0 | Y5: 0 | Z5: 0 | AA5: 0 | AB5: 0 | AC5: 0 | AD5: 0 | AE5: 0.035014511 | AF5: 0.86907076 | AH5: =K5+Y5-Y5/100 -> 0.024733448 | AI5: =Y5 -> 0 | AJ5: =Z5 -> 0 | AK5: =AA5 -> 0 | AL5: =AB5 -> 0 | AM5: =AC5 -> 0 | AN5: =AD5 -> 0 | AR5: =A5 -> 39447 | AS5: =AF5*4+2 -> 5.476283 | AT5: =AH5 -> 0.024733448 | AU5: =SUM(AV5:BA5) -> 0 | AV5: =AI5 -> 0 | AW5: =AJ5 -> 0 | AX5: =AK5 -> 0 | AY5: =AL5 -> 0 | AZ5: =AM5 -> 0 | BA5: =AN5 -> 0 | BC5: =AR5 -> 39447 | BD5: =AT5 -> 0.024733448 | BE5: =AU5 -> 0
A6: 39538 | B6: -0.0017947097 | C6: -0.0003933734 | D6: -0.17379543 | E6: 4.1640913e-08 | F6: 0.24330441 | G6: -0.0094038734 | H6: -3.0191972e-05 | I6: -0.075682169 | J6: -0.059083667 | K6: 0.027431403 | L6: 4.5698247e-05 | M6: 0 | N6: 0 | O6: 0.024035226 | P6: 0 | Q6: 0.0001932567 | R6: 0 | S6: 0 | T6: 1.0447664 | U6: 0 | V6: 0 | W6: 0 | X6: 0 | Y6: 0 | Z6: 0 | AA6: 0 | AB6: 0 | AC6: 0 | AD6: 0 | AE6: 0.034555629 | AF6: 1.0750228 | AH6: =K6+Y6-Y6/100 -> 0.027431403 | AI6: =Y6 -> 0 | AJ6: =Z6 -> 0 | AK6: =AA6 -> 0 | AL6: =AB6 -> 0 | AM6: =AC6 -> 0 | AN6: =AD6 -> 0 | AR6: =A6 -> 39538 | AS6: =AF6*4+2 -> 6.3000912 | AT6: =AH6 -> 0.027431403 | AU6: =SUM(AV6:BA6) -> 0 | AV6: =AI6 -> 0 | AW6: =AJ6 -> 0 | AX6: =AK6 -> 0 | AY6: =AL6 -> 0 | AZ6: =AM6 -> 0 | BA6: =AN6 -> 0 | BC6: =AR6 -> 39538 | BD6: =AT6 -> 0.027431403 | BE6: =AU6 -> 0
A7: 39629 | B7: -0.0017283825 | C7: -0.00052098134 | D7: -0.17948205 | E7: -8.4770635e-08 | F7: 0.25457248 | G7: -0.0094675548 | H7: -2.4387526e-05 | I7: -0.53246487 | J7: -0.062762084 | K7: 0.025474549 | L7: 0.00015518565 | M7: 0 | N7: 0 | O7: 0.024579932 | P7: 0 | Q7: 0.00025217967 | R7: 0 | S7: 0 | T7: 0.55768634 | U7: 0 | V7: 0 | W7: 0 | X7: 0 | Y7: 0 | Z7: 0 | AA7: 0 | AB7: 0 | AC7: 0 | AD7: 0 | AE7: 0.034103845 | AF7: 0.10910267 | AH7: =K7+Y7-Y7/100 -> 0.025474549 | AI7: =Y7 -> 0 | AJ7: =Z7 -> 0 | AK7: =AA7 -> 0 | AL7: =AB7 -> 0 | AM7: =AC7 -> 0 | AN7: =AD7 -> 0 | AR7: =A7 -> 39629 | AS7: =AF7*4+2 -> 2.4364107 | AT7: =AH7 -> 0.025474549 | AU7: =SUM(AV7:BA7) -> 0 | AV7: =AI7 -> 0 | AW7: =AJ7 -> 0 | AX7: =AK7 -> 0 | AY7: =AL7 -> 0 | AZ7: =AM7 -> 0 | BA7: =AN7 -> 0 | BC7: =AR7 -> 39629 | BD7: =AT7 -> 0.025474549 | BE7: =AU7 -> 0
A8: 39721 | B8: -0.0015061545 | C8: -0.00082754778 | D8: -0.18355115 | E8: -2.1032052e-07 | F8: 0.26437332 | G8: -0.0096179459 | H8: -7.5678916e-06 | I8: -0.14485768 | J8: -0.050365823 | K8: 0.023972166 | L8: 0.00035591919 | M8: 0 | N8: 0 | O8: 0.026352006 | P8: 0 | Q8: 0.0002999625 | R8: 0 | S8: 0 | T8: -0.036013235 | U8: 0 | V8: 0 | W8: 0 | X8: 0 | Y8: 0 | Z8: 0 | AA8: 0 | AB8: 0 | AC8: 0 | AD8: 0 | AE8: 0.033658996 | AF8: -0.079941369 | AH8: =K8+Y8-Y8/100 -> 0.023972166 | AI8: =Y8 -> 0 | AJ8: =Z8 -> 0 | AK8: =AA8 -> 0 | AL8: =AB8 -> 0 | AM8: =AC8 -> 0 | AN8: =AD8 -> 0 | AR8: =A8 -> 39721 | AS8: =AF8*4+2 -> 1.6802345 | AT8: =AH8 -> 0.023972166 | AU8: =SUM(AV8:BA8) -> 0 | AV8: =AI8 -> 0 | AW8: =AJ8 -> 0 | AX8: =AK8 -> 0 | AY8: =AL8 -> 0 | AZ8: =AM8 -> 0 | BA8: =AN8 -> 0 | BC8: =AR8 -> 39721 | BD8: =AT8 -> 0.023972166 | BE8: =AU8 -> 0
A9: 39813 | B9: -0.0017549138 | C9: -0.00156211 | D9: -0.1933762 | E9: -1.8715314e-07 | F9: 0.25092315 | G9: -0.01007109 | H9: 4.9196496e-05 | I9: -0.040406385 | J9: -0.043813379 | K9: 0.021710964 | L9: 0.00096220758 | M9: 0 | N9: 0 | O9: 0.027999195 | P9: 0 | Q9: 0.00032064405 | R9: 0 | S9: 0 | T9: -0.34690997 | U9: 0 | V9: 0 | W9: 0 | X9: 0 | Y9: 0.00070843025 | Z9: -0.0015217668 | AA9: 0.0012434729 | AB9: -0.00011281199 | AC9: -0.00027900983 | AD9: -0.0006330498 | AE9: 0.033220923 | AF9: -0.31011519 | AH9: =K9+Y9-Y9/100 -> 0.02241231 | AI9: =Y9/1010 -> 7.0141609e-07 | AJ9: =Z9 -> -0.0015217668 | AK9: =AA9 -> 0.0012434729 | AL9: =AB9 -> -0.00011281199 | AM9: =AC9 -> -0.00027900983 | AN9: =AD9 -> -0.0006330498 | AR9: =A9 -> 39813 | AS9: =AF9*4+2 -> 0.75953925 | AT9: =AH9 -> 0.02241231 | AU9: =SUM(AV9:BA9) -> -0.0013024641 | AV9: =AI9 -> 7.0141609e-07 | AW9: =AJ9 -> -0.0015217668 | AX9: =AK9 -> 0.0012434729 | AY9: =AL9 -> -0.00011281199 | AZ9: =AM9 -> -0.00027900983 | BA9: =AN9 -> -0.0006330498 | BC9: =AR9 -> 39813 | BD9: =AT9 -> 0.02241231 | BE9: =AU9 -> -0.0013024641
A10: 39903 | B10: -0.0019454651 | C10: -0.0020700598 | D10: -0.190723 | E10: -1.6006965e-07 | F10: 0.24064261 | G10: -0.010410226 | H10: 5.9186259e-05 | I10: -0.45255197 | J10: -0.040579955 | K10: 0.025697384 | L10: 0.0014714383 | M10: 0 | N10: 0 | O10: 0.028632362 | P10: 0 | Q10: 0.00026107654 | R10: 0 | S10: 0 | T10: -0.61148125 | U10: 0 | V10: 0 | W10: 0 | X10: 0 | Y10: -0.017335051 | Z10: 0.00028225495 | AA10: 0.0015825516 | AB10: -0.00047262247 | AC10: -0.00092929223 | AD10: -0.0029323275 | AE10: 0.032789475 | AF10: -1.0185632 | AH10: =K10+Y10-Y10/100 -> 0.0085356841 | AI10: =Y10/1010 -> -1.7163416e-05 | AJ10: =Z10 -> 0.00028225495 | AK10: =AA10 -> 0.0015825516 | AL10: =AB10 -> -0.00047262247 | AM10: =AC10 -> -0.00092929223 | AN10: =AD10 -> -0.0029323275 | AR10: =A10 -> 39903 | AS10: =AF10*4+2 -> -2.074253 | AT10: =AH10 -> 0.0085356841 | AU10: =SUM(AV10:BA10) -> -0.0024865991 | AV10: =AI10 -> -1.7163416e-05 | AW10: =AJ10 -> 0.00028225495 | AX10: =AK10 -> 0.0015825516 | AY10: =AL10 -> -0.00047262247 | AZ10: =AM10 -> -0.00092929223 | BA10: =AN10 -> -0.0029323275 | BC10: =AR10 -> 39903 | BD10: =AT10 -> 0.0085356841 | BE10: =AU10 -> -0.0024865991
A11: 39994 | B11: -0.0020344507 | C11: -0.002721877 | D11: -0.17909841 | E11: -5.3592286e-08 | F11: 0.22222929 | G11: -0.010635415 | H11: -1.2502908e-05 | I11: -0.42127389 | J11: -0.029536743 | K11: 0.047202925 | L11: 0.0015929992 | M11: 0 | N11: 0 | O11: 0.029097626 | P11: 0 | Q11: 0.00016675153 | R11: 0 | S11: 0 | T11: -0.42917612 | U11: 0 | V11: 0 | W11: 0 | X11: 0 | Y11: -0.041929311 | Z11: 0.003121548 | AA11: 0.0014838274 | AB11: -0.001187285 | AC11: -0.0011340987 | AD11: -0.0063679069 | AE11: 0.032364504 | AF11: -0.80288902 | AH11: =K11+Y11-Y11/100 -> 0.0056929076 | AI11: =Y11/1010 -> -4.1514169e-05 | AJ11: =Z11 -> 0.003121548 | AK11: =AA11 -> 0.0014838274 | AL11: =AB11 -> -0.001187285 | AM11: =AC11 -> -0.0011340987 | AN11: =AD11 -> -0.0063679069 | AR11: =A11 -> 39994 | AS11: =AF11*4+2 -> -1.2115561 | AT11: =AH11 -> 0.0056929076 | AU11: =SUM(AV11:BA11) -> -0.0041254295 | AV11: =AI11 -> -4.1514169e-05 | AW11: =AJ11 -> 0.003121548 | AX11: =AK11 -> 0.0014838274 | AY11: =AL11 -> -0.001187285 | AZ11: =AM11 -> -0.0011340987 | BA11: =AN11 -> -0.0063679069 | BC11: =AR11 -> 39994 | BD11: =AT11 -> 0.0056929076 | BE11: =AU11 -> -0.0041254295
A12: 40086 | B12: -0.002067631 | C12: -0.00337687 | D12: -0.15673999 | E12: 2.3187976e-07 | F12: 0.19859034 | G12: -0.01073315 | H12: -2.8778658e-05 | I12: -0.042175304 | J12: -0.014411846 | K12: 0.069653433 | L12: 0.0015007486 | M12: 0 | N12: 0 | O12: 0.029915693 | P12: 0 | Q12: 0.00013276591 | R12: 0 | S12: 0 | T12: -1.2045993 | U12: 0 | V12: 0 | W12: 0 | X12: 0 | Y12: -0.060882389 | Z12: 0.0045827932 | AA12: 0.00087449553 | AB12: -0.0024357544 | AC12: -0.0019012159 | AD12: -0.011224735 | AE12: 0.031945867 | AF12: -1.19785 | AH12: =K12+Y12-Y12/100 -> 0.0093798676 | AI12: =Y12/1010 -> -6.0279593e-05 | AJ12: =Z12 -> 0.0045827932 | AK12: =AA12 -> 0.00087449553 | AL12: =AB12 -> -0.0024357544 | AM12: =AC12 -> -0.0019012159 | AN12: =AD12 -> -0.011224735 | AR12: =A12 -> 40086 | AS12: =AF12*4+2 -> -2.7913999 | AT12: =AH12 -> 0.0093798676 | AU12: =SUM(AV12:BA12) -> -0.010164697 | AV12: =AI12 -> -6.0279593e-05 | AW12: =AJ12 -> 0.0045827932 | AX12: =AK12 -> 0.00087449553 | AY12: =AL12 -> -0.0024357544 | AZ12: =AM12 -> -0.0019012159 | BA12: =AN12 -> -0.011224735 | BC12: =AR12 -> 40086 | BD12: =AT12 -> 0.0093798676 | BE12: =AU12 -> -0.010164697
A13: 40178 | B13: -0.0019039885 | C13: -0.0034857199 | D13: -0.13826055 | E13: 4.5224278e-07 | F13: 0.18680347 | G13: -0.010817037 | H13: -7.4483907e-06 | I13: -0.55025309 | J13: -0.0084786115 | K13: 0.085800489 | L13: 0.0014108205 | M13: 0 | N13: 0 | O13: 0.029825542 | P13: 0 | Q13: 0.00011992906 | R13: 0 | S13: 0 | T13: -0.66781616 | U13: 0 | V13: 0 | W13: 0 | X13: 0 | Y13: -0.075357566 | Z13: 0.0064716328 | AA13: 0.00040512964 | AB13: -0.0033562359 | AC13: -0.0019804733 | AD13: -0.016332099 | AE13: 0.031533427 | AF13: -1.1562081 | AH13: =K13+Y13-Y13/100 -> 0.011196499 | AI13: =Y13/1010 -> -7.4611451e-05 | AJ13: =Z13 -> 0.0064716328 | AK13: =AA13 -> 0.00040512964 | AL13: =AB13 -> -0.0033562359 | AM13: =AC13 -> -0.0019804733 | AN13: =AD13 -> -0.016332099 | AR13: =A13 -> 40178 | AS13: =AF13*4+2 -> -2.6248325 | AT13: =AH13 -> 0.011196499 | AU13: =SUM(AV13:BA13) -> -0.014866657 | AV13: =AI13 -> -7.4611451e-05 | AW13: =AJ13 -> 0.0064716328 | AX13: =AK13 -> 0.00040512964 | AY13: =AL13 -> -0.0033562359 | AZ13: =AM13 -> -0.0019804733 | BA13: =AN13 -> -0.016332099 | BC13: =AR13 -> 40178 | BD13: =AT13 -> 0.011196499 | BE13: =AU13 -> -0.014866657
A14: 40268 | B14: -0.001768788 | C14: -0.0035200668 | D14: -0.12706516 | E14: 5.26805e-07 | F14: 0.17185687 | G14: -0.010899309 | H14: -1.0561186e-05 | I14: -0.44949232 | J14: -0.011643689 | K14: 0.10182928 | L14: 0.0013920941 | M14: 0 | N14: 0 | O14: 0.030030724 | P14: 0 | Q14: 0.00010142116 | R14: 0 | S14: 0 | T14: -0.76982936 | U14: 0 | V14: 0 | W14: 0 | X14: 0 | Y14: -0.085165599 | Z14: 0.0094093821 | AA14: 0.0013787772 | AB14: -0.0031525209 | AC14: -0.0012348492 | AD14: -0.020652981 | AE14: 0.031127049 | AF14: -1.15807 | AH14: =K14+Y14-Y14/100 -> 0.017515336 | AI14: =Y14/1010 -> -8.4322375e-05 | AJ14: =Z14 -> 0.0094093821 | AK14: =AA14 -> 0.0013787772 | AL14: =AB14 -> -0.0031525209 | AM14: =AC14 -> -0.0012348492 | AN14: =AD14 -> -0.020652981 | AR14: =A14 -> 40268 | AS14: =AF14*4+2 -> -2.6322801 | AT14: =AH14 -> 0.017515336 | AU14: =SUM(AV14:BA14) -> -0.014336514 | AV14: =AI14 -> -8.4322375e-05 | AW14: =AJ14 -> 0.0094093821 | AX14: =AK14 -> 0.0013787772 | AY14: =AL14 -> -0.0031525209 | AZ14: =AM14 -> -0.0012348492 | BA14: =AN14 -> -0.020652981 | BC14: =AR14 -> 40268 | BD14: =AT14 -> 0.017515336 | BE14: =AU14 -> -0.014336514
A15: 40359 | B15: -0.0016055442 | C15: -0.0034126173 | D15: -0.12024167 | E15: 6.1831082e-07 | F15: 0.14974555 | G15: -0.010999744 | H15: 1.1225093e-05 | I15: -0.3859079 | J15: -0.010546563 | K15: 0.1137369 | L15: 0.0012674654 | M15: 0 | N15: 0 | O15: 0.03029255 | P15: 0 | Q15: 8.5443216e-05 | R15: 0 | S15: 0 | T15: -0.74550929 | U15: 0 | V15: 0 | W15: 0 | X15: 0 | Y15: -0.094219354 | Z15: 0.012620793 | AA15: 0.0037813698 | AB15: -0.0012855556 | AC15: 0.00056690679 | AD15: -0.023176605 | AE15: 0.030726605 | AF15: -1.0735987 | AH15: =K15+Y15-Y15/100 -> 0.02045974 | AI15: =Y15/1010 -> -9.3286489e-05 | AJ15: =Z15 -> 0.012620793 | AK15: =AA15 -> 0.0037813698 | AL15: =AB15 -> -0.0012855556 | AM15: =AC15 -> 0.00056690679 | AN15: =AD15 -> -0.023176605 | AR15: =A15 -> 40359 | AS15: =AF15*4+2 -> -2.2943948 | AT15: =AH15 -> 0.02045974 | AU15: =SUM(AV15:BA15) -> -0.007586378 | AV15: =AI15 -> -9.3286489e-05 | AW15: =AJ15 -> 0.012620793 | AX15: =AK15 -> 0.0037813698 | AY15: =AL15 -> -0.0012855556 | AZ15: =AM15 -> 0.00056690679 | BA15: =AN15 -> -0.023176605 | BC15: =AR15 -> 40359 | BD15: =AT15 -> 0.02045974 | BE15: =AU15 -> -0.007586378
A16: 40451 | B16: -0.0015195804 | C16: -0.0032687084 | D16: -0.1153459 | E16: 7.2160802e-07 | F16: 0.14285232 | G16: -0.011072744 | H16: 8.8154421e-06 | I16: 0.030795735 | J16: -0.015183955 | K16: 0.12312668 | L16: 0.0013868123 | M16: 0 | N16: 0 | O16: 0.031305321 | P16: 0 | Q16: 5.5392826e-05 | R16: 0 | S16: 0 | T16: -0.77668895 | U16: 0 | V16: 0 | W16: 0 | X16: 0 | Y16: -0.1056787 | Z16: 0.014564632 | AA16: 0.004651098 | AB16: -0.00028653286 | AC16: 0.0016313845 | AD16: -0.024586607 | AE16: 0.030331971 | AF16: -0.6876071 | AH16: =K16+Y16-Y16/100 -> 0.018504761 | AI16: =Y16/1010 -> -0.00010463238 | AJ16: =Z16 -> 0.014564632 | AK16: =AA16 -> 0.004651098 | AL16: =AB16 -> -0.00028653286 | AM16: =AC16 -> 0.0016313845 | AN16: =AD16 -> -0.024586607 | AR16: =A16 -> 40451 | AS16: =AF16*4+2 -> -0.75042838 | AT16: =AH16 -> 0.018504761 | AU16: =SUM(AV16:BA16) -> -0.0041306584 | AV16: =AI16 -> -0.00010463238 | AW16: =AJ16 -> 0.014564632 | AX16: =AK16 -> 0.004651098 | AY16: =AL16 -> -0.00028653286 | AZ16: =AM16 -> 0.0016313845 | BA16: =AN16 -> -0.024586607 | BC16: =AR16 -> 40451 | BD16: =AT16 -> 0.018504761 | BE16: =AU16 -> -0.0041306584
A17: 40543 | B17: -0.0013371114 | C17: -0.0030069557 | D17: -0.11680429 | E17: 7.5777917e-07 | F17: 0.1604768 | G17: -0.011130844 | H17: -1.3967529e-05 | I17: -0.53120714 | J17: -0.020569429 | K17: 0.13514114 | L17: 0.0013693178 | M17: 0 | N17: 0 | O17: 0.031637455 | P17: 0 | Q17: 2.1527973e-05 | R17: 0 | S17: 0 | T17: -0.1423499 | U17: 0 | V17: 0 | W17: 0 | X17: 0 | Y17: -0.12188145 | Z17: 0.016047211 | AA17: 0.0046091224 | AB17: -0.0002321107 | AC17: 0.0015502993 | AD17: -0.026035114 | AE17: 0.029943024 | AF17: -0.60589549 | AH17: =K17+Y17-Y17/100 -> 0.014478505 | AI17: =Y17/1010 -> -0.00012067471 | AJ17: =Z17 -> 0.016047211 | AK17: =AA17 -> 0.0046091224 | AL17: =AB17 -> -0.0002321107 | AM17: =AC17 -> 0.0015502993 | AN17: =AD17 -> -0.026035114 | AR17: =A17 -> 40543 | AS17: =AF17*4+2 -> -0.42358195 | AT17: =AH17 -> 0.014478505 | AU17: =SUM(AV17:BA17) -> -0.0041812674 | AV17: =AI17 -> -0.00012067471 | AW17: =AJ17 -> 0.016047211 | AX17: =AK17 -> 0.0046091224 | AY17: =AL17 -> -0.0002321107 | AZ17: =AM17 -> 0.0015502993 | BA17: =AN17 -> -0.026035114 | BC17: =AR17 -> 40543 | BD17: =AT17 -> 0.014478505 | BE17: =AU17 -> -0.0041812674
A18: 40633 | B18: -0.001532286 | C18: -0.0030637023 | D18: -0.12140879 | E18: 1.0029129e-06 | F18: 0.19879283 | G18: -0.01119554 | H18: -2.7882324e-05 | I18: -0.18688172 | J18: -0.015301681 | K18: 0.15058927 | L18: 0.0012852384 | M18: 0 | N18: 0 | O18: 0.032742452 | P18: 0 | Q18: 1.4912948e-05 | R18: 0 | S18: 0 | T18: -0.13549147 | U18: 0 | V18: 0 | W18: 0 | X18: 0 | Y18: -0.14325903 | Z18: 0.015494468 | AA18: 0.0021559779 | AB18: -0.0022332803 | AC18: -0.00024279061 | AD18: -0.028997077 | AE18: 0.029559647 | AF18: -0.22396376 | AH18: =K18+Y18-Y18/100 -> 0.0087628235 | AI18: =Y18/1010 -> -0.00014184063 | AJ18: =Z18 -> 0.015494468 | AK18: =AA18 -> 0.0021559779 | AL18: =AB18 -> -0.0022332803 | AM18: =AC18 -> -0.00024279061 | AN18: =AD18 -> -0.028997077 | AR18: =A18 -> 40633 | AS18: =AF18*4+2 -> 1.104145 | AT18: =AH18 -> 0.0087628235 | AU18: =SUM(AV18:BA18) -> -0.013964543 | AV18: =AI18 -> -0.00014184063 | AW18: =AJ18 -> 0.015494468 | AX18: =AK18 -> 0.0021559779 | AY18: =AL18 -> -0.0022332803 | AZ18: =AM18 -> -0.00024279061 | BA18: =AN18 -> -0.028997077 | BC18: =AR18 -> 40633 | BD18: =AT18 -> 0.0087628235 | BE18: =AU18 -> -0.013964543
A19: 40724 | B19: -0.0013887264 | C19: -0.0026312904 | D19: -0.11897872 | E19: 1.2248825e-06 | F19: 0.22837771 | G19: -0.011258261 | H19: 2.002581e-05 | I19: -0.30315083 | J19: -0.011646391 | K19: 0.16881612 | L19: 0.0013859892 | M19: 0 | N19: 0 | O19: 0.033785775 | P19: 0 | Q19: 2.0237128e-05 | R19: 0 | S19: 0 | T19: 0.07829521 | U19: 0 | V19: 0 | W19: 0 | X19: 0 | Y19: -0.1718397 | Z19: 0.016461217 | AA19: 0.00069928078 | AB19: -0.0031950007 | AC19: -0.00097890427 | AD19: -0.032208723 | AE19: 0.029181729 | AF19: -0.10335766 | AH19: =K19+Y19-Y19/100 -> -0.001305185 | AI19: =Y19/1010 -> -0.00017013832 | AJ19: =Z19 -> 0.016461217 | AK19: =AA19 -> 0.00069928078 | AL19: =AB19 -> -0.0031950007 | AM19: =AC19 -> -0.00097890427 | AN19: =AD19 -> -0.032208723 | AR19: =A19 -> 40724 | AS19: =AF19*4+2 -> 1.5865694 | AT19: =AH19 -> -0.001305185 | AU19: =SUM(AV19:BA19) -> -0.019392268 | AV19: =AI19 -> -0.00017013832 | AW19: =AJ19 -> 0.016461217 | AX19: =AK19 -> 0.00069928078 | AY19: =AL19 -> -0.0031950007 | AZ19: =AM19 -> -0.00097890427 | BA19: =AN19 -> -0.032208723 | BC19: =AR19 -> 40724 | BD19: =AT19 -> -0.001305185 | BE19: =AU19 -> -0.019392268
A20: 40816 | B20: -0.0015124037 | C20: -0.0024314791 | D20: -0.11554017 | E20: 1.2930845e-06 | F20: 0.18396915 | G20: -0.01133035 | H20: -1.4453412e-05 | I20: -0.059234404 | J20: -0.015603639 | K20: 0.19455535 | L20: 0.0014810747 | M20: 0 | N20: 0 | O20: 0.034028768 | P20: 0 | Q20: -4.934565e-06 | R20: 0 | S20: 0 | T20: -0.10252246 | U20: 0 | V20: 0 | W20: 0 | X20: 0 | Y20: -0.19596717 | Z20: 0.022855452 | AA20: 0.0035417646 | AB20: -0.00062814047 | AC20: 0.0010605802 | AD20: -0.033246181 | AE20: 0.028809157 | AF20: -0.069799206 | AH20: =K20+Y20-Y20/100 -> 0.00054784675 | AI20: =Y20/1010 -> -0.0001940269 | AJ20: =Z20 -> 0.022855452 | AK20: =AA20 -> 0.0035417646 | AL20: =AB20 -> -0.00062814047 | AM20: =AC20 -> 0.0010605802 | AN20: =AD20 -> -0.033246181 | AR20: =A20 -> 40816 | AS20: =AF20*4+2 -> 1.7208032 | AT20: =AH20 -> 0.00054784675 | AU20: =SUM(AV20:BA20) -> -0.0066105514 | AV20: =AI20 -> -0.0001940269 | AW20: =AJ20 -> 0.022855452 | AX20: =AK20 -> 0.0035417646 | AY20: =AL20 -> -0.00062814047 | AZ20: =AM20 -> 0.0010605802 | BA20: =AN20 -> -0.033246181 | BC20: =AR20 -> 40816 | BD20: =AT20 -> 0.00054784675 | BE20: =AU20 -> -0.0066105514
... A132: 51043 | B132: -0.043141873 | C132: -0.00014191675 | D132: -0.060150045 | E132: 0.00016375639 | F132: 0.077003819 | G132: -0.017761409 | H132: 0.10657899 | I132: -0.12938709 | J132: -0.23383062 | K132: -0.0013647494 | L132: 0.028622522 | M132: 0 | N132: 0 | O132: 0.44750605 | P132: 0 | Q132: 0.30446726 | R132: 0 | S132: 0 | T132: 0 | U132: 0 | V132: 0 | W132: 0 | X132: 0 | Y132: 0.0014171204 | Z132: -0.0014470184 | AA132: 0.00054189822 | AB132: -0.00029329794 | AC132: 0.0013717805 | AD132: 0.0037302372 | AE132: -0.072867892 | AF132: 0.418171 | AH132: =K132+Y132-Y132/100 -> 3.8199787e-05 | AI132: =Y132/1010 -> 1.4030895e-06 | AJ132: =Z132 -> -0.0014470184 | AK132: =AA132 -> 0.00054189822 | AL132: =AB132 -> -0.00029329794 | AM132: =AC132 -> 0.0013717805 | AN132: =AD132 -> 0.0037302372 | AR132: =A132 -> 51043 | AS132: =AF132*4+2 -> 3.672684 | AT132: =AH132 -> 3.8199787e-05 | AU132: =SUM(AV132:BA132) -> 0.0039050027 | AV132: =AI132 -> 1.4030895e-06 | AW132: =AJ132 -> -0.0014470184 | AX132: =AK132 -> 0.00054189822 | AY132: =AL132 -> -0.00029329794 | AZ132: =AM132 -> 0.0013717805 | BA132: =AN132 -> 0.0037302372 | BC132: =AR132 -> 51043 | BD132: =AT132 -> 3.8199787e-05 | BE132: =AU132 -> 0.0039050027

Sheet EA_raw_policy_shocks
A1: date | C1: Monetary Policy | D1: FG1 | E1: FG2 | F1: FG3 | G1: FG4 | H1: FG5 | I1: FG6 | L1: Date | M1: Monetary Policy | N1: FG1 | O1: FG2 | P1: FG3 | Q1: FG4 | R1: FG5 | S1: FG6
A2: 26480 | C2: -0.13372599 | D2: -7.0937759e-15 | E2: 6.1916191e-16 | F2: -4.0637422e-15 | G2: -7.7242506e-15 | H2: -7.0753749e-15 | I2: 9.7413678e-16 | M2: =C2 -> -0.13372599 | N2: =D2/10 -> -7.0937759e-16 | O2: =E2 -> 6.1916191e-16 | P2: =F2 -> -4.0637422e-15 | Q2: =G2 -> -7.7242506e-15 | R2: =H2 -> -7.0753749e-15 | S2: =I2 -> 9.7413678e-16
A3: 26572 | C3: -0.32978154 | D3: -6.9791533e-15 | E3: -2.3362694e-16 | F3: -2.8572172e-15 | G3: -7.2602506e-15 | H3: -5.9936663e-15 | I3: 1.3121579e-16 | M3: =C3 -> -0.32978154 | N3: =D3/10 -> -6.9791533e-16 | O3: =E3 -> -2.3362694e-16 | P3: =F3 -> -2.8572172e-15 | Q3: =G3 -> -7.2602506e-15 | R3: =H3 -> -5.9936663e-15 | S3: =I3 -> 1.3121579e-16
A4: 26664 | C4: 0.25187082 | D4: -8.386221e-15 | E4: 4.8258192e-16 | F4: -2.7999737e-15 | G4: -6.2051305e-15 | H4: -6.7020971e-15 | I4: 1.0800576e-16 | M4: =C4 -> 0.25187082 | N4: =D4/10 -> -8.386221e-16 | O4: =E4 -> 4.8258192e-16 | P4: =F4 -> -2.7999737e-15 | Q4: =G4 -> -6.2051305e-15 | R4: =H4 -> -6.7020971e-15 | S4: =I4 -> 1.0800576e-16
A5: 26754 | C5: 0.03359876 | D5: -7.7139114e-15 | E5: 5.2390174e-16 | F5: -1.7790139e-15 | G5: -7.4373859e-15 | H5: -7.7448034e-15 | I5: -3.6196971e-16 | M5: =C5 -> 0.03359876 | N5: =D5/10 -> -7.7139114e-16 | O5: =E5 -> 5.2390174e-16 | P5: =F5 -> -1.7790139e-15 | Q5: =G5 -> -7.4373859e-15 | R5: =H5 -> -7.7448034e-15 | S5: =I5 -> -3.6196971e-16
A6: 26845 | C6: 0.29482685 | D6: -7.6968198e-15 | E6: 2.0333413e-15 | F6: -2.3580494e-15 | G6: -7.6039765e-15 | H6: -7.1909983e-15 | I6: 5.5837779e-16 | M6: =C6 -> 0.29482685 | N6: =D6/10 -> -7.6968198e-16 | O6: =E6 -> 2.0333413e-15 | P6: =F6 -> -2.3580494e-15 | Q6: =G6 -> -7.6039765e-15 | R6: =H6 -> -7.1909983e-15 | S6: =I6 -> 5.5837779e-16
A7: 26937 | C7: 0.40092867 | D7: -6.696605e-15 | E7: 9.0186821e-16 | F7: -2.9334294e-15 | G7: -7.6070683e-15 | H7: -7.1271962e-15 | I7: -6.7705197e-17 | M7: =C7 -> 0.40092867 | N7: =D7/10 -> -6.696605e-16 | O7: =E7 -> 9.0186821e-16 | P7: =F7 -> -2.9334294e-15 | Q7: =G7 -> -7.6070683e-15 | R7: =H7 -> -7.1271962e-15 | S7: =I7 -> -6.7705197e-17
A8: 27029 | C8: -0.017830037 | D8: -7.6991443e-15 | E8: 5.7668906e-16 | F8: -2.6337783e-15 | G8: -7.7697419e-15 | H8: -8.480101e-15 | I8: -3.0600183e-16 | M8: =C8 -> -0.017830037 | N8: =D8/10 -> -7.6991443e-16 | O8: =E8 -> 5.7668906e-16 | P8: =F8 -> -2.6337783e-15 | Q8: =G8 -> -7.7697419e-15 | R8: =H8 -> -8.480101e-15 | S8: =I8 -> -3.0600183e-16
A9: 27119 | C9: 0.010781378 | D9: -8.0047356e-15 | E9: 1.0700406e-15 | F9: -2.4008864e-15 | G9: -8.6493955e-15 | H9: -8.3859727e-15 | I9: 2.3217865e-16 | M9: =C9 -> 0.010781378 | N9: =D9/10 -> -8.0047356e-16 | O9: =E9 -> 1.0700406e-15 | P9: =F9 -> -2.4008864e-15 | Q9: =G9 -> -8.6493955e-15 | R9: =H9 -> -8.3859727e-15 | S9: =I9 -> 2.3217865e-16
A10: 27210 | C10: -0.137027 | D10: -7.4558942e-15 | E10: 9.8099133e-16 | F10: -4.0956519e-15 | G10: -9.72435e-15 | H10: -9.0499551e-15 | I10: -1.0055611e-15 | M10: =C10 -> -0.137027 | N10: =D10/10 -> -7.4558942e-16 | O10: =E10 -> 9.8099133e-16 | P10: =F10 -> -4.0956519e-15 | Q10: =G10 -> -9.72435e-15 | R10: =H10 -> -9.0499551e-15 | S10: =I10 -> -1.0055611e-15
A11: 27302 | C11: 0.032328036 | D11: -7.4117278e-15 | E11: -1.1286932e-16 | F11: -3.9612004e-15 | G11: -8.5412236e-15 | H11: -8.2672821e-15 | I11: 9.3170634e-16 | M11: =C11 -> 0.032328036 | N11: =D11/10 -> -7.4117278e-16 | O11: =E11 -> -1.1286932e-16 | P11: =F11 -> -3.9612004e-15 | Q11: =G11 -> -8.5412236e-15 | R11: =H11 -> -8.2672821e-15 | S11: =I11 -> 9.3170634e-16
A12: 27394 | C12: -0.035677399 | D12: -8.753826e-15 | E12: -1.0175977e-15 | F12: -4.5950315e-15 | G12: -1.0287227e-14 | H12: -9.1584751e-15 | I12: -1.6462595e-15 | M12: =C12 -> -0.035677399 | N12: =D12/10 -> -8.753826e-16 | O12: =E12 -> -1.0175977e-15 | P12: =F12 -> -4.5950315e-15 | Q12: =G12 -> -1.0287227e-14 | R12: =H12 -> -9.1584751e-15 | S12: =I12 -> -1.6462595e-15
A13: 27484 | C13: -0.46076124 | D13: -9.015226e-15 | E13: -6.9339322e-16 | F13: -4.9091102e-15 | G13: -9.3953792e-15 | H13: -9.8120895e-15 | I13: 1.6577716e-16 | M13: =C13 -> -0.46076124 | N13: =D13/10 -> -9.015226e-16 | O13: =E13 -> -6.9339322e-16 | P13: =F13 -> -4.9091102e-15 | Q13: =G13 -> -9.3953792e-15 | R13: =H13 -> -9.8120895e-15 | S13: =I13 -> 1.6577716e-16
... A140: 39082 | C140: 0.049165061 | D140: -1.0486407e-14 | E140: 2.2068117e-15 | F140: -5.328786e-15 | G140: -1.7011581e-14 | H140: -1.6342592e-14 | I140: 3.0560804e-16 | M140: =C140 -> 0.049165061 | N140: =D140/10 -> -1.0486407e-15 | O140: =E140 -> 2.2068117e-15 | P140: =F140 -> -5.328786e-15 | Q140: =G140 -> -1.7011581e-14 | R140: =H140 -> -1.6342592e-14 | S140: =I140 -> 3.0560804e-16
A141: 39172 | B141: 1q07 | C141: 0.096451189 | D141: -9.9673708e-15 | E141: 2.2930298e-15 | F141: -5.4823221e-15 | G141: -1.7146264e-14 | H141: -1.604325e-14 | I141: 3.4385437e-16 | L141: ="20"&RIGHT(B141,2)&"Q"&LEFT(B141,1) -> 2007Q1 | M141: =C141 -> 0.096451189 | N141: =D141/10 -> -9.9673708e-16 | O141: =E141 -> 2.2930298e-15 | P141: =F141 -> -5.4823221e-15 | Q141: =G141 -> -1.7146264e-14 | R141: =H141 -> -1.604325e-14 | S141: =I141 -> 3.4385437e-16 | AE141: =M141 -> 0.096451189 | AF141: =N141 -> -9.9673708e-16 | AG141: =O141 -> 2.2930298e-15 | AH141: =P141 -> -5.4823221e-15 | AI141: =Q141 -> -1.7146264e-14 | AJ141: =R141 -> -1.604325e-14 | AK141: =S141 -> 3.4385437e-16
A142: 39263 | B142: 2q07 | C142: -0.079942737 | D142: -9.9527803e-15 | E142: 2.0189506e-15 | F142: -5.8984503e-15 | G142: -1.6954323e-14 | H142: -1.5795915e-14 | I142: 1.3532937e-16 | L142: ="20"&RIGHT(B142,2)&"Q"&LEFT(B142,1) -> 2007Q2 | M142: =C142 -> -0.079942737 | N142: =D142/10 -> -9.9527803e-16 | O142: =E142 -> 2.0189506e-15 | P142: =F142 -> -5.8984503e-15 | Q142: =G142 -> -1.6954323e-14 | R142: =H142 -> -1.5795915e-14 | S142: =I142 -> 1.3532937e-16 | AE142: =M142 -> -0.079942737 | AF142: =N142 -> -9.9527803e-16 | AG142: =O142 -> 2.0189506e-15 | AH142: =P142 -> -5.8984503e-15 | AI142: =Q142 -> -1.6954323e-14 | AJ142: =R142 -> -1.5795915e-14 | AK142: =S142 -> 1.3532937e-16
A143: 39355 | B143: 3q07 | C143: 0.036631347 | D143: -1.1471632e-14 | E143: 1.30004e-15 | F143: -5.730854e-15 | G143: -1.6034603e-14 | H143: -1.4791452e-14 | I143: 8.9944721e-16 | L143: ="20"&RIGHT(B143,2)&"Q"&LEFT(B143,1) -> 2007Q3 | M143: =C143 -> 0.036631347 | N143: =D143/10 -> -1.1471632e-15 | O143: =E143 -> 1.30004e-15 | P143: =F143 -> -5.730854e-15 | Q143: =G143 -> -1.6034603e-14 | R143: =H143 -> -1.4791452e-14 | S143: =I143 -> 8.9944721e-16 | AE143: =M143 -> 0.036631347 | AF143: =N143 -> -1.1471632e-15 | AG143: =O143 -> 1.30004e-15 | AH143: =P143 -> -5.730854e-15 | AI143: =Q143 -> -1.6034603e-14 | AJ143: =R143 -> -1.4791452e-14 | AK143: =S143 -> 8.9944721e-16
A144: 39447 | B144: 4q07 | C144: -0.073000196 | D144: -1.2732741e-14 | E144: 1.4612799e-15 | F144: -4.0269544e-15 | G144: -1.4985715e-14 | H144: -1.529939e-14 | I144: 8.3454599e-16 | L144: ="20"&RIGHT(B144,2)&"Q"&LEFT(B144,1) -> 2007Q4 | M144: =C144 -> -0.073000196 | N144: =D144/10 -> -1.2732741e-15 | O144: =E144 -> 1.4612799e-15 | P144: =F144 -> -4.0269544e-15 | Q144: =G144 -> -1.4985715e-14 | R144: =H144 -> -1.529939e-14 | S144: =I144 -> 8.3454599e-16 | AD144: =LEFT(L144,4)+1 -> 2008 | AE144: =M144 -> -0.073000196 | AF144: =N144 -> -1.2732741e-15 | AG144: =O144 -> 1.4612799e-15 | AH144: =P144 -> -4.0269544e-15 | AI144: =Q144 -> -1.4985715e-14 | AJ144: =R144 -> -1.529939e-14 | AK144: =S144 -> 8.3454599e-16
A145: 39538 | B145: 1q08 | C145: -0.12232583 | D145: -1.4382912e-14 | E145: 2.6126614e-15 | F145: -3.1597493e-15 | G145: -1.5646211e-14 | H145: -1.5686843e-14 | I145: 7.5415734e-16 | L145: ="20"&RIGHT(B145,2)&"Q"&LEFT(B145,1) -> 2008Q1 | M145: =C145 -> -0.12232583 | N145: =D145/10 -> -1.4382912e-15 | O145: =E145 -> 2.6126614e-15 | P145: =F145 -> -3.1597493e-15 | Q145: =G145 -> -1.5646211e-14 | R145: =H145 -> -1.5686843e-14 | S145: =I145 -> 7.5415734e-16 | AD145: =LEFT(L145,4)+1 -> 2009 | AE145: =M145 -> -0.12232583 | AF145: =N145 -> -1.4382912e-15 | AG145: =O145 -> 2.6126614e-15 | AH145: =P145 -> -3.1597493e-15 | AI145: =Q145 -> -1.5646211e-14 | AJ145: =R145 -> -1.5686843e-14 | AK145: =S145 -> 7.5415734e-16
A146: 39629 | B146: 2q08 | C146: 0.085616678 | D146: -1.2574437e-14 | E146: 3.865563e-15 | F146: -2.3516121e-15 | G146: -1.6436028e-14 | H146: -1.9011273e-14 | I146: 1.6098045e-16 | L146: ="20"&RIGHT(B146,2)&"Q"&LEFT(B146,1) -> 2008Q2 | M146: =C146 -> 0.085616678 | N146: =D146/10 -> -1.2574437e-15 | O146: =E146 -> 3.865563e-15 | P146: =F146 -> -2.3516121e-15 | Q146: =G146 -> -1.6436028e-14 | R146: =H146 -> -1.9011273e-14 | S146: =I146 -> 1.6098045e-16 | AD146: =LEFT(L146,4)+1 -> 2009 | AE146: =M146 -> 0.085616678 | AF146: =N146 -> -1.2574437e-15 | AG146: =O146 -> 3.865563e-15 | AH146: =P146 -> -2.3516121e-15 | AI146: =Q146 -> -1.6436028e-14 | AJ146: =R146 -> -1.9011273e-14 | AK146: =S146 -> 1.6098045e-16
A147: 39721 | B147: 3q08 | C147: 0.024114352 | D147: -1.3427455e-14 | E147: 3.8170215e-15 | F147: -3.918892e-15 | G147: -1.9226514e-14 | H147: -1.7675893e-14 | I147: 7.3930435e-16 | L147: ="20"&RIGHT(B147,2)&"Q"&LEFT(B147,1) -> 2008Q3 | M147: =C147 -> 0.024114352 | N147: =D147/10 -> -1.3427455e-15 | O147: =E147 -> 3.8170215e-15 | P147: =F147 -> -3.918892e-15 | Q147: =G147 -> -1.9226514e-14 | R147: =H147 -> -1.7675893e-14 | S147: =I147 -> 7.3930435e-16 | AD147: =LEFT(L147,4)+1 -> 2009 | AE147: =M147 -> 0.024114352 | AF147: =N147 -> -1.3427455e-15 | AG147: =O147 -> 3.8170215e-15 | AH147: =P147 -> -3.918892e-15 | AI147: =Q147 -> -1.9226514e-14 | AJ147: =R147 -> -1.7675893e-14 | AK147: =S147 -> 7.3930435e-16
A148: 39813 | B148: 4q08 | C148: 0.054270209 | D148: -0.02758659 | E148: 0.057226894 | F148: -0.045349997 | G148: 0.0040063363 | H148: 0.0096842244 | I148: 0.021546318 | L148: ="20"&RIGHT(B148,2)&"Q"&LEFT(B148,1) -> 2008Q4 | M148: =C148 -> 0.054270209 | N148: =D148/10 -> -0.002758659 | O148: =E148 -> 0.057226894 | P148: =F148 -> -0.045349997 | Q148: =G148 -> 0.0040063363 | R148: =H148 -> 0.0096842244 | S148: =I148 -> 0.021546318 | AD148: =LEFT(L148,4)+1 -> 2009 | AE148: =M148 -> 0.054270209 | AF148: =N148 -> -0.002758659 | AG148: =O148 -> 0.057226894 | AH148: =P148 -> -0.045349997 | AI148: =Q148 -> 0.0040063363 | AJ148: =R148 -> 0.0096842244 | AK148: =S148 -> 0.021546318
A149: 39903 | B149: 1q09 | C149: -0.23276322 | D149: 0.7701374 | E149: -0.13446309 | F149: 0.0085426888 | G149: 0.020965193 | H149: 0.040489408 | I149: 0.070169286 | L149: ="20"&RIGHT(B149,2)&"Q"&LEFT(B149,1) -> 2009Q1 | M149: =C149 -> -0.23276322 | N149: =D149/10 -> 0.07701374 | O149: =E149 -> -0.13446309 | P149: =F149 -> 0.0085426888 | Q149: =G149 -> 0.020965193 | R149: =H149 -> 0.040489408 | S149: =I149 -> 0.070169286 | AD149: =LEFT(L149,4)+1 -> 2010 | AE149: =M149 -> -0.23276322 | AF149: =N149 -> 0.07701374 | AG149: =O149 -> -0.13446309 | AH149: =P149 -> 0.0085426888 | AI149: =Q149 -> 0.020965193 | AJ149: =R149 -> 0.040489408 | AK149: =S149 -> 0.070169286
A150: 39994 | B150: 2q09 | C150: -0.087880247 | D150: 0.56265234 | E150: -0.072336955 | F150: 0.028689131 | G150: 0.061132871 | H150: 0.068904315 | I150: 0.087714356 | L150: ="20"&RIGHT(B150,2)&"Q"&LEFT(B150,1) -> 2009Q2 | M150: =C150 -> -0.087880247 | N150: =D150/10 -> 0.056265234 | O150: =E150 -> -0.072336955 | P150: =F150 -> 0.028689131 | Q150: =G150 -> 0.061132871 | R150: =H150 -> 0.068904315 | S150: =I150 -> 0.087714356 | AD150: =LEFT(L150,4)+1 -> 2010 | AE150: =M150 -> -0.087880247 | AF150: =N150 -> 0.056265234 | AG150: =O150 -> -0.072336955 | AH150: =P150 -> 0.028689131 | AI150: =Q150 -> 0.061132871 | AJ150: =R150 -> 0.068904315 | AK150: =S150 -> 0.087714356
A151: 40086 | B151: 3q09 | C151: -0.053379596 | D151: 0.31932821 | E151: 0.013424012 | F151: 0.081292299 | G151: 0.10392751 | H151: 0.11197047 | I151: 0.12219401 | L151: ="20"&RIGHT(B151,2)&"Q"&LEFT(B151,1) -> 2009Q3 | M151: =C151 -> -0.053379596 | N151: =D151/10 -> 0.031932821 | O151: =E151 -> 0.013424012 | P151: =F151 -> 0.081292299 | Q151: =G151 -> 0.10392751 | R151: =H151 -> 0.11197047 | S151: =I151 -> 0.12219401 | AD151: =LEFT(L151,4)+1 -> 2010 | AE151: =M151 -> -0.053379596 | AF151: =N151 -> 0.031932821 | AG151: =O151 -> 0.013424012 | AH151: =P151 -> 0.081292299 | AI151: =Q151 -> 0.10392751 | AJ151: =R151 -> 0.11197047 | AK151: =S151 -> 0.12219401
A152: 40178 | B152: 4q09 | C152: -0.033873189 | D152: 0.32518556 | E152: 0.029346754 | F152: 0.11197614 | G152: 0.12854045 | H152: 0.11538989 | I152: 0.11362157 | L152: ="20"&RIGHT(B152,2)&"Q"&LEFT(B152,1) -> 2009Q4 | M152: =C152 -> -0.033873189 | N152: =D152/10 -> 0.032518556 | O152: =E152 -> 0.029346754 | P152: =F152 -> 0.11197614 | Q152: =G152 -> 0.12854045 | R152: =H152 -> 0.11538989 | S152: =I152 -> 0.11362157 | AD152: =LEFT(L152,4)+1 -> 2010 | AE152: =M152 -> -0.033873189 | AF152: =N152 -> 0.032518556 | AG152: =O152 -> 0.029346754 | AH152: =P152 -> 0.11197614 | AI152: =Q152 -> 0.12854045 | AJ152: =R152 -> 0.11538989 | AK152: =S152 -> 0.11362157
A153: 40268 | B153: 1q10 | C153: -0.12772884 | D153: 0.23528331 | E153: 0.025662304 | F153: 0.086055391 | G153: 0.096898318 | H153: 0.08742842 | I153: 0.085280084 | L153: ="20"&RIGHT(B153,2)&"Q"&LEFT(B153,1) -> 2010Q1 | M153: =C153 -> -0.12772884 | N153: =D153/10 -> 0.023528331 | O153: =E153 -> 0.025662304 | P153: =F153 -> 0.086055391 | Q153: =G153 -> 0.096898318 | R153: =H153 -> 0.08742842 | S153: =I153 -> 0.085280084 | AD153: =LEFT(L153,4)+1 -> 2011 | AE153: =M153 -> -0.12772884 | AF153: =N153 -> 0.023528331 | AG153: =O153 -> 0.025662304 | AH153: =P153 -> 0.086055391 | AI153: =Q153 -> 0.096898318 | AJ153: =R153 -> 0.08742842 | AK153: =S153 -> 0.085280084
A154: 40359 | B154: 2q10 | C154: -0.075634628 | D154: 0.27915299 | E154: 0.0030318924 | F154: 0.02212539 | G154: 0.025268456 | H154: 0.033297534 | I154: 0.036133974 | L154: ="20"&RIGHT(B154,2)&"Q"&LEFT(B154,1) -> 2010Q2 | M154: =C154 -> -0.075634628 | N154: =D154/10 -> 0.027915299 | O154: =E154 -> 0.0030318924 | P154: =F154 -> 0.02212539 | Q154: =G154 -> 0.025268456 | R154: =H154 -> 0.033297534 | S154: =I154 -> 0.036133974 | AD154: =LEFT(L154,4)+1 -> 2011 | AE154: =M154 -> -0.075634628 | AF154: =N154 -> 0.027915299 | AG154: =O154 -> 0.0030318924 | AH154: =P154 -> 0.02212539 | AI154: =Q154 -> 0.025268456 | AJ154: =R154 -> 0.033297534 | AK154: =S154 -> 0.036133974
A155: 40451 | B155: 3q10 | C155: 0.0049105092 | D155: 0.36839622 | E155: -0.010999363 | F155: 0.025502412 | G155: 0.024168257 | H155: 0.023356494 | I155: 0.023256193 | L155: ="20"&RIGHT(B155,2)&"Q"&LEFT(B155,1) -> 2010Q3 | M155: =C155 -> 0.0049105092 | N155: =D155/10 -> 0.036839622 | O155: =E155 -> -0.010999363 | P155: =F155 -> 0.025502412 | Q155: =G155 -> 0.024168257 | R155: =H155 -> 0.023356494 | S155: =I155 -> 0.023256193 | AD155: =LEFT(L155,4)+1 -> 2011 | AE155: =M155 -> 0.0049105092 | AF155: =N155 -> 0.036839622 | AG155: =O155 -> -0.010999363 | AH155: =P155 -> 0.025502412 | AI155: =Q155 -> 0.024168257 | AJ155: =R155 -> 0.023356494 | AK155: =S155 -> 0.023256193
... A210: 45473 | B210: 2q24 | C210: 0.037578746 | D210: -0.1767428 | E210: -0.067586547 | F210: -0.040001519 | G210: -0.020410624 | H210: -0.0095734509 | I210: -0.0028966043 | L210: ="20"&RIGHT(B210,2)&"Q"&LEFT(B210,1) -> 2024Q2 | M210: =C210 -> 0.037578746 | N210: =D210/10 -> -0.01767428 | O210: =E210 -> -0.067586547 | P210: =F210 -> -0.040001519 | Q210: =G210 -> -0.020410624 | R210: =H210 -> -0.0095734509 | S210: =I210 -> -0.0028966043 | AD210: =LEFT(L210,4)+1 -> 2025 | AE210: =M210 -> 0.037578746 | AF210: =N210 -> -0.01767428 | AG210: =O210 -> -0.067586547 | AH210: =P210 -> -0.040001519 | AI210: =Q210 -> -0.020410624 | AJ210: =R210 -> -0.0095734509 | AK210: =S210 -> -0.0028966043
A211: 45565 | B211: 3q24 | L211: ="20"&RIGHT(B211,2)&"Q"&LEFT(B211,1) -> 2024Q3 | M211: =C211 -> 0 | N211: =D211/10 -> 0 | O211: =E211 -> 0 | P211: =F211 -> 0 | Q211: =G211 -> 0 | R211: =H211 -> 0 | S211: =I211 -> 0 | AD211: =LEFT(L211,4)+1 -> 2025 | AE211: =M211 -> 0 | AF211: =N211 -> 0 | AG211: =O211 -> 0 | AH211: =P211 -> 0 | AI211: =Q211 -> 0 | AJ211: =R211 -> 0 | AK211: =S211 -> 0

Sheet EA_core_obs
A1: date | B1: g_sh | C1: b_liqtil_sh | D1: b_liqp_sh | E1: b_safetil_sh | F1: b_safep_sh | G1: mu_sh | H1: z_sh | I1: lambda_f_sh | J1: lambda_w_sh | K1: rm_sh | L1: sigma_omega_sh | M1: mu_e_sh | N1: gamma_sh | O1: pi_star_sh | P1: lr_sh | Q1: zp_sh | R1: tfp_sh | S1: gdpdef_sh | T1: corepce_sh | U1: gdp_sh | V1: gdi_sh | W1: BBB_sh | X1: AAA_sh | Y1: rm_shl1 | Z1: rm_shl2 | AA1: rm_shl3 | AB1: rm_shl4 | AC1: rm_shl5 | AD1: rm_shl6 | AE1: dettrend | AF1: detrendedMean | AH1: rm_sh | AI1: =Y1 -> rm_shl1 | AJ1: =Z1 -> rm_shl2 | AK1: =AA1 -> rm_shl3 | AL1: =AB1 -> rm_shl4 | AM1: =AC1 -> rm_shl5 | AN1: =AD1 -> rm_shl6 | AQ1: Plot | AR1: =A1 -> date | AS1: =AF1 -> detrendedMean | AT1: Monetary Policy | AU1: Fgsum | AV1: FG1 | AW1: FG2 | AX1: FG3 | AY1: FG4 | AZ1: FG5 | BA1: FG6 | BC1: date | BD1: rm_sh | BE1: Fgsum
A2: 39172 | B2: -0.0019508847 | C2: -0.00044949594 | D2: -0.13911193 | E2: 2.6700597e-07 | F2: 0.18028947 | G2: -0.0092832979 | H2: -9.5227129e-06 | I2: -0.33420427 | J2: -0.060491883 | K2: 0.024806955 | L2: -0.00020267534 | M2: 0 | N2: 0 | O2: 0.019158519 | P2: 0 | Q2: 7.7258442e-05 | R2: 0 | S2: 0 | T2: 0.50261524 | U2: 0 | V2: 0 | W2: 0 | X2: 0 | Y2: 0 | Z2: 0 | AA2: 0 | AB2: 0 | AC2: 0 | AD2: 0 | AE2: 0.036435471 | AF2: 0.22016319 | AH2: =K2+Y2-Y2/100 -> 0.024806955 | AI2: =Y2 -> 0 | AJ2: =Z2 -> 0 | AK2: =AA2 -> 0 | AL2: =AB2 -> 0 | AM2: =AC2 -> 0 | AN2: =AD2 -> 0 | AR2: =A2 -> 39172 | AS2: =AF2*4+2 -> 2.8806528 | AT2: =AH2 -> 0.024806955 | AU2: =SUM(AV2:BA2) -> 0 | AV2: =AI2 -> 0 | AW2: =AJ2 -> 0 | AX2: =AK2 -> 0 | AY2: =AL2 -> 0 | AZ2: =AM2 -> 0 | BA2: =AN2 -> 0 | BC2: =AR2 -> 39172 | BD2: =AT2 -> 0.024806955 | BE2: =AU2 -> 0
A3: 39263 | B3: -0.001910232 | C3: -0.00033353949 | D3: -0.14952585 | E3: 1.8081252e-07 | F3: 0.20476775 | G3: -0.0092487068 | H3: -1.5875485e-05 | I3: -0.40434241 | J3: -0.065233156 | K3: 0.025255502 | L3: -0.00021052273 | M3: 0 | N3: 0 | O3: 0.020245405 | P3: 0 | Q3: 9.7038271e-05 | R3: 0 | S3: 0 | T3: 0.41534977 | U3: 0 | V3: 0 | W3: 0 | X3: 0 | Y3: 0 | Z3: 0 | AA3: 0 | AB3: 0 | AC3: 0 | AD3: 0 | AE3: 0.035954254 | AF3: 0.070229362 | AH3: =K3+Y3-Y3/100 -> 0.025255502 | AI3: =Y3 -> 0 | AJ3: =Z3 -> 0 | AK3: =AA3 -> 0 | AL3: =AB3 -> 0 | AM3: =AC3 -> 0 | AN3: =AD3 -> 0 | AR3: =A3 -> 39263 | AS3: =AF3*4+2 -> 2.2809174 | AT3: =AH3 -> 0.025255502 | AU3: =SUM(AV3:BA3) -> 0 | AV3: =AI3 -> 0 | AW3: =AJ3 -> 0 | AX3: =AK3 -> 0 | AY3: =AL3 -> 0 | AZ3: =AM3 -> 0 | BA3: =AN3 -> 0 | BC3: =AR3 -> 39263 | BD3: =AT3 -> 0.025255502 | BE3: =AU3 -> 0
A4: 39355 | B4: -0.0019527526 | C4: -0.00042054317 | D4: -0.15990279 | E4: 2.0866553e-07 | F4: 0.22376056 | G4: -0.009266434 | H4: -6.2988432e-06 | I4: -0.009955934 | J4: -0.0645373 | K4: 0.023798391 | L4: -0.00017549804 | M4: 0 | N4: 0 | O4: 0.022058994 | P4: 0 | Q4: 0.00013361978 | R4: 0 | S4: 0 | T4: -0.31246178 | U4: 0 | V4: 0 | W4: 0 | X4: 0 | Y4: 0 | Z4: 0 | AA4: 0 | AB4: 0 | AC4: 0 | AD4: 0 | AE4: 0.035480661 | AF4: -0.25915581 | AH4: =K4+Y4-Y4/100 -> 0.023798391 | AI4: =Y4 -> 0 | AJ4: =Z4 -> 0 | AK4: =AA4 -> 0 | AL4: =AB4 -> 0 | AM4: =AC4 -> 0 | AN4: =AD4 -> 0 | AR4: =A4 -> 39355 | AS4: =AF4*4+2 -> 0.96337677 | AT4: =AH4 -> 0.023798391 | AU4: =SUM(AV4:BA4) -> 0 | AV4: =AI4 -> 0 | AW4: =AJ4 -> 0 | AX4: =AK4 -> 0 | AY4: =AL4 -> 0 | AZ4: =AM4 -> 0 | BA4: =AN4 -> 0 | BC4: =AR4 -> 39355 | BD4: =AT4 -> 0.023798391 | BE4: =AU4 -> 0
A5: 39447 | B5: -0.001819592 | C5: -0.00026552038 | D5: -0.1690069 | E5: 6.1493388e-08 | F5: 0.23796722 | G5: -0.0093067312 | H5: 1.4725119e-06 | I5: -0.51029866 | J5: -0.065204379 | K5: 0.024733448 | L5: -0.00022667152 | M5: 0 | N5: 0 | O5: 0.022562176 | P5: 0 | Q5: 0.00016303021 | R5: 0 | S5: 0 | T5: 1.294007 | U5: 0 | V5: 0 | W5: 0 | X5: 0 | Y5: 0 | Z5: 0 | AA5: 0 | AB5: 0 | AC5: 0 | AD5: 0 | AE5: 0.035014511 | AF5: 0.86907076 | AH5: =K5+Y5-Y5/100 -> 0.024733448 | AI5: =Y5 -> 0 | AJ5: =Z5 -> 0 | AK5: =AA5 -> 0 | AL5: =AB5 -> 0 | AM5: =AC5 -> 0 | AN5: =AD5 -> 0 | AR5: =A5 -> 39447 | AS5: =AF5*4+2 -> 5.476283 | AT5: =AH5 -> 0.024733448 | AU5: =SUM(AV5:BA5) -> 0 | AV5: =AI5 -> 0 | AW5: =AJ5 -> 0 | AX5: =AK5 -> 0 | AY5: =AL5 -> 0 | AZ5: =AM5 -> 0 | BA5: =AN5 -> 0 | BC5: =AR5 -> 39447 | BD5: =AT5 -> 0.024733448 | BE5: =AU5 -> 0
A6: 39538 | B6: -0.0017947097 | C6: -0.0003933734 | D6: -0.17379543 | E6: 4.1640913e-08 | F6: 0.24330441 | G6: -0.0094038734 | H6: -3.0191972e-05 | I6: -0.075682169 | J6: -0.059083667 | K6: 0.027431403 | L6: 4.5698247e-05 | M6: 0 | N6: 0 | O6: 0.024035226 | P6: 0 | Q6: 0.0001932567 | R6: 0 | S6: 0 | T6: 1.0447664 | U6: 0 | V6: 0 | W6: 0 | X6: 0 | Y6: 0 | Z6: 0 | AA6: 0 | AB6: 0 | AC6: 0 | AD6: 0 | AE6: 0.034555629 | AF6: 1.0750228 | AH6: =K6+Y6-Y6/100 -> 0.027431403 | AI6: =Y6 -> 0 | AJ6: =Z6 -> 0 | AK6: =AA6 -> 0 | AL6: =AB6 -> 0 | AM6: =AC6 -> 0 | AN6: =AD6 -> 0 | AR6: =A6 -> 39538 | AS6: =AF6*4+2 -> 6.3000912 | AT6: =AH6 -> 0.027431403 | AU6: =SUM(AV6:BA6) -> 0 | AV6: =AI6 -> 0 | AW6: =AJ6 -> 0 | AX6: =AK6 -> 0 | AY6: =AL6 -> 0 | AZ6: =AM6 -> 0 | BA6: =AN6 -> 0 | BC6: =AR6 -> 39538 | BD6: =AT6 -> 0.027431403 | BE6: =AU6 -> 0
A7: 39629 | B7: -0.0017283825 | C7: -0.00052098134 | D7: -0.17948205 | E7: -8.4770635e-08 | F7: 0.25457248 | G7: -0.0094675548 | H7: -2.4387526e-05 | I7: -0.53246487 | J7: -0.062762084 | K7: 0.025474549 | L7: 0.00015518565 | M7: 0 | N7: 0 | O7: 0.024579932 | P7: 0 | Q7: 0.00025217967 | R7: 0 | S7: 0 | T7: 0.55768634 | U7: 0 | V7: 0 | W7: 0 | X7: 0 | Y7: 0 | Z7: 0 | AA7: 0 | AB7: 0 | AC7: 0 | AD7: 0 | AE7: 0.034103845 | AF7: 0.10910267 | AH7: =K7+Y7-Y7/100 -> 0.025474549 | AI7: =Y7 -> 0 | AJ7: =Z7 -> 0 | AK7: =AA7 -> 0 | AL7: =AB7 -> 0 | AM7: =AC7 -> 0 | AN7: =AD7 -> 0 | AR7: =A7 -> 39629 | AS7: =AF7*4+2 -> 2.4364107 | AT7: =AH7 -> 0.025474549 | AU7: =SUM(AV7:BA7) -> 0 | AV7: =AI7 -> 0 | AW7: =AJ7 -> 0 | AX7: =AK7 -> 0 | AY7: =AL7 -> 0 | AZ7: =AM7 -> 0 | BA7: =AN7 -> 0 | BC7: =AR7 -> 39629 | BD7: =AT7 -> 0.025474549 | BE7: =AU7 -> 0
A8: 39721 | B8: -0.0015061545 | C8: -0.00082754778 | D8: -0.18355115 | E8: -2.1032052e-07 | F8: 0.26437332 | G8: -0.0096179459 | H8: -7.5678916e-06 | I8: -0.14485768 | J8: -0.050365823 | K8: 0.023972166 | L8: 0.00035591919 | M8: 0 | N8: 0 | O8: 0.026352006 | P8: 0 | Q8: 0.0002999625 | R8: 0 | S8: 0 | T8: -0.036013235 | U8: 0 | V8: 0 | W8: 0 | X8: 0 | Y8: 0 | Z8: 0 | AA8: 0 | AB8: 0 | AC8: 0 | AD8: 0 | AE8: 0.033658996 | AF8: -0.079941369 | AH8: =K8+Y8-Y8/100 -> 0.023972166 | AI8: =Y8 -> 0 | AJ8: =Z8 -> 0 | AK8: =AA8 -> 0 | AL8: =AB8 -> 0 | AM8: =AC8 -> 0 | AN8: =AD8 -> 0 | AR8: =A8 -> 39721 | AS8: =AF8*4+2 -> 1.6802345 | AT8: =AH8 -> 0.023972166 | AU8: =SUM(AV8:BA8) -> 0 | AV8: =AI8 -> 0 | AW8: =AJ8 -> 0 | AX8: =AK8 -> 0 | AY8: =AL8 -> 0 | AZ8: =AM8 -> 0 | BA8: =AN8 -> 0 | BC8: =AR8 -> 39721 | BD8: =AT8 -> 0.023972166 | BE8: =AU8 -> 0
A9: 39813 | B9: -0.0017549138 | C9: -0.00156211 | D9: -0.1933762 | E9: -1.8715314e-07 | F9: 0.25092315 | G9: -0.01007109 | H9: 4.9196496e-05 | I9: -0.040406385 | J9: -0.043813379 | K9: 0.021710964 | L9: 0.00096220758 | M9: 0 | N9: 0 | O9: 0.027999195 | P9: 0 | Q9: 0.00032064405 | R9: 0 | S9: 0 | T9: -0.34690997 | U9: 0 | V9: 0 | W9: 0 | X9: 0 | Y9: 0.00070843025 | Z9: -0.0015217668 | AA9: 0.0012434729 | AB9: -0.00011281199 | AC9: -0.00027900983 | AD9: -0.0006330498 | AE9: 0.033220923 | AF9: -0.31011519 | AH9: =K9+Y9-Y9/100 -> 0.02241231 | AI9: =Y9/1010 -> 7.0141609e-07 | AJ9: =Z9 -> -0.0015217668 | AK9: =AA9 -> 0.0012434729 | AL9: =AB9 -> -0.00011281199 | AM9: =AC9 -> -0.00027900983 | AN9: =AD9 -> -0.0006330498 | AR9: =A9 -> 39813 | AS9: =AF9*4+2 -> 0.75953925 | AT9: =AH9 -> 0.02241231 | AU9: =SUM(AV9:BA9) -> -0.0013024641 | AV9: =AI9 -> 7.0141609e-07 | AW9: =AJ9 -> -0.0015217668 | AX9: =AK9 -> 0.0012434729 | AY9: =AL9 -> -0.00011281199 | AZ9: =AM9 -> -0.00027900983 | BA9: =AN9 -> -0.0006330498 | BC9: =AR9 -> 39813 | BD9: =AT9 -> 0.02241231 | BE9: =AU9 -> -0.0013024641
A10: 39903 | B10: -0.0019454651 | C10: -0.0020700598 | D10: -0.190723 | E10: -1.6006965e-07 | F10: 0.24064261 | G10: -0.010410226 | H10: 5.9186259e-05 | I10: -0.45255197 | J10: -0.040579955 | K10: 0.025697384 | L10: 0.0014714383 | M10: 0 | N10: 0 | O10: 0.028632362 | P10: 0 | Q10: 0.00026107654 | R10: 0 | S10: 0 | T10: -0.61148125 | U10: 0 | V10: 0 | W10: 0 | X10: 0 | Y10: -0.017335051 | Z10: 0.00028225495 | AA10: 0.0015825516 | AB10: -0.00047262247 | AC10: -0.00092929223 | AD10: -0.0029323275 | AE10: 0.032789475 | AF10: -1.0185632 | AH10: =K10+Y10-Y10/100 -> 0.0085356841 | AI10: =Y10/1010 -> -1.7163416e-05 | AJ10: =Z10 -> 0.00028225495 | AK10: =AA10 -> 0.0015825516 | AL10: =AB10 -> -0.00047262247 | AM10: =AC10 -> -0.00092929223 | AN10: =AD10 -> -0.0029323275 | AR10: =A10 -> 39903 | AS10: =AF10*4+2 -> -2.074253 | AT10: =AH10 -> 0.0085356841 | AU10: =SUM(AV10:BA10) -> -0.0024865991 | AV10: =AI10 -> -1.7163416e-05 | AW10: =AJ10 -> 0.00028225495 | AX10: =AK10 -> 0.0015825516 | AY10: =AL10 -> -0.00047262247 | AZ10: =AM10 -> -0.00092929223 | BA10: =AN10 -> -0.0029323275 | BC10: =AR10 -> 39903 | BD10: =AT10 -> 0.0085356841 | BE10: =AU10 -> -0.0024865991
A11: 39994 | B11: -0.0020344507 | C11: -0.002721877 | D11: -0.17909841 | E11: -5.3592286e-08 | F11: 0.22222929 | G11: -0.010635415 | H11: -1.2502908e-05 | I11: -0.42127389 | J11: -0.029536743 | K11: 0.047202925 | L11: 0.0015929992 | M11: 0 | N11: 0 | O11: 0.029097626 | P11: 0 | Q11: 0.00016675153 | R11: 0 | S11: 0 | T11: -0.42917612 | U11: 0 | V11: 0 | W11: 0 | X11: 0 | Y11: -0.041929311 | Z11: 0.003121548 | AA11: 0.0014838274 | AB11: -0.001187285 | AC11: -0.0011340987 | AD11: -0.0063679069 | AE11: 0.032364504 | AF11: -0.80288902 | AH11: =K11+Y11-Y11/100 -> 0.0056929076 | AI11: =Y11/1010 -> -4.1514169e-05 | AJ11: =Z11 -> 0.003121548 | AK11: =AA11 -> 0.0014838274 | AL11: =AB11 -> -0.001187285 | AM11: =AC11 -> -0.0011340987 | AN11: =AD11 -> -0.0063679069 | AR11: =A11 -> 39994 | AS11: =AF11*4+2 -> -1.2115561 | AT11: =AH11 -> 0.0056929076 | AU11: =SUM(AV11:BA11) -> -0.0041254295 | AV11: =AI11 -> -4.1514169e-05 | AW11: =AJ11 -> 0.003121548 | AX11: =AK11 -> 0.0014838274 | AY11: =AL11 -> -0.001187285 | AZ11: =AM11 -> -0.0011340987 | BA11: =AN11 -> -0.0063679069 | BC11: =AR11 -> 39994 | BD11: =AT11 -> 0.0056929076 | BE11: =AU11 -> -0.0041254295
A12: 40086 | B12: -0.002067631 | C12: -0.00337687 | D12: -0.15673999 | E12: 2.3187976e-07 | F12: 0.19859034 | G12: -0.01073315 | H12: -2.8778658e-05 | I12: -0.042175304 | J12: -0.014411846 | K12: 0.069653433 | L12: 0.0015007486 | M12: 0 | N12: 0 | O12: 0.029915693 | P12: 0 | Q12: 0.00013276591 | R12: 0 | S12: 0 | T12: -1.2045993 | U12: 0 | V12: 0 | W12: 0 | X12: 0 | Y12: -0.060882389 | Z12: 0.0045827932 | AA12: 0.00087449553 | AB12: -0.0024357544 | AC12: -0.0019012159 | AD12: -0.011224735 | AE12: 0.031945867 | AF12: -1.19785 | AH12: =K12+Y12-Y12/100 -> 0.0093798676 | AI12: =Y12/1010 -> -6.0279593e-05 | AJ12: =Z12 -> 0.0045827932 | AK12: =AA12 -> 0.00087449553 | AL12: =AB12 -> -0.0024357544 | AM12: =AC12 -> -0.0019012159 | AN12: =AD12 -> -0.011224735 | AR12: =A12 -> 40086 | AS12: =AF12*4+2 -> -2.7913999 | AT12: =AH12 -> 0.0093798676 | AU12: =SUM(AV12:BA12) -> -0.010164697 | AV12: =AI12 -> -6.0279593e-05 | AW12: =AJ12 -> 0.0045827932 | AX12: =AK12 -> 0.00087449553 | AY12: =AL12 -> -0.0024357544 | AZ12: =AM12 -> -0.0019012159 | BA12: =AN12 -> -0.011224735 | BC12: =AR12 -> 40086 | BD12: =AT12 -> 0.0093798676 | BE12: =AU12 -> -0.010164697
A13: 40178 | B13: -0.0019039885 | C13: -0.0034857199 | D13: -0.13826055 | E13: 4.5224278e-07 | F13: 0.18680347 | G13: -0.010817037 | H13: -7.4483907e-06 | I13: -0.55025309 | J13: -0.0084786115 | K13: 0.085800489 | L13: 0.0014108205 | M13: 0 | N13: 0 | O13: 0.029825542 | P13: 0 | Q13: 0.00011992906 | R13: 0 | S13: 0 | T13: -0.66781616 | U13: 0 | V13: 0 | W13: 0 | X13: 0 | Y13: -0.075357566 | Z13: 0.0064716328 | AA13: 0.00040512964 | AB13: -0.0033562359 | AC13: -0.0019804733 | AD13: -0.016332099 | AE13: 0.031533427 | AF13: -1.1562081 | AH13: =K13+Y13-Y13/100 -> 0.011196499 | AI13: =Y13/1010 -> -7.4611451e-05 | AJ13: =Z13 -> 0.0064716328 | AK13: =AA13 -> 0.00040512964 | AL13: =AB13 -> -0.0033562359 | AM13: =AC13 -> -0.0019804733 | AN13: =AD13 -> -0.016332099 | AR13: =A13 -> 40178 | AS13: =AF13*4+2 -> -2.6248325 | AT13: =AH13 -> 0.011196499 | AU13: =SUM(AV13:BA13) -> -0.014866657 | AV13: =AI13 -> -7.4611451e-05 | AW13: =AJ13 -> 0.0064716328 | AX13: =AK13 -> 0.00040512964 | AY13: =AL13 -> -0.0033562359 | AZ13: =AM13 -> -0.0019804733 | BA13: =AN13 -> -0.016332099 | BC13: =AR13 -> 40178 | BD13: =AT13 -> 0.011196499 | BE13: =AU13 -> -0.014866657
A14: 40268 | B14: -0.001768788 | C14: -0.0035200668 | D14: -0.12706516 | E14: 5.26805e-07 | F14: 0.17185687 | G14: -0.010899309 | H14: -1.0561186e-05 | I14: -0.44949232 | J14: -0.011643689 | K14: 0.10182928 | L14: 0.0013920941 | M14: 0 | N14: 0 | O14: 0.030030724 | P14: 0 | Q14: 0.00010142116 | R14: 0 | S14: 0 | T14: -0.76982936 | U14: 0 | V14: 0 | W14: 0 | X14: 0 | Y14: -0.085165599 | Z14: 0.0094093821 | AA14: 0.0013787772 | AB14: -0.0031525209 | AC14: -0.0012348492 | AD14: -0.020652981 | AE14: 0.031127049 | AF14: -1.15807 | AH14: =K14+Y14-Y14/100 -> 0.017515336 | AI14: =Y14/1010 -> -8.4322375e-05 | AJ14: =Z14 -> 0.0094093821 | AK14: =AA14 -> 0.0013787772 | AL14: =AB14 -> -0.0031525209 | AM14: =AC14 -> -0.0012348492 | AN14: =AD14 -> -0.020652981 | AR14: =A14 -> 40268 | AS14: =AF14*4+2 -> -2.6322801 | AT14: =AH14 -> 0.017515336 | AU14: =SUM(AV14:BA14) -> -0.014336514 | AV14: =AI14 -> -8.4322375e-05 | AW14: =AJ14 -> 0.0094093821 | AX14: =AK14 -> 0.0013787772 | AY14: =AL14 -> -0.0031525209 | AZ14: =AM14 -> -0.0012348492 | BA14: =AN14 -> -0.020652981 | BC14: =AR14 -> 40268 | BD14: =AT14 -> 0.017515336 | BE14: =AU14 -> -0.014336514
A15: 40359 | B15: -0.0016055442 | C15: -0.0034126173 | D15: -0.12024167 | E15: 6.1831082e-07 | F15: 0.14974555 | G15: -0.010999744 | H15: 1.1225093e-05 | I15: -0.3859079 | J15: -0.010546563 | K15: 0.1137369 | L15: 0.0012674654 | M15: 0 | N15: 0 | O15: 0.03029255 | P15: 0 | Q15: 8.5443216e-05 | R15: 0 | S15: 0 | T15: -0.74550929 | U15: 0 | V15: 0 | W15: 0 | X15: 0 | Y15: -0.094219354 | Z15: 0.012620793 | AA15: 0.0037813698 | AB15: -0.0012855556 | AC15: 0.00056690679 | AD15: -0.023176605 | AE15: 0.030726605 | AF15: -1.0735987 | AH15: =K15+Y15-Y15/100 -> 0.02045974 | AI15: =Y15/1010 -> -9.3286489e-05 | AJ15: =Z15 -> 0.012620793 | AK15: =AA15 -> 0.0037813698 | AL15: =AB15 -> -0.0012855556 | AM15: =AC15 -> 0.00056690679 | AN15: =AD15 -> -0.023176605 | AR15: =A15 -> 40359 | AS15: =AF15*4+2 -> -2.2943948 | AT15: =AH15 -> 0.02045974 | AU15: =SUM(AV15:BA15) -> -0.007586378 | AV15: =AI15 -> -9.3286489e-05 | AW15: =AJ15 -> 0.012620793 | AX15: =AK15 -> 0.0037813698 | AY15: =AL15 -> -0.0012855556 | AZ15: =AM15 -> 0.00056690679 | BA15: =AN15 -> -0.023176605 | BC15: =AR15 -> 40359 | BD15: =AT15 -> 0.02045974 | BE15: =AU15 -> -0.007586378
A16: 40451 | B16: -0.0015195804 | C16: -0.0032687084 | D16: -0.1153459 | E16: 7.2160802e-07 | F16: 0.14285232 | G16: -0.011072744 | H16: 8.8154421e-06 | I16: 0.030795735 | J16: -0.015183955 | K16: 0.12312668 | L16: 0.0013868123 | M16: 0 | N16: 0 | O16: 0.031305321 | P16: 0 | Q16: 5.5392826e-05 | R16: 0 | S16: 0 | T16: -0.77668895 | U16: 0 | V16: 0 | W16: 0 | X16: 0 | Y16: -0.1056787 | Z16: 0.014564632 | AA16: 0.004651098 | AB16: -0.00028653286 | AC16: 0.0016313845 | AD16: -0.024586607 | AE16: 0.030331971 | AF16: -0.6876071 | AH16: =K16+Y16-Y16/100 -> 0.018504761 | AI16: =Y16/1010 -> -0.00010463238 | AJ16: =Z16 -> 0.014564632 | AK16: =AA16 -> 0.004651098 | AL16: =AB16 -> -0.00028653286 | AM16: =AC16 -> 0.0016313845 | AN16: =AD16 -> -0.024586607 | AR16: =A16 -> 40451 | AS16: =AF16*4+2 -> -0.75042838 | AT16: =AH16 -> 0.018504761 | AU16: =SUM(AV16:BA16) -> -0.0041306584 | AV16: =AI16 -> -0.00010463238 | AW16: =AJ16 -> 0.014564632 | AX16: =AK16 -> 0.004651098 | AY16: =AL16 -> -0.00028653286 | AZ16: =AM16 -> 0.0016313845 | BA16: =AN16 -> -0.024586607 | BC16: =AR16 -> 40451 | BD16: =AT16 -> 0.018504761 | BE16: =AU16 -> -0.0041306584
A17: 40543 | B17: -0.0013371114 | C17: -0.0030069557 | D17: -0.11680429 | E17: 7.5777917e-07 | F17: 0.1604768 | G17: -0.011130844 | H17: -1.3967529e-05 | I17: -0.53120714 | J17: -0.020569429 | K17: 0.13514114 | L17: 0.0013693178 | M17: 0 | N17: 0 | O17: 0.031637455 | P17: 0 | Q17: 2.1527973e-05 | R17: 0 | S17: 0 | T17: -0.1423499 | U17: 0 | V17: 0 | W17: 0 | X17: 0 | Y17: -0.12188145 | Z17: 0.016047211 | AA17: 0.0046091224 | AB17: -0.0002321107 | AC17: 0.0015502993 | AD17: -0.026035114 | AE17: 0.029943024 | AF17: -0.60589549 | AH17: =K17+Y17-Y17/100 -> 0.014478505 | AI17: =Y17/1010 -> -0.00012067471 | AJ17: =Z17 -> 0.016047211 | AK17: =AA17 -> 0.0046091224 | AL17: =AB17 -> -0.0002321107 | AM17: =AC17 -> 0.0015502993 | AN17: =AD17 -> -0.026035114 | AR17: =A17 -> 40543 | AS17: =AF17*4+2 -> -0.42358195 | AT17: =AH17 -> 0.014478505 | AU17: =SUM(AV17:BA17) -> -0.0041812674 | AV17: =AI17 -> -0.00012067471 | AW17: =AJ17 -> 0.016047211 | AX17: =AK17 -> 0.0046091224 | AY17: =AL17 -> -0.0002321107 | AZ17: =AM17 -> 0.0015502993 | BA17: =AN17 -> -0.026035114 | BC17: =AR17 -> 40543 | BD17: =AT17 -> 0.014478505 | BE17: =AU17 -> -0.0041812674
A18: 40633 | B18: -0.001532286 | C18: -0.0030637023 | D18: -0.12140879 | E18: 1.0029129e-06 | F18: 0.19879283 | G18: -0.01119554 | H18: -2.7882324e-05 | I18: -0.18688172 | J18: -0.015301681 | K18: 0.15058927 | L18: 0.0012852384 | M18: 0 | N18: 0 | O18: 0.032742452 | P18: 0 | Q18: 1.4912948e-05 | R18: 0 | S18: 0 | T18: -0.13549147 | U18: 0 | V18: 0 | W18: 0 | X18: 0 | Y18: -0.14325903 | Z18: 0.015494468 | AA18: 0.0021559779 | AB18: -0.0022332803 | AC18: -0.00024279061 | AD18: -0.028997077 | AE18: 0.029559647 | AF18: -0.22396376 | AH18: =K18+Y18-Y18/100 -> 0.0087628235 | AI18: =Y18/1010 -> -0.00014184063 | AJ18: =Z18 -> 0.015494468 | AK18: =AA18 -> 0.0021559779 | AL18: =AB18 -> -0.0022332803 | AM18: =AC18 -> -0.00024279061 | AN18: =AD18 -> -0.028997077 | AR18: =A18 -> 40633 | AS18: =AF18*4+2 -> 1.104145 | AT18: =AH18 -> 0.0087628235 | AU18: =SUM(AV18:BA18) -> -0.013964543 | AV18: =AI18 -> -0.00014184063 | AW18: =AJ18 -> 0.015494468 | AX18: =AK18 -> 0.0021559779 | AY18: =AL18 -> -0.0022332803 | AZ18: =AM18 -> -0.00024279061 | BA18: =AN18 -> -0.028997077 | BC18: =AR18 -> 40633 | BD18: =AT18 -> 0.0087628235 | BE18: =AU18 -> -0.013964543
A19: 40724 | B19: -0.0013887264 | C19: -0.0026312904 | D19: -0.11897872 | E19: 1.2248825e-06 | F19: 0.22837771 | G19: -0.011258261 | H19: 2.002581e-05 | I19: -0.30315083 | J19: -0.011646391 | K19: 0.16881612 | L19: 0.0013859892 | M19: 0 | N19: 0 | O19: 0.033785775 | P19: 0 | Q19: 2.0237128e-05 | R19: 0 | S19: 0 | T19: 0.07829521 | U19: 0 | V19: 0 | W19: 0 | X19: 0 | Y19: -0.1718397 | Z19: 0.016461217 | AA19: 0.00069928078 | AB19: -0.0031950007 | AC19: -0.00097890427 | AD19: -0.032208723 | AE19: 0.029181729 | AF19: -0.10335766 | AH19: =K19+Y19-Y19/100 -> -0.001305185 | AI19: =Y19/1010 -> -0.00017013832 | AJ19: =Z19 -> 0.016461217 | AK19: =AA19 -> 0.00069928078 | AL19: =AB19 -> -0.0031950007 | AM19: =AC19 -> -0.00097890427 | AN19: =AD19 -> -0.032208723 | AR19: =A19 -> 40724 | AS19: =AF19*4+2 -> 1.5865694 | AT19: =AH19 -> -0.001305185 | AU19: =SUM(AV19:BA19) -> -0.019392268 | AV19: =AI19 -> -0.00017013832 | AW19: =AJ19 -> 0.016461217 | AX19: =AK19 -> 0.00069928078 | AY19: =AL19 -> -0.0031950007 | AZ19: =AM19 -> -0.00097890427 | BA19: =AN19 -> -0.032208723 | BC19: =AR19 -> 40724 | BD19: =AT19 -> -0.001305185 | BE19: =AU19 -> -0.019392268
A20: 40816 | B20: -0.0015124037 | C20: -0.0024314791 | D20: -0.11554017 | E20: 1.2930845e-06 | F20: 0.18396915 | G20: -0.01133035 | H20: -1.4453412e-05 | I20: -0.059234404 | J20: -0.015603639 | K20: 0.19455535 | L20: 0.0014810747 | M20: 0 | N20: 0 | O20: 0.034028768 | P20: 0 | Q20: -4.934565e-06 | R20: 0 | S20: 0 | T20: -0.10252246 | U20: 0 | V20: 0 | W20: 0 | X20: 0 | Y20: -0.19596717 | Z20: 0.022855452 | AA20: 0.0035417646 | AB20: -0.00062814047 | AC20: 0.0010605802 | AD20: -0.033246181 | AE20: 0.028809157 | AF20: -0.069799206 | AH20: =K20+Y20-Y20/100 -> 0.00054784675 | AI20: =Y20/1010 -> -0.0001940269 | AJ20: =Z20 -> 0.022855452 | AK20: =AA20 -> 0.0035417646 | AL20: =AB20 -> -0.00062814047 | AM20: =AC20 -> 0.0010605802 | AN20: =AD20 -> -0.033246181 | AR20: =A20 -> 40816 | AS20: =AF20*4+2 -> 1.7208032 | AT20: =AH20 -> 0.00054784675 | AU20: =SUM(AV20:BA20) -> -0.0066105514 | AV20: =AI20 -> -0.0001940269 | AW20: =AJ20 -> 0.022855452 | AX20: =AK20 -> 0.0035417646 | AY20: =AL20 -> -0.00062814047 | AZ20: =AM20 -> 0.0010605802 | BA20: =AN20 -> -0.033246181 | BC20: =AR20 -> 40816 | BD20: =AT20 -> 0.00054784675 | BE20: =AU20 -> -0.0066105514
... A132: 51043 | B132: -0.043141873 | C132: -0.00014191675 | D132: -0.060150045 | E132: 0.00016375639 | F132: 0.077003819 | G132: -0.017761409 | H132: 0.10657899 | I132: -0.12938709 | J132: -0.23383062 | K132: -0.0013647494 | L132: 0.028622522 | M132: 0 | N132: 0 | O132: 0.44750605 | P132: 0 | Q132: 0.30446726 | R132: 0 | S132: 0 | T132: 0 | U132: 0 | V132: 0 | W132: 0 | X132: 0 | Y132: 0.0014171204 | Z132: -0.0014470184 | AA132: 0.00054189822 | AB132: -0.00029329794 | AC132: 0.0013717805 | AD132: 0.0037302372 | AE132: -0.072867892 | AF132: 0.418171 | AH132: =K132+Y132-Y132/100 -> 3.8199787e-05 | AI132: =Y132/1010 -> 1.4030895e-06 | AJ132: =Z132 -> -0.0014470184 | AK132: =AA132 -> 0.00054189822 | AL132: =AB132 -> -0.00029329794 | AM132: =AC132 -> 0.0013717805 | AN132: =AD132 -> 0.0037302372 | AR132: =A132 -> 51043 | AS132: =AF132*4+2 -> 3.672684 | AT132: =AH132 -> 3.8199787e-05 | AU132: =SUM(AV132:BA132) -> 0.0039050027 | AV132: =AI132 -> 1.4030895e-06 | AW132: =AJ132 -> -0.0014470184 | AX132: =AK132 -> 0.00054189822 | AY132: =AL132 -> -0.00029329794 | AZ132: =AM132 -> 0.0013717805 | BA132: =AN132 -> 0.0037302372 | BC132: =AR132 -> 51043 | BD132: =AT132 -> 3.8199787e-05 | BE132: =AU132 -> 0.0039050027

Sheet Chart NA - DSGE Raw Data
A2: date | B2: obs_gdp | C2: obs_gdpdeflator | D2: obs_nominalrate | F2: obs_longinflation | G2: obs_longrate
A3: 21823 | B3: -0.30408411 | C3: 0.38618932 | D3: 0.8925
A4: 21915 | B4: -0.085396239 | C4: 0.3912113 | D4: 0.9975
A5: 22006 | B5: 1.8569299 | C5: 0.39616873 | D5: 0.9825
A6: 22097 | B6: -0.91034251 | C6: 0.25246817 | D6: 0.925
A7: 22189 | B7: 0.12315845 | C7: 0.34207927 | D7: 0.735
A8: 22281 | B8: -1.6584688 | C8: 0.29595338 | D8: 0.575
A9: 22371 | B9: 0.30422427 | C9: 0.21818657 | D9: 0.4975
A10: 22462 | B10: 1.3165542 | C10: 0.23050337 | D10: 0.4325
A11: 22554 | B11: 1.5360756 | C11: 0.25549324 | D11: 0.42
A12: 22646 | B12: 1.5758415 | C12: 0.31209223 | D12: 0.6
A13: 22736 | B13: 1.399261 | C13: 0.51378122 | D13: 0.615
A14: 22827 | B14: 0.52884844 | C14: 0.16435935 | D14: 0.6525
... A50: 26114 | B50: -0.010363799 | C50: 1.3054021 | D50: 1.1425
A51: 26206 | B51: 0.2690258 | C51: 1.0125119 | D51: 1.37 | G51: 1.5257
A52: 26298 | B52: -0.32043651 | C52: 0.83057731 | D52: 1.1875 | G52: 1.491925
A53: 26389 | B53: 1.2602782 | C53: 1.5126649 | D53: 0.8875 | G53: 1.5448
A54: 26480 | B54: 1.6860456 | C54: 0.62055319 | D54: 1.075 | G54: 1.53105
A55: 26572 | B55: 0.3852877 | C55: 0.9507066 | D55: 1.185 | G55: 1.5853
A56: 26664 | B56: 1.1057907 | C56: 1.2670582 | D56: 1.2875 | G56: 1.569
A57: 26754 | B57: 1.8936626 | C57: 1.1457007 | D57: 1.635 | G57: 1.645375
A58: 26845 | B58: 0.53249332 | C58: 1.5276802 | D58: 1.955 | G58: 1.66725
A59: 26937 | B59: -1.06861 | C59: 1.9262302 | D59: 2.64 | G59: 1.690725
A60: 27029 | B60: 0.40548359 | C60: 1.9731808 | D60: 2.5 | G60: 1.684425
A61: 27119 | B61: -1.3981815 | C61: 1.869599 | D61: 2.3325 | G61: 1.835475
A62: 27210 | B62: -0.29322437 | C62: 2.3358372 | D62: 2.8125 | G62: 1.929325
... A83: 29128 | B83: 0.32743149 | C83: 2.1632932 | D83: 2.735 | G83: 2.270025
A84: 29220 | B84: -0.15362911 | C84: 1.8384466 | D84: 3.395 | F84: 1.6 | G84: 2.4906
A85: 29311 | B85: -0.08319259 | C85: 2.0793092 | D85: 3.7675 | G85: 2.978425
A86: 29402 | B86: -2.4706014 | C86: 2.3510302 | D86: 3.1675 | F86: 1.8375 | G86: 2.4489
A87: 29494 | B87: -0.49739301 | C87: 2.2090655 | D87: 2.455 | G87: 2.878775
A88: 29586 | B88: 1.4763561 | C88: 2.5713717 | D88: 3.9625 | F88: 1.9375 | G88: 2.96035
A89: 29676 | B89: 1.5757765 | C89: 2.6000618 | D89: 4.15 | G89: 3.210275
A90: 29767 | B90: -1.0984483 | C90: 1.9622379 | D90: 4.4475 | F90: 1.825 | G90: 3.264225
A91: 29859 | B91: 0.8416346 | C91: 1.8647478 | D91: 4.3975 | G91: 3.723025
A92: 29951 | B92: -1.4356505 | C92: 1.7132211 | D92: 3.3975 | F92: 1.6375 | G92: 3.37825
A93: 30041 | B93: -1.8983795 | C93: 1.3662426 | D93: 3.5525 | G93: 3.342825
A94: 30132 | B94: 0.12845338 | C94: 1.2906547 | D94: 3.6275 | F94: 1.3 | G94: 3.398
A95: 30224 | B95: -0.70404248 | C95: 1.4087662 | D95: 2.7525 | G95: 2.90445
A96: 30316 | B96: -0.27615918 | C96: 1.0313596 | D96: 2.32 | F96: 1.2875 | G96: 2.6224
A97: 30406 | B97: 0.99738501 | C97: 0.75275151 | D97: 2.165 | F97: 1.2 | G97: 2.653475
A98: 30497 | B98: 1.9450419 | C98: 0.73866867 | D98: 2.2 | G98: 2.7268
A99: 30589 | B99: 1.6751664 | C99: 1.0581219 | D99: 2.365 | G99: 2.837275
A100: 30681 | B100: 1.765739 | C100: 0.7546419 | D100: 2.3575 | F100: 1.175 | G100: 2.9111
A101: 30772 | B101: 1.6376035 | C101: 1.0083772 | D101: 2.4225 | F101: 1.275 | G101: 3.060925
A102: 30863 | B102: 1.4185504 | C102: 0.85164394 | D102: 2.6375 | G102: 3.3661
A103: 30955 | B103: 0.66661449 | C103: 0.88487172 | D103: 2.8475 | G103: 3.021825
A104: 31047 | B104: 0.52562947 | C104: 0.74482992 | D104: 2.315 | F104: 1.175 | G104: 2.86935
A105: 31137 | B105: 0.67391324 | C105: 0.98389258 | D105: 2.12 | F105: 0.9625 | G105: 2.900725
A106: 31228 | B106: 0.58741275 | C106: 0.64138315 | D106: 1.98 | G106: 2.585725
A107: 31320 | B107: 1.2259866 | C107: 0.60199666 | D107: 1.975 | G107: 2.612675
A108: 31412 | B108: 0.45245779 | C108: 0.5574423 | D108: 2.025 | F108: 1.0125 | G108: 2.29525
A109: 31502 | B109: 0.64152083 | C109: 0.49614375 | D109: 1.9575 | F109: 0.875 | G109: 1.877275
A110: 31593 | B110: 0.16244968 | C110: 0.37775003 | D110: 1.73 | G110: 1.93435
A111: 31685 | B111: 0.66664551 | C111: 0.40906955 | D111: 1.5525 | G111: 1.97845
A112: 31777 | B112: 0.24959199 | C112: 0.54347438 | D112: 1.5675 | F112: 0.875 | G112: 1.8907
A113: 31867 | B113: 0.45396977 | C113: 0.63763794 | D113: 1.555 | F113: 0.925 | G113: 1.9158
A114: 31958 | B114: 0.78974225 | C114: 0.69031186 | D114: 1.6625 | G114: 2.12505
A115: 32050 | B115: 0.5808548 | C115: 0.75500476 | D115: 1.71 | G115: 2.410475
A116: 32142 | B116: 1.4206977 | C116: 0.79401824 | D116: 1.73 | F116: 1 | G116: 2.23695
A117: 32233 | B117: 0.23668349 | C117: 0.78037784 | D117: 1.6675 | F117: 0.95 | G117: 2.190725
A118: 32324 | B118: 1.0261362 | C118: 0.96835706 | D118: 1.7875 | G118: 2.223725
A119: 32416 | B119: 0.30526185 | C119: 1.1888239 | D119: 1.995 | G119: 2.2176
A120: 32508 | B120: 1.0471089 | C120: 0.86004237 | D120: 2.1175 | F120: 0.9625 | G120: 2.2516
A121: 32598 | B121: 0.7344863 | C121: 1.037276 | D121: 2.3625 | F121: 0.9375 | G121: 2.268475
A122: 32689 | B122: 0.48391105 | C122: 1.0599653 | D122: 2.4325 | G122: 2.020575
A123: 32781 | B123: 0.46408218 | C123: 0.72716152 | D123: 2.27 | G123: 2.062825
A124: 32873 | B124: -0.077196821 | C124: 0.70980748 | D124: 2.1525 | F124: 0.925 | G124: 1.977675
A125: 32963 | B125: 0.81351513 | C125: 1.0733186 | D125: 2.0625 | F125: 0.8625 | G125: 2.141
A126: 33054 | B126: 0.090763781 | C126: 1.1143835 | D126: 2.06 | G126: 2.096325
A127: 33146 | B127: -0.20120596 | C127: 0.85245976 | D127: 2.04 | G127: 2.2162
A128: 33238 | B128: -1.1813362 | C128: 0.74206882 | D128: 1.935 | F128: 0.9125 | G128: 2.054825
A129: 33328 | B129: -0.73274762 | C129: 0.97434034 | D129: 1.6075 | F129: 0.8875 | G129: 2.0437
A130: 33419 | B130: 0.5147953 | C130: 0.73112351 | D130: 1.465 | G130: 2.110025
A131: 33511 | B131: 0.24333858 | C131: 0.77943226 | D131: 1.4125 | G131: 1.928225
A132: 33603 | B132: 0.091240538 | C132: 0.5911092 | D132: 1.205 | F132: 0.875 | G132: 1.7813
A133: 33694 | B133: 0.93477162 | C133: 0.37069314 | D133: 1.005 | F133: 0.8 | G133: 1.9399
A134: 33785 | B134: 0.82402613 | C134: 0.59986065 | D134: 0.9425 | F134: 0.85 | G134: 1.89465
A135: 33877 | B135: 0.73027323 | C135: 0.48813267 | D135: 0.815 | F135: 0.8125 | G135: 1.751125
A136: 33969 | B136: 0.78730875 | C136: 0.68509712 | D136: 0.7575 | F136: 0.775 | G136: 1.773675
A137: 34059 | B137: -0.083962687 | C137: 0.55949272 | D137: 0.76 | F137: 0.75 | G137: 1.63275
A138: 34150 | B138: 0.33092577 | C138: 0.59388273 | D138: 0.75 | F138: 0.8 | G138: 1.522725
A139: 34242 | B139: 0.2279217 | C139: 0.5919297 | D139: 0.765 | F139: 0.7375 | G139: 1.4198
A140: 34334 | B140: 1.1023308 | C140: 0.54366058 | D140: 0.7475 | F140: 0.7375 | G140: 1.5183
A141: 34424 | B141: 0.71592769 | C141: 0.47771037 | D141: 0.8025 | F141: 0.7375 | G141: 1.7449
A142: 34515 | B142: 1.0969236 | C142: 0.48155909 | D142: 0.985 | F142: 0.75 | G142: 1.87925
A143: 34607 | B143: 0.3315289 | C143: 0.5720883 | D143: 1.1225 | F143: 0.75 | G143: 1.924025
... A265: 45747 | B265: -0.36381372 | C265: 0.92398346 | D265: 1.0825 | F265: 0.45 | G265: 1.064275
A266: 45838 | B266: 0.4932566 | C266: 0.49317485 | D266: 1.0825

Sheet DSGE HVD wFG - difference
A1: date | B1: g | C1: b_liq | D1: b_safe | E1: FF | F1: z | G1: p-mkp | H1: w-mkp | I1: pol | J1: fg1 | K1: fg2 | L1: fg3 | M1: fg4 | N1: fg5 | O1: fg6 | P1: pi-LR | Q1: mu | R1: me | S1: zp | T1: dt | U1: DSGE r* | X1: Chart | Y1: Date | Z1: Government | AA1: Liquidity | AB1: Safety | AC1: Technology | AD1: Financial Frictions | AE1: Investment Specific Technology | AF1: Price Markups | AG1: Wage Markups | AH1: Others + Initial condition | AI1: DSGE r* (with FG)
A2: 39172 | B2: -0.078284074 | C2: -3.3536928 | D2: 4.0625681 | E2: -0.078929587 | F2: -0.00021463587 | G2: -1.7325996e-14 | H2: 4.9828714e-14 | I2: 9.7037389e-14 | J2: 0 | K2: 0 | L2: 0 | M2: 0 | N2: 0 | O2: 0 | P2: 1.0116916e-14 | Q2: -0.079101283 | R2: 0 | S2: 0.00018951412 | T2: 0.75299375 | U2: =+SUM(B2:T2) -> 1.225529 | Y2: =+A2 -> 39172 | Z2: =+B2-$B$2 -> 0 | AA2: =+C2-C$2 -> 0 | AB2: =+D2-D$2 -> 0 | AC2: =+E2-E$2 -> 0 | AD2: =+F2-F$2 -> 0 | AE2: =+G2-G$2 -> 0 | AF2: =+H2-H$2 -> 0 | AG2: =+I2-I$2 -> 0 | AH2: =+J2-J$2 -> 0 | AI2: =+SUM(Z2:AH2) -> 0
A3: 39263 | B3: -0.068935732 | C3: -3.6820787 | D3: 4.8583334 | E3: -0.065752494 | F3: -0.00033729862 | G3: -1.7397732e-14 | H3: 5.0568971e-14 | I3: 9.9168848e-14 | J3: 0 | K3: 0 | L3: 0 | M3: 0 | N3: 0 | O3: 0 | P3: 1.0240682e-14 | Q3: -0.073240178 | R3: 0 | S3: -0.00019716767 | T3: 0.74523245 | U3: =+SUM(B3:T3) -> 1.7130243 | Y3: =+A3 -> 39263 | Z3: =+B3-$B$2 -> 0.0093483423 | AA3: =+C3-C$2 -> -0.32838585 | AB3: =+D3-D$2 -> 0.79576526 | AC3: =+E3-E$2 -> 0.013177094 | AD3: =+F3-F$2 -> -0.00012266275 | AE3: =+G3-G$2 -> -7.173584e-17 | AF3: =+H3-H$2 -> 7.402563e-16 | AG3: =+I3-I$2 -> 2.1314586e-15 | AH3: =+J3-J$2 -> 0 | AI3: =+SUM(Z3:AH3) -> 0.48978218
A4: 39355 | B4: -0.071663741 | C4: -3.9397261 | D4: 5.2294426 | E4: -0.050365319 | F4: -0.00023177784 | G4: -1.6029971e-14 | H4: 4.8456027e-14 | I4: 9.7349024e-14 | J4: 0 | K4: 0 | L4: 0 | M4: 0 | N4: 0 | O4: 0 | P4: 1.0401761e-14 | Q4: -0.029467412 | R4: 0 | S4: -0.00076596643 | T4: 0.73754994 | U4: =+SUM(B4:T4) -> 1.8747723 | Y4: =+A4 -> 39355 | Z4: =+B4-$B$2 -> 0.0066203333 | AA4: =+C4-C$2 -> -0.58603323 | AB4: =+D4-D$2 -> 1.1668745 | AC4: =+E4-E$2 -> 0.028564268 | AD4: =+F4-F$2 -> -1.7141974e-05 | AE4: =+G4-G$2 -> 1.2960253e-15 | AF4: =+H4-H$2 -> -1.3726875e-15 | AG4: =+I4-I$2 -> 3.1163495e-16 | AH4: =+J4-J$2 -> 0 | AI4: =+SUM(Z4:AH4) -> 0.61600877
A5: 39447 | B5: -0.063542094 | C5: -4.1234372 | D5: 5.4945509 | E5: -0.058856392 | F5: -0.0001388145 | G5: -1.7116864e-14 | H5: 4.8423608e-14 | I5: 9.9035455e-14 | J5: 0 | K5: 0 | L5: 0 | M5: 0 | N5: 0 | O5: 0 | P5: 1.0489179e-14 | Q5: -0.0002354462 | R5: 0 | S5: -0.00075334577 | T5: 0.72994541 | U5: =+SUM(B5:T5) -> 1.9775329 | Y5: =+A5 -> 39447 | Z5: =+B5-$B$2 -> 0.01474198 | AA5: =+C5-C$2 -> -0.76974441 | AB5: =+D5-D$2 -> 1.4319828 | AC5: =+E5-E$2 -> 0.020073195 | AD5: =+F5-F$2 -> 7.5821375e-05 | AE5: =+G5-G$2 -> 2.0913155e-16 | AF5: =+H5-H$2 -> -1.4051065e-15 | AG5: =+I5-I$2 -> 1.9980662e-15 | AH5: =+J5-J$2 -> 0 | AI5: =+SUM(Z5:AH5) -> 0.69712936
A6: 39538 | B6: -0.064728899 | C6: -4.1837789 | D6: 5.4841232 | E6: 0.0098443971 | F6: -0.0007450019 | G6: -1.5812244e-14 | H6: 4.4077833e-14 | I6: 1.0186488e-13 | J6: 0 | K6: 0 | L6: 0 | M6: 0 | N6: 0 | O6: 0 | P6: 1.0659592e-14 | Q6: 0.054260301 | R6: 0 | S6: -0.0008088874 | T6: 0.72241806 | U6: =+SUM(B6:T6) -> 2.0205843 | Y6: =+A6 -> 39538 | Z6: =+B6-$B$2 -> 0.013555174 | AA6: =+C6-C$2 -> -0.83008604 | AB6: =+D6-D$2 -> 1.4215551 | AC6: =+E6-E$2 -> 0.088773984 | AD6: =+F6-F$2 -> -0.00053036603 | AE6: =+G6-G$2 -> 1.5137519e-15 | AF6: =+H6-H$2 -> -5.7508813e-15 | AG6: =+I6-I$2 -> 4.8274899e-15 | AH6: =+J6-J$2 -> 0 | AI6: =+SUM(Z6:AH6) -> 0.69326783
A7: 39629 | B7: -0.061585403 | C7: -4.3355729 | D7: 5.8403263 | E7: 0.011744722 | F7: -0.00071597614 | G7: -1.6856279e-14 | H7: 4.7147638e-14 | I7: 9.8624591e-14 | J7: 0 | K7: 0 | L7: 0 | M7: 0 | N7: 0 | O7: 0 | P7: 1.0771832e-14 | Q7: 0.036064208 | R7: 0 | S7: -0.0015668548 | T7: 0.71496711 | U7: =+SUM(B7:T7) -> 2.2036612 | Y7: =+A7 -> 39629 | Z7: =+B7-$B$2 -> 0.016698671 | AA7: =+C7-C$2 -> -0.98188011 | AB7: =+D7-D$2 -> 1.7777582 | AC7: =+E7-E$2 -> 0.090674309 | AD7: =+F7-F$2 -> -0.00050134027 | AE7: =+G7-G$2 -> 4.6971659e-16 | AF7: =+H7-H$2 -> -2.6810759e-15 | AG7: =+I7-I$2 -> 1.5872019e-15 | AH7: =+J7-J$2 -> 0 | AI7: =+SUM(Z7:AH7) -> 0.90274974
A8: 39721 | B8: -0.051207574 | C8: -4.4226039 | D8: 6.0498805 | E8: 0.045598632 | F8: -0.00053713845 | G8: -1.5730993e-14 | H8: 3.8444489e-14 | I8: 9.7722347e-14 | J8: 0 | K8: 0 | L8: 0 | M8: 0 | N8: 0 | O8: 0 | P8: 1.0974835e-14 | Q8: 0.098057092 | R8: 0 | S8: -0.0013954541 | T8: 0.70759176 | U8: =+SUM(B8:T8) -> 2.4253838 | Y8: =+A8 -> 39721 | Z8: =+B8-$B$2 -> 0.0270765 | AA8: =+C8-C$2 -> -1.0689111 | AB8: =+D8-D$2 -> 1.9873124 | AC8: =+E8-E$2 -> 0.12452822 | AD8: =+F8-F$2 -> -0.00032250258 | AE8: =+G8-G$2 -> 1.5950031e-15 | AF8: =+H8-H$2 -> -1.1384226e-14 | AG8: =+I8-I$2 -> 6.8495775e-16 | AH8: =+J8-J$2 -> 0 | AI8: =+SUM(Z8:AH8) -> 1.0696835
A9: 39813 | B9: -0.068689601 | C9: -4.7838093 | D9: 5.3758771 | E9: 0.15728435 | F9: 0.00050732851 | G9: -1.5008818e-14 | H9: 3.7023818e-14 | I9: 9.5618368e-14 | J9: 7.7636183e-16 | K9: -1.9932398e-15 | L9: 1.6186512e-15 | M9: -1.6603179e-16 | N9: -3.9430529e-16 | O9: -8.8999268e-16 | P9: 1.1161055e-14 | Q9: 0.36017357 | R9: 0 | S9: -0.00056760183 | T9: 0.70029125 | U9: =+SUM(B9:T9) -> 1.7410671 | Y9: =+A9 -> 39813 | Z9: =+B9-$B$2 -> 0.0095944727 | AA9: =+C9-C$2 -> -1.4301164 | AB9: =+D9-D$2 -> 1.313309 | AC9: =+E9-E$2 -> 0.23621394 | AD9: =+F9-F$2 -> 0.00072196438 | AE9: =+G9-G$2 -> 2.3171777e-15 | AF9: =+H9-H$2 -> -1.2804896e-14 | AG9: =+I9-I$2 -> -1.4190214e-15 | AH9: =+J9-J$2 -> 7.7636183e-16 | AI9: =+SUM(Z9:AH9) -> 0.12972289
A10: 39903 | B10: -0.073441058 | C10: -4.5362461 | D10: 5.1776753 | E10: 0.20677613 | F10: 0.0009137068 | G10: -1.5907451e-14 | H10: 3.6269444e-14 | I10: 1.0114036e-13 | J10: -2.129443e-14 | K10: 9.5471163e-16 | L10: 1.5223913e-15 | M10: -6.1157008e-16 | N10: -1.1680121e-15 | O10: -3.801997e-15 | P10: 1.1306375e-14 | Q10: 0.32451927 | R10: 0 | S10: 0.0019847909 | T10: 0.69306481 | U10: =+SUM(B10:T10) -> 1.7952468 | Y10: =+A10 -> 39903 | Z10: =+B10-$B$2 -> 0.0048430159 | AA10: =+C10-C$2 -> -1.1825533 | AB10: =+D10-D$2 -> 1.1151072 | AC10: =+E10-E$2 -> 0.28570572 | AD10: =+F10-F$2 -> 0.0011283427 | AE10: =+G10-G$2 -> 1.4185452e-15 | AF10: =+H10-H$2 -> -1.355927e-14 | AG10: =+I10-I$2 -> 4.1029678e-15 | AH10: =+J10-J$2 -> -2.129443e-14 | AI10: =+SUM(Z10:AH10) -> 0.224231
A11: 39994 | B11: -0.07398642 | C11: -4.1428582 | D11: 4.6096002 | E11: 0.17543063 | F11: -6.3751945e-05 | G11: -1.5895798e-14 | H11: 3.0183394e-14 | I11: 1.251219e-13 | J11: -4.4403668e-14 | K11: 3.813376e-15 | L11: 1.3146739e-15 | M11: -1.417915e-15 | N11: -1.1748694e-15 | O11: -7.5474058e-15 | P11: 1.1468968e-14 | Q11: 0.20851281 | R11: 0 | S11: 0.003886969 | T11: 0.68591169 | U11: =+SUM(B11:T11) -> 1.466434 | Y11: =+A11 -> 39994 | Z11: =+B11-$B$2 -> 0.0042976535 | AA11: =+C11-C$2 -> -0.78916533 | AB11: =+D11-D$2 -> 0.5470321 | AC11: =+E11-E$2 -> 0.25436022 | AD11: =+F11-F$2 -> 0.00015088392 | AE11: =+G11-G$2 -> 1.430198e-15 | AF11: =+H11-H$2 -> -1.964532e-14 | AG11: =+I11-I$2 -> 2.8084512e-14 | AH11: =+J11-J$2 -> -4.4403668e-14 | AI11: =+SUM(Z11:AH11) -> 0.016675523
A12: 40086 | B12: -0.073653072 | C12: -3.4599427 | D12: 3.9612346 | E12: 0.13057815 | F12: -0.00022882546 | G12: -1.464391e-14 | H12: 2.3612202e-14 | I12: 1.4448187e-13 | J12: -5.9618656e-14 | K12: 4.5553952e-15 | L12: 6.4309241e-16 | M12: -2.8006834e-15 | N12: -2.1829048e-15 | O12: -1.2848328e-14 | P12: 1.1661022e-14 | Q12: 0.040595185 | R12: 0 | S12: 0.0032288968 | T12: 0.67883112 | U12: =+SUM(B12:T12) -> 1.2806434 | Y12: =+A12 -> 40086 | Z12: =+B12-$B$2 -> 0.0046310021 | AA12: =+C12-C$2 -> -0.10624983 | AB12: =+D12-D$2 -> -0.10133349 | AC12: =+E12-E$2 -> 0.20950774 | AD12: =+F12-F$2 -> -1.418959e-05 | AE12: =+G12-G$2 -> 2.682086e-15 | AF12: =+H12-H$2 -> -2.6216512e-14 | AG12: =+I12-I$2 -> 4.7444482e-14 | AH12: =+J12-J$2 -> -5.9618656e-14 | AI12: =+SUM(Z12:AH12) -> 0.0065412311
A13: 40178 | B13: -0.06419439 | C13: -3.0559098 | D13: 3.8581322 | E13: 0.10703947 | F13: 4.5429166e-05 | G13: -1.5823259e-14 | H13: 2.3547395e-14 | I13: 1.5766787e-13 | J13: -7.323975e-14 | K13: 6.6079109e-15 | L13: 3.6756254e-16 | M13: -3.5615799e-15 | N13: -2.0156895e-15 | O13: -1.8016609e-14 | P13: 1.1805466e-14 | Q13: -0.045205747 | R13: 0 | S13: 0.002903373 | T13: 0.67182238 | U13: =+SUM(B13:T13) -> 1.4746329 | Y13: =+A13 -> 40178 | Z13: =+B13-$B$2 -> 0.014089684 | AA13: =+C13-C$2 -> 0.297783 | AB13: =+D13-D$2 -> -0.2044359 | AC13: =+E13-E$2 -> 0.18596905 | AD13: =+F13-F$2 -> 0.00026006504 | AE13: =+G13-G$2 -> 1.5027373e-15 | AF13: =+H13-H$2 -> -2.6281319e-14 | AG13: =+I13-I$2 -> 6.0630477e-14 | AH13: =+J13-J$2 -> -7.323975e-14 | AI13: =+SUM(Z13:AH13) -> 0.2936659
... A131: 50951 | B131: -0.11623914 | C131: -1.345537 | D131: 3.088072 | E131: 0.0066416295 | F131: -8.7878743e-06 | G131: 2.6677613e-15 | H131: -1.8863064e-14 | I131: 3.1017843e-13 | J131: 3.8000555e-13 | K131: 4.6128837e-14 | L131: 4.1087059e-14 | M131: 3.2089611e-14 | N131: 2.8074824e-14 | O131: 1.7685319e-15 | P131: 6.3387837e-15 | Q131: -0.07972901 | R131: 0 | S131: -0.00031801307 | T131: 0.1932494 | U131: =+SUM(B131:T131) -> 1.746131 | Y131: =+A131 -> 50951 | Z131: =+B131-$B$2 -> -0.037955068 | AA131: =+C131-C$2 -> 2.0081558 | AB131: =+D131-D$2 -> -0.97449611 | AC131: =+E131-E$2 -> 0.085571217 | AD131: =+F131-F$2 -> 0.000205848 | AE131: =+G131-G$2 -> 1.9993757e-14 | AF131: =+H131-H$2 -> -6.8691778e-14 | AG131: =+I131-I$2 -> 2.1314104e-13 | AH131: =+J131-J$2 -> 3.8000555e-13 | AI131: =+SUM(Z131:AH131) -> 1.0814817
A132: 51043 | U132: =+SUM(B132:T132) -> 0 | Y132: =+A132 -> 51043 | Z132: =+B132-$B$2 -> 0.078284074 | AA132: =+C132-C$2 -> 3.3536928 | AB132: =+D132-D$2 -> -4.0625681 | AC132: =+E132-E$2 -> 0.078929587 | AD132: =+F132-F$2 -> 0.00021463587 | AE132: =+G132-G$2 -> 1.7325996e-14 | AF132: =+H132-H$2 -> -4.9828714e-14 | AG132: =+I132-I$2 -> -9.7037389e-14 | AH132: =+J132-J$2 -> 0 | AI132: =+SUM(Z132:AH132) -> -0.55144698

Sheet YC Chart - Policy rate
K1: Chart | L1: Chart | M1: 1 | N1: 2 | O1: 3 | P1: 4 | Q1: 5 | R1: 6 | S1: 7 | T1: 8 | U1: 9 | V1: 10 | W1: 11 | X1: 12 | Y1: 13 | Z1: 14 | AA1: 15 | AB1: 16 | AC1: 17 | AD1: 18 | AE1: 19 | AF1: 20 | AG1: 21 | AH1: 22 | AI1: 23 | AJ1: 24 | AK1: 25 | AL1: 26 | AT1: 1 | AU1: 2 | AV1: 3 | AW1: 4 | AX1: 5 | AY1: 6
A2: date | D2: obs_nominalrate | K2: Date | L2: Policy rate(%,apr) | M2: =+_xlfn.CONCAT("V",M1) -> V1 | N2: =+_xlfn.CONCAT("V",N1) -> V2 | O2: =+_xlfn.CONCAT("V",O1) -> V3 | P2: =+_xlfn.CONCAT("V",P1) -> V4 | Q2: =+_xlfn.CONCAT("V",Q1) -> V5 | R2: =+_xlfn.CONCAT("V",R1) -> V6 | S2: =+_xlfn.CONCAT("V",S1) -> V7 | T2: =+_xlfn.CONCAT("V",T1) -> V8 | ... AL2: =+_xlfn.CONCAT("V",AL1) -> V26 | AT2: obs_nominalrate1 | AU2: obs_nominalrate2 | AV2: obs_nominalrate3 | AW2: obs_nominalrate4 | AX2: obs_nominalrate5 | AY2: obs_nominalrate6 | BJ2: yc1 | BK2: yc2 | BL2: yc3 | BM2: yc4 | BN2: yc5 | BO2: yc6
A3: 25749 | D3: 1.98925 | K3: =+A3 -> 25749 | L3: =+D3*4 -> 7.957
A4: 25841 | D4: 1.9005 | K4: =+A4 -> 25841 | L4: =+D4*4 -> 7.602
A5: 25933 | D5: 1.8105 | K5: =+A5 -> 25933 | L5: =+D5*4 -> 7.242
A6: 26023 | D6: 1.62925 | K6: =+A6 -> 26023 | L6: =+D6*4 -> 6.517
A7: 26114 | D7: 1.48475 | K7: =+A7 -> 26114 | L7: =+D7*4 -> 5.939
A8: 26206 | D8: 1.5565 | K8: =+A8 -> 26206 | L8: =+D8*4 -> 6.226
A9: 26298 | D9: 1.5015 | K9: =+A9 -> 26298 | L9: =+D9*4 -> 6.006
A10: 26389 | D10: 1.26175 | K10: =+A10 -> 26389 | L10: =+D10*4 -> 5.047
A11: 26480 | D11: 1.1885 | K11: =+A11 -> 26480 | L11: =+D11*4 -> 4.754
A12: 26572 | D12: 1.21425 | K12: =+A12 -> 26572 | L12: =+D12*4 -> 4.857
A13: 26664 | D13: 1.59875 | K13: =+A13 -> 26664 | L13: =+D13*4 -> 6.395
A14: 26754 | D14: 1.69775 | K14: =+A14 -> 26754 | L14: =+D14*4 -> 6.791
... A157: 39813 | D157: 0.9725 | K157: =+A157 -> 39813 | L157: =+D157*4 -> 3.89
A158: 39903 | D158: 0.42 | K158: =+A158 -> 39903 | L158: =+D158*4 -> 1.68 | M158: =+L158 -> 1.68 | AT158: 1.0533333 | AU158: 1.0033333 | AV158: 1.0161962 | AW158: 1.0466667 | AX158: 1.0945548 | AY158: 1.1718265
A159: 39994 | D159: 0.2325 | K159: =+A159 -> 39994 | L159: =+D159*4 -> 0.93 | M159: 1.0533333 | N159: =+L159 -> 0.93 | AT159: 0.74666667 | AU159: 0.75 | AV159: 0.78875618 | AW159: 0.86 | AX159: 0.94054332 | AY159: 1.0408533 | BJ159: =+AT158*1 -> 1.0533333
A160: 40086 | D160: 0.1325 | K160: =+A160 -> 40086 | L160: =+D160*4 -> 0.53 | M160: 1.0033333 | N160: 0.74666667 | O160: =+L160 -> 0.53 | AT160: 0.43 | AU160: 0.48666667 | AV160: 0.57783631 | AW160: 0.69333333 | AX160: 0.82007707 | AY160: 0.96154999 | BJ160: =+AT159*1 -> 0.74666667 | BK160: =+AU158*1 -> 1.0033333
A161: 40178 | D161: 0.1125 | K161: =+A161 -> 40178 | L161: =+D161*4 -> 0.45 | M161: 1.0161962 | N161: 0.75 | O161: 0.43 | P161: =+L161 -> 0.45 | AT161: 0.42666667 | AU161: 0.49333333 | AV161: 0.60725117 | AW161: 0.74333333 | AX161: 0.87227474 | AY161: 1.0035035 | BJ161: =+AT160*1 -> 0.43 | BK161: =+AU159*1 -> 0.75 | BL161: =+AV158*1 -> 1.0161962
A162: 40268 | D162: 0.105 | K162: =+A162 -> 40268 | L162: =+D162*4 -> 0.42 | M162: 1.0466667 | N162: 0.78875618 | O162: 0.48666667 | P162: 0.42666667 | Q162: =+L162 -> 0.42 | AT162: 0.36333333 | AU162: 0.43666667 | AV162: 0.53901761 | AW162: 0.65333333 | AX162: 0.7606598 | AY162: 0.86762352 | BJ162: =+AT161*1 -> 0.42666667 | BK162: =+AU160*1 -> 0.48666667 | BL162: =+AV159*1 -> 0.78875618 | BM162: =+AW158*1 -> 1.0466667
A163: 40359 | D163: 0.105 | K163: =+A163 -> 40359 | L163: =+D163*4 -> 0.42 | M163: 1.0945548 | N163: 0.86 | O163: 0.57783631 | P163: 0.49333333 | Q163: 0.36333333 | R163: =+L163 -> 0.42 | AT163: 0.40666667 | AU163: 0.47333333 | AV163: 0.52599239 | AW163: 0.57666667 | AX163: 0.63240126 | AY163: 0.69028261 | BJ163: =+AT162*1 -> 0.36333333 | BK163: =+AU161*1 -> 0.49333333 | BL163: =+AV160*1 -> 0.57783631 | BM163: =+AW159*1 -> 0.86 | BN163: =+AX158*1 -> 1.0945548
A164: 40451 | D164: 0.1525 | K164: =+A164 -> 40451 | L164: =+D164*4 -> 0.61 | M164: 1.1718265 | N164: 0.94054332 | O164: 0.69333333 | P164: 0.60725117 | Q164: 0.43666667 | R164: 0.40666667 | S164: =+L164 -> 0.61 | AT164: 0.53333333 | AU164: 0.59 | AV164: 0.64179759 | AW164: 0.69 | AX164: 0.73507369 | AY164: 0.77821365 | BJ164: =+AT163*1 -> 0.40666667 | BK164: =+AU162*1 -> 0.43666667 | BL164: =+AV161*1 -> 0.60725117 | BM164: =+AW160*1 -> 0.69333333 | BN164: =+AX159*1 -> 0.94054332 | BO164: =+AY158*1 -> 1.1718265
A165: 40543 | D165: 0.2025 | K165: =+A165 -> 40543 | L165: =+D165*4 -> 0.81 | N165: 1.0408533 | O165: 0.82007707 | P165: 0.74333333 | Q165: 0.53901761 | R165: 0.47333333 | S165: 0.53333333 | T165: =+L165 -> 0.81 | AT165: 0.71666667 | AU165: 0.78 | AV165: 0.83122476 | AW165: 0.88 | AX165: 0.93222257 | AY165: 0.98567932 | BJ165: =+AT164*1 -> 0.53333333 | BK165: =+AU163*1 -> 0.47333333 | BL165: =+AV162*1 -> 0.53901761 | BM165: =+AW161*1 -> 0.74333333 | BN165: =+AX160*1 -> 0.82007707 | BO165: =+AY159*1 -> 1.0408533
A166: 40633 | D166: 0.215 | K166: =+A166 -> 40633 | L166: =+D166*4 -> 0.86 | O166: 0.96154999 | P166: 0.87227474 | Q166: 0.65333333 | R166: 0.52599239 | S166: 0.59 | T166: 0.71666667 | U166: =L166 -> 0.86 | AT166: 0.82333333 | AU166: 0.94333333 | AV166: 1.0594018 | AW166: 1.17 | AX166: 1.2739464 | AY166: 1.3742487 | BJ166: =+AT165*1 -> 0.71666667 | BK166: =+AU164*1 -> 0.59 | BL166: =+AV163*1 -> 0.52599239 | BM166: =+AW162*1 -> 0.65333333 | BN166: =+AX161*1 -> 0.87227474 | BO166: =+AY160*1 -> 0.96154999
A167: 40724 | D167: 0.305 | K167: =+A167 -> 40724 | L167: =+D167*4 -> 1.22 | P167: 1.0035035 | Q167: 0.7606598 | R167: 0.57666667 | S167: 0.64179759 | T167: 0.78 | U167: 0.82333333 | V167: =L167 -> 1.22 | AT167: 1.1833333 | AU167: 1.3166667 | AV167: 1.4272438 | AW167: 1.5233333 | AX167: 1.6099914 | AY167: 1.6907331 | BJ167: =+AT166*1 -> 0.82333333 | BK167: =+AU165*1 -> 0.78 | BL167: =+AV164*1 -> 0.64179759 | BM167: =+AW163*1 -> 0.57666667 | BN167: =+AX162*1 -> 0.7606598 | BO167: =+AY161*1 -> 1.0035035
A168: 40816 | D168: 0.345 | K168: =+A168 -> 40816 | L168: =+D168*4 -> 1.38 | Q168: 0.86762352 | R168: 0.63240126 | S168: 0.69 | T168: 0.83122476 | U168: 0.94333333 | V168: 1.1833333 | W168: =L168 -> 1.38 | AT168: 0.99666667 | AU168: 0.98 | AV168: 0.97442337 | AW168: 0.97666667 | AX168: 0.98830096 | AY168: 1.0036749 | BJ168: =+AT167*1 -> 1.1833333 | BK168: =+AU166*1 -> 0.94333333 | BL168: =+AV165*1 -> 0.83122476 | BM168: =+AW164*1 -> 0.69 | BN168: =+AX163*1 -> 0.63240126 | BO168: =+AY162*1 -> 0.86762352
A169: 40908 | D169: 0.31 | K169: =+A169 -> 40908 | L169: =+D169*4 -> 1.24 | M169: =L169 -> 1.24 | R169: 0.69028261 | S169: 0.73507369 | T169: 0.88 | U169: 1.0594018 | V169: 1.3166667 | W169: 0.99666667 | AT169: 0.61666667 | AU169: 0.56333333 | AV169: 0.55116979 | AW169: 0.54666667 | AX169: 0.55239583 | AY169: 0.56916667 | BJ169: =+AT168*1 -> 0.99666667 | BK169: =+AU167*1 -> 1.3166667 | BL169: =+AV166*1 -> 1.0594018 | BM169: =+AW165*1 -> 0.88 | BN169: =+AX164*1 -> 0.73507369 | BO169: =+AY163*1 -> 0.69028261
A170: 40999 | D170: 0.1625 | K170: =+A170 -> 40999 | L170: =+D170*4 -> 0.65 | M170: 0.61666667 | N170: =L170 -> 0.65 | S170: 0.77821365 | T170: 0.93222257 | U170: 1.17 | V170: 1.4272438 | W170: 0.98 | AT170: 0.35333333 | AU170: 0.34333333 | AV170: 0.34541941 | AW170: 0.35 | AX170: 0.35895216 | AY170: 0.37499451 | BJ170: =+AT169*1 -> 0.61666667 | BK170: =+AU168*1 -> 0.98 | BL170: =+AV167*1 -> 1.4272438 | BM170: =+AW166*1 -> 1.17 | BN170: =+AX165*1 -> 0.93222257 | BO170: =+AY164*1 -> 0.77821365
A171: 41090 | D171: 0.0975 | K171: =+A171 -> 41090 | L171: =+D171*4 -> 0.39 | M171: 0.56333333 | N171: 0.35333333 | O171: =L171 -> 0.39 | T171: 0.98567932 | U171: 1.2739464 | V171: 1.5233333 | W171: 0.97442337 | AT171: 0.29666667 | AU171: 0.28333333 | AV171: 0.27857143 | AW171: 0.27666667 | AX171: 0.28041667 | AY171: 0.29111111 | BJ171: =+AT170*1 -> 0.35333333 | BK171: =+AU169*1 -> 0.56333333 | BL171: =+AV168*1 -> 0.97442337 | BM171: =+AW167*1 -> 1.5233333 | BN171: =+AX166*1 -> 1.2739464 | BO171: =+AY165*1 -> 0.98567932
A172: 41182 | D172: 0.04 | K172: =+A172 -> 41182 | L172: =+D172*4 -> 0.16 | M172: 0.55116979 | N172: 0.34333333 | O172: 0.29666667 | P172: =L172 -> 0.16 | U172: 1.3742487 | V172: 1.6099914 | W172: 0.97666667 | AT172: 0.09 | AU172: 0.08 | AV172: 0.075512821 | AW172: 0.073333333 | AX172: 0.077083333 | AY172: 0.087777778 | BJ172: =+AT171*1 -> 0.29666667 | BK172: =+AU170*1 -> 0.34333333 | BL172: =+AV169*1 -> 0.55116979 | BM172: =+AW168*1 -> 0.97666667 | BN172: =+AX167*1 -> 1.6099914 | BO172: =+AY166*1 -> 1.3742487
A173: 41274 | D173: 0.0275 | K173: =+A173 -> 41274 | L173: =+D173*4 -> 0.11 | M173: 0.54666667 | N173: 0.34541941 | O173: 0.28333333 | P173: 0.09 | Q173: =L173 -> 0.11 | V173: 1.6907331 | W173: 0.98830096 | AT173: 0.073333333 | AU173: 0.06 | AV173: 0.05775641 | AW173: 0.056666667 | AX173: 0.060364583 | AY173: 0.070694444 | BJ173: =+AT172*1 -> 0.09 | BK173: =+AU171*1 -> 0.28333333 | BL173: =+AV170*1 -> 0.34541941 | BM173: =+AW169*1 -> 0.54666667 | BN173: =+AX168*1 -> 0.98830096 | BO173: =+AY167*1 -> 1.6907331
A174: 41364 | D174: 0.03 | K174: =+A174 -> 41364 | L174: =+D174*4 -> 0.12 | M174: 0.55239583 | N174: 0.35 | O174: 0.27857143 | P174: 0.08 | Q174: 0.073333333 | R174: =L174 -> 0.12 | W174: 1.0036749 | AT174: 0.09 | AU174: 0.10333333 | AV174: 0.11712381 | AW174: 0.13333333 | AX174: 0.15171672 | AY174: 0.17226671 | BJ174: =+AT173*1 -> 0.073333333 | BK174: =+AU172*1 -> 0.08 | BL174: =+AV171*1 -> 0.27857143 | BM174: =+AW170*1 -> 0.35 | BN174: =+AX169*1 -> 0.55239583 | BO174: =+AY168*1 -> 1.0036749
A175: 41455 | D175: 0.03 | K175: =+A175 -> 41455 | L175: =+D175*4 -> 0.12 | M175: 0.56916667 | N175: 0.35895216 | O175: 0.27666667 | P175: 0.075512821 | Q175: 0.06 | R175: 0.09 | S175: =L175 -> 0.12 | AT175: 0.08 | AU175: 0.08 | AV175: 0.086972496 | AW175: 0.096666667 | AX175: 0.10838926 | AY175: 0.12375342 | BJ175: =+AT174*1 -> 0.09 | BK175: =+AU173*1 -> 0.06 | BL175: =+AV172*1 -> 0.075512821 | BM175: =+AW171*1 -> 0.27666667 | BN175: =+AX170*1 -> 0.35895216 | BO175: =+AY169*1 -> 0.56916667
A176: 41547 | D176: 0.0325 | K176: =+A176 -> 41547 | L176: =+D176*4 -> 0.13 | N176: 0.37499451 | O176: 0.28041667 | P176: 0.073333333 | Q176: 0.05775641 | R176: 0.10333333 | S176: 0.08 | T176: =L176 -> 0.13 | AT176: 0.10333333 | AU176: 0.11333333 | AV176: 0.13186188 | AW176: 0.15666667 | AX176: 0.18222303 | AY176: 0.21012418 | BJ176: =+AT175*1 -> 0.08 | BK176: =+AU174*1 -> 0.10333333 | BL176: =+AV173*1 -> 0.05775641 | BM176: =+AW172*1 -> 0.073333333 | BN176: =+AX171*1 -> 0.28041667 | BO176: =+AY170*1 -> 0.37499451
A177: 41639 | D177: 0.04 | K177: =+A177 -> 41639 | L177: =+D177*4 -> 0.16 | O177: 0.29111111 | P177: 0.077083333 | Q177: 0.056666667 | R177: 0.11712381 | S177: 0.08 | T177: 0.10333333 | U177: =L177 -> 0.16 | AT177: 0.13 | AU177: 0.13 | AV177: 0.13760255 | AW177: 0.14666667 | AX177: 0.15831093 | AY177: 0.17368379 | BJ177: =+AT176*1 -> 0.10333333 | BK177: =+AU175*1 -> 0.08 | BL177: =+AV174*1 -> 0.11712381 | BM177: =+AW173*1 -> 0.056666667 | BN177: =+AX172*1 -> 0.077083333 | BO177: =+AY171*1 -> 0.29111111
A178: 41729 | D178: 0.055 | K178: =+A178 -> 41729 | L178: =+D178*4 -> 0.22 | P178: 0.087777778 | Q178: 0.060364583 | R178: 0.13333333 | S178: 0.086972496 | T178: 0.11333333 | U178: 0.13 | V178: =L178 -> 0.22 | AT178: 0.16 | AU178: 0.14666667 | AV178: 0.14204212 | AW178: 0.14 | AX178: 0.14244792 | AY178: 0.14958333 | BJ178: =+AT177*1 -> 0.13 | BK178: =+AU176*1 -> 0.11333333 | BL178: =+AV175*1 -> 0.086972496 | BM178: =+AW174*1 -> 0.13333333 | BN178: =+AX173*1 -> 0.060364583 | BO178: =+AY172*1 -> 0.087777778
A179: 41820 | D179: 0.055 | K179: =+A179 -> 41820 | L179: =+D179*4 -> 0.22 | M179: =L179 -> 0.22 | Q179: 0.070694444 | R179: 0.15171672 | S179: 0.096666667 | T179: 0.13186188 | U179: 0.13 | V179: 0.16 | W179: =L179 -> 0.22 | AT179: 0.13 | AU179: 0.10666667 | AV179: 0.099538019 | AW179: 0.096666667 | AX179: 0.097604167 | AY179: 0.10083333 | BJ179: =+AT178*1 -> 0.16 | BK179: =+AU177*1 -> 0.13 | BL179: =+AV176*1 -> 0.13186188 | BM179: =+AW175*1 -> 0.096666667 | BN179: =+AX174*1 -> 0.15171672 | BO179: =+AY173*1 -> 0.070694444
A180: 41912 | D180: 0.0175 | K180: =+A180 -> 41912 | L180: =+D180*4 -> 0.07 | M180: 0.02 | N180: =L180 -> 0.07 | R180: 0.17226671 | S180: 0.10838926 | T180: 0.15666667 | U180: 0.13760255 | V180: 0.14666667 | W180: 0.13 | AT180: 0.02 | AU180: 0.02 | AV180: 0.013333333 | AW180: 0.006666667 | AX180: 0.006822917 | AY180: 0.007916667 | BJ180: =+AT179*1 -> 0.13 | BK180: =+AU178*1 -> 0.14666667 | BL180: =+AV177*1 -> 0.13760255 | BM180: =+AW176*1 -> 0.15666667 | BN180: =+AX175*1 -> 0.10838926 | BO180: =+AY174*1 -> 0.17226671
A181: 42004 | D181: 0.0025 | K181: =+A181 -> 42004 | L181: =+D181*4 -> 0.01 | M181: 0.02 | N181: -0.013333333 | O181: =L181 -> 0.01 | S181: 0.12375342 | T181: 0.18222303 | U181: 0.14666667 | V181: 0.14204212 | W181: 0.10666667 | AT181: -0.013333333 | AU181: -0.023333333 | AV181: -0.035320513 | AW181: -0.043333333 | AX181: -0.04328125 | AY181: -0.042916667 | BJ181: =+AT180*1 -> 0.02 | BK181: =+AU179*1 -> 0.10666667 | BL181: =+AV178*1 -> 0.14204212 | BM181: =+AW177*1 -> 0.14666667 | BN181: =+AX176*1 -> 0.18222303 | BO181: =+AY175*1 -> 0.12375342
A182: 42094 | D182: 0 | K182: =+A182 -> 42094 | L182: =+D182*4 -> 0 | M182: 0.013333333 | N182: -0.023333333 | O182: -0.013333333 | P182: =L182 -> 0 | T182: 0.21012418 | U182: 0.15831093 | V182: 0.14 | W182: 0.099538019 | AT182: -0.056666667 | AU182: -0.083333333 | AV182: -0.096777095 | AW182: -0.10333333 | AX182: -0.10465774 | AY182: -0.10571429 | BJ182: =+AT181*1 -> -0.013333333 | BK182: =+AU180*1 -> 0.02 | BL182: =+AV179*1 -> 0.099538019 | BM182: =+AW178*1 -> 0.14 | BN182: =+AX177*1 -> 0.15831093 | BO182: =+AY176*1 -> 0.21012418
A183: 42185 | D183: -0.0125 | K183: =+A183 -> 42185 | L183: =+D183*4 -> -0.05 | M183: 0.006666667 | N183: -0.035320513 | O183: -0.023333333 | P183: -0.056666667 | Q183: =L183 -> -0.05 | U183: 0.17368379 | V183: 0.14244792 | W183: 0.096666667 | AT183: -0.11333333 | AU183: -0.12333333 | AV183: -0.12632246 | AW183: -0.12666667 | AX183: -0.12405571 | AY183: -0.12027174 | BJ183: =+AT182*1 -> -0.056666667 | BK183: =+AU181*1 -> -0.023333333 | BL183: =+AV180*1 -> 0.013333333 | BM183: =+AW179*1 -> 0.096666667 | BN183: =+AX178*1 -> 0.14244792 | BO183: =+AY177*1 -> 0.17368379
A184: 42277 | D184: -0.0225 | K184: =+A184 -> 42277 | L184: =+D184*4 -> -0.09 | M184: 0.006822917 | N184: -0.043333333 | O184: -0.035320513 | P184: -0.083333333 | Q184: -0.11333333 | R184: =L184 -> -0.09 | V184: 0.14958333 | W184: 0.097604167 | AT184: -0.13 | AU184: -0.13666667 | AV184: -0.14057692 | AW184: -0.14333333 | AX184: -0.14244792 | AY184: -0.13958333 | BJ184: =+AT183*1 -> -0.11333333 | BK184: =+AU182*1 -> -0.083333333 | BL184: =+AV181*1 -> -0.035320513 | BM184: =+AW180*1 -> 0.006666667 | BN184: =+AX179*1 -> 0.097604167 | BO184: =+AY178*1 -> 0.14958333
A185: 42369 | D185: -0.0375 | K185: =+A185 -> 42369 | L185: =+D185*4 -> -0.15 | M185: 0.007916667 | N185: -0.04328125 | O185: -0.043333333 | P185: -0.096777095 | Q185: -0.12333333 | R185: -0.13 | S185: =L185 -> -0.15 | W185: 0.10083333 | AT185: -0.21 | AU185: -0.23 | AV185: -0.24295357 | AW185: -0.25 | AX185: -0.25127232 | AY185: -0.25196429 | BJ185: =+AT184*1 -> -0.13 | BK185: =+AU183*1 -> -0.12333333 | BL185: =+AV182*1 -> -0.096777095 | BM185: =+AW181*1 -> -0.043333333 | BN185: =+AX180*1 -> 0.006822917 | BO185: =+AY179*1 -> 0.10083333
A186: 42460 | D186: -0.065 | K186: =+A186 -> 42460 | L186: =+D186*4 -> -0.26 | N186: -0.042916667 | O186: -0.04328125 | P186: -0.10333333 | Q186: -0.12632246 | R186: -0.13666667 | S186: -0.21 | T186: =L186 -> -0.26 | AT186: -0.31666667 | AU186: -0.34666667 | AV186: -0.36967603 | AW186: -0.38333333 | AX186: -0.38745618 | AY186: -0.3906092 | BJ186: =+AT185*1 -> -0.21 | BK186: =+AU184*1 -> -0.13666667 | BL186: =+AV183*1 -> -0.12632246 | BM186: =+AW182*1 -> -0.10333333 | BN186: =+AX181*1 -> -0.04328125 | BO186: =+AY180*1 -> 0.007916667
A187: 42551 | D187: -0.0875 | K187: =+A187 -> 42551 | L187: =+D187*4 -> -0.35 | O187: -0.042916667 | P187: -0.10465774 | Q187: -0.12666667 | R187: -0.14057692 | S187: -0.23 | T187: -0.31666667 | U187: =L187 -> -0.35 | AT187: -0.34666667 | AU187: -0.36333333 | AV187: -0.37798897 | AW187: -0.39 | AX187: -0.39873402 | AY187: -0.40646728 | BJ187: =+AT186*1 -> -0.31666667 | BK187: =+AU185*1 -> -0.23 | BL187: =+AV184*1 -> -0.14057692 | BM187: =+AW183*1 -> -0.12666667 | BN187: =+AX182*1 -> -0.10465774 | BO187: =+AY181*1 -> -0.042916667
A188: 42643 | D188: -0.0925 | K188: =+A188 -> 42643 | L188: =+D188*4 -> -0.37 | P188: -0.10571429 | Q188: -0.12405571 | R188: -0.14333333 | S188: -0.24295357 | T188: -0.34666667 | U188: -0.34666667 | V188: =L188 -> -0.37 | AT188: -0.35 | AU188: -0.37333333 | AV188: -0.38993126 | AW188: -0.40333333 | AX188: -0.41516449 | AY188: -0.42607214 | BJ188: =+AT187*1 -> -0.34666667 | BK188: =+AU186*1 -> -0.34666667 | BL188: =+AV185*1 -> -0.24295357 | BM188: =+AW184*1 -> -0.14333333 | BN188: =+AX183*1 -> -0.12405571 | BO188: =+AY182*1 -> -0.10571429
A189: 42735 | D189: -0.0925 | K189: =+A189 -> 42735 | L189: =+D189*4 -> -0.37 | Q189: -0.12027174 | R189: -0.14244792 | S189: -0.25 | T189: -0.36967603 | U189: -0.36333333 | V189: -0.35 | W189: =L189 -> -0.37 | AT189: -0.35 | AU189: -0.35333333 | AV189: -0.35576465 | AW189: -0.35666667 | AX189: -0.35661287 | AY189: -0.3559707 | BJ189: =+AT188*1 -> -0.35 | BK189: =+AU187*1 -> -0.36333333 | BL189: =+AV186*1 -> -0.36967603 | BM189: =+AW185*1 -> -0.25 | BN189: =+AX184*1 -> -0.14244792 | BO189: =+AY183*1 -> -0.12027174
A190: 42825 | D190: -0.0925 | K190: =+A190 -> 42825 | L190: =+D190*4 -> -0.37 | M190: =L190 -> -0.37 | R190: -0.13958333 | S190: -0.25127232 | T190: -0.38333333 | U190: -0.37798897 | V190: -0.37333333 | W190: -0.35 | AT190: -0.35 | AU190: -0.35 | AV190: -0.34639493 | AW190: -0.34 | AX190: -0.33337183 | AY190: -0.32484903 | BJ190: =+AT189*1 -> -0.35 | BK190: =+AU188*1 -> -0.37333333 | BL190: =+AV187*1 -> -0.37798897 | BM190: =+AW186*1 -> -0.38333333 | BN190: =+AX185*1 -> -0.25127232 | BO190: =+AY184*1 -> -0.13958333
A191: 42916 | D191: -0.0925 | K191: =+A191 -> 42916 | L191: =+D191*4 -> -0.37 | M191: -0.35 | N191: =L191 -> -0.37 | S191: -0.25196429 | T191: -0.38745618 | U191: -0.39 | V191: -0.38993126 | W191: -0.35333333 | AT191: -0.36 | AU191: -0.36 | AV191: -0.35541549 | AW191: -0.34666667 | AX191: -0.33724223 | AY191: -0.3256968 | BJ191: =+AT190*1 -> -0.35 | BK191: =+AU189*1 -> -0.35333333 | BL191: =+AV188*1 -> -0.38993126 | BM191: =+AW187*1 -> -0.39 | BN191: =+AX186*1 -> -0.38745618 | BO191: =+AY185*1 -> -0.25196429
A192: 43008 | D192: -0.0925 | K192: =+A192 -> 43008 | L192: =+D192*4 -> -0.37 | M192: -0.35 | N192: -0.36 | O192: =L192 -> -0.37 | T192: -0.3906092 | U192: -0.39873402 | V192: -0.40333333 | W192: -0.35576465 | AT192: -0.36 | AU192: -0.35666667 | AV192: -0.35323179 | AW192: -0.34666667 | AX192: -0.33835347 | AY192: -0.32631419 | BJ192: =+AT191*1 -> -0.36 | BK192: =+AU190*1 -> -0.35 | BL192: =+AV189*1 -> -0.35576465 | BM192: =+AW188*1 -> -0.40333333 | BN192: =+AX187*1 -> -0.39873402 | BO192: =+AY186*1 -> -0.3906092
A193: 43100 | D193: -0.0925 | K193: =+A193 -> 43100 | L193: =+D193*4 -> -0.37 | M193: -0.34639493 | N193: -0.36 | O193: -0.36 | P193: =L193 -> -0.37 | U193: -0.40646728 | V193: -0.41516449 | W193: -0.35666667 | AT193: -0.35333333 | AU193: -0.35333333 | AV193: -0.3511039 | AW193: -0.34666667 | AX193: -0.33985998 | AY193: -0.32876443 | BJ193: =+AT192*1 -> -0.36 | BK193: =+AU191*1 -> -0.36 | BL193: =+AV190*1 -> -0.34639493 | BM193: =+AW189*1 -> -0.35666667 | BN193: =+AX188*1 -> -0.41516449 | BO193: =+AY187*1 -> -0.40646728
A194: 43190 | D194: -0.0925 | K194: =+A194 -> 43190 | L194: =+D194*4 -> -0.37 | M194: -0.34 | N194: -0.35541549 | O194: -0.35666667 | P194: -0.35333333 | Q194: =L194 -> -0.37 | V194: -0.42607214 | W194: -0.35661287 | AT194: -0.35 | AU194: -0.34666667 | AV194: -0.34462489 | AW194: -0.34 | AX194: -0.32912525 | AY194: -0.30811134 | BJ194: =+AT193*1 -> -0.35333333 | BK194: =+AU192*1 -> -0.35666667 | BL194: =+AV191*1 -> -0.35541549 | BM194: =+AW190*1 -> -0.34 | BN194: =+AX189*1 -> -0.35661287 | BO194: =+AY188*1 -> -0.42607214
A195: 43281 | D195: -0.0925 | K195: =+A195 -> 43281 | L195: =+D195*4 -> -0.37 | M195: -0.33337183 | N195: -0.34666667 | O195: -0.35323179 | P195: -0.35333333 | Q195: -0.35 | R195: =L195 -> -0.37 | W195: -0.3559707 | AT195: -0.36 | AU195: -0.35666667 | AV195: -0.35459513 | AW195: -0.35 | AX195: -0.3404943 | AY195: -0.32303197 | BJ195: =+AT194*1 -> -0.35 | BK195: =+AU193*1 -> -0.35333333 | BL195: =+AV192*1 -> -0.35323179 | BM195: =+AW191*1 -> -0.34666667 | BN195: =+AX190*1 -> -0.33337183 | BO195: =+AY189*1 -> -0.3559707
A196: 43373 | D196: -0.0925 | K196: =+A196 -> 43373 | L196: =+D196*4 -> -0.37 | M196: -0.32484903 | N196: -0.33724223 | O196: -0.34666667 | P196: -0.3511039 | Q196: -0.34666667 | R196: -0.36 | S196: =L196 -> -0.37 | AT196: -0.36 | AU196: -0.35666667 | AV196: -0.35561046 | AW196: -0.35333333 | AX196: -0.34550145 | AY196: -0.32822351 | BJ196: =+AT195*1 -> -0.36 | BK196: =+AU194*1 -> -0.34666667 | BL196: =+AV193*1 -> -0.3511039 | BM196: =+AW192*1 -> -0.34666667 | BN196: =+AX191*1 -> -0.33724223 | BO196: =+AY190*1 -> -0.32484903
A197: 43465 | D197: -0.0925 | K197: =+A197 -> 43465 | L197: =+D197*4 -> -0.37 | N197: -0.3256968 | O197: -0.33835347 | P197: -0.34666667 | Q197: -0.34462489 | R197: -0.35666667 | S197: -0.36 | T197: =L197 -> -0.37 | AT197: -0.35666667 | AU197: -0.35666667 | AV197: -0.35300152 | AW197: -0.34666667 | AX197: -0.3344485 | AY197: -0.31395422 | BJ197: =+AT196*1 -> -0.36 | BK197: =+AU195*1 -> -0.35666667 | BL197: =+AV194*1 -> -0.34462489 | BM197: =+AW193*1 -> -0.34666667 | BN197: =+AX192*1 -> -0.33835347 | BO197: =+AY191*1 -> -0.3256968
A198: 43555 | D198: -0.0925 | K198: =+A198 -> 43555 | L198: =+D198*4 -> -0.37 | O198: -0.32631419 | P198: -0.33985998 | Q198: -0.34 | R198: -0.35459513 | S198: -0.35666667 | T198: -0.35666667 | U198: =L198 -> -0.37 | AT198: -0.36 | AU198: -0.36 | AV198: -0.35671992 | AW198: -0.35 | AX198: -0.3413385 | AY198: -0.32933793 | BJ198: =+AT197*1 -> -0.35666667 | BK198: =+AU196*1 -> -0.35666667 | BL198: =+AV195*1 -> -0.35459513 | BM198: =+AW194*1 -> -0.34 | BN198: =+AX193*1 -> -0.33985998 | BO198: =+AY192*1 -> -0.32631419
A199: 43646 | D199: -0.0925 | K199: =+A199 -> 43646 | L199: =+D199*4 -> -0.37 | P199: -0.32876443 | Q199: -0.32912525 | R199: -0.35 | S199: -0.35561046 | T199: -0.35666667 | U199: -0.36 | V199: =L199 -> -0.37 | AT199: -0.37 | AU199: -0.38333333 | AV199: -0.39086539 | AW199: -0.39666667 | AX199: -0.39944712 | AY199: -0.40061966 | BJ199: =+AT198*1 -> -0.36 | BK199: =+AU197*1 -> -0.35666667 | BL199: =+AV196*1 -> -0.35561046 | BM199: =+AW195*1 -> -0.35 | BN199: =+AX194*1 -> -0.32912525 | BO199: =+AY193*1 -> -0.32876443
A200: 43738 | D200: -0.105 | K200: =+A200 -> 43738 | L200: =+D200*4 -> -0.42 | Q200: -0.30811134 | R200: -0.3404943 | S200: -0.35333333 | T200: -0.35300152 | U200: -0.36 | V200: -0.37 | W200: =L200 -> -0.42 | AT200: -0.45333333 | AU200: -0.5 | AV200: -0.53286526 | AW200: -0.55666667 | AX200: -0.57394376 | AY200: -0.58896853 | BJ200: =+AT199*1 -> -0.37 | BK200: =+AU198*1 -> -0.36 | BL200: =+AV197*1 -> -0.35300152 | BM200: =+AW196*1 -> -0.35333333 | BN200: =+AX195*1 -> -0.3404943 | BO200: =+AY194*1 -> -0.30811134
A201: 43830 | D201: -0.1125 | K201: =+A201 -> 43830 | L201: =+D201*4 -> -0.45 | M201: =L201 -> -0.45 | R201: -0.32303197 | S201: -0.34550145 | T201: -0.34666667 | U201: -0.35671992 | V201: -0.38333333 | W201: -0.45333333 | AT201: -0.45333333 | AU201: -0.46333333 | AV201: -0.47439575 | AW201: -0.48333333 | AX201: -0.4880111 | AY201: -0.49202839 | BJ201: =+AT200*1 -> -0.45333333 | BK201: =+AU199*1 -> -0.38333333 | BL201: =+AV198*1 -> -0.35671992 | BM201: =+AW197*1 -> -0.34666667 | BN201: =+AX196*1 -> -0.34550145 | BO201: =+AY195*1 -> -0.32303197
A202: 43921 | D202: -0.1175 | K202: =+A202 -> 43921 | L202: =+D202*4 -> -0.47 | M202: -0.45333333 | N202: =L202 -> -0.47 | S202: -0.32822351 | T202: -0.3344485 | U202: -0.35 | V202: -0.39086539 | W202: -0.5 | AT202: -0.47666667 | AU202: -0.49 | AV202: -0.50224832 | AW202: -0.51 | AX202: -0.51127232 | AY202: -0.51196429 | BJ202: =+AT201*1 -> -0.45333333 | BK202: =+AU200*1 -> -0.5 | BL202: =+AV199*1 -> -0.39086539 | BM202: =+AW198*1 -> -0.35 | BN202: =+AX197*1 -> -0.3344485 | BO202: =+AY196*1 -> -0.32822351
A203: 44012 | D203: -0.115 | K203: =+A203 -> 44012 | L203: =+D203*4 -> -0.46 | M203: -0.46333333 | N203: -0.47666667 | O203: =L203 -> -0.46 | T203: -0.31395422 | U203: -0.3413385 | V203: -0.39666667 | W203: -0.53286526 | AT203: -0.46666667 | AU203: -0.47666667 | AV203: -0.48728701 | AW203: -0.49666667 | AX203: -0.5039688 | AY203: -0.51056486 | BJ203: =+AT202*1 -> -0.47666667 | BK203: =+AU201*1 -> -0.46333333 | BL203: =+AV200*1 -> -0.53286526 | BM203: =+AW199*1 -> -0.39666667 | BN203: =+AX198*1 -> -0.3413385 | BO203: =+AY197*1 -> -0.31395422
A204: 44104 | D204: -0.13 | K204: =+A204 -> 44104 | L204: =+D204*4 -> -0.52 | M204: -0.47439575 | N204: -0.49 | O204: -0.46666667 | P204: =L204 -> -0.52 | U204: -0.32933793 | V204: -0.39944712 | W204: -0.55666667 | AT204: -0.46666667 | AU204: -0.48 | AV204: -0.49094086 | AW204: -0.5 | AX204: -0.50730213 | AY204: -0.51389819 | BJ204: =+AT203*1 -> -0.46666667 | BK204: =+AU202*1 -> -0.49 | BL204: =+AV201*1 -> -0.47439575 | BM204: =+AW200*1 -> -0.55666667 | BN204: =+AX199*1 -> -0.39944712 | BO204: =+AY198*1 -> -0.32933793
A205: 44196 | D205: -0.1375 | K205: =+A205 -> 44196 | L205: =+D205*4 -> -0.55 | M205: -0.48333333 | N205: -0.50224832 | O205: -0.47666667 | P205: -0.46666667 | Q205: =L205 -> -0.55 | V205: -0.40061966 | W205: -0.57394376 | AT205: -0.48 | AU205: -0.49 | AV205: -0.50229236 | AW205: -0.51333333 | AX205: -0.52115785 | AY205: -0.52806624 | BJ205: =+AT204*1 -> -0.46666667 | BK205: =+AU203*1 -> -0.47666667 | BL205: =+AV202*1 -> -0.50224832 | BM205: =+AW201*1 -> -0.48333333 | BN205: =+AX200*1 -> -0.57394376 | BO205: =+AY199*1 -> -0.40061966
A206: 44286 | D206: -0.1375 | K206: =+A206 -> 44286 | L206: =+D206*4 -> -0.55 | M206: -0.4880111 | N206: -0.51 | O206: -0.48728701 | P206: -0.48 | Q206: -0.48 | R206: =L206 -> -0.55 | V206: -0.48 | W206: -0.58896853 | AT206: -0.48 | AU206: -0.48666667 | AV206: -0.48987179 | AW206: -0.49333333 | AX206: -0.49637821 | AY206: -0.49974359 | BJ206: =+AT205*1 -> -0.48 | BK206: =+AU204*1 -> -0.48 | BL206: =+AV203*1 -> -0.48728701 | BM206: =+AW202*1 -> -0.51 | BN206: =+AX201*1 -> -0.4880111 | BO206: =+AY200*1 -> -0.58896853
A207: 44377 | D207: -0.14 | K207: =+A207 -> 44377 | L207: =+D207*4 -> -0.56 | M207: -0.49202839 | N207: -0.51127232 | O207: -0.49666667 | P207: -0.49094086 | Q207: -0.49 | R207: -0.48 | S207: =L207 -> -0.56 | AT207: -0.48 | AU207: -0.48 | AV207: -0.485 | AW207: -0.49 | AX207: -0.48992188 | AY207: -0.489375 | BJ207: =+AT206*1 -> -0.48 | BK207: =+AU205*1 -> -0.49 | BL207: =+AV204*1 -> -0.49094086 | BM207: =+AW203*1 -> -0.49666667 | BN207: =+AX202*1 -> -0.51127232 | BO207: =+AY201*1 -> -0.49202839
A208: 44469 | D208: -0.14 | K208: =+A208 -> 44469 | L208: =+D208*4 -> -0.56 | N208: -0.51196429 | O208: -0.5039688 | P208: -0.5 | Q208: -0.50229236 | R208: -0.48666667 | S208: -0.48 | T208: =L208 -> -0.56 | AT208: -0.48 | AU208: -0.48 | AV208: -0.485 | AW208: -0.49 | AX208: -0.48992188 | AY208: -0.489375 | BJ208: =+AT207*1 -> -0.48 | BK208: =+AU206*1 -> -0.48666667 | BL208: =+AV205*1 -> -0.50229236 | BM208: =+AW204*1 -> -0.5 | BN208: =+AX203*1 -> -0.5039688 | BO208: =+AY202*1 -> -0.51196429
A209: 44561 | D209: -0.145 | K209: =+A209 -> 44561 | L209: =+D209*4 -> -0.58 | O209: -0.51056486 | P209: -0.50730213 | Q209: -0.51333333 | R209: -0.48987179 | S209: -0.48 | T209: -0.48 | U209: =L209 -> -0.58 | AT209: -0.48 | AU209: -0.48 | AV209: -0.48 | AW209: -0.48 | BJ209: =+AT208*1 -> -0.48 | BK209: =+AU207*1 -> -0.48 | BL209: =+AV206*1 -> -0.48987179 | BM209: =+AW205*1 -> -0.51333333 | BN209: =+AX204*1 -> -0.50730213 | BO209: =+AY203*1 -> -0.51056486
A210: 44651 | D210: -0.1375 | K210: =+A210 -> 44651 | L210: =+D210*4 -> -0.55 | P210: -0.51389819 | Q210: -0.52115785 | R210: -0.49333333 | S210: -0.485 | T210: -0.48 | U210: -0.48 | AT210: -0.48 | BJ210: =+AT209*1 -> -0.48 | BK210: =+AU208*1 -> -0.48 | BL210: =+AV207*1 -> -0.485 | BM210: =+AW206*1 -> -0.49333333 | BN210: =+AX205*1 -> -0.52115785 | BO210: =+AY204*1 -> -0.51389819
A211: 44742 | D211: -0.135 | K211: =+A211 -> 44742 | L211: =+D211*4 -> -0.54 | Q211: -0.52806624 | R211: -0.49637821 | S211: -0.49 | T211: -0.485 | U211: -0.48 | BJ211: =+AT210*1 -> -0.48 | BK211: =+AU209*1 -> -0.48 | BL211: =+AV208*1 -> -0.485 | BM211: =+AW207*1 -> -0.49 | BN211: =+AX206*1 -> -0.49637821 | BO211: =+AY205*1 -> -0.52806624
A212: 44834 | D212: 0.0225 | K212: =+A212 -> 44834 | L212: =+D212*4 -> 0.09 | R212: -0.49974359 | S212: -0.48992188 | T212: -0.49 | U212: -0.48 | BL212: =+AV209*1 -> -0.48 | BM212: =+AW208*1 -> -0.49 | BN212: =+AX207*1 -> -0.48992188 | BO212: =+AY206*1 -> -0.49974359
A213: 44926 | D213: 0.3375 | K213: =+A213 -> 44926 | L213: =+D213*4 -> 1.35 | S213: -0.489375 | T213: -0.48992188 | U213: -0.48 | BM213: =+AW209*1 -> -0.48 | BN213: =+AX208*1 -> -0.48992188 | BO213: =+AY207*1 -> -0.489375
A214: 45016 | D214: 0.5875 | K214: =+A214 -> 45016 | L214: =+D214*4 -> 2.35 | T214: -0.489375 | BO214: =+AY208*1 -> -0.489375
A215: 45107 | D215: 0.7875 | K215: =+A215 -> 45107 | L215: =+D215*4 -> 3.15
A216: 45199 | D216: 0.905 | K216: =+A216 -> 45199 | L216: =+D216*4 -> 3.62
A217: 45291 | D217: 0.9625 | K217: =+A217 -> 45291 | L217: =+D217*4 -> 3.85
A218: 45382 | D218: 0.965 | K218: =+A218 -> 45382 | L218: =+D218*4 -> 3.86
A219: 45473 | D219: 0.9425 | K219: =+A219 -> 45473 | L219: =+D219*4 -> 3.77
A220: 45565 | D220: 0.8875 | K220: =+A220 -> 45565 | L220: =+D220*4 -> 3.55

Sheet Chart 2 - Real rate gaps
K1: PCECTPI (yoy growth rate inflation) - source:https://fred.stlouisfed.org/series/PCECTPI | L1: GDP percent change yoy | N1: wFG | P1: woFG
A2: observation_date | D2: obs_nominalrate | H2: PCECTPI | I2: NBER Recession | J2: NBER Recession | K2: Inflation (yoy, apr) | L2: GDP (yoy, apr) | M2: Policy rate (quarterly average, apr) | N2: Real rate gap - with FG (lhs) | O2: 5-year real rate gap - with FG (rhs) | P2: Real rate gap - without FG (lhs) | Q2: 5-year real rate gap - without FG (rhs)
A3: 25749 | D3: 1.98925 | M3: =+D3*4 -> 7.957
A4: 25841 | D4: 1.9005 | M4: =+D4*4 -> 7.602
A5: 25933 | D5: 1.8105 | I5: 4 | J5: -1 | M5: =+D5*4 -> 7.242
A6: 26023 | D6: 1.62925 | I6: 4 | J6: -1 | M6: =+D6*4 -> 6.517
A7: 26114 | D7: 1.48475 | I7: 4 | J7: -1 | M7: =+D7*4 -> 5.939
A8: 26206 | D8: 1.5565 | M8: =+D8*4 -> 6.226
A9: 26298 | D9: 1.5015 | M9: =+D9*4 -> 6.006
A10: 26389 | D10: 1.26175 | M10: =+D10*4 -> 5.047
A11: 26480 | D11: 1.1885 | M11: =+D11*4 -> 4.754 | N11: =+hist_ExAnteRealRate_wFG!D2-hist_RealNaturalRate_wFG!D2 -> -0.36357494 | O11: =+hist_Forward5YearRealR_wFG!D2-hist_Forward5YearRNatR_wFG!D2 -> -0.52204844 | P11: =+hist_ExAnteRealRate_woFG!D2-hist_RealNaturalRate_woFG!D2 -> -0.26629989 | Q11: =+hist_Forward5YearRealR_woFG!D2-hist_Forward5YearRNatR_woFG!D2 -> -0.46898451
A12: 26572 | D12: 1.21425 | M12: =+D12*4 -> 4.857 | N12: =+hist_ExAnteRealRate_wFG!D3-hist_RealNaturalRate_wFG!D3 -> -1.2219513 | O12: =+hist_Forward5YearRealR_wFG!D3-hist_Forward5YearRNatR_wFG!D3 -> -0.65867962 | P12: =+hist_ExAnteRealRate_woFG!D3-hist_RealNaturalRate_woFG!D3 -> -1.124098 | Q12: =+hist_Forward5YearRealR_woFG!D3-hist_Forward5YearRNatR_woFG!D3 -> -0.60541875
A13: 26664 | D13: 1.59875 | M13: =+D13*4 -> 6.395 | N13: =+hist_ExAnteRealRate_wFG!D4-hist_RealNaturalRate_wFG!D4 -> -1.3864478 | O13: =+hist_Forward5YearRealR_wFG!D4-hist_Forward5YearRNatR_wFG!D4 -> -0.5737134 | P13: =+hist_ExAnteRealRate_woFG!D4-hist_RealNaturalRate_woFG!D4 -> -1.2880104 | Q13: =+hist_Forward5YearRealR_woFG!D4-hist_Forward5YearRNatR_woFG!D4 -> -0.52025322
A14: 26754 | D14: 1.69775 | M14: =+D14*4 -> 6.791 | N14: =+hist_ExAnteRealRate_wFG!D5-hist_RealNaturalRate_wFG!D5 -> -1.236155 | O14: =+hist_Forward5YearRealR_wFG!D5-hist_Forward5YearRNatR_wFG!D5 -> -0.58665598 | P14: =+hist_ExAnteRealRate_woFG!D5-hist_RealNaturalRate_woFG!D5 -> -1.137129 | Q14: =+hist_Forward5YearRealR_woFG!D5-hist_Forward5YearRNatR_woFG!D5 -> -0.53299331
A15: 26845 | D15: 2.12125 | M15: =+D15*4 -> 8.485 | N15: =+hist_ExAnteRealRate_wFG!D6-hist_RealNaturalRate_wFG!D6 -> -1.8476247 | O15: =+hist_Forward5YearRealR_wFG!D6-hist_Forward5YearRNatR_wFG!D6 -> -0.53649599 | P15: =+hist_ExAnteRealRate_woFG!D6-hist_RealNaturalRate_woFG!D6 -> -1.7480062 | Q15: =+hist_Forward5YearRealR_woFG!D6-hist_Forward5YearRNatR_woFG!D6 -> -0.48262698
A16: 26937 | D16: 2.55275 | M16: =+D16*4 -> 10.211 | N16: =+hist_ExAnteRealRate_wFG!D7-hist_RealNaturalRate_wFG!D7 -> -1.9896387 | O16: =+hist_Forward5YearRealR_wFG!D7-hist_Forward5YearRNatR_wFG!D7 -> -0.44072979 | P16: =+hist_ExAnteRealRate_woFG!D7-hist_RealNaturalRate_woFG!D7 -> -1.8894245 | Q16: =+hist_Forward5YearRealR_woFG!D7-hist_Forward5YearRNatR_woFG!D7 -> -0.38664998
A17: 27029 | D17: 2.77075 | M17: =+D17*4 -> 11.083 | N17: =+hist_ExAnteRealRate_wFG!D8-hist_RealNaturalRate_wFG!D8 -> -2.62511 | O17: =+hist_Forward5YearRealR_wFG!D8-hist_Forward5YearRNatR_wFG!D8 -> -0.50477666 | P17: =+hist_ExAnteRealRate_woFG!D8-hist_RealNaturalRate_woFG!D8 -> -2.5242975 | Q17: =+hist_Forward5YearRealR_woFG!D8-hist_Forward5YearRNatR_woFG!D8 -> -0.45048113
A18: 27119 | D18: 2.80675 | M18: =+D18*4 -> 11.227 | N18: =+hist_ExAnteRealRate_wFG!D9-hist_RealNaturalRate_wFG!D9 -> -2.0339989 | O18: =+hist_Forward5YearRealR_wFG!D9-hist_Forward5YearRNatR_wFG!D9 -> -0.49549772 | P18: =+hist_ExAnteRealRate_woFG!D9-hist_RealNaturalRate_woFG!D9 -> -1.9325859 | Q18: =+hist_Forward5YearRealR_woFG!D9-hist_Forward5YearRNatR_woFG!D9 -> -0.44098113
A19: 27210 | D19: 2.86625 | M19: =+D19*4 -> 11.465 | N19: =+hist_ExAnteRealRate_wFG!D10-hist_RealNaturalRate_wFG!D10 -> -2.3277556 | O19: =+hist_Forward5YearRealR_wFG!D10-hist_Forward5YearRNatR_wFG!D10 -> -0.57816426 | P19: =+hist_ExAnteRealRate_woFG!D10-hist_RealNaturalRate_woFG!D10 -> -2.22574 | Q19: =+hist_Forward5YearRealR_woFG!D10-hist_Forward5YearRNatR_woFG!D10 -> -0.52342093
A20: 27302 | D20: 2.881 | M20: =+D20*4 -> 11.524 | N20: =+hist_ExAnteRealRate_wFG!D11-hist_RealNaturalRate_wFG!D11 -> -1.7541624 | O20: =+hist_Forward5YearRealR_wFG!D11-hist_Forward5YearRNatR_wFG!D11 -> -0.53812506 | P20: =+hist_ExAnteRealRate_woFG!D11-hist_RealNaturalRate_woFG!D11 -> -1.6515423 | Q20: =+hist_Forward5YearRealR_woFG!D11-hist_Forward5YearRNatR_woFG!D11 -> -0.48314906
A21: 27394 | D21: 2.665 | M21: =+D21*4 -> 10.66 | N21: =+hist_ExAnteRealRate_wFG!D12-hist_RealNaturalRate_wFG!D12 -> -0.74051867 | O21: =+hist_Forward5YearRealR_wFG!D12-hist_Forward5YearRNatR_wFG!D12 -> -0.51398855 | P21: =+hist_ExAnteRealRate_woFG!D12-hist_RealNaturalRate_woFG!D12 -> -0.63729214 | Q21: =+hist_Forward5YearRealR_woFG!D12-hist_Forward5YearRNatR_woFG!D12 -> -0.45877378
A22: 27484 | D22: 2.2035 | M22: =+D22*4 -> 8.814 | N22: =+hist_ExAnteRealRate_wFG!D13-hist_RealNaturalRate_wFG!D13 -> -0.60673675 | O22: =+hist_Forward5YearRealR_wFG!D13-hist_Forward5YearRNatR_wFG!D13 -> -0.61573245 | P22: =+hist_ExAnteRealRate_woFG!D13-hist_RealNaturalRate_woFG!D13 -> -0.50290192 | Q22: =+hist_Forward5YearRealR_woFG!D13-hist_Forward5YearRNatR_woFG!D13 -> -0.56027267
... A43: 29402 | D43: 3.30925 | M43: =+D43*4 -> 13.237 | N43: =+hist_ExAnteRealRate_wFG!D34-hist_RealNaturalRate_wFG!D34 -> -1.3873815 | O43: =+hist_Forward5YearRealR_wFG!D34-hist_Forward5YearRNatR_wFG!D34 -> -0.71925702 | P43: =+hist_ExAnteRealRate_woFG!D34-hist_RealNaturalRate_woFG!D34 -> -1.2700585 | Q43: =+hist_Forward5YearRealR_woFG!D34-hist_Forward5YearRNatR_woFG!D34 -> -0.65731292
A44: 29494 | D44: 3.05975 | I44: 4 | J44: -1 | M44: =+D44*4 -> 12.239 | N44: =+hist_ExAnteRealRate_wFG!D35-hist_RealNaturalRate_wFG!D35 -> -1.5875339 | O44: =+hist_Forward5YearRealR_wFG!D35-hist_Forward5YearRNatR_wFG!D35 -> -0.82989997 | P44: =+hist_ExAnteRealRate_woFG!D35-hist_RealNaturalRate_woFG!D35 -> -1.4695295 | Q44: =+hist_Forward5YearRealR_woFG!D35-hist_Forward5YearRNatR_woFG!D35 -> -0.76759531
A45: 29586 | D45: 3.16575 | I45: 4 | J45: -1 | M45: =+D45*4 -> 12.663 | N45: =+hist_ExAnteRealRate_wFG!D36-hist_RealNaturalRate_wFG!D36 -> -1.5619467 | O45: =+hist_Forward5YearRealR_wFG!D36-hist_Forward5YearRNatR_wFG!D36 -> -0.78848185 | P45: =+hist_ExAnteRealRate_woFG!D36-hist_RealNaturalRate_woFG!D36 -> -1.4432583 | Q45: =+hist_Forward5YearRealR_woFG!D36-hist_Forward5YearRNatR_woFG!D36 -> -0.72581329
A46: 29676 | D46: 3.35825 | I46: 4 | J46: -1 | M46: =+D46*4 -> 13.433 | N46: =+hist_ExAnteRealRate_wFG!D37-hist_RealNaturalRate_wFG!D37 -> -1.477445 | O46: =+hist_Forward5YearRealR_wFG!D37-hist_Forward5YearRNatR_wFG!D37 -> -0.71421912 | P46: =+hist_ExAnteRealRate_woFG!D37-hist_RealNaturalRate_woFG!D37 -> -1.3580705 | Q46: =+hist_Forward5YearRealR_woFG!D37-hist_Forward5YearRNatR_woFG!D37 -> -0.65118351
A47: 29767 | D47: 3.877 | M47: =+D47*4 -> 15.508 | N47: =+hist_ExAnteRealRate_wFG!D38-hist_RealNaturalRate_wFG!D38 -> -1.8878529 | O47: =+hist_Forward5YearRealR_wFG!D38-hist_Forward5YearRNatR_wFG!D38 -> -0.57505906 | P47: =+hist_ExAnteRealRate_woFG!D38-hist_RealNaturalRate_woFG!D38 -> -1.7677907 | Q47: =+hist_Forward5YearRealR_woFG!D38-hist_Forward5YearRNatR_woFG!D38 -> -0.5116535
A48: 29859 | D48: 4.03325 | M48: =+D48*4 -> 16.133 | N48: =+hist_ExAnteRealRate_wFG!D39-hist_RealNaturalRate_wFG!D39 -> -1.5705504 | O48: =+hist_Forward5YearRealR_wFG!D39-hist_Forward5YearRNatR_wFG!D39 -> -0.53936082 | P48: =+hist_ExAnteRealRate_woFG!D39-hist_RealNaturalRate_woFG!D39 -> -1.4497993 | Q48: =+hist_Forward5YearRealR_woFG!D39-hist_Forward5YearRNatR_woFG!D39 -> -0.47558267
A49: 29951 | D49: 3.8565 | M49: =+D49*4 -> 15.426 | N49: =+hist_ExAnteRealRate_wFG!D40-hist_RealNaturalRate_wFG!D40 -> -1.3493726 | O49: =+hist_Forward5YearRealR_wFG!D40-hist_Forward5YearRNatR_wFG!D40 -> -0.60418791 | P49: =+hist_ExAnteRealRate_woFG!D40-hist_RealNaturalRate_woFG!D40 -> -1.2279323 | Q49: =+hist_Forward5YearRealR_woFG!D40-hist_Forward5YearRNatR_woFG!D40 -> -0.54003485
A50: 30041 | D50: 3.58275 | M50: =+D50*4 -> 14.331 | N50: =+hist_ExAnteRealRate_wFG!D41-hist_RealNaturalRate_wFG!D41 -> -0.79457239 | O50: =+hist_Forward5YearRealR_wFG!D41-hist_Forward5YearRNatR_wFG!D41 -> -0.59292017 | P50: =+hist_ExAnteRealRate_woFG!D41-hist_RealNaturalRate_woFG!D41 -> -0.67244277 | Q50: =+hist_Forward5YearRealR_woFG!D41-hist_Forward5YearRNatR_woFG!D41 -> -0.52839021
A51: 30132 | D51: 3.6 | M51: =+D51*4 -> 14.4 | N51: =+hist_ExAnteRealRate_wFG!D42-hist_RealNaturalRate_wFG!D42 -> -0.95327884 | O51: =+hist_Forward5YearRealR_wFG!D42-hist_Forward5YearRNatR_wFG!D42 -> -0.52951532 | P51: =+hist_ExAnteRealRate_woFG!D42-hist_RealNaturalRate_woFG!D42 -> -0.83046086 | Q51: =+hist_Forward5YearRealR_woFG!D42-hist_Forward5YearRNatR_woFG!D42 -> -0.46460693
A52: 30224 | D52: 3.3375 | M52: =+D52*4 -> 13.35 | N52: =+hist_ExAnteRealRate_wFG!D43-hist_RealNaturalRate_wFG!D43 -> -0.37891682 | O52: =+hist_Forward5YearRealR_wFG!D43-hist_Forward5YearRNatR_wFG!D43 -> -0.53634584 | P52: =+hist_ExAnteRealRate_woFG!D43-hist_RealNaturalRate_woFG!D43 -> -0.25541222 | Q52: =+hist_Forward5YearRealR_woFG!D43-hist_Forward5YearRNatR_woFG!D43 -> -0.47105799
A53: 30316 | D53: 3.15175 | M53: =+D53*4 -> 12.607 | N53: =+hist_ExAnteRealRate_wFG!D44-hist_RealNaturalRate_wFG!D44 -> -0.7806933 | O53: =+hist_Forward5YearRealR_wFG!D44-hist_Forward5YearRNatR_wFG!D44 -> -0.59123016 | P53: =+hist_ExAnteRealRate_woFG!D44-hist_RealNaturalRate_woFG!D44 -> -0.6565048 | Q53: =+hist_Forward5YearRealR_woFG!D44-hist_Forward5YearRNatR_woFG!D44 -> -0.52556243
A54: 30406 | D54: 2.9715 | M54: =+D54*4 -> 11.886 | N54: =+hist_ExAnteRealRate_wFG!D45-hist_RealNaturalRate_wFG!D45 -> -0.63469197 | O54: =+hist_Forward5YearRealR_wFG!D45-hist_Forward5YearRNatR_wFG!D45 -> -0.586313 | P54: =+hist_ExAnteRealRate_woFG!D45-hist_RealNaturalRate_woFG!D45 -> -0.50982344 | Q54: =+hist_Forward5YearRealR_woFG!D45-hist_Forward5YearRNatR_woFG!D45 -> -0.5202658
A55: 30497 | D55: 2.962 | M55: =+D55*4 -> 11.848 | N55: =+hist_ExAnteRealRate_wFG!D46-hist_RealNaturalRate_wFG!D46 -> -0.76121868 | O55: =+hist_Forward5YearRealR_wFG!D46-hist_Forward5YearRNatR_wFG!D46 -> -0.56469454 | P55: =+hist_ExAnteRealRate_woFG!D46-hist_RealNaturalRate_woFG!D46 -> -0.63567527 | Q55: =+hist_Forward5YearRealR_woFG!D46-hist_Forward5YearRNatR_woFG!D46 -> -0.49826923
A56: 30589 | D56: 3.05475 | M56: =+D56*4 -> 12.219 | N56: =+hist_ExAnteRealRate_wFG!D47-hist_RealNaturalRate_wFG!D47 -> -0.63052788 | O56: =+hist_Forward5YearRealR_wFG!D47-hist_Forward5YearRNatR_wFG!D47 -> -0.484656 | P56: =+hist_ExAnteRealRate_woFG!D47-hist_RealNaturalRate_woFG!D47 -> -0.50431626 | Q56: =+hist_Forward5YearRealR_woFG!D47-hist_Forward5YearRNatR_woFG!D47 -> -0.41785523
A57: 30681 | D57: 3.04225 | M57: =+D57*4 -> 12.169 | N57: =+hist_ExAnteRealRate_wFG!D48-hist_RealNaturalRate_wFG!D48 -> -1.0476633 | O57: =+hist_Forward5YearRealR_wFG!D48-hist_Forward5YearRNatR_wFG!D48 -> -0.5422291 | P57: =+hist_ExAnteRealRate_woFG!D48-hist_RealNaturalRate_woFG!D48 -> -0.9207917 | Q57: =+hist_Forward5YearRealR_woFG!D48-hist_Forward5YearRNatR_woFG!D48 -> -0.47505711
A58: 30772 | D58: 2.858 | M58: =+D58*4 -> 11.432 | N58: =+hist_ExAnteRealRate_wFG!D49-hist_RealNaturalRate_wFG!D49 -> -0.86020624 | O58: =+hist_Forward5YearRealR_wFG!D49-hist_Forward5YearRNatR_wFG!D49 -> -0.58141571 | P58: =+hist_ExAnteRealRate_woFG!D49-hist_RealNaturalRate_woFG!D49 -> -0.7326844 | Q58: =+hist_Forward5YearRealR_woFG!D49-hist_Forward5YearRNatR_woFG!D49 -> -0.51387876
A59: 30863 | D59: 2.7145 | I59: 4 | J59: -1 | M59: =+D59*4 -> 10.858 | N59: =+hist_ExAnteRealRate_wFG!D50-hist_RealNaturalRate_wFG!D50 -> -0.29091149 | O59: =+hist_Forward5YearRealR_wFG!D50-hist_Forward5YearRNatR_wFG!D50 -> -0.55507686 | P59: =+hist_ExAnteRealRate_woFG!D50-hist_RealNaturalRate_woFG!D50 -> -0.16275014 | Q59: =+hist_Forward5YearRealR_woFG!D50-hist_Forward5YearRNatR_woFG!D50 -> -0.48718379
A60: 30955 | D60: 2.6035 | I60: 4 | J60: -1 | M60: =+D60*4 -> 10.414 | N60: =+hist_ExAnteRealRate_wFG!D51-hist_RealNaturalRate_wFG!D51 -> -0.35526648 | O60: =+hist_Forward5YearRealR_wFG!D51-hist_Forward5YearRNatR_wFG!D51 -> -0.52946927 | P60: =+hist_ExAnteRealRate_woFG!D51-hist_RealNaturalRate_woFG!D51 -> -0.22647554 | Q60: =+hist_Forward5YearRealR_woFG!D51-hist_Forward5YearRNatR_woFG!D51 -> -0.46123204
A61: 31047 | D61: 2.532 | I61: 4 | J61: -1 | M61: =+D61*4 -> 10.128 | N61: =+hist_ExAnteRealRate_wFG!D52-hist_RealNaturalRate_wFG!D52 -> -0.6850469 | O61: =+hist_Forward5YearRealR_wFG!D52-hist_Forward5YearRNatR_wFG!D52 -> -0.54055676 | P61: =+hist_ExAnteRealRate_woFG!D52-hist_RealNaturalRate_woFG!D52 -> -0.55563099 | Q61: =+hist_Forward5YearRealR_woFG!D52-hist_Forward5YearRNatR_woFG!D52 -> -0.47199114
A62: 31137 | D62: 2.46575 | I62: 4 | J62: -1 | M62: =+D62*4 -> 9.863 | N62: =+hist_ExAnteRealRate_wFG!D53-hist_RealNaturalRate_wFG!D53 -> -0.95518435 | O62: =+hist_Forward5YearRealR_wFG!D53-hist_Forward5YearRNatR_wFG!D53 -> -0.59653091 | P62: =+hist_ExAnteRealRate_woFG!D53-hist_RealNaturalRate_woFG!D53 -> -0.8251319 | Q62: =+hist_Forward5YearRealR_woFG!D53-hist_Forward5YearRNatR_woFG!D53 -> -0.52765674
A63: 31228 | D63: 2.4905 | I63: 4 | J63: -1 | M63: =+D63*4 -> 9.962 | N63: =+hist_ExAnteRealRate_wFG!D54-hist_RealNaturalRate_wFG!D54 -> -0.9524679 | O63: =+hist_Forward5YearRealR_wFG!D54-hist_Forward5YearRNatR_wFG!D54 -> -0.55344901 | P63: =+hist_ExAnteRealRate_woFG!D54-hist_RealNaturalRate_woFG!D54 -> -0.82188543 | Q63: =+hist_Forward5YearRealR_woFG!D54-hist_Forward5YearRNatR_woFG!D54 -> -0.48432872
A64: 31320 | D64: 2.33675 | I64: 4 | J64: -1 | M64: =+D64*4 -> 9.347 | N64: =+hist_ExAnteRealRate_wFG!D55-hist_RealNaturalRate_wFG!D55 -> -0.72845728 | O64: =+hist_Forward5YearRealR_wFG!D55-hist_Forward5YearRNatR_wFG!D55 -> -0.57753761 | P64: =+hist_ExAnteRealRate_woFG!D55-hist_RealNaturalRate_woFG!D55 -> -0.59743734 | Q64: =+hist_Forward5YearRealR_woFG!D55-hist_Forward5YearRNatR_woFG!D55 -> -0.50820565
A65: 31412 | D65: 2.157 | M65: =+D65*4 -> 8.628 | N65: =+hist_ExAnteRealRate_wFG!D56-hist_RealNaturalRate_wFG!D56 -> -0.47305347 | O65: =+hist_Forward5YearRealR_wFG!D56-hist_Forward5YearRNatR_wFG!D56 -> -0.58577184 | P65: =+hist_ExAnteRealRate_woFG!D56-hist_RealNaturalRate_woFG!D56 -> -0.34166606 | Q65: =+hist_Forward5YearRealR_woFG!D56-hist_Forward5YearRNatR_woFG!D56 -> -0.51625592
A66: 31502 | D66: 2.18725 | M66: =+D66*4 -> 8.749 | N66: =+hist_ExAnteRealRate_wFG!D57-hist_RealNaturalRate_wFG!D57 -> -0.20915521 | O66: =+hist_Forward5YearRealR_wFG!D57-hist_Forward5YearRNatR_wFG!D57 -> -0.50121851 | P66: =+hist_ExAnteRealRate_woFG!D57-hist_RealNaturalRate_woFG!D57 -> -0.07745171 | Q66: =+hist_Forward5YearRealR_woFG!D57-hist_Forward5YearRNatR_woFG!D57 -> -0.43154089
A67: 31593 | D67: 2.007 | M67: =+D67*4 -> 8.028 | N67: =+hist_ExAnteRealRate_wFG!D58-hist_RealNaturalRate_wFG!D58 -> -0.84675319 | O67: =+hist_Forward5YearRealR_wFG!D58-hist_Forward5YearRNatR_wFG!D58 -> -0.5568232 | P67: =+hist_ExAnteRealRate_woFG!D58-hist_RealNaturalRate_woFG!D58 -> -0.71476974 | Q67: =+hist_Forward5YearRealR_woFG!D58-hist_Forward5YearRNatR_woFG!D58 -> -0.48700179
A68: 31685 | D68: 1.93825 | M68: =+D68*4 -> 7.753 | N68: =+hist_ExAnteRealRate_wFG!D59-hist_RealNaturalRate_wFG!D59 -> -0.39715266 | O68: =+hist_Forward5YearRealR_wFG!D59-hist_Forward5YearRNatR_wFG!D59 -> -0.51262798 | P68: =+hist_ExAnteRealRate_woFG!D59-hist_RealNaturalRate_woFG!D59 -> -0.26491327 | Q68: =+hist_Forward5YearRealR_woFG!D59-hist_Forward5YearRNatR_woFG!D59 -> -0.44267715
A69: 31777 | D69: 1.96875 | M69: =+D69*4 -> 7.875 | N69: =+hist_ExAnteRealRate_wFG!D60-hist_RealNaturalRate_wFG!D60 -> -0.66654864 | O69: =+hist_Forward5YearRealR_wFG!D60-hist_Forward5YearRNatR_wFG!D60 -> -0.51003608 | P69: =+hist_ExAnteRealRate_woFG!D60-hist_RealNaturalRate_woFG!D60 -> -0.53406806 | Q69: =+hist_Forward5YearRealR_woFG!D60-hist_Forward5YearRNatR_woFG!D60 -> -0.43996735
A70: 31867 | D70: 2.02625 | M70: =+D70*4 -> 8.105 | N70: =+hist_ExAnteRealRate_wFG!D61-hist_RealNaturalRate_wFG!D61 -> -0.34742758 | O70: =+hist_Forward5YearRealR_wFG!D61-hist_Forward5YearRNatR_wFG!D61 -> -0.45962373 | P70: =+hist_ExAnteRealRate_woFG!D61-hist_RealNaturalRate_woFG!D61 -> -0.21471371 | Q70: =+hist_Forward5YearRealR_woFG!D61-hist_Forward5YearRNatR_woFG!D61 -> -0.38944629
A71: 31958 | D71: 2.1065 | M71: =+D71*4 -> 8.426 | N71: =+hist_ExAnteRealRate_wFG!D62-hist_RealNaturalRate_wFG!D62 -> -1.275016 | O71: =+hist_Forward5YearRealR_wFG!D62-hist_Forward5YearRNatR_wFG!D62 -> -0.50426973 | P71: =+hist_ExAnteRealRate_woFG!D62-hist_RealNaturalRate_woFG!D62 -> -1.1420719 | Q71: =+hist_Forward5YearRealR_woFG!D62-hist_Forward5YearRNatR_woFG!D62 -> -0.43399089
A72: 32050 | D72: 2.1225 | M72: =+D72*4 -> 8.49 | N72: =+hist_ExAnteRealRate_wFG!D63-hist_RealNaturalRate_wFG!D63 -> -0.77670654 | O72: =+hist_Forward5YearRealR_wFG!D63-hist_Forward5YearRNatR_wFG!D63 -> -0.496151 | P72: =+hist_ExAnteRealRate_woFG!D63-hist_RealNaturalRate_woFG!D63 -> -0.64353206 | Q72: =+hist_Forward5YearRealR_woFG!D63-hist_Forward5YearRNatR_woFG!D63 -> -0.42577651
A73: 32142 | D73: 2.1065 | M73: =+D73*4 -> 8.426 | N73: =+hist_ExAnteRealRate_wFG!D64-hist_RealNaturalRate_wFG!D64 -> -0.66435277 | O73: =+hist_Forward5YearRealR_wFG!D64-hist_Forward5YearRNatR_wFG!D64 -> -0.49384179 | P73: =+hist_ExAnteRealRate_woFG!D64-hist_RealNaturalRate_woFG!D64 -> -0.53094565 | Q73: =+hist_Forward5YearRealR_woFG!D64-hist_Forward5YearRNatR_woFG!D64 -> -0.42337612
A74: 32233 | D74: 1.8635 | M74: =+D74*4 -> 7.454 | N74: =+hist_ExAnteRealRate_wFG!D65-hist_RealNaturalRate_wFG!D65 -> 0.19103754 | O74: =+hist_Forward5YearRealR_wFG!D65-hist_Forward5YearRNatR_wFG!D65 -> -0.45997139 | P74: =+hist_ExAnteRealRate_woFG!D65-hist_RealNaturalRate_woFG!D65 -> 0.32468069 | Q74: =+hist_Forward5YearRealR_woFG!D65-hist_Forward5YearRNatR_woFG!D65 -> -0.38941797
A75: 32324 | D75: 1.815 | M75: =+D75*4 -> 7.26 | N75: =+hist_ExAnteRealRate_wFG!D66-hist_RealNaturalRate_wFG!D66 -> -0.22392387 | O75: =+hist_Forward5YearRealR_wFG!D66-hist_Forward5YearRNatR_wFG!D66 -> -0.46162129 | P75: =+hist_ExAnteRealRate_woFG!D66-hist_RealNaturalRate_woFG!D66 -> -0.09003969 | Q75: =+hist_Forward5YearRealR_woFG!D66-hist_Forward5YearRNatR_woFG!D66 -> -0.39098255
A76: 32416 | D76: 1.9935 | M76: =+D76*4 -> 7.974 | N76: =+hist_ExAnteRealRate_wFG!D67-hist_RealNaturalRate_wFG!D67 -> -0.90695 | O76: =+hist_Forward5YearRealR_wFG!D67-hist_Forward5YearRNatR_wFG!D67 -> -0.4621158 | P76: =+hist_ExAnteRealRate_woFG!D67-hist_RealNaturalRate_woFG!D67 -> -0.7728202 | Q76: =+hist_Forward5YearRealR_woFG!D67-hist_Forward5YearRNatR_woFG!D67 -> -0.39139348
... A83: 33054 | D83: 2.6545 | M83: =+D83*4 -> 10.618 | N83: =+hist_ExAnteRealRate_wFG!D74-hist_RealNaturalRate_wFG!D74 -> 0.10480179 | O83: =+hist_Forward5YearRealR_wFG!D74-hist_Forward5YearRNatR_wFG!D74 -> -0.1799827 | P83: =+hist_ExAnteRealRate_woFG!D74-hist_RealNaturalRate_woFG!D74 -> 0.24077547 | Q83: =+hist_Forward5YearRealR_woFG!D74-hist_Forward5YearRNatR_woFG!D74 -> -0.10868219
A84: 33146 | D84: 2.634 | I84: 4 | J84: -1 | M84: =+D84*4 -> 10.536 | N84: =+hist_ExAnteRealRate_wFG!D75-hist_RealNaturalRate_wFG!D75 -> 0.061942655 | O84: =+hist_Forward5YearRealR_wFG!D75-hist_Forward5YearRNatR_wFG!D75 -> -0.15882963 | P84: =+hist_ExAnteRealRate_woFG!D75-hist_RealNaturalRate_woFG!D75 -> 0.19819469 | Q84: =+hist_Forward5YearRealR_woFG!D75-hist_Forward5YearRNatR_woFG!D75 -> -0.087443727
A85: 33238 | D85: 2.7615 | I85: 4 | J85: -1 | M85: =+D85*4 -> 11.046 | N85: =+hist_ExAnteRealRate_wFG!D76-hist_RealNaturalRate_wFG!D76 -> -0.3776565 | O85: =+hist_Forward5YearRealR_wFG!D76-hist_Forward5YearRNatR_wFG!D76 -> -0.14927284 | P85: =+hist_ExAnteRealRate_woFG!D76-hist_RealNaturalRate_woFG!D76 -> -0.24112334 | Q85: =+hist_Forward5YearRealR_woFG!D76-hist_Forward5YearRNatR_woFG!D76 -> -0.07780031
A86: 33328 | D86: 2.77425 | M86: =+D86*4 -> 11.097 | N86: =+hist_ExAnteRealRate_wFG!D77-hist_RealNaturalRate_wFG!D77 -> -0.21341142 | O86: =+hist_Forward5YearRealR_wFG!D77-hist_Forward5YearRNatR_wFG!D77 -> -0.13600805 | P86: =+hist_ExAnteRealRate_woFG!D77-hist_RealNaturalRate_woFG!D77 -> -0.076594752 | Q86: =+hist_Forward5YearRealR_woFG!D77-hist_Forward5YearRNatR_woFG!D77 -> -0.064447591
A87: 33419 | D87: 2.6155 | M87: =+D87*4 -> 10.462 | N87: =+hist_ExAnteRealRate_wFG!D78-hist_RealNaturalRate_wFG!D78 -> -0.31268632 | O87: =+hist_Forward5YearRealR_wFG!D78-hist_Forward5YearRNatR_wFG!D78 -> -0.19448105 | P87: =+hist_ExAnteRealRate_woFG!D78-hist_RealNaturalRate_woFG!D78 -> -0.17558425 | Q87: =+hist_Forward5YearRealR_woFG!D78-hist_Forward5YearRNatR_woFG!D78 -> -0.12283134
A88: 33511 | D88: 2.6265 | M88: =+D88*4 -> 10.506 | N88: =+hist_ExAnteRealRate_wFG!D79-hist_RealNaturalRate_wFG!D79 -> -0.19940993 | O88: =+hist_Forward5YearRealR_wFG!D79-hist_Forward5YearRNatR_wFG!D79 -> -0.16912094 | P88: =+hist_ExAnteRealRate_woFG!D79-hist_RealNaturalRate_woFG!D79 -> -0.062021091 | Q88: =+hist_Forward5YearRealR_woFG!D79-hist_Forward5YearRNatR_woFG!D79 -> -0.09738065
A89: 33603 | D89: 2.683 | M89: =+D89*4 -> 10.732 | N89: =+hist_ExAnteRealRate_wFG!D80-hist_RealNaturalRate_wFG!D80 -> -0.88794954 | O89: =+hist_Forward5YearRealR_wFG!D80-hist_Forward5YearRNatR_wFG!D80 -> -0.21922546 | P89: =+hist_ExAnteRealRate_woFG!D80-hist_RealNaturalRate_woFG!D80 -> -0.7502732 | Q89: =+hist_Forward5YearRealR_woFG!D80-hist_Forward5YearRNatR_woFG!D80 -> -0.14739328
A90: 33694 | D90: 2.71225 | I90: 4 | J90: -1 | M90: =+D90*4 -> 10.849 | N90: =+hist_ExAnteRealRate_wFG!D81-hist_RealNaturalRate_wFG!D81 -> -0.7986409 | O90: =+hist_Forward5YearRealR_wFG!D81-hist_Forward5YearRNatR_wFG!D81 -> -0.20513146 | P90: =+hist_ExAnteRealRate_woFG!D81-hist_RealNaturalRate_woFG!D81 -> -0.66067707 | Q90: =+hist_Forward5YearRealR_woFG!D81-hist_Forward5YearRNatR_woFG!D81 -> -0.13320613
A91: 33785 | D91: 2.74475 | I91: 4 | J91: -1 | M91: =+D91*4 -> 10.979 | N91: =+hist_ExAnteRealRate_wFG!D82-hist_RealNaturalRate_wFG!D82 -> -0.40321599 | O91: =+hist_Forward5YearRealR_wFG!D82-hist_Forward5YearRNatR_wFG!D82 -> -0.18335956 | P91: =+hist_ExAnteRealRate_woFG!D82-hist_RealNaturalRate_woFG!D82 -> -0.26496553 | Q91: =+hist_Forward5YearRealR_woFG!D82-hist_Forward5YearRNatR_woFG!D82 -> -0.11133993
A92: 33877 | D92: 2.982 | I92: 4 | J92: -1 | M92: =+D92*4 -> 11.928 | N92: =+hist_ExAnteRealRate_wFG!D83-hist_RealNaturalRate_wFG!D83 -> -0.47883365 | O92: =+hist_Forward5YearRealR_wFG!D83-hist_Forward5YearRNatR_wFG!D83 -> -0.093725814 | P92: =+hist_ExAnteRealRate_woFG!D83-hist_RealNaturalRate_woFG!D83 -> -0.34029846 | Q92: =+hist_Forward5YearRealR_woFG!D83-hist_Forward5YearRNatR_woFG!D83 -> -0.021610804
A93: 33969 | D93: 2.863 | I93: 4 | J93: -1 | M93: =+D93*4 -> 11.452 | N93: =+hist_ExAnteRealRate_wFG!D84-hist_RealNaturalRate_wFG!D84 -> -0.7536055 | O93: =+hist_Forward5YearRealR_wFG!D84-hist_Forward5YearRNatR_wFG!D84 -> -0.19412026 | P93: =+hist_ExAnteRealRate_woFG!D84-hist_RealNaturalRate_woFG!D84 -> -0.61478866 | Q93: =+hist_Forward5YearRealR_woFG!D84-hist_Forward5YearRNatR_woFG!D84 -> -0.12190895
A94: 34059 | D94: 2.6765 | I94: 4 | J94: -1 | M94: =+D94*4 -> 10.706 | N94: =+hist_ExAnteRealRate_wFG!D85-hist_RealNaturalRate_wFG!D85 -> 0.47975054 | O94: =+hist_Forward5YearRealR_wFG!D85-hist_Forward5YearRNatR_wFG!D85 -> -0.10204904 | P94: =+hist_ExAnteRealRate_woFG!D85-hist_RealNaturalRate_woFG!D85 -> 0.61884456 | Q94: =+hist_Forward5YearRealR_woFG!D85-hist_Forward5YearRNatR_woFG!D85 -> -0.029740675
A95: 34150 | D95: 2.27275 | M95: =+D95*4 -> 9.091 | N95: =+hist_ExAnteRealRate_wFG!D86-hist_RealNaturalRate_wFG!D86 -> 0.49929809 | O95: =+hist_Forward5YearRealR_wFG!D86-hist_Forward5YearRNatR_wFG!D86 -> -0.18076379 | P95: =+hist_ExAnteRealRate_woFG!D86-hist_RealNaturalRate_woFG!D86 -> 0.6386632 | Q95: =+hist_Forward5YearRealR_woFG!D86-hist_Forward5YearRNatR_woFG!D86 -> -0.10835782
A96: 34242 | D96: 2.03 | M96: =+D96*4 -> 8.12 | N96: =+hist_ExAnteRealRate_wFG!D87-hist_RealNaturalRate_wFG!D87 -> 0.030901645 | O96: =+hist_Forward5YearRealR_wFG!D87-hist_Forward5YearRNatR_wFG!D87 -> -0.23285753 | P96: =+hist_ExAnteRealRate_woFG!D87-hist_RealNaturalRate_woFG!D87 -> 0.17052995 | Q96: =+hist_Forward5YearRealR_woFG!D87-hist_Forward5YearRNatR_woFG!D87 -> -0.16035362
A97: 34334 | D97: 1.853 | M97: =+D97*4 -> 7.412 | N97: =+hist_ExAnteRealRate_wFG!D88-hist_RealNaturalRate_wFG!D88 -> -0.11916573 | O97: =+hist_Forward5YearRealR_wFG!D88-hist_Forward5YearRNatR_wFG!D88 -> -0.28221857 | P97: =+hist_ExAnteRealRate_woFG!D88-hist_RealNaturalRate_woFG!D88 -> 0.020715716 | Q97: =+hist_Forward5YearRealR_woFG!D88-hist_Forward5YearRNatR_woFG!D88 -> -0.20961669
A98: 34424 | D98: 1.745 | M98: =+D98*4 -> 6.98 | N98: =+hist_ExAnteRealRate_wFG!D89-hist_RealNaturalRate_wFG!D89 -> -0.24627304 | O98: =+hist_Forward5YearRealR_wFG!D89-hist_Forward5YearRNatR_wFG!D89 -> -0.28303631 | P98: =+hist_ExAnteRealRate_woFG!D89-hist_RealNaturalRate_woFG!D89 -> -0.1061509 | Q98: =+hist_Forward5YearRealR_woFG!D89-hist_Forward5YearRNatR_woFG!D89 -> -0.21033674
A99: 34515 | D99: 1.6075 | M99: =+D99*4 -> 6.43 | N99: =+hist_ExAnteRealRate_wFG!D90-hist_RealNaturalRate_wFG!D90 -> 0.076119726 | O99: =+hist_Forward5YearRealR_wFG!D90-hist_Forward5YearRNatR_wFG!D90 -> -0.30186729 | P99: =+hist_ExAnteRealRate_woFG!D90-hist_RealNaturalRate_woFG!D90 -> 0.21646737 | Q99: =+hist_Forward5YearRealR_woFG!D90-hist_Forward5YearRNatR_woFG!D90 -> -0.22907068
A100: 34607 | D100: 1.5575 | M100: =+D100*4 -> 6.23 | N100: =+hist_ExAnteRealRate_wFG!D91-hist_RealNaturalRate_wFG!D91 -> 0.083402134 | O100: =+hist_Forward5YearRealR_wFG!D91-hist_Forward5YearRNatR_wFG!D91 -> -0.32799005 | P100: =+hist_ExAnteRealRate_woFG!D91-hist_RealNaturalRate_woFG!D91 -> 0.22395699 | Q100: =+hist_Forward5YearRealR_woFG!D91-hist_Forward5YearRNatR_woFG!D91 -> -0.25509748
A101: 34699 | D101: 1.5675 | E101: Gross domestic product at market prices (MNA.Q.Y.I9.W2.S1.S1.B.B1GQ._Z._Z._Z.EUR.LR.N) - Modified value (Year-to-year %-change) | M101: =+D101*4 -> 6.27 | N101: =+hist_ExAnteRealRate_wFG!D92-hist_RealNaturalRate_wFG!D92 -> 0.24646456 | O101: =+hist_Forward5YearRealR_wFG!D92-hist_Forward5YearRNatR_wFG!D92 -> -0.29149155 | P101: =+hist_ExAnteRealRate_woFG!D92-hist_RealNaturalRate_woFG!D92 -> 0.38720487 | Q101: =+hist_Forward5YearRealR_woFG!D92-hist_Forward5YearRNatR_woFG!D92 -> -0.21850461
A102: 34789 | D102: 1.68 | M102: =+D102*4 -> 6.72 | N102: =+hist_ExAnteRealRate_wFG!D93-hist_RealNaturalRate_wFG!D93 -> -0.029636856 | O102: =+hist_Forward5YearRealR_wFG!D93-hist_Forward5YearRNatR_wFG!D93 -> -0.29458687 | P102: =+hist_ExAnteRealRate_woFG!D93-hist_RealNaturalRate_woFG!D93 -> 0.11126326 | Q102: =+hist_Forward5YearRealR_woFG!D93-hist_Forward5YearRNatR_woFG!D93 -> -0.2215077
A103: 34880 | D103: 1.7675 | M103: =+D103*4 -> 7.07 | N103: =+hist_ExAnteRealRate_wFG!D94-hist_RealNaturalRate_wFG!D94 -> -0.41081069 | O103: =+hist_Forward5YearRealR_wFG!D94-hist_Forward5YearRNatR_wFG!D94 -> -0.28591844 | P103: =+hist_ExAnteRealRate_woFG!D94-hist_RealNaturalRate_woFG!D94 -> -0.26978075 | Q103: =+hist_Forward5YearRealR_woFG!D94-hist_Forward5YearRNatR_woFG!D94 -> -0.21274982
A104: 34972 | D104: 1.665 | M104: =+D104*4 -> 6.66 | N104: =+hist_ExAnteRealRate_wFG!D95-hist_RealNaturalRate_wFG!D95 -> -0.04021656 | O104: =+hist_Forward5YearRealR_wFG!D95-hist_Forward5YearRNatR_wFG!D95 -> -0.28611134 | P104: =+hist_ExAnteRealRate_woFG!D95-hist_RealNaturalRate_woFG!D95 -> 0.10090842 | Q104: =+hist_Forward5YearRealR_woFG!D95-hist_Forward5YearRNatR_woFG!D95 -> -0.21285677
A105: 35064 | D105: 1.625 | M105: =+D105*4 -> 6.5 | N105: =+hist_ExAnteRealRate_wFG!D96-hist_RealNaturalRate_wFG!D96 -> -0.021908007 | O105: =+hist_Forward5YearRealR_wFG!D96-hist_Forward5YearRNatR_wFG!D96 -> -0.25692547 | P105: =+hist_ExAnteRealRate_woFG!D96-hist_RealNaturalRate_woFG!D96 -> 0.11927193 | Q105: =+hist_Forward5YearRealR_woFG!D96-hist_Forward5YearRNatR_woFG!D96 -> -0.18358924
A106: 35155 | D106: 1.4175 | E106: 1.43 | L106: =+E106 -> 1.43 | M106: =+D106*4 -> 5.67 | N106: =+hist_ExAnteRealRate_wFG!D97-hist_RealNaturalRate_wFG!D97 -> -0.1804111 | O106: =+hist_Forward5YearRealR_wFG!D97-hist_Forward5YearRNatR_wFG!D97 -> -0.35113032 | P106: =+hist_ExAnteRealRate_woFG!D97-hist_RealNaturalRate_woFG!D97 -> -0.039222123 | Q106: =+hist_Forward5YearRealR_woFG!D97-hist_Forward5YearRNatR_woFG!D97 -> -0.27771755
A107: 35246 | D107: 1.2975 | E107: 1.44 | L107: =+E107 -> 1.44 | M107: =+D107*4 -> 5.19 | N107: =+hist_ExAnteRealRate_wFG!D98-hist_RealNaturalRate_wFG!D98 -> -0.048398722 | O107: =+hist_Forward5YearRealR_wFG!D98-hist_Forward5YearRNatR_wFG!D98 -> -0.31938207 | P107: =+hist_ExAnteRealRate_woFG!D98-hist_RealNaturalRate_woFG!D98 -> 0.092746965 | Q107: =+hist_Forward5YearRealR_woFG!D98-hist_Forward5YearRNatR_woFG!D98 -> -0.24589874
A108: 35338 | D108: 1.25 | E108: 1.66 | L108: =+E108 -> 1.66 | M108: =+D108*4 -> 5 | N108: =+hist_ExAnteRealRate_wFG!D99-hist_RealNaturalRate_wFG!D99 -> -0.074922026 | O108: =+hist_Forward5YearRealR_wFG!D99-hist_Forward5YearRNatR_wFG!D99 -> -0.33356547 | P108: =+hist_ExAnteRealRate_woFG!D99-hist_RealNaturalRate_woFG!D99 -> 0.066120941 | Q108: =+hist_Forward5YearRealR_woFG!D99-hist_Forward5YearRNatR_woFG!D99 -> -0.26001838
A109: 35430 | B109: TIME PERIOD | C109: HICP - Overall index (ICP.M.U2.N.000000.4.ANR) - Modified value (Quarterly) | D109: 1.1575 | E109: 2 | L109: =+E109 -> 2 | M109: =+D109*4 -> 4.63 | N109: =+hist_ExAnteRealRate_wFG!D100-hist_RealNaturalRate_wFG!D100 -> 0.065720639 | O109: =+hist_Forward5YearRealR_wFG!D100-hist_Forward5YearRNatR_wFG!D100 -> -0.32380689 | P109: =+hist_ExAnteRealRate_woFG!D100-hist_RealNaturalRate_woFG!D100 -> 0.2065935 | Q109: =+hist_Forward5YearRealR_woFG!D100-hist_Forward5YearRNatR_woFG!D100 -> -0.25020355
A110: 35520 | B110: 1997Q1 | C110: 1.8 | D110: 1.1225 | E110: 2.14 | H110: =+C110 -> 1.8 | K110: =+C110 -> 1.8 | L110: =+E110 -> 2.14 | M110: =+D110*4 -> 4.49 | N110: =+hist_ExAnteRealRate_wFG!D101-hist_RealNaturalRate_wFG!D101 -> -0.061481869 | O110: =+hist_Forward5YearRealR_wFG!D101-hist_Forward5YearRNatR_wFG!D101 -> -0.32484362 | P110: =+hist_ExAnteRealRate_woFG!D101-hist_RealNaturalRate_woFG!D101 -> 0.079144253 | Q110: =+hist_Forward5YearRealR_woFG!D101-hist_Forward5YearRNatR_woFG!D101 -> -0.25119203
A111: 35611 | B111: 1997Q2 | C111: 1.4 | D111: 1.08 | E111: 2.55 | H111: =+C111 -> 1.4 | K111: =+C111 -> 1.4 | L111: =+E111 -> 2.55 | M111: =+D111*4 -> 4.32 | N111: =+hist_ExAnteRealRate_wFG!D102-hist_RealNaturalRate_wFG!D102 -> -0.02550331 | O111: =+hist_Forward5YearRealR_wFG!D102-hist_Forward5YearRNatR_wFG!D102 -> -0.30605684 | P111: =+hist_ExAnteRealRate_woFG!D102-hist_RealNaturalRate_woFG!D102 -> 0.11478796 | Q111: =+hist_Forward5YearRealR_woFG!D102-hist_Forward5YearRNatR_woFG!D102 -> -0.23236506
A112: 35703 | B112: 1997Q3 | C112: 1.6 | D112: 1.0725 | E112: 2.87 | H112: =+C112 -> 1.6 | K112: =+C112 -> 1.6 | L112: =+E112 -> 2.87 | M112: =+D112*4 -> 4.29 | N112: =+hist_ExAnteRealRate_wFG!D103-hist_RealNaturalRate_wFG!D103 -> -0.29833021 | O112: =+hist_Forward5YearRealR_wFG!D103-hist_Forward5YearRNatR_wFG!D103 -> -0.32580173 | P112: =+hist_ExAnteRealRate_woFG!D103-hist_RealNaturalRate_woFG!D103 -> -0.15847771 | Q112: =+hist_Forward5YearRealR_woFG!D103-hist_Forward5YearRNatR_woFG!D103 -> -0.25207728
A113: 35795 | B113: 1997Q4 | C113: 1.5 | D113: 1.095 | E113: 3.37 | H113: =+C113 -> 1.5 | K113: =+C113 -> 1.5 | L113: =+E113 -> 3.37 | M113: =+D113*4 -> 4.38 | N113: =+hist_ExAnteRealRate_wFG!D104-hist_RealNaturalRate_wFG!D104 -> -0.66953885 | O113: =+hist_Forward5YearRealR_wFG!D104-hist_Forward5YearRNatR_wFG!D104 -> -0.34383994 | P113: =+hist_ExAnteRealRate_woFG!D104-hist_RealNaturalRate_woFG!D104 -> -0.53025421 | Q113: =+hist_Forward5YearRealR_woFG!D104-hist_Forward5YearRNatR_woFG!D104 -> -0.27008911
A114: 35885 | B114: 1998Q1 | C114: 1.1 | D114: 1.0525 | E114: 3.79 | H114: =+C114 -> 1.1 | K114: =+C114 -> 1.1 | L114: =+E114 -> 3.79 | M114: =+D114*4 -> 4.21 | N114: =+hist_ExAnteRealRate_wFG!D105-hist_RealNaturalRate_wFG!D105 -> -0.28152265 | O114: =+hist_Forward5YearRealR_wFG!D105-hist_Forward5YearRNatR_wFG!D105 -> -0.3067965 | P114: =+hist_ExAnteRealRate_woFG!D105-hist_RealNaturalRate_woFG!D105 -> -0.14327752 | Q114: =+hist_Forward5YearRealR_woFG!D105-hist_Forward5YearRNatR_woFG!D105 -> -0.23290128
A115: 35976 | B115: 1998Q2 | C115: 1.3 | D115: 1.0175 | E115: 2.98 | H115: =+C115 -> 1.3 | K115: =+C115 -> 1.3 | L115: =+E115 -> 2.98 | M115: =+D115*4 -> 4.07 | N115: =+hist_ExAnteRealRate_wFG!D106-hist_RealNaturalRate_wFG!D106 -> -0.28876514 | O115: =+hist_Forward5YearRealR_wFG!D106-hist_Forward5YearRNatR_wFG!D106 -> -0.30722369 | P115: =+hist_ExAnteRealRate_woFG!D106-hist_RealNaturalRate_woFG!D106 -> -0.15147577 | Q115: =+hist_Forward5YearRealR_woFG!D106-hist_Forward5YearRNatR_woFG!D106 -> -0.23314645
A116: 36068 | B116: 1998Q3 | C116: 1.1 | D116: 0.9875 | E116: 2.71 | H116: =+C116 -> 1.1 | K116: =+C116 -> 1.1 | L116: =+E116 -> 2.71 | M116: =+D116*4 -> 3.95 | N116: =+hist_ExAnteRealRate_wFG!D107-hist_RealNaturalRate_wFG!D107 -> -0.64753312 | O116: =+hist_Forward5YearRealR_wFG!D107-hist_Forward5YearRNatR_wFG!D107 -> -0.35406508 | P116: =+hist_ExAnteRealRate_woFG!D107-hist_RealNaturalRate_woFG!D107 -> -0.51127906 | Q116: =+hist_Forward5YearRealR_woFG!D107-hist_Forward5YearRNatR_woFG!D107 -> -0.2798121
A117: 36160 | B117: 1998Q4 | C117: 0.8 | D117: 0.915 | E117: 1.95 | H117: =+C117 -> 0.8 | K117: =+C117 -> 0.8 | L117: =+E117 -> 1.95 | M117: =+D117*4 -> 3.66 | N117: =+hist_ExAnteRealRate_wFG!D108-hist_RealNaturalRate_wFG!D108 -> -0.60217954 | O117: =+hist_Forward5YearRealR_wFG!D108-hist_Forward5YearRNatR_wFG!D108 -> -0.38314451 | P117: =+hist_ExAnteRealRate_woFG!D108-hist_RealNaturalRate_woFG!D108 -> -0.46710114 | Q117: =+hist_Forward5YearRealR_woFG!D108-hist_Forward5YearRNatR_woFG!D108 -> -0.30872409
A118: 36250 | B118: 1999Q1 | C118: 0.8 | D118: 0.7775 | E118: 2.25 | H118: =+C118 -> 0.8 | K118: =+C118 -> 0.8 | L118: =+E118 -> 2.25 | M118: =+D118*4 -> 3.11 | N118: =+hist_ExAnteRealRate_wFG!D109-hist_RealNaturalRate_wFG!D109 -> -0.52193973 | O118: =+hist_Forward5YearRealR_wFG!D109-hist_Forward5YearRNatR_wFG!D109 -> -0.39189895 | P118: =+hist_ExAnteRealRate_woFG!D109-hist_RealNaturalRate_woFG!D109 -> -0.38820878 | Q118: =+hist_Forward5YearRealR_woFG!D109-hist_Forward5YearRNatR_woFG!D109 -> -0.31732129
A119: 36341 | B119: 1999Q2 | C119: 1 | D119: 0.655 | E119: 2.33 | H119: =+C119 -> 1 | K119: =+C119 -> 1 | L119: =+E119 -> 2.33 | M119: =+D119*4 -> 2.62 | N119: =+hist_ExAnteRealRate_wFG!D110-hist_RealNaturalRate_wFG!D110 -> -0.45099452 | O119: =+hist_Forward5YearRealR_wFG!D110-hist_Forward5YearRNatR_wFG!D110 -> -0.43452035 | P119: =+hist_ExAnteRealRate_woFG!D110-hist_RealNaturalRate_woFG!D110 -> -0.31872883 | Q119: =+hist_Forward5YearRealR_woFG!D110-hist_Forward5YearRNatR_woFG!D110 -> -0.35976171
A120: 36433 | B120: 1999Q3 | C120: 1.1 | D120: 0.6525 | E120: 3.13 | H120: =+C120 -> 1.1 | K120: =+C120 -> 1.1 | L120: =+E120 -> 3.13 | M120: =+D120*4 -> 2.61 | N120: =+hist_ExAnteRealRate_wFG!D111-hist_RealNaturalRate_wFG!D111 -> -0.53364391 | O120: =+hist_Forward5YearRealR_wFG!D111-hist_Forward5YearRNatR_wFG!D111 -> -0.45606886 | P120: =+hist_ExAnteRealRate_woFG!D111-hist_RealNaturalRate_woFG!D111 -> -0.40317704 | Q120: =+hist_Forward5YearRealR_woFG!D111-hist_Forward5YearRNatR_woFG!D111 -> -0.38113543
A121: 36525 | B121: 1999Q4 | C121: 1.5 | D121: 0.7775 | E121: 3.9 | H121: =+C121 -> 1.5 | K121: =+C121 -> 1.5 | L121: =+E121 -> 3.9 | M121: =+D121*4 -> 3.11 | N121: =+hist_ExAnteRealRate_wFG!D112-hist_RealNaturalRate_wFG!D112 -> -0.62907387 | O121: =+hist_Forward5YearRealR_wFG!D112-hist_Forward5YearRNatR_wFG!D112 -> -0.43664764 | P121: =+hist_ExAnteRealRate_woFG!D112-hist_RealNaturalRate_woFG!D112 -> -0.50068364 | Q121: =+hist_Forward5YearRealR_woFG!D112-hist_Forward5YearRNatR_woFG!D112 -> -0.36154774
... A125: 36891 | B125: 2000Q4 | C125: 2.5 | D125: 1.2275 | E125: 3.38 | H125: =+C125 -> 2.5 | K125: =+C125 -> 2.5 | L125: =+E125 -> 3.38 | M125: =+D125*4 -> 4.91 | N125: =+hist_ExAnteRealRate_wFG!D116-hist_RealNaturalRate_wFG!D116 -> -0.98230097 | O125: =+hist_Forward5YearRealR_wFG!D116-hist_Forward5YearRNatR_wFG!D116 -> -0.43698349 | P125: =+hist_ExAnteRealRate_woFG!D116-hist_RealNaturalRate_woFG!D116 -> -0.86552453 | Q125: =+hist_Forward5YearRealR_woFG!D116-hist_Forward5YearRNatR_woFG!D116 -> -0.36127407
A126: 36981 | B126: 2001Q1 | C126: 2.1 | D126: 1.1975 | E126: 3.19 | H126: =+C126 -> 2.1 | I126: 4 | J126: -1 | K126: =+C126 -> 2.1 | L126: =+E126 -> 3.19 | M126: =+D126*4 -> 4.79 | N126: =+hist_ExAnteRealRate_wFG!D117-hist_RealNaturalRate_wFG!D117 -> -1.0986754 | O126: =+hist_Forward5YearRealR_wFG!D117-hist_Forward5YearRNatR_wFG!D117 -> -0.45553398 | P126: =+hist_ExAnteRealRate_woFG!D117-hist_RealNaturalRate_woFG!D117 -> -0.98577984 | Q126: =+hist_Forward5YearRealR_woFG!D117-hist_Forward5YearRNatR_woFG!D117 -> -0.37968565
A127: 37072 | B127: 2001Q2 | C127: 2.9 | D127: 1.165 | E127: 2.31 | H127: =+C127 -> 2.9 | I127: 4 | J127: -1 | K127: =+C127 -> 2.9 | L127: =+E127 -> 2.31 | M127: =+D127*4 -> 4.66 | N127: =+hist_ExAnteRealRate_wFG!D118-hist_RealNaturalRate_wFG!D118 -> -0.92665426 | O127: =+hist_Forward5YearRealR_wFG!D118-hist_Forward5YearRNatR_wFG!D118 -> -0.47041422 | P127: =+hist_ExAnteRealRate_woFG!D118-hist_RealNaturalRate_woFG!D118 -> -0.81806261 | Q127: =+hist_Forward5YearRealR_woFG!D118-hist_Forward5YearRNatR_woFG!D118 -> -0.39442493
A128: 37164 | B128: 2001Q3 | C128: 2.3 | D128: 1.085 | E128: 1.85 | H128: =+C128 -> 2.3 | I128: 4 | J128: -1 | K128: =+C128 -> 2.3 | L128: =+E128 -> 1.85 | M128: =+D128*4 -> 4.34 | N128: =+hist_ExAnteRealRate_wFG!D119-hist_RealNaturalRate_wFG!D119 -> -0.58387499 | O128: =+hist_Forward5YearRealR_wFG!D119-hist_Forward5YearRNatR_wFG!D119 -> -0.47195192 | P128: =+hist_ExAnteRealRate_woFG!D119-hist_RealNaturalRate_woFG!D119 -> -0.48012073 | Q128: =+hist_Forward5YearRealR_woFG!D119-hist_Forward5YearRNatR_woFG!D119 -> -0.39582548
A129: 37256 | B129: 2001Q4 | C129: 2.1 | D129: 0.88 | E129: 1.31 | H129: =+C129 -> 2.1 | K129: =+C129 -> 2.1 | L129: =+E129 -> 1.31 | M129: =+D129*4 -> 3.52 | N129: =+hist_ExAnteRealRate_wFG!D120-hist_RealNaturalRate_wFG!D120 -> -0.19966875 | O129: =+hist_Forward5YearRealR_wFG!D120-hist_Forward5YearRNatR_wFG!D120 -> -0.48858422 | P129: =+hist_ExAnteRealRate_woFG!D120-hist_RealNaturalRate_woFG!D120 -> -0.10133717 | Q129: =+hist_Forward5YearRealR_woFG!D120-hist_Forward5YearRNatR_woFG!D120 -> -0.41232454
...

Sheet Decomposition
A1: Date | B1: Trend Growth (g), Annualized | C1: Other Determinants (z) | D1: HLW r* | E1: Trend Growth (g), Annualized | F1: Other Determinants (z) | G1: HLW r*
A2: 22282 | B2: =+'2025Q2'!E7 -> NA | C2: =+'2025Q2'!I7 -> NA | D2: =+'2025Q2'!M7 -> NA
A3: 22372 | B3: =+'2025Q2'!E8 -> NA | C3: =+'2025Q2'!I8 -> NA | D3: =+'2025Q2'!M8 -> NA
A4: 22463 | B4: =+'2025Q2'!E9 -> NA | C4: =+'2025Q2'!I9 -> NA | D4: =+'2025Q2'!M9 -> NA
A5: 22555 | B5: =+'2025Q2'!E10 -> NA | C5: =+'2025Q2'!I10 -> NA | D5: =+'2025Q2'!M10 -> NA
A6: 22647 | B6: =+'2025Q2'!E11 -> NA | C6: =+'2025Q2'!I11 -> NA | D6: =+'2025Q2'!M11 -> NA
A7: 22737 | B7: =+'2025Q2'!E12 -> NA | C7: =+'2025Q2'!I12 -> NA | D7: =+'2025Q2'!M12 -> NA
A8: 22828 | B8: =+'2025Q2'!E13 -> NA | C8: =+'2025Q2'!I13 -> NA | D8: =+'2025Q2'!M13 -> NA
A9: 22920 | B9: =+'2025Q2'!E14 -> NA | C9: =+'2025Q2'!I14 -> NA | D9: =+'2025Q2'!M14 -> NA
A10: 23012 | B10: =+'2025Q2'!E15 -> NA | C10: =+'2025Q2'!I15 -> NA | D10: =+'2025Q2'!M15 -> NA
A11: 23102 | B11: =+'2025Q2'!E16 -> NA | C11: =+'2025Q2'!I16 -> NA | D11: =+'2025Q2'!M16 -> NA
A12: 23193 | B12: =+'2025Q2'!E17 -> NA | C12: =+'2025Q2'!I17 -> NA | D12: =+'2025Q2'!M17 -> NA
A13: 23285 | B13: =+'2025Q2'!E18 -> NA | C13: =+'2025Q2'!I18 -> NA | D13: =+'2025Q2'!M18 -> NA
... A184: 38899 | B184: =+'2025Q2'!E189 -> 2.0509884 | C184: =+'2025Q2'!I189 -> 0.079511346 | D184: =+'2025Q2'!M189 -> 2.0729332
A185: 38991 | B185: =+'2025Q2'!E190 -> 2.1067492 | C185: =+'2025Q2'!I190 -> 0.12603146 | D185: =+'2025Q2'!M190 -> 2.173649 | E185: =+B185-$B$185 -> 0 | F185: =+C185-$C$185 -> 0 | G185: =+D185-$D$185 -> 0
A186: 39083 | B186: =+'2025Q2'!E191 -> 2.1031823 | C186: =+'2025Q2'!I191 -> 0.12764924 | D186: =+'2025Q2'!M191 -> 2.1718 | E186: =+B186-$B$185 -> -0.0035668234 | F186: =+C186-$C$185 -> 0.0016177804 | G186: =+D186-$D$185 -> -0.0018489303
A187: 39173 | B187: =+'2025Q2'!E192 -> 2.1114349 | C187: =+'2025Q2'!I192 -> 0.1392341 | D187: =+'2025Q2'!M192 -> 2.1914058 | E187: =+B187-$B$185 -> 0.0046857333 | F187: =+C187-$C$185 -> 0.013202645 | G187: =+D187-$D$185 -> 0.01775686
A188: 39264 | B188: =+'2025Q2'!E193 -> 2.099 | C188: =+'2025Q2'!I193 -> 0.10448259 | D188: =+'2025Q2'!M193 -> 2.1445684 | E188: =+B188-$B$185 -> -0.0077491599 | F188: =+C188-$C$185 -> -0.021548865 | G188: =+D188-$D$185 -> -0.029080523
A189: 39356 | B189: =+'2025Q2'!E194 -> 2.0960123 | C189: =+'2025Q2'!I194 -> 0.3022267 | D189: =+'2025Q2'!M194 -> 2.3394087 | E189: =+B189-$B$185 -> -0.010736909 | F189: =+C189-$C$185 -> 0.17619524 | G189: =+D189-$D$185 -> 0.16575969
A190: 39448 | B190: =+'2025Q2'!E195 -> 2.1143419 | C190: =+'2025Q2'!I195 -> 0.39070926 | D190: =+'2025Q2'!M195 -> 2.4457064 | E190: =+B190-$B$185 -> 0.007592716 | F190: =+C190-$C$185 -> 0.2646778 | G190: =+D190-$D$185 -> 0.27205741
A191: 39539 | B191: =+'2025Q2'!E196 -> 2.038651 | C191: =+'2025Q2'!I196 -> 0.073882875 | D191: =+'2025Q2'!M196 -> 2.0553136 | E191: =+B191-$B$185 -> -0.068098186 | F191: =+C191-$C$185 -> -0.052148584 | G191: =+D191-$D$185 -> -0.11833541
A192: 39630 | B192: =+'2025Q2'!E197 -> 1.9751943 | C192: =+'2025Q2'!I197 -> 0.01247776 | D192: =+'2025Q2'!M197 -> 1.9322328 | E192: =+B192-$B$185 -> -0.1315549 | F192: =+C192-$C$185 -> -0.1135537 | G192: =+D192-$D$185 -> -0.24141615
A193: 39722 | B193: =+'2025Q2'!E198 -> 1.8233127 | C193: =+'2025Q2'!I198 -> -0.36081338 | D193: =+'2025Q2'!M198 -> 1.4113231 | E193: =+B193-$B$185 -> -0.28343648 | F193: =+C193-$C$185 -> -0.48684484 | G193: =+D193-$D$185 -> -0.7623259
A194: 39814 | B194: =+'2025Q2'!E199 -> 1.56992 | C194: =+'2025Q2'!I199 -> -0.80048459 | D194: =+'2025Q2'!M199 -> 0.72537129 | E194: =+B194-$B$185 -> -0.53682921 | F194: =+C194-$C$185 -> -0.92651605 | G194: =+D194-$D$185 -> -1.4482777
A195: 39904 | B195: =+'2025Q2'!E200 -> 1.6687866 | C195: =+'2025Q2'!I200 -> -0.83151963 | D195: =+'2025Q2'!M200 -> 0.79042797 | E195: =+B195-$B$185 -> -0.43796251 | F195: =+C195-$C$185 -> -0.95755109 | G195: =+D195-$D$185 -> -1.383221
A196: 39995 | B196: =+'2025Q2'!E201 -> 1.7034486 | C196: =+'2025Q2'!I201 -> -0.79110413 | D196: =+'2025Q2'!M201 -> 0.86453257 | E196: =+B196-$B$185 -> -0.40330053 | F196: =+C196-$C$185 -> -0.91713559 | G196: =+D196-$D$185 -> -1.3091164
... A259: 45748 | B259: =+'2025Q2'!E264 -> 1.2634939 | C259: =+'2025Q2'!I264 -> -1.0188489 | D259: =+'2025Q2'!M264 -> 0.20918164 | E259: =+B259-$B$185 -> -0.84325525 | F259: =+C259-$C$185 -> -1.1448803 | G259: =+D259-$D$185 -> -1.9644673

Sheet DSGE HVD wFG
A1: date | B1: g | C1: b_liq | D1: b_safe | E1: FF | F1: z | G1: p-mkp | H1: w-mkp | I1: pol | J1: fg1 | K1: fg2 | L1: fg3 | M1: fg4 | N1: fg5 | O1: fg6 | P1: pi-LR | Q1: mu | R1: me | S1: zp | T1: dt | U1: DSGE r* | X1: Chart | Y1: Date | Z1: Government | AA1: Liquidity | AB1: Safety | AC1: Technology | AD1: Financial Frictions | AE1: Investment Specific Technology | AF1: Price Markups | AG1: Wage Markups | AH1: Others | AI1: DSGE r* (with FG)
A2: 39172 | B2: -0.078284074 | C2: -3.3536928 | D2: 4.0625681 | E2: -0.078929587 | F2: -0.00021463587 | G2: -1.7325996e-14 | H2: 4.9828714e-14 | I2: 9.7037389e-14 | J2: 0 | K2: 0 | L2: 0 | M2: 0 | N2: 0 | O2: 0 | P2: 1.0116916e-14 | Q2: -0.079101283 | R2: 0 | S2: 0.00018951412 | T2: 0.75299375 | U2: =+SUM(B2:T2) -> 1.225529 | Y2: =+A2 -> 39172 | Z2: =+B2 -> -0.078284074 | AA2: =+C2 -> -3.3536928 | AB2: =+D2 -> 4.0625681 | AC2: =+F2+S2 -> -2.5121749e-05 | AD2: =+E2 -> -0.078929587 | AE2: =+Q2 -> -0.079101283 | AF2: =+G2 -> -1.7325996e-14 | AG2: =+H2 -> 4.9828714e-14 | AH2: =+SUM(T2,I2:P2) -> 0.75299375 | AI2: =+SUM(Z2:AH2) -> 1.225529
A3: 39263 | B3: -0.068935732 | C3: -3.6820787 | D3: 4.8583334 | E3: -0.065752494 | F3: -0.00033729862 | G3: -1.7397732e-14 | H3: 5.0568971e-14 | I3: 9.9168848e-14 | J3: 0 | K3: 0 | L3: 0 | M3: 0 | N3: 0 | O3: 0 | P3: 1.0240682e-14 | Q3: -0.073240178 | R3: 0 | S3: -0.00019716767 | T3: 0.74523245 | U3: =+SUM(B3:T3) -> 1.7130243 | Y3: =+A3 -> 39263 | Z3: =+B3 -> -0.068935732 | AA3: =+C3 -> -3.6820787 | AB3: =+D3 -> 4.8583334 | AC3: =+F3+S3 -> -0.00053446629 | AD3: =+E3 -> -0.065752494 | AE3: =+Q3 -> -0.073240178 | AF3: =+G3 -> -1.7397732e-14 | AG3: =+H3 -> 5.0568971e-14 | AH3: =+SUM(T3,I3:P3) -> 0.74523245 | AI3: =+SUM(Z3:AH3) -> 1.7130243
A4: 39355 | B4: -0.071663741 | C4: -3.9397261 | D4: 5.2294426 | E4: -0.050365319 | F4: -0.00023177784 | G4: -1.6029971e-14 | H4: 4.8456027e-14 | I4: 9.7349024e-14 | J4: 0 | K4: 0 | L4: 0 | M4: 0 | N4: 0 | O4: 0 | P4: 1.0401761e-14 | Q4: -0.029467412 | R4: 0 | S4: -0.00076596643 | T4: 0.73754994 | U4: =+SUM(B4:T4) -> 1.8747723 | Y4: =+A4 -> 39355 | Z4: =+B4 -> -0.071663741 | AA4: =+C4 -> -3.9397261 | AB4: =+D4 -> 5.2294426 | AC4: =+F4+S4 -> -0.00099774427 | AD4: =+E4 -> -0.050365319 | AE4: =+Q4 -> -0.029467412 | AF4: =+G4 -> -1.6029971e-14 | AG4: =+H4 -> 4.8456027e-14 | AH4: =+SUM(T4,I4:P4) -> 0.73754994 | AI4: =+SUM(Z4:AH4) -> 1.8747723
A5: 39447 | B5: -0.063542094 | C5: -4.1234372 | D5: 5.4945509 | E5: -0.058856392 | F5: -0.0001388145 | G5: -1.7116864e-14 | H5: 4.8423608e-14 | I5: 9.9035455e-14 | J5: 0 | K5: 0 | L5: 0 | M5: 0 | N5: 0 | O5: 0 | P5: 1.0489179e-14 | Q5: -0.0002354462 | R5: 0 | S5: -0.00075334577 | T5: 0.72994541 | U5: =+SUM(B5:T5) -> 1.9775329 | Y5: =+A5 -> 39447 | Z5: =+B5 -> -0.063542094 | AA5: =+C5 -> -4.1234372 | AB5: =+D5 -> 5.4945509 | AC5: =+F5+S5 -> -0.00089216027 | AD5: =+E5 -> -0.058856392 | AE5: =+Q5 -> -0.0002354462 | AF5: =+G5 -> -1.7116864e-14 | AG5: =+H5 -> 4.8423608e-14 | AH5: =+SUM(T5,I5:P5) -> 0.72994541 | AI5: =+SUM(Z5:AH5) -> 1.9775329
A6: 39538 | B6: -0.064728899 | C6: -4.1837789 | D6: 5.4841232 | E6: 0.0098443971 | F6: -0.0007450019 | G6: -1.5812244e-14 | H6: 4.4077833e-14 | I6: 1.0186488e-13 | J6: 0 | K6: 0 | L6: 0 | M6: 0 | N6: 0 | O6: 0 | P6: 1.0659592e-14 | Q6: 0.054260301 | R6: 0 | S6: -0.0008088874 | T6: 0.72241806 | U6: =+SUM(B6:T6) -> 2.0205843 | Y6: =+A6 -> 39538 | Z6: =+B6 -> -0.064728899 | AA6: =+C6 -> -4.1837789 | AB6: =+D6 -> 5.4841232 | AC6: =+F6+S6 -> -0.0015538893 | AD6: =+E6 -> 0.0098443971 | AE6: =+Q6 -> 0.054260301 | AF6: =+G6 -> -1.5812244e-14 | AG6: =+H6 -> 4.4077833e-14 | AH6: =+SUM(T6,I6:P6) -> 0.72241806 | AI6: =+SUM(Z6:AH6) -> 2.0205843
A7: 39629 | B7: -0.061585403 | C7: -4.3355729 | D7: 5.8403263 | E7: 0.011744722 | F7: -0.00071597614 | G7: -1.6856279e-14 | H7: 4.7147638e-14 | I7: 9.8624591e-14 | J7: 0 | K7: 0 | L7: 0 | M7: 0 | N7: 0 | O7: 0 | P7: 1.0771832e-14 | Q7: 0.036064208 | R7: 0 | S7: -0.0015668548 | T7: 0.71496711 | U7: =+SUM(B7:T7) -> 2.2036612 | Y7: =+A7 -> 39629 | Z7: =+B7 -> -0.061585403 | AA7: =+C7 -> -4.3355729 | AB7: =+D7 -> 5.8403263 | AC7: =+F7+S7 -> -0.002282831 | AD7: =+E7 -> 0.011744722 | AE7: =+Q7 -> 0.036064208 | AF7: =+G7 -> -1.6856279e-14 | AG7: =+H7 -> 4.7147638e-14 | AH7: =+SUM(T7,I7:P7) -> 0.71496711 | AI7: =+SUM(Z7:AH7) -> 2.2036612
A8: 39721 | B8: -0.051207574 | C8: -4.4226039 | D8: 6.0498805 | E8: 0.045598632 | F8: -0.00053713845 | G8: -1.5730993e-14 | H8: 3.8444489e-14 | I8: 9.7722347e-14 | J8: 0 | K8: 0 | L8: 0 | M8: 0 | N8: 0 | O8: 0 | P8: 1.0974835e-14 | Q8: 0.098057092 | R8: 0 | S8: -0.0013954541 | T8: 0.70759176 | U8: =+SUM(B8:T8) -> 2.4253838 | Y8: =+A8 -> 39721 | Z8: =+B8 -> -0.051207574 | AA8: =+C8 -> -4.4226039 | AB8: =+D8 -> 6.0498805 | AC8: =+F8+S8 -> -0.0019325926 | AD8: =+E8 -> 0.045598632 | AE8: =+Q8 -> 0.098057092 | AF8: =+G8 -> -1.5730993e-14 | AG8: =+H8 -> 3.8444489e-14 | AH8: =+SUM(T8,I8:P8) -> 0.70759176 | AI8: =+SUM(Z8:AH8) -> 2.4253838
A9: 39813 | B9: -0.068689601 | C9: -4.7838093 | D9: 5.3758771 | E9: 0.15728435 | F9: 0.00050732851 | G9: -1.5008818e-14 | H9: 3.7023818e-14 | I9: 9.5618368e-14 | J9: 7.7636183e-16 | K9: -1.9932398e-15 | L9: 1.6186512e-15 | M9: -1.6603179e-16 | N9: -3.9430529e-16 | O9: -8.8999268e-16 | P9: 1.1161055e-14 | Q9: 0.36017357 | R9: 0 | S9: -0.00056760183 | T9: 0.70029125 | U9: =+SUM(B9:T9) -> 1.7410671 | Y9: =+A9 -> 39813 | Z9: =+B9 -> -0.068689601 | AA9: =+C9 -> -4.7838093 | AB9: =+D9 -> 5.3758771 | AC9: =+F9+S9 -> -6.027332e-05 | AD9: =+E9 -> 0.15728435 | AE9: =+Q9 -> 0.36017357 | AF9: =+G9 -> -1.5008818e-14 | AG9: =+H9 -> 3.7023818e-14 | AH9: =+SUM(T9,I9:P9) -> 0.70029125 | AI9: =+SUM(Z9:AH9) -> 1.7410671
A10: 39903 | B10: -0.073441058 | C10: -4.5362461 | D10: 5.1776753 | E10: 0.20677613 | F10: 0.0009137068 | G10: -1.5907451e-14 | H10: 3.6269444e-14 | I10: 1.0114036e-13 | J10: -2.129443e-14 | K10: 9.5471163e-16 | L10: 1.5223913e-15 | M10: -6.1157008e-16 | N10: -1.1680121e-15 | O10: -3.801997e-15 | P10: 1.1306375e-14 | Q10: 0.32451927 | R10: 0 | S10: 0.0019847909 | T10: 0.69306481 | U10: =+SUM(B10:T10) -> 1.7952468 | Y10: =+A10 -> 39903 | Z10: =+B10 -> -0.073441058 | AA10: =+C10 -> -4.5362461 | AB10: =+D10 -> 5.1776753 | AC10: =+F10+S10 -> 0.0028984977 | AD10: =+E10 -> 0.20677613 | AE10: =+Q10 -> 0.32451927 | AF10: =+G10 -> -1.5907451e-14 | AG10: =+H10 -> 3.6269444e-14 | AH10: =+SUM(T10,I10:P10) -> 0.69306481 | AI10: =+SUM(Z10:AH10) -> 1.7952468
A11: 39994 | B11: -0.07398642 | C11: -4.1428582 | D11: 4.6096002 | E11: 0.17543063 | F11: -6.3751945e-05 | G11: -1.5895798e-14 | H11: 3.0183394e-14 | I11: 1.251219e-13 | J11: -4.4403668e-14 | K11: 3.813376e-15 | L11: 1.3146739e-15 | M11: -1.417915e-15 | N11: -1.1748694e-15 | O11: -7.5474058e-15 | P11: 1.1468968e-14 | Q11: 0.20851281 | R11: 0 | S11: 0.003886969 | T11: 0.68591169 | U11: =+SUM(B11:T11) -> 1.466434 | Y11: =+A11 -> 39994 | Z11: =+B11 -> -0.07398642 | AA11: =+C11 -> -4.1428582 | AB11: =+D11 -> 4.6096002 | AC11: =+F11+S11 -> 0.003823217 | AD11: =+E11 -> 0.17543063 | AE11: =+Q11 -> 0.20851281 | AF11: =+G11 -> -1.5895798e-14 | AG11: =+H11 -> 3.0183394e-14 | AH11: =+SUM(T11,I11:P11) -> 0.68591169 | AI11: =+SUM(Z11:AH11) -> 1.466434
A12: 40086 | B12: -0.073653072 | C12: -3.4599427 | D12: 3.9612346 | E12: 0.13057815 | F12: -0.00022882546 | G12: -1.464391e-14 | H12: 2.3612202e-14 | I12: 1.4448187e-13 | J12: -5.9618656e-14 | K12: 4.5553952e-15 | L12: 6.4309241e-16 | M12: -2.8006834e-15 | N12: -2.1829048e-15 | O12: -1.2848328e-14 | P12: 1.1661022e-14 | Q12: 0.040595185 | R12: 0 | S12: 0.0032288968 | T12: 0.67883112 | U12: =+SUM(B12:T12) -> 1.2806434 | Y12: =+A12 -> 40086 | Z12: =+B12 -> -0.073653072 | AA12: =+C12 -> -3.4599427 | AB12: =+D12 -> 3.9612346 | AC12: =+F12+S12 -> 0.0030000713 | AD12: =+E12 -> 0.13057815 | AE12: =+Q12 -> 0.040595185 | AF12: =+G12 -> -1.464391e-14 | AG12: =+H12 -> 2.3612202e-14 | AH12: =+SUM(T12,I12:P12) -> 0.67883112 | AI12: =+SUM(Z12:AH12) -> 1.2806434
A13: 40178 | B13: -0.06419439 | C13: -3.0559098 | D13: 3.8581322 | E13: 0.10703947 | F13: 4.5429166e-05 | G13: -1.5823259e-14 | H13: 2.3547395e-14 | I13: 1.5766787e-13 | J13: -7.323975e-14 | K13: 6.6079109e-15 | L13: 3.6756254e-16 | M13: -3.5615799e-15 | N13: -2.0156895e-15 | O13: -1.8016609e-14 | P13: 1.1805466e-14 | Q13: -0.045205747 | R13: 0 | S13: 0.002903373 | T13: 0.67182238 | U13: =+SUM(B13:T13) -> 1.4746329 | Y13: =+A13 -> 40178 | Z13: =+B13 -> -0.06419439 | AA13: =+C13 -> -3.0559098 | AB13: =+D13 -> 3.8581322 | AC13: =+F13+S13 -> 0.0029488022 | AD13: =+E13 -> 0.10703947 | AE13: =+Q13 -> -0.045205747 | AF13: =+G13 -> -1.5823259e-14 | AG13: =+H13 -> 2.3547395e-14 | AH13: =+SUM(T13,I13:P13) -> 0.67182238 | AI13: =+SUM(Z13:AH13) -> 1.4746329
... A131: 50951 | B131: -0.11623914 | C131: -1.345537 | D131: 3.088072 | E131: 0.0066416295 | F131: -8.7878743e-06 | G131: 2.6677613e-15 | H131: -1.8863064e-14 | I131: 3.1017843e-13 | J131: 3.8000555e-13 | K131: 4.6128837e-14 | L131: 4.1087059e-14 | M131: 3.2089611e-14 | N131: 2.8074824e-14 | O131: 1.7685319e-15 | P131: 6.3387837e-15 | Q131: -0.07972901 | R131: 0 | S131: -0.00031801307 | T131: 0.1932494 | U131: =+SUM(B131:T131) -> 1.746131 | Y131: =+A131 -> 50951 | Z131: =+B131 -> -0.11623914 | AA131: =+C131 -> -1.345537 | AB131: =+D131 -> 3.088072 | AC131: =+F131+S131 -> -0.00032680094 | AD131: =+E131 -> 0.0066416295 | AE131: =+Q131 -> -0.07972901 | AF131: =+G131 -> 2.6677613e-15 | AG131: =+H131 -> -1.8863064e-14 | AH131: =+SUM(T131,I131:P131) -> 0.1932494 | AI131: =+SUM(Z131:AH131) -> 1.746131
A132: 51043 | U132: =+SUM(B132:T132) -> 0 | Y132: =+A132 -> 51043 | Z132: =+B132 -> 0 | AA132: =+C132 -> 0 | AB132: =+D132 -> 0 | AC132: =+F132+S132 -> 0 | AD132: =+E132 -> 0 | AE132: =+Q132 -> 0 | AF132: =+G132 -> 0 | AG132: =+H132 -> 0 | AH132: =+SUM(T132,I132:P132) -> 0 | AI132: =+SUM(Z132:AH132) -> 0

Sheet EA_output_withoutFG
A1: date | B1: g_sh | C1: b_liqtil_sh | D1: b_liqp_sh | E1: b_safetil_sh | F1: b_safep_sh | G1: mu_sh | H1: z_sh | I1: lambda_f_sh | J1: lambda_w_sh | K1: rm_sh | L1: sigma_omega_sh | M1: mu_e_sh | N1: gamma_sh | O1: pi_star_sh | P1: lr_sh | Q1: zp_sh | R1: tfp_sh | S1: gdpdef_sh | T1: corepce_sh | U1: gdp_sh | V1: gdi_sh | W1: BBB_sh | X1: AAA_sh | Y1: rm_shl1 | Z1: rm_shl2 | AA1: rm_shl3 | AB1: rm_shl4 | AC1: rm_shl5 | AD1: rm_shl6 | AE1: dettrend | AF1: detrendedMean | AG1: DSGE Output (with FG) | AH1: DSGE Output (without FG) | AI1: EC Output gap (cubic spline) | AJ1: HLW Output gap | AK1: IMF Output gap
A2: 39172 | B2: 2.5363082 | C2: -0.18049422 | D2: -5.026568 | E2: -0.00051095038 | F2: 6.5669289 | G2: 14.167348 | H2: -0.028136165 | I2: 0.24489409 | J2: -0.05757504 | K2: 2.5748891 | L2: 0.26640205 | M2: 0 | N2: 0 | O2: 0.43018806 | P2: 0 | Q2: -0.017234495 | R2: 0 | S2: 0 | T2: 0 | U2: 0 | V2: 0 | W2: 0 | X2: 0 | Y2: 0 | Z2: 0 | AA2: 0 | AB2: 0 | AC2: 0 | AD2: 0 | AE2: 7.4683269 | AF2: 28.944766 | AG2: =+AF2-AVERAGE($AF$2:$AF$131) -> 4.0087735 | AH2: =AG2-K2-SUM(Y2:AD2) -> 1.4338843 | AI2: 2.737 | AJ2: 1.1661532 | AK2: 2.4409062
A3: 39263 | B3: 2.1888377 | C3: -0.10201437 | D3: -5.4151599 | E3: 0.000432913 | F3: 7.4635098 | G3: 14.09681 | H3: -0.017718534 | I3: 0.23729294 | J3: -0.058482715 | K3: 2.6753132 | L3: 0.30577422 | M3: 0 | N3: 0 | O3: 0.44487798 | P3: 0 | Q3: -0.025392488 | R3: 0 | S3: 0 | T3: 0 | U3: 0 | V3: 0 | W3: 0 | X3: 0 | Y3: 0 | Z3: 0 | AA3: 0 | AB3: 0 | AC3: 0 | AD3: 0 | AE3: 7.445194 | AF3: 29.239275 | AG3: =+AF3-AVERAGE($AF$2:$AF$131) -> 4.3032822 | AH3: =AG3-K3-SUM(Y3:AD3) -> 1.627969 | AI3: 3.0494018 | AJ3: 0.6307333 | AK3: 2.7138438
A4: 39355 | B4: 2.3018784 | C4: -0.18582521 | D4: -5.7797078 | E4: -0.00024449342 | F4: 8.1065585 | G4: 14.1473 | H4: 0.0099248504 | I4: 0.31153154 | J4: -0.061960515 | K4: 2.506994 | L4: 0.30064004 | M4: 0 | N4: 0 | O4: 0.46631618 | P4: 0 | Q4: -0.040553603 | R4: 0 | S4: 0 | T4: 0 | U4: 0 | V4: 0 | W4: 0 | X4: 0 | Y4: 0 | Z4: 0 | AA4: 0 | AB4: 0 | AC4: 0 | AD4: 0 | AE4: 7.4221487 | AF4: 29.505 | AG4: =+AF4-AVERAGE($AF$2:$AF$131) -> 4.5690074 | AH4: =AG4-K4-SUM(Y4:AD4) -> 2.0620134 | AI4: 2.995168 | AJ4: 0.4902968 | AK4: 2.8524687
A5: 39447 | B5: 2.0031345 | C5: -0.059805901 | D5: -6.0906698 | E5: 0.00065881996 | F5: 8.5748649 | G5: 14.245587 | H5: 0.01546791 | I5: 0.248964 | J5: -0.063329388 | K5: 2.6392114 | L5: 0.34661216 | M5: 0 | N5: 0 | O5: 0.47709801 | P5: 0 | Q5: -0.045182361 | R5: 0 | S5: 0 | T5: 0 | U5: 0 | V5: 0 | W5: 0 | X5: 0 | Y5: 0 | Z5: 0 | AA5: 0 | AB5: 0 | AC5: 0 | AD5: 0 | AE5: 7.3991902 | AF5: 29.691802 | AG5: =+AF5-AVERAGE($AF$2:$AF$131) -> 4.7558088 | AH5: =AG5-K5-SUM(Y5:AD5) -> 2.1165974 | AI5: 2.5742987 | AJ5: 0.5864777 | AK5: 2.8567813
A6: 39538 | B6: 2.0564368 | C6: -0.17410702 | D6: -6.2409237 | E6: -8.1488331e-05 | F6: 8.7254233 | G6: 14.470225 | H6: -0.053129904 | I6: 0.30778976 | J6: -0.066874845 | K6: 2.9688718 | L6: 0.14427824 | M6: 0 | N6: 0 | O6: 0.49713924 | P6: 0 | Q6: -0.050515251 | R6: 0 | S6: 0 | T6: 0 | U6: 0 | V6: 0 | W6: 0 | X6: 0 | Y6: 0 | Z6: 0 | AA6: 0 | AB6: 0 | AC6: 0 | AD6: 0 | AE6: 7.376318 | AF6: 29.96085 | AG6: =+AF6-AVERAGE($AF$2:$AF$131) -> 5.024857 | AH6: =AG6-K6-SUM(Y6:AD6) -> 2.0559852 | AI6: 1.7867937 | AJ6: 0.0776205 | AK6: 3.106625
A7: 39629 | B7: 1.9437086 | C7: -0.25968328 | D7: -6.4409474 | E7: 0.00050280931 | F7: 9.1352305 | G7: 14.602996 | H7: -0.0028221986 | I7: 0.2461009 | J7: -0.063600816 | K7: 2.6992023 | L7: 0.031560885 | M7: 0 | N7: 0 | O7: 0.50964208 | P7: 0 | Q7: -0.07357073 | R7: 0 | S7: 0 | T7: 0 | U7: 0 | V7: 0 | W7: 0 | X7: 0 | Y7: 0 | Z7: 0 | AA7: 0 | AB7: 0 | AC7: 0 | AD7: 0 | AE7: 7.3535315 | AF7: 29.681851 | AG7: =+AF7-AVERAGE($AF$2:$AF$131) -> 4.745858 | AH7: =AG7-K7-SUM(Y7:AD7) -> 2.0466557 | AI7: 0.63265318 | AJ7: -0.2666434 | AK7: 2.690375
A8: 39721 | B8: 1.5553725 | C8: -0.47264141 | D8: -6.5811779 | E8: 0.00045985532 | F8: 9.4802157 | G8: 14.927721 | H8: 0.027059605 | I8: 0.29587019 | J8: -0.068185466 | K8: 2.5210749 | L8: -0.16240357 | M8: 0 | N8: 0 | O8: 0.53344519 | P8: 0 | Q8: -0.081467541 | R8: 0 | S8: 0 | T8: 0 | U8: 0 | V8: 0 | W8: 0 | X8: 0 | Y8: 0 | Z8: 0 | AA8: 0 | AB8: 0 | AC8: 0 | AD8: 0 | AE8: 7.3308301 | AF8: 29.306173 | AG8: =+AF8-AVERAGE($AF$2:$AF$131) -> 4.3701797 | AH8: =AG8-K8-SUM(Y8:AD8) -> 1.8491048 | AI8: -0.88812294 | AJ8: -0.438656 | AK8: 1.987875
A9: 39813 | B9: 2.2206634 | C9: -0.98689403 | D9: -6.9466266 | E9: -0.0002896115 | F9: 8.9449095 | G9: 15.944444 | H9: 0.11808668 | I9: 0.33695797 | J9: -0.065994594 | K9: 2.2587813 | L9: -0.68091049 | M9: 0 | N9: 0 | O9: 0.55671627 | P9: 0 | Q9: -0.073561543 | R9: 0 | S9: 0 | T9: 0 | U9: 0 | V9: 0 | W9: 0 | X9: 0 | Y9: 0.073690921 | Z9: -0.13359577 | AA9: 0.092384556 | AB9: -0.0071129062 | AC9: -0.014969052 | AD9: -0.028973438 | AE9: 7.3082133 | AF9: 28.91592 | AG9: =+AF9-AVERAGE($AF$2:$AF$131) -> 3.9799273 | AH9: =AG9-K9-SUM(Y9:AD9) -> 1.7397217 | AI9: -2.4691806 | AJ9: -1.9018168 | AK9: 0.999125
A10: 39903 | B10: 2.4024061 | C10: -1.2606797 | D10: -6.8199197 | E10: -0.0001738059 | F10: 8.6027343 | G10: 16.652521 | H10: 0.06749249 | I10: 0.27634318 | J10: -0.060941639 | K10: 2.7785999 | L10: -1.1798196 | M10: 0 | N10: 0 | O10: 0.57206768 | P10: 0 | Q10: -0.025279014 | R10: 0 | S10: 0 | T10: 0 | U10: 0 | V10: 0 | W10: 0 | X10: 0 | Y10: -1.7973575 | Z10: 0.013721478 | AA10: 0.12529789 | AB10: -0.030395868 | AC10: -0.051108838 | AD10: -0.13660702 | AE10: 7.2856806 | AF10: 27.414582 | AG10: =+AF10-AVERAGE($AF$2:$AF$131) -> 2.4785886 | AH10: =AG10-K10-SUM(Y10:AD10) -> 1.5764386 | AI10: -3.4688021 | AJ10: -2.6583602 | AK10: -1.9980625
A11: 39994 | B11: 2.4277616 | C11: -1.6490085 | D11: -6.3861468 | E11: -0.00049595052 | F11: 7.9593532 | G11: 17.059181 | H11: -0.089907165 | I11: 0.25785819 | J11: -0.059151639 | K11: 5.406976 | L11: -1.4181606 | M11: 0 | N11: 0 | O11: 0.58667403 | P11: 0 | Q11: 0.016546462 | R11: 0 | S11: 0 | T11: 0 | U11: 0 | V11: 0 | W11: 0 | X11: 0 | Y11: -4.5109297 | Z11: 0.25520858 | AA11: 0.13462049 | AB11: -0.078483828 | AC11: -0.067382708 | AD11: -0.30713781 | AE11: 7.2632314 | AF11: 26.800606 | AG11: =+AF11-AVERAGE($AF$2:$AF$131) -> 1.8646132 | AH11: =AG11-K11-SUM(Y11:AD11) -> 1.0317421 | AI11: -3.8667303 | AJ11: -2.4732533 | AK11: -2.8704375
A12: 40086 | B12: 2.4217085 | C12: -2.0203722 | D12: -5.5802494 | E12: -0.0013006478 | F12: 7.1417549 | G12: 17.135333 | H12: -0.0426744 | I12: 0.322457 | J12: -0.056528372 | K12: 7.9652821 | L12: -1.4766757 | M12: 0 | N12: 0 | O12: 0.60460848 | P12: 0 | Q12: 0.00073509913 | R12: 0 | S12: 0 | T12: 0 | U12: 0 | V12: 0 | W12: 0 | X12: 0 | Y12: -6.6481835 | Z12: 0.43002849 | AA12: 0.11092325 | AB12: -0.16598199 | AC12: -0.11796388 | AD12: -0.56485065 | AE12: 7.2408652 | AF12: 26.698915 | AG12: =+AF12-AVERAGE($AF$2:$AF$131) -> 1.7629224 | AH12: =AG12-K12-SUM(Y12:AD12) -> 0.75366863 | AI12: -3.6629654 | AJ12: -2.2970007 | AK12: -3.3401875
A13: 40178 | B13: 2.0701525 | C13: -1.9632677 | D13: -4.963927 | E13: -0.00080920876 | F13: 6.7932403 | G13: 17.165547 | H13: 0.018838774 | I13: 0.252927 | J13: -0.046777776 | K13: 9.6680861 | L13: -1.4944411 | M13: 0 | N13: 0 | O13: 0.61475522 | P13: 0 | Q13: -0.017101425 | R13: 0 | S13: 0 | T13: 0 | U13: 0 | V13: 0 | W13: 0 | X13: 0 | Y13: -8.2298802 | Z13: 0.64538339 | AA13: 0.075587373 | AB13: -0.24389615 | AC13: -0.13783327 | AD13: -0.86962231 | AE13: 7.2185815 | AF13: 26.555543 | AG13: =+AF13-AVERAGE($AF$2:$AF$131) -> 1.6195504 | AH13: =AG13-K13-SUM(Y13:AD13) -> 0.71172541 | AI13: -3.0097139 | AJ13: -1.4258796 | AK13: -3.4073125
... A75: 45838 | B75: 4.057487 | C75: 0.56094189 | D75: -3.4828916 | E75: 0.00010584421 | F75: 2.6784309 | G75: 14.912689 | H75: -0.0015615644 | I75: 0.15879885 | J75: -0.036835435 | K75: -16.703083 | L75: 1.2081812 | M75: 0 | N75: 0 | O75: 0.1634977 | P75: 0 | Q75: -0.029727965 | R75: 0 | S75: 0 | T75: 0 | U75: 0 | V75: 0 | W75: 0 | X75: 0 | Y75: 16.961889 | Z75: -0.94827617 | AA75: 0.51624543 | AB75: 0.61273185 | AC75: 0.55843932 | AD75: -0.029115553 | AE75: 5.9813156 | AF75: 27.139263 | AG75: =+AF75-AVERAGE($AF$2:$AF$131) -> 2.2032695 | AH75: =AG75-K75-SUM(Y75:AD75) -> 1.2344387 | AI75: -0.48010871 | AJ75: -0.631496 | AK75: -0.41065625
A76: 45930 | B76: 4.0157659 | C76: 0.48968772 | D76: -3.4594536 | E76: 0.00010189013 | F76: 2.6761726 | G76: 14.932423 | H76: -0.0014130573 | I76: 0.1482139 | J76: -0.03356933 | K76: -16.208105 | L76: 1.0785315 | M76: 0 | N76: 0 | O76: 0.15438363 | P76: 0 | Q76: -0.032859876 | R76: 0 | S76: 0 | T76: 0 | U76: 0 | V76: 0 | W76: 0 | X76: 0 | Y76: 16.446263 | Z76: -0.91628328 | AA76: 0.50258699 | AB76: 0.59742063 | AC76: 0.5476894 | AD76: -0.014704871 | AE76: 5.9634613 | AF76: 26.886312 | AG76: =+AF76-AVERAGE($AF$2:$AF$131) -> 1.950319 | AH76: =AG76-K76-SUM(Y76:AD76) -> 0.99545217 | AI76: -0.51683636 | AK76: -0.46228125
A77: 46022 | B77: 3.9740808 | C77: 0.42810901 | D77: -3.4346427 | E77: 9.7784953e-05 | F77: 2.6700933 | G77: 14.946217 | H77: -0.0012833931 | I77: 0.13812772 | J77: -0.030260912 | K77: -15.72148 | L77: 0.95780479 | M77: 0 | N77: 0 | O77: 0.14559604 | P77: 0 | Q77: -0.035914293 | R77: 0 | S77: 0 | T77: 0 | U77: 0 | V77: 0 | W77: 0 | X77: 0 | Y77: 15.942023 | Z77: -0.88565918 | AA77: 0.4886372 | AB77: 0.581054 | AC77: 0.53395091 | AD77: -0.0071720927 | AE77: 5.9456675 | AF77: 26.635046 | AG77: =+AF77-AVERAGE($AF$2:$AF$131) -> 1.6990532 | AH77: =AG77-K77-SUM(Y77:AD77) -> 0.76769921 | AI77: -0.5065835 | AK77: -0.51096875
A78: 46112 | B78: 3.9324542 | C78: 0.37485512 | D78: -3.4087414 | E78: 9.3444987e-05 | F78: 2.6608721 | G78: 14.954455 | H78: -0.0011876676 | I78: 0.1285779 | J78: -0.026953907 | K78: -15.244878 | L78: 0.84628227 | M78: 0 | N78: 0 | O78: 0.13712412 | P78: 0 | Q78: -0.038568499 | R78: 0 | S78: 0 | T78: 0 | U78: 0 | V78: 0 | W78: 0 | X78: 0 | Y78: 15.450229 | Z78: -0.85617724 | AA78: 0.47477416 | AB78: 0.56456195 | AC78: 0.51931551 | AD78: -0.0036718824 | AE78: 5.927934 | AF78: 26.39135 | AG78: =+AF78-AVERAGE($AF$2:$AF$131) -> 1.4553568 | AH78: =AG78-K78-SUM(Y78:AD78) -> 0.55120318 | AI78: -0.44935012
A79: 46203 | B79: 3.8909215 | C79: 0.32876232 | D79: -3.3819542 | E79: 8.8919717e-05 | F79: 2.6489971 | G79: 14.957537 | H79: -0.0011162048 | I79: 0.11957037 | J79: -0.023684559 | K79: -14.779102 | L79: 0.74406216 | M79: 0 | N79: 0 | O79: 0.12895712 | P79: 0 | Q79: -0.040641984 | R79: 0 | S79: 0 | T79: 0 | U79: 0 | V79: 0 | W79: 0 | X79: 0 | Y79: 14.971329 | Z79: -0.82775903 | AA79: 0.46112173 | AB79: 0.54825473 | AC79: 0.50458237 | AD79: -0.0018182879 | AE79: 5.9102605 | AF79: 26.158368 | AG79: =+AF79-AVERAGE($AF$2:$AF$131) -> 1.2223749 | AH79: =AG79-K79-SUM(Y79:AD79) -> 0.34576732 | AI79: -0.35325663
A80: 46295 | B80: 3.8495216 | C80: 0.28883407 | D80: -3.3544505 | E80: 8.4286275e-05 | F80: 2.6348746 | G80: 14.955871 | H80: -0.0010577841 | I80: 0.11109409 | J80: -0.020483368 | K80: -14.324629 | L80: 0.65108527 | M80: 0 | N80: 0 | O80: 0.1210846 | P80: 0 | Q80: -0.042050998 | R80: 0 | S80: 0 | T80: 0 | U80: 0 | V80: 0 | W80: 0 | X80: 0 | Y80: 14.505528 | Z80: -0.80036705 | AA80: 0.44772443 | AB80: 0.53223638 | AC80: 0.49001865 | AD80: -0.0006779802 | AE80: 5.8926467 | AF80: 25.936888 | AG80: =+AF80-AVERAGE($AF$2:$AF$131) -> 1.0008947 | AH80: =AG80-K80-SUM(Y80:AD80) -> 0.15106073 | AI80: -0.27173932
A81: 46387 | B81: 3.8082933 | C81: 0.25421812 | D81: -3.3263786 | E81: 7.9619673e-05 | F81: 2.6188615 | G81: 14.949862 | H81: -0.0010047217 | I81: 0.10313014 | J81: -0.017375604 | K81: -13.881767 | L81: 0.56716088 | M81: 0 | N81: 0 | O81: 0.11349644 | P81: 0 | Q81: -0.042776816 | R81: 0 | S81: 0 | T81: 0 | U81: 0 | V81: 0 | W81: 0 | X81: 0 | Y81: 14.052909 | Z81: -0.77397319 | AA81: 0.43460188 | AB81: 0.51654595 | AC81: 0.4757141 | AD81: 7.8497944e-05 | AE81: 5.8750924 | AF81: 25.726767 | AG81: =+AF81-AVERAGE($AF$2:$AF$131) -> 0.79077418 | AH81: =AG81-K81-SUM(Y81:AD81) -> -0.033334775 | AI81: -0.21453901
A82: 46477 | B82: 3.7672733 | C82: 0.2241852 | D82: -3.2978697 | E82: 7.4985108e-05 | F82: 2.6012761 | G82: 14.939907 | H82: -0.00095279491 | I82: 0.095656249 | J82: -0.014381659 | K82: -13.45072 | L82: 0.49199113 | M82: 0 | N82: 0 | O82: 0.10618286 | P82: 0 | Q82: -0.042843662 | R82: 0 | S82: 0 | T82: 0 | U82: 0 | V82: 0 | W82: 0 | X82: 0 | Y82: 13.613467 | Z82: -0.74854994 | AA82: 0.42176519 | AB82: 0.5012015 | AC82: 0.4617025 | AD82: 0.00057768853 | AE82: 5.8575973 | AF82: 25.527541 | AG82: =+AF82-AVERAGE($AF$2:$AF$131) -> 0.59154776 | AH82: =AG82-K82-SUM(Y82:AD82) -> -0.20789619 | AI82: -0.18165569
A83: 46568 | B83: 3.7264958 | C83: 0.19811065 | D83: -3.2690403 | E83: 7.0436689e-05 | F83: 2.5824028 | G83: 14.926396 | H83: -0.00090014542 | I83: 0.088648846 | J83: -0.011517426 | K83: -13.031602 | L83: 0.42519331 | M83: 0 | N83: 0 | O83: 0.099134411 | P83: 0 | Q83: -0.042303195 | R83: 0 | S83: 0 | T83: 0 | U83: 0 | V83: 0 | W83: 0 | X83: 0 | Y83: 13.187132 | Z83: -0.72406831 | AA83: 0.40922184 | AB83: 0.48621346 | AC83: 0.44799956 | AD83: 0.00088098974 | AE83: 5.8401613 | AF83: 25.33863 | AG83: =+AF83-AVERAGE($AF$2:$AF$131) -> 0.402637 | AH83: =AG83-K83-SUM(Y83:AD83) -> -0.37314018 | AI83: -0.17144368
A84: 46660 | B84: 3.6859917 | C84: 0.17545862 | D84: -3.2399927 | E84: 6.6017983e-05 | F84: 2.5624942 | G84: 14.909701 | H84: -0.00084630041 | I84: 0.082084098 | J84: -0.0087947249 | K84: -12.624455 | L84: 0.3663198 | M84: 0 | N84: 0 | O84: 0.092342001 | P84: 0 | Q84: -0.04122349 | R84: 0 | S84: 0 | T84: 0 | U84: 0 | V84: 0 | W84: 0 | X84: 0 | Y84: 12.773777 | Z84: -0.70049768 | AA84: 0.39697723 | AB84: 0.47158862 | AC84: 0.43461439 | AD84: 0.0010277896 | AE84: 5.8227839 | AF84: 25.159416 | AG84: =+AF84-AVERAGE($AF$2:$AF$131) -> 0.22342299 | AH84: =AG84-K84-SUM(Y84:AD84) -> -0.52960906 | AI84: -0.16337945
A85: 46752 | B85: 3.6457888 | C85: 0.1557688 | D85: -3.2108168 | E85: 6.1763048e-05 | F85: 2.5417734 | G85: 14.890175 | H85: -0.0007915102 | I85: 0.075938372 | J85: -0.0062217493 | K85: -12.229256 | L85: 0.31487583 | M85: 0 | N85: 0 | O85: 0.085796859 | P85: 0 | Q85: -0.039681192 | R85: 0 | S85: 0 | T85: 0 | U85: 0 | V85: 0 | W85: 0 | X85: 0 | Y85: 12.373229 | Z85: -0.67780613 | AA85: 0.38503507 | AB85: 0.45733143 | AC85: 0.42155295 | AD85: 0.0010485802 | AE85: 5.8054651 | AF85: 24.989267 | AG85: =+AF85-AVERAGE($AF$2:$AF$131) -> 0.053274198 | AH85: =AG85-K85-SUM(Y85:AD85) -> -0.67785995 | AI85: -0.15131179
A86: 46843 | B86: 3.6059117 | C86: 0.13864514 | D86: -3.1815906 | E86: 5.7697559e-05 | F86: 2.520436 | G86: 14.868154 | H86: -0.00073635016 | I86: 0.070188499 | J86: -0.0038035186 | K86: -11.845927 | L86: 0.270335 | M86: 0 | N86: 0 | O86: 0.079490534 | P86: 0 | Q86: -0.037755923 | R86: 0 | S86: 0 | T86: 0 | U86: 0 | V86: 0 | W86: 0 | X86: 0 | Y86: 11.985273 | Z86: -0.65596092 | AA86: 0.3733977 | AB86: 0.44344447 | AC86: 0.40881915 | AD86: 0.00096898993 | AE86: 5.7882045 | AF86: 24.827553 | AG86: =+AF86-AVERAGE($AF$2:$AF$131) -> -0.10844022 | AH86: =AG86-K86-SUM(Y86:AD86) -> -0.8184559 | AI86: -0.1352407
A87: 46934 | B87: 3.5663816 | C87: 0.12374632 | D87: -3.152381 | E87: 5.3839887e-05 | F87: 2.498652 | G87: 14.84395 | H87: -0.00068149838 | I87: 0.064811936 | J87: -0.0015423135 | K87: -11.474341 | L87: 0.23215275 | M87: 0 | N87: 0 | O87: 0.073414888 | P87: 0 | Q87: -0.035526364 | R87: 0 | S87: 0 | T87: 0 | U87: 0 | V87: 0 | W87: 0 | X87: 0 | Y87: 11.609665 | Z87: -0.63492887 | AA87: 0.36206615 | AB87: 0.42992864 | AC87: 0.39641526 | AD87: 0.00081112415 | AE87: 5.7710019 | AF87: 24.673651 | AG87: =+AF87-AVERAGE($AF$2:$AF$131) -> -0.26234229 | AH87: =AG87-K87-SUM(Y87:AD87) -> -0.95195856 | AI87: -0.1152633
A88: 47026 | B88: 3.527217 | C88: 0.11077779 | D88: -3.1232452 | E88: 5.020212e-05 | F88: 2.4765681 | G88: 14.817852 | H88: -0.00062761912 | I88: 0.059786875 | J88: 0.00056191171 | K88: -11.114332 | L88: 0.19977784 | M88: 0 | N88: 0 | O88: 0.067562083 | P88: 0 | Q88: -0.033067563 | R88: 0 | S88: 0 | T88: 0 | U88: 0 | V88: 0 | W88: 0 | X88: 0 | Y88: 11.246131 | Z88: -0.61467678 | AA88: 0.35104029 | AB88: 0.41678339 | AC88: 0.3843421 | AD88: 0.00059411582 | AE88: 5.7538571 | AF88: 24.526954 | AG88: =+AF88-AVERAGE($AF$2:$AF$131) -> -0.40903936 | AH88: =AG88-K88-SUM(Y88:AD88) -> -1.078922 | AI88: -0.094455966
A89: 47118 | B89: 3.4884333 | C89: 0.099484922 | D89: -3.0942315 | E89: 4.6790998e-05 | F89: 2.4543096 | G89: 14.790127 | H89: -0.00057530653 | I89: 0.055092317 | J89: 0.0025111452 | K89: -10.765696 | L89: 0.17266213 | M89: 0 | N89: 0 | O89: 0.061924572 | P89: 0 | Q89: -0.030449158 | R89: 0 | S89: 0 | T89: 0 | U89: 0 | V89: 0 | W89: 0 | X89: 0 | Y89: 10.894376 | Z89: -0.59517174 | AA89: 0.3403189 | AB89: 0.40400684 | AC89: 0.37259918 | AD89: 0.00033444451 | AE89: 5.7367698 | AF89: 24.386874 | AG89: =+AF89-AVERAGE($AF$2:$AF$131) -> -0.54911947 | AH89: =AG89-K89-SUM(Y89:AD89) -> -1.1998875 | AI89: -0.074287344
... A117: 49674 | B117: 2.5651294 | C117: 0.020148859 | D117: -2.3817779 | E117: 1.2417194e-05 | F117: 1.9110446 | G117: 13.856637 | H117: -9.2773835e-05 | I117: -0.00060307564 | J117: 0.018995769 | K117: -4.4992019 | L117: 0.10683063 | M117: 0 | N117: 0 | O117: -0.032032259 | P117: 0 | Q117: 0.0043931293 | R117: 0 | S117: 0 | T117: 0 | U117: 0 | V117: 0 | W117: 0 | X117: 0 | Y117: 4.5684259 | Z117: -0.25086187 | AA117: 0.1425253 | AB117: 0.16909308 | AC117: 0.15591404 | AD117: -0.0028954675 | AE117: 5.2807376 | AF117: 21.632423 | AG117: =+AF117-AVERAGE($AF$2:$AF$131) -> -3.3035704 | AH117: =AG117-K117-SUM(Y117:AD117) -> -3.5865696 | AI117: -0.499
A118: 49765 | B118: 2.5373695 | C118: 0.019584789 | D118: -2.3596467 | E118: 1.2106943e-05 | F118: 1.8945548 | G118: 13.823224 | H118: -9.392465e-05 | I118: -0.0011869201 | J118: 0.018985818 | K118: -4.3635318 | L118: 0.10593133 | M118: 0 | N118: 0 | O118: -0.033751019 | P118: 0 | Q118: 0.0042248075 | R118: 0 | S118: 0 | T118: 0 | U118: 0 | V118: 0 | W118: 0 | X118: 0 | Y118: 4.430753 | Z118: -0.24333499 | AA118: 0.13820975 | AB118: 0.16397526 | AC118: 0.15119191 | AD118: -0.0028228506 | AE118: 5.265219 | AF118: 21.548868 | AG118: =+AF118-AVERAGE($AF$2:$AF$131) -> -3.3871248 | AH118: =AG118-K118-SUM(Y118:AD118) -> -3.661565
A119: 49856 | B119: 2.5099149 | C119: 0.019040559 | D119: -2.3376986 | E119: 1.1807547e-05 | F119: 1.8781837 | G119: 13.789809 | H119: -9.5145184e-05 | I119: -0.0017252413 | J119: 0.018964458 | K119: -4.2319935 | L119: 0.10480899 | M119: 0 | N119: 0 | O119: -0.035391111 | P119: 0 | Q119: 0.0040346903 | R119: 0 | S119: 0 | T119: 0 | U119: 0 | V119: 0 | W119: 0 | X119: 0 | Y119: 4.2972472 | Z119: -0.23603103 | AA119: 0.1340272 | AB119: 0.15901503 | AC119: 0.14661554 | AD119: -0.0027477596 | AE119: 5.2497513 | AF119: 21.465742 | AG119: =+AF119-AVERAGE($AF$2:$AF$131) -> -3.4702511 | AH119: =AG119-K119-SUM(Y119:AD119) -> -3.7363838
A120: 49948 | B120: 2.4827611 | C120: 0.018513873 | D120: -2.3159307 | E120: 1.1517407e-05 | F120: 1.8619262 | G120: 13.756383 | H120: -9.6384119e-05 | I120: -0.0022207919 | J120: 0.018932751 | K120: -4.1044511 | L120: 0.10348672 | M120: 0 | N120: 0 | O120: -0.036955163 | P120: 0 | Q120: 0.0038283966 | R120: 0 | S120: 0 | T120: 0 | U120: 0 | V120: 0 | W120: 0 | X120: 0 | Y120: 4.1677753 | Z120: -0.22894331 | AA120: 0.12997325 | AB120: 0.15420717 | AC120: 0.14218011 | AD120: -0.0026709653 | AE120: 5.2343342 | AF120: 21.383046 | AG120: =+AF120-AVERAGE($AF$2:$AF$131) -> -3.5529474 | AH120: =AG120-K120-SUM(Y120:AD120) -> -3.8110179
