Workbook
Name BoxPlot: "BoxPlot"
Name Bubble: "Bubble"
Name Candlestick: "Candlestick"
Name Chart: "Chart"
Name ChartImage: "ChartImage"
Name ColumnRange: "ColumnRange"
Name Dumbbell: "Dumbbell"
Name Heatmap: "Heatmap"
Name Histogram: "Histogram"
Name Map: "Map"
Name OHLC: "OHLC"
Name PieChart: "PieChart"
Name Scatter: "Scatter"
Name Series: "Series"
Name Stripe: "Stripe"
Name Table: "Table"
Name TreeMap: "TreeMap"
Name Waterfall: "Waterfall"

Sheet Allcharts

Sheet US_output_policy
A1: date | B1: g_sh | C1: b_liqtil_sh | D1: b_liqp_sh | E1: b_safetil_sh | F1: b_safep_sh | G1: mu_sh | H1: z_sh | I1: lambda_f_sh | J1: lambda_w_sh | K1: rm_sh | L1: sigma_omega_sh | M1: mu_e_sh | N1: gamma_sh | O1: pi_star_sh | P1: lr_sh | Q1: zp_sh | R1: tfp_sh | S1: gdpdef_sh | T1: corepce_sh | U1: gdp_sh | V1: gdi_sh | W1: BBB_sh | X1: AAA_sh | Y1: rm_shl1 | Z1: rm_shl2 | AA1: rm_shl3 | AB1: rm_shl4 | AC1: rm_shl5 | AD1: rm_shl6 | AE1: dettrend | AF1: detrendedMean | AH1: rm_sh | AI1: =Y1 -> rm_shl1 | AJ1: =Z1 -> rm_shl2 | AK1: =AA1 -> rm_shl3 | AL1: =AB1 -> rm_shl4 | AM1: =AC1 -> rm_shl5 | AN1: =AD1 -> rm_shl6 | AQ1: Plot | AR1: =A1 -> date | AS1: =AF1 -> detrendedMean | AT1: Monetary Policy | AU1: Fgsum | AV1: FG1 | AW1: FG2 | AX1: FG3 | AY1: FG4 | AZ1: FG5 | BA1: FG6 | BC1: date | BD1: rm_sh | BE1: Fgsum
A2: 39172 | B2: -1.0215877 | C2: 0.14738424 | D2: -0.044907453 | E2: 0.56515568 | F2: 0.33471877 | G2: 1.4053436 | H2: 0.54693072 | I2: -0.65393335 | J2: 0.64232717 | K2: 1.7750614 | L2: 1.2826525 | M2: 0 | N2: 0 | O2: 0.3278555 | P2: 0 | Q2: 0.11087454 | R2: 0 | S2: 0 | T2: 0 | U2: 0 | V2: 0 | W2: 0 | X2: 0 | Y2: 0 | Z2: 0 | AA2: 0 | AB2: 0 | AC2: 0 | AD2: 0 | AE2: 0.13099711 | AF2: 5.5488727 | AH2: =K2 -> 1.7750614 | AI2: =Y2 -> 0 | AJ2: =Z2 -> 0 | AK2: =AA2 -> 0 | AL2: =AB2 -> 0 | AM2: =AC2 -> 0 | AN2: =AD2 -> 0 | AR2: =A2 -> 39172 | AS2: =AF2*4+2 -> 24.195491 | AT2: =AH2 -> 1.7750614 | AU2: =SUM(AV2:BA2) -> 0 | AV2: =AI2 -> 0 | AW2: =AJ2 -> 0 | AX2: =AK2 -> 0 | AY2: =AL2 -> 0 | AZ2: =AM2 -> 0 | BA2: =AN2 -> 0 | BC2: =AR2 -> 39172 | BD2: =AT2 -> 1.7750614 | BE2: =AU2 -> 0
A3: 39263 | B3: -0.87702165 | C3: 0.14867978 | D3: -0.050839217 | E3: 0.5967583 | F3: 0.35694143 | G3: 1.4459149 | H3: 0.10615582 | I3: -0.67075329 | J3: 0.60096046 | K3: 1.5688765 | L3: 1.2418066 | M3: 0 | N3: 0 | O3: 0.33267031 | P3: 0 | Q3: 0.070231968 | R3: 0 | S3: 0 | T3: 0 | U3: 0 | V3: 0 | W3: 0 | X3: 0 | Y3: 0 | Z3: 0 | AA3: 0 | AB3: 0 | AC3: 0 | AD3: 0 | AE3: 0.13039267 | AF3: 5.0007746 | AH3: =K3 -> 1.5688765 | AI3: =Y3 -> 0 | AJ3: =Z3 -> 0 | AK3: =AA3 -> 0 | AL3: =AB3 -> 0 | AM3: =AC3 -> 0 | AN3: =AD3 -> 0 | AR3: =A3 -> 39263 | AS3: =AF3*4+2 -> 22.003098 | AT3: =AH3 -> 1.5688765 | AU3: =SUM(AV3:BA3) -> 0 | AV3: =AI3 -> 0 | AW3: =AJ3 -> 0 | AX3: =AK3 -> 0 | AY3: =AL3 -> 0 | AZ3: =AM3 -> 0 | BA3: =AN3 -> 0 | BC3: =AR3 -> 39263 | BD3: =AT3 -> 1.5688765 | BE3: =AU3 -> 0
A4: 39355 | B4: -1.040355 | C4: 0.13425109 | D4: -0.14587387 | E4: 0.69031317 | F4: 0.37191894 | G4: 1.4503632 | H4: 0.31183503 | I4: -0.6798581 | J4: 0.61019793 | K4: 1.5086958 | L4: 1.1510338 | M4: 0 | N4: 0 | O4: 0.37118543 | P4: 0 | Q4: 0.037371485 | R4: 0 | S4: 0 | T4: 0 | U4: 0 | V4: 0 | W4: 0 | X4: 0 | Y4: 0 | Z4: 0 | AA4: 0 | AB4: 0 | AC4: 0 | AD4: 0 | AE4: 0.12978091 | AF4: 4.9008599 | AH4: =K4 -> 1.5086958 | AI4: =Y4 -> 0 | AJ4: =Z4 -> 0 | AK4: =AA4 -> 0 | AL4: =AB4 -> 0 | AM4: =AC4 -> 0 | AN4: =AD4 -> 0 | AR4: =A4 -> 39355 | AS4: =AF4*4+2 -> 21.603439 | AT4: =AH4 -> 1.5086958 | AU4: =SUM(AV4:BA4) -> 0 | AV4: =AI4 -> 0 | AW4: =AJ4 -> 0 | AX4: =AK4 -> 0 | AY4: =AL4 -> 0 | AZ4: =AM4 -> 0 | BA4: =AN4 -> 0 | BC4: =AR4 -> 39355 | BD4: =AT4 -> 1.5086958 | BE4: =AU4 -> 0
A5: 39447 | B5: -0.99330901 | C5: 0.14258815 | D5: -0.26310356 | E5: 0.73768743 | F5: 0.36639612 | G5: 1.4317096 | H5: 0.21867959 | I5: -0.68920012 | J5: 0.66599438 | K5: 1.7274198 | L5: 1.0093212 | M5: 0 | N5: 0 | O5: 0.40724837 | P5: 0 | Q5: 0.016106972 | R5: 0 | S5: 0 | T5: 0 | U5: 0 | V5: 0 | W5: 0 | X5: 0 | Y5: 0 | Z5: 0 | AA5: 0 | AB5: 0 | AC5: 0 | AD5: 0 | AE5: 0.12916218 | AF5: 4.9067011 | AH5: =K5 -> 1.7274198 | AI5: =Y5 -> 0 | AJ5: =Z5 -> 0 | AK5: =AA5 -> 0 | AL5: =AB5 -> 0 | AM5: =AC5 -> 0 | AN5: =AD5 -> 0 | AR5: =A5 -> 39447 | AS5: =AF5*4+2 -> 21.626804 | AT5: =AH5 -> 1.7274198 | AU5: =SUM(AV5:BA5) -> 0 | AV5: =AI5 -> 0 | AW5: =AJ5 -> 0 | AX5: =AK5 -> 0 | AY5: =AL5 -> 0 | AZ5: =AM5 -> 0 | BA5: =AN5 -> 0 | BC5: =AR5 -> 39447 | BD5: =AT5 -> 1.7274198 | BE5: =AU5 -> 0
A6: 39538 | B6: -1.0476842 | C6: 0.03061779 | D6: -0.40243934 | E6: 0.39311962 | F6: 0.33629364 | G6: 1.42832 | H6: 0.27379584 | I6: -0.67868028 | J6: 0.70115772 | K6: 2.0053504 | L6: 0.85487701 | M6: 0 | N6: 0 | O6: 0.44493982 | P6: 0 | Q6: -0.019590161 | R6: 0 | S6: 0 | T6: 0 | U6: 0 | V6: 0 | W6: 0 | X6: 0 | Y6: 0 | Z6: 0 | AA6: 0 | AB6: 0 | AC6: 0 | AD6: 0 | AE6: 0.12853685 | AF6: 4.4486148 | AH6: =K6 -> 2.0053504 | AI6: =Y6 -> 0 | AJ6: =Z6 -> 0 | AK6: =AA6 -> 0 | AL6: =AB6 -> 0 | AM6: =AC6 -> 0 | AN6: =AD6 -> 0 | AR6: =A6 -> 39538 | AS6: =AF6*4+2 -> 19.794459 | AT6: =AH6 -> 2.0053504 | AU6: =SUM(AV6:BA6) -> 0 | AV6: =AI6 -> 0 | AW6: =AJ6 -> 0 | AX6: =AK6 -> 0 | AY6: =AL6 -> 0 | AZ6: =AM6 -> 0 | BA6: =AN6 -> 0 | BC6: =AR6 -> 39538 | BD6: =AT6 -> 2.0053504 | BE6: =AU6 -> 0
A7: 39629 | B7: -1.1086433 | C7: -0.033609602 | D7: -0.44750789 | E7: 0.09339584 | F7: 0.34011857 | G7: 1.4242313 | H7: 0.099730651 | I7: -0.64918611 | J7: 0.69311266 | K7: 2.3003353 | L7: 0.71023288 | M7: 0 | N7: 0 | O7: 0.48647302 | P7: 0 | Q7: -0.047607001 | R7: 0 | S7: 0 | T7: 0 | U7: 0 | V7: 0 | W7: 0 | X7: 0 | Y7: 0 | Z7: 0 | AA7: 0 | AB7: 0 | AC7: 0 | AD7: 0 | AE7: 0.12790526 | AF7: 3.9889816 | AH7: =K7 -> 2.3003353 | AI7: =Y7 -> 0 | AJ7: =Z7 -> 0 | AK7: =AA7 -> 0 | AL7: =AB7 -> 0 | AM7: =AC7 -> 0 | AN7: =AD7 -> 0 | AR7: =A7 -> 39629 | AS7: =AF7*4+2 -> 17.955926 | AT7: =AH7 -> 2.3003353 | AU7: =SUM(AV7:BA7) -> 0 | AV7: =AI7 -> 0 | AW7: =AJ7 -> 0 | AX7: =AK7 -> 0 | AY7: =AL7 -> 0 | AZ7: =AM7 -> 0 | BA7: =AN7 -> 0 | BC7: =AR7 -> 39629 | BD7: =AT7 -> 2.3003353 | BE7: =AU7 -> 0
A8: 39721 | B8: -0.80373451 | C8: -0.20400532 | D8: -0.52579161 | E8: -0.37809506 | F8: 0.32715602 | G8: 1.4371073 | H8: 0.049769223 | I8: -0.6241057 | J8: 0.72601851 | K8: 1.9637541 | L8: 0.57993927 | M8: 0 | N8: 0 | O8: 0.49767707 | P8: 0 | Q8: -0.074978682 | R8: 0 | S8: 0 | T8: 0 | U8: 0 | V8: 0 | W8: 0 | X8: 0 | Y8: 0 | Z8: 0 | AA8: 0 | AB8: 0 | AC8: 0 | AD8: 0 | AE8: 0.12726775 | AF8: 3.0979785 | AH8: =K8 -> 1.9637541 | AI8: =Y8 -> 0 | AJ8: =Z8 -> 0 | AK8: =AA8 -> 0 | AL8: =AB8 -> 0 | AM8: =AC8 -> 0 | AN8: =AD8 -> 0 | AR8: =A8 -> 39721 | AS8: =AF8*4+2 -> 14.391914 | AT8: =AH8 -> 1.9637541 | AU8: =SUM(AV8:BA8) -> 0 | AV8: =AI8 -> 0 | AW8: =AJ8 -> 0 | AX8: =AK8 -> 0 | AY8: =AL8 -> 0 | AZ8: =AM8 -> 0 | BA8: =AN8 -> 0 | BC8: =AR8 -> 39721 | BD8: =AT8 -> 1.9637541 | BE8: =AU8 -> 0
A9: 39813 | B9: -0.21677727 | C9: -0.56638658 | D9: -0.87656555 | E9: -1.0760328 | F9: 0.163132 | G9: 1.567453 | H9: 0.77708187 | I9: -0.52720457 | J9: 0.77689645 | K9: 1.3356925 | L9: 0.32530383 | M9: 0 | N9: 0 | O9: 0.56267499 | P9: 0 | Q9: -0.12285996 | R9: 0 | S9: 0 | T9: 0 | U9: 0 | V9: 0 | W9: 0 | X9: 0 | Y9: -0.18334085 | Z9: -0.085809019 | AA9: -0.014995051 | AB9: -0.0025678522 | AC9: -0.0010749068 | AD9: -0.0015146036 | AE9: 0.12662465 | AF9: 1.9597303 | AH9: =K9 -> 1.3356925 | AI9: =Y9 -> -0.18334085 | AJ9: =Z9 -> -0.085809019 | AK9: =AA9 -> -0.014995051 | AL9: =AB9 -> -0.0025678522 | AM9: =AC9 -> -0.0010749068 | AN9: =AD9 -> -0.0015146036 | AR9: =A9 -> 39813 | AS9: =AF9*4+2 -> 9.8389213 | AT9: =AH9 -> 1.3356925 | AU9: =SUM(AV9:BA9) -> -0.28930228 | AV9: =AI9 -> -0.18334085 | AW9: =AJ9 -> -0.085809019 | AX9: =AK9 -> -0.014995051 | AY9: =AL9 -> -0.0025678522 | AZ9: =AM9 -> -0.0010749068 | BA9: =AN9 -> -0.0015146036 | BC9: =AR9 -> 39813 | BD9: =AT9 -> 1.3356925 | BE9: =AU9 -> -0.28930228
A10: 39903 | B10: -0.13539004 | C10: -0.65246513 | D10: -0.91826335 | E10: -1.4441778 | F10: 0.115455 | G10: 1.5230468 | H10: 0.27896396 | I10: -0.40325188 | J10: 0.66681609 | K10: 0.39863999 | L10: 0.0012907793 | M10: 0 | N10: 0 | O10: 0.65980691 | P10: 0 | Q10: -0.15244255 | R10: 0 | S10: 0 | T10: 0 | U10: 0 | V10: 0 | W10: 0 | X10: 0 | Y10: -0.40182322 | Z10: -0.21133372 | AA10: -0.064564658 | AB10: -0.0076746478 | AC10: -0.0097111472 | AD10: -0.013463276 | AE10: 0.12597629 | AF10: -0.64456556 | AH10: =K10 -> 0.39863999 | AI10: =Y10 -> -0.40182322 | AJ10: =Z10 -> -0.21133372 | AK10: =AA10 -> -0.064564658 | AL10: =AB10 -> -0.0076746478 | AM10: =AC10 -> -0.0097111472 | AN10: =AD10 -> -0.013463276 | AR10: =A10 -> 39903 | AS10: =AF10*4+2 -> -0.57826224 | AT10: =AH10 -> 0.39863999 | AU10: =SUM(AV10:BA10) -> -0.70857067 | AV10: =AI10 -> -0.40182322 | AW10: =AJ10 -> -0.21133372 | AX10: =AK10 -> -0.064564658 | AY10: =AL10 -> -0.0076746478 | AZ10: =AM10 -> -0.0097111472 | BA10: =AN10 -> -0.013463276 | BC10: =AR10 -> 39903 | BD10: =AT10 -> 0.39863999 | BE10: =AU10 -> -0.70857067
A11: 39994 | B11: -0.073128195 | C11: -0.59127453 | D11: -0.82556116 | E11: -1.5731642 | F11: 0.099746456 | G11: 1.4374342 | H11: -0.35522693 | I11: -0.28293943 | J11: 0.84351191 | K11: -0.30041232 | L11: -0.18272965 | M11: 0 | N11: 0 | O11: 0.6458429 | P11: 0 | Q11: -0.16787271 | R11: 0 | S11: 0 | T11: 0 | U11: 0 | V11: 0 | W11: 0 | X11: 0 | Y11: -0.51335586 | Z11: -0.31584038 | AA11: -0.13962108 | AB11: -0.03410106 | AC11: -0.016607341 | AD11: -0.041339223 | AE11: 0.12532296 | AF11: -2.2613156 | AH11: =K11 -> -0.30041232 | AI11: =Y11 -> -0.51335586 | AJ11: =Z11 -> -0.31584038 | AK11: =AA11 -> -0.13962108 | AL11: =AB11 -> -0.03410106 | AM11: =AC11 -> -0.016607341 | AN11: =AD11 -> -0.041339223 | AR11: =A11 -> 39994 | AS11: =AF11*4+2 -> -7.0452625 | AT11: =AH11 -> -0.30041232 | AU11: =SUM(AV11:BA11) -> -1.0608649 | AV11: =AI11 -> -0.51335586 | AW11: =AJ11 -> -0.31584038 | AX11: =AK11 -> -0.13962108 | AY11: =AL11 -> -0.03410106 | AZ11: =AM11 -> -0.016607341 | BA11: =AN11 -> -0.041339223 | BC11: =AR11 -> 39994 | BD11: =AT11 -> -0.30041232 | BE11: =AU11 -> -1.0608649
A12: 40086 | B12: -0.53090932 | C12: -0.26450707 | D12: -0.67212326 | E12: -1.5028278 | F12: 0.069033869 | G12: 1.1961043 | H12: -0.54411897 | I12: -0.18186777 | J12: 0.89049329 | K12: -0.56877654 | L12: -0.18360036 | M12: 0 | N12: 0 | O12: 0.48885426 | P12: 0 | Q12: -0.2019199 | R12: 0 | S12: 0 | T12: 0 | U12: 0 | V12: 0 | W12: 0 | X12: 0 | Y12: -0.43225273 | Z12: -0.32122089 | AA12: -0.17245864 | AB12: -0.050099817 | AC12: -0.0204331 | AD12: -0.08404302 | AE12: 0.12466498 | AF12: -2.9620085 | AH12: =K12 -> -0.56877654 | AI12: =Y12 -> -0.43225273 | AJ12: =Z12 -> -0.32122089 | AK12: =AA12 -> -0.17245864 | AL12: =AB12 -> -0.050099817 | AM12: =AC12 -> -0.0204331 | AN12: =AD12 -> -0.08404302 | AR12: =A12 -> 40086 | AS12: =AF12*4+2 -> -9.8480338 | AT12: =AH12 -> -0.56877654 | AU12: =SUM(AV12:BA12) -> -1.0805082 | AV12: =AI12 -> -0.43225273 | AW12: =AJ12 -> -0.32122089 | AX12: =AK12 -> -0.17245864 | AY12: =AL12 -> -0.050099817 | AZ12: =AM12 -> -0.0204331 | BA12: =AN12 -> -0.08404302 | BC12: =AR12 -> 40086 | BD12: =AT12 -> -0.56877654 | BE12: =AU12 -> -1.0805082
A13: 40178 | B13: -0.25242317 | C13: -0.21161538 | D13: -0.55513346 | E13: -1.5319895 | F13: 0.034934349 | G13: 0.99553621 | H13: -1.0349527 | I13: -0.1401452 | J13: 0.90746758 | K13: -1.1530786 | L13: -0.071269525 | M13: 0 | N13: 0 | O13: 0.29361464 | P13: 0 | Q13: -0.2238056 | R13: 0 | S13: 0 | T13: 0 | U13: 0 | V13: 0 | W13: 0 | X13: 0 | Y13: -0.35928238 | Z13: -0.28959157 | AA13: -0.22762518 | AB13: -0.069279424 | AC13: -0.028449793 | AD13: -0.14778106 | AE13: 0.12400264 | AF13: -3.9408671 | AH13: =K13 -> -1.1530786 | AI13: =Y13 -> -0.35928238 | AJ13: =Z13 -> -0.28959157 | AK13: =AA13 -> -0.22762518 | AL13: =AB13 -> -0.069279424 | AM13: =AC13 -> -0.028449793 | AN13: =AD13 -> -0.14778106 | AR13: =A13 -> 40178 | AS13: =AF13*4+2 -> -13.763469 | AT13: =AH13 -> -1.1530786 | AU13: =SUM(AV13:BA13) -> -1.1220094 | AV13: =AI13 -> -0.35928238 | AW13: =AJ13 -> -0.28959157 | AX13: =AK13 -> -0.22762518 | AY13: =AL13 -> -0.069279424 | AZ13: =AM13 -> -0.028449793 | BA13: =AN13 -> -0.14778106 | BC13: =AR13 -> 40178 | BD13: =AT13 -> -1.1530786 | BE13: =AU13 -> -1.1220094
... A132: 51043 | B132: -1.1485256 | C132: 0.00012590441 | D132: -0.042684349 | E132: -0.00047395337 | F132: 0.10831097 | G132: -0.17615887 | H132: 0.054636968 | I132: 0.15047017 | J132: 0.26718227 | K132: 0.0018162856 | L132: 0.37632535 | M132: 0 | N132: 0 | O132: 0.54539942 | P132: 0 | Q132: -0.20667783 | R132: 0 | S132: 0 | T132: 0 | U132: 0 | V132: 0 | W132: 0 | X132: 0 | Y132: -0.0016294185 | Z132: 0.0019674278 | AA132: -0.00054863095 | AB132: 0.00047969275 | AC132: -0.0015716835 | AD132: -0.0046451761 | AE132: 0.053433982 | AF132: -0.022767062 | AH132: =K132 -> 0.0018162856 | AI132: =Y132 -> -0.0016294185 | AJ132: =Z132 -> 0.0019674278 | AK132: =AA132 -> -0.00054863095 | AL132: =AB132 -> 0.00047969275 | AM132: =AC132 -> -0.0015716835 | AN132: =AD132 -> -0.0046451761 | AR132: =A132 -> 51043 | AS132: =AF132*4+2 -> 1.9089318 | AT132: =AH132 -> 0.0018162856 | AU132: =SUM(AV132:BA132) -> -0.0059477884 | AV132: =AI132 -> -0.0016294185 | AW132: =AJ132 -> 0.0019674278 | AX132: =AK132 -> -0.00054863095 | AY132: =AL132 -> 0.00047969275 | AZ132: =AM132 -> -0.0015716835 | BA132: =AN132 -> -0.0046451761 | BC132: =AR132 -> 51043 | BD132: =AT132 -> 0.0018162856 | BE132: =AU132 -> -0.0059477884

Sheet US_output_with_textbckup
A1: date | B1: g_sh | C1: b_liqtil_sh | D1: b_liqp_sh | E1: b_safetil_sh | F1: b_safep_sh | G1: mu_sh | H1: z_sh | I1: lambda_f_sh | J1: lambda_w_sh | K1: rm_sh | L1: sigma_omega_sh | M1: mu_e_sh | N1: gamma_sh | O1: pi_star_sh | P1: lr_sh | Q1: zp_sh | R1: tfp_sh | S1: gdpdef_sh | T1: corepce_sh | U1: gdp_sh | V1: gdi_sh | W1: BBB_sh | X1: AAA_sh | Y1: rm_shl1 | Z1: rm_shl2 | AA1: rm_shl3 | AB1: rm_shl4 | AC1: rm_shl5 | AD1: rm_shl6 | AE1: dettrend | AF1: detrendedMean | AH1: rm_sh | AI1: =Y1 -> rm_shl1 | AJ1: =Z1 -> rm_shl2 | AK1: =AA1 -> rm_shl3 | AL1: =AB1 -> rm_shl4 | AM1: =AC1 -> rm_shl5 | AN1: =AD1 -> rm_shl6 | AQ1: Plot | AR1: =A1 -> date | AS1: Monetary Policy | AT1: FG1 | AU1: FG2 | AV1: FG3 | AW1: FG4 | AX1: FG5 | AY1: FG6 | BA1: date | BB1: rm_sh | BC1: Fgsum
A2: 39172 | B2: -1.0215877 | C2: 0.14738424 | D2: -0.044907453 | E2: 0.56515568 | F2: 0.33471877 | G2: 1.4053436 | H2: 0.54693072 | I2: -0.65393335 | J2: 0.64232717 | K2: 1.7750614 | L2: 1.2826525 | M2: 0 | N2: 0 | O2: 0.3278555 | P2: 0 | Q2: 0.11087454 | R2: 0 | S2: 0 | T2: 0 | U2: 0 | V2: 0 | W2: 0 | X2: 0 | Y2: 0 | Z2: 0 | AA2: 0 | AB2: 0 | AC2: 0 | AD2: 0 | AE2: 0.13099711 | AF2: 5.5488727 | AH2: =K2 -> 1.7750614 | AI2: =Y2 -> 0 | AJ2: =Z2 -> 0 | AK2: =AA2 -> 0 | AL2: =AB2 -> 0 | AM2: =AC2 -> 0 | AN2: =AD2 -> 0 | AR2: =A2 -> 39172 | AS2: 0 | AT2: =AI2 -> 0 | AU2: =AJ2 -> 0 | AV2: =AK2 -> 0 | AW2: =AL2 -> 0 | AX2: =AM2 -> 0 | AY2: =AN2 -> 0 | BA2: =AR2 -> 39172 | BB2: =AS2 -> 0 | BC2: =#REF! -> #REF!
A3: 39263 | B3: -0.87702165 | C3: 0.14867978 | D3: -0.050839217 | E3: 0.5967583 | F3: 0.35694143 | G3: 1.4459149 | H3: 0.10615582 | I3: -0.67075329 | J3: 0.60096046 | K3: 1.5688765 | L3: 1.2418066 | M3: 0 | N3: 0 | O3: 0.33267031 | P3: 0 | Q3: 0.070231968 | R3: 0 | S3: 0 | T3: 0 | U3: 0 | V3: 0 | W3: 0 | X3: 0 | Y3: 0 | Z3: 0 | AA3: 0 | AB3: 0 | AC3: 0 | AD3: 0 | AE3: 0.13039267 | AF3: 5.0007746 | AH3: =K3 -> 1.5688765 | AI3: =Y3 -> 0 | AJ3: =Z3 -> 0 | AK3: =AA3 -> 0 | AL3: =AB3 -> 0 | AM3: =AC3 -> 0 | AN3: =AD3 -> 0 | AR3: =A3 -> 39263 | AS3: 0 | AT3: =AI3 -> 0 | AU3: =AJ3 -> 0 | AV3: =AK3 -> 0 | AW3: =AL3 -> 0 | AX3: =AM3 -> 0 | AY3: =AN3 -> 0 | BA3: =AR3 -> 39263 | BB3: =AS3 -> 0 | BC3: =#REF! -> #REF!
A4: 39355 | B4: -1.040355 | C4: 0.13425109 | D4: -0.14587387 | E4: 0.69031317 | F4: 0.37191894 | G4: 1.4503632 | H4: 0.31183503 | I4: -0.6798581 | J4: 0.61019793 | K4: 1.5086958 | L4: 1.1510338 | M4: 0 | N4: 0 | O4: 0.37118543 | P4: 0 | Q4: 0.037371485 | R4: 0 | S4: 0 | T4: 0 | U4: 0 | V4: 0 | W4: 0 | X4: 0 | Y4: 0 | Z4: 0 | AA4: 0 | AB4: 0 | AC4: 0 | AD4: 0 | AE4: 0.12978091 | AF4: 4.9008599 | AH4: =K4 -> 1.5086958 | AI4: =Y4 -> 0 | AJ4: =Z4 -> 0 | AK4: =AA4 -> 0 | AL4: =AB4 -> 0 | AM4: =AC4 -> 0 | AN4: =AD4 -> 0 | AR4: =A4 -> 39355 | AS4: 0 | AT4: =AI4 -> 0 | AU4: =AJ4 -> 0 | AV4: =AK4 -> 0 | AW4: =AL4 -> 0 | AX4: =AM4 -> 0 | AY4: =AN4 -> 0 | BA4: =AR4 -> 39355 | BB4: =AS4 -> 0 | BC4: =#REF! -> #REF!
A5: 39447 | B5: -0.99330901 | C5: 0.14258815 | D5: -0.26310356 | E5: 0.73768743 | F5: 0.36639612 | G5: 1.4317096 | H5: 0.21867959 | I5: -0.68920012 | J5: 0.66599438 | K5: 1.7274198 | L5: 1.0093212 | M5: 0 | N5: 0 | O5: 0.40724837 | P5: 0 | Q5: 0.016106972 | R5: 0 | S5: 0 | T5: 0 | U5: 0 | V5: 0 | W5: 0 | X5: 0 | Y5: 0 | Z5: 0 | AA5: 0 | AB5: 0 | AC5: 0 | AD5: 0 | AE5: 0.12916218 | AF5: 4.9067011 | AH5: =K5 -> 1.7274198 | AI5: =Y5 -> 0 | AJ5: =Z5 -> 0 | AK5: =AA5 -> 0 | AL5: =AB5 -> 0 | AM5: =AC5 -> 0 | AN5: =AD5 -> 0 | AR5: =A5 -> 39447 | AS5: 0 | AT5: =AI5 -> 0 | AU5: =AJ5 -> 0 | AV5: =AK5 -> 0 | AW5: =AL5 -> 0 | AX5: =AM5 -> 0 | AY5: =AN5 -> 0 | BA5: =AR5 -> 39447 | BB5: =AS5 -> 0 | BC5: =#REF! -> #REF!
A6: 39538 | B6: -1.0476842 | C6: 0.03061779 | D6: -0.40243934 | E6: 0.39311962 | F6: 0.33629364 | G6: 1.42832 | H6: 0.27379584 | I6: -0.67868028 | J6: 0.70115772 | K6: 2.0053504 | L6: 0.85487701 | M6: 0 | N6: 0 | O6: 0.44493982 | P6: 0 | Q6: -0.019590161 | R6: 0 | S6: 0 | T6: 0 | U6: 0 | V6: 0 | W6: 0 | X6: 0 | Y6: 0 | Z6: 0 | AA6: 0 | AB6: 0 | AC6: 0 | AD6: 0 | AE6: 0.12853685 | AF6: 4.4486148 | AH6: =K6 -> 2.0053504 | AI6: =Y6 -> 0 | AJ6: =Z6 -> 0 | AK6: =AA6 -> 0 | AL6: =AB6 -> 0 | AM6: =AC6 -> 0 | AN6: =AD6 -> 0 | AR6: =A6 -> 39538 | AS6: 0 | AT6: =AI6 -> 0 | AU6: =AJ6 -> 0 | AV6: =AK6 -> 0 | AW6: =AL6 -> 0 | AX6: =AM6 -> 0 | AY6: =AN6 -> 0 | BA6: =AR6 -> 39538 | BB6: =AS6 -> 0 | BC6: =#REF! -> #REF!
A7: 39629 | B7: -1.1086433 | C7: -0.033609602 | D7: -0.44750789 | E7: 0.09339584 | F7: 0.34011857 | G7: 1.4242313 | H7: 0.099730651 | I7: -0.64918611 | J7: 0.69311266 | K7: 2.3003353 | L7: 0.71023288 | M7: 0 | N7: 0 | O7: 0.48647302 | P7: 0 | Q7: -0.047607001 | R7: 0 | S7: 0 | T7: 0 | U7: 0 | V7: 0 | W7: 0 | X7: 0 | Y7: 0 | Z7: 0 | AA7: 0 | AB7: 0 | AC7: 0 | AD7: 0 | AE7: 0.12790526 | AF7: 3.9889816 | AH7: =K7 -> 2.3003353 | AI7: =Y7 -> 0 | AJ7: =Z7 -> 0 | AK7: =AA7 -> 0 | AL7: =AB7 -> 0 | AM7: =AC7 -> 0 | AN7: =AD7 -> 0 | AR7: =A7 -> 39629 | AS7: 0 | AT7: =AI7 -> 0 | AU7: =AJ7 -> 0 | AV7: =AK7 -> 0 | AW7: =AL7 -> 0 | AX7: =AM7 -> 0 | AY7: =AN7 -> 0 | BA7: =AR7 -> 39629 | BB7: =AS7 -> 0 | BC7: =#REF! -> #REF!
A8: 39721 | B8: -0.80373451 | C8: -0.20400532 | D8: -0.52579161 | E8: -0.37809506 | F8: 0.32715602 | G8: 1.4371073 | H8: 0.049769223 | I8: -0.6241057 | J8: 0.72601851 | K8: 1.9637541 | L8: 0.57993927 | M8: 0 | N8: 0 | O8: 0.49767707 | P8: 0 | Q8: -0.074978682 | R8: 0 | S8: 0 | T8: 0 | U8: 0 | V8: 0 | W8: 0 | X8: 0 | Y8: 0 | Z8: 0 | AA8: 0 | AB8: 0 | AC8: 0 | AD8: 0 | AE8: 0.12726775 | AF8: 3.0979785 | AH8: =K8 -> 1.9637541 | AI8: =Y8 -> 0 | AJ8: =Z8 -> 0 | AK8: =AA8 -> 0 | AL8: =AB8 -> 0 | AM8: =AC8 -> 0 | AN8: =AD8 -> 0 | AR8: =A8 -> 39721 | AS8: =AH8-$AH$8 -> 0 | AT8: =AI8 -> 0 | AU8: =AJ8 -> 0 | AV8: =AK8 -> 0 | AW8: =AL8 -> 0 | AX8: =AM8 -> 0 | AY8: =AN8 -> 0 | BA8: =AR8 -> 39721 | BB8: =AS8 -> 0 | BC8: =#REF! -> #REF!
A9: 39813 | B9: -0.21677727 | C9: -0.56638658 | D9: -0.87656555 | E9: -1.0760328 | F9: 0.163132 | G9: 1.567453 | H9: 0.77708187 | I9: -0.52720457 | J9: 0.77689645 | K9: 1.3356925 | L9: 0.32530383 | M9: 0 | N9: 0 | O9: 0.56267499 | P9: 0 | Q9: -0.12285996 | R9: 0 | S9: 0 | T9: 0 | U9: 0 | V9: 0 | W9: 0 | X9: 0 | Y9: -0.18334085 | Z9: -0.085809019 | AA9: -0.014995051 | AB9: -0.0025678522 | AC9: -0.0010749068 | AD9: -0.0015146036 | AE9: 0.12662465 | AF9: 1.9597303 | AH9: =K9 -> 1.3356925 | AI9: =Y9 -> -0.18334085 | AJ9: =Z9 -> -0.085809019 | AK9: =AA9 -> -0.014995051 | AL9: =AB9 -> -0.0025678522 | AM9: =AC9 -> -0.0010749068 | AN9: =AD9 -> -0.0015146036 | AR9: =A9 -> 39813 | AS9: =AH9-$AH$8 -> -0.62806164 | AT9: =AI9 -> -0.18334085 | AU9: =AJ9 -> -0.085809019 | AV9: =AK9 -> -0.014995051 | AW9: =AL9 -> -0.0025678522 | AX9: =AM9 -> -0.0010749068 | AY9: =AN9 -> -0.0015146036 | BA9: =AR9 -> 39813 | BB9: =AS9 -> -0.62806164 | BC9: =#REF! -> #REF!
A10: 39903 | B10: -0.13539004 | C10: -0.65246513 | D10: -0.91826335 | E10: -1.4441778 | F10: 0.115455 | G10: 1.5230468 | H10: 0.27896396 | I10: -0.40325188 | J10: 0.66681609 | K10: 0.39863999 | L10: 0.0012907793 | M10: 0 | N10: 0 | O10: 0.65980691 | P10: 0 | Q10: -0.15244255 | R10: 0 | S10: 0 | T10: 0 | U10: 0 | V10: 0 | W10: 0 | X10: 0 | Y10: -0.40182322 | Z10: -0.21133372 | AA10: -0.064564658 | AB10: -0.0076746478 | AC10: -0.0097111472 | AD10: -0.013463276 | AE10: 0.12597629 | AF10: -0.64456556 | AH10: =K10 -> 0.39863999 | AI10: =Y10 -> -0.40182322 | AJ10: =Z10 -> -0.21133372 | AK10: =AA10 -> -0.064564658 | AL10: =AB10 -> -0.0076746478 | AM10: =AC10 -> -0.0097111472 | AN10: =AD10 -> -0.013463276 | AR10: =A10 -> 39903 | AS10: =AH10-$AH$8 -> -1.5651141 | AT10: =AI10 -> -0.40182322 | AU10: =AJ10 -> -0.21133372 | AV10: =AK10 -> -0.064564658 | AW10: =AL10 -> -0.0076746478 | AX10: =AM10 -> -0.0097111472 | AY10: =AN10 -> -0.013463276 | BA10: =AR10 -> 39903 | BB10: =AS10 -> -1.5651141 | BC10: =#REF! -> #REF!
A11: 39994 | B11: -0.073128195 | C11: -0.59127453 | D11: -0.82556116 | E11: -1.5731642 | F11: 0.099746456 | G11: 1.4374342 | H11: -0.35522693 | I11: -0.28293943 | J11: 0.84351191 | K11: -0.30041232 | L11: -0.18272965 | M11: 0 | N11: 0 | O11: 0.6458429 | P11: 0 | Q11: -0.16787271 | R11: 0 | S11: 0 | T11: 0 | U11: 0 | V11: 0 | W11: 0 | X11: 0 | Y11: -0.51335586 | Z11: -0.31584038 | AA11: -0.13962108 | AB11: -0.03410106 | AC11: -0.016607341 | AD11: -0.041339223 | AE11: 0.12532296 | AF11: -2.2613156 | AH11: =K11 -> -0.30041232 | AI11: =Y11 -> -0.51335586 | AJ11: =Z11 -> -0.31584038 | AK11: =AA11 -> -0.13962108 | AL11: =AB11 -> -0.03410106 | AM11: =AC11 -> -0.016607341 | AN11: =AD11 -> -0.041339223 | AR11: =A11 -> 39994 | AS11: =AH11-$AH$8 -> -2.2641664 | AT11: =AI11 -> -0.51335586 | AU11: =AJ11 -> -0.31584038 | AV11: =AK11 -> -0.13962108 | AW11: =AL11 -> -0.03410106 | AX11: =AM11 -> -0.016607341 | AY11: =AN11 -> -0.041339223 | BA11: =AR11 -> 39994 | BB11: =AS11 -> -2.2641664 | BC11: =#REF! -> #REF!
A12: 40086 | B12: -0.53090932 | C12: -0.26450707 | D12: -0.67212326 | E12: -1.5028278 | F12: 0.069033869 | G12: 1.1961043 | H12: -0.54411897 | I12: -0.18186777 | J12: 0.89049329 | K12: -0.56877654 | L12: -0.18360036 | M12: 0 | N12: 0 | O12: 0.48885426 | P12: 0 | Q12: -0.2019199 | R12: 0 | S12: 0 | T12: 0 | U12: 0 | V12: 0 | W12: 0 | X12: 0 | Y12: -0.43225273 | Z12: -0.32122089 | AA12: -0.17245864 | AB12: -0.050099817 | AC12: -0.0204331 | AD12: -0.08404302 | AE12: 0.12466498 | AF12: -2.9620085 | AH12: =K12 -> -0.56877654 | AI12: =Y12 -> -0.43225273 | AJ12: =Z12 -> -0.32122089 | AK12: =AA12 -> -0.17245864 | AL12: =AB12 -> -0.050099817 | AM12: =AC12 -> -0.0204331 | AN12: =AD12 -> -0.08404302 | AR12: =A12 -> 40086 | AS12: =AH12-$AH$8 -> -2.5325307 | AT12: =AI12 -> -0.43225273 | AU12: =AJ12 -> -0.32122089 | AV12: =AK12 -> -0.17245864 | AW12: =AL12 -> -0.050099817 | AX12: =AM12 -> -0.0204331 | AY12: =AN12 -> -0.08404302 | BA12: =AR12 -> 40086 | BB12: =AS12 -> -2.5325307 | BC12: =#REF! -> #REF!
A13: 40178 | B13: -0.25242317 | C13: -0.21161538 | D13: -0.55513346 | E13: -1.5319895 | F13: 0.034934349 | G13: 0.99553621 | H13: -1.0349527 | I13: -0.1401452 | J13: 0.90746758 | K13: -1.1530786 | L13: -0.071269525 | M13: 0 | N13: 0 | O13: 0.29361464 | P13: 0 | Q13: -0.2238056 | R13: 0 | S13: 0 | T13: 0 | U13: 0 | V13: 0 | W13: 0 | X13: 0 | Y13: -0.35928238 | Z13: -0.28959157 | AA13: -0.22762518 | AB13: -0.069279424 | AC13: -0.028449793 | AD13: -0.14778106 | AE13: 0.12400264 | AF13: -3.9408671 | AH13: =K13 -> -1.1530786 | AI13: =Y13 -> -0.35928238 | AJ13: =Z13 -> -0.28959157 | AK13: =AA13 -> -0.22762518 | AL13: =AB13 -> -0.069279424 | AM13: =AC13 -> -0.028449793 | AN13: =AD13 -> -0.14778106 | AR13: =A13 -> 40178 | AS13: =AH13-$AH$8 -> -3.1168327 | AT13: =AI13 -> -0.35928238 | AU13: =AJ13 -> -0.28959157 | AV13: =AK13 -> -0.22762518 | AW13: =AL13 -> -0.069279424 | AX13: =AM13 -> -0.028449793 | AY13: =AN13 -> -0.14778106 | BA13: =AR13 -> 40178 | BB13: =AS13 -> -3.1168327 | BC13: =#REF! -> #REF!
A14: 40268 | B14: -0.33874738 | C14: -0.10632206 | D14: -0.44967817 | E14: -1.4913585 | F14: -0.010181156 | G14: 0.69241508 | H14: -0.74172809 | I14: -0.11958877 | J14: 0.84768893 | K14: -1.5087443 | L14: -0.0038602509 | M14: 0 | N14: 0 | O14: 0.19290541 | P14: 0 | Q14: -0.279538 | R14: 0 | S14: 0 | T14: 0 | U14: 0 | V14: 0 | W14: 0 | X14: 0 | Y14: -0.27734524 | Z14: -0.19522988 | AA14: -0.22127803 | AB14: -0.074980746 | AC14: -0.026938269 | AD14: -0.2361105 | AE14: 0.12333622 | AF14: -4.2252837 | AH14: =K14 -> -1.5087443 | AI14: =Y14 -> -0.27734524 | AJ14: =Z14 -> -0.19522988 | AK14: =AA14 -> -0.22127803 | AL14: =AB14 -> -0.074980746 | AM14: =AC14 -> -0.026938269 | AN14: =AD14 -> -0.2361105 | AR14: =A14 -> 40268 | AS14: =AH14-$AH$8 -> -3.4724984 | AT14: =AI14 -> -0.27734524 | AU14: =AJ14 -> -0.19522988 | AV14: =AK14 -> -0.22127803 | AW14: =AL14 -> -0.074980746 | AX14: =AM14 -> -0.026938269 | AY14: =AN14 -> -0.2361105 | BA14: =AR14 -> 40268 | BB14: =AS14 -> -3.4724984 | BC14: =#REF! -> #REF!
A15: 40359 | B15: -0.35320502 | C15: 0.1284906 | D15: -0.48133731 | E15: -1.2669877 | F15: -0.1610503 | G15: 0.44814344 | H15: -0.50176464 | I15: -0.1039252 | J15: 0.89953939 | K15: -1.4722494 | L15: 0.12890494 | M15: 0 | N15: 0 | O15: 0.031533582 | P15: 0 | Q15: -0.34419421 | R15: 0 | S15: 0 | T15: 0 | U15: 0 | V15: 0 | W15: 0 | X15: 0 | Y15: -0.10109961 | Z15: -0.059472477 | AA15: -0.12320261 | AB15: -0.036630312 | AC15: 0.010559019 | AD15: -0.33688892 | AE15: 0.122666 | AF15: -3.5721707 | AH15: =K15 -> -1.4722494 | AI15: =Y15 -> -0.10109961 | AJ15: =Z15 -> -0.059472477 | AK15: =AA15 -> -0.12320261 | AL15: =AB15 -> -0.036630312 | AM15: =AC15 -> 0.010559019 | AN15: =AD15 -> -0.33688892 | AR15: =A15 -> 40359 | AS15: =AH15-$AH$8 -> -3.4360035 | AT15: =AI15 -> -0.10109961 | AU15: =AJ15 -> -0.059472477 | AV15: =AK15 -> -0.12320261 | AW15: =AL15 -> -0.036630312 | AX15: =AM15 -> 0.010559019 | AY15: =AN15 -> -0.33688892 | BA15: =AR15 -> 40359 | BB15: =AS15 -> -3.4360035 | BC15: =#REF! -> #REF!
A16: 40451 | B16: -0.18159418 | C16: 0.13350859 | D16: -0.52650157 | E16: -1.0309365 | F16: -0.24665644 | G16: 0.16785317 | H16: -0.67012212 | I16: -0.076108514 | J16: 0.9217927 | K16: -1.59298 | L16: 0.15284787 | M16: 0 | N16: 0 | O16: -0.052534263 | P16: 0 | Q16: -0.37563281 | R16: 0 | S16: 0 | T16: 0 | U16: 0 | V16: 0 | W16: 0 | X16: 0 | Y16: -0.013065689 | Z16: 0.033369509 | AA16: -0.038560426 | AB16: 0.0060221368 | AC16: 0.061731846 | AD16: -0.44696724 | AE16: 0.12199225 | AF16: -3.6525417 | AH16: =K16 -> -1.59298 | AI16: =Y16 -> -0.013065689 | AJ16: =Z16 -> 0.033369509 | AK16: =AA16 -> -0.038560426 | AL16: =AB16 -> 0.0060221368 | AM16: =AC16 -> 0.061731846 | AN16: =AD16 -> -0.44696724 | AR16: =A16 -> 40451 | AS16: =AH16-$AH$8 -> -3.5567341 | AT16: =AI16 -> -0.013065689 | AU16: =AJ16 -> 0.033369509 | AV16: =AK16 -> -0.038560426 | AW16: =AL16 -> 0.0060221368 | AX16: =AM16 -> 0.061731846 | AY16: =AN16 -> -0.44696724 | BA16: =AR16 -> 40451 | BB16: =AS16 -> -3.5567341 | BC16: =#REF! -> #REF!
A17: 40543 | B17: -0.67462173 | C17: 0.071741193 | D17: -0.53275634 | E17: -0.81967091 | F17: -0.27434821 | G17: -0.032583 | H17: -0.60380231 | I17: -0.073918489 | J17: 0.92659326 | K17: -1.7387402 | L17: 0.23867936 | M17: 0 | N17: 0 | O17: -0.13992718 | P17: 0 | Q17: -0.40801408 | R17: 0 | S17: 0 | T17: 0 | U17: 0 | V17: 0 | W17: 0 | X17: 0 | Y17: 0.029830564 | Z17: 0.098258457 | AA17: 0.048896882 | AB17: 0.052191984 | AC17: 0.10898808 | AD17: -0.55805791 | AE17: 0.12131523 | AF17: -4.1599454 | AH17: =K17 -> -1.7387402 | AI17: =Y17 -> 0.029830564 | AJ17: =Z17 -> 0.098258457 | AK17: =AA17 -> 0.048896882 | AL17: =AB17 -> 0.052191984 | AM17: =AC17 -> 0.10898808 | AN17: =AD17 -> -0.55805791 | AR17: =A17 -> 40543 | AS17: =AH17-$AH$8 -> -3.7024944 | AT17: =AI17 -> 0.029830564 | AU17: =AJ17 -> 0.098258457 | AV17: =AK17 -> 0.048896882 | AW17: =AL17 -> 0.052191984 | AX17: =AM17 -> 0.10898808 | AY17: =AN17 -> -0.55805791 | BA17: =AR17 -> 40543 | BB17: =AS17 -> -3.7024944 | BC17: =#REF! -> #REF!
A18: 40633 | B18: -0.93230197 | C18: 0.039774018 | D18: -0.44687427 | E18: -0.83190869 | F18: -0.28233932 | G18: -0.29215817 | H18: -0.18609297 | I18: -0.088269937 | J18: 1.0024035 | K18: -1.6968653 | L18: 0.26709511 | M18: 0 | N18: 0 | O18: -0.21240008 | P18: 0 | Q18: -0.43294472 | R18: 0 | S18: 0 | T18: 0 | U18: 0 | V18: 0 | W18: 0 | X18: 0 | Y18: 0.032516825 | Z18: 0.10590467 | AA18: 0.097443157 | AB18: 0.087569484 | AC18: 0.16036278 | AD18: -0.65569136 | AE18: 0.12063519 | AF18: -4.1441421 | AH18: =K18 -> -1.6968653 | AI18: =Y18 -> 0.032516825 | AJ18: =Z18 -> 0.10590467 | AK18: =AA18 -> 0.097443157 | AL18: =AB18 -> 0.087569484 | AM18: =AC18 -> 0.16036278 | AN18: =AD18 -> -0.65569136 | AR18: =A18 -> 40633 | AS18: =AH18-$AH$8 -> -3.6606194 | AT18: =AI18 -> 0.032516825 | AU18: =AJ18 -> 0.10590467 | AV18: =AK18 -> 0.097443157 | AW18: =AL18 -> 0.087569484 | AX18: =AM18 -> 0.16036278 | AY18: =AN18 -> -0.65569136 | BA18: =AR18 -> 40633 | BB18: =AS18 -> -3.6606194 | BC18: =#REF! -> #REF!
A19: 40724 | B19: -0.90587513 | C19: 0.098363709 | D19: -0.48611675 | E19: -0.71317116 | F19: -0.33380644 | G19: -0.50539638 | H19: -0.3271888 | I19: -0.14068208 | J19: 0.93559777 | K19: -1.6665226 | L19: 0.37356818 | M19: 0 | N19: 0 | O19: -0.28612682 | P19: 0 | Q19: -0.5059314 | R19: 0 | S19: 0 | T19: 0 | U19: 0 | V19: 0 | W19: 0 | X19: 0 | Y19: 0.1010403 | Z19: 0.14363434 | AA19: 0.15678932 | AB19: 0.13734152 | AC19: 0.24024031 | AD19: -0.72192533 | AE19: 0.11995239 | AF19: -4.286215 | AH19: =K19 -> -1.6665226 | AI19: =Y19 -> 0.1010403 | AJ19: =Z19 -> 0.14363434 | AK19: =AA19 -> 0.15678932 | AL19: =AB19 -> 0.13734152 | AM19: =AC19 -> 0.24024031 | AN19: =AD19 -> -0.72192533 | AR19: =A19 -> 40724 | AS19: =AH19-$AH$8 -> -3.6302767 | AT19: =AI19 -> 0.1010403 | AU19: =AJ19 -> 0.14363434 | AV19: =AK19 -> 0.15678932 | AW19: =AL19 -> 0.13734152 | AX19: =AM19 -> 0.24024031 | AY19: =AN19 -> -0.72192533 | BA19: =AR19 -> 40724 | BB19: =AS19 -> -3.6302767 | BC19: =#REF! -> #REF!
... A132: 51043 | B132: -1.1485256 | C132: 0.00012590441 | D132: -0.042684349 | E132: -0.00047395337 | F132: 0.10831097 | G132: -0.17615887 | H132: 0.054636968 | I132: 0.15047017 | J132: 0.26718227 | K132: 0.0018162856 | L132: 0.37632535 | M132: 0 | N132: 0 | O132: 0.54539942 | P132: 0 | Q132: -0.20667783 | R132: 0 | S132: 0 | T132: 0 | U132: 0 | V132: 0 | W132: 0 | X132: 0 | Y132: -0.0016294185 | Z132: 0.0019674278 | AA132: -0.00054863095 | AB132: 0.00047969275 | AC132: -0.0015716835 | AD132: -0.0046451761 | AE132: 0.053433982 | AF132: -0.022767062 | AH132: =K132 -> 0.0018162856 | AI132: =Y132 -> -0.0016294185 | AJ132: =Z132 -> 0.0019674278 | AK132: =AA132 -> -0.00054863095 | AL132: =AB132 -> 0.00047969275 | AM132: =AC132 -> -0.0015716835 | AN132: =AD132 -> -0.0046451761 | AR132: =A132 -> 51043 | AS132: =AH132-$AH$8 -> -1.9619378 | AT132: =AI132 -> -0.0016294185 | AU132: =AJ132 -> 0.0019674278 | AV132: =AK132 -> -0.00054863095 | AW132: =AL132 -> 0.00047969275 | AX132: =AM132 -> -0.0015716835 | AY132: =AN132 -> -0.0046451761 | BA132: =AR132 -> 51043 | BB132: =AS132 -> -1.9619378 | BC132: =#REF! -> #REF!

Sheet US_nominal_obs_with_text
A1: date | B1: g_sh | C1: b_liqtil_sh | D1: b_liqp_sh | E1: b_safetil_sh | F1: b_safep_sh | G1: mu_sh | H1: z_sh | I1: lambda_f_sh | J1: lambda_w_sh | K1: rm_sh | L1: sigma_omega_sh | M1: mu_e_sh | N1: gamma_sh | O1: pi_star_sh | P1: lr_sh | Q1: zp_sh | R1: tfp_sh | S1: gdpdef_sh | T1: corepce_sh | U1: gdp_sh | V1: gdi_sh | W1: BBB_sh | X1: AAA_sh | Y1: rm_shl1 | Z1: rm_shl2 | AA1: rm_shl3 | AB1: rm_shl4 | AC1: rm_shl5 | AD1: rm_shl6 | AE1: dettrend | AF1: detrendedMean | AH1: rm_sh | AI1: =Y1 -> rm_shl1 | AJ1: =Z1 -> rm_shl2 | AK1: =AA1 -> rm_shl3 | AL1: =AB1 -> rm_shl4 | AM1: =AC1 -> rm_shl5 | AN1: =AD1 -> rm_shl6 | AQ1: Plot | AR1: =A1 -> date | AS1: =AF1 -> detrendedMean | AT1: Monetary Policy | AU1: Combined FG | AV1: FG1 | AW1: FG2 | AX1: FG3 | AY1: FG4 | AZ1: FG5 | BA1: FG6 | BC1: date | BD1: rm_sh | BE1: Fgsum
A2: 39172 | B2: -0.11401048 | C2: 0.20535128 | D2: -0.30209741 | E2: 0.8474755 | F2: 0.90070432 | G2: 0.041937669 | H2: 0.80119869 | I2: 0.5101117 | J2: -1.027226 | K2: -1.0879287 | L2: 0.1797764 | M2: 0 | N2: 0 | O2: 0.56068505 | P2: 0 | Q2: 0.069366088 | R2: 0 | S2: 0 | T2: 0 | U2: 0 | V2: 0 | W2: 0 | X2: 0 | Y2: 0 | Z2: 0 | AA2: 0 | AB2: 0 | AC2: 0 | AD2: 0 | AE2: -0.23818946 | AF2: 1.3471547 | AH2: =K2 -> -1.0879287 | AI2: =Y2 -> 0 | AJ2: =Z2 -> 0 | AK2: =AA2 -> 0 | AL2: =AB2 -> 0 | AM2: =AC2 -> 0 | AN2: =AD2 -> 0 | AR2: =A2 -> 39172 | AS2: =AF2*4+2 -> 7.3886186 | AT2: =AH2 -> -1.0879287 | AU2: =SUM(AV2:BA2) -> 0 | AV2: =AI2 -> 0 | AW2: =AJ2 -> 0 | AX2: =AK2 -> 0 | AY2: =AL2 -> 0 | AZ2: =AM2 -> 0 | BA2: =AN2 -> 0 | BC2: =AR2 -> 39172 | BD2: =AT2 -> -1.0879287 | BE2: =AU2 -> 0
A3: 39263 | B3: -0.0829638 | C3: 0.1979316 | D3: -0.30632052 | E3: 0.84832418 | F3: 0.93236416 | G3: 0.051456625 | H3: 0.50404739 | I3: 0.45107844 | J3: -1.1432998 | K3: -0.57113226 | L3: 0.129534 | M3: 0 | N3: 0 | O3: 0.56999491 | P3: 0 | Q3: 0.0021416526 | R3: 0 | S3: 0 | T3: 0 | U3: 0 | V3: 0 | W3: 0 | X3: 0 | Y3: 0 | Z3: 0 | AA3: 0 | AB3: 0 | AC3: 0 | AD3: 0 | AE3: -0.23600196 | AF3: 1.3471547 | AH3: =K3 -> -0.57113226 | AI3: =Y3 -> 0 | AJ3: =Z3 -> 0 | AK3: =AA3 -> 0 | AL3: =AB3 -> 0 | AM3: =AC3 -> 0 | AN3: =AD3 -> 0 | AR3: =A3 -> 39263 | AS3: =AF3*4+2 -> 7.3886186 | AT3: =AH3 -> -0.57113226 | AU3: =SUM(AV3:BA3) -> 0 | AV3: =AI3 -> 0 | AW3: =AJ3 -> 0 | AX3: =AK3 -> 0 | AY3: =AL3 -> 0 | AZ3: =AM3 -> 0 | BA3: =AN3 -> 0 | BC3: =AR3 -> 39263 | BD3: =AT3 -> -0.57113226 | BE3: =AU3 -> 0
A4: 39355 | B4: -0.15392337 | C4: 0.16990305 | D4: -0.44946874 | E4: 0.9398166 | F4: 0.95374823 | G4: 0.063708809 | H4: 0.61741563 | I4: 0.42669807 | J4: -1.2125307 | K4: -0.64943507 | L4: 0.11571594 | M4: 0 | N4: 0 | O4: 0.61141748 | P4: 0 | Q4: -0.032081448 | R4: 0 | S4: 0 | T4: 0 | U4: 0 | V4: 0 | W4: 0 | X4: 0 | Y4: 0 | Z4: 0 | AA4: 0 | AB4: 0 | AC4: 0 | AD4: 0 | AE4: -0.23382987 | AF4: 1.1671547 | AH4: =K4 -> -0.64943507 | AI4: =Y4 -> 0 | AJ4: =Z4 -> 0 | AK4: =AA4 -> 0 | AL4: =AB4 -> 0 | AM4: =AC4 -> 0 | AN4: =AD4 -> 0 | AR4: =A4 -> 39355 | AS4: =AF4*4+2 -> 6.6686186 | AT4: =AH4 -> -0.64943507 | AU4: =SUM(AV4:BA4) -> 0 | AV4: =AI4 -> 0 | AW4: =AJ4 -> 0 | AX4: =AK4 -> 0 | AY4: =AL4 -> 0 | AZ4: =AM4 -> 0 | BA4: =AN4 -> 0 | BC4: =AR4 -> 39355 | BD4: =AT4 -> -0.64943507 | BE4: =AU4 -> 0
A5: 39447 | B5: -0.15363652 | C5: 0.17558103 | D5: -0.630747 | E5: 0.96697803 | F5: 0.94364037 | G5: 0.062024371 | H5: 0.59346198 | I5: 0.45002707 | J5: -1.1937889 | K5: -1.0906308 | L5: 0.088389876 | M5: 0 | N5: 0 | O5: 0.64479227 | P5: 0 | Q5: -0.027263892 | R5: 0 | S5: 0 | T5: 0 | U5: 0 | V5: 0 | W5: 0 | X5: 0 | Y5: 0 | Z5: 0 | AA5: 0 | AB5: 0 | AC5: 0 | AD5: 0 | AE5: -0.23167323 | AF5: 0.59715465 | AH5: =K5 -> -1.0906308 | AI5: =Y5 -> 0 | AJ5: =Z5 -> 0 | AK5: =AA5 -> 0 | AL5: =AB5 -> 0 | AM5: =AC5 -> 0 | AN5: =AD5 -> 0 | AR5: =A5 -> 39447 | AS5: =AF5*4+2 -> 4.3886186 | AT5: =AH5 -> -1.0906308 | AU5: =SUM(AV5:BA5) -> 0 | AV5: =AI5 -> 0 | AW5: =AJ5 -> 0 | AX5: =AK5 -> 0 | AY5: =AL5 -> 0 | AZ5: =AM5 -> 0 | BA5: =AN5 -> 0 | BC5: =AR5 -> 39447 | BD5: =AT5 -> -1.0906308 | BE5: =AU5 -> 0
A6: 39538 | B6: -0.17654154 | C6: 0.014279886 | D6: -0.84968192 | E6: 0.45145768 | F6: 0.89491982 | G6: 0.049151621 | H6: 0.65422473 | I6: 0.36489 | J6: -1.1859989 | K6: -1.3356229 | L6: 0.025228524 | M6: 0 | N6: 0 | O6: 0.67497521 | P6: 0 | Q6: -0.074595448 | R6: 0 | S6: 0 | T6: 0 | U6: 0 | V6: 0 | W6: 0 | X6: 0 | Y6: 0 | Z6: 0 | AA6: 0 | AB6: 0 | AC6: 0 | AD6: 0 | AE6: -0.22953208 | AF6: -0.72284535 | AH6: =K6 -> -1.3356229 | AI6: =Y6 -> 0 | AJ6: =Z6 -> 0 | AK6: =AA6 -> 0 | AL6: =AB6 -> 0 | AM6: =AC6 -> 0 | AN6: =AD6 -> 0 | AR6: =A6 -> 39538 | AS6: =AF6*4+2 -> -0.89138139 | AT6: =AH6 -> -1.3356229 | AU6: =SUM(AV6:BA6) -> 0 | AV6: =AI6 -> 0 | AW6: =AJ6 -> 0 | AX6: =AK6 -> 0 | AY6: =AL6 -> 0 | AZ6: =AM6 -> 0 | BA6: =AN6 -> 0 | BC6: =AR6 -> 39538 | BD6: =AT6 -> -1.3356229 | BE6: =AU6 -> 0
A7: 39629 | B7: -0.20191707 | C7: -0.072830785 | D7: -0.92562239 | E7: 0.024837465 | F7: 0.89781248 | G7: 0.039769291 | H7: 0.5553546 | I7: 0.2809677 | J7: -1.2640069 | K7: -1.497997 | L7: -0.053407566 | M7: 0 | N7: 0 | O7: 0.70510088 | P7: 0 | Q7: -0.083499592 | R7: 0 | S7: 0 | T7: 0 | U7: 0 | V7: 0 | W7: 0 | X7: 0 | Y7: 0 | Z7: 0 | AA7: 0 | AB7: 0 | AC7: 0 | AD7: 0 | AE7: -0.22740646 | AF7: -1.8228453 | AH7: =K7 -> -1.497997 | AI7: =Y7 -> 0 | AJ7: =Z7 -> 0 | AK7: =AA7 -> 0 | AL7: =AB7 -> 0 | AM7: =AC7 -> 0 | AN7: =AD7 -> 0 | AR7: =A7 -> 39629 | AS7: =AF7*4+2 -> -5.2913814 | AT7: =AH7 -> -1.497997 | AU7: =SUM(AV7:BA7) -> 0 | AV7: =AI7 -> 0 | AW7: =AJ7 -> 0 | AX7: =AK7 -> 0 | AY7: =AL7 -> 0 | AZ7: =AM7 -> 0 | BA7: =AN7 -> 0 | BC7: =AR7 -> 39629 | BD7: =AT7 -> -1.497997 | BE7: =AU7 -> 0
A8: 39721 | B8: -0.089411128 | C8: -0.30391018 | D8: -1.0525338 | E8: -0.62106526 | F8: 0.87518085 | G8: 0.032332229 | H8: 0.50940327 | I8: 0.31075263 | J8: -1.2818167 | K8: -0.60798148 | L8: -0.12702577 | M8: 0 | N8: 0 | O8: 0.70140354 | P8: 0 | Q8: -0.082877244 | R8: 0 | S8: 0 | T8: 0 | U8: 0 | V8: 0 | W8: 0 | X8: 0 | Y8: 0 | Z8: 0 | AA8: 0 | AB8: 0 | AC8: 0 | AD8: 0 | AE8: -0.22529638 | AF8: -1.9628453 | AH8: =K8 -> -0.60798148 | AI8: =Y8 -> 0 | AJ8: =Z8 -> 0 | AK8: =AA8 -> 0 | AL8: =AB8 -> 0 | AM8: =AC8 -> 0 | AN8: =AD8 -> 0 | AR8: =A8 -> 39721 | AS8: =AF8*4+2 -> -5.8513814 | AT8: =AH8 -> -0.60798148 | AU8: =SUM(AV8:BA8) -> 0 | AV8: =AI8 -> 0 | AW8: =AJ8 -> 0 | AX8: =AK8 -> 0 | AY8: =AL8 -> 0 | AZ8: =AM8 -> 0 | BA8: =AN8 -> 0 | BC8: =AR8 -> 39721 | BD8: =AT8 -> -0.60798148 | BE8: =AU8 -> 0
A9: 39813 | B9: 0.13485818 | C9: -0.79217761 | D9: -1.6043944 | E9: -1.5547182 | F9: 0.61745713 | G9: 0.036130617 | H9: 1.0808468 | I9: -0.041293101 | J9: -1.2454774 | K9: 0.12813139 | L9: -0.1382118 | M9: 0 | N9: 0 | O9: 0.75204073 | P9: 0 | Q9: -0.13766645 | R9: 0 | S9: 0 | T9: 0 | U9: 0 | V9: 0 | W9: 0 | X9: 0 | Y9: -0.25638525 | Z9: -0.12030565 | AA9: -0.021104289 | AB9: -0.0036357936 | AC9: -0.0015368701 | AD9: -0.0022014941 | AE9: -0.22320187 | AF9: -3.3928453 | AH9: =K9 -> 0.12813139 | AI9: =Y9 -> -0.25638525 | AJ9: =Z9 -> -0.12030565 | AK9: =AA9 -> -0.021104289 | AL9: =AB9 -> -0.0036357936 | AM9: =AC9 -> -0.0015368701 | AN9: =AD9 -> -0.0022014941 | AR9: =A9 -> 39813 | AS9: =AF9*4+2 -> -11.571381 | AT9: =AH9 -> 0.12813139 | AU9: =SUM(AV9:BA9) -> -0.40516934 | AV9: =AI9 -> -0.25638525 | AW9: =AJ9 -> -0.12030565 | AX9: =AK9 -> -0.021104289 | AY9: =AL9 -> -0.0036357936 | AZ9: =AM9 -> -0.0015368701 | BA9: =AN9 -> -0.0022014941 | BC9: =AR9 -> 39813 | BD9: =AT9 -> 0.12813139 | BE9: =AU9 -> -0.40516934
A10: 39903 | B10: 0.16168339 | C10: -0.87584388 | D10: -1.6876661 | E10: -1.9921387 | F10: 0.53457376 | G10: 0.07776 | H10: 0.8672465 | I10: -0.18521718 | J10: -1.5674078 | K10: 0.96091862 | L10: -0.21059841 | M10: 0 | N10: 0 | O10: 0.83058518 | P10: 0 | Q10: -0.10143052 | R10: 0 | S10: 0 | T10: 0 | U10: 0 | V10: 0 | W10: 0 | X10: 0 | Y10: 0.11106692 | Z10: -0.29123047 | AA10: -0.089995246 | AB10: -0.010718854 | AC10: -0.013823975 | AD10: -0.019485595 | AE10: -0.22112295 | AF10: -3.7228453 | AH10: =K10 -> 0.96091862 | AI10: =Y10 -> 0.11106692 | AJ10: =Z10 -> -0.29123047 | AK10: =AA10 -> -0.089995246 | AL10: =AB10 -> -0.010718854 | AM10: =AC10 -> -0.013823975 | AN10: =AD10 -> -0.019485595 | AR10: =A10 -> 39903 | AS10: =AF10*4+2 -> -12.891381 | AT10: =AH10 -> 0.96091862 | AU10: =SUM(AV10:BA10) -> -0.31418722 | AV10: =AI10 -> 0.11106692 | AW10: =AJ10 -> -0.29123047 | AX10: =AK10 -> -0.089995246 | AY10: =AL10 -> -0.010718854 | AZ10: =AM10 -> -0.013823975 | BA10: =AN10 -> -0.019485595 | BC10: =AR10 -> 39903 | BD10: =AT10 -> 0.96091862 | BE10: =AU10 -> -0.31418722
A11: 39994 | B11: 0.14543892 | C11: -0.75459901 | D11: -1.5585879 | E11: -2.0853044 | F11: 0.50176509 | G11: 0.062438847 | H11: 0.35467143 | I11: -0.18173936 | J11: -1.3758204 | K11: 1.0274072 | L11: -0.39438341 | M11: 0 | N11: 0 | O11: 0.79029194 | P11: 0 | Q11: -0.013172518 | R11: 0 | S11: 0 | T11: 0 | U11: 0 | V11: 0 | W11: 0 | X11: 0 | Y11: 0.33599819 | Z11: -0.036183899 | AA11: -0.19193871 | AB11: -0.047698813 | AC11: -0.023130777 | AD11: -0.059238196 | AE11: -0.21905963 | AF11: -3.7228453 | AH11: =K11 -> 1.0274072 | AI11: =Y11 -> 0.33599819 | AJ11: =Z11 -> -0.036183899 | AK11: =AA11 -> -0.19193871 | AL11: =AB11 -> -0.047698813 | AM11: =AC11 -> -0.023130777 | AN11: =AD11 -> -0.059238196 | AR11: =A11 -> 39994 | AS11: =AF11*4+2 -> -12.891381 | AT11: =AH11 -> 1.0274072 | AU11: =SUM(AV11:BA11) -> -0.022192205 | AV11: =AI11 -> 0.33599819 | AW11: =AJ11 -> -0.036183899 | AX11: =AK11 -> -0.19193871 | AY11: =AL11 -> -0.047698813 | AZ11: =AM11 -> -0.023130777 | BA11: =AN11 -> -0.059238196 | BC11: =AR11 -> 39994 | BD11: =AT11 -> 1.0274072 | BE11: =AU11 -> -0.022192205
A12: 40086 | B12: -0.062353511 | C12: -0.27312012 | D12: -1.3292818 | E12: -1.9060385 | F12: 0.44642715 | G12: 0.012925012 | H12: 0.080859986 | I12: -0.15167571 | J12: -1.3163403 | K12: 0.56616084 | L12: -0.54183291 | M12: 0 | N12: 0 | O12: 0.61082403 | P12: 0 | Q12: 0.0016531346 | R12: 0 | S12: 0 | T12: 0 | U12: 0 | V12: 0 | W12: 0 | X12: 0 | Y12: 0.41404851 | Z12: 0.26792166 | AA12: -0.14115197 | AB12: -0.068417176 | AC12: -0.027625262 | AD12: -0.11881657 | AE12: -0.21701192 | AF12: -3.7528453 | AH12: =K12 -> 0.56616084 | AI12: =Y12 -> 0.41404851 | AJ12: =Z12 -> 0.26792166 | AK12: =AA12 -> -0.14115197 | AL12: =AB12 -> -0.068417176 | AM12: =AC12 -> -0.027625262 | AN12: =AD12 -> -0.11881657 | AR12: =A12 -> 40086 | AS12: =AF12*4+2 -> -13.011381 | AT12: =AH12 -> 0.56616084 | AU12: =SUM(AV12:BA12) -> 0.32595919 | AV12: =AI12 -> 0.41404851 | AW12: =AJ12 -> 0.26792166 | AX12: =AK12 -> -0.14115197 | AY12: =AL12 -> -0.068417176 | AZ12: =AM12 -> -0.027625262 | BA12: =AN12 -> -0.11881657 | BC12: =AR12 -> 40086 | BD12: =AT12 -> 0.56616084 | BE12: =AU12 -> 0.32595919
A13: 40178 | B13: 0.00050746881 | C13: -0.19682351 | D13: -1.1508529 | E13: -1.8816935 | F13: 0.38547561 | G13: -0.095120943 | H13: -0.39911134 | I13: 0.063178418 | J13: -1.2794913 | K13: 1.0641138 | L13: -0.57081218 | M13: 0 | N13: 0 | O13: 0.41206864 | P13: 0 | Q13: 0.055765932 | R13: 0 | S13: 0 | T13: 0 | U13: 0 | V13: 0 | W13: 0 | X13: 0 | Y13: 0.019309171 | Z13: 0.3039599 | AA13: 0.017642377 | AB13: -0.071919374 | AC13: -0.037899564 | AD13: -0.20616227 | AE13: -0.2149798 | AF13: -3.7828453 | AH13: =K13 -> 1.0641138 | AI13: =Y13 -> 0.019309171 | AJ13: =Z13 -> 0.3039599 | AK13: =AA13 -> 0.017642377 | AL13: =AB13 -> -0.071919374 | AM13: =AC13 -> -0.037899564 | AN13: =AD13 -> -0.20616227 | AR13: =A13 -> 40178 | AS13: =AF13*4+2 -> -13.131381 | AT13: =AH13 -> 1.0641138 | AU13: =SUM(AV13:BA13) -> 0.024930243 | AV13: =AI13 -> 0.019309171 | AW13: =AJ13 -> 0.3039599 | AX13: =AK13 -> 0.017642377 | AY13: =AL13 -> -0.071919374 | AZ13: =AM13 -> -0.037899564 | BA13: =AN13 -> -0.20616227 | BC13: =AR13 -> 40178 | BD13: =AT13 -> 1.0641138 | BE13: =AU13 -> 0.024930243
... A132: 51043 | B132: -0.15667678 | C132: -0.0002117682 | D132: -0.16260993 | E132: -5.0202682e-05 | F132: 0.2514027 | G132: 0.011259126 | H132: 0.073990792 | I132: -0.15141055 | J132: -0.28232529 | K132: -0.0012069852 | L132: -0.0052149979 | M132: 0 | N132: 0 | O132: 0.40992744 | P132: 0 | Q132: 0.15161488 | R132: 0 | S132: 0 | T132: 0 | U132: 0 | V132: 0 | W132: 0 | X132: 0 | Y132: 0.0017353699 | Z132: -0.0014038441 | AA132: 0.00070264928 | AB132: -0.00022776197 | AC132: 0.001659447 | AD132: 0.0040525021 | AE132: -0.066359325 | AF132: 0.078647472 | AH132: =K132 -> -0.0012069852 | AI132: =Y132 -> 0.0017353699 | AJ132: =Z132 -> -0.0014038441 | AK132: =AA132 -> 0.00070264928 | AL132: =AB132 -> -0.00022776197 | AM132: =AC132 -> 0.001659447 | AN132: =AD132 -> 0.0040525021 | AR132: =A132 -> 51043 | AS132: =AF132*4+2 -> 2.3145899 | AT132: =AH132 -> -0.0012069852 | AU132: =SUM(AV132:BA132) -> 0.0065183623 | AV132: =AI132 -> 0.0017353699 | AW132: =AJ132 -> -0.0014038441 | AX132: =AK132 -> 0.00070264928 | AY132: =AL132 -> -0.00022776197 | AZ132: =AM132 -> 0.001659447 | BA132: =AN132 -> 0.0040525021 | BC132: =AR132 -> 51043 | BD132: =AT132 -> -0.0012069852 | BE132: =AU132 -> 0.0065183623

Sheet US_output_with_text_backup
A1: date | B1: g_sh | C1: b_liqtil_sh | D1: b_liqp_sh | E1: b_safetil_sh | F1: b_safep_sh | G1: mu_sh | H1: z_sh | I1: lambda_f_sh | J1: lambda_w_sh | K1: rm_sh | L1: sigma_omega_sh | M1: mu_e_sh | N1: gamma_sh | O1: pi_star_sh | P1: lr_sh | Q1: zp_sh | R1: tfp_sh | S1: gdpdef_sh | T1: corepce_sh | U1: gdp_sh | V1: gdi_sh | W1: BBB_sh | X1: AAA_sh | Y1: rm_shl1 | Z1: rm_shl2 | AA1: rm_shl3 | AB1: rm_shl4 | AC1: rm_shl5 | AD1: rm_shl6 | AE1: dettrend | AF1: detrendedMean | AH1: rm_sh | AI1: =Y1 -> rm_shl1 | AJ1: =Z1 -> rm_shl2 | AK1: =AA1 -> rm_shl3 | AL1: =AB1 -> rm_shl4 | AM1: =AC1 -> rm_shl5 | AN1: =AD1 -> rm_shl6 | AQ1: Plot | AR1: =A1 -> date | AS1: =AF1 -> detrendedMean | AT1: Monetary Policy | AU1: Fgsum | AV1: FG1 | AW1: FG2 | AX1: FG3 | AY1: FG4 | AZ1: FG5 | BA1: FG6 | BC1: date | BD1: rm_sh | BE1: Fgsum
A2: 39172 | B2: -1.0215877 | C2: 0.14738424 | D2: -0.044907453 | E2: 0.56515568 | F2: 0.33471877 | G2: 1.4053436 | H2: 0.54693072 | I2: -0.65393335 | J2: 0.64232717 | K2: 1.7750614 | L2: 1.2826525 | M2: 0 | N2: 0 | O2: 0.3278555 | P2: 0 | Q2: 0.11087454 | R2: 0 | S2: 0 | T2: 0 | U2: 0 | V2: 0 | W2: 0 | X2: 0 | Y2: 0 | Z2: 0 | AA2: 0 | AB2: 0 | AC2: 0 | AD2: 0 | AE2: 0.13099711 | AF2: 5.5488727 | AH2: =K2 -> 1.7750614 | AI2: =Y2 -> 0 | AJ2: =Z2 -> 0 | AK2: =AA2 -> 0 | AL2: =AB2 -> 0 | AM2: =AC2 -> 0 | AN2: =AD2 -> 0 | AR2: =A2 -> 39172 | AS2: =AF2*4+2 -> 24.195491 | AT2: =AH2 -> 1.7750614 | AU2: =SUM(AV2:BA2) -> 0 | AV2: =AI2 -> 0 | AW2: =AJ2 -> 0 | AX2: =AK2 -> 0 | AY2: =AL2 -> 0 | AZ2: =AM2 -> 0 | BA2: =AN2 -> 0 | BC2: =AR2 -> 39172 | BD2: =AT2 -> 1.7750614 | BE2: =AU2 -> 0
A3: 39263 | B3: -0.87702165 | C3: 0.14867978 | D3: -0.050839217 | E3: 0.5967583 | F3: 0.35694143 | G3: 1.4459149 | H3: 0.10615582 | I3: -0.67075329 | J3: 0.60096046 | K3: 1.5688765 | L3: 1.2418066 | M3: 0 | N3: 0 | O3: 0.33267031 | P3: 0 | Q3: 0.070231968 | R3: 0 | S3: 0 | T3: 0 | U3: 0 | V3: 0 | W3: 0 | X3: 0 | Y3: 0 | Z3: 0 | AA3: 0 | AB3: 0 | AC3: 0 | AD3: 0 | AE3: 0.13039267 | AF3: 5.0007746 | AH3: =K3 -> 1.5688765 | AI3: =Y3 -> 0 | AJ3: =Z3 -> 0 | AK3: =AA3 -> 0 | AL3: =AB3 -> 0 | AM3: =AC3 -> 0 | AN3: =AD3 -> 0 | AR3: =A3 -> 39263 | AS3: =AF3*4+2 -> 22.003098 | AT3: =AH3 -> 1.5688765 | AU3: =SUM(AV3:BA3) -> 0 | AV3: =AI3 -> 0 | AW3: =AJ3 -> 0 | AX3: =AK3 -> 0 | AY3: =AL3 -> 0 | AZ3: =AM3 -> 0 | BA3: =AN3 -> 0 | BC3: =AR3 -> 39263 | BD3: =AT3 -> 1.5688765 | BE3: =AU3 -> 0
A4: 39355 | B4: -1.040355 | C4: 0.13425109 | D4: -0.14587387 | E4: 0.69031317 | F4: 0.37191894 | G4: 1.4503632 | H4: 0.31183503 | I4: -0.6798581 | J4: 0.61019793 | K4: 1.5086958 | L4: 1.1510338 | M4: 0 | N4: 0 | O4: 0.37118543 | P4: 0 | Q4: 0.037371485 | R4: 0 | S4: 0 | T4: 0 | U4: 0 | V4: 0 | W4: 0 | X4: 0 | Y4: 0 | Z4: 0 | AA4: 0 | AB4: 0 | AC4: 0 | AD4: 0 | AE4: 0.12978091 | AF4: 4.9008599 | AH4: =K4 -> 1.5086958 | AI4: =Y4 -> 0 | AJ4: =Z4 -> 0 | AK4: =AA4 -> 0 | AL4: =AB4 -> 0 | AM4: =AC4 -> 0 | AN4: =AD4 -> 0 | AR4: =A4 -> 39355 | AS4: =AF4*4+2 -> 21.603439 | AT4: =AH4 -> 1.5086958 | AU4: =SUM(AV4:BA4) -> 0 | AV4: =AI4 -> 0 | AW4: =AJ4 -> 0 | AX4: =AK4 -> 0 | AY4: =AL4 -> 0 | AZ4: =AM4 -> 0 | BA4: =AN4 -> 0 | BC4: =AR4 -> 39355 | BD4: =AT4 -> 1.5086958 | BE4: =AU4 -> 0
A5: 39447 | B5: -0.99330901 | C5: 0.14258815 | D5: -0.26310356 | E5: 0.73768743 | F5: 0.36639612 | G5: 1.4317096 | H5: 0.21867959 | I5: -0.68920012 | J5: 0.66599438 | K5: 1.7274198 | L5: 1.0093212 | M5: 0 | N5: 0 | O5: 0.40724837 | P5: 0 | Q5: 0.016106972 | R5: 0 | S5: 0 | T5: 0 | U5: 0 | V5: 0 | W5: 0 | X5: 0 | Y5: 0 | Z5: 0 | AA5: 0 | AB5: 0 | AC5: 0 | AD5: 0 | AE5: 0.12916218 | AF5: 4.9067011 | AH5: =K5 -> 1.7274198 | AI5: =Y5 -> 0 | AJ5: =Z5 -> 0 | AK5: =AA5 -> 0 | AL5: =AB5 -> 0 | AM5: =AC5 -> 0 | AN5: =AD5 -> 0 | AR5: =A5 -> 39447 | AS5: =AF5*4+2 -> 21.626804 | AT5: =AH5 -> 1.7274198 | AU5: =SUM(AV5:BA5) -> 0 | AV5: =AI5 -> 0 | AW5: =AJ5 -> 0 | AX5: =AK5 -> 0 | AY5: =AL5 -> 0 | AZ5: =AM5 -> 0 | BA5: =AN5 -> 0 | BC5: =AR5 -> 39447 | BD5: =AT5 -> 1.7274198 | BE5: =AU5 -> 0
A6: 39538 | B6: -1.0476842 | C6: 0.03061779 | D6: -0.40243934 | E6: 0.39311962 | F6: 0.33629364 | G6: 1.42832 | H6: 0.27379584 | I6: -0.67868028 | J6: 0.70115772 | K6: 2.0053504 | L6: 0.85487701 | M6: 0 | N6: 0 | O6: 0.44493982 | P6: 0 | Q6: -0.019590161 | R6: 0 | S6: 0 | T6: 0 | U6: 0 | V6: 0 | W6: 0 | X6: 0 | Y6: 0 | Z6: 0 | AA6: 0 | AB6: 0 | AC6: 0 | AD6: 0 | AE6: 0.12853685 | AF6: 4.4486148 | AH6: =K6 -> 2.0053504 | AI6: =Y6 -> 0 | AJ6: =Z6 -> 0 | AK6: =AA6 -> 0 | AL6: =AB6 -> 0 | AM6: =AC6 -> 0 | AN6: =AD6 -> 0 | AR6: =A6 -> 39538 | AS6: =AF6*4+2 -> 19.794459 | AT6: =AH6 -> 2.0053504 | AU6: =SUM(AV6:BA6) -> 0 | AV6: =AI6 -> 0 | AW6: =AJ6 -> 0 | AX6: =AK6 -> 0 | AY6: =AL6 -> 0 | AZ6: =AM6 -> 0 | BA6: =AN6 -> 0 | BC6: =AR6 -> 39538 | BD6: =AT6 -> 2.0053504 | BE6: =AU6 -> 0
A7: 39629 | B7: -1.1086433 | C7: -0.033609602 | D7: -0.44750789 | E7: 0.09339584 | F7: 0.34011857 | G7: 1.4242313 | H7: 0.099730651 | I7: -0.64918611 | J7: 0.69311266 | K7: 2.3003353 | L7: 0.71023288 | M7: 0 | N7: 0 | O7: 0.48647302 | P7: 0 | Q7: -0.047607001 | R7: 0 | S7: 0 | T7: 0 | U7: 0 | V7: 0 | W7: 0 | X7: 0 | Y7: 0 | Z7: 0 | AA7: 0 | AB7: 0 | AC7: 0 | AD7: 0 | AE7: 0.12790526 | AF7: 3.9889816 | AH7: =K7 -> 2.3003353 | AI7: =Y7 -> 0 | AJ7: =Z7 -> 0 | AK7: =AA7 -> 0 | AL7: =AB7 -> 0 | AM7: =AC7 -> 0 | AN7: =AD7 -> 0 | AR7: =A7 -> 39629 | AS7: =AF7*4+2 -> 17.955926 | AT7: =AH7 -> 2.3003353 | AU7: =SUM(AV7:BA7) -> 0 | AV7: =AI7 -> 0 | AW7: =AJ7 -> 0 | AX7: =AK7 -> 0 | AY7: =AL7 -> 0 | AZ7: =AM7 -> 0 | BA7: =AN7 -> 0 | BC7: =AR7 -> 39629 | BD7: =AT7 -> 2.3003353 | BE7: =AU7 -> 0
A8: 39721 | B8: -0.80373451 | C8: -0.20400532 | D8: -0.52579161 | E8: -0.37809506 | F8: 0.32715602 | G8: 1.4371073 | H8: 0.049769223 | I8: -0.6241057 | J8: 0.72601851 | K8: 1.9637541 | L8: 0.57993927 | M8: 0 | N8: 0 | O8: 0.49767707 | P8: 0 | Q8: -0.074978682 | R8: 0 | S8: 0 | T8: 0 | U8: 0 | V8: 0 | W8: 0 | X8: 0 | Y8: 0 | Z8: 0 | AA8: 0 | AB8: 0 | AC8: 0 | AD8: 0 | AE8: 0.12726775 | AF8: 3.0979785 | AH8: =K8 -> 1.9637541 | AI8: =Y8 -> 0 | AJ8: =Z8 -> 0 | AK8: =AA8 -> 0 | AL8: =AB8 -> 0 | AM8: =AC8 -> 0 | AN8: =AD8 -> 0 | AR8: =A8 -> 39721 | AS8: =AF8*4+2 -> 14.391914 | AT8: =AH8 -> 1.9637541 | AU8: =SUM(AV8:BA8) -> 0 | AV8: =AI8 -> 0 | AW8: =AJ8 -> 0 | AX8: =AK8 -> 0 | AY8: =AL8 -> 0 | AZ8: =AM8 -> 0 | BA8: =AN8 -> 0 | BC8: =AR8 -> 39721 | BD8: =AT8 -> 1.9637541 | BE8: =AU8 -> 0
A9: 39813 | B9: -0.21677727 | C9: -0.56638658 | D9: -0.87656555 | E9: -1.0760328 | F9: 0.163132 | G9: 1.567453 | H9: 0.77708187 | I9: -0.52720457 | J9: 0.77689645 | K9: 1.3356925 | L9: 0.32530383 | M9: 0 | N9: 0 | O9: 0.56267499 | P9: 0 | Q9: -0.12285996 | R9: 0 | S9: 0 | T9: 0 | U9: 0 | V9: 0 | W9: 0 | X9: 0 | Y9: -0.18334085 | Z9: -0.085809019 | AA9: -0.014995051 | AB9: -0.0025678522 | AC9: -0.0010749068 | AD9: -0.0015146036 | AE9: 0.12662465 | AF9: 1.9597303 | AH9: =K9 -> 1.3356925 | AI9: =Y9 -> -0.18334085 | AJ9: =Z9 -> -0.085809019 | AK9: =AA9 -> -0.014995051 | AL9: =AB9 -> -0.0025678522 | AM9: =AC9 -> -0.0010749068 | AN9: =AD9 -> -0.0015146036 | AR9: =A9 -> 39813 | AS9: =AF9*4+2 -> 9.8389213 | AT9: =AH9 -> 1.3356925 | AU9: =SUM(AV9:BA9) -> -0.28930228 | AV9: =AI9 -> -0.18334085 | AW9: =AJ9 -> -0.085809019 | AX9: =AK9 -> -0.014995051 | AY9: =AL9 -> -0.0025678522 | AZ9: =AM9 -> -0.0010749068 | BA9: =AN9 -> -0.0015146036 | BC9: =AR9 -> 39813 | BD9: =AT9 -> 1.3356925 | BE9: =AU9 -> -0.28930228
A10: 39903 | B10: -0.13539004 | C10: -0.65246513 | D10: -0.91826335 | E10: -1.4441778 | F10: 0.115455 | G10: 1.5230468 | H10: 0.27896396 | I10: -0.40325188 | J10: 0.66681609 | K10: 0.39863999 | L10: 0.0012907793 | M10: 0 | N10: 0 | O10: 0.65980691 | P10: 0 | Q10: -0.15244255 | R10: 0 | S10: 0 | T10: 0 | U10: 0 | V10: 0 | W10: 0 | X10: 0 | Y10: -0.40182322 | Z10: -0.21133372 | AA10: -0.064564658 | AB10: -0.0076746478 | AC10: -0.0097111472 | AD10: -0.013463276 | AE10: 0.12597629 | AF10: -0.64456556 | AH10: =K10 -> 0.39863999 | AI10: =Y10 -> -0.40182322 | AJ10: =Z10 -> -0.21133372 | AK10: =AA10 -> -0.064564658 | AL10: =AB10 -> -0.0076746478 | AM10: =AC10 -> -0.0097111472 | AN10: =AD10 -> -0.013463276 | AR10: =A10 -> 39903 | AS10: =AF10*4+2 -> -0.57826224 | AT10: =AH10 -> 0.39863999 | AU10: =SUM(AV10:BA10) -> -0.70857067 | AV10: =AI10 -> -0.40182322 | AW10: =AJ10 -> -0.21133372 | AX10: =AK10 -> -0.064564658 | AY10: =AL10 -> -0.0076746478 | AZ10: =AM10 -> -0.0097111472 | BA10: =AN10 -> -0.013463276 | BC10: =AR10 -> 39903 | BD10: =AT10 -> 0.39863999 | BE10: =AU10 -> -0.70857067
A11: 39994 | B11: -0.073128195 | C11: -0.59127453 | D11: -0.82556116 | E11: -1.5731642 | F11: 0.099746456 | G11: 1.4374342 | H11: -0.35522693 | I11: -0.28293943 | J11: 0.84351191 | K11: -0.30041232 | L11: -0.18272965 | M11: 0 | N11: 0 | O11: 0.6458429 | P11: 0 | Q11: -0.16787271 | R11: 0 | S11: 0 | T11: 0 | U11: 0 | V11: 0 | W11: 0 | X11: 0 | Y11: -0.51335586 | Z11: -0.31584038 | AA11: -0.13962108 | AB11: -0.03410106 | AC11: -0.016607341 | AD11: -0.041339223 | AE11: 0.12532296 | AF11: -2.2613156 | AH11: =K11 -> -0.30041232 | AI11: =Y11 -> -0.51335586 | AJ11: =Z11 -> -0.31584038 | AK11: =AA11 -> -0.13962108 | AL11: =AB11 -> -0.03410106 | AM11: =AC11 -> -0.016607341 | AN11: =AD11 -> -0.041339223 | AR11: =A11 -> 39994 | AS11: =AF11*4+2 -> -7.0452625 | AT11: =AH11 -> -0.30041232 | AU11: =SUM(AV11:BA11) -> -1.0608649 | AV11: =AI11 -> -0.51335586 | AW11: =AJ11 -> -0.31584038 | AX11: =AK11 -> -0.13962108 | AY11: =AL11 -> -0.03410106 | AZ11: =AM11 -> -0.016607341 | BA11: =AN11 -> -0.041339223 | BC11: =AR11 -> 39994 | BD11: =AT11 -> -0.30041232 | BE11: =AU11 -> -1.0608649
A12: 40086 | B12: -0.53090932 | C12: -0.26450707 | D12: -0.67212326 | E12: -1.5028278 | F12: 0.069033869 | G12: 1.1961043 | H12: -0.54411897 | I12: -0.18186777 | J12: 0.89049329 | K12: -0.56877654 | L12: -0.18360036 | M12: 0 | N12: 0 | O12: 0.48885426 | P12: 0 | Q12: -0.2019199 | R12: 0 | S12: 0 | T12: 0 | U12: 0 | V12: 0 | W12: 0 | X12: 0 | Y12: -0.43225273 | Z12: -0.32122089 | AA12: -0.17245864 | AB12: -0.050099817 | AC12: -0.0204331 | AD12: -0.08404302 | AE12: 0.12466498 | AF12: -2.9620085 | AH12: =K12 -> -0.56877654 | AI12: =Y12 -> -0.43225273 | AJ12: =Z12 -> -0.32122089 | AK12: =AA12 -> -0.17245864 | AL12: =AB12 -> -0.050099817 | AM12: =AC12 -> -0.0204331 | AN12: =AD12 -> -0.08404302 | AR12: =A12 -> 40086 | AS12: =AF12*4+2 -> -9.8480338 | AT12: =AH12 -> -0.56877654 | AU12: =SUM(AV12:BA12) -> -1.0805082 | AV12: =AI12 -> -0.43225273 | AW12: =AJ12 -> -0.32122089 | AX12: =AK12 -> -0.17245864 | AY12: =AL12 -> -0.050099817 | AZ12: =AM12 -> -0.0204331 | BA12: =AN12 -> -0.08404302 | BC12: =AR12 -> 40086 | BD12: =AT12 -> -0.56877654 | BE12: =AU12 -> -1.0805082
A13: 40178 | B13: -0.25242317 | C13: -0.21161538 | D13: -0.55513346 | E13: -1.5319895 | F13: 0.034934349 | G13: 0.99553621 | H13: -1.0349527 | I13: -0.1401452 | J13: 0.90746758 | K13: -1.1530786 | L13: -0.071269525 | M13: 0 | N13: 0 | O13: 0.29361464 | P13: 0 | Q13: -0.2238056 | R13: 0 | S13: 0 | T13: 0 | U13: 0 | V13: 0 | W13: 0 | X13: 0 | Y13: -0.35928238 | Z13: -0.28959157 | AA13: -0.22762518 | AB13: -0.069279424 | AC13: -0.028449793 | AD13: -0.14778106 | AE13: 0.12400264 | AF13: -3.9408671 | AH13: =K13 -> -1.1530786 | AI13: =Y13 -> -0.35928238 | AJ13: =Z13 -> -0.28959157 | AK13: =AA13 -> -0.22762518 | AL13: =AB13 -> -0.069279424 | AM13: =AC13 -> -0.028449793 | AN13: =AD13 -> -0.14778106 | AR13: =A13 -> 40178 | AS13: =AF13*4+2 -> -13.763469 | AT13: =AH13 -> -1.1530786 | AU13: =SUM(AV13:BA13) -> -1.1220094 | AV13: =AI13 -> -0.35928238 | AW13: =AJ13 -> -0.28959157 | AX13: =AK13 -> -0.22762518 | AY13: =AL13 -> -0.069279424 | AZ13: =AM13 -> -0.028449793 | BA13: =AN13 -> -0.14778106 | BC13: =AR13 -> 40178 | BD13: =AT13 -> -1.1530786 | BE13: =AU13 -> -1.1220094
... A132: 51043 | B132: -1.1485256 | C132: 0.00012590441 | D132: -0.042684349 | E132: -0.00047395337 | F132: 0.10831097 | G132: -0.17615887 | H132: 0.054636968 | I132: 0.15047017 | J132: 0.26718227 | K132: 0.0018162856 | L132: 0.37632535 | M132: 0 | N132: 0 | O132: 0.54539942 | P132: 0 | Q132: -0.20667783 | R132: 0 | S132: 0 | T132: 0 | U132: 0 | V132: 0 | W132: 0 | X132: 0 | Y132: -0.0016294185 | Z132: 0.0019674278 | AA132: -0.00054863095 | AB132: 0.00047969275 | AC132: -0.0015716835 | AD132: -0.0046451761 | AE132: 0.053433982 | AF132: -0.022767062 | AH132: =K132 -> 0.0018162856 | AI132: =Y132 -> -0.0016294185 | AJ132: =Z132 -> 0.0019674278 | AK132: =AA132 -> -0.00054863095 | AL132: =AB132 -> 0.00047969275 | AM132: =AC132 -> -0.0015716835 | AN132: =AD132 -> -0.0046451761 | AR132: =A132 -> 51043 | AS132: =AF132*4+2 -> 1.9089318 | AT132: =AH132 -> 0.0018162856 | AU132: =SUM(AV132:BA132) -> -0.0059477884 | AV132: =AI132 -> -0.0016294185 | AW132: =AJ132 -> 0.0019674278 | AX132: =AK132 -> -0.00054863095 | AY132: =AL132 -> 0.00047969275 | AZ132: =AM132 -> -0.0015716835 | BA132: =AN132 -> -0.0046451761 | BC132: =AR132 -> 51043 | BD132: =AT132 -> 0.0018162856 | BE132: =AU132 -> -0.0059477884

Sheet US_output_with_text_backup_1
A1: date | B1: g_sh | C1: b_liqtil_sh | D1: b_liqp_sh | E1: b_safetil_sh | F1: b_safep_sh | G1: mu_sh | H1: z_sh | I1: lambda_f_sh | J1: lambda_w_sh | K1: rm_sh | L1: sigma_omega_sh | M1: mu_e_sh | N1: gamma_sh | O1: pi_star_sh | P1: lr_sh | Q1: zp_sh | R1: tfp_sh | S1: gdpdef_sh | T1: corepce_sh | U1: gdp_sh | V1: gdi_sh | W1: BBB_sh | X1: AAA_sh | Y1: rm_shl1 | Z1: rm_shl2 | AA1: rm_shl3 | AB1: rm_shl4 | AC1: rm_shl5 | AD1: rm_shl6 | AE1: dettrend | AF1: detrendedMean | AH1: rm_sh | AI1: =Y1 -> rm_shl1 | AJ1: =Z1 -> rm_shl2 | AK1: =AA1 -> rm_shl3 | AL1: =AB1 -> rm_shl4 | AM1: =AC1 -> rm_shl5 | AN1: =AD1 -> rm_shl6 | AQ1: Plot | AR1: =A1 -> date | AS1: =AF1 -> detrendedMean | AT1: Monetary Policy | AU1: Fgsum | AV1: FG1 | AW1: FG2 | AX1: FG3 | AY1: FG4 | AZ1: FG5 | BA1: FG6 | BC1: date | BD1: rm_sh | BE1: Fgsum
A2: 39172 | B2: -1.0215877 | C2: 0.14738424 | D2: -0.044907453 | E2: 0.56515568 | F2: 0.33471877 | G2: 1.4053436 | H2: 0.54693072 | I2: -0.65393335 | J2: 0.64232717 | K2: 1.7750614 | L2: 1.2826525 | M2: 0 | N2: 0 | O2: 0.3278555 | P2: 0 | Q2: 0.11087454 | R2: 0 | S2: 0 | T2: 0 | U2: 0 | V2: 0 | W2: 0 | X2: 0 | Y2: 0 | Z2: 0 | AA2: 0 | AB2: 0 | AC2: 0 | AD2: 0 | AE2: 0.13099711 | AF2: 5.5488727 | AH2: =K2 -> 1.7750614 | AI2: =Y2 -> 0 | AJ2: =Z2 -> 0 | AK2: =AA2 -> 0 | AL2: =AB2 -> 0 | AM2: =AC2 -> 0 | AN2: =AD2 -> 0 | AR2: =A2 -> 39172 | AS2: =AF2*4+2 -> 24.195491 | AT2: =AH2 -> 1.7750614 | AU2: =SUM(AV2:BA2) -> 0 | AV2: =AI2 -> 0 | AW2: =AJ2 -> 0 | AX2: =AK2 -> 0 | AY2: =AL2 -> 0 | AZ2: =AM2 -> 0 | BA2: =AN2 -> 0 | BC2: =AR2 -> 39172 | BD2: =AT2 -> 1.7750614 | BE2: =AU2 -> 0
A3: 39263 | B3: -0.87702165 | C3: 0.14867978 | D3: -0.050839217 | E3: 0.5967583 | F3: 0.35694143 | G3: 1.4459149 | H3: 0.10615582 | I3: -0.67075329 | J3: 0.60096046 | K3: 1.5688765 | L3: 1.2418066 | M3: 0 | N3: 0 | O3: 0.33267031 | P3: 0 | Q3: 0.070231968 | R3: 0 | S3: 0 | T3: 0 | U3: 0 | V3: 0 | W3: 0 | X3: 0 | Y3: 0 | Z3: 0 | AA3: 0 | AB3: 0 | AC3: 0 | AD3: 0 | AE3: 0.13039267 | AF3: 5.0007746 | AH3: =K3 -> 1.5688765 | AI3: =Y3 -> 0 | AJ3: =Z3 -> 0 | AK3: =AA3 -> 0 | AL3: =AB3 -> 0 | AM3: =AC3 -> 0 | AN3: =AD3 -> 0 | AR3: =A3 -> 39263 | AS3: =AF3*4+2 -> 22.003098 | AT3: =AH3 -> 1.5688765 | AU3: =SUM(AV3:BA3) -> 0 | AV3: =AI3 -> 0 | AW3: =AJ3 -> 0 | AX3: =AK3 -> 0 | AY3: =AL3 -> 0 | AZ3: =AM3 -> 0 | BA3: =AN3 -> 0 | BC3: =AR3 -> 39263 | BD3: =AT3 -> 1.5688765 | BE3: =AU3 -> 0
A4: 39355 | B4: -1.040355 | C4: 0.13425109 | D4: -0.14587387 | E4: 0.69031317 | F4: 0.37191894 | G4: 1.4503632 | H4: 0.31183503 | I4: -0.6798581 | J4: 0.61019793 | K4: 1.5086958 | L4: 1.1510338 | M4: 0 | N4: 0 | O4: 0.37118543 | P4: 0 | Q4: 0.037371485 | R4: 0 | S4: 0 | T4: 0 | U4: 0 | V4: 0 | W4: 0 | X4: 0 | Y4: 0 | Z4: 0 | AA4: 0 | AB4: 0 | AC4: 0 | AD4: 0 | AE4: 0.12978091 | AF4: 4.9008599 | AH4: =K4 -> 1.5086958 | AI4: =Y4 -> 0 | AJ4: =Z4 -> 0 | AK4: =AA4 -> 0 | AL4: =AB4 -> 0 | AM4: =AC4 -> 0 | AN4: =AD4 -> 0 | AR4: =A4 -> 39355 | AS4: =AF4*4+2 -> 21.603439 | AT4: =AH4 -> 1.5086958 | AU4: =SUM(AV4:BA4) -> 0 | AV4: =AI4 -> 0 | AW4: =AJ4 -> 0 | AX4: =AK4 -> 0 | AY4: =AL4 -> 0 | AZ4: =AM4 -> 0 | BA4: =AN4 -> 0 | BC4: =AR4 -> 39355 | BD4: =AT4 -> 1.5086958 | BE4: =AU4 -> 0
A5: 39447 | B5: -0.99330901 | C5: 0.14258815 | D5: -0.26310356 | E5: 0.73768743 | F5: 0.36639612 | G5: 1.4317096 | H5: 0.21867959 | I5: -0.68920012 | J5: 0.66599438 | K5: 1.7274198 | L5: 1.0093212 | M5: 0 | N5: 0 | O5: 0.40724837 | P5: 0 | Q5: 0.016106972 | R5: 0 | S5: 0 | T5: 0 | U5: 0 | V5: 0 | W5: 0 | X5: 0 | Y5: 0 | Z5: 0 | AA5: 0 | AB5: 0 | AC5: 0 | AD5: 0 | AE5: 0.12916218 | AF5: 4.9067011 | AH5: =K5 -> 1.7274198 | AI5: =Y5 -> 0 | AJ5: =Z5 -> 0 | AK5: =AA5 -> 0 | AL5: =AB5 -> 0 | AM5: =AC5 -> 0 | AN5: =AD5 -> 0 | AR5: =A5 -> 39447 | AS5: =AF5*4+2 -> 21.626804 | AT5: =AH5 -> 1.7274198 | AU5: =SUM(AV5:BA5) -> 0 | AV5: =AI5 -> 0 | AW5: =AJ5 -> 0 | AX5: =AK5 -> 0 | AY5: =AL5 -> 0 | AZ5: =AM5 -> 0 | BA5: =AN5 -> 0 | BC5: =AR5 -> 39447 | BD5: =AT5 -> 1.7274198 | BE5: =AU5 -> 0
A6: 39538 | B6: -1.0476842 | C6: 0.03061779 | D6: -0.40243934 | E6: 0.39311962 | F6: 0.33629364 | G6: 1.42832 | H6: 0.27379584 | I6: -0.67868028 | J6: 0.70115772 | K6: 2.0053504 | L6: 0.85487701 | M6: 0 | N6: 0 | O6: 0.44493982 | P6: 0 | Q6: -0.019590161 | R6: 0 | S6: 0 | T6: 0 | U6: 0 | V6: 0 | W6: 0 | X6: 0 | Y6: 0 | Z6: 0 | AA6: 0 | AB6: 0 | AC6: 0 | AD6: 0 | AE6: 0.12853685 | AF6: 4.4486148 | AH6: =K6 -> 2.0053504 | AI6: =Y6 -> 0 | AJ6: =Z6 -> 0 | AK6: =AA6 -> 0 | AL6: =AB6 -> 0 | AM6: =AC6 -> 0 | AN6: =AD6 -> 0 | AR6: =A6 -> 39538 | AS6: =AF6*4+2 -> 19.794459 | AT6: =AH6 -> 2.0053504 | AU6: =SUM(AV6:BA6) -> 0 | AV6: =AI6 -> 0 | AW6: =AJ6 -> 0 | AX6: =AK6 -> 0 | AY6: =AL6 -> 0 | AZ6: =AM6 -> 0 | BA6: =AN6 -> 0 | BC6: =AR6 -> 39538 | BD6: =AT6 -> 2.0053504 | BE6: =AU6 -> 0
A7: 39629 | B7: -1.1086433 | C7: -0.033609602 | D7: -0.44750789 | E7: 0.09339584 | F7: 0.34011857 | G7: 1.4242313 | H7: 0.099730651 | I7: -0.64918611 | J7: 0.69311266 | K7: 2.3003353 | L7: 0.71023288 | M7: 0 | N7: 0 | O7: 0.48647302 | P7: 0 | Q7: -0.047607001 | R7: 0 | S7: 0 | T7: 0 | U7: 0 | V7: 0 | W7: 0 | X7: 0 | Y7: 0 | Z7: 0 | AA7: 0 | AB7: 0 | AC7: 0 | AD7: 0 | AE7: 0.12790526 | AF7: 3.9889816 | AH7: =K7 -> 2.3003353 | AI7: =Y7 -> 0 | AJ7: =Z7 -> 0 | AK7: =AA7 -> 0 | AL7: =AB7 -> 0 | AM7: =AC7 -> 0 | AN7: =AD7 -> 0 | AR7: =A7 -> 39629 | AS7: =AF7*4+2 -> 17.955926 | AT7: =AH7 -> 2.3003353 | AU7: =SUM(AV7:BA7) -> 0 | AV7: =AI7 -> 0 | AW7: =AJ7 -> 0 | AX7: =AK7 -> 0 | AY7: =AL7 -> 0 | AZ7: =AM7 -> 0 | BA7: =AN7 -> 0 | BC7: =AR7 -> 39629 | BD7: =AT7 -> 2.3003353 | BE7: =AU7 -> 0
A8: 39721 | B8: -0.80373451 | C8: -0.20400532 | D8: -0.52579161 | E8: -0.37809506 | F8: 0.32715602 | G8: 1.4371073 | H8: 0.049769223 | I8: -0.6241057 | J8: 0.72601851 | K8: 1.9637541 | L8: 0.57993927 | M8: 0 | N8: 0 | O8: 0.49767707 | P8: 0 | Q8: -0.074978682 | R8: 0 | S8: 0 | T8: 0 | U8: 0 | V8: 0 | W8: 0 | X8: 0 | Y8: 0 | Z8: 0 | AA8: 0 | AB8: 0 | AC8: 0 | AD8: 0 | AE8: 0.12726775 | AF8: 3.0979785 | AH8: =K8 -> 1.9637541 | AI8: =Y8 -> 0 | AJ8: =Z8 -> 0 | AK8: =AA8 -> 0 | AL8: =AB8 -> 0 | AM8: =AC8 -> 0 | AN8: =AD8 -> 0 | AR8: =A8 -> 39721 | AS8: =AF8*4+2 -> 14.391914 | AT8: =AH8 -> 1.9637541 | AU8: =SUM(AV8:BA8) -> 0 | AV8: =AI8 -> 0 | AW8: =AJ8 -> 0 | AX8: =AK8 -> 0 | AY8: =AL8 -> 0 | AZ8: =AM8 -> 0 | BA8: =AN8 -> 0 | BC8: =AR8 -> 39721 | BD8: =AT8 -> 1.9637541 | BE8: =AU8 -> 0
A9: 39813 | B9: -0.21677727 | C9: -0.56638658 | D9: -0.87656555 | E9: -1.0760328 | F9: 0.163132 | G9: 1.567453 | H9: 0.77708187 | I9: -0.52720457 | J9: 0.77689645 | K9: 1.3356925 | L9: 0.32530383 | M9: 0 | N9: 0 | O9: 0.56267499 | P9: 0 | Q9: -0.12285996 | R9: 0 | S9: 0 | T9: 0 | U9: 0 | V9: 0 | W9: 0 | X9: 0 | Y9: -0.18334085 | Z9: -0.085809019 | AA9: -0.014995051 | AB9: -0.0025678522 | AC9: -0.0010749068 | AD9: -0.0015146036 | AE9: 0.12662465 | AF9: 1.9597303 | AH9: =K9 -> 1.3356925 | AI9: =Y9 -> -0.18334085 | AJ9: =Z9 -> -0.085809019 | AK9: =AA9 -> -0.014995051 | AL9: =AB9 -> -0.0025678522 | AM9: =AC9 -> -0.0010749068 | AN9: =AD9 -> -0.0015146036 | AR9: =A9 -> 39813 | AS9: =AF9*4+2 -> 9.8389213 | AT9: =AH9 -> 1.3356925 | AU9: =SUM(AV9:BA9) -> -0.28930228 | AV9: =AI9 -> -0.18334085 | AW9: =AJ9 -> -0.085809019 | AX9: =AK9 -> -0.014995051 | AY9: =AL9 -> -0.0025678522 | AZ9: =AM9 -> -0.0010749068 | BA9: =AN9 -> -0.0015146036 | BC9: =AR9 -> 39813 | BD9: =AT9 -> 1.3356925 | BE9: =AU9 -> -0.28930228
A10: 39903 | B10: -0.13539004 | C10: -0.65246513 | D10: -0.91826335 | E10: -1.4441778 | F10: 0.115455 | G10: 1.5230468 | H10: 0.27896396 | I10: -0.40325188 | J10: 0.66681609 | K10: 0.39863999 | L10: 0.0012907793 | M10: 0 | N10: 0 | O10: 0.65980691 | P10: 0 | Q10: -0.15244255 | R10: 0 | S10: 0 | T10: 0 | U10: 0 | V10: 0 | W10: 0 | X10: 0 | Y10: -0.40182322 | Z10: -0.21133372 | AA10: -0.064564658 | AB10: -0.0076746478 | AC10: -0.0097111472 | AD10: -0.013463276 | AE10: 0.12597629 | AF10: -0.64456556 | AH10: =K10 -> 0.39863999 | AI10: =Y10 -> -0.40182322 | AJ10: =Z10 -> -0.21133372 | AK10: =AA10 -> -0.064564658 | AL10: =AB10 -> -0.0076746478 | AM10: =AC10 -> -0.0097111472 | AN10: =AD10 -> -0.013463276 | AR10: =A10 -> 39903 | AS10: =AF10*4+2 -> -0.57826224 | AT10: =AH10 -> 0.39863999 | AU10: =SUM(AV10:BA10) -> -0.70857067 | AV10: =AI10 -> -0.40182322 | AW10: =AJ10 -> -0.21133372 | AX10: =AK10 -> -0.064564658 | AY10: =AL10 -> -0.0076746478 | AZ10: =AM10 -> -0.0097111472 | BA10: =AN10 -> -0.013463276 | BC10: =AR10 -> 39903 | BD10: =AT10 -> 0.39863999 | BE10: =AU10 -> -0.70857067
A11: 39994 | B11: -0.073128195 | C11: -0.59127453 | D11: -0.82556116 | E11: -1.5731642 | F11: 0.099746456 | G11: 1.4374342 | H11: -0.35522693 | I11: -0.28293943 | J11: 0.84351191 | K11: -0.30041232 | L11: -0.18272965 | M11: 0 | N11: 0 | O11: 0.6458429 | P11: 0 | Q11: -0.16787271 | R11: 0 | S11: 0 | T11: 0 | U11: 0 | V11: 0 | W11: 0 | X11: 0 | Y11: -0.51335586 | Z11: -0.31584038 | AA11: -0.13962108 | AB11: -0.03410106 | AC11: -0.016607341 | AD11: -0.041339223 | AE11: 0.12532296 | AF11: -2.2613156 | AH11: =K11 -> -0.30041232 | AI11: =Y11 -> -0.51335586 | AJ11: =Z11 -> -0.31584038 | AK11: =AA11 -> -0.13962108 | AL11: =AB11 -> -0.03410106 | AM11: =AC11 -> -0.016607341 | AN11: =AD11 -> -0.041339223 | AR11: =A11 -> 39994 | AS11: =AF11*4+2 -> -7.0452625 | AT11: =AH11 -> -0.30041232 | AU11: =SUM(AV11:BA11) -> -1.0608649 | AV11: =AI11 -> -0.51335586 | AW11: =AJ11 -> -0.31584038 | AX11: =AK11 -> -0.13962108 | AY11: =AL11 -> -0.03410106 | AZ11: =AM11 -> -0.016607341 | BA11: =AN11 -> -0.041339223 | BC11: =AR11 -> 39994 | BD11: =AT11 -> -0.30041232 | BE11: =AU11 -> -1.0608649
A12: 40086 | B12: -0.53090932 | C12: -0.26450707 | D12: -0.67212326 | E12: -1.5028278 | F12: 0.069033869 | G12: 1.1961043 | H12: -0.54411897 | I12: -0.18186777 | J12: 0.89049329 | K12: -0.56877654 | L12: -0.18360036 | M12: 0 | N12: 0 | O12: 0.48885426 | P12: 0 | Q12: -0.2019199 | R12: 0 | S12: 0 | T12: 0 | U12: 0 | V12: 0 | W12: 0 | X12: 0 | Y12: -0.43225273 | Z12: -0.32122089 | AA12: -0.17245864 | AB12: -0.050099817 | AC12: -0.0204331 | AD12: -0.08404302 | AE12: 0.12466498 | AF12: -2.9620085 | AH12: =K12 -> -0.56877654 | AI12: =Y12 -> -0.43225273 | AJ12: =Z12 -> -0.32122089 | AK12: =AA12 -> -0.17245864 | AL12: =AB12 -> -0.050099817 | AM12: =AC12 -> -0.0204331 | AN12: =AD12 -> -0.08404302 | AR12: =A12 -> 40086 | AS12: =AF12*4+2 -> -9.8480338 | AT12: =AH12 -> -0.56877654 | AU12: =SUM(AV12:BA12) -> -1.0805082 | AV12: =AI12 -> -0.43225273 | AW12: =AJ12 -> -0.32122089 | AX12: =AK12 -> -0.17245864 | AY12: =AL12 -> -0.050099817 | AZ12: =AM12 -> -0.0204331 | BA12: =AN12 -> -0.08404302 | BC12: =AR12 -> 40086 | BD12: =AT12 -> -0.56877654 | BE12: =AU12 -> -1.0805082
A13: 40178 | B13: -0.25242317 | C13: -0.21161538 | D13: -0.55513346 | E13: -1.5319895 | F13: 0.034934349 | G13: 0.99553621 | H13: -1.0349527 | I13: -0.1401452 | J13: 0.90746758 | K13: -1.1530786 | L13: -0.071269525 | M13: 0 | N13: 0 | O13: 0.29361464 | P13: 0 | Q13: -0.2238056 | R13: 0 | S13: 0 | T13: 0 | U13: 0 | V13: 0 | W13: 0 | X13: 0 | Y13: -0.35928238 | Z13: -0.28959157 | AA13: -0.22762518 | AB13: -0.069279424 | AC13: -0.028449793 | AD13: -0.14778106 | AE13: 0.12400264 | AF13: -3.9408671 | AH13: =K13 -> -1.1530786 | AI13: =Y13 -> -0.35928238 | AJ13: =Z13 -> -0.28959157 | AK13: =AA13 -> -0.22762518 | AL13: =AB13 -> -0.069279424 | AM13: =AC13 -> -0.028449793 | AN13: =AD13 -> -0.14778106 | AR13: =A13 -> 40178 | AS13: =AF13*4+2 -> -13.763469 | AT13: =AH13 -> -1.1530786 | AU13: =SUM(AV13:BA13) -> -1.1220094 | AV13: =AI13 -> -0.35928238 | AW13: =AJ13 -> -0.28959157 | AX13: =AK13 -> -0.22762518 | AY13: =AL13 -> -0.069279424 | AZ13: =AM13 -> -0.028449793 | BA13: =AN13 -> -0.14778106 | BC13: =AR13 -> 40178 | BD13: =AT13 -> -1.1530786 | BE13: =AU13 -> -1.1220094
... A132: 51043 | B132: -1.1485256 | C132: 0.00012590441 | D132: -0.042684349 | E132: -0.00047395337 | F132: 0.10831097 | G132: -0.17615887 | H132: 0.054636968 | I132: 0.15047017 | J132: 0.26718227 | K132: 0.0018162856 | L132: 0.37632535 | M132: 0 | N132: 0 | O132: 0.54539942 | P132: 0 | Q132: -0.20667783 | R132: 0 | S132: 0 | T132: 0 | U132: 0 | V132: 0 | W132: 0 | X132: 0 | Y132: -0.0016294185 | Z132: 0.0019674278 | AA132: -0.00054863095 | AB132: 0.00047969275 | AC132: -0.0015716835 | AD132: -0.0046451761 | AE132: 0.053433982 | AF132: -0.022767062 | AH132: =K132 -> 0.0018162856 | AI132: =Y132 -> -0.0016294185 | AJ132: =Z132 -> 0.0019674278 | AK132: =AA132 -> -0.00054863095 | AL132: =AB132 -> 0.00047969275 | AM132: =AC132 -> -0.0015716835 | AN132: =AD132 -> -0.0046451761 | AR132: =A132 -> 51043 | AS132: =AF132*4+2 -> 1.9089318 | AT132: =AH132 -> 0.0018162856 | AU132: =SUM(AV132:BA132) -> -0.0059477884 | AV132: =AI132 -> -0.0016294185 | AW132: =AJ132 -> 0.0019674278 | AX132: =AK132 -> -0.00054863095 | AY132: =AL132 -> 0.00047969275 | AZ132: =AM132 -> -0.0015716835 | BA132: =AN132 -> -0.0046451761 | BC132: =AR132 -> 51043 | BD132: =AT132 -> 0.0018162856 | BE132: =AU132 -> -0.0059477884

Sheet US_core_obs_with_textbckup
A1: date | B1: g_sh | C1: b_liqtil_sh | D1: b_liqp_sh | E1: b_safetil_sh | F1: b_safep_sh | G1: mu_sh | H1: z_sh | I1: lambda_f_sh | J1: lambda_w_sh | K1: rm_sh | L1: sigma_omega_sh | M1: mu_e_sh | N1: gamma_sh | O1: pi_star_sh | P1: lr_sh | Q1: zp_sh | R1: tfp_sh | S1: gdpdef_sh | T1: corepce_sh | U1: gdp_sh | V1: gdi_sh | W1: BBB_sh | X1: AAA_sh | Y1: rm_shl1 | Z1: rm_shl2 | AA1: rm_shl3 | AB1: rm_shl4 | AC1: rm_shl5 | AD1: rm_shl6 | AE1: dettrend | AF1: detrendedMean | AH1: rm_sh | AI1: =Y1 -> rm_shl1 | AJ1: =Z1 -> rm_shl2 | AK1: =AA1 -> rm_shl3 | AL1: =AB1 -> rm_shl4 | AM1: =AC1 -> rm_shl5 | AN1: =AD1 -> rm_shl6 | AQ1: Plot | AR1: =A1 -> date | AS1: Monetary Policy | AT1: FG1 | AU1: FG2 | AV1: FG3 | AW1: FG4 | AX1: FG5 | AY1: FG6 | BA1: date | BB1: rm_sh | BC1: Fgsum
A2: 39172 | B2: -0.04656955 | C2: 6.6857837e-05 | D2: -0.12107115 | E2: 0.0055571623 | F2: 0.29566638 | G2: -0.097339567 | H2: 0.242653 | I2: 1.0199768 | J2: -0.95012393 | K2: 0.031410275 | L2: -0.11629573 | M2: 0 | N2: 0 | O2: 0.62102095 | P2: 0 | Q2: -0.028873853 | R2: 0 | S2: 0 | T2: 0.17412573 | U2: 0 | V2: 0 | W2: 0 | X2: 0 | Y2: 0 | Z2: 0 | AA2: 0 | AB2: 0 | AC2: 0 | AD2: 0 | AE2: -0.27154927 | AF2: 0.76346908 | AH2: =K2 -> 0.031410275 | AI2: =Y2 -> 0 | AJ2: =Z2 -> 0 | AK2: =AA2 -> 0 | AL2: =AB2 -> 0 | AM2: =AC2 -> 0 | AN2: =AD2 -> 0 | AR2: =A2 -> 39172 | AS2: 0 | AT2: =AI2 -> 0 | AU2: =AJ2 -> 0 | AV2: =AK2 -> 0 | AW2: =AL2 -> 0 | AX2: =AM2 -> 0 | AY2: =AN2 -> 0 | BA2: =AR2 -> 39172 | BB2: =AS2 -> 0 | BC2: =#REF! -> #REF!
A3: 39263 | B3: -0.041373765 | C3: -0.00024595173 | D3: -0.12421857 | E3: 0.0044496944 | F3: 0.30820019 | G3: -0.10557509 | H3: 0.19524989 | I3: 0.50023836 | J3: -1.0905131 | K3: 0.028022272 | L3: -0.11610905 | M3: 0 | N3: 0 | O3: 0.64479076 | P3: 0 | Q3: 0.07027945 | R3: 0 | S3: 0 | T3: -0.32870966 | U3: 0 | V3: 0 | W3: 0 | X3: 0 | Y3: 0 | Z3: 0 | AA3: 0 | AB3: 0 | AC3: 0 | AD3: 0 | AE3: -0.26890542 | AF3: -0.34173686 | AH3: =K3 -> 0.028022272 | AI3: =Y3 -> 0 | AJ3: =Z3 -> 0 | AK3: =AA3 -> 0 | AL3: =AB3 -> 0 | AM3: =AC3 -> 0 | AN3: =AD3 -> 0 | AR3: =A3 -> 39263 | AS3: 0 | AT3: =AI3 -> 0 | AU3: =AJ3 -> 0 | AV3: =AK3 -> 0 | AW3: =AL3 -> 0 | AX3: =AM3 -> 0 | AY3: =AN3 -> 0 | BA3: =AR3 -> 39263 | BB3: =AS3 -> 0 | BC3: =#REF! -> #REF!
A4: 39355 | B4: -0.042698816 | C4: -0.00054061997 | D4: -0.17511163 | E4: 0.0035197522 | F4: 0.31268306 | G4: -0.098445474 | H4: 0.22426866 | I4: 0.56066465 | J4: -1.2109319 | K4: 0.028694151 | L4: -0.10308787 | M4: 0 | N4: 0 | O4: 0.68905081 | P4: 0 | Q4: 0.1263565 | R4: 0 | S4: 0 | T4: -0.075869274 | U4: 0 | V4: 0 | W4: 0 | X4: 0 | Y4: 0 | Z4: 0 | AA4: 0 | AB4: 0 | AC4: 0 | AD4: 0 | AE4: -0.26628403 | AF4: -0.041333904 | AH4: =K4 -> 0.028694151 | AI4: =Y4 -> 0 | AJ4: =Z4 -> 0 | AK4: =AA4 -> 0 | AL4: =AB4 -> 0 | AM4: =AC4 -> 0 | AN4: =AD4 -> 0 | AR4: =A4 -> 39355 | AS4: 0 | AT4: =AI4 -> 0 | AU4: =AJ4 -> 0 | AV4: =AK4 -> 0 | AW4: =AL4 -> 0 | AX4: =AM4 -> 0 | AY4: =AN4 -> 0 | BA4: =AR4 -> 39355 | BB4: =AS4 -> 0 | BC4: =#REF! -> #REF!
A5: 39447 | B5: -0.041509973 | C5: -0.00084051646 | D5: -0.22632931 | E5: 0.00245953 | F5: 0.30585847 | G5: -0.089583103 | H5: 0.22615008 | I5: 0.71979624 | J5: -1.1731183 | K5: 0.033606282 | L5: -0.085577213 | M5: 0 | N5: 0 | O5: 0.71164067 | P5: 0 | Q5: 0.11229443 | R5: 0 | S5: 0 | T5: 0.53685152 | U5: 0 | V5: 0 | W5: 0 | X5: 0 | Y5: 0 | Z5: 0 | AA5: 0 | AB5: 0 | AC5: 0 | AD5: 0 | AE5: -0.26368501 | AF5: 0.77117619 | AH5: =K5 -> 0.033606282 | AI5: =Y5 -> 0 | AJ5: =Z5 -> 0 | AK5: =AA5 -> 0 | AL5: =AB5 -> 0 | AM5: =AC5 -> 0 | AN5: =AD5 -> 0 | AR5: =A5 -> 39447 | AS5: 0 | AT5: =AI5 -> 0 | AU5: =AJ5 -> 0 | AV5: =AK5 -> 0 | AW5: =AL5 -> 0 | AX5: =AM5 -> 0 | AY5: =AN5 -> 0 | BA5: =AR5 -> 39447 | BB5: =AS5 -> 0 | BC5: =#REF! -> #REF!
A6: 39538 | B6: -0.042159162 | C6: -0.00093182491 | D6: -0.28492927 | E6: 0.00057296347 | F6: 0.28801431 | G6: -0.092070004 | H6: 0.24492393 | I6: 0.26378547 | J6: -1.1318102 | K6: 0.038135505 | L6: -0.072334971 | M6: 0 | N6: 0 | O6: 0.73156921 | P6: 0 | Q6: 0.22897399 | R6: 0 | S6: 0 | T6: 0.21638093 | U6: 0 | V6: 0 | W6: 0 | X6: 0 | Y6: 0 | Z6: 0 | AA6: 0 | AB6: 0 | AC6: 0 | AD6: 0 | AE6: -0.2611083 | AF6: 0.11790821 | AH6: =K6 -> 0.038135505 | AI6: =Y6 -> 0 | AJ6: =Z6 -> 0 | AK6: =AA6 -> 0 | AL6: =AB6 -> 0 | AM6: =AC6 -> 0 | AN6: =AD6 -> 0 | AR6: =A6 -> 39538 | AS6: 0 | AT6: =AI6 -> 0 | AU6: =AJ6 -> 0 | AV6: =AK6 -> 0 | AW6: =AL6 -> 0 | AX6: =AM6 -> 0 | AY6: =AN6 -> 0 | BA6: =AR6 -> 39538 | BB6: =AS6 -> 0 | BC6: =#REF! -> #REF!
A7: 39629 | B7: -0.04379341 | C7: -0.00091690978 | D7: -0.28711526 | E7: -0.00069982559 | F7: 0.29321687 | G7: -0.09253843 | H7: 0.22624034 | I7: 0.12500858 | J7: -1.2341142 | K7: 0.042370011 | L7: -0.063030173 | M7: 0 | N7: 0 | O7: 0.7532105 | P7: 0 | Q7: 0.29368416 | R7: 0 | S7: 0 | T7: -0.065172848 | U7: 0 | V7: 0 | W7: 0 | X7: 0 | Y7: 0 | Z7: 0 | AA7: 0 | AB7: 0 | AC7: 0 | AD7: 0 | AE7: -0.2585538 | AF7: -0.33077165 | AH7: =K7 -> 0.042370011 | AI7: =Y7 -> 0 | AJ7: =Z7 -> 0 | AK7: =AA7 -> 0 | AL7: =AB7 -> 0 | AM7: =AC7 -> 0 | AN7: =AD7 -> 0 | AR7: =A7 -> 39629 | AS7: 0 | AT7: =AI7 -> 0 | AU7: =AJ7 -> 0 | AV7: =AK7 -> 0 | AW7: =AL7 -> 0 | AX7: =AM7 -> 0 | AY7: =AN7 -> 0 | BA7: =AR7 -> 39629 | BB7: =AS7 -> 0 | BC7: =#REF! -> #REF!
A8: 39721 | B8: -0.036786898 | C8: -0.00057270423 | D8: -0.3202672 | E8: -0.001910312 | F8: 0.28518735 | G8: -0.098640354 | H8: 0.2119083 | I8: 0.48032411 | J8: -1.260181 | K8: 0.035855439 | L8: -0.055106821 | M8: 0 | N8: 0 | O8: 0.73492454 | P8: 0 | Q8: 0.35519731 | R8: 0 | S8: 0 | T8: -0.023351863 | U8: 0 | V8: 0 | W8: 0 | X8: 0 | Y8: 0 | Z8: 0 | AA8: 0 | AB8: 0 | AC8: 0 | AD8: 0 | AE8: -0.25602142 | AF8: 0.037276857 | AH8: =K8 -> 0.035855439 | AI8: =Y8 -> 0 | AJ8: =Z8 -> 0 | AK8: =AA8 -> 0 | AL8: =AB8 -> 0 | AM8: =AC8 -> 0 | AN8: =AD8 -> 0 | AR8: =A8 -> 39721 | AS8: =AH8-$AH$8 -> 0 | AT8: =AI8 -> 0 | AU8: =AJ8 -> 0 | AV8: =AK8 -> 0 | AW8: =AL8 -> 0 | AX8: =AM8 -> 0 | AY8: =AN8 -> 0 | BA8: =AR8 -> 39721 | BB8: =AS8 -> 0 | BC8: =#REF! -> #REF!
A9: 39813 | B9: -0.019051908 | C9: 0.00039391664 | D9: -0.50484687 | E9: -0.0029901249 | F9: 0.19330924 | G9: -0.14313249 | H9: 0.34908351 | I9: -1.1794005 | J9: -1.1872455 | K9: 0.027346268 | L9: -0.019735076 | M9: 0 | N9: 0 | O9: 0.79272106 | P9: 0 | Q9: 0.5725535 | R9: 0 | S9: 0 | T9: -0.90423628 | U9: 0 | V9: 0 | W9: 0 | X9: 0 | Y9: -0.0046602345 | Z9: -0.0032534387 | AA9: -0.0008489732 | AB9: -0.00022071955 | AC9: -0.00014406503 | AD9: -0.00032751503 | AE9: -0.25351107 | AF9: -2.3333306 | AH9: =K9 -> 0.027346268 | AI9: =Y9 -> -0.0046602345 | AJ9: =Z9 -> -0.0032534387 | AK9: =AA9 -> -0.0008489732 | AL9: =AB9 -> -0.00022071955 | AM9: =AC9 -> -0.00014406503 | AN9: =AD9 -> -0.00032751503 | AR9: =A9 -> 39813 | AS9: =AH9-$AH$8 -> -0.0085091715 | AT9: =AI9 -> -0.0046602345 | AU9: =AJ9 -> -0.0032534387 | AV9: =AK9 -> -0.0008489732 | AW9: =AL9 -> -0.00022071955 | AX9: =AM9 -> -0.00014406503 | AY9: =AN9 -> -0.00032751503 | BA9: =AR9 -> 39813 | BB9: =AS9 -> -0.0085091715 | BC9: =#REF! -> #REF!
A10: 39903 | B10: -0.0088838781 | C10: 0.0015216111 | D10: -0.48045713 | E10: -0.0024772033 | F10: 0.18735855 | G10: -0.1021781 | H10: 0.32785381 | I10: -0.83317088 | J10: -1.6534315 | K10: 0.015650166 | L10: 0.014512646 | M10: 0 | N10: 0 | O10: 0.8701949 | P10: 0 | Q10: 0.62656666 | R10: 0 | S10: 0 | T10: -0.66787461 | U10: 0 | V10: 0 | W10: 0 | X10: 0 | Y10: -0.0076239905 | Z10: -0.0060776716 | AA10: -0.0031169771 | AB10: -0.00051108152 | AC10: -0.0011992944 | AD10: -0.0026694055 | AE10: -0.25102265 | AF10: -2.0246819 | AH10: =K10 -> 0.015650166 | AI10: =Y10 -> -0.0076239905 | AJ10: =Z10 -> -0.0060776716 | AK10: =AA10 -> -0.0031169771 | AL10: =AB10 -> -0.00051108152 | AM10: =AC10 -> -0.0011992944 | AN10: =AD10 -> -0.0026694055 | AR10: =A10 -> 39903 | AS10: =AH10-$AH$8 -> -0.020205274 | AT10: =AI10 -> -0.0076239905 | AU10: =AJ10 -> -0.0060776716 | AV10: =AK10 -> -0.0031169771 | AW10: =AL10 -> -0.00051108152 | AX10: =AM10 -> -0.0011992944 | AY10: =AN10 -> -0.0026694055 | BA10: =AR10 -> 39903 | BB10: =AS10 -> -0.020205274 | BC10: =#REF! -> #REF!
A11: 39994 | B11: -0.0016392847 | C11: 0.0026571168 | D11: -0.41530551 | E11: -0.0010258689 | F11: 0.18768215 | G11: -0.075216881 | H11: 0.20805356 | I11: -0.45099997 | J11: -1.3750451 | K11: 0.0098796611 | L11: 0.010574395 | M11: 0 | N11: 0 | O11: 0.7945309 | P11: 0 | Q11: 0.54204045 | R11: 0 | S11: 0 | T11: 0.42136932 | U11: 0 | V11: 0 | W11: 0 | X11: 0 | Y11: -0.0077225494 | Z11: -0.0064522642 | AA11: -0.0053651544 | AB11: -0.0024223879 | AC11: -0.0012541237 | AD11: -0.0066621159 | AE11: -0.24855607 | AF11: -0.44640572 | AH11: =K11 -> 0.0098796611 | AI11: =Y11 -> -0.0077225494 | AJ11: =Z11 -> -0.0064522642 | AK11: =AA11 -> -0.0053651544 | AL11: =AB11 -> -0.0024223879 | AM11: =AC11 -> -0.0012541237 | AN11: =AD11 -> -0.0066621159 | AR11: =A11 -> 39994 | AS11: =AH11-$AH$8 -> -0.025975778 | AT11: =AI11 -> -0.0077225494 | AU11: =AJ11 -> -0.0064522642 | AV11: =AK11 -> -0.0053651544 | AW11: =AL11 -> -0.0024223879 | AX11: =AM11 -> -0.0012541237 | AY11: =AN11 -> -0.0066621159 | BA11: =AR11 -> 39994 | BB11: =AS11 -> -0.025975778 | BC11: =#REF! -> #REF!
A12: 40086 | B12: -0.0088587798 | C12: 0.0032704207 | D12: -0.34119341 | E12: 0.00094675771 | F12: 0.17267413 | G12: -0.0073648259 | H12: 0.11138429 | I12: -0.32898704 | J12: -1.2012606 | K12: 0.010727173 | L12: -0.01288965 | M12: 0 | N12: 0 | O12: 0.58534165 | P12: 0 | Q12: 0.57832902 | R12: 0 | S12: 0 | T12: 0.1372099 | U12: 0 | V12: 0 | W12: 0 | X12: 0 | Y12: -0.0044141949 | Z12: -0.0040548158 | AA12: -0.0037010475 | AB12: -0.0021091098 | AC12: -0.00070098011 | AD12: -0.010372398 | AE12: -0.24611123 | AF12: -0.59458616 | AH12: =K12 -> 0.010727173 | AI12: =Y12 -> -0.0044141949 | AJ12: =Z12 -> -0.0040548158 | AK12: =AA12 -> -0.0037010475 | AL12: =AB12 -> -0.0021091098 | AM12: =AC12 -> -0.00070098011 | AN12: =AD12 -> -0.010372398 | AR12: =A12 -> 40086 | AS12: =AH12-$AH$8 -> -0.025128267 | AT12: =AI12 -> -0.0044141949 | AU12: =AJ12 -> -0.0040548158 | AV12: =AK12 -> -0.0037010475 | AW12: =AL12 -> -0.0021091098 | AX12: =AM12 -> -0.00070098011 | AY12: =AN12 -> -0.010372398 | BA12: =AR12 -> 40086 | BB12: =AS12 -> -0.025128267 | BC12: =#REF! -> #REF!
A13: 40178 | B13: -0.0041259572 | C13: 0.0037769523 | D13: -0.30060972 | E13: 0.0025164451 | F13: 0.15618437 | G13: 0.013478816 | H13: -0.048747454 | I13: 0.56010376 | J13: -1.1290423 | K13: 0.0043932254 | L13: -0.033449991 | M13: 0 | N13: 0 | O13: 0.39894746 | P13: 0 | Q13: 0.49842621 | R13: 0 | S13: 0 | T13: 0.64801933 | U13: 0 | V13: 0 | W13: 0 | X13: 0 | Y13: -0.0038018908 | Z13: -0.0031772213 | AA13: -0.0046047315 | AB13: -0.0020995461 | AC13: -0.00090141919 | AD13: -0.014426647 | AE13: -0.24368801 | AF13: 0.49515122 | AH13: =K13 -> 0.0043932254 | AI13: =Y13 -> -0.0038018908 | AJ13: =Z13 -> -0.0031772213 | AK13: =AA13 -> -0.0046047315 | AL13: =AB13 -> -0.0020995461 | AM13: =AC13 -> -0.00090141919 | AN13: =AD13 -> -0.014426647 | AR13: =A13 -> 40178 | AS13: =AH13-$AH$8 -> -0.031462214 | AT13: =AI13 -> -0.0038018908 | AU13: =AJ13 -> -0.0031772213 | AV13: =AK13 -> -0.0046047315 | AW13: =AL13 -> -0.0020995461 | AX13: =AM13 -> -0.00090141919 | AY13: =AN13 -> -0.014426647 | BA13: =AR13 -> 40178 | BB13: =AS13 -> -0.031462214 | BC13: =#REF! -> #REF!
A14: 40268 | B14: -0.0043879314 | C14: 0.0039505321 | D14: -0.26403258 | E14: 0.0041664706 | F14: 0.13382673 | G14: 0.072315031 | H14: -0.097699544 | I14: 0.15371623 | J14: -1.3608881 | K14: 0.0030041083 | L14: -0.027865556 | M14: 0 | N14: 0 | O14: 0.36324942 | P14: 0 | Q14: 0.68184658 | R14: 0 | S14: 0 | T14: -0.015524865 | U14: 0 | V14: 0 | W14: 0 | X14: 0 | Y14: -0.0025247759 | Z14: -0.0011392963 | AA14: -0.0026311512 | AB14: -0.00090622969 | AC14: 0.00042852871 | AD14: -0.018364044 | AE14: -0.24128632 | AF14: -0.64475468 | AH14: =K14 -> 0.0030041083 | AI14: =Y14 -> -0.0025247759 | AJ14: =Z14 -> -0.0011392963 | AK14: =AA14 -> -0.0026311512 | AL14: =AB14 -> -0.00090622969 | AM14: =AC14 -> 0.00042852871 | AN14: =AD14 -> -0.018364044 | AR14: =A14 -> 40268 | AS14: =AH14-$AH$8 -> -0.032851331 | AT14: =AI14 -> -0.0025247759 | AU14: =AJ14 -> -0.0011392963 | AV14: =AK14 -> -0.0026311512 | AW14: =AL14 -> -0.00090622969 | AX14: =AM14 -> 0.00042852871 | AY14: =AN14 -> -0.018364044 | BA14: =AR14 -> 40268 | BB14: =AS14 -> -0.032851331 | BC14: =#REF! -> #REF!
A15: 40359 | B15: -0.0047370661 | C15: 0.0036702239 | D15: -0.30212164 | E15: 0.0060516929 | F15: 0.053154696 | G15: 0.091914005 | H15: -0.10735471 | I15: -0.026876573 | J15: -1.3483041 | K15: 0.007235275 | L15: -0.039850391 | M15: 0 | N15: 0 | O15: 0.23017405 | P15: 0 | Q15: 0.93404127 | R15: 0 | S15: 0 | T15: -0.16166955 | U15: 0 | V15: 0 | W15: 0 | X15: 0 | Y15: 0.00089646601 | Z15: 0.0018511946 | AA15: 0.0017305419 | AB15: 0.0031244631 | AC15: 0.0055460947 | AD15: -0.018716254 | AE15: -0.23890604 | AF15: -0.93824378 | AH15: =K15 -> 0.007235275 | AI15: =Y15 -> 0.00089646601 | AJ15: =Z15 -> 0.0018511946 | AK15: =AA15 -> 0.0017305419 | AL15: =AB15 -> 0.0031244631 | AM15: =AC15 -> 0.0055460947 | AN15: =AD15 -> -0.018716254 | AR15: =A15 -> 40359 | AS15: =AH15-$AH$8 -> -0.028620164 | AT15: =AI15 -> 0.00089646601 | AU15: =AJ15 -> 0.0018511946 | AV15: =AK15 -> 0.0017305419 | AW15: =AL15 -> 0.0031244631 | AX15: =AM15 -> 0.0055460947 | AY15: =AN15 -> -0.018716254 | BA15: =AR15 -> 40359 | BB15: =AS15 -> -0.028620164 | BC15: =#REF! -> #REF!
A16: 40451 | B16: -0.00062906475 | C16: 0.0033450481 | D16: -0.32888131 | E16: 0.0075691273 | F16: 0.023286611 | G16: 0.13246592 | H16: -0.16956321 | I16: -0.26886155 | J16: -1.3369544 | K16: 0.0067947242 | L16: -0.022913045 | M16: 0 | N16: 0 | O16: 0.21211588 | P16: 0 | Q16: 0.91266169 | R16: 0 | S16: 0 | T16: -0.30290794 | U16: 0 | V16: 0 | W16: 0 | X16: 0 | Y16: 0.00072084334 | Z16: 0.0019737883 | AA16: 0.0027451016 | AB16: 0.003387332 | AC16: 0.0076217821 | AD16: -0.017287506 | AE16: -0.23654706 | AF16: -1.4033623 | AH16: =K16 -> 0.0067947242 | AI16: =Y16 -> 0.00072084334 | AJ16: =Z16 -> 0.0019737883 | AK16: =AA16 -> 0.0027451016 | AL16: =AB16 -> 0.003387332 | AM16: =AC16 -> 0.0076217821 | AN16: =AD16 -> -0.017287506 | AR16: =A16 -> 40451 | AS16: =AH16-$AH$8 -> -0.029060715 | AT16: =AI16 -> 0.00072084334 | AU16: =AJ16 -> 0.0019737883 | AV16: =AK16 -> 0.0027451016 | AW16: =AL16 -> 0.003387332 | AX16: =AM16 -> 0.0076217821 | AY16: =AN16 -> -0.017287506 | BA16: =AR16 -> 40451 | BB16: =AS16 -> -0.029060715 | BC16: =#REF! -> #REF!
A17: 40543 | B17: -0.011372879 | C17: 0.0030241989 | D17: -0.32812589 | E17: 0.0086382463 | F17: 0.019738835 | G17: 0.14042288 | H17: -0.20791232 | I17: 0.4478026 | J17: -1.3815556 | K17: 0.0061266593 | L17: -0.032054721 | M17: 0 | N17: 0 | O17: 0.16644919 | P17: 0 | Q17: 0.88049151 | R17: 0 | S17: 0 | T17: -0.19682746 | U17: 0 | V17: 0 | W17: 0 | X17: 0 | Y17: 0.00077661276 | Z17: 0.001887183 | AA17: 0.0027602001 | AB17: 0.003062094 | AC17: 0.0063574995 | AD17: -0.017088608 | AE17: -0.23420927 | AF17: -0.74969799 | AH17: =K17 -> 0.0061266593 | AI17: =Y17 -> 0.00077661276 | AJ17: =Z17 -> 0.001887183 | AK17: =AA17 -> 0.0027602001 | AL17: =AB17 -> 0.003062094 | AM17: =AC17 -> 0.0063574995 | AN17: =AD17 -> -0.017088608 | AR17: =A17 -> 40543 | AS17: =AH17-$AH$8 -> -0.02972878 | AT17: =AI17 -> 0.00077661276 | AU17: =AJ17 -> 0.001887183 | AV17: =AK17 -> 0.0027602001 | AW17: =AL17 -> 0.003062094 | AX17: =AM17 -> 0.0063574995 | AY17: =AN17 -> -0.017088608 | BA17: =AR17 -> 40543 | BB17: =AS17 -> -0.02972878 | BC17: =#REF! -> #REF!
A18: 40633 | B18: -0.022416807 | C18: 0.0027353283 | D18: -0.27959616 | E18: 0.0088719022 | F18: 0.017961792 | G18: 0.1845536 | H18: -0.16639013 | I18: 0.41810987 | J18: -1.1869705 | K18: 0.0085206144 | L18: -0.023892752 | M18: 0 | N18: 0 | O18: 0.13521537 | P18: 0 | Q18: 0.76883476 | R18: 0 | S18: 0 | T18: 0.14138897 | U18: 0 | V18: 0 | W18: 0 | X18: 0 | Y18: 0.00020219985 | Z18: 0.001083498 | AA18: 0.0011527572 | AB18: 0.001478678 | AC18: 0.0056280385 | AD18: -0.018825034 | AE18: -0.23189254 | AF18: -0.25099681 | AH18: =K18 -> 0.0085206144 | AI18: =Y18 -> 0.00020219985 | AJ18: =Z18 -> 0.001083498 | AK18: =AA18 -> 0.0011527572 | AL18: =AB18 -> 0.001478678 | AM18: =AC18 -> 0.0056280385 | AN18: =AD18 -> -0.018825034 | AR18: =A18 -> 40633 | AS18: =AH18-$AH$8 -> -0.027334825 | AT18: =AI18 -> 0.00020219985 | AU18: =AJ18 -> 0.001083498 | AV18: =AK18 -> 0.0011527572 | AW18: =AL18 -> 0.001478678 | AX18: =AM18 -> 0.0056280385 | AY18: =AN18 -> -0.018825034 | BA18: =AR18 -> 40633 | BB18: =AS18 -> -0.027334825 | BC18: =#REF! -> #REF!
A19: 40724 | B19: -0.027247371 | C19: 0.0023738882 | D19: -0.31422335 | E19: 0.0093425001 | F19: -0.013049634 | G19: 0.20469262 | H19: -0.18816193 | I19: 0.98633916 | J19: -1.3756401 | K19: 0.0096535166 | L19: -0.038413426 | M19: 0 | N19: 0 | O19: 0.095508167 | P19: 0 | Q19: 1.0330844 | R19: 0 | S19: 0 | T19: 0.19781486 | U19: 0 | V19: 0 | W19: 0 | X19: 0 | Y19: 0.0017974433 | Z19: 0.0024593157 | AA19: 0.0034491551 | AB19: 0.0026918082 | AC19: 0.0081607622 | AD19: -0.019227747 | AE19: -0.22959677 | AF19: 0.33796355 | AH19: =K19 -> 0.0096535166 | AI19: =Y19 -> 0.0017974433 | AJ19: =Z19 -> 0.0024593157 | AK19: =AA19 -> 0.0034491551 | AL19: =AB19 -> 0.0026918082 | AM19: =AC19 -> 0.0081607622 | AN19: =AD19 -> -0.019227747 | AR19: =A19 -> 40724 | AS19: =AH19-$AH$8 -> -0.026201923 | AT19: =AI19 -> 0.0017974433 | AU19: =AJ19 -> 0.0024593157 | AV19: =AK19 -> 0.0034491551 | AW19: =AL19 -> 0.0026918082 | AX19: =AM19 -> 0.0081607622 | AY19: =AN19 -> -0.019227747 | BA19: =AR19 -> 40724 | BB19: =AS19 -> -0.026201923 | BC19: =#REF! -> #REF!
... A132: 51043 | B132: -0.043141873 | C132: -0.00014191675 | D132: -0.060150045 | E132: 0.00016375639 | F132: 0.077003819 | G132: -0.017761409 | H132: 0.10657899 | I132: -0.12938709 | J132: -0.23383062 | K132: -0.0013647494 | L132: 0.028622522 | M132: 0 | N132: 0 | O132: 0.44750605 | P132: 0 | Q132: 0.30446726 | R132: 0 | S132: 0 | T132: 0 | U132: 0 | V132: 0 | W132: 0 | X132: 0 | Y132: 0.0014171204 | Z132: -0.0014470184 | AA132: 0.00054189822 | AB132: -0.00029329794 | AC132: 0.0013717805 | AD132: 0.0037302372 | AE132: -0.072867892 | AF132: 0.418171 | AH132: =K132 -> -0.0013647494 | AI132: =Y132 -> 0.0014171204 | AJ132: =Z132 -> -0.0014470184 | AK132: =AA132 -> 0.00054189822 | AL132: =AB132 -> -0.00029329794 | AM132: =AC132 -> 0.0013717805 | AN132: =AD132 -> 0.0037302372 | AR132: =A132 -> 51043 | AS132: =AH132-$AH$8 -> -0.037220189 | AT132: =AI132 -> 0.0014171204 | AU132: =AJ132 -> -0.0014470184 | AV132: =AK132 -> 0.00054189822 | AW132: =AL132 -> -0.00029329794 | AX132: =AM132 -> 0.0013717805 | AY132: =AN132 -> 0.0037302372 | BA132: =AR132 -> 51043 | BB132: =AS132 -> -0.037220189 | BC132: =#REF! -> #REF!

Sheet US_core_obs_with_text_backup
A1: date | B1: g_sh | C1: b_liqtil_sh | D1: b_liqp_sh | E1: b_safetil_sh | F1: b_safep_sh | G1: mu_sh | H1: z_sh | I1: lambda_f_sh | J1: lambda_w_sh | K1: rm_sh | L1: sigma_omega_sh | M1: mu_e_sh | N1: gamma_sh | O1: pi_star_sh | P1: lr_sh | Q1: zp_sh | R1: tfp_sh | S1: gdpdef_sh | T1: corepce_sh | U1: gdp_sh | V1: gdi_sh | W1: BBB_sh | X1: AAA_sh | Y1: rm_shl1 | Z1: rm_shl2 | AA1: rm_shl3 | AB1: rm_shl4 | AC1: rm_shl5 | AD1: rm_shl6 | AE1: dettrend | AF1: detrendedMean | AH1: rm_sh | AI1: =Y1 -> rm_shl1 | AJ1: =Z1 -> rm_shl2 | AK1: =AA1 -> rm_shl3 | AL1: =AB1 -> rm_shl4 | AM1: =AC1 -> rm_shl5 | AN1: =AD1 -> rm_shl6 | AQ1: Plot | AR1: =A1 -> date | AS1: =AF1 -> detrendedMean | AT1: Monetary Policy | AU1: Fgsum | AV1: FG1 | AW1: FG2 | AX1: FG3 | AY1: FG4 | AZ1: FG5 | BA1: FG6 | BC1: date | BD1: rm_sh | BE1: Fgsum
A2: 39172 | B2: -0.04656955 | C2: 6.6857837e-05 | D2: -0.12107115 | E2: 0.0055571623 | F2: 0.29566638 | G2: -0.097339567 | H2: 0.242653 | I2: 1.0199768 | J2: -0.95012393 | K2: 0.031410275 | L2: -0.11629573 | M2: 0 | N2: 0 | O2: 0.62102095 | P2: 0 | Q2: -0.028873853 | R2: 0 | S2: 0 | T2: 0.17412573 | U2: 0 | V2: 0 | W2: 0 | X2: 0 | Y2: 0 | Z2: 0 | AA2: 0 | AB2: 0 | AC2: 0 | AD2: 0 | AE2: -0.27154927 | AF2: 0.76346908 | AH2: =K2 -> 0.031410275 | AI2: =Y2 -> 0 | AJ2: =Z2 -> 0 | AK2: =AA2 -> 0 | AL2: =AB2 -> 0 | AM2: =AC2 -> 0 | AN2: =AD2 -> 0 | AR2: =A2 -> 39172 | AS2: =AF2*4+2 -> 5.0538763 | AT2: =AH2 -> 0.031410275 | AU2: =SUM(AV2:BA2) -> 0 | AV2: =AI2 -> 0 | AW2: =AJ2 -> 0 | AX2: =AK2 -> 0 | AY2: =AL2 -> 0 | AZ2: =AM2 -> 0 | BA2: =AN2 -> 0 | BC2: =AR2 -> 39172 | BD2: =AT2 -> 0.031410275 | BE2: =AU2 -> 0
A3: 39263 | B3: -0.041373765 | C3: -0.00024595173 | D3: -0.12421857 | E3: 0.0044496944 | F3: 0.30820019 | G3: -0.10557509 | H3: 0.19524989 | I3: 0.50023836 | J3: -1.0905131 | K3: 0.028022272 | L3: -0.11610905 | M3: 0 | N3: 0 | O3: 0.64479076 | P3: 0 | Q3: 0.07027945 | R3: 0 | S3: 0 | T3: -0.32870966 | U3: 0 | V3: 0 | W3: 0 | X3: 0 | Y3: 0 | Z3: 0 | AA3: 0 | AB3: 0 | AC3: 0 | AD3: 0 | AE3: -0.26890542 | AF3: -0.34173686 | AH3: =K3 -> 0.028022272 | AI3: =Y3 -> 0 | AJ3: =Z3 -> 0 | AK3: =AA3 -> 0 | AL3: =AB3 -> 0 | AM3: =AC3 -> 0 | AN3: =AD3 -> 0 | AR3: =A3 -> 39263 | AS3: =AF3*4+2 -> 0.63305257 | AT3: =AH3 -> 0.028022272 | AU3: =SUM(AV3:BA3) -> 0 | AV3: =AI3 -> 0 | AW3: =AJ3 -> 0 | AX3: =AK3 -> 0 | AY3: =AL3 -> 0 | AZ3: =AM3 -> 0 | BA3: =AN3 -> 0 | BC3: =AR3 -> 39263 | BD3: =AT3 -> 0.028022272 | BE3: =AU3 -> 0
A4: 39355 | B4: -0.042698816 | C4: -0.00054061997 | D4: -0.17511163 | E4: 0.0035197522 | F4: 0.31268306 | G4: -0.098445474 | H4: 0.22426866 | I4: 0.56066465 | J4: -1.2109319 | K4: 0.028694151 | L4: -0.10308787 | M4: 0 | N4: 0 | O4: 0.68905081 | P4: 0 | Q4: 0.1263565 | R4: 0 | S4: 0 | T4: -0.075869274 | U4: 0 | V4: 0 | W4: 0 | X4: 0 | Y4: 0 | Z4: 0 | AA4: 0 | AB4: 0 | AC4: 0 | AD4: 0 | AE4: -0.26628403 | AF4: -0.041333904 | AH4: =K4 -> 0.028694151 | AI4: =Y4 -> 0 | AJ4: =Z4 -> 0 | AK4: =AA4 -> 0 | AL4: =AB4 -> 0 | AM4: =AC4 -> 0 | AN4: =AD4 -> 0 | AR4: =A4 -> 39355 | AS4: =AF4*4+2 -> 1.8346644 | AT4: =AH4 -> 0.028694151 | AU4: =SUM(AV4:BA4) -> 0 | AV4: =AI4 -> 0 | AW4: =AJ4 -> 0 | AX4: =AK4 -> 0 | AY4: =AL4 -> 0 | AZ4: =AM4 -> 0 | BA4: =AN4 -> 0 | BC4: =AR4 -> 39355 | BD4: =AT4 -> 0.028694151 | BE4: =AU4 -> 0
A5: 39447 | B5: -0.041509973 | C5: -0.00084051646 | D5: -0.22632931 | E5: 0.00245953 | F5: 0.30585847 | G5: -0.089583103 | H5: 0.22615008 | I5: 0.71979624 | J5: -1.1731183 | K5: 0.033606282 | L5: -0.085577213 | M5: 0 | N5: 0 | O5: 0.71164067 | P5: 0 | Q5: 0.11229443 | R5: 0 | S5: 0 | T5: 0.53685152 | U5: 0 | V5: 0 | W5: 0 | X5: 0 | Y5: 0 | Z5: 0 | AA5: 0 | AB5: 0 | AC5: 0 | AD5: 0 | AE5: -0.26368501 | AF5: 0.77117619 | AH5: =K5 -> 0.033606282 | AI5: =Y5 -> 0 | AJ5: =Z5 -> 0 | AK5: =AA5 -> 0 | AL5: =AB5 -> 0 | AM5: =AC5 -> 0 | AN5: =AD5 -> 0 | AR5: =A5 -> 39447 | AS5: =AF5*4+2 -> 5.0847048 | AT5: =AH5 -> 0.033606282 | AU5: =SUM(AV5:BA5) -> 0 | AV5: =AI5 -> 0 | AW5: =AJ5 -> 0 | AX5: =AK5 -> 0 | AY5: =AL5 -> 0 | AZ5: =AM5 -> 0 | BA5: =AN5 -> 0 | BC5: =AR5 -> 39447 | BD5: =AT5 -> 0.033606282 | BE5: =AU5 -> 0
A6: 39538 | B6: -0.042159162 | C6: -0.00093182491 | D6: -0.28492927 | E6: 0.00057296347 | F6: 0.28801431 | G6: -0.092070004 | H6: 0.24492393 | I6: 0.26378547 | J6: -1.1318102 | K6: 0.038135505 | L6: -0.072334971 | M6: 0 | N6: 0 | O6: 0.73156921 | P6: 0 | Q6: 0.22897399 | R6: 0 | S6: 0 | T6: 0.21638093 | U6: 0 | V6: 0 | W6: 0 | X6: 0 | Y6: 0 | Z6: 0 | AA6: 0 | AB6: 0 | AC6: 0 | AD6: 0 | AE6: -0.2611083 | AF6: 0.11790821 | AH6: =K6 -> 0.038135505 | AI6: =Y6 -> 0 | AJ6: =Z6 -> 0 | AK6: =AA6 -> 0 | AL6: =AB6 -> 0 | AM6: =AC6 -> 0 | AN6: =AD6 -> 0 | AR6: =A6 -> 39538 | AS6: =AF6*4+2 -> 2.4716328 | AT6: =AH6 -> 0.038135505 | AU6: =SUM(AV6:BA6) -> 0 | AV6: =AI6 -> 0 | AW6: =AJ6 -> 0 | AX6: =AK6 -> 0 | AY6: =AL6 -> 0 | AZ6: =AM6 -> 0 | BA6: =AN6 -> 0 | BC6: =AR6 -> 39538 | BD6: =AT6 -> 0.038135505 | BE6: =AU6 -> 0
A7: 39629 | B7: -0.04379341 | C7: -0.00091690978 | D7: -0.28711526 | E7: -0.00069982559 | F7: 0.29321687 | G7: -0.09253843 | H7: 0.22624034 | I7: 0.12500858 | J7: -1.2341142 | K7: 0.042370011 | L7: -0.063030173 | M7: 0 | N7: 0 | O7: 0.7532105 | P7: 0 | Q7: 0.29368416 | R7: 0 | S7: 0 | T7: -0.065172848 | U7: 0 | V7: 0 | W7: 0 | X7: 0 | Y7: 0 | Z7: 0 | AA7: 0 | AB7: 0 | AC7: 0 | AD7: 0 | AE7: -0.2585538 | AF7: -0.33077165 | AH7: =K7 -> 0.042370011 | AI7: =Y7 -> 0 | AJ7: =Z7 -> 0 | AK7: =AA7 -> 0 | AL7: =AB7 -> 0 | AM7: =AC7 -> 0 | AN7: =AD7 -> 0 | AR7: =A7 -> 39629 | AS7: =AF7*4+2 -> 0.67691341 | AT7: =AH7 -> 0.042370011 | AU7: =SUM(AV7:BA7) -> 0 | AV7: =AI7 -> 0 | AW7: =AJ7 -> 0 | AX7: =AK7 -> 0 | AY7: =AL7 -> 0 | AZ7: =AM7 -> 0 | BA7: =AN7 -> 0 | BC7: =AR7 -> 39629 | BD7: =AT7 -> 0.042370011 | BE7: =AU7 -> 0
A8: 39721 | B8: -0.036786898 | C8: -0.00057270423 | D8: -0.3202672 | E8: -0.001910312 | F8: 0.28518735 | G8: -0.098640354 | H8: 0.2119083 | I8: 0.48032411 | J8: -1.260181 | K8: 0.035855439 | L8: -0.055106821 | M8: 0 | N8: 0 | O8: 0.73492454 | P8: 0 | Q8: 0.35519731 | R8: 0 | S8: 0 | T8: -0.023351863 | U8: 0 | V8: 0 | W8: 0 | X8: 0 | Y8: 0 | Z8: 0 | AA8: 0 | AB8: 0 | AC8: 0 | AD8: 0 | AE8: -0.25602142 | AF8: 0.037276857 | AH8: =K8 -> 0.035855439 | AI8: =Y8 -> 0 | AJ8: =Z8 -> 0 | AK8: =AA8 -> 0 | AL8: =AB8 -> 0 | AM8: =AC8 -> 0 | AN8: =AD8 -> 0 | AR8: =A8 -> 39721 | AS8: =AF8*4+2 -> 2.1491074 | AT8: =AH8 -> 0.035855439 | AU8: =SUM(AV8:BA8) -> 0 | AV8: =AI8 -> 0 | AW8: =AJ8 -> 0 | AX8: =AK8 -> 0 | AY8: =AL8 -> 0 | AZ8: =AM8 -> 0 | BA8: =AN8 -> 0 | BC8: =AR8 -> 39721 | BD8: =AT8 -> 0.035855439 | BE8: =AU8 -> 0
A9: 39813 | B9: -0.019051908 | C9: 0.00039391664 | D9: -0.50484687 | E9: -0.0029901249 | F9: 0.19330924 | G9: -0.14313249 | H9: 0.34908351 | I9: -1.1794005 | J9: -1.1872455 | K9: 0.027346268 | L9: -0.019735076 | M9: 0 | N9: 0 | O9: 0.79272106 | P9: 0 | Q9: 0.5725535 | R9: 0 | S9: 0 | T9: -0.90423628 | U9: 0 | V9: 0 | W9: 0 | X9: 0 | Y9: -0.0046602345 | Z9: -0.0032534387 | AA9: -0.0008489732 | AB9: -0.00022071955 | AC9: -0.00014406503 | AD9: -0.00032751503 | AE9: -0.25351107 | AF9: -2.3333306 | AH9: =K9 -> 0.027346268 | AI9: =Y9 -> -0.0046602345 | AJ9: =Z9 -> -0.0032534387 | AK9: =AA9 -> -0.0008489732 | AL9: =AB9 -> -0.00022071955 | AM9: =AC9 -> -0.00014406503 | AN9: =AD9 -> -0.00032751503 | AR9: =A9 -> 39813 | AS9: =AF9*4+2 -> -7.3333223 | AT9: =AH9 -> 0.027346268 | AU9: =SUM(AV9:BA9) -> -0.0094549461 | AV9: =AI9 -> -0.0046602345 | AW9: =AJ9 -> -0.0032534387 | AX9: =AK9 -> -0.0008489732 | AY9: =AL9 -> -0.00022071955 | AZ9: =AM9 -> -0.00014406503 | BA9: =AN9 -> -0.00032751503 | BC9: =AR9 -> 39813 | BD9: =AT9 -> 0.027346268 | BE9: =AU9 -> -0.0094549461
A10: 39903 | B10: -0.0088838781 | C10: 0.0015216111 | D10: -0.48045713 | E10: -0.0024772033 | F10: 0.18735855 | G10: -0.1021781 | H10: 0.32785381 | I10: -0.83317088 | J10: -1.6534315 | K10: 0.015650166 | L10: 0.014512646 | M10: 0 | N10: 0 | O10: 0.8701949 | P10: 0 | Q10: 0.62656666 | R10: 0 | S10: 0 | T10: -0.66787461 | U10: 0 | V10: 0 | W10: 0 | X10: 0 | Y10: -0.0076239905 | Z10: -0.0060776716 | AA10: -0.0031169771 | AB10: -0.00051108152 | AC10: -0.0011992944 | AD10: -0.0026694055 | AE10: -0.25102265 | AF10: -2.0246819 | AH10: =K10 -> 0.015650166 | AI10: =Y10 -> -0.0076239905 | AJ10: =Z10 -> -0.0060776716 | AK10: =AA10 -> -0.0031169771 | AL10: =AB10 -> -0.00051108152 | AM10: =AC10 -> -0.0011992944 | AN10: =AD10 -> -0.0026694055 | AR10: =A10 -> 39903 | AS10: =AF10*4+2 -> -6.0987276 | AT10: =AH10 -> 0.015650166 | AU10: =SUM(AV10:BA10) -> -0.021198421 | AV10: =AI10 -> -0.0076239905 | AW10: =AJ10 -> -0.0060776716 | AX10: =AK10 -> -0.0031169771 | AY10: =AL10 -> -0.00051108152 | AZ10: =AM10 -> -0.0011992944 | BA10: =AN10 -> -0.0026694055 | BC10: =AR10 -> 39903 | BD10: =AT10 -> 0.015650166 | BE10: =AU10 -> -0.021198421
A11: 39994 | B11: -0.0016392847 | C11: 0.0026571168 | D11: -0.41530551 | E11: -0.0010258689 | F11: 0.18768215 | G11: -0.075216881 | H11: 0.20805356 | I11: -0.45099997 | J11: -1.3750451 | K11: 0.0098796611 | L11: 0.010574395 | M11: 0 | N11: 0 | O11: 0.7945309 | P11: 0 | Q11: 0.54204045 | R11: 0 | S11: 0 | T11: 0.42136932 | U11: 0 | V11: 0 | W11: 0 | X11: 0 | Y11: -0.0077225494 | Z11: -0.0064522642 | AA11: -0.0053651544 | AB11: -0.0024223879 | AC11: -0.0012541237 | AD11: -0.0066621159 | AE11: -0.24855607 | AF11: -0.44640572 | AH11: =K11 -> 0.0098796611 | AI11: =Y11 -> -0.0077225494 | AJ11: =Z11 -> -0.0064522642 | AK11: =AA11 -> -0.0053651544 | AL11: =AB11 -> -0.0024223879 | AM11: =AC11 -> -0.0012541237 | AN11: =AD11 -> -0.0066621159 | AR11: =A11 -> 39994 | AS11: =AF11*4+2 -> 0.21437711 | AT11: =AH11 -> 0.0098796611 | AU11: =SUM(AV11:BA11) -> -0.029878596 | AV11: =AI11 -> -0.0077225494 | AW11: =AJ11 -> -0.0064522642 | AX11: =AK11 -> -0.0053651544 | AY11: =AL11 -> -0.0024223879 | AZ11: =AM11 -> -0.0012541237 | BA11: =AN11 -> -0.0066621159 | BC11: =AR11 -> 39994 | BD11: =AT11 -> 0.0098796611 | BE11: =AU11 -> -0.029878596
A12: 40086 | B12: -0.0088587798 | C12: 0.0032704207 | D12: -0.34119341 | E12: 0.00094675771 | F12: 0.17267413 | G12: -0.0073648259 | H12: 0.11138429 | I12: -0.32898704 | J12: -1.2012606 | K12: 0.010727173 | L12: -0.01288965 | M12: 0 | N12: 0 | O12: 0.58534165 | P12: 0 | Q12: 0.57832902 | R12: 0 | S12: 0 | T12: 0.1372099 | U12: 0 | V12: 0 | W12: 0 | X12: 0 | Y12: -0.0044141949 | Z12: -0.0040548158 | AA12: -0.0037010475 | AB12: -0.0021091098 | AC12: -0.00070098011 | AD12: -0.010372398 | AE12: -0.24611123 | AF12: -0.59458616 | AH12: =K12 -> 0.010727173 | AI12: =Y12 -> -0.0044141949 | AJ12: =Z12 -> -0.0040548158 | AK12: =AA12 -> -0.0037010475 | AL12: =AB12 -> -0.0021091098 | AM12: =AC12 -> -0.00070098011 | AN12: =AD12 -> -0.010372398 | AR12: =A12 -> 40086 | AS12: =AF12*4+2 -> -0.37834465 | AT12: =AH12 -> 0.010727173 | AU12: =SUM(AV12:BA12) -> -0.025352546 | AV12: =AI12 -> -0.0044141949 | AW12: =AJ12 -> -0.0040548158 | AX12: =AK12 -> -0.0037010475 | AY12: =AL12 -> -0.0021091098 | AZ12: =AM12 -> -0.00070098011 | BA12: =AN12 -> -0.010372398 | BC12: =AR12 -> 40086 | BD12: =AT12 -> 0.010727173 | BE12: =AU12 -> -0.025352546
A13: 40178 | B13: -0.0041259572 | C13: 0.0037769523 | D13: -0.30060972 | E13: 0.0025164451 | F13: 0.15618437 | G13: 0.013478816 | H13: -0.048747454 | I13: 0.56010376 | J13: -1.1290423 | K13: 0.0043932254 | L13: -0.033449991 | M13: 0 | N13: 0 | O13: 0.39894746 | P13: 0 | Q13: 0.49842621 | R13: 0 | S13: 0 | T13: 0.64801933 | U13: 0 | V13: 0 | W13: 0 | X13: 0 | Y13: -0.0038018908 | Z13: -0.0031772213 | AA13: -0.0046047315 | AB13: -0.0020995461 | AC13: -0.00090141919 | AD13: -0.014426647 | AE13: -0.24368801 | AF13: 0.49515122 | AH13: =K13 -> 0.0043932254 | AI13: =Y13 -> -0.0038018908 | AJ13: =Z13 -> -0.0031772213 | AK13: =AA13 -> -0.0046047315 | AL13: =AB13 -> -0.0020995461 | AM13: =AC13 -> -0.00090141919 | AN13: =AD13 -> -0.014426647 | AR13: =A13 -> 40178 | AS13: =AF13*4+2 -> 3.9806049 | AT13: =AH13 -> 0.0043932254 | AU13: =SUM(AV13:BA13) -> -0.029011456 | AV13: =AI13 -> -0.0038018908 | AW13: =AJ13 -> -0.0031772213 | AX13: =AK13 -> -0.0046047315 | AY13: =AL13 -> -0.0020995461 | AZ13: =AM13 -> -0.00090141919 | BA13: =AN13 -> -0.014426647 | BC13: =AR13 -> 40178 | BD13: =AT13 -> 0.0043932254 | BE13: =AU13 -> -0.029011456
... A132: 51043 | B132: -0.043141873 | C132: -0.00014191675 | D132: -0.060150045 | E132: 0.00016375639 | F132: 0.077003819 | G132: -0.017761409 | H132: 0.10657899 | I132: -0.12938709 | J132: -0.23383062 | K132: -0.0013647494 | L132: 0.028622522 | M132: 0 | N132: 0 | O132: 0.44750605 | P132: 0 | Q132: 0.30446726 | R132: 0 | S132: 0 | T132: 0 | U132: 0 | V132: 0 | W132: 0 | X132: 0 | Y132: 0.0014171204 | Z132: -0.0014470184 | AA132: 0.00054189822 | AB132: -0.00029329794 | AC132: 0.0013717805 | AD132: 0.0037302372 | AE132: -0.072867892 | AF132: 0.418171 | AH132: =K132 -> -0.0013647494 | AI132: =Y132 -> 0.0014171204 | AJ132: =Z132 -> -0.0014470184 | AK132: =AA132 -> 0.00054189822 | AL132: =AB132 -> -0.00029329794 | AM132: =AC132 -> 0.0013717805 | AN132: =AD132 -> 0.0037302372 | AR132: =A132 -> 51043 | AS132: =AF132*4+2 -> 3.672684 | AT132: =AH132 -> -0.0013647494 | AU132: =SUM(AV132:BA132) -> 0.00532072 | AV132: =AI132 -> 0.0014171204 | AW132: =AJ132 -> -0.0014470184 | AX132: =AK132 -> 0.00054189822 | AY132: =AL132 -> -0.00029329794 | AZ132: =AM132 -> 0.0013717805 | BA132: =AN132 -> 0.0037302372 | BC132: =AR132 -> 51043 | BD132: =AT132 -> -0.0013647494 | BE132: =AU132 -> 0.00532072

Sheet US_core_obs
A1: date | B1: g_sh | C1: b_liqtil_sh | D1: b_liqp_sh | E1: b_safetil_sh | F1: b_safep_sh | G1: mu_sh | H1: z_sh | I1: lambda_f_sh | J1: lambda_w_sh | K1: rm_sh | L1: sigma_omega_sh | M1: mu_e_sh | N1: gamma_sh | O1: pi_star_sh | P1: lr_sh | Q1: zp_sh | R1: tfp_sh | S1: gdpdef_sh | T1: corepce_sh | U1: gdp_sh | V1: gdi_sh | W1: BBB_sh | X1: AAA_sh | Y1: rm_shl1 | Z1: rm_shl2 | AA1: rm_shl3 | AB1: rm_shl4 | AC1: rm_shl5 | AD1: rm_shl6 | AE1: dettrend | AF1: detrendedMean | AH1: rm_sh | AI1: =Y1 -> rm_shl1 | AJ1: =Z1 -> rm_shl2 | AK1: =AA1 -> rm_shl3 | AL1: =AB1 -> rm_shl4 | AM1: =AC1 -> rm_shl5 | AN1: =AD1 -> rm_shl6 | AQ1: Plot | AR1: =A1 -> date | AS1: =AF1 -> detrendedMean | AT1: Monetary Policy | AU1: Fgsum | AV1: FG1 | AW1: FG2 | AX1: FG3 | AY1: FG4 | AZ1: FG5 | BA1: FG6 | BC1: date | BD1: rm_sh | BE1: Fgsum
A2: 39172 | B2: -0.04656955 | C2: 6.6857837e-05 | D2: -0.12107115 | E2: 0.0055571623 | F2: 0.29566638 | G2: -0.097339567 | H2: 0.242653 | I2: 1.0199768 | J2: -0.95012393 | K2: 0.031410275 | L2: -0.11629573 | M2: 0 | N2: 0 | O2: 0.62102095 | P2: 0 | Q2: -0.028873853 | R2: 0 | S2: 0 | T2: 0.17412573 | U2: 0 | V2: 0 | W2: 0 | X2: 0 | Y2: 0 | Z2: 0 | AA2: 0 | AB2: 0 | AC2: 0 | AD2: 0 | AE2: -0.27154927 | AF2: 0.76346908 | AH2: =K2 -> 0.031410275 | AI2: =Y2 -> 0 | AJ2: =Z2 -> 0 | AK2: =AA2 -> 0 | AL2: =AB2 -> 0 | AM2: =AC2 -> 0 | AN2: =AD2 -> 0 | AR2: =A2 -> 39172 | AS2: =AF2*4+2 -> 5.0538763 | AT2: =AH2 -> 0.031410275 | AU2: =SUM(AV2:BA2) -> 0 | AV2: =AI2 -> 0 | AW2: =AJ2 -> 0 | AX2: =AK2 -> 0 | AY2: =AL2 -> 0 | AZ2: =AM2 -> 0 | BA2: =AN2 -> 0 | BC2: =AR2 -> 39172 | BD2: =AT2 -> 0.031410275 | BE2: =AU2 -> 0
A3: 39263 | B3: -0.041373765 | C3: -0.00024595173 | D3: -0.12421857 | E3: 0.0044496944 | F3: 0.30820019 | G3: -0.10557509 | H3: 0.19524989 | I3: 0.50023836 | J3: -1.0905131 | K3: 0.028022272 | L3: -0.11610905 | M3: 0 | N3: 0 | O3: 0.64479076 | P3: 0 | Q3: 0.07027945 | R3: 0 | S3: 0 | T3: -0.32870966 | U3: 0 | V3: 0 | W3: 0 | X3: 0 | Y3: 0 | Z3: 0 | AA3: 0 | AB3: 0 | AC3: 0 | AD3: 0 | AE3: -0.26890542 | AF3: -0.34173686 | AH3: =K3 -> 0.028022272 | AI3: =Y3 -> 0 | AJ3: =Z3 -> 0 | AK3: =AA3 -> 0 | AL3: =AB3 -> 0 | AM3: =AC3 -> 0 | AN3: =AD3 -> 0 | AR3: =A3 -> 39263 | AS3: =AF3*4+2 -> 0.63305257 | AT3: =AH3 -> 0.028022272 | AU3: =SUM(AV3:BA3) -> 0 | AV3: =AI3 -> 0 | AW3: =AJ3 -> 0 | AX3: =AK3 -> 0 | AY3: =AL3 -> 0 | AZ3: =AM3 -> 0 | BA3: =AN3 -> 0 | BC3: =AR3 -> 39263 | BD3: =AT3 -> 0.028022272 | BE3: =AU3 -> 0
A4: 39355 | B4: -0.042698816 | C4: -0.00054061997 | D4: -0.17511163 | E4: 0.0035197522 | F4: 0.31268306 | G4: -0.098445474 | H4: 0.22426866 | I4: 0.56066465 | J4: -1.2109319 | K4: 0.028694151 | L4: -0.10308787 | M4: 0 | N4: 0 | O4: 0.68905081 | P4: 0 | Q4: 0.1263565 | R4: 0 | S4: 0 | T4: -0.075869274 | U4: 0 | V4: 0 | W4: 0 | X4: 0 | Y4: 0 | Z4: 0 | AA4: 0 | AB4: 0 | AC4: 0 | AD4: 0 | AE4: -0.26628403 | AF4: -0.041333904 | AH4: =K4 -> 0.028694151 | AI4: =Y4 -> 0 | AJ4: =Z4 -> 0 | AK4: =AA4 -> 0 | AL4: =AB4 -> 0 | AM4: =AC4 -> 0 | AN4: =AD4 -> 0 | AR4: =A4 -> 39355 | AS4: =AF4*4+2 -> 1.8346644 | AT4: =AH4 -> 0.028694151 | AU4: =SUM(AV4:BA4) -> 0 | AV4: =AI4 -> 0 | AW4: =AJ4 -> 0 | AX4: =AK4 -> 0 | AY4: =AL4 -> 0 | AZ4: =AM4 -> 0 | BA4: =AN4 -> 0 | BC4: =AR4 -> 39355 | BD4: =AT4 -> 0.028694151 | BE4: =AU4 -> 0
A5: 39447 | B5: -0.041509973 | C5: -0.00084051646 | D5: -0.22632931 | E5: 0.00245953 | F5: 0.30585847 | G5: -0.089583103 | H5: 0.22615008 | I5: 0.71979624 | J5: -1.1731183 | K5: 0.033606282 | L5: -0.085577213 | M5: 0 | N5: 0 | O5: 0.71164067 | P5: 0 | Q5: 0.11229443 | R5: 0 | S5: 0 | T5: 0.53685152 | U5: 0 | V5: 0 | W5: 0 | X5: 0 | Y5: 0 | Z5: 0 | AA5: 0 | AB5: 0 | AC5: 0 | AD5: 0 | AE5: -0.26368501 | AF5: 0.77117619 | AH5: =K5 -> 0.033606282 | AI5: =Y5 -> 0 | AJ5: =Z5 -> 0 | AK5: =AA5 -> 0 | AL5: =AB5 -> 0 | AM5: =AC5 -> 0 | AN5: =AD5 -> 0 | AR5: =A5 -> 39447 | AS5: =AF5*4+2 -> 5.0847048 | AT5: =AH5 -> 0.033606282 | AU5: =SUM(AV5:BA5) -> 0 | AV5: =AI5 -> 0 | AW5: =AJ5 -> 0 | AX5: =AK5 -> 0 | AY5: =AL5 -> 0 | AZ5: =AM5 -> 0 | BA5: =AN5 -> 0 | BC5: =AR5 -> 39447 | BD5: =AT5 -> 0.033606282 | BE5: =AU5 -> 0
A6: 39538 | B6: -0.042159162 | C6: -0.00093182491 | D6: -0.28492927 | E6: 0.00057296347 | F6: 0.28801431 | G6: -0.092070004 | H6: 0.24492393 | I6: 0.26378547 | J6: -1.1318102 | K6: 0.038135505 | L6: -0.072334971 | M6: 0 | N6: 0 | O6: 0.73156921 | P6: 0 | Q6: 0.22897399 | R6: 0 | S6: 0 | T6: 0.21638093 | U6: 0 | V6: 0 | W6: 0 | X6: 0 | Y6: 0 | Z6: 0 | AA6: 0 | AB6: 0 | AC6: 0 | AD6: 0 | AE6: -0.2611083 | AF6: 0.11790821 | AH6: =K6 -> 0.038135505 | AI6: =Y6 -> 0 | AJ6: =Z6 -> 0 | AK6: =AA6 -> 0 | AL6: =AB6 -> 0 | AM6: =AC6 -> 0 | AN6: =AD6 -> 0 | AR6: =A6 -> 39538 | AS6: =AF6*4+2 -> 2.4716328 | AT6: =AH6 -> 0.038135505 | AU6: =SUM(AV6:BA6) -> 0 | AV6: =AI6 -> 0 | AW6: =AJ6 -> 0 | AX6: =AK6 -> 0 | AY6: =AL6 -> 0 | AZ6: =AM6 -> 0 | BA6: =AN6 -> 0 | BC6: =AR6 -> 39538 | BD6: =AT6 -> 0.038135505 | BE6: =AU6 -> 0
A7: 39629 | B7: -0.04379341 | C7: -0.00091690978 | D7: -0.28711526 | E7: -0.00069982559 | F7: 0.29321687 | G7: -0.09253843 | H7: 0.22624034 | I7: 0.12500858 | J7: -1.2341142 | K7: 0.042370011 | L7: -0.063030173 | M7: 0 | N7: 0 | O7: 0.7532105 | P7: 0 | Q7: 0.29368416 | R7: 0 | S7: 0 | T7: -0.065172848 | U7: 0 | V7: 0 | W7: 0 | X7: 0 | Y7: 0 | Z7: 0 | AA7: 0 | AB7: 0 | AC7: 0 | AD7: 0 | AE7: -0.2585538 | AF7: -0.33077165 | AH7: =K7 -> 0.042370011 | AI7: =Y7 -> 0 | AJ7: =Z7 -> 0 | AK7: =AA7 -> 0 | AL7: =AB7 -> 0 | AM7: =AC7 -> 0 | AN7: =AD7 -> 0 | AR7: =A7 -> 39629 | AS7: =AF7*4+2 -> 0.67691341 | AT7: =AH7 -> 0.042370011 | AU7: =SUM(AV7:BA7) -> 0 | AV7: =AI7 -> 0 | AW7: =AJ7 -> 0 | AX7: =AK7 -> 0 | AY7: =AL7 -> 0 | AZ7: =AM7 -> 0 | BA7: =AN7 -> 0 | BC7: =AR7 -> 39629 | BD7: =AT7 -> 0.042370011 | BE7: =AU7 -> 0
A8: 39721 | B8: -0.036786898 | C8: -0.00057270423 | D8: -0.3202672 | E8: -0.001910312 | F8: 0.28518735 | G8: -0.098640354 | H8: 0.2119083 | I8: 0.48032411 | J8: -1.260181 | K8: 0.035855439 | L8: -0.055106821 | M8: 0 | N8: 0 | O8: 0.73492454 | P8: 0 | Q8: 0.35519731 | R8: 0 | S8: 0 | T8: -0.023351863 | U8: 0 | V8: 0 | W8: 0 | X8: 0 | Y8: 0 | Z8: 0 | AA8: 0 | AB8: 0 | AC8: 0 | AD8: 0 | AE8: -0.25602142 | AF8: 0.037276857 | AH8: =K8 -> 0.035855439 | AI8: =Y8 -> 0 | AJ8: =Z8 -> 0 | AK8: =AA8 -> 0 | AL8: =AB8 -> 0 | AM8: =AC8 -> 0 | AN8: =AD8 -> 0 | AR8: =A8 -> 39721 | AS8: =AF8*4+2 -> 2.1491074 | AT8: =AH8 -> 0.035855439 | AU8: =SUM(AV8:BA8) -> 0 | AV8: =AI8 -> 0 | AW8: =AJ8 -> 0 | AX8: =AK8 -> 0 | AY8: =AL8 -> 0 | AZ8: =AM8 -> 0 | BA8: =AN8 -> 0 | BC8: =AR8 -> 39721 | BD8: =AT8 -> 0.035855439 | BE8: =AU8 -> 0
A9: 39813 | B9: -0.019051908 | C9: 0.00039391664 | D9: -0.50484687 | E9: -0.0029901249 | F9: 0.19330924 | G9: -0.14313249 | H9: 0.34908351 | I9: -1.1794005 | J9: -1.1872455 | K9: 0.027346268 | L9: -0.019735076 | M9: 0 | N9: 0 | O9: 0.79272106 | P9: 0 | Q9: 0.5725535 | R9: 0 | S9: 0 | T9: -0.90423628 | U9: 0 | V9: 0 | W9: 0 | X9: 0 | Y9: -0.0046602345 | Z9: -0.0032534387 | AA9: -0.0008489732 | AB9: -0.00022071955 | AC9: -0.00014406503 | AD9: -0.00032751503 | AE9: -0.25351107 | AF9: -2.3333306 | AH9: =K9 -> 0.027346268 | AI9: =Y9 -> -0.0046602345 | AJ9: =Z9 -> -0.0032534387 | AK9: =AA9 -> -0.0008489732 | AL9: =AB9 -> -0.00022071955 | AM9: =AC9 -> -0.00014406503 | AN9: =AD9 -> -0.00032751503 | AR9: =A9 -> 39813 | AS9: =AF9*4+2 -> -7.3333223 | AT9: =AH9 -> 0.027346268 | AU9: =SUM(AV9:BA9) -> -0.0094549461 | AV9: =AI9 -> -0.0046602345 | AW9: =AJ9 -> -0.0032534387 | AX9: =AK9 -> -0.0008489732 | AY9: =AL9 -> -0.00022071955 | AZ9: =AM9 -> -0.00014406503 | BA9: =AN9 -> -0.00032751503 | BC9: =AR9 -> 39813 | BD9: =AT9 -> 0.027346268 | BE9: =AU9 -> -0.0094549461
A10: 39903 | B10: -0.0088838781 | C10: 0.0015216111 | D10: -0.48045713 | E10: -0.0024772033 | F10: 0.18735855 | G10: -0.1021781 | H10: 0.32785381 | I10: -0.83317088 | J10: -1.6534315 | K10: 0.015650166 | L10: 0.014512646 | M10: 0 | N10: 0 | O10: 0.8701949 | P10: 0 | Q10: 0.62656666 | R10: 0 | S10: 0 | T10: -0.66787461 | U10: 0 | V10: 0 | W10: 0 | X10: 0 | Y10: -0.0076239905 | Z10: -0.0060776716 | AA10: -0.0031169771 | AB10: -0.00051108152 | AC10: -0.0011992944 | AD10: -0.0026694055 | AE10: -0.25102265 | AF10: -2.0246819 | AH10: =K10 -> 0.015650166 | AI10: =Y10 -> -0.0076239905 | AJ10: =Z10 -> -0.0060776716 | AK10: =AA10 -> -0.0031169771 | AL10: =AB10 -> -0.00051108152 | AM10: =AC10 -> -0.0011992944 | AN10: =AD10 -> -0.0026694055 | AR10: =A10 -> 39903 | AS10: =AF10*4+2 -> -6.0987276 | AT10: =AH10 -> 0.015650166 | AU10: =SUM(AV10:BA10) -> -0.021198421 | AV10: =AI10 -> -0.0076239905 | AW10: =AJ10 -> -0.0060776716 | AX10: =AK10 -> -0.0031169771 | AY10: =AL10 -> -0.00051108152 | AZ10: =AM10 -> -0.0011992944 | BA10: =AN10 -> -0.0026694055 | BC10: =AR10 -> 39903 | BD10: =AT10 -> 0.015650166 | BE10: =AU10 -> -0.021198421
A11: 39994 | B11: -0.0016392847 | C11: 0.0026571168 | D11: -0.41530551 | E11: -0.0010258689 | F11: 0.18768215 | G11: -0.075216881 | H11: 0.20805356 | I11: -0.45099997 | J11: -1.3750451 | K11: 0.0098796611 | L11: 0.010574395 | M11: 0 | N11: 0 | O11: 0.7945309 | P11: 0 | Q11: 0.54204045 | R11: 0 | S11: 0 | T11: 0.42136932 | U11: 0 | V11: 0 | W11: 0 | X11: 0 | Y11: -0.0077225494 | Z11: -0.0064522642 | AA11: -0.0053651544 | AB11: -0.0024223879 | AC11: -0.0012541237 | AD11: -0.0066621159 | AE11: -0.24855607 | AF11: -0.44640572 | AH11: =K11 -> 0.0098796611 | AI11: =Y11 -> -0.0077225494 | AJ11: =Z11 -> -0.0064522642 | AK11: =AA11 -> -0.0053651544 | AL11: =AB11 -> -0.0024223879 | AM11: =AC11 -> -0.0012541237 | AN11: =AD11 -> -0.0066621159 | AR11: =A11 -> 39994 | AS11: =AF11*4+2 -> 0.21437711 | AT11: =AH11 -> 0.0098796611 | AU11: =SUM(AV11:BA11) -> -0.029878596 | AV11: =AI11 -> -0.0077225494 | AW11: =AJ11 -> -0.0064522642 | AX11: =AK11 -> -0.0053651544 | AY11: =AL11 -> -0.0024223879 | AZ11: =AM11 -> -0.0012541237 | BA11: =AN11 -> -0.0066621159 | BC11: =AR11 -> 39994 | BD11: =AT11 -> 0.0098796611 | BE11: =AU11 -> -0.029878596
A12: 40086 | B12: -0.0088587798 | C12: 0.0032704207 | D12: -0.34119341 | E12: 0.00094675771 | F12: 0.17267413 | G12: -0.0073648259 | H12: 0.11138429 | I12: -0.32898704 | J12: -1.2012606 | K12: 0.010727173 | L12: -0.01288965 | M12: 0 | N12: 0 | O12: 0.58534165 | P12: 0 | Q12: 0.57832902 | R12: 0 | S12: 0 | T12: 0.1372099 | U12: 0 | V12: 0 | W12: 0 | X12: 0 | Y12: -0.0044141949 | Z12: -0.0040548158 | AA12: -0.0037010475 | AB12: -0.0021091098 | AC12: -0.00070098011 | AD12: -0.010372398 | AE12: -0.24611123 | AF12: -0.59458616 | AH12: =K12 -> 0.010727173 | AI12: =Y12 -> -0.0044141949 | AJ12: =Z12 -> -0.0040548158 | AK12: =AA12 -> -0.0037010475 | AL12: =AB12 -> -0.0021091098 | AM12: =AC12 -> -0.00070098011 | AN12: =AD12 -> -0.010372398 | AR12: =A12 -> 40086 | AS12: =AF12*4+2 -> -0.37834465 | AT12: =AH12 -> 0.010727173 | AU12: =SUM(AV12:BA12) -> -0.025352546 | AV12: =AI12 -> -0.0044141949 | AW12: =AJ12 -> -0.0040548158 | AX12: =AK12 -> -0.0037010475 | AY12: =AL12 -> -0.0021091098 | AZ12: =AM12 -> -0.00070098011 | BA12: =AN12 -> -0.010372398 | BC12: =AR12 -> 40086 | BD12: =AT12 -> 0.010727173 | BE12: =AU12 -> -0.025352546
A13: 40178 | B13: -0.0041259572 | C13: 0.0037769523 | D13: -0.30060972 | E13: 0.0025164451 | F13: 0.15618437 | G13: 0.013478816 | H13: -0.048747454 | I13: 0.56010376 | J13: -1.1290423 | K13: 0.0043932254 | L13: -0.033449991 | M13: 0 | N13: 0 | O13: 0.39894746 | P13: 0 | Q13: 0.49842621 | R13: 0 | S13: 0 | T13: 0.64801933 | U13: 0 | V13: 0 | W13: 0 | X13: 0 | Y13: -0.0038018908 | Z13: -0.0031772213 | AA13: -0.0046047315 | AB13: -0.0020995461 | AC13: -0.00090141919 | AD13: -0.014426647 | AE13: -0.24368801 | AF13: 0.49515122 | AH13: =K13 -> 0.0043932254 | AI13: =Y13 -> -0.0038018908 | AJ13: =Z13 -> -0.0031772213 | AK13: =AA13 -> -0.0046047315 | AL13: =AB13 -> -0.0020995461 | AM13: =AC13 -> -0.00090141919 | AN13: =AD13 -> -0.014426647 | AR13: =A13 -> 40178 | AS13: =AF13*4+2 -> 3.9806049 | AT13: =AH13 -> 0.0043932254 | AU13: =SUM(AV13:BA13) -> -0.029011456 | AV13: =AI13 -> -0.0038018908 | AW13: =AJ13 -> -0.0031772213 | AX13: =AK13 -> -0.0046047315 | AY13: =AL13 -> -0.0020995461 | AZ13: =AM13 -> -0.00090141919 | BA13: =AN13 -> -0.014426647 | BC13: =AR13 -> 40178 | BD13: =AT13 -> 0.0043932254 | BE13: =AU13 -> -0.029011456
... A132: 51043 | B132: -0.043141873 | C132: -0.00014191675 | D132: -0.060150045 | E132: 0.00016375639 | F132: 0.077003819 | G132: -0.017761409 | H132: 0.10657899 | I132: -0.12938709 | J132: -0.23383062 | K132: -0.0013647494 | L132: 0.028622522 | M132: 0 | N132: 0 | O132: 0.44750605 | P132: 0 | Q132: 0.30446726 | R132: 0 | S132: 0 | T132: 0 | U132: 0 | V132: 0 | W132: 0 | X132: 0 | Y132: 0.0014171204 | Z132: -0.0014470184 | AA132: 0.00054189822 | AB132: -0.00029329794 | AC132: 0.0013717805 | AD132: 0.0037302372 | AE132: -0.072867892 | AF132: 0.418171 | AH132: =K132 -> -0.0013647494 | AI132: =Y132 -> 0.0014171204 | AJ132: =Z132 -> -0.0014470184 | AK132: =AA132 -> 0.00054189822 | AL132: =AB132 -> -0.00029329794 | AM132: =AC132 -> 0.0013717805 | AN132: =AD132 -> 0.0037302372 | AR132: =A132 -> 51043 | AS132: =AF132*4+2 -> 3.672684 | AT132: =AH132 -> -0.0013647494 | AU132: =SUM(AV132:BA132) -> 0.00532072 | AV132: =AI132 -> 0.0014171204 | AW132: =AJ132 -> -0.0014470184 | AX132: =AK132 -> 0.00054189822 | AY132: =AL132 -> -0.00029329794 | AZ132: =AM132 -> 0.0013717805 | BA132: =AN132 -> 0.0037302372 | BC132: =AR132 -> 51043 | BD132: =AT132 -> -0.0013647494 | BE132: =AU132 -> 0.00532072

Sheet US_core_with_text
A1: date | B1: g_sh | C1: b_liqtil_sh | D1: b_liqp_sh | E1: b_safetil_sh | F1: b_safep_sh | G1: mu_sh | H1: z_sh | I1: lambda_f_sh | J1: lambda_w_sh | K1: rm_sh | L1: sigma_omega_sh | M1: mu_e_sh | N1: gamma_sh | O1: pi_star_sh | P1: lr_sh | Q1: zp_sh | R1: tfp_sh | S1: gdpdef_sh | T1: corepce_sh | U1: gdp_sh | V1: gdi_sh | W1: BBB_sh | X1: AAA_sh | Y1: rm_shl1 | Z1: rm_shl2 | AA1: rm_shl3 | AB1: rm_shl4 | AC1: rm_shl5 | AD1: rm_shl6 | AE1: dettrend | AF1: detrendedMean | AH1: rm_sh | AI1: =Y1 -> rm_shl1 | AJ1: =Z1 -> rm_shl2 | AK1: =AA1 -> rm_shl3 | AL1: =AB1 -> rm_shl4 | AM1: =AC1 -> rm_shl5 | AN1: =AD1 -> rm_shl6 | AQ1: Plot | AR1: =A1 -> date | AS1: Monetary Policy | AT1: FG1 | AU1: FG2 | AV1: FG3 | AW1: FG4 | AX1: FG5 | AY1: FG6 | AZ1: Combined | BA1: date | BB1: rm_sh | BC1: Fgsum
A2: 39172 | B2: -0.04656955 | C2: 6.6857837e-05 | D2: -0.12107115 | E2: 0.0055571623 | F2: 0.29566638 | G2: -0.097339567 | H2: 0.242653 | I2: 1.0199768 | J2: -0.95012393 | K2: 0.031410275 | L2: -0.11629573 | M2: 0 | N2: 0 | O2: 0.62102095 | P2: 0 | Q2: -0.028873853 | R2: 0 | S2: 0 | T2: 0.17412573 | U2: 0 | V2: 0 | W2: 0 | X2: 0 | Y2: 0 | Z2: 0 | AA2: 0 | AB2: 0 | AC2: 0 | AD2: 0 | AE2: -0.27154927 | AF2: 0.76346908 | AH2: =K2 -> 0.031410275 | AI2: =Y2 -> 0 | AJ2: =Z2 -> 0 | AK2: =AA2 -> 0 | AL2: =AB2 -> 0 | AM2: =AC2 -> 0 | AN2: =AD2 -> 0 | AR2: =A2 -> 39172 | AS2: =K2-$K$2 -> 0 | AT2: =AI2 -> 0 | AU2: =AJ2 -> 0 | AV2: =AK2 -> 0 | AW2: =AL2 -> 0 | AX2: =AM2 -> 0 | AY2: =AN2 -> 0 | AZ2: =SUM(AS2:AY2) -> 0 | BA2: =AR2 -> 39172 | BB2: =AS2 -> 0 | BC2: =#REF! -> #REF!
A3: 39263 | B3: -0.041373765 | C3: -0.00024595173 | D3: -0.12421857 | E3: 0.0044496944 | F3: 0.30820019 | G3: -0.10557509 | H3: 0.19524989 | I3: 0.50023836 | J3: -1.0905131 | K3: 0.028022272 | L3: -0.11610905 | M3: 0 | N3: 0 | O3: 0.64479076 | P3: 0 | Q3: 0.07027945 | R3: 0 | S3: 0 | T3: -0.32870966 | U3: 0 | V3: 0 | W3: 0 | X3: 0 | Y3: 0 | Z3: 0 | AA3: 0 | AB3: 0 | AC3: 0 | AD3: 0 | AE3: -0.26890542 | AF3: -0.34173686 | AH3: =K3 -> 0.028022272 | AI3: =Y3 -> 0 | AJ3: =Z3 -> 0 | AK3: =AA3 -> 0 | AL3: =AB3 -> 0 | AM3: =AC3 -> 0 | AN3: =AD3 -> 0 | AR3: =A3 -> 39263 | AS3: =K3-$K$2 -> -0.0033880026 | AT3: =AI3 -> 0 | AU3: =AJ3 -> 0 | AV3: =AK3 -> 0 | AW3: =AL3 -> 0 | AX3: =AM3 -> 0 | AY3: =AN3 -> 0 | AZ3: =SUM(AS3:AY3) -> -0.0033880026 | BA3: =AR3 -> 39263 | BB3: =AS3 -> -0.0033880026 | BC3: =#REF! -> #REF!
A4: 39355 | B4: -0.042698816 | C4: -0.00054061997 | D4: -0.17511163 | E4: 0.0035197522 | F4: 0.31268306 | G4: -0.098445474 | H4: 0.22426866 | I4: 0.56066465 | J4: -1.2109319 | K4: 0.028694151 | L4: -0.10308787 | M4: 0 | N4: 0 | O4: 0.68905081 | P4: 0 | Q4: 0.1263565 | R4: 0 | S4: 0 | T4: -0.075869274 | U4: 0 | V4: 0 | W4: 0 | X4: 0 | Y4: 0 | Z4: 0 | AA4: 0 | AB4: 0 | AC4: 0 | AD4: 0 | AE4: -0.26628403 | AF4: -0.041333904 | AH4: =K4 -> 0.028694151 | AI4: =Y4 -> 0 | AJ4: =Z4 -> 0 | AK4: =AA4 -> 0 | AL4: =AB4 -> 0 | AM4: =AC4 -> 0 | AN4: =AD4 -> 0 | AR4: =A4 -> 39355 | AS4: =K4-$K$2 -> -0.0027161234 | AT4: =AI4 -> 0 | AU4: =AJ4 -> 0 | AV4: =AK4 -> 0 | AW4: =AL4 -> 0 | AX4: =AM4 -> 0 | AY4: =AN4 -> 0 | AZ4: =SUM(AS4:AY4) -> -0.0027161234 | BA4: =AR4 -> 39355 | BB4: =AS4 -> -0.0027161234 | BC4: =#REF! -> #REF!
A5: 39447 | B5: -0.041509973 | C5: -0.00084051646 | D5: -0.22632931 | E5: 0.00245953 | F5: 0.30585847 | G5: -0.089583103 | H5: 0.22615008 | I5: 0.71979624 | J5: -1.1731183 | K5: 0.033606282 | L5: -0.085577213 | M5: 0 | N5: 0 | O5: 0.71164067 | P5: 0 | Q5: 0.11229443 | R5: 0 | S5: 0 | T5: 0.53685152 | U5: 0 | V5: 0 | W5: 0 | X5: 0 | Y5: 0 | Z5: 0 | AA5: 0 | AB5: 0 | AC5: 0 | AD5: 0 | AE5: -0.26368501 | AF5: 0.77117619 | AH5: =K5 -> 0.033606282 | AI5: =Y5 -> 0 | AJ5: =Z5 -> 0 | AK5: =AA5 -> 0 | AL5: =AB5 -> 0 | AM5: =AC5 -> 0 | AN5: =AD5 -> 0 | AR5: =A5 -> 39447 | AS5: =K5-$K$2 -> 0.0021960077 | AT5: =AI5 -> 0 | AU5: =AJ5 -> 0 | AV5: =AK5 -> 0 | AW5: =AL5 -> 0 | AX5: =AM5 -> 0 | AY5: =AN5 -> 0 | AZ5: =SUM(AS5:AY5) -> 0.0021960077 | BA5: =AR5 -> 39447 | BB5: =AS5 -> 0.0021960077 | BC5: =#REF! -> #REF!
A6: 39538 | B6: -0.042159162 | C6: -0.00093182491 | D6: -0.28492927 | E6: 0.00057296347 | F6: 0.28801431 | G6: -0.092070004 | H6: 0.24492393 | I6: 0.26378547 | J6: -1.1318102 | K6: 0.038135505 | L6: -0.072334971 | M6: 0 | N6: 0 | O6: 0.73156921 | P6: 0 | Q6: 0.22897399 | R6: 0 | S6: 0 | T6: 0.21638093 | U6: 0 | V6: 0 | W6: 0 | X6: 0 | Y6: 0 | Z6: 0 | AA6: 0 | AB6: 0 | AC6: 0 | AD6: 0 | AE6: -0.2611083 | AF6: 0.11790821 | AH6: =K6 -> 0.038135505 | AI6: =Y6 -> 0 | AJ6: =Z6 -> 0 | AK6: =AA6 -> 0 | AL6: =AB6 -> 0 | AM6: =AC6 -> 0 | AN6: =AD6 -> 0 | AR6: =A6 -> 39538 | AS6: =K6-$K$2 -> 0.0067252304 | AT6: =AI6 -> 0 | AU6: =AJ6 -> 0 | AV6: =AK6 -> 0 | AW6: =AL6 -> 0 | AX6: =AM6 -> 0 | AY6: =AN6 -> 0 | AZ6: =SUM(AS6:AY6) -> 0.0067252304 | BA6: =AR6 -> 39538 | BB6: =AS6 -> 0.0067252304 | BC6: =#REF! -> #REF!
A7: 39629 | B7: -0.04379341 | C7: -0.00091690978 | D7: -0.28711526 | E7: -0.00069982559 | F7: 0.29321687 | G7: -0.09253843 | H7: 0.22624034 | I7: 0.12500858 | J7: -1.2341142 | K7: 0.042370011 | L7: -0.063030173 | M7: 0 | N7: 0 | O7: 0.7532105 | P7: 0 | Q7: 0.29368416 | R7: 0 | S7: 0 | T7: -0.065172848 | U7: 0 | V7: 0 | W7: 0 | X7: 0 | Y7: 0 | Z7: 0 | AA7: 0 | AB7: 0 | AC7: 0 | AD7: 0 | AE7: -0.2585538 | AF7: -0.33077165 | AH7: =K7 -> 0.042370011 | AI7: =Y7 -> 0 | AJ7: =Z7 -> 0 | AK7: =AA7 -> 0 | AL7: =AB7 -> 0 | AM7: =AC7 -> 0 | AN7: =AD7 -> 0 | AR7: =A7 -> 39629 | AS7: =K7-$K$2 -> 0.010959737 | AT7: =AI7 -> 0 | AU7: =AJ7 -> 0 | AV7: =AK7 -> 0 | AW7: =AL7 -> 0 | AX7: =AM7 -> 0 | AY7: =AN7 -> 0 | AZ7: =SUM(AS7:AY7) -> 0.010959737 | BA7: =AR7 -> 39629 | BB7: =AS7 -> 0.010959737 | BC7: =#REF! -> #REF!
A8: 39721 | B8: -0.036786898 | C8: -0.00057270423 | D8: -0.3202672 | E8: -0.001910312 | F8: 0.28518735 | G8: -0.098640354 | H8: 0.2119083 | I8: 0.48032411 | J8: -1.260181 | K8: 0.035855439 | L8: -0.055106821 | M8: 0 | N8: 0 | O8: 0.73492454 | P8: 0 | Q8: 0.35519731 | R8: 0 | S8: 0 | T8: -0.023351863 | U8: 0 | V8: 0 | W8: 0 | X8: 0 | Y8: 0 | Z8: 0 | AA8: 0 | AB8: 0 | AC8: 0 | AD8: 0 | AE8: -0.25602142 | AF8: 0.037276857 | AH8: =K8 -> 0.035855439 | AI8: =Y8 -> 0 | AJ8: =Z8 -> 0 | AK8: =AA8 -> 0 | AL8: =AB8 -> 0 | AM8: =AC8 -> 0 | AN8: =AD8 -> 0 | AR8: =A8 -> 39721 | AS8: =K8-$K$2 -> 0.0044451648 | AT8: =AI8 -> 0 | AU8: =AJ8 -> 0 | AV8: =AK8 -> 0 | AW8: =AL8 -> 0 | AX8: =AM8 -> 0 | AY8: =AN8 -> 0 | AZ8: =SUM(AS8:AY8) -> 0.0044451648 | BA8: =AR8 -> 39721 | BB8: =AS8 -> 0.0044451648 | BC8: =#REF! -> #REF!
A9: 39813 | B9: -0.019051908 | C9: 0.00039391664 | D9: -0.50484687 | E9: -0.0029901249 | F9: 0.19330924 | G9: -0.14313249 | H9: 0.34908351 | I9: -1.1794005 | J9: -1.1872455 | K9: 0.027346268 | L9: -0.019735076 | M9: 0 | N9: 0 | O9: 0.79272106 | P9: 0 | Q9: 0.5725535 | R9: 0 | S9: 0 | T9: -0.90423628 | U9: 0 | V9: 0 | W9: 0 | X9: 0 | Y9: -0.0046602345 | Z9: -0.0032534387 | AA9: -0.0008489732 | AB9: -0.00022071955 | AC9: -0.00014406503 | AD9: -0.00032751503 | AE9: -0.25351107 | AF9: -2.3333306 | AH9: =K9 -> 0.027346268 | AI9: =Y9 -> -0.0046602345 | AJ9: =Z9 -> -0.0032534387 | AK9: =AA9 -> -0.0008489732 | AL9: =AB9 -> -0.00022071955 | AM9: =AC9 -> -0.00014406503 | AN9: =AD9 -> -0.00032751503 | AR9: =A9 -> 39813 | AS9: =K9-$K$2 -> -0.0040640067 | AT9: =AI9 -> -0.0046602345 | AU9: =AJ9 -> -0.0032534387 | AV9: =AK9 -> -0.0008489732 | AW9: =AL9 -> -0.00022071955 | AX9: =AM9 -> -0.00014406503 | AY9: =AN9 -> -0.00032751503 | AZ9: =SUM(AS9:AY9) -> -0.013518953 | BA9: =AR9 -> 39813 | BB9: =AS9 -> -0.0040640067 | BC9: =#REF! -> #REF!
A10: 39903 | B10: -0.0088838781 | C10: 0.0015216111 | D10: -0.48045713 | E10: -0.0024772033 | F10: 0.18735855 | G10: -0.1021781 | H10: 0.32785381 | I10: -0.83317088 | J10: -1.6534315 | K10: 0.015650166 | L10: 0.014512646 | M10: 0 | N10: 0 | O10: 0.8701949 | P10: 0 | Q10: 0.62656666 | R10: 0 | S10: 0 | T10: -0.66787461 | U10: 0 | V10: 0 | W10: 0 | X10: 0 | Y10: -0.0076239905 | Z10: -0.0060776716 | AA10: -0.0031169771 | AB10: -0.00051108152 | AC10: -0.0011992944 | AD10: -0.0026694055 | AE10: -0.25102265 | AF10: -2.0246819 | AH10: =K10 -> 0.015650166 | AI10: =Y10 -> -0.0076239905 | AJ10: =Z10 -> -0.0060776716 | AK10: =AA10 -> -0.0031169771 | AL10: =AB10 -> -0.00051108152 | AM10: =AC10 -> -0.0011992944 | AN10: =AD10 -> -0.0026694055 | AR10: =A10 -> 39903 | AS10: =K10-$K$2 -> -0.015760109 | AT10: =AI10 -> -0.0076239905 | AU10: =AJ10 -> -0.0060776716 | AV10: =AK10 -> -0.0031169771 | AW10: =AL10 -> -0.00051108152 | AX10: =AM10 -> -0.0011992944 | AY10: =AN10 -> -0.0026694055 | AZ10: =SUM(AS10:AY10) -> -0.03695853 | BA10: =AR10 -> 39903 | BB10: =AS10 -> -0.015760109 | BC10: =#REF! -> #REF!
A11: 39994 | B11: -0.0016392847 | C11: 0.0026571168 | D11: -0.41530551 | E11: -0.0010258689 | F11: 0.18768215 | G11: -0.075216881 | H11: 0.20805356 | I11: -0.45099997 | J11: -1.3750451 | K11: 0.0098796611 | L11: 0.010574395 | M11: 0 | N11: 0 | O11: 0.7945309 | P11: 0 | Q11: 0.54204045 | R11: 0 | S11: 0 | T11: 0.42136932 | U11: 0 | V11: 0 | W11: 0 | X11: 0 | Y11: -0.0077225494 | Z11: -0.0064522642 | AA11: -0.0053651544 | AB11: -0.0024223879 | AC11: -0.0012541237 | AD11: -0.0066621159 | AE11: -0.24855607 | AF11: -0.44640572 | AH11: =K11 -> 0.0098796611 | AI11: =Y11 -> -0.0077225494 | AJ11: =Z11 -> -0.0064522642 | AK11: =AA11 -> -0.0053651544 | AL11: =AB11 -> -0.0024223879 | AM11: =AC11 -> -0.0012541237 | AN11: =AD11 -> -0.0066621159 | AR11: =A11 -> 39994 | AS11: =K11-$K$2 -> -0.021530614 | AT11: =AI11 -> -0.0077225494 | AU11: =AJ11 -> -0.0064522642 | AV11: =AK11 -> -0.0053651544 | AW11: =AL11 -> -0.0024223879 | AX11: =AM11 -> -0.0012541237 | AY11: =AN11 -> -0.0066621159 | AZ11: =SUM(AS11:AY11) -> -0.051409209 | BA11: =AR11 -> 39994 | BB11: =AS11 -> -0.021530614 | BC11: =#REF! -> #REF!
A12: 40086 | B12: -0.0088587798 | C12: 0.0032704207 | D12: -0.34119341 | E12: 0.00094675771 | F12: 0.17267413 | G12: -0.0073648259 | H12: 0.11138429 | I12: -0.32898704 | J12: -1.2012606 | K12: 0.010727173 | L12: -0.01288965 | M12: 0 | N12: 0 | O12: 0.58534165 | P12: 0 | Q12: 0.57832902 | R12: 0 | S12: 0 | T12: 0.1372099 | U12: 0 | V12: 0 | W12: 0 | X12: 0 | Y12: -0.0044141949 | Z12: -0.0040548158 | AA12: -0.0037010475 | AB12: -0.0021091098 | AC12: -0.00070098011 | AD12: -0.010372398 | AE12: -0.24611123 | AF12: -0.59458616 | AH12: =K12 -> 0.010727173 | AI12: =Y12 -> -0.0044141949 | AJ12: =Z12 -> -0.0040548158 | AK12: =AA12 -> -0.0037010475 | AL12: =AB12 -> -0.0021091098 | AM12: =AC12 -> -0.00070098011 | AN12: =AD12 -> -0.010372398 | AR12: =A12 -> 40086 | AS12: =K12-$K$2 -> -0.020683102 | AT12: =AI12 -> -0.0044141949 | AU12: =AJ12 -> -0.0040548158 | AV12: =AK12 -> -0.0037010475 | AW12: =AL12 -> -0.0021091098 | AX12: =AM12 -> -0.00070098011 | AY12: =AN12 -> -0.010372398 | AZ12: =SUM(AS12:AY12) -> -0.046035647 | BA12: =AR12 -> 40086 | BB12: =AS12 -> -0.020683102 | BC12: =#REF! -> #REF!
A13: 40178 | B13: -0.0041259572 | C13: 0.0037769523 | D13: -0.30060972 | E13: 0.0025164451 | F13: 0.15618437 | G13: 0.013478816 | H13: -0.048747454 | I13: 0.56010376 | J13: -1.1290423 | K13: 0.0043932254 | L13: -0.033449991 | M13: 0 | N13: 0 | O13: 0.39894746 | P13: 0 | Q13: 0.49842621 | R13: 0 | S13: 0 | T13: 0.64801933 | U13: 0 | V13: 0 | W13: 0 | X13: 0 | Y13: -0.0038018908 | Z13: -0.0031772213 | AA13: -0.0046047315 | AB13: -0.0020995461 | AC13: -0.00090141919 | AD13: -0.014426647 | AE13: -0.24368801 | AF13: 0.49515122 | AH13: =K13 -> 0.0043932254 | AI13: =Y13 -> -0.0038018908 | AJ13: =Z13 -> -0.0031772213 | AK13: =AA13 -> -0.0046047315 | AL13: =AB13 -> -0.0020995461 | AM13: =AC13 -> -0.00090141919 | AN13: =AD13 -> -0.014426647 | AR13: =A13 -> 40178 | AS13: =K13-$K$2 -> -0.027017049 | AT13: =AI13 -> -0.0038018908 | AU13: =AJ13 -> -0.0031772213 | AV13: =AK13 -> -0.0046047315 | AW13: =AL13 -> -0.0020995461 | AX13: =AM13 -> -0.00090141919 | AY13: =AN13 -> -0.014426647 | AZ13: =SUM(AS13:AY13) -> -0.056028505 | BA13: =AR13 -> 40178 | BB13: =AS13 -> -0.027017049 | BC13: =#REF! -> #REF!
... A132: 51043 | B132: -0.043141873 | C132: -0.00014191675 | D132: -0.060150045 | E132: 0.00016375639 | F132: 0.077003819 | G132: -0.017761409 | H132: 0.10657899 | I132: -0.12938709 | J132: -0.23383062 | K132: -0.0013647494 | L132: 0.028622522 | M132: 0 | N132: 0 | O132: 0.44750605 | P132: 0 | Q132: 0.30446726 | R132: 0 | S132: 0 | T132: 0 | U132: 0 | V132: 0 | W132: 0 | X132: 0 | Y132: 0.0014171204 | Z132: -0.0014470184 | AA132: 0.00054189822 | AB132: -0.00029329794 | AC132: 0.0013717805 | AD132: 0.0037302372 | AE132: -0.072867892 | AF132: 0.418171 | AH132: =K132 -> -0.0013647494 | AI132: =Y132 -> 0.0014171204 | AJ132: =Z132 -> -0.0014470184 | AK132: =AA132 -> 0.00054189822 | AL132: =AB132 -> -0.00029329794 | AM132: =AC132 -> 0.0013717805 | AN132: =AD132 -> 0.0037302372 | AR132: =A132 -> 51043 | AS132: =K132-$K$2 -> -0.032775024 | AT132: =AI132 -> 0.0014171204 | AU132: =AJ132 -> -0.0014470184 | AV132: =AK132 -> 0.00054189822 | AW132: =AL132 -> -0.00029329794 | AX132: =AM132 -> 0.0013717805 | AY132: =AN132 -> 0.0037302372 | AZ132: =SUM(AS132:AY132) -> -0.027454304 | BA132: =AR132 -> 51043 | BB132: =AS132 -> -0.032775024 | BC132: =#REF! -> #REF!

Sheet US_output_with_text
A1: date | B1: g_sh | C1: b_liqtil_sh | D1: b_liqp_sh | E1: b_safetil_sh | F1: b_safep_sh | G1: mu_sh | H1: z_sh | I1: lambda_f_sh | J1: lambda_w_sh | K1: rm_sh | L1: sigma_omega_sh | M1: mu_e_sh | N1: gamma_sh | O1: pi_star_sh | P1: lr_sh | Q1: zp_sh | R1: tfp_sh | S1: gdpdef_sh | T1: corepce_sh | U1: gdp_sh | V1: gdi_sh | W1: BBB_sh | X1: AAA_sh | Y1: rm_shl1 | Z1: rm_shl2 | AA1: rm_shl3 | AB1: rm_shl4 | AC1: rm_shl5 | AD1: rm_shl6 | AE1: dettrend | AF1: detrendedMean | AH1: rm_sh | AI1: =Y1 -> rm_shl1 | AJ1: =Z1 -> rm_shl2 | AK1: =AA1 -> rm_shl3 | AL1: =AB1 -> rm_shl4 | AM1: =AC1 -> rm_shl5 | AN1: =AD1 -> rm_shl6 | AQ1: Plot | AR1: =A1 -> date | AS1: Monetary Policy | AT1: FG1 | AU1: FG2 | AV1: FG3 | AW1: FG4 | AX1: FG5 | AY1: FG6 | AZ1: Combined | BA1: date | BB1: rm_sh | BC1: Fgsum
A2: 39172 | B2: -1.021588 | C2: 0.147384 | D2: -0.044907 | E2: 0.565156 | F2: 0.334719 | G2: 1.405344 | H2: 0.546931 | I2: -0.653933 | J2: 0.642327 | K2: 1.775061 | L2: 1.282652 | M2: 0 | N2: 0 | O2: 0.327856 | P2: 0 | Q2: 0.110875 | R2: 0 | S2: 0 | T2: 0 | U2: 0 | V2: 0 | W2: 0 | X2: 0 | Y2: 0 | Z2: 0 | AA2: 0 | AB2: 0 | AC2: 0 | AD2: 0 | AE2: 0.130997 | AF2: 5.548873 | AH2: =K2 -> 1.775061 | AI2: =Y2 -> 0 | AJ2: =Z2 -> 0 | AK2: =AA2 -> 0 | AL2: =AB2 -> 0 | AM2: =AC2 -> 0 | AN2: =AD2 -> 0 | AR2: =A2 -> 39172 | AS2: =K2-$K$2 -> 0 | AT2: =AI2 -> 0 | AU2: =AJ2 -> 0 | AV2: =AK2 -> 0 | AW2: =AL2 -> 0 | AX2: =AM2 -> 0 | AY2: =AN2 -> 0 | AZ2: =SUM(AS2:AY2) -> 0 | BA2: =AR2 -> 39172 | BB2: =AS2 -> 0 | BC2: =#REF! -> #REF!
A3: 39263 | B3: -0.877022 | C3: 0.14868 | D3: -0.050839 | E3: 0.596758 | F3: 0.356941 | G3: 1.445915 | H3: 0.106156 | I3: -0.670753 | J3: 0.60096 | K3: 1.568877 | L3: 1.241807 | M3: 0 | N3: 0 | O3: 0.33267 | P3: 0 | Q3: 0.070232 | R3: 0 | S3: 0 | T3: 0 | U3: 0 | V3: 0 | W3: 0 | X3: 0 | Y3: 0 | Z3: 0 | AA3: 0 | AB3: 0 | AC3: 0 | AD3: 0 | AE3: 0.130393 | AF3: 5.000775 | AH3: =K3 -> 1.568877 | AI3: =Y3 -> 0 | AJ3: =Z3 -> 0 | AK3: =AA3 -> 0 | AL3: =AB3 -> 0 | AM3: =AC3 -> 0 | AN3: =AD3 -> 0 | AR3: =A3 -> 39263 | AS3: =K3-$K$2 -> -0.206184 | AT3: =AI3 -> 0 | AU3: =AJ3 -> 0 | AV3: =AK3 -> 0 | AW3: =AL3 -> 0 | AX3: =AM3 -> 0 | AY3: =AN3 -> 0 | AZ3: =SUM(AS3:AY3) -> -0.206184 | BA3: =AR3 -> 39263 | BB3: =AS3 -> -0.206184 | BC3: =#REF! -> #REF!
A4: 39355 | B4: -1.040355 | C4: 0.134251 | D4: -0.145874 | E4: 0.690313 | F4: 0.371919 | G4: 1.450363 | H4: 0.311835 | I4: -0.679858 | J4: 0.610198 | K4: 1.508696 | L4: 1.151034 | M4: 0 | N4: 0 | O4: 0.371185 | P4: 0 | Q4: 0.037371 | R4: 0 | S4: 0 | T4: 0 | U4: 0 | V4: 0 | W4: 0 | X4: 0 | Y4: 0 | Z4: 0 | AA4: 0 | AB4: 0 | AC4: 0 | AD4: 0 | AE4: 0.129781 | AF4: 4.90086 | AH4: =K4 -> 1.508696 | AI4: =Y4 -> 0 | AJ4: =Z4 -> 0 | AK4: =AA4 -> 0 | AL4: =AB4 -> 0 | AM4: =AC4 -> 0 | AN4: =AD4 -> 0 | AR4: =A4 -> 39355 | AS4: =K4-$K$2 -> -0.266365 | AT4: =AI4 -> 0 | AU4: =AJ4 -> 0 | AV4: =AK4 -> 0 | AW4: =AL4 -> 0 | AX4: =AM4 -> 0 | AY4: =AN4 -> 0 | AZ4: =SUM(AS4:AY4) -> -0.266365 | BA4: =AR4 -> 39355 | BB4: =AS4 -> -0.266365 | BC4: =#REF! -> #REF!
A5: 39447 | B5: -0.993309 | C5: 0.142588 | D5: -0.263104 | E5: 0.737687 | F5: 0.366396 | G5: 1.43171 | H5: 0.21868 | I5: -0.6892 | J5: 0.665994 | K5: 1.72742 | L5: 1.009321 | M5: 0 | N5: 0 | O5: 0.407248 | P5: 0 | Q5: 0.016107 | R5: 0 | S5: 0 | T5: 0 | U5: 0 | V5: 0 | W5: 0 | X5: 0 | Y5: 0 | Z5: 0 | AA5: 0 | AB5: 0 | AC5: 0 | AD5: 0 | AE5: 0.129162 | AF5: 4.906701 | AH5: =K5 -> 1.72742 | AI5: =Y5 -> 0 | AJ5: =Z5 -> 0 | AK5: =AA5 -> 0 | AL5: =AB5 -> 0 | AM5: =AC5 -> 0 | AN5: =AD5 -> 0 | AR5: =A5 -> 39447 | AS5: =K5-$K$2 -> -0.047641 | AT5: =AI5 -> 0 | AU5: =AJ5 -> 0 | AV5: =AK5 -> 0 | AW5: =AL5 -> 0 | AX5: =AM5 -> 0 | AY5: =AN5 -> 0 | AZ5: =SUM(AS5:AY5) -> -0.047641 | BA5: =AR5 -> 39447 | BB5: =AS5 -> -0.047641 | BC5: =#REF! -> #REF!
A6: 39538 | B6: -1.047684 | C6: 0.030618 | D6: -0.402439 | E6: 0.39312 | F6: 0.336294 | G6: 1.42832 | H6: 0.273796 | I6: -0.67868 | J6: 0.701158 | K6: 2.00535 | L6: 0.854877 | M6: 0 | N6: 0 | O6: 0.44494 | P6: 0 | Q6: -0.01959 | R6: 0 | S6: 0 | T6: 0 | U6: 0 | V6: 0 | W6: 0 | X6: 0 | Y6: 0 | Z6: 0 | AA6: 0 | AB6: 0 | AC6: 0 | AD6: 0 | AE6: 0.128537 | AF6: 4.448615 | AH6: =K6 -> 2.00535 | AI6: =Y6 -> 0 | AJ6: =Z6 -> 0 | AK6: =AA6 -> 0 | AL6: =AB6 -> 0 | AM6: =AC6 -> 0 | AN6: =AD6 -> 0 | AR6: =A6 -> 39538 | AS6: =K6-$K$2 -> 0.230289 | AT6: =AI6 -> 0 | AU6: =AJ6 -> 0 | AV6: =AK6 -> 0 | AW6: =AL6 -> 0 | AX6: =AM6 -> 0 | AY6: =AN6 -> 0 | AZ6: =SUM(AS6:AY6) -> 0.230289 | BA6: =AR6 -> 39538 | BB6: =AS6 -> 0.230289 | BC6: =#REF! -> #REF!
A7: 39629 | B7: -1.108643 | C7: -0.03361 | D7: -0.447508 | E7: 0.093396 | F7: 0.340119 | G7: 1.424231 | H7: 0.099731 | I7: -0.649186 | J7: 0.693113 | K7: 2.300335 | L7: 0.710233 | M7: 0 | N7: 0 | O7: 0.486473 | P7: 0 | Q7: -0.047607 | R7: 0 | S7: 0 | T7: 0 | U7: 0 | V7: 0 | W7: 0 | X7: 0 | Y7: 0 | Z7: 0 | AA7: 0 | AB7: 0 | AC7: 0 | AD7: 0 | AE7: 0.127905 | AF7: 3.988982 | AH7: =K7 -> 2.300335 | AI7: =Y7 -> 0 | AJ7: =Z7 -> 0 | AK7: =AA7 -> 0 | AL7: =AB7 -> 0 | AM7: =AC7 -> 0 | AN7: =AD7 -> 0 | AR7: =A7 -> 39629 | AS7: =K7-$K$2 -> 0.525274 | AT7: =AI7 -> 0 | AU7: =AJ7 -> 0 | AV7: =AK7 -> 0 | AW7: =AL7 -> 0 | AX7: =AM7 -> 0 | AY7: =AN7 -> 0 | AZ7: =SUM(AS7:AY7) -> 0.525274 | BA7: =AR7 -> 39629 | BB7: =AS7 -> 0.525274 | BC7: =#REF! -> #REF!
A8: 39721 | B8: -0.803735 | C8: -0.204005 | D8: -0.525792 | E8: -0.378095 | F8: 0.327156 | G8: 1.437107 | H8: 0.049769 | I8: -0.624106 | J8: 0.726019 | K8: 1.963754 | L8: 0.579939 | M8: 0 | N8: 0 | O8: 0.497677 | P8: 0 | Q8: -0.074979 | R8: 0 | S8: 0 | T8: 0 | U8: 0 | V8: 0 | W8: 0 | X8: 0 | Y8: 0 | Z8: 0 | AA8: 0 | AB8: 0 | AC8: 0 | AD8: 0 | AE8: 0.127268 | AF8: 3.097978 | AH8: =K8 -> 1.963754 | AI8: =Y8 -> 0 | AJ8: =Z8 -> 0 | AK8: =AA8 -> 0 | AL8: =AB8 -> 0 | AM8: =AC8 -> 0 | AN8: =AD8 -> 0 | AR8: =A8 -> 39721 | AS8: =K8-$K$2 -> 0.188693 | AT8: =AI8 -> 0 | AU8: =AJ8 -> 0 | AV8: =AK8 -> 0 | AW8: =AL8 -> 0 | AX8: =AM8 -> 0 | AY8: =AN8 -> 0 | AZ8: =SUM(AS8:AY8) -> 0.188693 | BA8: =AR8 -> 39721 | BB8: =AS8 -> 0.188693 | BC8: =#REF! -> #REF!
A9: 39813 | B9: -0.216777 | C9: -0.566387 | D9: -0.876566 | E9: -1.076033 | F9: 0.163132 | G9: 1.567453 | H9: 0.777082 | I9: -0.527205 | J9: 0.776896 | K9: 1.335692 | L9: 0.325304 | M9: 0 | N9: 0 | O9: 0.562675 | P9: 0 | Q9: -0.12286 | R9: 0 | S9: 0 | T9: 0 | U9: 0 | V9: 0 | W9: 0 | X9: 0 | Y9: -0.183341 | Z9: -0.085809 | AA9: -0.014995 | AB9: -0.002568 | AC9: -0.001075 | AD9: -0.001515 | AE9: 0.126625 | AF9: 1.95973 | AH9: =K9 -> 1.335692 | AI9: =Y9 -> -0.183341 | AJ9: =Z9 -> -0.085809 | AK9: =AA9 -> -0.014995 | AL9: =AB9 -> -0.002568 | AM9: =AC9 -> -0.001075 | AN9: =AD9 -> -0.001515 | AR9: =A9 -> 39813 | AS9: =K9-$K$2 -> -0.439369 | AT9: =AI9 -> -0.183341 | AU9: =AJ9 -> -0.085809 | AV9: =AK9 -> -0.014995 | AW9: =AL9 -> -0.002568 | AX9: =AM9 -> -0.001075 | AY9: =AN9 -> -0.001515 | AZ9: =SUM(AS9:AY9) -> -0.728672 | BA9: =AR9 -> 39813 | BB9: =AS9 -> -0.439369 | BC9: =#REF! -> #REF!
A10: 39903 | B10: -0.13539 | C10: -0.652465 | D10: -0.918263 | E10: -1.444178 | F10: 0.115455 | G10: 1.523047 | H10: 0.278964 | I10: -0.403252 | J10: 0.666816 | K10: 0.39864 | L10: 0.001291 | M10: 0 | N10: 0 | O10: 0.659807 | P10: 0 | Q10: -0.152443 | R10: 0 | S10: 0 | T10: 0 | U10: 0 | V10: 0 | W10: 0 | X10: 0 | Y10: -0.401823 | Z10: -0.211334 | AA10: -0.064565 | AB10: -0.007675 | AC10: -0.009711 | AD10: -0.013463 | AE10: 0.125976 | AF10: -0.644566 | AH10: =K10 -> 0.39864 | AI10: =Y10 -> -0.401823 | AJ10: =Z10 -> -0.211334 | AK10: =AA10 -> -0.064565 | AL10: =AB10 -> -0.007675 | AM10: =AC10 -> -0.009711 | AN10: =AD10 -> -0.013463 | AR10: =A10 -> 39903 | AS10: =K10-$K$2 -> -1.376421 | AT10: =AI10 -> -0.401823 | AU10: =AJ10 -> -0.211334 | AV10: =AK10 -> -0.064565 | AW10: =AL10 -> -0.007675 | AX10: =AM10 -> -0.009711 | AY10: =AN10 -> -0.013463 | AZ10: =SUM(AS10:AY10) -> -2.084992 | BA10: =AR10 -> 39903 | BB10: =AS10 -> -1.376421 | BC10: =#REF! -> #REF!
A11: 39994 | B11: -0.073128 | C11: -0.591275 | D11: -0.825561 | E11: -1.573164 | F11: 0.099746 | G11: 1.437434 | H11: -0.355227 | I11: -0.282939 | J11: 0.843512 | K11: -0.300412 | L11: -0.18273 | M11: 0 | N11: 0 | O11: 0.645843 | P11: 0 | Q11: -0.167873 | R11: 0 | S11: 0 | T11: 0 | U11: 0 | V11: 0 | W11: 0 | X11: 0 | Y11: -0.513356 | Z11: -0.31584 | AA11: -0.139621 | AB11: -0.034101 | AC11: -0.016607 | AD11: -0.041339 | AE11: 0.125323 | AF11: -2.261316 | AH11: =K11 -> -0.300412 | AI11: =Y11 -> -0.513356 | AJ11: =Z11 -> -0.31584 | AK11: =AA11 -> -0.139621 | AL11: =AB11 -> -0.034101 | AM11: =AC11 -> -0.016607 | AN11: =AD11 -> -0.041339 | AR11: =A11 -> 39994 | AS11: =K11-$K$2 -> -2.075473 | AT11: =AI11 -> -0.513356 | AU11: =AJ11 -> -0.31584 | AV11: =AK11 -> -0.139621 | AW11: =AL11 -> -0.034101 | AX11: =AM11 -> -0.016607 | AY11: =AN11 -> -0.041339 | AZ11: =SUM(AS11:AY11) -> -3.136337 | BA11: =AR11 -> 39994 | BB11: =AS11 -> -2.075473 | BC11: =#REF! -> #REF!
A12: 40086 | B12: -0.530909 | C12: -0.264507 | D12: -0.672123 | E12: -1.502828 | F12: 0.069034 | G12: 1.196104 | H12: -0.544119 | I12: -0.181868 | J12: 0.890493 | K12: -0.568777 | L12: -0.1836 | M12: 0 | N12: 0 | O12: 0.488854 | P12: 0 | Q12: -0.20192 | R12: 0 | S12: 0 | T12: 0 | U12: 0 | V12: 0 | W12: 0 | X12: 0 | Y12: -0.432253 | Z12: -0.321221 | AA12: -0.172459 | AB12: -0.0501 | AC12: -0.020433 | AD12: -0.084043 | AE12: 0.124665 | AF12: -2.962008 | AH12: =K12 -> -0.568777 | AI12: =Y12 -> -0.432253 | AJ12: =Z12 -> -0.321221 | AK12: =AA12 -> -0.172459 | AL12: =AB12 -> -0.0501 | AM12: =AC12 -> -0.020433 | AN12: =AD12 -> -0.084043 | AR12: =A12 -> 40086 | AS12: =K12-$K$2 -> -2.343838 | AT12: =AI12 -> -0.432253 | AU12: =AJ12 -> -0.321221 | AV12: =AK12 -> -0.172459 | AW12: =AL12 -> -0.0501 | AX12: =AM12 -> -0.020433 | AY12: =AN12 -> -0.084043 | AZ12: =SUM(AS12:AY12) -> -3.424347 | BA12: =AR12 -> 40086 | BB12: =AS12 -> -2.343838 | BC12: =#REF! -> #REF!
A13: 40178 | B13: -0.252423 | C13: -0.211615 | D13: -0.555133 | E13: -1.531989 | F13: 0.034934 | G13: 0.995536 | H13: -1.034953 | I13: -0.140145 | J13: 0.907468 | K13: -1.153079 | L13: -0.07127 | M13: 0 | N13: 0 | O13: 0.293615 | P13: 0 | Q13: -0.223806 | R13: 0 | S13: 0 | T13: 0 | U13: 0 | V13: 0 | W13: 0 | X13: 0 | Y13: -0.359282 | Z13: -0.289592 | AA13: -0.227625 | AB13: -0.069279 | AC13: -0.02845 | AD13: -0.147781 | AE13: 0.124003 | AF13: -3.940867 | AH13: =K13 -> -1.153079 | AI13: =Y13 -> -0.359282 | AJ13: =Z13 -> -0.289592 | AK13: =AA13 -> -0.227625 | AL13: =AB13 -> -0.069279 | AM13: =AC13 -> -0.02845 | AN13: =AD13 -> -0.147781 | AR13: =A13 -> 40178 | AS13: =K13-$K$2 -> -2.92814 | AT13: =AI13 -> -0.359282 | AU13: =AJ13 -> -0.289592 | AV13: =AK13 -> -0.227625 | AW13: =AL13 -> -0.069279 | AX13: =AM13 -> -0.02845 | AY13: =AN13 -> -0.147781 | AZ13: =SUM(AS13:AY13) -> -4.050149 | BA13: =AR13 -> 40178 | BB13: =AS13 -> -2.92814 | BC13: =#REF! -> #REF!
... A132: 14518 | B132: -1.148526 | C132: 0.000126 | D132: -0.042684 | E132: -0.000474 | F132: 0.108311 | G132: -0.176159 | H132: 0.054637 | I132: 0.15047 | J132: 0.267182 | K132: 0.001816 | L132: 0.376325 | M132: 0 | N132: 0 | O132: 0.545399 | P132: 0 | Q132: -0.206678 | R132: 0 | S132: 0 | T132: 0 | U132: 0 | V132: 0 | W132: 0 | X132: 0 | Y132: -0.001629 | Z132: 0.001967 | AA132: -0.000549 | AB132: 0.00048 | AC132: -0.001572 | AD132: -0.004645 | AE132: 0.053434 | AF132: -0.022767 | AH132: =K132 -> 0.001816 | AI132: =Y132 -> -0.001629 | AJ132: =Z132 -> 0.001967 | AK132: =AA132 -> -0.000549 | AL132: =AB132 -> 0.00048 | AM132: =AC132 -> -0.001572 | AN132: =AD132 -> -0.004645 | AR132: =A132 -> 14518 | AS132: =K132-$K$2 -> -1.773245 | AT132: =AI132 -> -0.001629 | AU132: =AJ132 -> 0.001967 | AV132: =AK132 -> -0.000549 | AW132: =AL132 -> 0.00048 | AX132: =AM132 -> -0.001572 | AY132: =AN132 -> -0.004645 | AZ132: =SUM(AS132:AY132) -> -1.779193 | BA132: =AR132 -> 14518 | BB132: =AS132 -> -1.773245 | BC132: =#REF! -> #REF!

Sheet US_raw_policy_shocks_with_text
A1: date | B1: g_sh | C1: b_liqtil_sh | D1: b_liqp_sh | E1: b_safetil_sh | F1: b_safep_sh | G1: mu_sh | H1: z_sh | I1: lambda_f_sh | J1: lambda_w_sh | K1: rm_sh | L1: sigma_omega_sh | M1: mu_e_sh | N1: gamma_sh | O1: pi_star_sh | P1: lr_sh | Q1: zp_sh | R1: tfp_sh | S1: gdpdef_sh | T1: corepce_sh | U1: gdp_sh | V1: gdi_sh | W1: BBB_sh | X1: AAA_sh | Y1: rm_shl1 | Z1: rm_shl2 | AA1: rm_shl3 | AB1: rm_shl4 | AC1: rm_shl5 | AD1: rm_shl6 | AE1: dettrend | AF1: detrendedMean | AH1: rm_sh | AI1: =Y1 -> rm_shl1 | AJ1: =Z1 -> rm_shl2 | AK1: =AA1 -> rm_shl3 | AL1: =AB1 -> rm_shl4 | AM1: =AC1 -> rm_shl5 | AN1: =AD1 -> rm_shl6 | AQ1: Plot | AR1: =A1 -> date | AS1: Monetary Policy | AT1: FG1 | AU1: FG2 | AV1: FG3 | AW1: FG4 | AX1: FG5 | AY1: FG6 | AZ1: Combined | BA1: date | BB1: rm_sh | BC1: Fgsum
A2: 39172 | AH2: =K2 -> 0 | AI2: =Y2 -> 0 | AJ2: =Z2 -> 0 | AK2: =AA2 -> 0 | AL2: =AB2 -> 0 | AM2: =AC2 -> 0 | AN2: =AD2 -> 0 | AR2: =A2 -> 39172 | AS2: =Raw_Policy_Shocks!D190 -> -0.18811826 | AT2: =Raw_Policy_Shocks!E190 -> 1.2188572e-15 | AU2: =Raw_Policy_Shocks!F190 -> 6.5675434e-16 | AV2: =Raw_Policy_Shocks!G190 -> 1.1229232e-15 | AW2: =Raw_Policy_Shocks!H190 -> 8.4365608e-16 | AX2: =Raw_Policy_Shocks!I190 -> 5.6591939e-16 | AY2: =Raw_Policy_Shocks!J190 -> 1.7357586e-17 | AZ2: =SUM(AS2:AY2) -> -0.18811826 | BA2: =AR2 -> 39172 | BB2: =AS2 -> -0.18811826 | BC2: =#REF! -> #REF!
A3: 39263 | AH3: =K3 -> 0 | AI3: =Y3 -> 0 | AJ3: =Z3 -> 0 | AK3: =AA3 -> 0 | AL3: =AB3 -> 0 | AM3: =AC3 -> 0 | AN3: =AD3 -> 0 | AR3: =A3 -> 39263 | AS3: =Raw_Policy_Shocks!D191 -> 0.088413341 | AT3: =Raw_Policy_Shocks!E191 -> 1.0668508e-15 | AU3: =Raw_Policy_Shocks!F191 -> 4.1596599e-16 | AV3: =Raw_Policy_Shocks!G191 -> 9.2366684e-16 | AW3: =Raw_Policy_Shocks!H191 -> 6.4979925e-16 | AX3: =Raw_Policy_Shocks!I191 -> 4.0467114e-16 | AY3: =Raw_Policy_Shocks!J191 -> -3.0146913e-17 | AZ3: =SUM(AS3:AY3) -> 0.088413341 | BA3: =AR3 -> 39263 | BB3: =AS3 -> 0.088413341 | BC3: =#REF! -> #REF!
A4: 39355 | AH4: =K4 -> 0 | AI4: =Y4 -> 0 | AJ4: =Z4 -> 0 | AK4: =AA4 -> 0 | AL4: =AB4 -> 0 | AM4: =AC4 -> 0 | AN4: =AD4 -> 0 | AR4: =A4 -> 39355 | AS4: =Raw_Policy_Shocks!D192 -> -0.083222004 | AT4: =Raw_Policy_Shocks!E192 -> 9.6364217e-16 | AU4: =Raw_Policy_Shocks!F192 -> 4.4199236e-16 | AV4: =Raw_Policy_Shocks!G192 -> 9.0270424e-16 | AW4: =Raw_Policy_Shocks!H192 -> 6.0202352e-16 | AX4: =Raw_Policy_Shocks!I192 -> 4.2637017e-16 | AY4: =Raw_Policy_Shocks!J192 -> 9.310451e-19 | AZ4: =SUM(AS4:AY4) -> -0.083222004 | BA4: =AR4 -> 39355 | BB4: =AS4 -> -0.083222004 | BC4: =#REF! -> #REF!
A5: 39447 | AH5: =K5 -> 0 | AI5: =Y5 -> 0 | AJ5: =Z5 -> 0 | AK5: =AA5 -> 0 | AL5: =AB5 -> 0 | AM5: =AC5 -> 0 | AN5: =AD5 -> 0 | AR5: =A5 -> 39447 | AS5: =Raw_Policy_Shocks!D193 -> -0.27201267 | AT5: =Raw_Policy_Shocks!E193 -> 9.3987567e-16 | AU5: =Raw_Policy_Shocks!F193 -> 5.1277387e-16 | AV5: =Raw_Policy_Shocks!G193 -> 8.4776194e-16 | AW5: =Raw_Policy_Shocks!H193 -> 6.249558e-16 | AX5: =Raw_Policy_Shocks!I193 -> 4.56534e-16 | AY5: =Raw_Policy_Shocks!J193 -> 3.4740652e-17 | AZ5: =SUM(AS5:AY5) -> -0.27201267 | BA5: =AR5 -> 39447 | BB5: =AS5 -> -0.27201267 | BC5: =#REF! -> #REF!
A6: 39538 | AH6: =K6 -> 0 | AI6: =Y6 -> 0 | AJ6: =Z6 -> 0 | AK6: =AA6 -> 0 | AL6: =AB6 -> 0 | AM6: =AC6 -> 0 | AN6: =AD6 -> 0 | AR6: =A6 -> 39538 | AS6: =Raw_Policy_Shocks!D194 -> -0.2693945 | AT6: =Raw_Policy_Shocks!E194 -> 9.3046474e-16 | AU6: =Raw_Policy_Shocks!F194 -> 4.6942962e-16 | AV6: =Raw_Policy_Shocks!G194 -> 7.9036322e-16 | AW6: =Raw_Policy_Shocks!H194 -> 5.6280671e-16 | AX6: =Raw_Policy_Shocks!I194 -> 3.8010689e-16 | AY6: =Raw_Policy_Shocks!J194 -> -1.4116953e-17 | AZ6: =SUM(AS6:AY6) -> -0.2693945 | BA6: =AR6 -> 39538 | BB6: =AS6 -> -0.2693945 | BC6: =#REF! -> #REF!
A7: 39629 | AH7: =K7 -> 0 | AI7: =Y7 -> 0 | AJ7: =Z7 -> 0 | AK7: =AA7 -> 0 | AL7: =AB7 -> 0 | AM7: =AC7 -> 0 | AN7: =AD7 -> 0 | AR7: =A7 -> 39629 | AS7: =Raw_Policy_Shocks!D195 -> -0.27516616 | AT7: =Raw_Policy_Shocks!E195 -> 7.7487379e-16 | AU7: =Raw_Policy_Shocks!F195 -> 4.021111e-16 | AV7: =Raw_Policy_Shocks!G195 -> 6.2916928e-16 | AW7: =Raw_Policy_Shocks!H195 -> 4.2157941e-16 | AX7: =Raw_Policy_Shocks!I195 -> 2.9293807e-16 | AY7: =Raw_Policy_Shocks!J195 -> -1.3472247e-17 | AZ7: =SUM(AS7:AY7) -> -0.27516616 | BA7: =AR7 -> 39629 | BB7: =AS7 -> -0.27516616 | BC7: =#REF! -> #REF!
A8: 39721 | AH8: =K8 -> 0 | AI8: =Y8 -> 0 | AJ8: =Z8 -> 0 | AK8: =AA8 -> 0 | AL8: =AB8 -> 0 | AM8: =AC8 -> 0 | AN8: =AD8 -> 0 | AR8: =A8 -> 39721 | AS8: =Raw_Policy_Shocks!D196 -> 0.19039529 | AT8: =Raw_Policy_Shocks!E196 -> 6.5796782e-16 | AU8: =Raw_Policy_Shocks!F196 -> 2.3303881e-16 | AV8: =Raw_Policy_Shocks!G196 -> 4.5168418e-16 | AW8: =Raw_Policy_Shocks!H196 -> 2.454091e-16 | AX8: =Raw_Policy_Shocks!I196 -> 1.8695887e-16 | AY8: =Raw_Policy_Shocks!J196 -> -9.7844569e-17 | AZ8: =SUM(AS8:AY8) -> 0.19039529 | BA8: =AR8 -> 39721 | BB8: =AS8 -> 0.19039529 | BC8: =#REF! -> #REF!
A9: 39813 | AH9: =K9 -> 0 | AI9: =Y9 -> 0 | AJ9: =Z9 -> 0 | AK9: =AA9 -> 0 | AL9: =AB9 -> 0 | AM9: =AC9 -> 0 | AN9: =AD9 -> 0 | AR9: =A9 -> 39813 | AS9: =Raw_Policy_Shocks!D197 -> 0.30134678 | AT9: =Raw_Policy_Shocks!E197 -> 0.1655123 | AU9: =Raw_Policy_Shocks!F197 -> 0.097415961 | AV9: =Raw_Policy_Shocks!G197 -> 0.022317107 | AW9: =Raw_Policy_Shocks!H197 -> 0.0052221681 | AX9: =Raw_Policy_Shocks!I197 -> 0.0031178032 | AY9: =Raw_Policy_Shocks!J197 -> 0.0065551145 | AZ9: =SUM(AS9:AY9) -> 0.60148724 | BA9: =AR9 -> 39813 | BB9: =AS9 -> 0.30134678 | BC9: =#REF! -> #REF!
A10: 39903 | AH10: =K10 -> 0 | AI10: =Y10 -> 0 | AJ10: =Z10 -> 0 | AK10: =AA10 -> 0 | AL10: =AB10 -> 0 | AM10: =AC10 -> 0 | AN10: =AD10 -> 0 | AR10: =A10 -> 39903 | AS10: =Raw_Policy_Shocks!D198 -> 0.6520254 | AT10: =Raw_Policy_Shocks!E198 -> 0.17614487 | AU10: =Raw_Policy_Shocks!F198 -> 0.089707506 | AV10: =Raw_Policy_Shocks!G198 -> 0.060666553 | AW10: =Raw_Policy_Shocks!H198 -> 0.0089712352 | AX10: =Raw_Policy_Shocks!I198 -> 0.028768845 | AY10: =Raw_Policy_Shocks!J198 -> 0.045538504 | AZ10: =SUM(AS10:AY10) -> 1.0618229 | BA10: =AR10 -> 39903 | BB10: =AS10 -> 0.6520254 | BC10: =#REF! -> #REF!
A11: 39994 | AH11: =K11 -> 0 | AI11: =Y11 -> 0 | AJ11: =Z11 -> 0 | AK11: =AA11 -> 0 | AL11: =AB11 -> 0 | AM11: =AC11 -> 0 | AN11: =AD11 -> 0 | AR11: =A11 -> 39994 | AS11: =Raw_Policy_Shocks!D199 -> 0.49367955 | AT11: =Raw_Policy_Shocks!E199 -> 0.088592728 | AU11: =Raw_Policy_Shocks!F199 -> 0.061974169 | AV11: =Raw_Policy_Shocks!G199 -> 0.05771283 | AW11: =Raw_Policy_Shocks!H199 -> 0.072781563 | AX11: =Raw_Policy_Shocks!I199 -> 0.04221117 | AY11: =Raw_Policy_Shocks!J199 -> 0.070445846 | AZ11: =SUM(AS11:AY11) -> 0.88739786 | BA11: =AR11 -> 39994 | BB11: =AS11 -> 0.49367955 | BC11: =#REF! -> #REF!
A12: 40086 | AH12: =K12 -> 0 | AI12: =Y12 -> 0 | AJ12: =Z12 -> 0 | AK12: =AA12 -> 0 | AL12: =AB12 -> 0 | AM12: =AC12 -> 0 | AN12: =AD12 -> 0 | AR12: =A12 -> 40086 | AS12: =Raw_Policy_Shocks!D200 -> 0.1642813 | AT12: =Raw_Policy_Shocks!E200 -> -0.034531184 | AU12: =Raw_Policy_Shocks!F200 -> -0.0049958817 | AV12: =Raw_Policy_Shocks!G200 -> 0.021215259 | AW12: =Raw_Policy_Shocks!H200 -> 0.026351763 | AX12: =Raw_Policy_Shocks!I200 -> 0.058693995 | AY12: =Raw_Policy_Shocks!J200 -> 0.058620331 | AZ12: =SUM(AS12:AY12) -> 0.28963558 | BA12: =AR12 -> 40086 | BB12: =AS12 -> 0.1642813 | BC12: =#REF! -> #REF!
A13: 40178 | AH13: =K13 -> 0 | AI13: =Y13 -> 0 | AJ13: =Z13 -> 0 | AK13: =AA13 -> 0 | AL13: =AB13 -> 0 | AM13: =AC13 -> 0 | AN13: =AD13 -> 0 | AR13: =A13 -> 40178 | AS13: =Raw_Policy_Shocks!D201 -> 0.36668055 | AT13: =Raw_Policy_Shocks!E201 -> 0.015206857 | AU13: =Raw_Policy_Shocks!F201 -> 0.021178897 | AV13: =Raw_Policy_Shocks!G201 -> 0.064780453 | AW13: =Raw_Policy_Shocks!H201 -> 0.061512326 | AX13: =Raw_Policy_Shocks!I201 -> 0.066057217 | AY13: =Raw_Policy_Shocks!J201 -> 0.067894049 | AZ13: =SUM(AS13:AY13) -> 0.66331034 | BA13: =AR13 -> 40178 | BB13: =AS13 -> 0.36668055 | BC13: =#REF! -> #REF!
... A132: 51043 | AH132: =K132 -> 0 | AI132: =Y132 -> 0 | AJ132: =Z132 -> 0 | AK132: =AA132 -> 0 | AL132: =AB132 -> 0 | AM132: =AC132 -> 0 | AN132: =AD132 -> 0 | AR132: =A132 -> 51043 | AS132: =Raw_Policy_Shocks!D320 -> 0 | AT132: =Raw_Policy_Shocks!E320 -> 0 | AU132: =Raw_Policy_Shocks!F320 -> 0 | AV132: =Raw_Policy_Shocks!G320 -> 0 | AW132: =Raw_Policy_Shocks!H320 -> 0 | AX132: =Raw_Policy_Shocks!I320 -> 0 | AY132: =Raw_Policy_Shocks!J320 -> 0 | AZ132: =SUM(AS132:AY132) -> 0 | BA132: =AR132 -> 51043 | BB132: =AS132 -> 0 | BC132: =#REF! -> #REF!

Sheet Output gap
A1: date | B1: DSGE Output (with FG) | C1: DSGE Output (without FG) | D1: IMF US Output Gap | M1: April 2025 WEO
A2: 22006 | B2: -0.95554787 | C2: -1.0133122 | L2: Quadratic match average
A3: 22097 | B3: -0.77493967 | C3: -0.83453005 | H3: USA_GAP | I3: EUR_GAP | L3: Euro area | M3: A163NGAP@IMFWEO
A4: 22189 | B4: -1.3410108 | C4: -1.4025888 | G4: 1q90 | H4: 3.5299375 | L4: USA | M4: A111NGAP@IMFWEO
A5: 22281 | B5: -1.7704944 | C5: -1.8342202 | G5: 2q90 | H5: 2.2035625
A6: 22371 | B6: -2.1755252 | C6: -2.2415621 | G6: 3q90 | H6: 1.0878125
A7: 22462 | B7: -2.5765202 | C7: -2.6450372 | G7: 4q90 | H7: 0.1826875
A8: 22554 | B8: -2.1053075 | C8: -2.176481 | G8: 1q91 | H8: -0.5118125 | I8: 1.716375
A9: 22646 | B9: -1.3711194 | C9: -1.4451345 | G9: 2q91 | H9: -0.9956875 | I9: 1.955125
A10: 22736 | B10: -0.91914985 | C10: -0.99620117 | G10: 3q91 | H10: -1.2689375 | I10: 2.042375
A11: 22827 | B11: -0.41658832 | C11: -0.49688172 | G11: 4q91 | H11: -1.3315625 | I11: 1.978125
A12: 22919 | B12: -0.53803931 | C12: -0.62179295 | G12: 1q92 | H12: -0.52590625 | I12: 1.762375
A13: 23011 | B13: -0.75769977 | C13: -0.84514585 | G13: 2q92 | H13: -0.43034375 | I13: 1.395125
A14: 23101 | B14: -0.43614086 | C14: -0.52752816 | G14: 3q92 | H14: -0.38721875 | I14: 0.876375
A15: 23192 | B15: 0.14427662 | C15: 0.048678175 | G15: 4q92 | H15: -0.39653125 | I15: 0.206125
A16: 23284 | B16: 0.25229055 | C16: 0.15218035 | G16: 1q93 | H16: -0.7578125 | I16: -1.6007812
A17: 23376 | B17: 0.83271936 | C17: 0.72774971 | G17: 2q93 | H17: -0.7521875 | I17: -2.1799687
A18: 23467 | B18: 1.3316132 | C18: 1.2214859 | G18: 3q93 | H18: -0.6791875 | I18: -2.5165937
A19: 23558 | B19: 2.5723481 | C19: 2.461226 | G19: 4q93 | H19: -0.5388125 | I19: -2.6106562
... A121: 32873 | B121: 6.0340534 | C121: 5.8667883 | G121: 2q19 | H121: 1.5348125 | I121: 0.96390625
A122: 32963 | B122: 6.8705373 | C122: 6.7027136 | D122: =+H4 -> 3.5299375 | G122: 3q19 | H122: 1.0630625 | I122: 0.28803125
A123: 33054 | B123: 6.280941 | C123: 6.112545 | D123: =+H5 -> 2.2035625 | G123: 4q19 | H123: 0.3034375 | I123: -0.76378125
A124: 33146 | B124: 5.5667705 | C124: 5.3977941 | D124: =+H6 -> 1.0878125 | G124: 1q20 | H124: -2.6345312 | I124: -4.5991875
A125: 33238 | B125: 5.1993069 | C125: 5.0297402 | D125: =+H7 -> 0.1826875 | G125: 2q20 | H125: -3.2137187 | I125: -5.4398125
A126: 33328 | B126: 4.2371894 | C126: 4.0670155 | D126: =+H8 -> -0.5118125 | G126: 3q20 | H126: -3.3245937 | I126: -5.6933125
A127: 33419 | B127: 3.9222969 | C127: 3.7514998 | D127: =+H9 -> -0.9956875 | G127: 4q20 | H127: -2.9671562 | I127: -5.3596875
A128: 33511 | B128: 3.5825915 | C128: 3.4111605 | D128: =+H10 -> -1.2689375 | G128: 1q21 | H128: -0.45953125 | I128: -2.7456563
A129: 33603 | B129: 3.3717869 | C129: 3.1997095 | D129: =+H11 -> -1.3315625 | G129: 2q21 | H129: 0.16178125 | I129: -1.9150938
A130: 33694 | B130: 3.1960304 | C130: 3.0232866 | D130: =+H12 -> -0.52590625 | G130: 3q21 | H130: 0.57865625 | I130: -1.1747188
A131: 33785 | B131: 3.7963096 | C131: 3.6228833 | D131: =+H13 -> -0.43034375 | G131: 4q21 | H131: 0.79109375 | I131: -0.52453125
A132: 33877 | B132: 3.477792 | C132: 3.3036662 | D132: =+H14 -> -0.38721875 | G132: 1q22 | H132: 0.23096875 | I132: 0.2503125
A133: 33969 | B133: 3.0951273 | C133: 2.9202842 | D133: =+H15 -> -0.39653125 | G133: 2q22 | H133: 0.26178125 | I133: 0.6341875
... A147: 35246 | B147: 4.9250567 | C147: 4.7378113 | D147: =+H29 -> -0.10378125 | G147: 4q25 | H147: 0.1316875 | I147: -0.51096875
A148: 35338 | B148: 5.6935429 | C148: 5.5052007 | D148: =+H30 -> 0.04909375
A149: 35430 | B149: 5.847328 | C149: 5.657854 | D149: =+H31 -> 0.23265625
A150: 35520 | B150: 6.0959873 | C150: 5.905345 | D150: =+H32 -> 0.52940625
A151: 35611 | B151: 6.7051118 | C151: 6.5132631 | D151: =+H33 -> 0.74134375
A152: 35703 | B152: 7.0860154 | C152: 6.8929204 | D152: =+H34 -> 0.95096875
A153: 35795 | B153: 7.275514 | C153: 7.0811309 | D153: =+H35 -> 1.1582812
A154: 35885 | B154: 6.9437528 | C154: 6.748038 | D154: =+H36 -> 1.3128125
A155: 35976 | B155: 6.6814462 | C155: 6.4843539 | D155: =+H37 -> 1.5356875
A156: 36068 | B156: 6.5838887 | C156: 6.385371 | D156: =+H38 -> 1.7764375
A157: 36160 | B157: 7.0682737 | C157: 6.8682802 | D157: =+H39 -> 2.0350625
A158: 36250 | B158: 6.9433983 | C158: 6.7418763 | D158: =+H40 -> 2.44
A159: 36341 | B159: 6.8475731 | C159: 6.6444671 | D159: =+H41 -> 2.683
... A260: 45565 | B260: -3.0267119 | C260: -2.6846562 | D260: =+H142 -> 1.0385625

Sheet Raw_Policy_Shocks
A1: date | C1: Date | D1: Monetary Policy | E1: FG1 | F1: FG2 | G1: FG3 | H1: FG4 | I1: FG5 | J1: FG6 | V1: Date | W1: Monetary Policy | X1: FG1 | Y1: FG2 | Z1: FG3 | AA1: FG4 | AB1: FG5 | AC1: FG6
A2: 22006 | D2: 0.048357662 | E2: -8.4068543e-16 | F2: -4.2048782e-16 | G2: -6.4617747e-16 | H2: -5.5875797e-16 | I2: -4.9970092e-16 | J2: 7.0593767e-17 | W2: 0.048357662 | X2: -8.4068543e-16 | Y2: -4.2048782e-16 | Z2: -6.4617747e-16 | AA2: -5.5875797e-16 | AB2: -4.9970092e-16 | AC2: 7.0593767e-17
A3: 22097 | D3: -0.2231241 | E3: -5.2733171e-16 | F3: -3.2043497e-16 | G3: -2.4090042e-16 | H3: -3.3838682e-16 | I3: -2.5232413e-16 | J3: 5.264955e-17 | W3: -0.2231241 | X3: -5.2733171e-16 | Y3: -3.2043497e-16 | Z3: -2.4090042e-16 | AA3: -3.3838682e-16 | AB3: -2.5232413e-16 | AC3: 5.264955e-17
A4: 22189 | D4: 0.075637485 | E4: -8.0935265e-16 | F4: -1.2405042e-16 | G4: -4.7799048e-16 | H4: -4.2189401e-16 | I4: -5.72672e-16 | J4: -6.3675629e-17 | W4: 0.075637485 | X4: -8.0935265e-16 | Y4: -1.2405042e-16 | Z4: -4.7799048e-16 | AA4: -4.2189401e-16 | AB4: -5.72672e-16 | AC4: -6.3675629e-17
A5: 22281 | D5: -0.077487568 | E5: -5.4165425e-16 | F5: -1.9002362e-16 | G5: -5.1163579e-16 | H5: -6.6075174e-16 | I5: -6.533805e-16 | J5: -1.1237991e-17 | W5: -0.077487568 | X5: -5.4165425e-16 | Y5: -1.9002362e-16 | Z5: -5.1163579e-16 | AA5: -6.6075174e-16 | AB5: -6.533805e-16 | AC5: -1.1237991e-17
A6: 22371 | D6: 0.10317668 | E6: -6.8909812e-16 | F6: -3.1242252e-16 | G6: -7.5536264e-16 | H6: -7.8964395e-16 | I6: -6.2234844e-16 | J6: -3.0956983e-17 | W6: 0.10317668 | X6: -6.8909812e-16 | Y6: -3.1242252e-16 | Z6: -7.5536264e-16 | AA6: -7.8964395e-16 | AB6: -6.2234844e-16 | AC6: -3.0956983e-17
A7: 22462 | D7: -0.049991598 | E7: -9.3206099e-16 | F7: -5.6817847e-16 | G7: -9.8985752e-16 | H7: -7.8202188e-16 | I7: -6.2306294e-16 | J7: 4.7434832e-17 | W7: -0.049991598 | X7: -9.3206099e-16 | Y7: -5.6817847e-16 | Z7: -9.8985752e-16 | AA7: -7.8202188e-16 | AB7: -6.2306294e-16 | AC7: 4.7434832e-17
A8: 22554 | D8: -0.057027306 | E8: -1.1371771e-15 | F8: -7.9095169e-16 | G8: -9.4878632e-16 | H8: -7.9647094e-16 | I8: -5.9795176e-16 | J8: 8.9597079e-19 | W8: -0.057027306 | X8: -1.1371771e-15 | Y8: -7.9095169e-16 | Z8: -9.4878632e-16 | AA8: -7.9647094e-16 | AB8: -5.9795176e-16 | AC8: 8.9597079e-19
A9: 22646 | D9: -0.11829278 | E9: -1.3118713e-15 | F9: -7.1735177e-16 | G9: -8.6551815e-16 | H9: -6.7990282e-16 | I9: -5.5352089e-16 | J9: 6.38188e-17 | W9: -0.11829278 | X9: -1.3118713e-15 | Y9: -7.1735177e-16 | Z9: -8.6551815e-16 | AA9: -6.7990282e-16 | AB9: -5.5352089e-16 | AC9: 6.38188e-17
A10: 22736 | D10: -0.154107 | E10: -1.1593355e-15 | F10: -5.8604023e-16 | G10: -6.8406629e-16 | H10: -6.2309143e-16 | I10: -5.2022779e-16 | J10: 2.3731922e-17 | W10: -0.154107 | X10: -1.1593355e-15 | Y10: -5.8604023e-16 | Z10: -6.8406629e-16 | AA10: -6.2309143e-16 | AB10: -5.2022779e-16 | AC10: 2.3731922e-17
A11: 22827 | D11: -0.21772283 | E11: -1.0458337e-15 | F11: -3.9661106e-16 | G11: -6.6910305e-16 | H11: -5.7468463e-16 | I11: -5.7478654e-16 | J11: 4.0601355e-17 | W11: -0.21772283 | X11: -1.0458337e-15 | Y11: -3.9661106e-16 | Z11: -6.6910305e-16 | AA11: -5.7468463e-16 | AB11: -5.7478654e-16 | AC11: 4.0601355e-17
A12: 22919 | D12: 0.030005588 | E12: -8.905318e-16 | F12: -4.6976474e-16 | G12: -6.0086767e-16 | H12: -6.6342271e-16 | I12: -5.798935e-16 | J12: -1.0042581e-17 | W12: 0.030005588 | X12: -8.905318e-16 | Y12: -4.6976474e-16 | Z12: -6.0086767e-16 | AA12: -6.6342271e-16 | AB12: -5.798935e-16 | AC12: -1.0042581e-17
A13: 23011 | D13: -0.038033335 | E13: -9.9418157e-16 | F13: -2.5330516e-16 | G13: -6.5562595e-16 | H13: -6.2446542e-16 | I13: -6.0818643e-16 | J13: 2.7667141e-17 | W13: -0.038033335 | X13: -9.9418157e-16 | Y13: -2.5330516e-16 | Z13: -6.5562595e-16 | AA13: -6.2446542e-16 | AB13: -6.0818643e-16 | AC13: 2.7667141e-17
... A189: 39082 | D189: -0.23645943 | E189: 1.1015954e-15 | F189: 5.3723538e-16 | G189: 1.1468443e-15 | H189: 7.866539e-16 | I189: 5.5634109e-16 | J189: 5.5885972e-17 | W189: -0.23645943 | X189: 1.1015954e-15 | Y189: 5.3723538e-16 | Z189: 1.1468443e-15 | AA189: 7.866539e-16 | AB189: 5.5634109e-16 | AC189: 5.5885972e-17
A190: 39172 | B190: 1q07 | C190: ="20"&RIGHT(B190,2)&"Q"&LEFT(B190,1) -> 2007Q1 | D190: -0.18811826 | E190: 1.2188572e-15 | F190: 6.5675434e-16 | G190: 1.1229232e-15 | H190: 8.4365608e-16 | I190: 5.6591939e-16 | J190: 1.7357586e-17 | W190: -0.18811826 | X190: 1.2188572e-15 | Y190: 6.5675434e-16 | Z190: 1.1229232e-15 | AA190: 8.4365608e-16 | AB190: 5.6591939e-16 | AC190: 1.7357586e-17
A191: 39263 | B191: 2q07 | C191: ="20"&RIGHT(B191,2)&"Q"&LEFT(B191,1) -> 2007Q2 | D191: 0.088413341 | E191: 1.0668508e-15 | F191: 4.1596599e-16 | G191: 9.2366684e-16 | H191: 6.4979925e-16 | I191: 4.0467114e-16 | J191: -3.0146913e-17 | W191: 0.088413341 | X191: 1.0668508e-15 | Y191: 4.1596599e-16 | Z191: 9.2366684e-16 | AA191: 6.4979925e-16 | AB191: 4.0467114e-16 | AC191: -3.0146913e-17
A192: 39355 | B192: 3q07 | C192: ="20"&RIGHT(B192,2)&"Q"&LEFT(B192,1) -> 2007Q3 | D192: -0.083222004 | E192: 9.6364217e-16 | F192: 4.4199236e-16 | G192: 9.0270424e-16 | H192: 6.0202352e-16 | I192: 4.2637017e-16 | J192: 9.310451e-19 | W192: -0.083222004 | X192: 9.6364217e-16 | Y192: 4.4199236e-16 | Z192: 9.0270424e-16 | AA192: 6.0202352e-16 | AB192: 4.2637017e-16 | AC192: 9.310451e-19
A193: 39447 | B193: 4q07 | C193: ="20"&RIGHT(B193,2)&"Q"&LEFT(B193,1) -> 2007Q4 | D193: -0.27201267 | E193: 9.3987567e-16 | F193: 5.1277387e-16 | G193: 8.4776194e-16 | H193: 6.249558e-16 | I193: 4.56534e-16 | J193: 3.4740652e-17 | V193: =LEFT(C193,4)+1 -> 2008 | W193: -0.27201267 | X193: 9.3987567e-16 | Y193: 5.1277387e-16 | Z193: 8.4776194e-16 | AA193: 6.249558e-16 | AB193: 4.56534e-16 | AC193: 3.4740652e-17
A194: 39538 | B194: 1q08 | C194: ="20"&RIGHT(B194,2)&"Q"&LEFT(B194,1) -> 2008Q1 | D194: -0.2693945 | E194: 9.3046474e-16 | F194: 4.6942962e-16 | G194: 7.9036322e-16 | H194: 5.6280671e-16 | I194: 3.8010689e-16 | J194: -1.4116953e-17 | V194: =LEFT(C194,4)+1 -> 2009 | W194: -0.2693945 | X194: 9.3046474e-16 | Y194: 4.6942962e-16 | Z194: 7.9036322e-16 | AA194: 5.6280671e-16 | AB194: 3.8010689e-16 | AC194: -1.4116953e-17
A195: 39629 | B195: 2q08 | C195: ="20"&RIGHT(B195,2)&"Q"&LEFT(B195,1) -> 2008Q2 | D195: -0.27516616 | E195: 7.7487379e-16 | F195: 4.021111e-16 | G195: 6.2916928e-16 | H195: 4.2157941e-16 | I195: 2.9293807e-16 | J195: -1.3472247e-17 | V195: =LEFT(C195,4)+1 -> 2009 | W195: -0.27516616 | X195: 7.7487379e-16 | Y195: 4.021111e-16 | Z195: 6.2916928e-16 | AA195: 4.2157941e-16 | AB195: 2.9293807e-16 | AC195: -1.3472247e-17
A196: 39721 | B196: 3q08 | C196: ="20"&RIGHT(B196,2)&"Q"&LEFT(B196,1) -> 2008Q3 | D196: 0.19039529 | E196: 6.5796782e-16 | F196: 2.3303881e-16 | G196: 4.5168418e-16 | H196: 2.454091e-16 | I196: 1.8695887e-16 | J196: -9.7844569e-17 | V196: =LEFT(C196,4)+1 -> 2009 | W196: 0.19039529 | X196: 6.5796782e-16 | Y196: 2.3303881e-16 | Z196: 4.5168418e-16 | AA196: 2.454091e-16 | AB196: 1.8695887e-16 | AC196: -9.7844569e-17
A197: 39813 | B197: 4q08 | C197: ="20"&RIGHT(B197,2)&"Q"&LEFT(B197,1) -> 2008Q4 | D197: 0.30134678 | E197: 0.1655123 | F197: 0.097415961 | G197: 0.022317107 | H197: 0.0052221681 | I197: 0.0031178032 | J197: 0.0065551145 | V197: =LEFT(C197,4)+1 -> 2009 | W197: 0.30134678 | X197: 0.1655123 | Y197: 0.097415961 | Z197: 0.022317107 | AA197: 0.0052221681 | AB197: 0.0031178032 | AC197: 0.0065551145
A198: 39903 | B198: 1q09 | C198: ="20"&RIGHT(B198,2)&"Q"&LEFT(B198,1) -> 2009Q1 | D198: 0.6520254 | E198: 0.17614487 | F198: 0.089707506 | G198: 0.060666553 | H198: 0.0089712352 | I198: 0.028768845 | J198: 0.045538504 | V198: =LEFT(C198,4)+1 -> 2010 | W198: 0.6520254 | X198: 0.17614487 | Y198: 0.089707506 | Z198: 0.060666553 | AA198: 0.0089712352 | AB198: 0.028768845 | AC198: 0.045538504
A199: 39994 | B199: 2q09 | C199: ="20"&RIGHT(B199,2)&"Q"&LEFT(B199,1) -> 2009Q2 | D199: 0.49367955 | E199: 0.088592728 | F199: 0.061974169 | G199: 0.05771283 | H199: 0.072781563 | I199: 0.04221117 | J199: 0.070445846 | V199: =LEFT(C199,4)+1 -> 2010 | W199: 0.49367955 | X199: 0.088592728 | Y199: 0.061974169 | Z199: 0.05771283 | AA199: 0.072781563 | AB199: 0.04221117 | AC199: 0.070445846
A200: 40086 | B200: 3q09 | C200: ="20"&RIGHT(B200,2)&"Q"&LEFT(B200,1) -> 2009Q3 | D200: 0.1642813 | E200: -0.034531184 | F200: -0.0049958817 | G200: 0.021215259 | H200: 0.026351763 | I200: 0.058693995 | J200: 0.058620331 | V200: =LEFT(C200,4)+1 -> 2010 | W200: 0.1642813 | X200: -0.034531184 | Y200: -0.0049958817 | Z200: 0.021215259 | AA200: 0.026351763 | AB200: 0.058693995 | AC200: 0.058620331
A201: 40178 | B201: 4q09 | C201: ="20"&RIGHT(B201,2)&"Q"&LEFT(B201,1) -> 2009Q4 | D201: 0.36668055 | E201: 0.015206857 | F201: 0.021178897 | G201: 0.064780453 | H201: 0.061512326 | I201: 0.066057217 | J201: 0.067894049 | V201: =LEFT(C201,4)+1 -> 2010 | W201: 0.36668055 | X201: 0.015206857 | Y201: 0.021178897 | Z201: 0.064780453 | AA201: 0.061512326 | AB201: 0.066057217 | AC201: 0.067894049
A202: 40268 | B202: 1q10 | C202: ="20"&RIGHT(B202,2)&"Q"&LEFT(B202,1) -> 2010Q1 | D202: 0.19692972 | E202: -0.0062025481 | F202: 0.018850957 | G202: 0.011805778 | H202: 0.039927015 | I202: 0.039010131 | J202: 0.065925896 | V202: =LEFT(C202,4)+1 -> 2011 | W202: 0.19692972 | X202: -0.0062025481 | Y202: 0.018850957 | Z202: 0.011805778 | AA202: 0.039927015 | AB202: 0.039010131 | AC202: 0.065925896
A203: 40359 | B203: 2q10 | C203: ="20"&RIGHT(B203,2)&"Q"&LEFT(B203,1) -> 2010Q2 | D203: -0.056527465 | E203: -0.084072686 | F203: -0.059342428 | G203: -0.057235519 | H203: -0.048283985 | I203: -0.038067399 | J203: -0.0029027201 | V203: =LEFT(C203,4)+1 -> 2011 | W203: -0.056527465 | X203: -0.084072686 | Y203: -0.059342428 | Z203: -0.057235519 | AA203: -0.048283985 | AB203: -0.038067399 | AC203: -0.0029027201
A204: 40451 | B204: 3q10 | C204: ="20"&RIGHT(B204,2)&"Q"&LEFT(B204,1) -> 2010Q3 | D204: 0.064275364 | E204: -0.026918037 | F204: -0.041940821 | G204: -0.04783042 | H204: -0.023417748 | I204: -0.024988327 | J204: -0.020801704 | V204: =LEFT(C204,4)+1 -> 2011 | W204: 0.064275364 | X204: -0.026918037 | Y204: -0.041940821 | Z204: -0.04783042 | AA204: -0.023417748 | AB204: -0.024988327 | AC204: -0.020801704
... A260: 45565 | B260: 3q24 | C260: ="20"&RIGHT(B260,2)&"Q"&LEFT(B260,1) -> 2024Q3 | D260: 0.20977583 | E260: -0.045422748 | F260: -0.058002755 | G260: -0.091669277 | H260: -0.056046769 | I260: -0.030443384 | J260: -0.01180571 | V260: =LEFT(C260,4)+1 -> 2025 | W260: 0.20977583 | X260: -0.045422748 | Y260: -0.058002755 | Z260: -0.091669277 | AA260: -0.056046769 | AB260: -0.030443384 | AC260: -0.01180571
B261: 4q24 | W261: =0.9*W260 -> 0.18879825 | X261: =0.9*X260 -> -0.040880473 | Y261: =0.9*Y260 -> -0.05220248 | Z261: =0.9*Z260 -> -0.08250235 | AA261: =0.9*AA260 -> -0.050442092 | AB261: =0.9*AB260 -> -0.027399046 | AC261: =0.9*AC260 -> -0.010625139

Sheet YC Chart - Policy rate
K1: Chart | L1: Chart | M1: 1 | N1: 2 | O1: 3 | P1: 4 | Q1: 5 | R1: 6 | S1: 7 | T1: 8 | U1: 9 | V1: 10 | W1: 11 | X1: 12 | Y1: 13 | Z1: 14 | AA1: 15 | AB1: 16 | AC1: 17 | AD1: 18 | AE1: 19 | AF1: 20 | AG1: 21 | AH1: 22 | AI1: 23 | AJ1: 24 | AK1: 25 | AL1: 26 | AT1: 1 | AU1: 2 | AV1: 3 | AW1: 4 | AX1: 5 | AY1: 6
A2: date | B2: obs_gdp | C2: obs_gdpdeflator | D2: obs_nominalrate | F2: obs_longinflation | G2: obs_longrate | K2: Date | L2: Policy rate (%,apr) | M2: =+_xlfn.CONCAT("V",M1) -> V1 | N2: =+_xlfn.CONCAT("V",N1) -> V2 | O2: =+_xlfn.CONCAT("V",O1) -> V3 | P2: =+_xlfn.CONCAT("V",P1) -> V4 | Q2: =+_xlfn.CONCAT("V",Q1) -> V5 | R2: =+_xlfn.CONCAT("V",R1) -> V6 | S2: =+_xlfn.CONCAT("V",S1) -> V7 | T2: =+_xlfn.CONCAT("V",T1) -> V8 | ... AL2: =+_xlfn.CONCAT("V",AL1) -> V26 | AT2: obs_nominalrate1 | AU2: obs_nominalrate2 | AV2: obs_nominalrate3 | AW2: obs_nominalrate4 | AX2: obs_nominalrate5 | AY2: obs_nominalrate6 | BJ2: yc1 | BK2: yc2 | BL2: yc3 | BM2: yc4 | BN2: yc5 | BO2: yc6
A3: 21823 | B3: -0.30408411 | C3: 0.38618932 | D3: 0.8925 | K3: =+A3 -> 21823 | L3: =+D3*4 -> 3.57
A4: 21915 | B4: -0.085396239 | C4: 0.3912113 | D4: 0.9975 | K4: =+A4 -> 21915 | L4: =+D4*4 -> 3.99
A5: 22006 | B5: 1.8569299 | C5: 0.39616873 | D5: 0.9825 | K5: =+A5 -> 22006 | L5: =+D5*4 -> 3.93
A6: 22097 | B6: -0.91034251 | C6: 0.25246817 | D6: 0.925 | K6: =+A6 -> 22097 | L6: =+D6*4 -> 3.7
A7: 22189 | B7: 0.12315845 | C7: 0.34207927 | D7: 0.735 | K7: =+A7 -> 22189 | L7: =+D7*4 -> 2.94
A8: 22281 | B8: -1.6584688 | C8: 0.29595338 | D8: 0.575 | K8: =+A8 -> 22281 | L8: =+D8*4 -> 2.3
A9: 22371 | B9: 0.30422427 | C9: 0.21818657 | D9: 0.4975 | K9: =+A9 -> 22371 | L9: =+D9*4 -> 1.99
A10: 22462 | B10: 1.3165542 | C10: 0.23050337 | D10: 0.4325 | K10: =+A10 -> 22462 | L10: =+D10*4 -> 1.73
A11: 22554 | B11: 1.5360756 | C11: 0.25549324 | D11: 0.42 | K11: =+A11 -> 22554 | L11: =+D11*4 -> 1.68
A12: 22646 | B12: 1.5758415 | C12: 0.31209223 | D12: 0.6 | K12: =+A12 -> 22646 | L12: =+D12*4 -> 2.4
A13: 22736 | B13: 1.399261 | C13: 0.51378122 | D13: 0.615 | K13: =+A13 -> 22736 | L13: =+D13*4 -> 2.46
A14: 22827 | B14: 0.52884844 | C14: 0.16435935 | D14: 0.6525 | K14: =+A14 -> 22827 | L14: =+D14*4 -> 2.61
... A50: 26114 | B50: -0.010363799 | C50: 1.3054021 | D50: 1.1425 | K50: =+A50 -> 26114 | L50: =+D50*4 -> 4.57
A51: 26206 | B51: 0.2690258 | C51: 1.0125119 | D51: 1.37 | G51: 1.5257 | K51: =+A51 -> 26206 | L51: =+D51*4 -> 5.48
A52: 26298 | B52: -0.32043651 | C52: 0.83057731 | D52: 1.1875 | G52: 1.491925 | K52: =+A52 -> 26298 | L52: =+D52*4 -> 4.75
A53: 26389 | B53: 1.2602782 | C53: 1.5126649 | D53: 0.8875 | G53: 1.5448 | K53: =+A53 -> 26389 | L53: =+D53*4 -> 3.55
A54: 26480 | B54: 1.6860456 | C54: 0.62055319 | D54: 1.075 | G54: 1.53105 | K54: =+A54 -> 26480 | L54: =+D54*4 -> 4.3
A55: 26572 | B55: 0.3852877 | C55: 0.9507066 | D55: 1.185 | G55: 1.5853 | K55: =+A55 -> 26572 | L55: =+D55*4 -> 4.74
A56: 26664 | B56: 1.1057907 | C56: 1.2670582 | D56: 1.2875 | G56: 1.569 | K56: =+A56 -> 26664 | L56: =+D56*4 -> 5.15
A57: 26754 | B57: 1.8936626 | C57: 1.1457007 | D57: 1.635 | G57: 1.645375 | K57: =+A57 -> 26754 | L57: =+D57*4 -> 6.54
A58: 26845 | B58: 0.53249332 | C58: 1.5276802 | D58: 1.955 | G58: 1.66725 | K58: =+A58 -> 26845 | L58: =+D58*4 -> 7.82
A59: 26937 | B59: -1.06861 | C59: 1.9262302 | D59: 2.64 | G59: 1.690725 | K59: =+A59 -> 26937 | L59: =+D59*4 -> 10.56
A60: 27029 | B60: 0.40548359 | C60: 1.9731808 | D60: 2.5 | G60: 1.684425 | K60: =+A60 -> 27029 | L60: =+D60*4 -> 10
A61: 27119 | B61: -1.3981815 | C61: 1.869599 | D61: 2.3325 | G61: 1.835475 | K61: =+A61 -> 27119 | L61: =+D61*4 -> 9.33
A62: 27210 | B62: -0.29322437 | C62: 2.3358372 | D62: 2.8125 | G62: 1.929325 | K62: =+A62 -> 27210 | L62: =+D62*4 -> 11.25
... A83: 29128 | B83: 0.32743149 | C83: 2.1632932 | D83: 2.735 | G83: 2.270025 | K83: =+A83 -> 29128 | L83: =+D83*4 -> 10.94
A84: 29220 | B84: -0.15362911 | C84: 1.8384466 | D84: 3.395 | F84: 1.6 | G84: 2.4906 | K84: =+A84 -> 29220 | L84: =+D84*4 -> 13.58
A85: 29311 | B85: -0.08319259 | C85: 2.0793092 | D85: 3.7675 | G85: 2.978425 | K85: =+A85 -> 29311 | L85: =+D85*4 -> 15.07
A86: 29402 | B86: -2.4706014 | C86: 2.3510302 | D86: 3.1675 | F86: 1.8375 | G86: 2.4489 | K86: =+A86 -> 29402 | L86: =+D86*4 -> 12.67
A87: 29494 | B87: -0.49739301 | C87: 2.2090655 | D87: 2.455 | G87: 2.878775 | K87: =+A87 -> 29494 | L87: =+D87*4 -> 9.82
A88: 29586 | B88: 1.4763561 | C88: 2.5713717 | D88: 3.9625 | F88: 1.9375 | G88: 2.96035 | K88: =+A88 -> 29586 | L88: =+D88*4 -> 15.85
A89: 29676 | B89: 1.5757765 | C89: 2.6000618 | D89: 4.15 | G89: 3.210275 | K89: =+A89 -> 29676 | L89: =+D89*4 -> 16.6
A90: 29767 | B90: -1.0984483 | C90: 1.9622379 | D90: 4.4475 | F90: 1.825 | G90: 3.264225 | K90: =+A90 -> 29767 | L90: =+D90*4 -> 17.79
A91: 29859 | B91: 0.8416346 | C91: 1.8647478 | D91: 4.3975 | G91: 3.723025 | K91: =+A91 -> 29859 | L91: =+D91*4 -> 17.59
A92: 29951 | B92: -1.4356505 | C92: 1.7132211 | D92: 3.3975 | F92: 1.6375 | G92: 3.37825 | K92: =+A92 -> 29951 | L92: =+D92*4 -> 13.59
A93: 30041 | B93: -1.8983795 | C93: 1.3662426 | D93: 3.5525 | G93: 3.342825 | K93: =+A93 -> 30041 | L93: =+D93*4 -> 14.21
A94: 30132 | B94: 0.12845338 | C94: 1.2906547 | D94: 3.6275 | F94: 1.3 | G94: 3.398 | K94: =+A94 -> 30132 | L94: =+D94*4 -> 14.51
A95: 30224 | B95: -0.70404248 | C95: 1.4087662 | D95: 2.7525 | G95: 2.90445 | K95: =+A95 -> 30224 | L95: =+D95*4 -> 11.01
A96: 30316 | B96: -0.27615918 | C96: 1.0313596 | D96: 2.32 | F96: 1.2875 | G96: 2.6224 | K96: =+A96 -> 30316 | L96: =+D96*4 -> 9.28
A97: 30406 | B97: 0.99738501 | C97: 0.75275151 | D97: 2.165 | F97: 1.2 | G97: 2.653475 | K97: =+A97 -> 30406 | L97: =+D97*4 -> 8.66
A98: 30497 | B98: 1.9450419 | C98: 0.73866867 | D98: 2.2 | G98: 2.7268 | K98: =+A98 -> 30497 | L98: =+D98*4 -> 8.8
A99: 30589 | B99: 1.6751664 | C99: 1.0581219 | D99: 2.365 | G99: 2.837275 | K99: =+A99 -> 30589 | L99: =+D99*4 -> 9.46
A100: 30681 | B100: 1.765739 | C100: 0.7546419 | D100: 2.3575 | F100: 1.175 | G100: 2.9111 | K100: =+A100 -> 30681 | L100: =+D100*4 -> 9.43
A101: 30772 | B101: 1.6376035 | C101: 1.0083772 | D101: 2.4225 | F101: 1.275 | G101: 3.060925 | K101: =+A101 -> 30772 | L101: =+D101*4 -> 9.69
A102: 30863 | B102: 1.4185504 | C102: 0.85164394 | D102: 2.6375 | G102: 3.3661 | K102: =+A102 -> 30863 | L102: =+D102*4 -> 10.55
A103: 30955 | B103: 0.66661449 | C103: 0.88487172 | D103: 2.8475 | G103: 3.021825 | K103: =+A103 -> 30955 | L103: =+D103*4 -> 11.39
A104: 31047 | B104: 0.52562947 | C104: 0.74482992 | D104: 2.315 | F104: 1.175 | G104: 2.86935 | K104: =+A104 -> 31047 | L104: =+D104*4 -> 9.26
A105: 31137 | B105: 0.67391324 | C105: 0.98389258 | D105: 2.12 | F105: 0.9625 | G105: 2.900725 | K105: =+A105 -> 31137 | L105: =+D105*4 -> 8.48
A106: 31228 | B106: 0.58741275 | C106: 0.64138315 | D106: 1.98 | G106: 2.585725 | K106: =+A106 -> 31228 | L106: =+D106*4 -> 7.92
A107: 31320 | B107: 1.2259866 | C107: 0.60199666 | D107: 1.975 | G107: 2.612675 | K107: =+A107 -> 31320 | L107: =+D107*4 -> 7.9
A108: 31412 | B108: 0.45245779 | C108: 0.5574423 | D108: 2.025 | F108: 1.0125 | G108: 2.29525 | K108: =+A108 -> 31412 | L108: =+D108*4 -> 8.1
A109: 31502 | B109: 0.64152083 | C109: 0.49614375 | D109: 1.9575 | F109: 0.875 | G109: 1.877275 | K109: =+A109 -> 31502 | L109: =+D109*4 -> 7.83
A110: 31593 | B110: 0.16244968 | C110: 0.37775003 | D110: 1.73 | G110: 1.93435 | K110: =+A110 -> 31593 | L110: =+D110*4 -> 6.92
A111: 31685 | B111: 0.66664551 | C111: 0.40906955 | D111: 1.5525 | G111: 1.97845 | K111: =+A111 -> 31685 | L111: =+D111*4 -> 6.21
A112: 31777 | B112: 0.24959199 | C112: 0.54347438 | D112: 1.5675 | F112: 0.875 | G112: 1.8907 | K112: =+A112 -> 31777 | L112: =+D112*4 -> 6.27
A113: 31867 | B113: 0.45396977 | C113: 0.63763794 | D113: 1.555 | F113: 0.925 | G113: 1.9158 | K113: =+A113 -> 31867 | L113: =+D113*4 -> 6.22
A114: 31958 | B114: 0.78974225 | C114: 0.69031186 | D114: 1.6625 | G114: 2.12505 | K114: =+A114 -> 31958 | L114: =+D114*4 -> 6.65
A115: 32050 | B115: 0.5808548 | C115: 0.75500476 | D115: 1.71 | G115: 2.410475 | K115: =+A115 -> 32050 | L115: =+D115*4 -> 6.84
A116: 32142 | B116: 1.4206977 | C116: 0.79401824 | D116: 1.73 | F116: 1 | G116: 2.23695 | K116: =+A116 -> 32142 | L116: =+D116*4 -> 6.92
A117: 32233 | B117: 0.23668349 | C117: 0.78037784 | D117: 1.6675 | F117: 0.95 | G117: 2.190725 | K117: =+A117 -> 32233 | L117: =+D117*4 -> 6.67
A118: 32324 | B118: 1.0261362 | C118: 0.96835706 | D118: 1.7875 | G118: 2.223725 | K118: =+A118 -> 32324 | L118: =+D118*4 -> 7.15
A119: 32416 | B119: 0.30526185 | C119: 1.1888239 | D119: 1.995 | G119: 2.2176 | K119: =+A119 -> 32416 | L119: =+D119*4 -> 7.98
A120: 32508 | B120: 1.0471089 | C120: 0.86004237 | D120: 2.1175 | F120: 0.9625 | G120: 2.2516 | K120: =+A120 -> 32508 | L120: =+D120*4 -> 8.47
A121: 32598 | B121: 0.7344863 | C121: 1.037276 | D121: 2.3625 | F121: 0.9375 | G121: 2.268475 | K121: =+A121 -> 32598 | L121: =+D121*4 -> 9.45
A122: 32689 | B122: 0.48391105 | C122: 1.0599653 | D122: 2.4325 | G122: 2.020575 | K122: =+A122 -> 32689 | L122: =+D122*4 -> 9.73
A123: 32781 | B123: 0.46408218 | C123: 0.72716152 | D123: 2.27 | G123: 2.062825 | K123: =+A123 -> 32781 | L123: =+D123*4 -> 9.08
A124: 32873 | B124: -0.077196821 | C124: 0.70980748 | D124: 2.1525 | F124: 0.925 | G124: 1.977675 | K124: =+A124 -> 32873 | L124: =+D124*4 -> 8.61
A125: 32963 | B125: 0.81351513 | C125: 1.0733186 | D125: 2.0625 | F125: 0.8625 | G125: 2.141 | K125: =+A125 -> 32963 | L125: =+D125*4 -> 8.25
A126: 33054 | B126: 0.090763781 | C126: 1.1143835 | D126: 2.06 | G126: 2.096325 | K126: =+A126 -> 33054 | L126: =+D126*4 -> 8.24
A127: 33146 | B127: -0.20120596 | C127: 0.85245976 | D127: 2.04 | G127: 2.2162 | K127: =+A127 -> 33146 | L127: =+D127*4 -> 8.16
A128: 33238 | B128: -1.1813362 | C128: 0.74206882 | D128: 1.935 | F128: 0.9125 | G128: 2.054825 | K128: =+A128 -> 33238 | L128: =+D128*4 -> 7.74
A129: 33328 | B129: -0.73274762 | C129: 0.97434034 | D129: 1.6075 | F129: 0.8875 | G129: 2.0437 | K129: =+A129 -> 33328 | L129: =+D129*4 -> 6.43
A130: 33419 | B130: 0.5147953 | C130: 0.73112351 | D130: 1.465 | G130: 2.110025 | K130: =+A130 -> 33419 | L130: =+D130*4 -> 5.86
A131: 33511 | B131: 0.24333858 | C131: 0.77943226 | D131: 1.4125 | G131: 1.928225 | K131: =+A131 -> 33511 | L131: =+D131*4 -> 5.65
A132: 33603 | B132: 0.091240538 | C132: 0.5911092 | D132: 1.205 | F132: 0.875 | G132: 1.7813 | K132: =+A132 -> 33603 | L132: =+D132*4 -> 4.82
A133: 33694 | B133: 0.93477162 | C133: 0.37069314 | D133: 1.005 | F133: 0.8 | G133: 1.9399 | K133: =+A133 -> 33694 | L133: =+D133*4 -> 4.02
A134: 33785 | B134: 0.82402613 | C134: 0.59986065 | D134: 0.9425 | F134: 0.85 | G134: 1.89465 | K134: =+A134 -> 33785 | L134: =+D134*4 -> 3.77
A135: 33877 | B135: 0.73027323 | C135: 0.48813267 | D135: 0.815 | F135: 0.8125 | G135: 1.751125 | K135: =+A135 -> 33877 | L135: =+D135*4 -> 3.26
A136: 33969 | B136: 0.78730875 | C136: 0.68509712 | D136: 0.7575 | F136: 0.775 | G136: 1.773675 | K136: =+A136 -> 33969 | L136: =+D136*4 -> 3.03
A137: 34059 | B137: -0.083962687 | C137: 0.55949272 | D137: 0.76 | F137: 0.75 | G137: 1.63275 | K137: =+A137 -> 34059 | L137: =+D137*4 -> 3.04
A138: 34150 | B138: 0.33092577 | C138: 0.59388273 | D138: 0.75 | F138: 0.8 | G138: 1.522725 | K138: =+A138 -> 34150 | L138: =+D138*4 -> 3
A139: 34242 | B139: 0.2279217 | C139: 0.5919297 | D139: 0.765 | F139: 0.7375 | G139: 1.4198 | K139: =+A139 -> 34242 | L139: =+D139*4 -> 3.06
A140: 34334 | B140: 1.1023308 | C140: 0.54366058 | D140: 0.7475 | F140: 0.7375 | G140: 1.5183 | K140: =+A140 -> 34334 | L140: =+D140*4 -> 2.99
A141: 34424 | B141: 0.71592769 | C141: 0.47771037 | D141: 0.8025 | F141: 0.7375 | G141: 1.7449 | K141: =+A141 -> 34424 | L141: =+D141*4 -> 3.21
A142: 34515 | B142: 1.0969236 | C142: 0.48155909 | D142: 0.985 | F142: 0.75 | G142: 1.87925 | K142: =+A142 -> 34515 | L142: =+D142*4 -> 3.94
A143: 34607 | B143: 0.3315289 | C143: 0.5720883 | D143: 1.1225 | F143: 0.75 | G143: 1.924025 | K143: =+A143 -> 34607 | L143: =+D143*4 -> 4.49
... A199: 39721 | B199: -0.77113979 | C199: 0.75055565 | D199: 0.485 | F199: 0.5 | G199: 1.05985 | K199: =+A199 -> 39721 | L199: =+D199*4 -> 1.94
A200: 39813 | B200: -2.4547899 | C200: 0.24179164 | D200: 0.1275 | F200: 0.5 | G200: 0.719775 | K200: =+A200 -> 39813 | L200: =+D200*4 -> 0.51 | M200: =+L200 -> 0.51 | AT200: 0.05 | AU200: 0.1 | AV200: 0.15 | AW200: 0.2 | AX200: 0.25 | AY200: 0.3
A201: 39903 | B201: -1.3823555 | C201: -0.079026399 | D201: 0.045 | F201: 0.475 | G201: 0.788675 | K201: =+A201 -> 39903 | L201: =+D201*4 -> 0.18 | M201: 0.2 | N201: =+L201 -> 0.18 | AT201: 0.05 | AU201: 0.075 | AV201: 0.125 | AW201: 0.15 | AX201: 0.2 | AY201: 0.275 | BJ201: =+AT200*4 -> 0.2
A202: 39994 | B202: -0.4177592 | C202: -0.166159 | D202: 0.045 | F202: 0.5 | G202: 1.0046 | K202: =+A202 -> 39994 | L202: =+D202*4 -> 0.18 | M202: 0.4 | N202: 0.2 | O202: =+L202 -> 0.18 | AT202: 0.05 | AU202: 0.1 | AV202: 0.175 | AW202: 0.275 | AX202: 0.35 | AY202: 0.45 | BJ202: =+AT201*4 -> 0.2 | BK202: =+AU200*4 -> 0.4
A203: 40086 | B203: 0.11177887 | C203: 0.11871316 | D203: 0.0375 | F203: 0.5 | G203: 0.92875 | K203: =+A203 -> 40086 | L203: =+D203*4 -> 0.15 | M203: 0.6 | N203: 0.3 | O203: 0.2 | P203: =+L203 -> 0.15 | AT203: 0.05 | AU203: 0.1 | AV203: 0.175 | AW203: 0.25 | AX203: 0.35 | AY203: 0.45 | BJ203: =+AT202*4 -> 0.2 | BK203: =+AU201*4 -> 0.3 | BL203: =+AV200*4 -> 0.6
A204: 40178 | B204: 0.83594329 | C204: 0.31588118 | D204: 0.03 | F204: 0.44 | G204: 1.0456 | K204: =+A204 -> 40178 | L204: =+D204*4 -> 0.12 | M204: 0.8 | N204: 0.5 | O204: 0.4 | P204: 0.2 | Q204: =+L204 -> 0.12 | AT204: 0.05 | AU204: 0.1 | AV204: 0.2 | AW204: 0.3 | AX204: 0.4 | AY204: 0.5 | BJ204: =+AT203*4 -> 0.2 | BK204: =+AU202*4 -> 0.4 | BL204: =+AV201*4 -> 0.5 | BM204: =+AW200*4 -> 0.8
A205: 40268 | B205: 0.24405659 | C205: 0.28681192 | D205: 0.0325 | F205: 0.4725 | G205: 1.02965 | K205: =+A205 -> 40268 | L205: =+D205*4 -> 0.13 | M205: 1 | N205: 0.6 | O205: 0.7 | P205: 0.4 | Q205: 0.2 | R205: =+L205 -> 0.13 | AT205: 0.05 | AU205: 0.1 | AV205: 0.15 | AW205: 0.225 | AX205: 0.3 | AY205: 0.4 | BJ205: =+AT204*4 -> 0.2 | BK205: =+AU203*4 -> 0.4 | BL205: =+AV202*4 -> 0.7 | BM205: =+AW201*4 -> 0.6 | BN205: =+AX200*4 -> 1
A206: 40359 | B206: 0.72086019 | C206: 0.48737681 | D206: 0.0475 | F206: 0.475 | G206: 0.81 | K206: =+A206 -> 40359 | L206: =+D206*4 -> 0.19 | M206: 1.2 | N206: 0.8 | O206: 1.1 | P206: 0.7 | Q206: 0.4 | R206: 0.2 | S206: =+L206 -> 0.19 | AT206: 0.05 | AU206: 0.075 | AV206: 0.1 | AW206: 0.125 | AX206: 0.15 | AY206: 0.2 | BJ206: =+AT205*4 -> 0.2 | BK206: =+AU204*4 -> 0.4 | BL206: =+AV203*4 -> 0.7 | BM206: =+AW202*4 -> 1.1 | BN206: =+AX201*4 -> 0.8 | BO206: =+AY200*4 -> 1.2
A207: 40451 | B207: 0.52488792 | C207: 0.30354795 | D207: 0.0475 | F207: 0.45 | G207: 0.683475 | K207: =+A207 -> 40451 | L207: =+D207*4 -> 0.19 | N207: 1.1 | O207: 1.4 | P207: 1 | Q207: 0.8 | R207: 0.4 | S207: 0.2 | T207: =+L207 -> 0.19 | AT207: 0.05 | AU207: 0.05 | AV207: 0.05 | AW207: 0.075 | AX207: 0.1 | AY207: 0.125 | BJ207: =+AT206*4 -> 0.2 | BK207: =+AU205*4 -> 0.4 | BL207: =+AV204*4 -> 0.8 | BM207: =+AW203*4 -> 1 | BN207: =+AX202*4 -> 1.4 | BO207: =+AY201*4 -> 1.1
A208: 40543 | B208: 0.27796205 | C208: 0.57886799 | D208: 0.0475 | F208: 0.425 | G208: 0.8862 | K208: =+A208 -> 40543 | L208: =+D208*4 -> 0.19 | O208: 1.8 | P208: 1.4 | Q208: 1.2 | R208: 0.6 | S208: 0.3 | T208: 0.2 | U208: =+L207 -> 0.19 | AT208: 0.05 | AU208: 0.05 | AV208: 0.075 | AW208: 0.1 | AX208: 0.15 | AY208: 0.2 | BJ208: =+AT207*4 -> 0.2 | BK208: =+AU206*4 -> 0.3 | BL208: =+AV205*4 -> 0.6 | BM208: =+AW204*4 -> 1.2 | BN208: =+AX203*4 -> 1.4 | BO208: =+AY202*4 -> 1.8
A209: 40633 | B209: -0.48517911 | C209: 0.51052655 | D209: 0.0375 | F209: 0.45 | G209: 0.924425 | K209: =+A209 -> 40633 | L209: =+D209*4 -> 0.15 | P209: 1.8 | Q209: 1.6 | R209: 0.9 | S209: 0.4 | T209: 0.2 | U209: 0.2 | V209: =+L209 -> 0.15 | AT209: 0.025 | AU209: 0.05 | AV209: 0.1 | AW209: 0.175 | AX209: 0.225 | AY209: 0.3 | BJ209: =+AT208*4 -> 0.2 | BK209: =+AU207*4 -> 0.2 | BL209: =+AV206*4 -> 0.4 | BM209: =+AW205*4 -> 0.9 | BN209: =+AX204*4 -> 1.6 | BO209: =+AY203*4 -> 1.8
A210: 40724 | B210: 0.42297668 | C210: 0.65915472 | D210: 0.0225 | F210: 0.475 | G210: 0.85755 | K210: =+A210 -> 40724 | L210: =+D210*4 -> 0.09 | Q210: 2 | R210: 1.2 | S210: 0.5 | T210: 0.2 | U210: 0.2 | V210: 0.1 | W210: =+L210 -> 0.09 | AT210: 0.025 | AU210: 0.05 | AV210: 0.075 | AW210: 0.1 | AX210: 0.125 | AY210: 0.175 | BJ210: =+AT209*4 -> 0.1 | BK210: =+AU208*4 -> 0.2 | BL210: =+AV207*4 -> 0.2 | BM210: =+AW206*4 -> 0.5 | BN210: =+AX205*4 -> 1.2 | BO210: =+AY204*4 -> 2
...

Sheet Chart 2 - Real rate gaps
E1: PCECTPI (yoy growth rate inflation) - source:https://fred.stlouisfed.org/series/PCECTPI | F1: GDP percent change yoy | H1: wFG | J1: woFG
A2: observation_date | B2: PCECTPI | C2: NBER Recession | D2: NBER Recession | E2: Inflation (yoy, apr) | F2: GDP (yoy, apr) | G2: Policy rate (%, apr) | H2: Real rate gap - with FG (lhs) | I2: 5-year real rate gap - with FG (rhs) | J2: Real rate gap - without FG (lhs) | K2: 5-year real rate gap - without FG (rhs) | L2: r* (%,apr)
A3: 17258 | B3: 0.8 | F3: 9.3
A4: 17349 | B4: 1.9 | F4: 10.8
A5: 17441 | B5: 2.5 | F5: 11.9
A6: 17533 | B6: 1.1 | E6: 6.4 | F6: 7.9
A7: 17624 | B7: 1 | E7: 6.7 | F7: 3.5
A8: 17715 | B8: 1.5 | E8: 6.3 | F8: -0.4
A9: 17807 | B9: -0.3 | C9: 1 | D9: -1 | E9: 3.4 | F9: -2.3
A10: 17899 | B10: -0.8 | C10: 1 | D10: -1 | E10: 1.4 | F10: -3.5
A11: 17989 | B11: -0.6 | C11: 1 | D11: -1 | E11: -0.2 | F11: 2.1
A12: 18080 | B12: -0.6 | C12: 1 | D12: -1 | E12: -2.3 | F12: 7
A13: 18172 | B13: -0.1 | E13: -2 | F13: 12.9
A14: 18264 | B14: -0.2 | E14: -1.4 | F14: 18.2
A15: 18354 | B15: 0.5 | E15: -0.3 | F15: 19.6
A16: 18445 | B16: 2.1 | E16: 2.3 | F16: 18.5
A17: 18537 | B17: 1.8 | E17: 4.2 | F17: 14
A18: 18629 | B18: 3.2 | E18: 7.7 | F18: 11.3
A19: 18719 | B19: 0.8 | E19: 8.1 | F19: 7.1
A20: 18810 | B20: 0.1 | E20: 6 | F20: 4.9
A21: 18902 | B21: 1.3 | E21: 5.5 | F21: 4.6
A22: 18994 | B22: 0.4 | E22: 2.7 | F22: 6.9
A23: 19085 | B23: 0 | E23: 1.9 | F23: 7.8
A24: 19176 | B24: 0.7 | E24: 2.4 | F24: 8.5
... A27: 19450 | B27: 0.1 | E27: 1.3 | F27: -0.7
A28: 19541 | B28: 0.5 | C28: 1 | D28: -1 | E28: 1.2 | F28: -1.4
A29: 19633 | B29: 0.4 | C29: 1 | D29: -1 | E29: 1.5 | F29: 0
A30: 19725 | B30: 0.5 | C30: 1 | D30: -1 | E30: 1.6 | F30: 3.6
A31: 19815 | B31: -0.1 | E31: 1.3 | F31: 7.2
A32: 19906 | B32: -0.3 | E32: 0.5 | F32: 9.2
A33: 19998 | B33: -0.1 | E33: -0.1 | F33: 10
A34: 20090 | B34: 0.3 | E34: -0.2 | F34: 9.3
A35: 20180 | B35: 0.1 | E35: 0 | F35: 6.5
A36: 20271 | B36: 0.4 | E36: 0.7 | F36: 5.8
A37: 20363 | B37: 0.3 | E37: 1.1 | F37: 4.9
A38: 20455 | B38: 0.4 | E38: 1.2 | F38: 5.3
A39: 20546 | B39: 0.7 | E39: 1.8 | F39: 6.8
A40: 20637 | B40: 1 | E40: 2.4 | F40: 5.8
A41: 20729 | B41: 0.6 | E41: 2.7 | F41: 6.3
A42: 20821 | B42: 0.9 | E42: 3.2 | F42: 3.1
A43: 20911 | B43: 0.6 | E43: 3.1 | F43: -0.5
A44: 21002 | B44: 0.8 | C44: 1 | D44: -1 | E44: 3 | F44: 0
A45: 21094 | B45: 0.5 | C45: 1 | D45: -1 | E45: 2.9 | F45: 1.3
A46: 21186 | B46: 1.2 | C46: 1 | D46: -1 | E46: 3.2 | F46: 5.2
A47: 21276 | B47: 0.2 | E47: 2.8 | F47: 9.2
A48: 21367 | B48: 0.1 | E48: 2 | F48: 10.7
A49: 21459 | B49: 0 | E49: 1.5 | F49: 8.1
A50: 21551 | B50: 0.7 | E50: 0.9 | F50: 5.8
A51: 21641 | B51: 0.4 | E51: 1.1 | F51: 6.3
A52: 21732 | B52: 0.6 | E52: 1.7 | F52: 3.5
A53: 21824 | B53: 0.5 | E53: 2.3 | F53: 3.9 | G53: =+'YC Chart - Policy rate'!D3*4 -> 3.57
A54: 21916 | B54: 0.1 | E54: 1.7 | F54: 2.2 | G54: =+'YC Chart - Policy rate'!D4*4 -> 3.99
A55: 22007 | B55: 0.5 | C55: 1 | D55: -1 | E55: 1.8 | F55: 0.4 | G55: =+'YC Chart - Policy rate'!D5*4 -> 3.93 | H55: =+hist_ExAnteRealRate_wFG!D2-hist_RealNaturalRate_wFG!D2 -> 0.98414473 | I55: =+hist_Forward5YearRealR_wFG!D2-hist_Forward5YearRNatR_wFG!D2 -> 0.215389 | J55: =+hist_ExAnteRealRate_woFG!D2-hist_RealNaturalRate_woFG!D2 -> 0.98874011 | K55: =+hist_Forward5YearRealR_woFG!D2-hist_Forward5YearRNatR_woFG!D2 -> 0.22076957 | L55: =+hist_Forward5YearRNatR_wFG!D2 -> 2.0631498
A56: 22098 | B56: 0.4 | C56: 1 | D56: -1 | E56: 1.6 | F56: 2.7 | G56: =+'YC Chart - Policy rate'!D6*4 -> 3.7 | H56: =+hist_ExAnteRealRate_wFG!D3-hist_RealNaturalRate_wFG!D3 -> -2.1797773 | I56: =+hist_Forward5YearRealR_wFG!D3-hist_Forward5YearRNatR_wFG!D3 -> 0.29669614 | J56: =+hist_ExAnteRealRate_woFG!D3-hist_RealNaturalRate_woFG!D3 -> -2.1740416 | K56: =+hist_Forward5YearRealR_woFG!D3-hist_Forward5YearRNatR_woFG!D3 -> 0.30217716 | L56: =+hist_Forward5YearRNatR_wFG!D3 -> 2.1205647
A57: 22190 | B57: 0.4 | C57: 1 | D57: -1 | E57: 1.5 | F57: 4 | G57: =+'YC Chart - Policy rate'!D7*4 -> 2.94 | H57: =+hist_ExAnteRealRate_wFG!D4-hist_RealNaturalRate_wFG!D4 -> 1.4683848 | I57: =+hist_Forward5YearRealR_wFG!D4-hist_Forward5YearRNatR_wFG!D4 -> 0.32520532 | J57: =+hist_ExAnteRealRate_woFG!D4-hist_RealNaturalRate_woFG!D4 -> 1.4753184 | K57: =+hist_Forward5YearRealR_woFG!D4-hist_Forward5YearRNatR_woFG!D4 -> 0.33078535 | L57: =+hist_Forward5YearRNatR_wFG!D4 -> 2.0224967
A58: 22282 | B58: 0.2 | E58: 1.5 | F58: 7.5 | G58: =+'YC Chart - Policy rate'!D8*4 -> 2.3 | H58: =+hist_ExAnteRealRate_wFG!D5-hist_RealNaturalRate_wFG!D5 -> 1.1932381 | I58: =+hist_Forward5YearRealR_wFG!D5-hist_Forward5YearRNatR_wFG!D5 -> 0.30407804 | J58: =+hist_ExAnteRealRate_woFG!D5-hist_RealNaturalRate_woFG!D5 -> 1.2014514 | K58: =+hist_Forward5YearRealR_woFG!D5-hist_Forward5YearRNatR_woFG!D5 -> 0.3097568 | L58: =+hist_Forward5YearRNatR_wFG!D5 -> 2.1038496
A59: 22372 | B59: 0 | E59: 1 | F59: 9 | G59: =+'YC Chart - Policy rate'!D9*4 -> 1.99 | H59: =+hist_ExAnteRealRate_wFG!D6-hist_RealNaturalRate_wFG!D6 -> 2.1195851 | I59: =+hist_Forward5YearRealR_wFG!D6-hist_Forward5YearRNatR_wFG!D6 -> 0.3340696 | J59: =+hist_ExAnteRealRate_woFG!D6-hist_RealNaturalRate_woFG!D6 -> 2.129168 | K59: =+hist_Forward5YearRealR_woFG!D6-hist_Forward5YearRNatR_woFG!D6 -> 0.33984786 | L59: =+hist_Forward5YearRNatR_wFG!D6 -> 2.1590386
A60: 22463 | B60: 0.4 | E60: 1 | F60: 8.1 | G60: =+'YC Chart - Policy rate'!D10*4 -> 1.73 | H60: =+hist_ExAnteRealRate_wFG!D7-hist_RealNaturalRate_wFG!D7 -> 2.3952093 | I60: =+hist_Forward5YearRealR_wFG!D7-hist_Forward5YearRNatR_wFG!D7 -> 0.30636396 | J60: =+hist_ExAnteRealRate_woFG!D7-hist_RealNaturalRate_woFG!D7 -> 2.406256 | K60: =+hist_Forward5YearRealR_woFG!D7-hist_Forward5YearRNatR_woFG!D7 -> 0.31224343 | L60: =+hist_Forward5YearRNatR_wFG!D7 -> 2.1723315
A61: 22555 | B61: 0.1 | E61: 0.6 | F61: 7.3 | G61: =+'YC Chart - Policy rate'!D11*4 -> 1.68 | H61: =+hist_ExAnteRealRate_wFG!D8-hist_RealNaturalRate_wFG!D8 -> 1.7102926 | I61: =+hist_Forward5YearRealR_wFG!D8-hist_Forward5YearRNatR_wFG!D8 -> 0.29183699 | J61: =+hist_ExAnteRealRate_woFG!D8-hist_RealNaturalRate_woFG!D8 -> 1.7229023 | K61: =+hist_Forward5YearRealR_woFG!D8-hist_Forward5YearRNatR_woFG!D8 -> 0.2978202 | L61: =+hist_Forward5YearRNatR_wFG!D8 -> 2.2626478
A62: 22647 | B62: 0.4 | E62: 0.9 | F62: 5.5 | G62: =+'YC Chart - Policy rate'!D12*4 -> 2.4 | H62: =+hist_ExAnteRealRate_wFG!D9-hist_RealNaturalRate_wFG!D9 -> -0.93240227 | I62: =+hist_Forward5YearRealR_wFG!D9-hist_Forward5YearRNatR_wFG!D9 -> 0.2624522 | J62: =+hist_ExAnteRealRate_woFG!D9-hist_RealNaturalRate_woFG!D9 -> -0.91812388 | K62: =+hist_Forward5YearRealR_woFG!D9-hist_Forward5YearRNatR_woFG!D9 -> 0.26854246 | L62: =+hist_Forward5YearRNatR_wFG!D9 -> 2.373264
A63: 22737 | B63: 0.4 | E63: 1.3 | F63: 4.7 | G63: =+'YC Chart - Policy rate'!D13*4 -> 2.46 | H63: =+hist_ExAnteRealRate_wFG!D10-hist_RealNaturalRate_wFG!D10 -> -0.11940061 | I63: =+hist_Forward5YearRealR_wFG!D10-hist_Forward5YearRNatR_wFG!D10 -> 0.27842854 | J63: =+hist_ExAnteRealRate_woFG!D10-hist_RealNaturalRate_woFG!D10 -> -0.10333895 | K63: =+hist_Forward5YearRealR_woFG!D10-hist_Forward5YearRNatR_woFG!D10 -> 0.2846298 | L63: =+hist_Forward5YearRNatR_wFG!D10 -> 2.4914681
A64: 22828 | B64: 0.3 | E64: 1.2 | F64: 4.9 | G64: =+'YC Chart - Policy rate'!D14*4 -> 2.61 | H64: =+hist_ExAnteRealRate_wFG!D11-hist_RealNaturalRate_wFG!D11 -> -0.89514752 | I64: =+hist_Forward5YearRealR_wFG!D11-hist_Forward5YearRNatR_wFG!D11 -> 0.23230554 | J64: =+hist_ExAnteRealRate_woFG!D11-hist_RealNaturalRate_woFG!D11 -> -0.87717688 | K64: =+hist_Forward5YearRealR_woFG!D11-hist_Forward5YearRNatR_woFG!D11 -> 0.23862237 | L64: =+hist_Forward5YearRNatR_wFG!D11 -> 2.4933496
A65: 22920 | B65: 0.3 | E65: 1.4 | F65: 5.8 | G65: =+'YC Chart - Policy rate'!D15*4 -> 2.85 | H65: =+hist_ExAnteRealRate_wFG!D12-hist_RealNaturalRate_wFG!D12 -> 0.4821998 | I65: =+hist_Forward5YearRealR_wFG!D12-hist_Forward5YearRNatR_wFG!D12 -> 0.26159565 | J65: =+hist_ExAnteRealRate_woFG!D12-hist_RealNaturalRate_woFG!D12 -> 0.50221873 | K65: =+hist_Forward5YearRealR_woFG!D12-hist_Forward5YearRNatR_woFG!D12 -> 0.26803317 | L65: =+hist_Forward5YearRNatR_wFG!D12 -> 2.5797766
A66: 23012 | B66: 0.3 | E66: 1.2 | F66: 6.8 | G66: =+'YC Chart - Policy rate'!D16*4 -> 2.92 | H66: =+hist_ExAnteRealRate_wFG!D13-hist_RealNaturalRate_wFG!D13 -> 0.22471561 | I66: =+hist_Forward5YearRealR_wFG!D13-hist_Forward5YearRNatR_wFG!D13 -> 0.277659 | J66: =+hist_ExAnteRealRate_woFG!D13-hist_RealNaturalRate_woFG!D13 -> 0.24693884 | K66: =+hist_Forward5YearRealR_woFG!D13-hist_Forward5YearRNatR_woFG!D13 -> 0.28422277 | L66: =+hist_Forward5YearRNatR_wFG!D13 -> 2.6508134
A67: 23102 | B67: 0.2 | E67: 1 | F67: 7.7 | G67: =+'YC Chart - Policy rate'!D17*4 -> 2.97 | H67: =+hist_ExAnteRealRate_wFG!D14-hist_RealNaturalRate_wFG!D14 -> 0.36163635 | I67: =+hist_Forward5YearRealR_wFG!D14-hist_Forward5YearRNatR_wFG!D14 -> 0.25422512 | J67: =+hist_ExAnteRealRate_woFG!D14-hist_RealNaturalRate_woFG!D14 -> 0.38624114 | K67: =+hist_Forward5YearRealR_woFG!D14-hist_Forward5YearRNatR_woFG!D14 -> 0.26092114 | L67: =+hist_Forward5YearRNatR_wFG!D14 -> 2.7580187
A68: 23193 | B68: 0.5 | E68: 1.2 | F68: 7.8 | G68: =+'YC Chart - Policy rate'!D18*4 -> 2.96 | H68: =+hist_ExAnteRealRate_wFG!D15-hist_RealNaturalRate_wFG!D15 -> -0.1579969 | I68: =+hist_Forward5YearRealR_wFG!D15-hist_Forward5YearRNatR_wFG!D15 -> 0.16605339 | J68: =+hist_ExAnteRealRate_woFG!D15-hist_RealNaturalRate_woFG!D15 -> -0.13080359 | K68: =+hist_Forward5YearRealR_woFG!D15-hist_Forward5YearRNatR_woFG!D15 -> 0.17288808 | L68: =+hist_Forward5YearRNatR_wFG!D15 -> 2.8481428
A69: 23285 | B69: 0.4 | E69: 1.3 | F69: 7.4 | G69: =+'YC Chart - Policy rate'!D19*4 -> 3.33 | H69: =+hist_ExAnteRealRate_wFG!D16-hist_RealNaturalRate_wFG!D16 -> -0.42785808 | I69: =+hist_Forward5YearRealR_wFG!D16-hist_Forward5YearRNatR_wFG!D16 -> 0.18305107 | J69: =+hist_ExAnteRealRate_woFG!D16-hist_RealNaturalRate_woFG!D16 -> -0.39782128 | K69: =+hist_Forward5YearRealR_woFG!D16-hist_Forward5YearRNatR_woFG!D16 -> 0.19003137 | L69: =+hist_Forward5YearRNatR_wFG!D16 -> 2.920799
... A93: 25477 | B93: 1.2 | E93: 4.7 | F93: 5.4 | G93: =+'YC Chart - Policy rate'!D43*4 -> 8.98 | H93: =+hist_ExAnteRealRate_wFG!D40-hist_RealNaturalRate_wFG!D40 -> -3.1066103 | I93: =+hist_Forward5YearRealR_wFG!D40-hist_Forward5YearRNatR_wFG!D40 -> 0.020357188 | J93: =+hist_ExAnteRealRate_woFG!D40-hist_RealNaturalRate_woFG!D40 -> -3.0804048 | K93: =+hist_Forward5YearRealR_woFG!D40-hist_Forward5YearRNatR_woFG!D40 -> 0.028694894 | L93: =+hist_Forward5YearRNatR_wFG!D40 -> 2.2026074
A94: 25569 | B94: 1.2 | C94: 1 | D94: -1 | E94: 4.9 | F94: 4.9 | G94: =+'YC Chart - Policy rate'!D44*4 -> 8.94 | H94: =+hist_ExAnteRealRate_wFG!D41-hist_RealNaturalRate_wFG!D41 -> -5.1834509 | I94: =+hist_Forward5YearRealR_wFG!D41-hist_Forward5YearRNatR_wFG!D41 -> 0.081705774 | J94: =+hist_ExAnteRealRate_woFG!D41-hist_RealNaturalRate_woFG!D41 -> -5.1571284 | K94: =+hist_Forward5YearRealR_woFG!D41-hist_Forward5YearRNatR_woFG!D41 -> 0.09006045 | L94: =+hist_Forward5YearRNatR_wFG!D41 -> 2.1943031
A95: 25659 | B95: 1.1 | C95: 1 | D95: -1 | E95: 4.7 | F95: 8 | G95: =+'YC Chart - Policy rate'!D45*4 -> 8.56 | H95: =+hist_ExAnteRealRate_wFG!D42-hist_RealNaturalRate_wFG!D42 -> -2.7508327 | I95: =+hist_Forward5YearRealR_wFG!D42-hist_Forward5YearRNatR_wFG!D42 -> 0.081626554 | J95: =+hist_ExAnteRealRate_woFG!D42-hist_RealNaturalRate_woFG!D42 -> -2.724402 | K95: =+hist_Forward5YearRealR_woFG!D42-hist_Forward5YearRNatR_woFG!D42 -> 0.089997341 | L95: =+hist_Forward5YearRNatR_wFG!D42 -> 1.8897571
A96: 25750 | B96: 1 | C96: 1 | D96: -1 | E96: 4.5 | F96: 8.3 | G96: =+'YC Chart - Policy rate'!D46*4 -> 7.88 | H96: =+hist_ExAnteRealRate_wFG!D43-hist_RealNaturalRate_wFG!D43 -> 1.0372343 | I96: =+hist_Forward5YearRealR_wFG!D43-hist_Forward5YearRNatR_wFG!D43 -> 0.1057637 | J96: =+hist_ExAnteRealRate_woFG!D43-hist_RealNaturalRate_woFG!D43 -> 1.0637645 | K96: =+hist_Forward5YearRealR_woFG!D43-hist_Forward5YearRNatR_woFG!D43 -> 0.11414982 | L96: =+hist_Forward5YearRNatR_wFG!D43 -> 1.9178022
A97: 25842 | B97: 1.3 | E97: 4.6 | F97: 8.4 | G97: =+'YC Chart - Policy rate'!D47*4 -> 6.71 | H97: =+hist_ExAnteRealRate_wFG!D44-hist_RealNaturalRate_wFG!D44 -> 1.4525303 | I97: =+hist_Forward5YearRealR_wFG!D44-hist_Forward5YearRNatR_wFG!D44 -> 0.065601787 | J97: =+hist_ExAnteRealRate_woFG!D44-hist_RealNaturalRate_woFG!D44 -> 1.4791516 | K97: =+hist_Forward5YearRealR_woFG!D44-hist_Forward5YearRNatR_woFG!D44 -> 0.074002536 | L97: =+hist_Forward5YearRNatR_wFG!D44 -> 1.5368141
A98: 25934 | B98: 0.9 | E98: 4.4 | F98: 9.3 | G98: =+'YC Chart - Policy rate'!D48*4 -> 5.57 | H98: =+hist_ExAnteRealRate_wFG!D45-hist_RealNaturalRate_wFG!D45 -> 1.9101381 | I98: =+hist_Forward5YearRealR_wFG!D45-hist_Forward5YearRNatR_wFG!D45 -> 0.096012508 | J98: =+hist_ExAnteRealRate_woFG!D45-hist_RealNaturalRate_woFG!D45 -> 1.9368419 | K98: =+hist_Forward5YearRealR_woFG!D45-hist_Forward5YearRNatR_woFG!D45 -> 0.10442725 | L98: =+hist_Forward5YearRNatR_wFG!D45 -> 1.3422137
A99: 26024 | B99: 1.1 | E99: 4.4 | F99: 8.4 | G99: =+'YC Chart - Policy rate'!D49*4 -> 3.86 | H99: =+hist_ExAnteRealRate_wFG!D46-hist_RealNaturalRate_wFG!D46 -> 4.1065232 | I99: =+hist_Forward5YearRealR_wFG!D46-hist_Forward5YearRNatR_wFG!D46 -> 0.033059257 | J99: =+hist_ExAnteRealRate_woFG!D46-hist_RealNaturalRate_woFG!D46 -> 4.1333001 | K99: =+hist_Forward5YearRealR_woFG!D46-hist_Forward5YearRNatR_woFG!D46 -> 0.041487429 | L99: =+hist_Forward5YearRNatR_wFG!D46 -> 1.4527322
A100: 26115 | B100: 1 | E100: 4.4 | F100: 9.5 | G100: =+'YC Chart - Policy rate'!D50*4 -> 4.57 | H100: =+hist_ExAnteRealRate_wFG!D47-hist_RealNaturalRate_wFG!D47 -> 2.4652834 | I100: =+hist_Forward5YearRealR_wFG!D47-hist_Forward5YearRNatR_wFG!D47 -> 0.01794157 | J100: =+hist_ExAnteRealRate_woFG!D47-hist_RealNaturalRate_woFG!D47 -> 2.4921227 | K100: =+hist_Forward5YearRealR_woFG!D47-hist_Forward5YearRNatR_woFG!D47 -> 0.026382681 | L100: =+hist_Forward5YearRNatR_wFG!D47 -> 1.3677747
A101: 26207 | B101: 0.6 | E101: 3.7 | F101: 9.6 | G101: =+'YC Chart - Policy rate'!D51*4 -> 5.48 | H101: =+hist_ExAnteRealRate_wFG!D48-hist_RealNaturalRate_wFG!D48 -> 1.4074273 | I101: =+hist_Forward5YearRealR_wFG!D48-hist_Forward5YearRNatR_wFG!D48 -> 0.055784154 | J101: =+hist_ExAnteRealRate_woFG!D48-hist_RealNaturalRate_woFG!D48 -> 1.4343153 | K101: =+hist_Forward5YearRealR_woFG!D48-hist_Forward5YearRNatR_woFG!D48 -> 0.064237839 | L101: =+hist_Forward5YearRNatR_wFG!D48 -> 1.3190477
A102: 26299 | B102: 1.1 | E102: 3.8 | F102: 11.6 | G102: =+'YC Chart - Policy rate'!D52*4 -> 4.75 | H102: =+hist_ExAnteRealRate_wFG!D49-hist_RealNaturalRate_wFG!D49 -> 0.091487229 | I102: =+hist_Forward5YearRealR_wFG!D49-hist_Forward5YearRNatR_wFG!D49 -> -0.023924673 | J102: =+hist_ExAnteRealRate_woFG!D49-hist_RealNaturalRate_woFG!D49 -> 0.11856188 | K102: =+hist_Forward5YearRealR_woFG!D49-hist_Forward5YearRNatR_woFG!D49 -> -0.01546171 | L102: =+hist_Forward5YearRNatR_wFG!D49 -> 1.3456769
A103: 26390 | B103: 0.6 | E103: 3.3 | F103: 11.9 | G103: =+'YC Chart - Policy rate'!D53*4 -> 3.55 | H103: =+hist_ExAnteRealRate_wFG!D50-hist_RealNaturalRate_wFG!D50 -> 0.43895532 | I103: =+hist_Forward5YearRealR_wFG!D50-hist_Forward5YearRNatR_wFG!D50 -> -0.067206181 | J103: =+hist_ExAnteRealRate_woFG!D50-hist_RealNaturalRate_woFG!D50 -> 0.46621015 | K103: =+hist_Forward5YearRealR_woFG!D50-hist_Forward5YearRNatR_woFG!D50 -> -0.058734659 | L103: =+hist_Forward5YearRNatR_wFG!D50 -> 1.5187459
A104: 26481 | B104: 0.9 | E104: 3.2 | F104: 11.6 | G104: =+'YC Chart - Policy rate'!D54*4 -> 4.3 | H104: =+hist_ExAnteRealRate_wFG!D51-hist_RealNaturalRate_wFG!D51 -> -0.21473409 | I104: =+hist_Forward5YearRealR_wFG!D51-hist_Forward5YearRNatR_wFG!D51 -> -0.050812244 | J104: =+hist_ExAnteRealRate_woFG!D51-hist_RealNaturalRate_woFG!D51 -> -0.18730194 | K104: =+hist_Forward5YearRealR_woFG!D51-hist_Forward5YearRNatR_woFG!D51 -> -0.042332805 | L104: =+hist_Forward5YearRNatR_wFG!D51 -> 1.6030396
A105: 26573 | B105: 0.8 | E105: 3.4 | F105: 11.1 | G105: =+'YC Chart - Policy rate'!D55*4 -> 4.74 | H105: =+hist_ExAnteRealRate_wFG!D52-hist_RealNaturalRate_wFG!D52 -> 1.2480661 | I105: =+hist_Forward5YearRealR_wFG!D52-hist_Forward5YearRNatR_wFG!D52 -> -0.043960713 | J105: =+hist_ExAnteRealRate_woFG!D52-hist_RealNaturalRate_woFG!D52 -> 1.2756756 | K105: =+hist_Forward5YearRealR_woFG!D52-hist_Forward5YearRNatR_woFG!D52 -> -0.035473982 | L105: =+hist_Forward5YearRNatR_wFG!D52 -> 1.5917993
A106: 26665 | B106: 1.2 | E106: 3.5 | F106: 11.1 | G106: =+'YC Chart - Policy rate'!D56*4 -> 5.15 | H106: =+hist_ExAnteRealRate_wFG!D53-hist_RealNaturalRate_wFG!D53 -> 1.224053 | I106: =+hist_Forward5YearRealR_wFG!D53-hist_Forward5YearRNatR_wFG!D53 -> -0.12395213 | J106: =+hist_ExAnteRealRate_woFG!D53-hist_RealNaturalRate_woFG!D53 -> 1.2518421 | K106: =+hist_Forward5YearRealR_woFG!D53-hist_Forward5YearRNatR_woFG!D53 -> -0.11545875 | L106: =+hist_Forward5YearRNatR_wFG!D53 -> 1.5531729
A107: 26755 | B107: 1.9 | E107: 4.9 | F107: 8.3 | G107: =+'YC Chart - Policy rate'!D57*4 -> 6.54 | H107: =+hist_ExAnteRealRate_wFG!D54-hist_RealNaturalRate_wFG!D54 -> 0.17938966 | I107: =+hist_Forward5YearRealR_wFG!D54-hist_Forward5YearRNatR_wFG!D54 -> -0.12386814 | J107: =+hist_ExAnteRealRate_woFG!D54-hist_RealNaturalRate_woFG!D54 -> 0.20736261 | K107: =+hist_Forward5YearRealR_woFG!D54-hist_Forward5YearRNatR_woFG!D54 -> -0.11536878 | L107: =+hist_Forward5YearRNatR_wFG!D54 -> 2.1203006
A108: 26846 | B108: 1.8 | E108: 5.9 | F108: 8.2 | G108: =+'YC Chart - Policy rate'!D58*4 -> 7.82 | H108: =+hist_ExAnteRealRate_wFG!D55-hist_RealNaturalRate_wFG!D55 -> -1.7279991 | I108: =+hist_Forward5YearRealR_wFG!D55-hist_Forward5YearRNatR_wFG!D55 -> -0.05667887 | J108: =+hist_ExAnteRealRate_woFG!D55-hist_RealNaturalRate_woFG!D55 -> -1.6998361 | K108: =+hist_Forward5YearRealR_woFG!D55-hist_Forward5YearRNatR_woFG!D55 -> -0.048174275 | L108: =+hist_Forward5YearRNatR_wFG!D55 -> 2.0331948
A109: 26938 | B109: 2 | C109: 1 | D109: -1 | E109: 7.2 | F109: 8.8 | G109: =+'YC Chart - Policy rate'!D59*4 -> 10.56 | H109: =+hist_ExAnteRealRate_wFG!D56-hist_RealNaturalRate_wFG!D56 -> -3.5849942 | I109: =+hist_Forward5YearRealR_wFG!D56-hist_Forward5YearRNatR_wFG!D56 -> 0.023106214 | J109: =+hist_ExAnteRealRate_woFG!D56-hist_RealNaturalRate_woFG!D56 -> -3.5566336 | K109: =+hist_Forward5YearRealR_woFG!D56-hist_Forward5YearRNatR_woFG!D56 -> 0.031615247 | L109: =+hist_Forward5YearRNatR_wFG!D56 -> 2.0008364
A110: 27030 | B110: 3 | C110: 1 | D110: -1 | E110: 9.1 | F110: 8.4 | G110: =+'YC Chart - Policy rate'!D60*4 -> 10 | H110: =+hist_ExAnteRealRate_wFG!D57-hist_RealNaturalRate_wFG!D57 -> -3.5749426 | I110: =+hist_Forward5YearRealR_wFG!D57-hist_Forward5YearRNatR_wFG!D57 -> 0.024017321 | J110: =+hist_ExAnteRealRate_woFG!D57-hist_RealNaturalRate_woFG!D57 -> -3.5463751 | K110: =+hist_Forward5YearRealR_woFG!D57-hist_Forward5YearRNatR_woFG!D57 -> 0.032529907 | L110: =+hist_Forward5YearRNatR_wFG!D57 -> 1.9057608
